Workbook

Sheet Assumptions
A1: Bitcoin Industry Production Cost Model — Assumptions
A3: Electricity price ($/kWh) | B3: 0.05 | C3: Industrial mining PPA benchmark; CBECI default. Efficient miners: $0.03-0.05; hosted: $0.07-0.08
A4: Electricity share of cash cost (%) | B4: 0.75 | C4: Electricity typically 60-80% of cash opex (labor, hosting, maintenance = rest). Default calibrated so cash cost ~ JPMorgan estimate (~$77k, Feb-26)
A5: Electricity share of all-in cost (%) | B5: 0.65 | C5: All-in adds D&A/hardware amortisation + SG&A. Default calibrated so all-in ~ Checkonchain difficulty-regression estimate (~$87k, Feb-26)
A8: Methodology
A9: 1. Network power draw (GW): Cambridge CBECI daily estimates (MIN / best-GUESS / MAX), which embed a profitability-weighted ASIC fleet efficiency model.
A10: 2. Electrical cost per BTC = power (GW) x 24h x 1e6 x electricity price ($/kWh) / BTC issued that day (from coinbase subsidy issuance).
A11: 3. Cash cost per BTC = electrical cost / electricity share of cash cost.
A12: 4. All-in cost per BTC = electrical cost / electricity share of all-in cost (captures D&A, SG&A).
A13: 5. Headline series = 7-day moving average of all-in cost (daily issuance is lumpy due to block-time variance).
A14: Sources: Cambridge CBECI (ccaf.io/cbnsi/cbeci) API pulled 02-Jul-2026; Blockchain.com charts API (hashrate, difficulty, issuance, price) pulled 02-Jul-2026.
A15: Cross-checks: Checkonchain industry avg ~$87k (Feb-26, per CoinDesk); JPMorgan ~$77k (Feb-26); Capriole "electrical cost" is energy-only and hence lower by design.

Sheet Daily Data
A1: Date | B1: Hashrate (EH/s) | C1: Difficulty (T) | D1: BTC Issued | E1: Network Power MIN (GW) | F1: Network Power GUESS (GW) | G1: Network Power MAX (GW) | H1: Implied Fleet Eff. (J/TH) | I1: BTC Price ($) | J1: Electrical Cost/BTC ($) | K1: Cash Cost/BTC ($) | L1: All-in Cost/BTC ($) | M1: All-in Cost LOW ($, MIN pwr) | N1: All-in Cost HIGH ($, MAX pwr) | O1: All-in Cost/BTC 7DMA ($) | P1: Price / All-in Cost (x)
A2: 45658 | B2: 764.02152 | C2: 109.78208 | D2: 437.5 | E2: 10.598727 | F2: 20.576088 | G2: 44.673605 | H2: =IF(B2="","",F2*1000/B2) -> 26.931294 | I2: 93406.74 | J2: =F2*24*1000000*Assumptions!$B$3/D2 -> 56437.271 | K2: =J2/Assumptions!$B$4 -> 75249.694 | L2: =J2/Assumptions!$B$5 -> 86826.57 | M2: =E2*24*1000000*Assumptions!$B$3/D2/Assumptions!$B$5 -> 44724.299 | N2: =G2*24*1000000*Assumptions!$B$3/D2/Assumptions!$B$5 -> 188512.79 | O2: =IF(ROW()<8,"",AVERAGE(L2:L2)) | P2: =IF(I2="","",I2/L2) -> 1.0757852
A3: 45659 | B3: 911.36853 | C3: 109.78208 | D3: 521.875 | E3: 10.798249 | F3: 21.205208 | G3: 45.767298 | H3: =IF(B3="","",F3*1000/B3) -> 23.267435 | I3: 94409.13 | J3: =F3*24*1000000*Assumptions!$B$3/D3 -> 48759.28 | K3: =J3/Assumptions!$B$4 -> 65012.373 | L3: =J3/Assumptions!$B$5 -> 75014.277 | M3: =E3*24*1000000*Assumptions!$B$3/D3/Assumptions!$B$5 -> 38199.241 | N3: =G3*24*1000000*Assumptions!$B$3/D3/Assumptions!$B$5 -> 161903.66 | O3: =IF(ROW()<8,"",AVERAGE(L2:L3)) | P3: =IF(I3="","",I3/L3) -> 1.2585488
A4: 45660 | B4: 774.93611 | C4: 109.78208 | D4: 443.75 | E4: 10.477441 | F4: 20.79127 | G4: 44.529295 | H4: =IF(B4="","",F4*1000/B4) -> 26.829657 | I4: 96853.63 | J4: =F4*24*1000000*Assumptions!$B$3/D4 -> 56224.279 | K4: =J4/Assumptions!$B$4 -> 74965.705 | L4: =J4/Assumptions!$B$5 -> 86498.891 | M4: =E4*24*1000000*Assumptions!$B$3/D4/Assumptions!$B$5 -> 43589.785 | N4: =G4*24*1000000*Assumptions!$B$3/D4/Assumptions!$B$5 -> 185257.31 | O4: =IF(ROW()<8,"",AVERAGE(L2:L4)) | P4: =IF(I4="","",I4/L4) -> 1.1197095
A5: 45661 | B5: 813.13719 | C5: 109.78208 | D5: 465.625 | E5: 10.380612 | F5: 20.852866 | G5: 44.858102 | H5: =IF(B5="","",F5*1000/B5) -> 25.644954 | I5: 98122.01 | J5: =F5*24*1000000*Assumptions!$B$3/D5 -> 53741.615 | K5: =J5/Assumptions!$B$4 -> 71655.487 | L5: =J5/Assumptions!$B$5 -> 82679.408 | M5: =E5*24*1000000*Assumptions!$B$3/D5/Assumptions!$B$5 -> 41158.028 | N5: =G5*24*1000000*Assumptions!$B$3/D5/Assumptions!$B$5 -> 177857.63 | O5: =IF(ROW()<8,"",AVERAGE(L2:L5)) | P5: =IF(I5="","",I5/L5) -> 1.1867769
A6: 45662 | B6: 851.33827 | C6: 109.78208 | D6: 487.5 | E6: 10.190134 | F6: 20.746874 | G6: 44.842137 | H6: =IF(B6="","",F6*1000/B6) -> 24.369719 | I6: 98242.07 | J6: =F6*24*1000000*Assumptions!$B$3/D6 -> 51069.228 | K6: =J6/Assumptions!$B$4 -> 68092.305 | L6: =J6/Assumptions!$B$5 -> 78568.044 | M6: =E6*24*1000000*Assumptions!$B$3/D6/Assumptions!$B$5 -> 38589.858 | N6: =G6*24*1000000*Assumptions!$B$3/D6/Assumptions!$B$5 -> 169816.38 | O6: =IF(ROW()<8,"",AVERAGE(L2:L6)) | P6: =IF(I6="","",I6/L6) -> 1.2504075
A7: 45663 | B7: 725.82044 | C7: 109.78208 | D7: 415.625 | E7: 9.7543466 | F7: 20.133403 | G7: 43.723235 | H7: =IF(B7="","",F7*1000/B7) -> 27.73882 | I7: 98319.2 | J7: =F7*24*1000000*Assumptions!$B$3/D7 -> 58129.523 | K7: =J7/Assumptions!$B$4 -> 77506.031 | L7: =J7/Assumptions!$B$5 -> 89430.036 | M7: =E7*24*1000000*Assumptions!$B$3/D7/Assumptions!$B$5 -> 43327.578 | N7: =G7*24*1000000*Assumptions!$B$3/D7/Assumptions!$B$5 -> 194213.1 | O7: =IF(ROW()<8,"",AVERAGE(L2:L7)) | P7: =IF(I7="","",I7/L7) -> 1.099398
A8: 45664 | B8: 731.27774 | C8: 109.78208 | D8: 418.75 | E8: 9.6473463 | F8: 20.150684 | G8: 43.938409 | H8: =IF(B8="","",F8*1000/B8) -> 27.555446 | I8: 102253.31 | J8: =F8*24*1000000*Assumptions!$B$3/D8 -> 57745.245 | K8: =J8/Assumptions!$B$4 -> 76993.66 | L8: =J8/Assumptions!$B$5 -> 88838.838 | M8: =E8*24*1000000*Assumptions!$B$3/D8/Assumptions!$B$5 -> 42532.503 | N8: =G8*24*1000000*Assumptions!$B$3/D8/Assumptions!$B$5 -> 193712.39 | O8: =IF(ROW()<8,"",AVERAGE(L2:L8)) -> 83979.438 | P8: =IF(I8="","",I8/L8) -> 1.1509978
A9: 45665 | B9: 682.16207 | C9: 109.78208 | D9: 390.625 | E9: 9.5056125 | F9: 19.854641 | G9: 43.292889 | H9: =IF(B9="","",F9*1000/B9) -> 29.10546 | I9: 96916.58 | J9: =F9*24*1000000*Assumptions!$B$3/D9 -> 60993.457 | K9: =J9/Assumptions!$B$4 -> 81324.61 | L9: =J9/Assumptions!$B$5 -> 93836.088 | M9: =E9*24*1000000*Assumptions!$B$3/D9/Assumptions!$B$5 -> 44924.987 | N9: =G9*24*1000000*Assumptions!$B$3/D9/Assumptions!$B$5 -> 204608.85 | O9: =IF(ROW()<8,"",AVERAGE(L3:L9)) -> 84980.797 | P9: =IF(I9="","",I9/L9) -> 1.0328284
A10: 45666 | B10: 829.50908 | C10: 109.78208 | D10: 475 | E10: 9.3638788 | F10: 19.558598 | G10: 42.647369 | H10: =IF(B10="","",F10*1000/B10) -> 23.578522 | I10: 95049.45 | J10: =F10*24*1000000*Assumptions!$B$3/D10 -> 49411.194 | K10: =J10/Assumptions!$B$4 -> 65881.592 | L10: =J10/Assumptions!$B$5 -> 76017.222 | M10: =E10*24*1000000*Assumptions!$B$3/D10/Assumptions!$B$5 -> 36394.023 | N10: =G10*24*1000000*Assumptions!$B$3/D10/Assumptions!$B$5 -> 165754.96 | O10: =IF(ROW()<8,"",AVERAGE(L4:L10)) -> 85124.075 | P10: =IF(I10="","",I10/L10) -> 1.2503673
A11: 45667 | B11: 774.93611 | C11: 109.78208 | D11: 443.75 | E11: 9.3638788 | F11: 19.558598 | G11: 42.647369 | H11: =IF(B11="","",F11*1000/B11) -> 25.238981 | I11: 92493.26 | J11: =F11*24*1000000*Assumptions!$B$3/D11 -> 52890.856 | K11: =J11/Assumptions!$B$4 -> 70521.141 | L11: =J11/Assumptions!$B$5 -> 81370.547 | M11: =E11*24*1000000*Assumptions!$B$3/D11/Assumptions!$B$5 -> 38956.982 | N11: =G11*24*1000000*Assumptions!$B$3/D11/Assumptions!$B$5 -> 177427.84 | O11: =IF(ROW()<8,"",AVERAGE(L5:L11)) -> 84391.455 | P11: =IF(I11="","",I11/L11) -> 1.1366921
A12: 45668 | B12: 753.10693 | C12: 109.78208 | D12: 431.25 | E12: 9.2599407 | F12: 19.341499 | G12: 42.173987 | H12: =IF(B12="","",F12*1000/B12) -> 25.682275 | I12: 94702.66 | J12: =F12*24*1000000*Assumptions!$B$3/D12 -> 53819.824 | K12: =J12/Assumptions!$B$4 -> 71759.765 | L12: =J12/Assumptions!$B$5 -> 82799.729 | M12: =E12*24*1000000*Assumptions!$B$3/D12/Assumptions!$B$5 -> 39641.218 | N12: =G12*24*1000000*Assumptions!$B$3/D12/Assumptions!$B$5 -> 180544.16 | O12: =IF(ROW()<8,"",AVERAGE(L6:L12)) -> 84408.644 | P12: =IF(I12="","",I12/L12) -> 1.1437557
A13: 45669 | B13: 939.75383 | C13: 109.91059 | D13: 537.5 | E13: 9.4133142 | F13: 19.661855 | G13: 42.87252 | H13: =IF(B13="","",F13*1000/B13) -> 20.922346 | I13: 94569.61 | J13: =F13*24*1000000*Assumptions!$B$3/D13 -> 43896.234 | K13: =J13/Assumptions!$B$4 -> 58528.312 | L13: =J13/Assumptions!$B$5 -> 67532.668 | M13: =E13*24*1000000*Assumptions!$B$3/D13/Assumptions!$B$5 -> 32331.956 | N13: =G13*24*1000000*Assumptions!$B$3/D13/Assumptions!$B$5 -> 147254.45 | O13: =IF(ROW()<8,"",AVERAGE(L7:L13)) -> 82832.161 | P13: =IF(I13="","",I13/L13) -> 1.4003535
A14: 45670 | B14: 702.79604 | C14: 110.45191 | D14: 400 | E14: 9.3734491 | F14: 19.578588 | G14: 42.690956 | H14: =IF(B14="","",F14*1000/B14) -> 27.858136 | I14: 94478.37 | J14: =F14*24*1000000*Assumptions!$B$3/D14 -> 58735.763 | K14: =J14/Assumptions!$B$4 -> 78314.35 | L14: =J14/Assumptions!$B$5 -> 90362.712 | M14: =E14*24*1000000*Assumptions!$B$3/D14/Assumptions!$B$5 -> 43262.073 | N14: =G14*24*1000000*Assumptions!$B$3/D14/Assumptions!$B$5 -> 197035.18 | O14: =IF(ROW()<8,"",AVERAGE(L8:L14)) -> 82965.401 | P14: =IF(I14="","",I14/L14) -> 1.045546
A15: 45671 | B15: 845.55149 | C15: 110.45191 | D15: 481.25 | E15: 9.5713059 | F15: 19.991857 | G15: 43.592086 | H15: =IF(B15="","",F15*1000/B15) -> 23.643571 | I15: 94497.68 | J15: =F15*24*1000000*Assumptions!$B$3/D15 -> 49849.825 | K15: =J15/Assumptions!$B$4 -> 66466.433 | L15: =J15/Assumptions!$B$5 -> 76692.038 | M15: =E15*24*1000000*Assumptions!$B$3/D15/Assumptions!$B$5 -> 36717.098 | N15: =G15*24*1000000*Assumptions!$B$3/D15/Assumptions!$B$5 -> 167226.39 | O15: =IF(ROW()<8,"",AVERAGE(L9:L15)) -> 81230.144 | P15: =IF(I15="","",I15/L15) -> 1.2321707
A16: 45672 | B16: 763.19258 | C16: 110.45191 | D16: 434.375 | E16: 9.7116046 | F16: 20.284902 | G16: 44.23107 | H16: =IF(B16="","",F16*1000/B16) -> 26.579009 | I16: 96527.14 | J16: =F16*24*1000000*Assumptions!$B$3/D16 -> 56038.867 | K16: =J16/Assumptions!$B$4 -> 74718.489 | L16: =J16/Assumptions!$B$5 -> 86213.642 | M16: =E16*24*1000000*Assumptions!$B$3/D16/Assumptions!$B$5 -> 41275.663 | N16: =G16*24*1000000*Assumptions!$B$3/D16/Assumptions!$B$5 -> 187988.17 | O16: =IF(ROW()<8,"",AVERAGE(L10:L16)) -> 80141.223 | P16: =IF(I16="","",I16/L16) -> 1.1196272
A17: 45673 | B17: 702.79604 | C17: 110.45191 | D17: 400 | E17: 9.49221 | F17: 19.826647 | G17: 43.231847 | H17: =IF(B17="","",F17*1000/B17) -> 28.211096 | I17: 100511.85 | J17: =F17*24*1000000*Assumptions!$B$3/D17 -> 59479.94 | K17: =J17/Assumptions!$B$4 -> 79306.587 | L17: =J17/Assumptions!$B$5 -> 91507.6 | M17: =E17*24*1000000*Assumptions!$B$3/D17/Assumptions!$B$5 -> 43810.2 | N17: =G17*24*1000000*Assumptions!$B$3/D17/Assumptions!$B$5 -> 199531.6 | O17: =IF(ROW()<8,"",AVERAGE(L11:L17)) -> 82354.134 | P17: =IF(I17="","",I17/L17) -> 1.0983989
A18: 45674 | B18: 823.58911 | C18: 110.45191 | D18: 468.75 | E18: 9.5764492 | F18: 20.0026 | G18: 43.615511 | H18: =IF(B18="","",F18*1000/B18) -> 24.28711 | I18: 99976.92 | J18: =F18*24*1000000*Assumptions!$B$3/D18 -> 51206.655 | K18: =J18/Assumptions!$B$4 -> 68275.54 | L18: =J18/Assumptions!$B$5 -> 78779.469 | M18: =E18*24*1000000*Assumptions!$B$3/D18/Assumptions!$B$5 -> 37716.477 | N18: =G18*24*1000000*Assumptions!$B$3/D18/Assumptions!$B$5 -> 171778.01 | O18: =IF(ROW()<8,"",AVERAGE(L12:L18)) -> 81983.98 | P18: =IF(I18="","",I18/L18) -> 1.2690733
A19: 45675 | B19: 713.77723 | C19: 110.45191 | D19: 406.25 | E19: 9.5083526 | F19: 19.860364 | G19: 43.305368 | H19: =IF(B19="","",F19*1000/B19) -> 27.824317 | I19: 104103.44 | J19: =F19*24*1000000*Assumptions!$B$3/D19 -> 58664.46 | K19: =J19/Assumptions!$B$4 -> 78219.28 | L19: =J19/Assumptions!$B$5 -> 90253.016 | M19: =E19*24*1000000*Assumptions!$B$3/D19/Assumptions!$B$5 -> 43209.555 | N19: =G19*24*1000000*Assumptions!$B$3/D19/Assumptions!$B$5 -> 196795.99 | O19: =IF(ROW()<8,"",AVERAGE(L13:L19)) -> 83048.735 | P19: =IF(I19="","",I19/L19) -> 1.1534622
... A319: 45975 | B319: 1086.6138 | C319: 155.02794 | D319: 450 | E319: 12.07265 | F319: 23.898474 | G319: 46.225476 | H319: =IF(B319="","",F319*1000/B319) -> 21.993531 | I319: 99675.15 | J319: =F319*24*1000000*Assumptions!$B$3/D319 -> 63729.263 | K319: =J319/Assumptions!$B$4 -> 84972.351 | L319: =J319/Assumptions!$B$5 -> 98045.02 | M319: =E319*24*1000000*Assumptions!$B$3/D319/Assumptions!$B$5 -> 49528.821 | N319: =G319*24*1000000*Assumptions!$B$3/D319/Assumptions!$B$5 -> 189642.98 | O319: =IF(ROW()<8,"",AVERAGE(L313:L319)) -> 100022.32 | P319: =IF(I319="","",I319/L319) -> 1.0166263
A320: 45976 | D320: 446.875 | E320: 12.313922 | F320: 24.363425 | G320: 46.962124 | H320: =IF(B320="","",F320*1000/B320) | I320: 94399.23 | J320: =F320*24*1000000*Assumptions!$B$3/D320 -> 65423.464 | K320: =J320/Assumptions!$B$4 -> 87231.285 | L320: =J320/Assumptions!$B$5 -> 100651.48 | M320: =E320*24*1000000*Assumptions!$B$3/D320/Assumptions!$B$5 -> 50871.931 | N320: =G320*24*1000000*Assumptions!$B$3/D320/Assumptions!$B$5 -> 194012.43 | O320: =IF(ROW()<8,"",AVERAGE(L314:L320)) -> 97535.31 | P320: =IF(I320="","",I320/L320) -> 0.93788216
A321: 45977 | B321: 1203.543 | C321: 152.27141 | D321: 496.875 | E321: 12.488991 | F321: 24.695468 | G321: 47.4178 | H321: =IF(B321="","",F321*1000/B321) -> 20.518975 | I321: 95534.16 | J321: =F321*24*1000000*Assumptions!$B$3/D321 -> 59641.884 | K321: =J321/Assumptions!$B$4 -> 79522.512 | L321: =J321/Assumptions!$B$5 -> 91756.744 | M321: =E321*24*1000000*Assumptions!$B$3/D321/Assumptions!$B$5 -> 46403.219 | N321: =G321*24*1000000*Assumptions!$B$3/D321/Assumptions!$B$5 -> 176182.25 | O321: =IF(ROW()<8,"",AVERAGE(L315:L321)) -> 96543.245 | P321: =IF(I321="","",I321/L321) -> 1.0411677
A322: 45978 | B322: 938.61213 | C322: 152.27141 | D322: 387.5 | E322: 12.255884 | F322: 24.198305 | G322: 46.238183 | H322: =IF(B322="","",F322*1000/B322) -> 25.780942 | I322: 94187.75 | J322: =F322*24*1000000*Assumptions!$B$3/D322 -> 74936.685 | K322: =J322/Assumptions!$B$4 -> 99915.58 | L322: =J322/Assumptions!$B$5 -> 115287.21 | M322: =E322*24*1000000*Assumptions!$B$3/D322/Assumptions!$B$5 -> 58390.316 | N322: =G322*24*1000000*Assumptions!$B$3/D322/Assumptions!$B$5 -> 220291.1 | O322: =IF(ROW()<8,"",AVERAGE(L316:L322)) -> 98886.682 | P322: =IF(I322="","",I322/L322) -> 0.81698353
A323: 45979 | B323: 1006.7372 | C323: 152.27141 | D323: 403.125 | E323: 11.970925 | F323: 23.610869 | G323: 45.060437 | H323: =IF(B323="","",F323*1000/B323) -> 23.452863 | I323: 92093.24 | J323: =F323*24*1000000*Assumptions!$B$3/D323 -> 70283.517 | K323: =J323/Assumptions!$B$4 -> 93711.356 | L323: =J323/Assumptions!$B$5 -> 108128.49 | M323: =E323*24*1000000*Assumptions!$B$3/D323/Assumptions!$B$5 -> 54822.123 | N323: =G323*24*1000000*Assumptions!$B$3/D323/Assumptions!$B$5 -> 206359.07 | O323: =IF(ROW()<8,"",AVERAGE(L317:L323)) -> 101157.95 | P323: =IF(I323="","",I323/L323) -> 0.85170191
A324: 45980 | B324: 1037.015 | C324: 152.27141 | D324: 440.625 | E324: 11.893665 | F324: 23.396164 | G324: 43.968382 | H324: =IF(B324="","",F324*1000/B324) -> 22.561066 | I324: 92979.11 | J324: =F324*24*1000000*Assumptions!$B$3/D324 -> 63717.212 | K324: =J324/Assumptions!$B$4 -> 84956.282 | L324: =J324/Assumptions!$B$5 -> 98026.48 | M324: =E324*24*1000000*Assumptions!$B$3/D324/Assumptions!$B$5 -> 49832.703 | N324: =G324*24*1000000*Assumptions!$B$3/D324/Assumptions!$B$5 -> 184221.04 | O324: =IF(ROW()<8,"",AVERAGE(L318:L324)) -> 100887.1 | P324: =IF(I324="","",I324/L324) -> 0.94851014
A325: 45981 | B325: 991.59829 | C325: 152.27141 | D325: 409.375 | E325: 11.665402 | F325: 22.885753 | G325: 42.340517 | H325: =IF(B325="","",F325*1000/B325) -> 23.079662 | I325: 91453.07 | J325: =F325*24*1000000*Assumptions!$B$3/D325 -> 67084.956 | K325: =J325/Assumptions!$B$4 -> 89446.608 | L325: =J325/Assumptions!$B$5 -> 103207.62 | M325: =E325*24*1000000*Assumptions!$B$3/D325/Assumptions!$B$5 -> 52607.334 | N325: =G325*24*1000000*Assumptions!$B$3/D325/Assumptions!$B$5 -> 190942.56 | O325: =IF(ROW()<8,"",AVERAGE(L319:L325)) -> 102157.58 | P325: =IF(I325="","",I325/L325) -> 0.88610769
A326: 45982 | B326: 1142.9873 | C326: 152.27141 | D326: 471.875 | E326: 11.749499 | F326: 22.983594 | G326: 41.776701 | H326: =IF(B326="","",F326*1000/B326) -> 20.108354 | I326: 86467.17 | J326: =F326*24*1000000*Assumptions!$B$3/D326 -> 58448.346 | K326: =J326/Assumptions!$B$4 -> 77931.128 | L326: =J326/Assumptions!$B$5 -> 89920.533 | M326: =E326*24*1000000*Assumptions!$B$3/D326/Assumptions!$B$5 -> 45968.493 | N326: =G326*24*1000000*Assumptions!$B$3/D326/Assumptions!$B$5 -> 163446.29 | O326: =IF(ROW()<8,"",AVERAGE(L320:L326)) -> 100996.94 | P326: =IF(I326="","",I326/L326) -> 0.96159539
A327: 45983 | B327: 1082.4317 | C327: 152.27141 | D327: 446.875 | E327: 11.749499 | F327: 22.91886 | G327: 40.941683 | H327: =IF(B327="","",F327*1000/B327) -> 21.173492 | I327: 85096.82 | J327: =F327*24*1000000*Assumptions!$B$3/D327 -> 61544.35 | K327: =J327/Assumptions!$B$4 -> 82059.134 | L327: =J327/Assumptions!$B$5 -> 94683.616 | M327: =E327*24*1000000*Assumptions!$B$3/D327/Assumptions!$B$5 -> 48540.157 | N327: =G327*24*1000000*Assumptions!$B$3/D327/Assumptions!$B$5 -> 169140.46 | O327: =IF(ROW()<8,"",AVERAGE(L321:L327)) -> 100144.38 | P327: =IF(I327="","",I327/L327) -> 0.89874916
A328: 45984 | B328: 1074.8623 | C328: 152.27141 | D328: 443.75 | E328: 11.545264 | F328: 22.450954 | G328: 39.340419 | H328: =IF(B328="","",F328*1000/B328) -> 20.887285 | I328: 84677.63 | J328: =F328*24*1000000*Assumptions!$B$3/D328 -> 60712.44 | K328: =J328/Assumptions!$B$4 -> 80949.92 | L328: =J328/Assumptions!$B$5 -> 93403.754 | M328: =E328*24*1000000*Assumptions!$B$3/D328/Assumptions!$B$5 -> 48032.302 | N328: =G328*24*1000000*Assumptions!$B$3/D328/Assumptions!$B$5 -> 163669.78 | O328: =IF(ROW()<8,"",AVERAGE(L322:L328)) -> 100379.67 | P328: =IF(I328="","",I328/L328) -> 0.9065763
A329: 45985 | B329: 1082.4317 | C329: 152.27141 | D329: 446.875 | E329: 11.773527 | F329: 22.859963 | G329: 39.462009 | H329: =IF(B329="","",F329*1000/B329) -> 21.119081 | I329: 86786.92 | J329: =F329*24*1000000*Assumptions!$B$3/D329 -> 61386.195 | K329: =J329/Assumptions!$B$4 -> 81848.26 | L329: =J329/Assumptions!$B$5 -> 94440.3 | M329: =E329*24*1000000*Assumptions!$B$3/D329/Assumptions!$B$5 -> 48639.421 | N329: =G329*24*1000000*Assumptions!$B$3/D329/Assumptions!$B$5 -> 163027.56 | O329: =IF(ROW()<8,"",AVERAGE(L323:L329)) -> 97401.542 | P329: =IF(I329="","",I329/L329) -> 0.91896066
A330: 45986 | B330: 870.48705 | C330: 152.27141 | D330: 359.375 | E330: 11.557278 | F330: 22.404817 | G330: 38.073481 | H330: =IF(B330="","",F330*1000/B330) -> 25.738254 | I330: 88276.26 | J330: =F330*24*1000000*Assumptions!$B$3/D330 -> 74812.605 | K330: =J330/Assumptions!$B$4 -> 99750.14 | L330: =J330/Assumptions!$B$5 -> 115096.32 | M330: =E330*24*1000000*Assumptions!$B$3/D330/Assumptions!$B$5 -> 59371.168 | N330: =G330*24*1000000*Assumptions!$B$3/D330/Assumptions!$B$5 -> 195588.19 | O330: =IF(ROW()<8,"",AVERAGE(L324:L330)) -> 98396.946 | P330: =IF(I330="","",I330/L330) -> 0.76697729
A331: 45987 | B331: 1241.3902 | C331: 152.27141 | D331: 512.5 | E331: 11.880713 | F331: 23.031825 | G331: 39.138984 | H331: =IF(B331="","",F331*1000/B331) -> 18.553251 | I331: 87330.85 | J331: =F331*24*1000000*Assumptions!$B$3/D331 -> 53928.175 | K331: =J331/Assumptions!$B$4 -> 71904.233 | L331: =J331/Assumptions!$B$5 -> 82966.423 | M331: =E331*24*1000000*Assumptions!$B$3/D331/Assumptions!$B$5 -> 42797.316 | N331: =G331*24*1000000*Assumptions!$B$3/D331/Assumptions!$B$5 -> 140988.46 | O331: =IF(ROW()<8,"",AVERAGE(L325:L331)) -> 96245.509 | P331: =IF(I331="","",I331/L331) -> 1.0526047
A332: 45988 | B332: 1061.4655 | C332: 149.32198 | D332: 434.375 | E332: 11.991368 | F332: 23.246339 | G332: 39.503517 | H332: =IF(B332="","",F332*1000/B332) -> 21.900231 | I332: 90517.55 | J332: =F332*24*1000000*Assumptions!$B$3/D332 -> 64220.103 | K332: =J332/Assumptions!$B$4 -> 85626.804 | L332: =J332/Assumptions!$B$5 -> 98800.158 | M332: =E332*24*1000000*Assumptions!$B$3/D332/Assumptions!$B$5 -> 50964.974 | N332: =G332*24*1000000*Assumptions!$B$3/D332/Assumptions!$B$5 -> 167895.41 | O332: =IF(ROW()<8,"",AVERAGE(L326:L332)) -> 95615.871 | P332: =IF(I332="","",I332/L332) -> 0.91616807
... A549: 46205 | B549: 951.62303 | C549: 133.86985 | D549: 425 | E549: 9.2740572 | F549: 17.50189 | G549: 28.197628 | H549: =IF(B549="","",F549*1000/B549) -> 18.391621 | I549: 59963.86 | J549: =F549*24*1000000*Assumptions!$B$3/D549 -> 49417.102 | K549: =J549/Assumptions!$B$4 -> 65889.469 | L549: =J549/Assumptions!$B$5 -> 76026.31 | M549: =E549*24*1000000*Assumptions!$B$3/D549/Assumptions!$B$5 -> 40285.497 | N549: =G549*24*1000000*Assumptions!$B$3/D549/Assumptions!$B$5 -> 122487.43 | O549: =IF(ROW()<8,"",AVERAGE(L543:L549)) -> 74509.491 | P549: =IF(I549="","",I549/L549) -> 0.78872511

Sheet Chart
