Workbook

Sheet Assumptions
A1: Hyperliquid Master Model — Assumptions
A2: Edit yellow cells to flex the model. All Daily Master formulas reference these names.
A3: Parameter | B3: Value | C3: Format | D3: Source / Note | E3: Defined Name
A4: FEE STRUCTURE
A5: Base perp taker rate (tier 0) | B5: 0.00045 | C5: 0.0000% | D5: Source: Hyperliquid docs — tier 0 taker = 0.045% | E5: BaseTakerRate
A6: Base perp maker rate (tier 0) | B6: 0.00015 | C6: 0.0000% | D6: Source: Hyperliquid docs — tier 0 maker = 0.015% | E6: BaseMakerRate
A7: Empirical core perp blended bps (pre-HIP-3, vol-weighted) | B7: 2.897 | C7: 0.000 | D7: Derived from Dec 23 2024 - Oct 12 2025: total_perp_fees / core_volume × 10000 | E7: CoreBpsBlended
A8: Growth mode discount factor | B8: 0.1 | C8: 0.00% | D8: Source: Hyperliquid HIP-3 Growth Mode (Nov 19 2025): 90% reduction | E8: GrowthModeFactor
A10: HIP-3 DEPLOYER FEE SCALES (from Hyperliquid info API perpDexs)
A11: HIP-3 trader scale (deployerFeeScale=1, most dexes) | B11: 2 | C11: 0.0000 | D11: scaleIfHip3 = deployerFeeScale × 2 when ≥ 1 → trader pays 2x base | E11: HIP3TraderScale_Std
A12: Hyperliquid retained share on 50/50 dexes | B12: 0.5 | C12: 0.00% | D12: When deployerFeeScale ≥ 1, HL keeps 50%, deployer keeps 50% (= 1x base each) | E12: HL_Retained_50
A13: HyENA trader scale (deployerFeeScale=0.1111) | B13: 1.1111 | C13: 0.0000 | D13: HyENA-specific: 1 + 0.1111 — trader pays 1.111x base | E13: HIP3TraderScale_Hyna
A14: Hyperliquid retained share on HyENA | B14: 0.9 | C14: 0.0% | D14: On HyENA, HL gets 90%, deployer 10% | E14: HL_Retained_Hyna
A16: HLP REVENUE SHARE — pre Aug 31 2025 | B16: 0.03 | C16: 0.00% | D16: HLP gets 3% of perp+spot revenue. Source: DefiLlama adapter + empirical 3.0928% = 3/97 ratio | E16: HlpSharePre
A17: HLP REVENUE SHARE — post Aug 31 2025 | B17: 0.01 | C17: 0.00% | D17: HLP gets 1% of perp+spot revenue. Empirical 1.0101% = 1/99 ratio confirmed | E17: HlpSharePost
A18: HLP share change date | B18: 45900 | C18: yyyy-mm-dd | D18: Empirically determined transition date from DefiLlama data | E18: HlpChangeDate
A20: AF revenue share (post HLP cut) | B20: 0.99 | C20: 0.00% | D20: Source: Hyperliquid docs: 99% of (fees-builders) flows to AF | E20: AfShare
A22: KEY DATES
A23: HIP-3 LAUNCH | B23: 45943 | C23: yyyy-mm-dd | D23: HIP-3 mainnet launch | E23: Hip3LaunchDate
A24: HIP-3 Growth Mode launch | B24: 45980 | C24: yyyy-mm-dd | D24: Growth Mode feature available; per-asset opt-in over time | E24: GrowthModeDate
A25: HIP-4 LAUNCH | B25: 46144 | C25: yyyy-mm-dd | D25: HIP-4 outcome markets mainnet launch — zero fees initially | E25: Hip4LaunchDate
A26: HIP-4 fee rate (zero in testing) | B26: 0 | C26: 0.0000% | D26: Source: Hyperliquid HIP-4 docs: "Fees are currently zero for outcome markets for initial testing" | E26: Hip4Rate
A28: STAKING
A29: Staking APR formula coefficient | B29: 474 | C29: 0 | D29: Source: Hyperliquid docs. At 400M staked, APR ≈ 2.37%. Formula: APR(S) = AprCoef/sqrt(S) | E29: AprCoef

Sheet Daily Master
A1: Daily Master — formulas reference Assumptions sheet
A2: YELLOW cells = raw API data. BLUE text = formula. Every derived value is auditable.
A3: Yellow = raw DL/HP API data; Blue text = Excel formula. Builder codes = supplyside_perps − (perp_rev × hlp_pct/(1−hlp_pct)).
A4: Date | B4: Core perp volume ($) | C4: HIP-3 perp volume ($) | D4: Spot volume ($) | E4: Total perp volume ($) | F4: Total volume incl spot ($) | G4: HIP-3 vol share % | H4: DL Perps fees ($) [raw] | I4: DL Spot fees ($) [raw] | J4: DL HLP entity fees [DOUBLECOUNT - DO NOT ADD] | K4: Total fees [= H+I, do NOT add J] | L4: Modeled HL's slice from HIP-3 ($) | M4: Implied core fees [= H - L] ($) | N4: Implied core bps | O4: DL Perps revenue ($) [raw] | P4: DL Spot revenue ($) [raw] | Q4: Total revenue to AF ($) | R4: Effective HLP share % | S4: Formula HLP slice [= Q*R/(1-R)] ($) | T4: DL HLP slice (=fees_hlp) ($) | U4: HLP diff (formula − DL) ($) | V4: Builder codes (perp) [= Y - O*R/(1-R)] ($) | W4: Unit revenue (spot) [= Z - P*R/(1-R)] ($) | X4: Supplyside check [= S + V + W] ($) | Y4: DL supplyside_perps (raw) ($) | Z4: DL supplyside_spot (raw) ($) | AA4: DL Holders rev = AF buyback ($) | AB4: HYPE close ($) | AC4: HYPE VWAP proxy ($) | AD4: HYPE bought daily (#) | AE4: CHECK: K - Q - X (should=0) | AF4: CHECK: Q - AA (should=0) | AG4: HP daily total fees ($) | AH4: HP/DL revenue ratio | AI4: Total staked HYPE (#) | AJ4: Staking APR [= AprCoef/SQRT(AI)] | AK4: Daily HYPE issuance (#) [= AI*AJ/365] | AL4: Daily HYPE burned (#) [= AD] | AM4: Net daily HYPE chg (#) [= AK-AL] | AN4: HIP-3 live? | AO4: HIP-4 status | AP4: # HIP-3 assets active | AQ4: # w/ growth mode | AR4: Modeled HIP-3 deployer slice [INFO] ($)
A5: 45066 | B5: 1.4896434e+08 | C5: 0 | E5: =B5+C5 -> 1.4896434e+08 | F5: =E5+D5 -> 1.4896434e+08 | G5: =IFERROR(C5/E5,0) -> 0 | K5: =H5+I5 -> 0 | M5: =H5-L5 -> 0 | N5: =IFERROR(M5/B5*10000,0) -> 0 | Q5: =O5+P5 -> 0 | R5: =IF(A5<HlpChangeDate,HlpSharePre,HlpSharePost) -> 0.03 | S5: =Q5*R5/(1-R5) -> 0 | U5: =S5-T5 -> 0 | V5: =Y5-O5*R5/(1-R5) -> 0 | W5: =Z5-P5*R5/(1-R5) -> 0 | X5: =S5+V5+W5 -> 0 | AA5: 0 | AD5: =IFERROR(AA5/AC5,0) -> 0 | AE5: =K5-Q5-X5 -> 0 | AF5: =Q5-AA5 -> 0 | AH5: =IFERROR(AG5/Q5,0) -> 0 | AI5: 0 | AJ5: =IF(AI5>0,AprCoef/SQRT(AI5),0) -> 0 | AK5: =AI5*AJ5/365 -> 0 | AL5: =AD5 -> 0 | AM5: =AK5-AL5 -> 0 | AN5: =IF(A5>=Hip3LaunchDate,"YES","") | AO5: =IF(A5<Hip4LaunchDate,"pre-launch","live (zero-fee)") -> pre-launch
A6: 45067 | B6: 1.7817381e+08 | C6: 0 | E6: =B6+C6 -> 1.7817381e+08 | F6: =E6+D6 -> 1.7817381e+08 | G6: =IFERROR(C6/E6,0) -> 0 | K6: =H6+I6 -> 0 | M6: =H6-L6 -> 0 | N6: =IFERROR(M6/B6*10000,0) -> 0 | Q6: =O6+P6 -> 0 | R6: =IF(A6<HlpChangeDate,HlpSharePre,HlpSharePost) -> 0.03 | S6: =Q6*R6/(1-R6) -> 0 | U6: =S6-T6 -> 0 | V6: =Y6-O6*R6/(1-R6) -> 0 | W6: =Z6-P6*R6/(1-R6) -> 0 | X6: =S6+V6+W6 -> 0 | AA6: 0 | AD6: =IFERROR(AA6/AC6,0) -> 0 | AE6: =K6-Q6-X6 -> 0 | AF6: =Q6-AA6 -> 0 | AH6: =IFERROR(AG6/Q6,0) -> 0 | AI6: 0 | AJ6: =IF(AI6>0,AprCoef/SQRT(AI6),0) -> 0 | AK6: =AI6*AJ6/365 -> 0 | AL6: =AD6 -> 0 | AM6: =AK6-AL6 -> 0 | AN6: =IF(A6>=Hip3LaunchDate,"YES","") | AO6: =IF(A6<Hip4LaunchDate,"pre-launch","live (zero-fee)") -> pre-launch
A7: 45068 | B7: 2.0381289e+08 | C7: 0 | E7: =B7+C7 -> 2.0381289e+08 | F7: =E7+D7 -> 2.0381289e+08 | G7: =IFERROR(C7/E7,0) -> 0 | K7: =H7+I7 -> 0 | M7: =H7-L7 -> 0 | N7: =IFERROR(M7/B7*10000,0) -> 0 | Q7: =O7+P7 -> 0 | R7: =IF(A7<HlpChangeDate,HlpSharePre,HlpSharePost) -> 0.03 | S7: =Q7*R7/(1-R7) -> 0 | U7: =S7-T7 -> 0 | V7: =Y7-O7*R7/(1-R7) -> 0 | W7: =Z7-P7*R7/(1-R7) -> 0 | X7: =S7+V7+W7 -> 0 | AA7: 0 | AD7: =IFERROR(AA7/AC7,0) -> 0 | AE7: =K7-Q7-X7 -> 0 | AF7: =Q7-AA7 -> 0 | AH7: =IFERROR(AG7/Q7,0) -> 0 | AI7: 0 | AJ7: =IF(AI7>0,AprCoef/SQRT(AI7),0) -> 0 | AK7: =AI7*AJ7/365 -> 0 | AL7: =AD7 -> 0 | AM7: =AK7-AL7 -> 0 | AN7: =IF(A7>=Hip3LaunchDate,"YES","") | AO7: =IF(A7<Hip4LaunchDate,"pre-launch","live (zero-fee)") -> pre-launch
A8: 45069 | B8: 2.3846318e+08 | C8: 0 | E8: =B8+C8 -> 2.3846318e+08 | F8: =E8+D8 -> 2.3846318e+08 | G8: =IFERROR(C8/E8,0) -> 0 | K8: =H8+I8 -> 0 | M8: =H8-L8 -> 0 | N8: =IFERROR(M8/B8*10000,0) -> 0 | Q8: =O8+P8 -> 0 | R8: =IF(A8<HlpChangeDate,HlpSharePre,HlpSharePost) -> 0.03 | S8: =Q8*R8/(1-R8) -> 0 | U8: =S8-T8 -> 0 | V8: =Y8-O8*R8/(1-R8) -> 0 | W8: =Z8-P8*R8/(1-R8) -> 0 | X8: =S8+V8+W8 -> 0 | AA8: 0 | AD8: =IFERROR(AA8/AC8,0) -> 0 | AE8: =K8-Q8-X8 -> 0 | AF8: =Q8-AA8 -> 0 | AH8: =IFERROR(AG8/Q8,0) -> 0 | AI8: 0 | AJ8: =IF(AI8>0,AprCoef/SQRT(AI8),0) -> 0 | AK8: =AI8*AJ8/365 -> 0 | AL8: =AD8 -> 0 | AM8: =AK8-AL8 -> 0 | AN8: =IF(A8>=Hip3LaunchDate,"YES","") | AO8: =IF(A8<Hip4LaunchDate,"pre-launch","live (zero-fee)") -> pre-launch
A9: 45070 | B9: 4.6949197e+08 | C9: 0 | E9: =B9+C9 -> 4.6949197e+08 | F9: =E9+D9 -> 4.6949197e+08 | G9: =IFERROR(C9/E9,0) -> 0 | K9: =H9+I9 -> 0 | M9: =H9-L9 -> 0 | N9: =IFERROR(M9/B9*10000,0) -> 0 | Q9: =O9+P9 -> 0 | R9: =IF(A9<HlpChangeDate,HlpSharePre,HlpSharePost) -> 0.03 | S9: =Q9*R9/(1-R9) -> 0 | U9: =S9-T9 -> 0 | V9: =Y9-O9*R9/(1-R9) -> 0 | W9: =Z9-P9*R9/(1-R9) -> 0 | X9: =S9+V9+W9 -> 0 | AA9: 0 | AD9: =IFERROR(AA9/AC9,0) -> 0 | AE9: =K9-Q9-X9 -> 0 | AF9: =Q9-AA9 -> 0 | AH9: =IFERROR(AG9/Q9,0) -> 0 | AI9: 0 | AJ9: =IF(AI9>0,AprCoef/SQRT(AI9),0) -> 0 | AK9: =AI9*AJ9/365 -> 0 | AL9: =AD9 -> 0 | AM9: =AK9-AL9 -> 0 | AN9: =IF(A9>=Hip3LaunchDate,"YES","") | AO9: =IF(A9<Hip4LaunchDate,"pre-launch","live (zero-fee)") -> pre-launch
A10: 45071 | B10: 6.5181124e+08 | C10: 0 | E10: =B10+C10 -> 6.5181124e+08 | F10: =E10+D10 -> 6.5181124e+08 | G10: =IFERROR(C10/E10,0) -> 0 | K10: =H10+I10 -> 0 | M10: =H10-L10 -> 0 | N10: =IFERROR(M10/B10*10000,0) -> 0 | Q10: =O10+P10 -> 0 | R10: =IF(A10<HlpChangeDate,HlpSharePre,HlpSharePost) -> 0.03 | S10: =Q10*R10/(1-R10) -> 0 | U10: =S10-T10 -> 0 | V10: =Y10-O10*R10/(1-R10) -> 0 | W10: =Z10-P10*R10/(1-R10) -> 0 | X10: =S10+V10+W10 -> 0 | AA10: 0 | AD10: =IFERROR(AA10/AC10,0) -> 0 | AE10: =K10-Q10-X10 -> 0 | AF10: =Q10-AA10 -> 0 | AH10: =IFERROR(AG10/Q10,0) -> 0 | AI10: 0 | AJ10: =IF(AI10>0,AprCoef/SQRT(AI10),0) -> 0 | AK10: =AI10*AJ10/365 -> 0 | AL10: =AD10 -> 0 | AM10: =AK10-AL10 -> 0 | AN10: =IF(A10>=Hip3LaunchDate,"YES","") | AO10: =IF(A10<Hip4LaunchDate,"pre-launch","live (zero-fee)") -> pre-launch
A11: 45072 | B11: 6.3554324e+08 | C11: 0 | E11: =B11+C11 -> 6.3554324e+08 | F11: =E11+D11 -> 6.3554324e+08 | G11: =IFERROR(C11/E11,0) -> 0 | K11: =H11+I11 -> 0 | M11: =H11-L11 -> 0 | N11: =IFERROR(M11/B11*10000,0) -> 0 | Q11: =O11+P11 -> 0 | R11: =IF(A11<HlpChangeDate,HlpSharePre,HlpSharePost) -> 0.03 | S11: =Q11*R11/(1-R11) -> 0 | U11: =S11-T11 -> 0 | V11: =Y11-O11*R11/(1-R11) -> 0 | W11: =Z11-P11*R11/(1-R11) -> 0 | X11: =S11+V11+W11 -> 0 | AA11: 0 | AD11: =IFERROR(AA11/AC11,0) -> 0 | AE11: =K11-Q11-X11 -> 0 | AF11: =Q11-AA11 -> 0 | AH11: =IFERROR(AG11/Q11,0) -> 0 | AI11: 0 | AJ11: =IF(AI11>0,AprCoef/SQRT(AI11),0) -> 0 | AK11: =AI11*AJ11/365 -> 0 | AL11: =AD11 -> 0 | AM11: =AK11-AL11 -> 0 | AN11: =IF(A11>=Hip3LaunchDate,"YES","") | AO11: =IF(A11<Hip4LaunchDate,"pre-launch","live (zero-fee)") -> pre-launch
A12: 45073 | B12: 6.2926637e+08 | C12: 0 | E12: =B12+C12 -> 6.2926637e+08 | F12: =E12+D12 -> 6.2926637e+08 | G12: =IFERROR(C12/E12,0) -> 0 | K12: =H12+I12 -> 0 | M12: =H12-L12 -> 0 | N12: =IFERROR(M12/B12*10000,0) -> 0 | Q12: =O12+P12 -> 0 | R12: =IF(A12<HlpChangeDate,HlpSharePre,HlpSharePost) -> 0.03 | S12: =Q12*R12/(1-R12) -> 0 | U12: =S12-T12 -> 0 | V12: =Y12-O12*R12/(1-R12) -> 0 | W12: =Z12-P12*R12/(1-R12) -> 0 | X12: =S12+V12+W12 -> 0 | AA12: 0 | AD12: =IFERROR(AA12/AC12,0) -> 0 | AE12: =K12-Q12-X12 -> 0 | AF12: =Q12-AA12 -> 0 | AH12: =IFERROR(AG12/Q12,0) -> 0 | AI12: 0 | AJ12: =IF(AI12>0,AprCoef/SQRT(AI12),0) -> 0 | AK12: =AI12*AJ12/365 -> 0 | AL12: =AD12 -> 0 | AM12: =AK12-AL12 -> 0 | AN12: =IF(A12>=Hip3LaunchDate,"YES","") | AO12: =IF(A12<Hip4LaunchDate,"pre-launch","live (zero-fee)") -> pre-launch
A13: 45074 | B13: 1.0302869e+09 | C13: 0 | E13: =B13+C13 -> 1.0302869e+09 | F13: =E13+D13 -> 1.0302869e+09 | G13: =IFERROR(C13/E13,0) -> 0 | K13: =H13+I13 -> 0 | M13: =H13-L13 -> 0 | N13: =IFERROR(M13/B13*10000,0) -> 0 | Q13: =O13+P13 -> 0 | R13: =IF(A13<HlpChangeDate,HlpSharePre,HlpSharePost) -> 0.03 | S13: =Q13*R13/(1-R13) -> 0 | U13: =S13-T13 -> 0 | V13: =Y13-O13*R13/(1-R13) -> 0 | W13: =Z13-P13*R13/(1-R13) -> 0 | X13: =S13+V13+W13 -> 0 | AA13: 0 | AD13: =IFERROR(AA13/AC13,0) -> 0 | AE13: =K13-Q13-X13 -> 0 | AF13: =Q13-AA13 -> 0 | AH13: =IFERROR(AG13/Q13,0) -> 0 | AI13: 0 | AJ13: =IF(AI13>0,AprCoef/SQRT(AI13),0) -> 0 | AK13: =AI13*AJ13/365 -> 0 | AL13: =AD13 -> 0 | AM13: =AK13-AL13 -> 0 | AN13: =IF(A13>=Hip3LaunchDate,"YES","") | AO13: =IF(A13<Hip4LaunchDate,"pre-launch","live (zero-fee)") -> pre-launch
A14: 45075 | B14: 1.6653697e+09 | C14: 0 | E14: =B14+C14 -> 1.6653697e+09 | F14: =E14+D14 -> 1.6653697e+09 | G14: =IFERROR(C14/E14,0) -> 0 | K14: =H14+I14 -> 0 | M14: =H14-L14 -> 0 | N14: =IFERROR(M14/B14*10000,0) -> 0 | Q14: =O14+P14 -> 0 | R14: =IF(A14<HlpChangeDate,HlpSharePre,HlpSharePost) -> 0.03 | S14: =Q14*R14/(1-R14) -> 0 | U14: =S14-T14 -> 0 | V14: =Y14-O14*R14/(1-R14) -> 0 | W14: =Z14-P14*R14/(1-R14) -> 0 | X14: =S14+V14+W14 -> 0 | AA14: 0 | AD14: =IFERROR(AA14/AC14,0) -> 0 | AE14: =K14-Q14-X14 -> 0 | AF14: =Q14-AA14 -> 0 | AH14: =IFERROR(AG14/Q14,0) -> 0 | AI14: 0 | AJ14: =IF(AI14>0,AprCoef/SQRT(AI14),0) -> 0 | AK14: =AI14*AJ14/365 -> 0 | AL14: =AD14 -> 0 | AM14: =AK14-AL14 -> 0 | AN14: =IF(A14>=Hip3LaunchDate,"YES","") | AO14: =IF(A14<Hip4LaunchDate,"pre-launch","live (zero-fee)") -> pre-launch
A15: 45076 | B15: 7.9048504e+08 | C15: 0 | E15: =B15+C15 -> 7.9048504e+08 | F15: =E15+D15 -> 7.9048504e+08 | G15: =IFERROR(C15/E15,0) -> 0 | K15: =H15+I15 -> 0 | M15: =H15-L15 -> 0 | N15: =IFERROR(M15/B15*10000,0) -> 0 | Q15: =O15+P15 -> 0 | R15: =IF(A15<HlpChangeDate,HlpSharePre,HlpSharePost) -> 0.03 | S15: =Q15*R15/(1-R15) -> 0 | U15: =S15-T15 -> 0 | V15: =Y15-O15*R15/(1-R15) -> 0 | W15: =Z15-P15*R15/(1-R15) -> 0 | X15: =S15+V15+W15 -> 0 | AA15: 0 | AD15: =IFERROR(AA15/AC15,0) -> 0 | AE15: =K15-Q15-X15 -> 0 | AF15: =Q15-AA15 -> 0 | AH15: =IFERROR(AG15/Q15,0) -> 0 | AI15: 0 | AJ15: =IF(AI15>0,AprCoef/SQRT(AI15),0) -> 0 | AK15: =AI15*AJ15/365 -> 0 | AL15: =AD15 -> 0 | AM15: =AK15-AL15 -> 0 | AN15: =IF(A15>=Hip3LaunchDate,"YES","") | AO15: =IF(A15<Hip4LaunchDate,"pre-launch","live (zero-fee)") -> pre-launch
A16: 45077 | B16: 6.9786168e+08 | C16: 0 | E16: =B16+C16 -> 6.9786168e+08 | F16: =E16+D16 -> 6.9786168e+08 | G16: =IFERROR(C16/E16,0) -> 0 | K16: =H16+I16 -> 0 | M16: =H16-L16 -> 0 | N16: =IFERROR(M16/B16*10000,0) -> 0 | Q16: =O16+P16 -> 0 | R16: =IF(A16<HlpChangeDate,HlpSharePre,HlpSharePost) -> 0.03 | S16: =Q16*R16/(1-R16) -> 0 | U16: =S16-T16 -> 0 | V16: =Y16-O16*R16/(1-R16) -> 0 | W16: =Z16-P16*R16/(1-R16) -> 0 | X16: =S16+V16+W16 -> 0 | AA16: 0 | AD16: =IFERROR(AA16/AC16,0) -> 0 | AE16: =K16-Q16-X16 -> 0 | AF16: =Q16-AA16 -> 0 | AH16: =IFERROR(AG16/Q16,0) -> 0 | AI16: 0 | AJ16: =IF(AI16>0,AprCoef/SQRT(AI16),0) -> 0 | AK16: =AI16*AJ16/365 -> 0 | AL16: =AD16 -> 0 | AM16: =AK16-AL16 -> 0 | AN16: =IF(A16>=Hip3LaunchDate,"YES","") | AO16: =IF(A16<Hip4LaunchDate,"pre-launch","live (zero-fee)") -> pre-launch
... A492: 45553 | B492: 1.3098399e+09 | C492: 0 | E492: =B492+C492 -> 1.3098399e+09 | F492: =E492+D492 -> 1.3098399e+09 | G492: =IFERROR(C492/E492,0) -> 0 | K492: =H492+I492 -> 0 | M492: =H492-L492 -> 0 | N492: =IFERROR(M492/B492*10000,0) -> 0 | Q492: =O492+P492 -> 0 | R492: =IF(A492<HlpChangeDate,HlpSharePre,HlpSharePost) -> 0.03 | S492: =Q492*R492/(1-R492) -> 0 | U492: =S492-T492 -> 0 | V492: =Y492-O492*R492/(1-R492) -> 0 | W492: =Z492-P492*R492/(1-R492) -> 0 | X492: =S492+V492+W492 -> 0 | AA492: 0 | AD492: =IFERROR(AA492/AC492,0) -> 0 | AE492: =K492-Q492-X492 -> 0 | AF492: =Q492-AA492 -> 0 | AH492: =IFERROR(AG492/Q492,0) -> 0 | AI492: 0 | AJ492: =IF(AI492>0,AprCoef/SQRT(AI492),0) -> 0 | AK492: =AI492*AJ492/365 -> 0 | AL492: =AD492 -> 0 | AM492: =AK492-AL492 -> 0 | AN492: =IF(A492>=Hip3LaunchDate,"YES","") | AO492: =IF(A492<Hip4LaunchDate,"pre-launch","live (zero-fee)") -> pre-launch
A493: 45554 | B493: 1.7619522e+09 | C493: 0 | D493: 3260099 | E493: =B493+C493 -> 1.7619522e+09 | F493: =E493+D493 -> 1.7652123e+09 | G493: =IFERROR(C493/E493,0) -> 0 | K493: =H493+I493 -> 0 | M493: =H493-L493 -> 0 | N493: =IFERROR(M493/B493*10000,0) -> 0 | Q493: =O493+P493 -> 0 | R493: =IF(A493<HlpChangeDate,HlpSharePre,HlpSharePost) -> 0.03 | S493: =Q493*R493/(1-R493) -> 0 | U493: =S493-T493 -> 0 | V493: =Y493-O493*R493/(1-R493) -> 0 | W493: =Z493-P493*R493/(1-R493) -> 0 | X493: =S493+V493+W493 -> 0 | AA493: 0 | AD493: =IFERROR(AA493/AC493,0) -> 0 | AE493: =K493-Q493-X493 -> 0 | AF493: =Q493-AA493 -> 0 | AH493: =IFERROR(AG493/Q493,0) -> 0 | AI493: 0 | AJ493: =IF(AI493>0,AprCoef/SQRT(AI493),0) -> 0 | AK493: =AI493*AJ493/365 -> 0 | AL493: =AD493 -> 0 | AM493: =AK493-AL493 -> 0 | AN493: =IF(A493>=Hip3LaunchDate,"YES","") | AO493: =IF(A493<Hip4LaunchDate,"pre-launch","live (zero-fee)") -> pre-launch
A494: 45555 | B494: 1.1603466e+09 | C494: 0 | D494: 4801770 | E494: =B494+C494 -> 1.1603466e+09 | F494: =E494+D494 -> 1.1651484e+09 | G494: =IFERROR(C494/E494,0) -> 0 | K494: =H494+I494 -> 0 | M494: =H494-L494 -> 0 | N494: =IFERROR(M494/B494*10000,0) -> 0 | Q494: =O494+P494 -> 0 | R494: =IF(A494<HlpChangeDate,HlpSharePre,HlpSharePost) -> 0.03 | S494: =Q494*R494/(1-R494) -> 0 | U494: =S494-T494 -> 0 | V494: =Y494-O494*R494/(1-R494) -> 0 | W494: =Z494-P494*R494/(1-R494) -> 0 | X494: =S494+V494+W494 -> 0 | AA494: 0 | AD494: =IFERROR(AA494/AC494,0) -> 0 | AE494: =K494-Q494-X494 -> 0 | AF494: =Q494-AA494 -> 0 | AH494: =IFERROR(AG494/Q494,0) -> 0 | AI494: 0 | AJ494: =IF(AI494>0,AprCoef/SQRT(AI494),0) -> 0 | AK494: =AI494*AJ494/365 -> 0 | AL494: =AD494 -> 0 | AM494: =AK494-AL494 -> 0 | AN494: =IF(A494>=Hip3LaunchDate,"YES","") | AO494: =IF(A494<Hip4LaunchDate,"pre-launch","live (zero-fee)") -> pre-launch
A495: 45556 | B495: 4.5167684e+08 | C495: 0 | D495: 4983173 | E495: =B495+C495 -> 4.5167684e+08 | F495: =E495+D495 -> 4.5666001e+08 | G495: =IFERROR(C495/E495,0) -> 0 | K495: =H495+I495 -> 0 | M495: =H495-L495 -> 0 | N495: =IFERROR(M495/B495*10000,0) -> 0 | Q495: =O495+P495 -> 0 | R495: =IF(A495<HlpChangeDate,HlpSharePre,HlpSharePost) -> 0.03 | S495: =Q495*R495/(1-R495) -> 0 | U495: =S495-T495 -> 0 | V495: =Y495-O495*R495/(1-R495) -> 0 | W495: =Z495-P495*R495/(1-R495) -> 0 | X495: =S495+V495+W495 -> 0 | AA495: 0 | AD495: =IFERROR(AA495/AC495,0) -> 0 | AE495: =K495-Q495-X495 -> 0 | AF495: =Q495-AA495 -> 0 | AH495: =IFERROR(AG495/Q495,0) -> 0 | AI495: 0 | AJ495: =IF(AI495>0,AprCoef/SQRT(AI495),0) -> 0 | AK495: =AI495*AJ495/365 -> 0 | AL495: =AD495 -> 0 | AM495: =AK495-AL495 -> 0 | AN495: =IF(A495>=Hip3LaunchDate,"YES","") | AO495: =IF(A495<Hip4LaunchDate,"pre-launch","live (zero-fee)") -> pre-launch
A496: 45557 | B496: 6.6972587e+08 | C496: 0 | D496: 4441106 | E496: =B496+C496 -> 6.6972587e+08 | F496: =E496+D496 -> 6.7416697e+08 | G496: =IFERROR(C496/E496,0) -> 0 | K496: =H496+I496 -> 0 | M496: =H496-L496 -> 0 | N496: =IFERROR(M496/B496*10000,0) -> 0 | Q496: =O496+P496 -> 0 | R496: =IF(A496<HlpChangeDate,HlpSharePre,HlpSharePost) -> 0.03 | S496: =Q496*R496/(1-R496) -> 0 | U496: =S496-T496 -> 0 | V496: =Y496-O496*R496/(1-R496) -> 0 | W496: =Z496-P496*R496/(1-R496) -> 0 | X496: =S496+V496+W496 -> 0 | AA496: 0 | AD496: =IFERROR(AA496/AC496,0) -> 0 | AE496: =K496-Q496-X496 -> 0 | AF496: =Q496-AA496 -> 0 | AH496: =IFERROR(AG496/Q496,0) -> 0 | AI496: 0 | AJ496: =IF(AI496>0,AprCoef/SQRT(AI496),0) -> 0 | AK496: =AI496*AJ496/365 -> 0 | AL496: =AD496 -> 0 | AM496: =AK496-AL496 -> 0 | AN496: =IF(A496>=Hip3LaunchDate,"YES","") | AO496: =IF(A496<Hip4LaunchDate,"pre-launch","live (zero-fee)") -> pre-launch
A497: 45558 | B497: 1.4264579e+09 | C497: 0 | D497: 9787031 | E497: =B497+C497 -> 1.4264579e+09 | F497: =E497+D497 -> 1.4362449e+09 | G497: =IFERROR(C497/E497,0) -> 0 | K497: =H497+I497 -> 0 | M497: =H497-L497 -> 0 | N497: =IFERROR(M497/B497*10000,0) -> 0 | Q497: =O497+P497 -> 0 | R497: =IF(A497<HlpChangeDate,HlpSharePre,HlpSharePost) -> 0.03 | S497: =Q497*R497/(1-R497) -> 0 | U497: =S497-T497 -> 0 | V497: =Y497-O497*R497/(1-R497) -> 0 | W497: =Z497-P497*R497/(1-R497) -> 0 | X497: =S497+V497+W497 -> 0 | AA497: 0 | AD497: =IFERROR(AA497/AC497,0) -> 0 | AE497: =K497-Q497-X497 -> 0 | AF497: =Q497-AA497 -> 0 | AH497: =IFERROR(AG497/Q497,0) -> 0 | AI497: 0 | AJ497: =IF(AI497>0,AprCoef/SQRT(AI497),0) -> 0 | AK497: =AI497*AJ497/365 -> 0 | AL497: =AD497 -> 0 | AM497: =AK497-AL497 -> 0 | AN497: =IF(A497>=Hip3LaunchDate,"YES","") | AO497: =IF(A497<Hip4LaunchDate,"pre-launch","live (zero-fee)") -> pre-launch
A498: 45559 | B498: 1.2194153e+09 | C498: 0 | D498: 4003448 | E498: =B498+C498 -> 1.2194153e+09 | F498: =E498+D498 -> 1.2234187e+09 | G498: =IFERROR(C498/E498,0) -> 0 | K498: =H498+I498 -> 0 | M498: =H498-L498 -> 0 | N498: =IFERROR(M498/B498*10000,0) -> 0 | Q498: =O498+P498 -> 0 | R498: =IF(A498<HlpChangeDate,HlpSharePre,HlpSharePost) -> 0.03 | S498: =Q498*R498/(1-R498) -> 0 | U498: =S498-T498 -> 0 | V498: =Y498-O498*R498/(1-R498) -> 0 | W498: =Z498-P498*R498/(1-R498) -> 0 | X498: =S498+V498+W498 -> 0 | AA498: 0 | AD498: =IFERROR(AA498/AC498,0) -> 0 | AE498: =K498-Q498-X498 -> 0 | AF498: =Q498-AA498 -> 0 | AH498: =IFERROR(AG498/Q498,0) -> 0 | AI498: 0 | AJ498: =IF(AI498>0,AprCoef/SQRT(AI498),0) -> 0 | AK498: =AI498*AJ498/365 -> 0 | AL498: =AD498 -> 0 | AM498: =AK498-AL498 -> 0 | AN498: =IF(A498>=Hip3LaunchDate,"YES","") | AO498: =IF(A498<Hip4LaunchDate,"pre-launch","live (zero-fee)") -> pre-launch
A499: 45560 | B499: 1.206077e+09 | C499: 0 | D499: 4050062 | E499: =B499+C499 -> 1.206077e+09 | F499: =E499+D499 -> 1.2101271e+09 | G499: =IFERROR(C499/E499,0) -> 0 | K499: =H499+I499 -> 0 | M499: =H499-L499 -> 0 | N499: =IFERROR(M499/B499*10000,0) -> 0 | Q499: =O499+P499 -> 0 | R499: =IF(A499<HlpChangeDate,HlpSharePre,HlpSharePost) -> 0.03 | S499: =Q499*R499/(1-R499) -> 0 | U499: =S499-T499 -> 0 | V499: =Y499-O499*R499/(1-R499) -> 0 | W499: =Z499-P499*R499/(1-R499) -> 0 | X499: =S499+V499+W499 -> 0 | AA499: 0 | AD499: =IFERROR(AA499/AC499,0) -> 0 | AE499: =K499-Q499-X499 -> 0 | AF499: =Q499-AA499 -> 0 | AH499: =IFERROR(AG499/Q499,0) -> 0 | AI499: 0 | AJ499: =IF(AI499>0,AprCoef/SQRT(AI499),0) -> 0 | AK499: =AI499*AJ499/365 -> 0 | AL499: =AD499 -> 0 | AM499: =AK499-AL499 -> 0 | AN499: =IF(A499>=Hip3LaunchDate,"YES","") | AO499: =IF(A499<Hip4LaunchDate,"pre-launch","live (zero-fee)") -> pre-launch
A500: 45561 | B500: 1.6520725e+09 | C500: 0 | D500: 2720909 | E500: =B500+C500 -> 1.6520725e+09 | F500: =E500+D500 -> 1.6547934e+09 | G500: =IFERROR(C500/E500,0) -> 0 | K500: =H500+I500 -> 0 | M500: =H500-L500 -> 0 | N500: =IFERROR(M500/B500*10000,0) -> 0 | Q500: =O500+P500 -> 0 | R500: =IF(A500<HlpChangeDate,HlpSharePre,HlpSharePost) -> 0.03 | S500: =Q500*R500/(1-R500) -> 0 | U500: =S500-T500 -> 0 | V500: =Y500-O500*R500/(1-R500) -> 0 | W500: =Z500-P500*R500/(1-R500) -> 0 | X500: =S500+V500+W500 -> 0 | AA500: 0 | AD500: =IFERROR(AA500/AC500,0) -> 0 | AE500: =K500-Q500-X500 -> 0 | AF500: =Q500-AA500 -> 0 | AH500: =IFERROR(AG500/Q500,0) -> 0 | AI500: 0 | AJ500: =IF(AI500>0,AprCoef/SQRT(AI500),0) -> 0 | AK500: =AI500*AJ500/365 -> 0 | AL500: =AD500 -> 0 | AM500: =AK500-AL500 -> 0 | AN500: =IF(A500>=Hip3LaunchDate,"YES","") | AO500: =IF(A500<Hip4LaunchDate,"pre-launch","live (zero-fee)") -> pre-launch
A501: 45562 | B501: 1.3608713e+09 | C501: 0 | D501: 3014452 | E501: =B501+C501 -> 1.3608713e+09 | F501: =E501+D501 -> 1.3638857e+09 | G501: =IFERROR(C501/E501,0) -> 0 | K501: =H501+I501 -> 0 | M501: =H501-L501 -> 0 | N501: =IFERROR(M501/B501*10000,0) -> 0 | Q501: =O501+P501 -> 0 | R501: =IF(A501<HlpChangeDate,HlpSharePre,HlpSharePost) -> 0.03 | S501: =Q501*R501/(1-R501) -> 0 | U501: =S501-T501 -> 0 | V501: =Y501-O501*R501/(1-R501) -> 0 | W501: =Z501-P501*R501/(1-R501) -> 0 | X501: =S501+V501+W501 -> 0 | AA501: 0 | AD501: =IFERROR(AA501/AC501,0) -> 0 | AE501: =K501-Q501-X501 -> 0 | AF501: =Q501-AA501 -> 0 | AH501: =IFERROR(AG501/Q501,0) -> 0 | AI501: 0 | AJ501: =IF(AI501>0,AprCoef/SQRT(AI501),0) -> 0 | AK501: =AI501*AJ501/365 -> 0 | AL501: =AD501 -> 0 | AM501: =AK501-AL501 -> 0 | AN501: =IF(A501>=Hip3LaunchDate,"YES","") | AO501: =IF(A501<Hip4LaunchDate,"pre-launch","live (zero-fee)") -> pre-launch
A502: 45563 | B502: 6.2587922e+08 | C502: 0 | D502: 2447124 | E502: =B502+C502 -> 6.2587922e+08 | F502: =E502+D502 -> 6.2832635e+08 | G502: =IFERROR(C502/E502,0) -> 0 | K502: =H502+I502 -> 0 | M502: =H502-L502 -> 0 | N502: =IFERROR(M502/B502*10000,0) -> 0 | Q502: =O502+P502 -> 0 | R502: =IF(A502<HlpChangeDate,HlpSharePre,HlpSharePost) -> 0.03 | S502: =Q502*R502/(1-R502) -> 0 | U502: =S502-T502 -> 0 | V502: =Y502-O502*R502/(1-R502) -> 0 | W502: =Z502-P502*R502/(1-R502) -> 0 | X502: =S502+V502+W502 -> 0 | AA502: 0 | AD502: =IFERROR(AA502/AC502,0) -> 0 | AE502: =K502-Q502-X502 -> 0 | AF502: =Q502-AA502 -> 0 | AH502: =IFERROR(AG502/Q502,0) -> 0 | AI502: 0 | AJ502: =IF(AI502>0,AprCoef/SQRT(AI502),0) -> 0 | AK502: =AI502*AJ502/365 -> 0 | AL502: =AD502 -> 0 | AM502: =AK502-AL502 -> 0 | AN502: =IF(A502>=Hip3LaunchDate,"YES","") | AO502: =IF(A502<Hip4LaunchDate,"pre-launch","live (zero-fee)") -> pre-launch
A503: 45564 | B503: 5.6653266e+08 | C503: 0 | D503: 1971820 | E503: =B503+C503 -> 5.6653266e+08 | F503: =E503+D503 -> 5.6850448e+08 | G503: =IFERROR(C503/E503,0) -> 0 | K503: =H503+I503 -> 0 | M503: =H503-L503 -> 0 | N503: =IFERROR(M503/B503*10000,0) -> 0 | Q503: =O503+P503 -> 0 | R503: =IF(A503<HlpChangeDate,HlpSharePre,HlpSharePost) -> 0.03 | S503: =Q503*R503/(1-R503) -> 0 | U503: =S503-T503 -> 0 | V503: =Y503-O503*R503/(1-R503) -> 0 | W503: =Z503-P503*R503/(1-R503) -> 0 | X503: =S503+V503+W503 -> 0 | AA503: 0 | AD503: =IFERROR(AA503/AC503,0) -> 0 | AE503: =K503-Q503-X503 -> 0 | AF503: =Q503-AA503 -> 0 | AH503: =IFERROR(AG503/Q503,0) -> 0 | AI503: 0 | AJ503: =IF(AI503>0,AprCoef/SQRT(AI503),0) -> 0 | AK503: =AI503*AJ503/365 -> 0 | AL503: =AD503 -> 0 | AM503: =AK503-AL503 -> 0 | AN503: =IF(A503>=Hip3LaunchDate,"YES","") | AO503: =IF(A503<Hip4LaunchDate,"pre-launch","live (zero-fee)") -> pre-launch
A504: 45565 | B504: 1.4412132e+09 | C504: 0 | D504: 2992524 | E504: =B504+C504 -> 1.4412132e+09 | F504: =E504+D504 -> 1.4442057e+09 | G504: =IFERROR(C504/E504,0) -> 0 | K504: =H504+I504 -> 0 | M504: =H504-L504 -> 0 | N504: =IFERROR(M504/B504*10000,0) -> 0 | Q504: =O504+P504 -> 0 | R504: =IF(A504<HlpChangeDate,HlpSharePre,HlpSharePost) -> 0.03 | S504: =Q504*R504/(1-R504) -> 0 | U504: =S504-T504 -> 0 | V504: =Y504-O504*R504/(1-R504) -> 0 | W504: =Z504-P504*R504/(1-R504) -> 0 | X504: =S504+V504+W504 -> 0 | AA504: 0 | AD504: =IFERROR(AA504/AC504,0) -> 0 | AE504: =K504-Q504-X504 -> 0 | AF504: =Q504-AA504 -> 0 | AH504: =IFERROR(AG504/Q504,0) -> 0 | AI504: 0 | AJ504: =IF(AI504>0,AprCoef/SQRT(AI504),0) -> 0 | AK504: =AI504*AJ504/365 -> 0 | AL504: =AD504 -> 0 | AM504: =AK504-AL504 -> 0 | AN504: =IF(A504>=Hip3LaunchDate,"YES","") | AO504: =IF(A504<Hip4LaunchDate,"pre-launch","live (zero-fee)") -> pre-launch
... A559: 45620 | B559: 2.2105278e+09 | C559: 0 | D559: 2473310 | E559: =B559+C559 -> 2.2105278e+09 | F559: =E559+D559 -> 2.2130012e+09 | G559: =IFERROR(C559/E559,0) -> 0 | K559: =H559+I559 -> 0 | M559: =H559-L559 -> 0 | N559: =IFERROR(M559/B559*10000,0) -> 0 | Q559: =O559+P559 -> 0 | R559: =IF(A559<HlpChangeDate,HlpSharePre,HlpSharePost) -> 0.03 | S559: =Q559*R559/(1-R559) -> 0 | U559: =S559-T559 -> 0 | V559: =Y559-O559*R559/(1-R559) -> 0 | W559: =Z559-P559*R559/(1-R559) -> 0 | X559: =S559+V559+W559 -> 0 | AA559: 0 | AD559: =IFERROR(AA559/AC559,0) -> 0 | AE559: =K559-Q559-X559 -> 0 | AF559: =Q559-AA559 -> 0 | AH559: =IFERROR(AG559/Q559,0) -> 0 | AI559: 0 | AJ559: =IF(AI559>0,AprCoef/SQRT(AI559),0) -> 0 | AK559: =AI559*AJ559/365 -> 0 | AL559: =AD559 -> 0 | AM559: =AK559-AL559 -> 0 | AN559: =IF(A559>=Hip3LaunchDate,"YES","") | AO559: =IF(A559<Hip4LaunchDate,"pre-launch","live (zero-fee)") -> pre-launch
A560: 45621 | B560: 3.2691508e+09 | C560: 0 | D560: 5628946 | E560: =B560+C560 -> 3.2691508e+09 | F560: =E560+D560 -> 3.2747798e+09 | G560: =IFERROR(C560/E560,0) -> 0 | K560: =H560+I560 -> 0 | M560: =H560-L560 -> 0 | N560: =IFERROR(M560/B560*10000,0) -> 0 | Q560: =O560+P560 -> 0 | R560: =IF(A560<HlpChangeDate,HlpSharePre,HlpSharePost) -> 0.03 | S560: =Q560*R560/(1-R560) -> 0 | U560: =S560-T560 -> 0 | V560: =Y560-O560*R560/(1-R560) -> 0 | W560: =Z560-P560*R560/(1-R560) -> 0 | X560: =S560+V560+W560 -> 0 | AA560: 0 | AD560: =IFERROR(AA560/AC560,0) -> 0 | AE560: =K560-Q560-X560 -> 0 | AF560: =Q560-AA560 -> 0 | AG560: 4585090.2 | AH560: =IFERROR(AG560/Q560,0) -> 0 | AI560: 0 | AJ560: =IF(AI560>0,AprCoef/SQRT(AI560),0) -> 0 | AK560: =AI560*AJ560/365 -> 0 | AL560: =AD560 -> 0 | AM560: =AK560-AL560 -> 0 | AN560: =IF(A560>=Hip3LaunchDate,"YES","") | AO560: =IF(A560<Hip4LaunchDate,"pre-launch","live (zero-fee)") -> pre-launch
A561: 45622 | B561: 3.3938162e+09 | C561: 0 | D561: 7041832 | E561: =B561+C561 -> 3.3938162e+09 | F561: =E561+D561 -> 3.4008581e+09 | G561: =IFERROR(C561/E561,0) -> 0 | K561: =H561+I561 -> 0 | M561: =H561-L561 -> 0 | N561: =IFERROR(M561/B561*10000,0) -> 0 | Q561: =O561+P561 -> 0 | R561: =IF(A561<HlpChangeDate,HlpSharePre,HlpSharePost) -> 0.03 | S561: =Q561*R561/(1-R561) -> 0 | U561: =S561-T561 -> 0 | V561: =Y561-O561*R561/(1-R561) -> 0 | W561: =Z561-P561*R561/(1-R561) -> 0 | X561: =S561+V561+W561 -> 0 | AA561: 0 | AD561: =IFERROR(AA561/AC561,0) -> 0 | AE561: =K561-Q561-X561 -> 0 | AF561: =Q561-AA561 -> 0 | AH561: =IFERROR(AG561/Q561,0) -> 0 | AI561: 0 | AJ561: =IF(AI561>0,AprCoef/SQRT(AI561),0) -> 0 | AK561: =AI561*AJ561/365 -> 0 | AL561: =AD561 -> 0 | AM561: =AK561-AL561 -> 0 | AN561: =IF(A561>=Hip3LaunchDate,"YES","") | AO561: =IF(A561<Hip4LaunchDate,"pre-launch","live (zero-fee)") -> pre-launch
A562: 45623 | B562: 2.2108559e+09 | C562: 0 | D562: 4131241 | E562: =B562+C562 -> 2.2108559e+09 | F562: =E562+D562 -> 2.2149872e+09 | G562: =IFERROR(C562/E562,0) -> 0 | K562: =H562+I562 -> 0 | M562: =H562-L562 -> 0 | N562: =IFERROR(M562/B562*10000,0) -> 0 | Q562: =O562+P562 -> 0 | R562: =IF(A562<HlpChangeDate,HlpSharePre,HlpSharePost) -> 0.03 | S562: =Q562*R562/(1-R562) -> 0 | U562: =S562-T562 -> 0 | V562: =Y562-O562*R562/(1-R562) -> 0 | W562: =Z562-P562*R562/(1-R562) -> 0 | X562: =S562+V562+W562 -> 0 | AA562: 0 | AD562: =IFERROR(AA562/AC562,0) -> 0 | AE562: =K562-Q562-X562 -> 0 | AF562: =Q562-AA562 -> 0 | AH562: =IFERROR(AG562/Q562,0) -> 0 | AI562: 0 | AJ562: =IF(AI562>0,AprCoef/SQRT(AI562),0) -> 0 | AK562: =AI562*AJ562/365 -> 0 | AL562: =AD562 -> 0 | AM562: =AK562-AL562 -> 0 | AN562: =IF(A562>=Hip3LaunchDate,"YES","") | AO562: =IF(A562<Hip4LaunchDate,"pre-launch","live (zero-fee)") -> pre-launch
A563: 45624 | B563: 1.7653393e+09 | C563: 0 | D563: 19036485 | E563: =B563+C563 -> 1.7653393e+09 | F563: =E563+D563 -> 1.7843758e+09 | G563: =IFERROR(C563/E563,0) -> 0 | K563: =H563+I563 -> 0 | M563: =H563-L563 -> 0 | N563: =IFERROR(M563/B563*10000,0) -> 0 | Q563: =O563+P563 -> 0 | R563: =IF(A563<HlpChangeDate,HlpSharePre,HlpSharePost) -> 0.03 | S563: =Q563*R563/(1-R563) -> 0 | U563: =S563-T563 -> 0 | V563: =Y563-O563*R563/(1-R563) -> 0 | W563: =Z563-P563*R563/(1-R563) -> 0 | X563: =S563+V563+W563 -> 0 | AA563: 0 | AD563: =IFERROR(AA563/AC563,0) -> 0 | AE563: =K563-Q563-X563 -> 0 | AF563: =Q563-AA563 -> 0 | AH563: =IFERROR(AG563/Q563,0) -> 0 | AI563: 0 | AJ563: =IF(AI563>0,AprCoef/SQRT(AI563),0) -> 0 | AK563: =AI563*AJ563/365 -> 0 | AL563: =AD563 -> 0 | AM563: =AK563-AL563 -> 0 | AN563: =IF(A563>=Hip3LaunchDate,"YES","") | AO563: =IF(A563<Hip4LaunchDate,"pre-launch","live (zero-fee)") -> pre-launch
A564: 45625 | B564: 1.8146872e+09 | C564: 0 | D564: 951196324 | E564: =B564+C564 -> 1.8146872e+09 | F564: =E564+D564 -> 2.7658836e+09 | G564: =IFERROR(C564/E564,0) -> 0 | K564: =H564+I564 -> 0 | M564: =H564-L564 -> 0 | N564: =IFERROR(M564/B564*10000,0) -> 0 | Q564: =O564+P564 -> 0 | R564: =IF(A564<HlpChangeDate,HlpSharePre,HlpSharePost) -> 0.03 | S564: =Q564*R564/(1-R564) -> 0 | U564: =S564-T564 -> 0 | V564: =Y564-O564*R564/(1-R564) -> 0 | W564: =Z564-P564*R564/(1-R564) -> 0 | X564: =S564+V564+W564 -> 0 | AA564: 0 | AB564: 6.252 | AC564: 4.2155 | AD564: =IFERROR(AA564/AC564,0) -> 0 | AE564: =K564-Q564-X564 -> 0 | AF564: =Q564-AA564 -> 0 | AG564: 2497425.1 | AH564: =IFERROR(AG564/Q564,0) -> 0 | AI564: 0 | AJ564: =IF(AI564>0,AprCoef/SQRT(AI564),0) -> 0 | AK564: =AI564*AJ564/365 -> 0 | AL564: =AD564 -> 0 | AM564: =AK564-AL564 -> 0 | AN564: =IF(A564>=Hip3LaunchDate,"YES","") | AO564: =IF(A564<Hip4LaunchDate,"pre-launch","live (zero-fee)") -> pre-launch
A565: 45626 | B565: 1.9278396e+09 | C565: 0 | D565: 460835741 | E565: =B565+C565 -> 1.9278396e+09 | F565: =E565+D565 -> 2.3886754e+09 | G565: =IFERROR(C565/E565,0) -> 0 | K565: =H565+I565 -> 0 | M565: =H565-L565 -> 0 | N565: =IFERROR(M565/B565*10000,0) -> 0 | Q565: =O565+P565 -> 0 | R565: =IF(A565<HlpChangeDate,HlpSharePre,HlpSharePost) -> 0.03 | S565: =Q565*R565/(1-R565) -> 0 | U565: =S565-T565 -> 0 | V565: =Y565-O565*R565/(1-R565) -> 0 | W565: =Z565-P565*R565/(1-R565) -> 0 | X565: =S565+V565+W565 -> 0 | AA565: 0 | AB565: 8.4985 | AC565: 7.454675 | AD565: =IFERROR(AA565/AC565,0) -> 0 | AE565: =K565-Q565-X565 -> 0 | AF565: =Q565-AA565 -> 0 | AH565: =IFERROR(AG565/Q565,0) -> 0 | AI565: 0 | AJ565: =IF(AI565>0,AprCoef/SQRT(AI565),0) -> 0 | AK565: =AI565*AJ565/365 -> 0 | AL565: =AD565 -> 0 | AM565: =AK565-AL565 -> 0 | AN565: =IF(A565>=Hip3LaunchDate,"YES","") | AO565: =IF(A565<Hip4LaunchDate,"pre-launch","live (zero-fee)") -> pre-launch
A566: 45627 | B566: 2.2309523e+09 | C566: 0 | D566: 382137710 | E566: =B566+C566 -> 2.2309523e+09 | F566: =E566+D566 -> 2.61309e+09 | G566: =IFERROR(C566/E566,0) -> 0 | K566: =H566+I566 -> 0 | M566: =H566-L566 -> 0 | N566: =IFERROR(M566/B566*10000,0) -> 0 | Q566: =O566+P566 -> 0 | R566: =IF(A566<HlpChangeDate,HlpSharePre,HlpSharePost) -> 0.03 | S566: =Q566*R566/(1-R566) -> 0 | U566: =S566-T566 -> 0 | V566: =Y566-O566*R566/(1-R566) -> 0 | W566: =Z566-P566*R566/(1-R566) -> 0 | X566: =S566+V566+W566 -> 0 | AA566: 0 | AB566: 9.4686 | AC566: 8.98335 | AD566: =IFERROR(AA566/AC566,0) -> 0 | AE566: =K566-Q566-X566 -> 0 | AF566: =Q566-AA566 -> 0 | AH566: =IFERROR(AG566/Q566,0) -> 0 | AI566: 0 | AJ566: =IF(AI566>0,AprCoef/SQRT(AI566),0) -> 0 | AK566: =AI566*AJ566/365 -> 0 | AL566: =AD566 -> 0 | AM566: =AK566-AL566 -> 0 | AN566: =IF(A566>=Hip3LaunchDate,"YES","") | AO566: =IF(A566<Hip4LaunchDate,"pre-launch","live (zero-fee)") -> pre-launch
A567: 45628 | B567: 5.3331258e+09 | C567: 0 | D567: 320571512 | E567: =B567+C567 -> 5.3331258e+09 | F567: =E567+D567 -> 5.6536974e+09 | G567: =IFERROR(C567/E567,0) -> 0 | K567: =H567+I567 -> 0 | M567: =H567-L567 -> 0 | N567: =IFERROR(M567/B567*10000,0) -> 0 | Q567: =O567+P567 -> 0 | R567: =IF(A567<HlpChangeDate,HlpSharePre,HlpSharePost) -> 0.03 | S567: =Q567*R567/(1-R567) -> 0 | U567: =S567-T567 -> 0 | V567: =Y567-O567*R567/(1-R567) -> 0 | W567: =Z567-P567*R567/(1-R567) -> 0 | X567: =S567+V567+W567 -> 0 | AA567: 0 | AB567: 8.4277 | AC567: 8.68185 | AD567: =IFERROR(AA567/AC567,0) -> 0 | AE567: =K567-Q567-X567 -> 0 | AF567: =Q567-AA567 -> 0 | AG567: 2313969.7 | AH567: =IFERROR(AG567/Q567,0) -> 0 | AI567: 0 | AJ567: =IF(AI567>0,AprCoef/SQRT(AI567),0) -> 0 | AK567: =AI567*AJ567/365 -> 0 | AL567: =AD567 -> 0 | AM567: =AK567-AL567 -> 0 | AN567: =IF(A567>=Hip3LaunchDate,"YES","") | AO567: =IF(A567<Hip4LaunchDate,"pre-launch","live (zero-fee)") -> pre-launch
A568: 45629 | B568: 4.8819819e+09 | C568: 0 | D568: 302890343 | E568: =B568+C568 -> 4.8819819e+09 | F568: =E568+D568 -> 5.1848722e+09 | G568: =IFERROR(C568/E568,0) -> 0 | K568: =H568+I568 -> 0 | M568: =H568-L568 -> 0 | N568: =IFERROR(M568/B568*10000,0) -> 0 | Q568: =O568+P568 -> 0 | R568: =IF(A568<HlpChangeDate,HlpSharePre,HlpSharePost) -> 0.03 | S568: =Q568*R568/(1-R568) -> 0 | U568: =S568-T568 -> 0 | V568: =Y568-O568*R568/(1-R568) -> 0 | W568: =Z568-P568*R568/(1-R568) -> 0 | X568: =S568+V568+W568 -> 0 | AA568: 0 | AB568: 11.082 | AC568: 9.76005 | AD568: =IFERROR(AA568/AC568,0) -> 0 | AE568: =K568-Q568-X568 -> 0 | AF568: =Q568-AA568 -> 0 | AH568: =IFERROR(AG568/Q568,0) -> 0 | AI568: 0 | AJ568: =IF(AI568>0,AprCoef/SQRT(AI568),0) -> 0 | AK568: =AI568*AJ568/365 -> 0 | AL568: =AD568 -> 0 | AM568: =AK568-AL568 -> 0 | AN568: =IF(A568>=Hip3LaunchDate,"YES","") | AO568: =IF(A568<Hip4LaunchDate,"pre-launch","live (zero-fee)") -> pre-launch
A569: 45630 | B569: 6.2259185e+09 | C569: 0 | D569: 318696984 | E569: =B569+C569 -> 6.2259185e+09 | F569: =E569+D569 -> 6.5446155e+09 | G569: =IFERROR(C569/E569,0) -> 0 | K569: =H569+I569 -> 0 | M569: =H569-L569 -> 0 | N569: =IFERROR(M569/B569*10000,0) -> 0 | Q569: =O569+P569 -> 0 | R569: =IF(A569<HlpChangeDate,HlpSharePre,HlpSharePost) -> 0.03 | S569: =Q569*R569/(1-R569) -> 0 | U569: =S569-T569 -> 0 | V569: =Y569-O569*R569/(1-R569) -> 0 | W569: =Z569-P569*R569/(1-R569) -> 0 | X569: =S569+V569+W569 -> 0 | AA569: 0 | AB569: 11.403 | AC569: 11.6015 | AD569: =IFERROR(AA569/AC569,0) -> 0 | AE569: =K569-Q569-X569 -> 0 | AF569: =Q569-AA569 -> 0 | AH569: =IFERROR(AG569/Q569,0) -> 0 | AI569: 0 | AJ569: =IF(AI569>0,AprCoef/SQRT(AI569),0) -> 0 | AK569: =AI569*AJ569/365 -> 0 | AL569: =AD569 -> 0 | AM569: =AK569-AL569 -> 0 | AN569: =IF(A569>=Hip3LaunchDate,"YES","") | AO569: =IF(A569<Hip4LaunchDate,"pre-launch","live (zero-fee)") -> pre-launch
A570: 45631 | B570: 9.7895628e+09 | C570: 0 | D570: 323114172 | E570: =B570+C570 -> 9.7895628e+09 | F570: =E570+D570 -> 1.0112677e+10 | G570: =IFERROR(C570/E570,0) -> 0 | K570: =H570+I570 -> 0 | M570: =H570-L570 -> 0 | N570: =IFERROR(M570/B570*10000,0) -> 0 | Q570: =O570+P570 -> 0 | R570: =IF(A570<HlpChangeDate,HlpSharePre,HlpSharePost) -> 0.03 | S570: =Q570*R570/(1-R570) -> 0 | U570: =S570-T570 -> 0 | V570: =Y570-O570*R570/(1-R570) -> 0 | W570: =Z570-P570*R570/(1-R570) -> 0 | X570: =S570+V570+W570 -> 0 | AA570: 0 | AB570: 12.71 | AC570: 12.115 | AD570: =IFERROR(AA570/AC570,0) -> 0 | AE570: =K570-Q570-X570 -> 0 | AF570: =Q570-AA570 -> 0 | AH570: =IFERROR(AG570/Q570,0) -> 0 | AI570: 0 | AJ570: =IF(AI570>0,AprCoef/SQRT(AI570),0) -> 0 | AK570: =AI570*AJ570/365 -> 0 | AL570: =AD570 -> 0 | AM570: =AK570-AL570 -> 0 | AN570: =IF(A570>=Hip3LaunchDate,"YES","") | AO570: =IF(A570<Hip4LaunchDate,"pre-launch","live (zero-fee)") -> pre-launch
A571: 45632 | B571: 7.8114744e+09 | C571: 0 | D571: 218646771 | E571: =B571+C571 -> 7.8114744e+09 | F571: =E571+D571 -> 8.0301212e+09 | G571: =IFERROR(C571/E571,0) -> 0 | K571: =H571+I571 -> 0 | M571: =H571-L571 -> 0 | N571: =IFERROR(M571/B571*10000,0) -> 0 | Q571: =O571+P571 -> 0 | R571: =IF(A571<HlpChangeDate,HlpSharePre,HlpSharePost) -> 0.03 | S571: =Q571*R571/(1-R571) -> 0 | U571: =S571-T571 -> 0 | V571: =Y571-O571*R571/(1-R571) -> 0 | W571: =Z571-P571*R571/(1-R571) -> 0 | X571: =S571+V571+W571 -> 0 | AA571: 0 | AB571: 13.829 | AC571: 13.2985 | AD571: =IFERROR(AA571/AC571,0) -> 0 | AE571: =K571-Q571-X571 -> 0 | AF571: =Q571-AA571 -> 0 | AH571: =IFERROR(AG571/Q571,0) -> 0 | AI571: 0 | AJ571: =IF(AI571>0,AprCoef/SQRT(AI571),0) -> 0 | AK571: =AI571*AJ571/365 -> 0 | AL571: =AD571 -> 0 | AM571: =AK571-AL571 -> 0 | AN571: =IF(A571>=Hip3LaunchDate,"YES","") | AO571: =IF(A571<Hip4LaunchDate,"pre-launch","live (zero-fee)") -> pre-launch
A572: 45633 | B572: 2.8624379e+09 | C572: 0 | D572: 182104753 | E572: =B572+C572 -> 2.8624379e+09 | F572: =E572+D572 -> 3.0445427e+09 | G572: =IFERROR(C572/E572,0) -> 0 | K572: =H572+I572 -> 0 | M572: =H572-L572 -> 0 | N572: =IFERROR(M572/B572*10000,0) -> 0 | Q572: =O572+P572 -> 0 | R572: =IF(A572<HlpChangeDate,HlpSharePre,HlpSharePost) -> 0.03 | S572: =Q572*R572/(1-R572) -> 0 | U572: =S572-T572 -> 0 | V572: =Y572-O572*R572/(1-R572) -> 0 | W572: =Z572-P572*R572/(1-R572) -> 0 | X572: =S572+V572+W572 -> 0 | AA572: 0 | AB572: 14.117 | AC572: 14.1115 | AD572: =IFERROR(AA572/AC572,0) -> 0 | AE572: =K572-Q572-X572 -> 0 | AF572: =Q572-AA572 -> 0 | AH572: =IFERROR(AG572/Q572,0) -> 0 | AI572: 0 | AJ572: =IF(AI572>0,AprCoef/SQRT(AI572),0) -> 0 | AK572: =AI572*AJ572/365 -> 0 | AL572: =AD572 -> 0 | AM572: =AK572-AL572 -> 0 | AN572: =IF(A572>=Hip3LaunchDate,"YES","") | AO572: =IF(A572<Hip4LaunchDate,"pre-launch","live (zero-fee)") -> pre-launch
A573: 45634 | B573: 3.2527988e+09 | C573: 0 | D573: 136064768 | E573: =B573+C573 -> 3.2527988e+09 | F573: =E573+D573 -> 3.3888636e+09 | G573: =IFERROR(C573/E573,0) -> 0 | K573: =H573+I573 -> 0 | M573: =H573-L573 -> 0 | N573: =IFERROR(M573/B573*10000,0) -> 0 | Q573: =O573+P573 -> 0 | R573: =IF(A573<HlpChangeDate,HlpSharePre,HlpSharePost) -> 0.03 | S573: =Q573*R573/(1-R573) -> 0 | U573: =S573-T573 -> 0 | V573: =Y573-O573*R573/(1-R573) -> 0 | W573: =Z573-P573*R573/(1-R573) -> 0 | X573: =S573+V573+W573 -> 0 | AA573: 0 | AB573: 14.02 | AC573: 14.07775 | AD573: =IFERROR(AA573/AC573,0) -> 0 | AE573: =K573-Q573-X573 -> 0 | AF573: =Q573-AA573 -> 0 | AH573: =IFERROR(AG573/Q573,0) -> 0 | AI573: 0 | AJ573: =IF(AI573>0,AprCoef/SQRT(AI573),0) -> 0 | AK573: =AI573*AJ573/365 -> 0 | AL573: =AD573 -> 0 | AM573: =AK573-AL573 -> 0 | AN573: =IF(A573>=Hip3LaunchDate,"YES","") | AO573: =IF(A573<Hip4LaunchDate,"pre-launch","live (zero-fee)") -> pre-launch
A574: 45635 | B574: 5.3063589e+09 | C574: 0 | D574: 270676721 | E574: =B574+C574 -> 5.3063589e+09 | F574: =E574+D574 -> 5.5770357e+09 | G574: =IFERROR(C574/E574,0) -> 0 | K574: =H574+I574 -> 0 | M574: =H574-L574 -> 0 | N574: =IFERROR(M574/B574*10000,0) -> 0 | Q574: =O574+P574 -> 0 | R574: =IF(A574<HlpChangeDate,HlpSharePre,HlpSharePost) -> 0.03 | S574: =Q574*R574/(1-R574) -> 0 | U574: =S574-T574 -> 0 | V574: =Y574-O574*R574/(1-R574) -> 0 | W574: =Z574-P574*R574/(1-R574) -> 0 | X574: =S574+V574+W574 -> 0 | AA574: 0 | AB574: 13.541 | AC574: 13.4875 | AD574: =IFERROR(AA574/AC574,0) -> 0 | AE574: =K574-Q574-X574 -> 0 | AF574: =Q574-AA574 -> 0 | AH574: =IFERROR(AG574/Q574,0) -> 0 | AI574: 0 | AJ574: =IF(AI574>0,AprCoef/SQRT(AI574),0) -> 0 | AK574: =AI574*AJ574/365 -> 0 | AL574: =AD574 -> 0 | AM574: =AK574-AL574 -> 0 | AN574: =IF(A574>=Hip3LaunchDate,"YES","") | AO574: =IF(A574<Hip4LaunchDate,"pre-launch","live (zero-fee)") -> pre-launch
A575: 45636 | B575: 1.0009954e+10 | C575: 0 | D575: 208129108 | E575: =B575+C575 -> 1.0009954e+10 | F575: =E575+D575 -> 1.0218083e+10 | G575: =IFERROR(C575/E575,0) -> 0 | K575: =H575+I575 -> 0 | M575: =H575-L575 -> 0 | N575: =IFERROR(M575/B575*10000,0) -> 0 | Q575: =O575+P575 -> 0 | R575: =IF(A575<HlpChangeDate,HlpSharePre,HlpSharePost) -> 0.03 | S575: =Q575*R575/(1-R575) -> 0 | U575: =S575-T575 -> 0 | V575: =Y575-O575*R575/(1-R575) -> 0 | W575: =Z575-P575*R575/(1-R575) -> 0 | X575: =S575+V575+W575 -> 0 | AA575: 0 | AB575: 13.562 | AC575: 13.54725 | AD575: =IFERROR(AA575/AC575,0) -> 0 | AE575: =K575-Q575-X575 -> 0 | AF575: =Q575-AA575 -> 0 | AH575: =IFERROR(AG575/Q575,0) -> 0 | AI575: 0 | AJ575: =IF(AI575>0,AprCoef/SQRT(AI575),0) -> 0 | AK575: =AI575*AJ575/365 -> 0 | AL575: =AD575 -> 0 | AM575: =AK575-AL575 -> 0 | AN575: =IF(A575>=Hip3LaunchDate,"YES","") | AO575: =IF(A575<Hip4LaunchDate,"pre-launch","live (zero-fee)") -> pre-launch
A576: 45637 | B576: 3.9793992e+09 | C576: 0 | D576: 211797447 | E576: =B576+C576 -> 3.9793992e+09 | F576: =E576+D576 -> 4.1911967e+09 | G576: =IFERROR(C576/E576,0) -> 0 | K576: =H576+I576 -> 0 | M576: =H576-L576 -> 0 | N576: =IFERROR(M576/B576*10000,0) -> 0 | Q576: =O576+P576 -> 0 | R576: =IF(A576<HlpChangeDate,HlpSharePre,HlpSharePost) -> 0.03 | S576: =Q576*R576/(1-R576) -> 0 | U576: =S576-T576 -> 0 | V576: =Y576-O576*R576/(1-R576) -> 0 | W576: =Z576-P576*R576/(1-R576) -> 0 | X576: =S576+V576+W576 -> 0 | AA576: 0 | AB576: 16.115 | AC576: 14.80575 | AD576: =IFERROR(AA576/AC576,0) -> 0 | AE576: =K576-Q576-X576 -> 0 | AF576: =Q576-AA576 -> 0 | AH576: =IFERROR(AG576/Q576,0) -> 0 | AI576: 0 | AJ576: =IF(AI576>0,AprCoef/SQRT(AI576),0) -> 0 | AK576: =AI576*AJ576/365 -> 0 | AL576: =AD576 -> 0 | AM576: =AK576-AL576 -> 0 | AN576: =IF(A576>=Hip3LaunchDate,"YES","") | AO576: =IF(A576<Hip4LaunchDate,"pre-launch","live (zero-fee)") -> pre-launch
A577: 45638 | B577: 4.8390459e+09 | C577: 0 | D577: 324908474 | E577: =B577+C577 -> 4.8390459e+09 | F577: =E577+D577 -> 5.1639544e+09 | G577: =IFERROR(C577/E577,0) -> 0 | K577: =H577+I577 -> 0 | M577: =H577-L577 -> 0 | N577: =IFERROR(M577/B577*10000,0) -> 0 | Q577: =O577+P577 -> 0 | R577: =IF(A577<HlpChangeDate,HlpSharePre,HlpSharePost) -> 0.03 | S577: =Q577*R577/(1-R577) -> 0 | U577: =S577-T577 -> 0 | V577: =Y577-O577*R577/(1-R577) -> 0 | W577: =Z577-P577*R577/(1-R577) -> 0 | X577: =S577+V577+W577 -> 0 | AA577: 0 | AB577: 18.041 | AC577: 17.1275 | AD577: =IFERROR(AA577/AC577,0) -> 0 | AE577: =K577-Q577-X577 -> 0 | AF577: =Q577-AA577 -> 0 | AH577: =IFERROR(AG577/Q577,0) -> 0 | AI577: 0 | AJ577: =IF(AI577>0,AprCoef/SQRT(AI577),0) -> 0 | AK577: =AI577*AJ577/365 -> 0 | AL577: =AD577 -> 0 | AM577: =AK577-AL577 -> 0 | AN577: =IF(A577>=Hip3LaunchDate,"YES","") | AO577: =IF(A577<Hip4LaunchDate,"pre-launch","live (zero-fee)") -> pre-launch
A578: 45639 | B578: 4.2533193e+09 | C578: 0 | D578: 334237923 | E578: =B578+C578 -> 4.2533193e+09 | F578: =E578+D578 -> 4.5875573e+09 | G578: =IFERROR(C578/E578,0) -> 0 | K578: =H578+I578 -> 0 | M578: =H578-L578 -> 0 | N578: =IFERROR(M578/B578*10000,0) -> 0 | Q578: =O578+P578 -> 0 | R578: =IF(A578<HlpChangeDate,HlpSharePre,HlpSharePost) -> 0.03 | S578: =Q578*R578/(1-R578) -> 0 | U578: =S578-T578 -> 0 | V578: =Y578-O578*R578/(1-R578) -> 0 | W578: =Z578-P578*R578/(1-R578) -> 0 | X578: =S578+V578+W578 -> 0 | AA578: 0 | AB578: 19.48 | AC578: 18.50825 | AD578: =IFERROR(AA578/AC578,0) -> 0 | AE578: =K578-Q578-X578 -> 0 | AF578: =Q578-AA578 -> 0 | AH578: =IFERROR(AG578/Q578,0) -> 0 | AI578: 0 | AJ578: =IF(AI578>0,AprCoef/SQRT(AI578),0) -> 0 | AK578: =AI578*AJ578/365 -> 0 | AL578: =AD578 -> 0 | AM578: =AK578-AL578 -> 0 | AN578: =IF(A578>=Hip3LaunchDate,"YES","") | AO578: =IF(A578<Hip4LaunchDate,"pre-launch","live (zero-fee)") -> pre-launch
A579: 45640 | B579: 3.1705221e+09 | C579: 0 | D579: 546075604 | E579: =B579+C579 -> 3.1705221e+09 | F579: =E579+D579 -> 3.7165977e+09 | G579: =IFERROR(C579/E579,0) -> 0 | K579: =H579+I579 -> 0 | M579: =H579-L579 -> 0 | N579: =IFERROR(M579/B579*10000,0) -> 0 | Q579: =O579+P579 -> 0 | R579: =IF(A579<HlpChangeDate,HlpSharePre,HlpSharePost) -> 0.03 | S579: =Q579*R579/(1-R579) -> 0 | U579: =S579-T579 -> 0 | V579: =Y579-O579*R579/(1-R579) -> 0 | W579: =Z579-P579*R579/(1-R579) -> 0 | X579: =S579+V579+W579 -> 0 | AA579: 0 | AB579: 24.151 | AC579: 21.7505 | AD579: =IFERROR(AA579/AC579,0) -> 0 | AE579: =K579-Q579-X579 -> 0 | AF579: =Q579-AA579 -> 0 | AH579: =IFERROR(AG579/Q579,0) -> 0 | AI579: 0 | AJ579: =IF(AI579>0,AprCoef/SQRT(AI579),0) -> 0 | AK579: =AI579*AJ579/365 -> 0 | AL579: =AD579 -> 0 | AM579: =AK579-AL579 -> 0 | AN579: =IF(A579>=Hip3LaunchDate,"YES","") | AO579: =IF(A579<Hip4LaunchDate,"pre-launch","live (zero-fee)") -> pre-launch
... A582: 45643 | B582: 5.5938649e+09 | C582: 0 | D582: 533018011 | E582: =B582+C582 -> 5.5938649e+09 | F582: =E582+D582 -> 6.1268829e+09 | G582: =IFERROR(C582/E582,0) -> 0 | K582: =H582+I582 -> 0 | M582: =H582-L582 -> 0 | N582: =IFERROR(M582/B582*10000,0) -> 0 | Q582: =O582+P582 -> 0 | R582: =IF(A582<HlpChangeDate,HlpSharePre,HlpSharePost) -> 0.03 | S582: =Q582*R582/(1-R582) -> 0 | U582: =S582-T582 -> 0 | V582: =Y582-O582*R582/(1-R582) -> 0 | W582: =Z582-P582*R582/(1-R582) -> 0 | X582: =S582+V582+W582 -> 0 | AA582: 0 | AB582: 25.583 | AC582: 26.38125 | AD582: =IFERROR(AA582/AC582,0) -> 0 | AE582: =K582-Q582-X582 -> 0 | AF582: =Q582-AA582 -> 0 | AH582: =IFERROR(AG582/Q582,0) -> 0 | AI582: 0 | AJ582: =IF(AI582>0,AprCoef/SQRT(AI582),0) -> 0 | AK582: =AI582*AJ582/365 -> 0 | AL582: =AD582 -> 0 | AM582: =AK582-AL582 -> 0 | AN582: =IF(A582>=Hip3LaunchDate,"YES","") | AO582: =IF(A582<Hip4LaunchDate,"pre-launch","live (zero-fee)") -> pre-launch
A583: 45644 | B583: 8.540539e+09 | C583: 0 | D583: 472394527 | E583: =B583+C583 -> 8.540539e+09 | F583: =E583+D583 -> 9.0129336e+09 | G583: =IFERROR(C583/E583,0) -> 0 | K583: =H583+I583 -> 0 | M583: =H583-L583 -> 0 | N583: =IFERROR(M583/B583*10000,0) -> 0 | Q583: =O583+P583 -> 0 | R583: =IF(A583<HlpChangeDate,HlpSharePre,HlpSharePost) -> 0.03 | S583: =Q583*R583/(1-R583) -> 0 | U583: =S583-T583 -> 0 | V583: =Y583-O583*R583/(1-R583) -> 0 | W583: =Z583-P583*R583/(1-R583) -> 0 | X583: =S583+V583+W583 -> 0 | AA583: 0 | AB583: 23.218 | AC583: 24.74275 | AD583: =IFERROR(AA583/AC583,0) -> 0 | AE583: =K583-Q583-X583 -> 0 | AF583: =Q583-AA583 -> 0 | AG583: 23328960 | AH583: =IFERROR(AG583/Q583,0) -> 0 | AI583: 0 | AJ583: =IF(AI583>0,AprCoef/SQRT(AI583),0) -> 0 | AK583: =AI583*AJ583/365 -> 0 | AL583: =AD583 -> 0 | AM583: =AK583-AL583 -> 0 | AN583: =IF(A583>=Hip3LaunchDate,"YES","") | AO583: =IF(A583<Hip4LaunchDate,"pre-launch","live (zero-fee)") -> pre-launch
A584: 45645 | B584: 1.1512982e+10 | C584: 0 | D584: 564194362 | E584: =B584+C584 -> 1.1512982e+10 | F584: =E584+D584 -> 1.2077177e+10 | G584: =IFERROR(C584/E584,0) -> 0 | K584: =H584+I584 -> 0 | M584: =H584-L584 -> 0 | N584: =IFERROR(M584/B584*10000,0) -> 0 | Q584: =O584+P584 -> 0 | R584: =IF(A584<HlpChangeDate,HlpSharePre,HlpSharePost) -> 0.03 | S584: =Q584*R584/(1-R584) -> 0 | U584: =S584-T584 -> 0 | V584: =Y584-O584*R584/(1-R584) -> 0 | W584: =Z584-P584*R584/(1-R584) -> 0 | X584: =S584+V584+W584 -> 0 | AA584: 0 | AB584: 24.92 | AC584: 24.34625 | AD584: =IFERROR(AA584/AC584,0) -> 0 | AE584: =K584-Q584-X584 -> 0 | AF584: =Q584-AA584 -> 0 | AH584: =IFERROR(AG584/Q584,0) -> 0 | AI584: 0 | AJ584: =IF(AI584>0,AprCoef/SQRT(AI584),0) -> 0 | AK584: =AI584*AJ584/365 -> 0 | AL584: =AD584 -> 0 | AM584: =AK584-AL584 -> 0 | AN584: =IF(A584>=Hip3LaunchDate,"YES","") | AO584: =IF(A584<Hip4LaunchDate,"pre-launch","live (zero-fee)") -> pre-launch
A585: 45646 | B585: 9.8785211e+09 | C585: 0 | D585: 703781781 | E585: =B585+C585 -> 9.8785211e+09 | F585: =E585+D585 -> 1.0582303e+10 | G585: =IFERROR(C585/E585,0) -> 0 | K585: =H585+I585 -> 0 | M585: =H585-L585 -> 0 | N585: =IFERROR(M585/B585*10000,0) -> 0 | Q585: =O585+P585 -> 0 | R585: =IF(A585<HlpChangeDate,HlpSharePre,HlpSharePost) -> 0.03 | S585: =Q585*R585/(1-R585) -> 0 | U585: =S585-T585 -> 0 | V585: =Y585-O585*R585/(1-R585) -> 0 | W585: =Z585-P585*R585/(1-R585) -> 0 | X585: =S585+V585+W585 -> 0 | AA585: 0 | AB585: 29.749 | AC585: 27.3575 | AD585: =IFERROR(AA585/AC585,0) -> 0 | AE585: =K585-Q585-X585 -> 0 | AF585: =Q585-AA585 -> 0 | AH585: =IFERROR(AG585/Q585,0) -> 0 | AI585: 0 | AJ585: =IF(AI585>0,AprCoef/SQRT(AI585),0) -> 0 | AK585: =AI585*AJ585/365 -> 0 | AL585: =AD585 -> 0 | AM585: =AK585-AL585 -> 0 | AN585: =IF(A585>=Hip3LaunchDate,"YES","") | AO585: =IF(A585<Hip4LaunchDate,"pre-launch","live (zero-fee)") -> pre-launch
A586: 45647 | B586: 5.2030282e+09 | C586: 0 | D586: 527191283 | E586: =B586+C586 -> 5.2030282e+09 | F586: =E586+D586 -> 5.7302195e+09 | G586: =IFERROR(C586/E586,0) -> 0 | K586: =H586+I586 -> 0 | M586: =H586-L586 -> 0 | N586: =IFERROR(M586/B586*10000,0) -> 0 | Q586: =O586+P586 -> 0 | R586: =IF(A586<HlpChangeDate,HlpSharePre,HlpSharePost) -> 0.03 | S586: =Q586*R586/(1-R586) -> 0 | U586: =S586-T586 -> 0 | V586: =Y586-O586*R586/(1-R586) -> 0 | W586: =Z586-P586*R586/(1-R586) -> 0 | X586: =S586+V586+W586 -> 0 | AA586: 0 | AB586: 32.029 | AC586: 31.49625 | AD586: =IFERROR(AA586/AC586,0) -> 0 | AE586: =K586-Q586-X586 -> 0 | AF586: =Q586-AA586 -> 0 | AH586: =IFERROR(AG586/Q586,0) -> 0 | AI586: 0 | AJ586: =IF(AI586>0,AprCoef/SQRT(AI586),0) -> 0 | AK586: =AI586*AJ586/365 -> 0 | AL586: =AD586 -> 0 | AM586: =AK586-AL586 -> 0 | AN586: =IF(A586>=Hip3LaunchDate,"YES","") | AO586: =IF(A586<Hip4LaunchDate,"pre-launch","live (zero-fee)") -> pre-launch
A587: 45648 | B587: 4.6867317e+09 | C587: 0 | D587: 471634786 | E587: =B587+C587 -> 4.6867317e+09 | F587: =E587+D587 -> 5.1583665e+09 | G587: =IFERROR(C587/E587,0) -> 0 | K587: =H587+I587 -> 0 | M587: =H587-L587 -> 0 | N587: =IFERROR(M587/B587*10000,0) -> 0 | Q587: =O587+P587 -> 0 | R587: =IF(A587<HlpChangeDate,HlpSharePre,HlpSharePost) -> 0.03 | S587: =Q587*R587/(1-R587) -> 0 | U587: =S587-T587 -> 0 | V587: =Y587-O587*R587/(1-R587) -> 0 | W587: =Z587-P587*R587/(1-R587) -> 0 | X587: =S587+V587+W587 -> 0 | AA587: 0 | AB587: 28.459 | AC587: 30.707 | AD587: =IFERROR(AA587/AC587,0) -> 0 | AE587: =K587-Q587-X587 -> 0 | AF587: =Q587-AA587 -> 0 | AG587: 10580501 | AH587: =IFERROR(AG587/Q587,0) -> 0 | AI587: 0 | AJ587: =IF(AI587>0,AprCoef/SQRT(AI587),0) -> 0 | AK587: =AI587*AJ587/365 -> 0 | AL587: =AD587 -> 0 | AM587: =AK587-AL587 -> 0 | AN587: =IF(A587>=Hip3LaunchDate,"YES","") | AO587: =IF(A587<Hip4LaunchDate,"pre-launch","live (zero-fee)") -> pre-launch
A588: 45649 | B588: 6.1684635e+09 | C588: 0 | D588: 375034673 | E588: =B588+C588 -> 6.1684635e+09 | F588: =E588+D588 -> 6.5434982e+09 | G588: =IFERROR(C588/E588,0) -> 0 | H588: 1372264 | I588: 96254 | J588: 0 | K588: =H588+I588 -> 1468518 | M588: =H588-L588 -> 1372264 | N588: =IFERROR(M588/B588*10000,0) -> 2.2246448 | O588: 1331096 | P588: 93366 | Q588: =O588+P588 -> 1424462 | R588: =IF(A588<HlpChangeDate,HlpSharePre,HlpSharePost) -> 0.03 | S588: =Q588*R588/(1-R588) -> 44055.526 | T588: 0 | U588: =S588-T588 -> 44055.526 | V588: =Y588-O588*R588/(1-R588) -> 0.082474227 | W588: =Z588-P588*R588/(1-R588) -> 0.39175258 | X588: =S588+V588+W588 -> 44056 | Y588: 41168 | Z588: 2888 | AA588: 1424462 | AB588: 28.623 | AC588: 28.0155 | AD588: =IFERROR(AA588/AC588,0) -> 50845.496 | AE588: =K588-Q588-X588 -> 0 | AF588: =Q588-AA588 -> 0 | AG588: 1461253.2 | AH588: =IFERROR(AG588/Q588,0) -> 1.0258282 | AI588: 0 | AJ588: =IF(AI588>0,AprCoef/SQRT(AI588),0) -> 0 | AK588: =AI588*AJ588/365 -> 0 | AL588: =AD588 -> 50845.496 | AM588: =AK588-AL588 -> -50845.496 | AN588: =IF(A588>=Hip3LaunchDate,"YES","") | AO588: =IF(A588<Hip4LaunchDate,"pre-launch","live (zero-fee)") -> pre-launch
A589: 45650 | B589: 4.4015652e+09 | C589: 0 | D589: 319403848 | E589: =B589+C589 -> 4.4015652e+09 | F589: =E589+D589 -> 4.7209691e+09 | G589: =IFERROR(C589/E589,0) -> 0 | H589: 1296670 | I589: 47315 | J589: 40320 | K589: =H589+I589 -> 1343985 | M589: =H589-L589 -> 1296670 | N589: =IFERROR(M589/B589*10000,0) -> 2.9459293 | O589: 1257770 | P589: 45895 | Q589: =O589+P589 -> 1303665 | R589: =IF(A589<HlpChangeDate,HlpSharePre,HlpSharePost) -> 0.03 | S589: =Q589*R589/(1-R589) -> 40319.536 | T589: 40320 | U589: =S589-T589 -> -0.46391753 | V589: =Y589-O589*R589/(1-R589) -> -0.10309278 | W589: =Z589-P589*R589/(1-R589) -> -0.43298969 | X589: =S589+V589+W589 -> 40319 | Y589: 38900 | Z589: 1419 | AA589: 1303665 | AB589: 29.783 | AC589: 29.311 | AD589: =IFERROR(AA589/AC589,0) -> 44476.988 | AE589: =K589-Q589-X589 -> 1 | AF589: =Q589-AA589 -> 0 | AG589: 1368596.4 | AH589: =IFERROR(AG589/Q589,0) -> 1.0498068 | AI589: 0 | AJ589: =IF(AI589>0,AprCoef/SQRT(AI589),0) -> 0 | AK589: =AI589*AJ589/365 -> 0 | AL589: =AD589 -> 44476.988 | AM589: =AK589-AL589 -> -44476.988 | AN589: =IF(A589>=Hip3LaunchDate,"YES","") | AO589: =IF(A589<Hip4LaunchDate,"pre-launch","live (zero-fee)") -> pre-launch
A590: 45651 | B590: 3.0900267e+09 | C590: 0 | D590: 310480616 | E590: =B590+C590 -> 3.0900267e+09 | F590: =E590+D590 -> 3.4005073e+09 | G590: =IFERROR(C590/E590,0) -> 0 | H590: 1002334 | I590: 43561 | J590: 31377 | K590: =H590+I590 -> 1045895 | M590: =H590-L590 -> 1002334 | N590: =IFERROR(M590/B590*10000,0) -> 3.2437713 | O590: 972264 | P590: 42254 | Q590: =O590+P590 -> 1014518 | R590: =IF(A590<HlpChangeDate,HlpSharePre,HlpSharePost) -> 0.03 | S590: =Q590*R590/(1-R590) -> 31376.845 | T590: 31377 | U590: =S590-T590 -> -0.15463918 | V590: =Y590-O590*R590/(1-R590) -> -0.020618557 | W590: =Z590-P590*R590/(1-R590) -> 0.17525773 | X590: =S590+V590+W590 -> 31377 | Y590: 30070 | Z590: 1307 | AA590: 1014518 | AB590: 26.544 | AC590: 28.2515 | AD590: =IFERROR(AA590/AC590,0) -> 35910.235 | AE590: =K590-Q590-X590 -> 0 | AF590: =Q590-AA590 -> 0 | AG590: 1047430.9 | AH590: =IFERROR(AG590/Q590,0) -> 1.0324419 | AI590: 0 | AJ590: =IF(AI590>0,AprCoef/SQRT(AI590),0) -> 0 | AK590: =AI590*AJ590/365 -> 0 | AL590: =AD590 -> 35910.235 | AM590: =AK590-AL590 -> -35910.235 | AN590: =IF(A590>=Hip3LaunchDate,"YES","") | AO590: =IF(A590<Hip4LaunchDate,"pre-launch","live (zero-fee)") -> pre-launch
A591: 45652 | B591: 3.8974652e+09 | C591: 0 | D591: 214091088 | E591: =B591+C591 -> 3.8974652e+09 | F591: =E591+D591 -> 4.1115563e+09 | G591: =IFERROR(C591/E591,0) -> 0 | H591: 1269042 | I591: 44254 | J591: 39399 | K591: =H591+I591 -> 1313296 | M591: =H591-L591 -> 1269042 | N591: =IFERROR(M591/B591*10000,0) -> 3.2560701 | O591: 1230971 | P591: 42926 | Q591: =O591+P591 -> 1273897 | R591: =IF(A591<HlpChangeDate,HlpSharePre,HlpSharePost) -> 0.03 | S591: =Q591*R591/(1-R591) -> 39398.876 | T591: 39399 | U591: =S591-T591 -> -0.12371134 | V591: =Y591-O591*R591/(1-R591) -> -0.26804124 | W591: =Z591-P591*R591/(1-R591) -> 0.39175258 | X591: =S591+V591+W591 -> 39399 | Y591: 38071 | Z591: 1328 | AA591: 1273897 | AB591: 27.217 | AC591: 26.22475 | AD591: =IFERROR(AA591/AC591,0) -> 48576.135 | AE591: =K591-Q591-X591 -> 0 | AF591: =Q591-AA591 -> 0 | AG591: 1019238 | AH591: =IFERROR(AG591/Q591,0) -> 0.80009451 | AI591: 0 | AJ591: =IF(AI591>0,AprCoef/SQRT(AI591),0) -> 0 | AK591: =AI591*AJ591/365 -> 0 | AL591: =AD591 -> 48576.135 | AM591: =AK591-AL591 -> -48576.135 | AN591: =IF(A591>=Hip3LaunchDate,"YES","") | AO591: =IF(A591<Hip4LaunchDate,"pre-launch","live (zero-fee)") -> pre-launch
A592: 45653 | B592: 3.8894731e+09 | C592: 0 | D592: 216391282 | E592: =B592+C592 -> 3.8894731e+09 | F592: =E592+D592 -> 4.1058644e+09 | G592: =IFERROR(C592/E592,0) -> 0 | H592: 1268921 | I592: 28523 | J592: 38923 | K592: =H592+I592 -> 1297444 | M592: =H592-L592 -> 1268921 | N592: =IFERROR(M592/B592*10000,0) -> 3.2624496 | O592: 1230853 | P592: 27667 | Q592: =O592+P592 -> 1258520 | R592: =IF(A592<HlpChangeDate,HlpSharePre,HlpSharePost) -> 0.03 | S592: =Q592*R592/(1-R592) -> 38923.299 | T592: 38923 | U592: =S592-T592 -> 0.29896907 | V592: =Y592-O592*R592/(1-R592) -> 0.3814433 | W592: =Z592-P592*R592/(1-R592) -> 0.31958763 | X592: =S592+V592+W592 -> 38924 | Y592: 38068 | Z592: 856 | AA592: 1258520 | AB592: 27.111 | AC592: 27.21625 | AD592: =IFERROR(AA592/AC592,0) -> 46241.492 | AE592: =K592-Q592-X592 -> 0 | AF592: =Q592-AA592 -> 0 | AG592: 1633333.4 | AH592: =IFERROR(AG592/Q592,0) -> 1.2978208 | AI592: 0 | AJ592: =IF(AI592>0,AprCoef/SQRT(AI592),0) -> 0 | AK592: =AI592*AJ592/365 -> 0 | AL592: =AD592 -> 46241.492 | AM592: =AK592-AL592 -> -46241.492 | AN592: =IF(A592>=Hip3LaunchDate,"YES","") | AO592: =IF(A592<Hip4LaunchDate,"pre-launch","live (zero-fee)") -> pre-launch
A593: 45654 | B593: 2.0771914e+09 | C593: 0 | D593: 212391739 | E593: =B593+C593 -> 2.0771914e+09 | F593: =E593+D593 -> 2.2895831e+09 | G593: =IFERROR(C593/E593,0) -> 0 | H593: 950246 | I593: 28430 | J593: 29360 | K593: =H593+I593 -> 978676 | M593: =H593-L593 -> 950246 | N593: =IFERROR(M593/B593*10000,0) -> 4.5746676 | O593: 921738 | P593: 27577 | Q593: =O593+P593 -> 949315 | R593: =IF(A593<HlpChangeDate,HlpSharePre,HlpSharePost) -> 0.03 | S593: =Q593*R593/(1-R593) -> 29360.258 | T593: 29360 | U593: =S593-T593 -> 0.25773196 | V593: =Y593-O593*R593/(1-R593) -> -0.36082474 | W593: =Z593-P593*R593/(1-R593) -> 0.10309278 | X593: =S593+V593+W593 -> 29360 | Y593: 28507 | Z593: 853 | AA593: 949315 | AB593: 29.265 | AC593: 27.85575 | AD593: =IFERROR(AA593/AC593,0) -> 34079.678 | AE593: =K593-Q593-X593 -> 1 | AF593: =Q593-AA593 -> 0 | AG593: 978675.75 | AH593: =IFERROR(AG593/Q593,0) -> 1.0309284 | AI593: 0 | AJ593: =IF(AI593>0,AprCoef/SQRT(AI593),0) -> 0 | AK593: =AI593*AJ593/365 -> 0 | AL593: =AD593 -> 34079.678 | AM593: =AK593-AL593 -> -34079.678 | AN593: =IF(A593>=Hip3LaunchDate,"YES","") | AO593: =IF(A593<Hip4LaunchDate,"pre-launch","live (zero-fee)") -> pre-launch
A594: 45655 | B594: 1.9659316e+09 | C594: 0 | D594: 342862746 | E594: =B594+C594 -> 1.9659316e+09 | F594: =E594+D594 -> 2.3087943e+09 | G594: =IFERROR(C594/E594,0) -> 0 | H594: 454244 | I594: 31496 | J594: 14412 | K594: =H594+I594 -> 485740 | M594: =H594-L594 -> 454244 | N594: =IFERROR(M594/B594*10000,0) -> 2.3105789 | O594: 440616 | P594: 30551 | Q594: =O594+P594 -> 471167 | R594: =IF(A594<HlpChangeDate,HlpSharePre,HlpSharePost) -> 0.03 | S594: =Q594*R594/(1-R594) -> 14572.175 | T594: 14412 | U594: =S594-T594 -> 160.17526 | V594: =Y594-O594*R594/(1-R594) -> -0.29896907 | W594: =Z594-P594*R594/(1-R594) -> 0.12371134 | X594: =S594+V594+W594 -> 14572 | Y594: 13627 | Z594: 945 | AA594: 471167 | AB594: 27.446 | AC594: 28.20625 | AD594: =IFERROR(AA594/AC594,0) -> 16704.347 | AE594: =K594-Q594-X594 -> 1 | AF594: =Q594-AA594 -> 0 | AG594: 480409.76 | AH594: =IFERROR(AG594/Q594,0) -> 1.0196167 | AI594: 0 | AJ594: =IF(AI594>0,AprCoef/SQRT(AI594),0) -> 0 | AK594: =AI594*AJ594/365 -> 0 | AL594: =AD594 -> 16704.347 | AM594: =AK594-AL594 -> -16704.347 | AN594: =IF(A594>=Hip3LaunchDate,"YES","") | AO594: =IF(A594<Hip4LaunchDate,"pre-launch","live (zero-fee)") -> pre-launch
A595: 45656 | B595: 4.6971711e+09 | C595: 0 | D595: 267028183 | E595: =B595+C595 -> 4.6971711e+09 | F595: =E595+D595 -> 4.9641993e+09 | G595: =IFERROR(C595/E595,0) -> 0 | H595: 1483664 | I595: 49113 | J595: 45905 | K595: =H595+I595 -> 1532777 | M595: =H595-L595 -> 1483664 | N595: =IFERROR(M595/B595*10000,0) -> 3.1586331 | O595: 1439154 | P595: 47640 | Q595: =O595+P595 -> 1486794 | R595: =IF(A595<HlpChangeDate,HlpSharePre,HlpSharePost) -> 0.03 | S595: =Q595*R595/(1-R595) -> 45983.32 | T595: 45905 | U595: =S595-T595 -> 78.319588 | V595: =Y595-O595*R595/(1-R595) -> 0.082474227 | W595: =Z595-P595*R595/(1-R595) -> -0.40206186 | X595: =S595+V595+W595 -> 45983 | Y595: 44510 | Z595: 1473 | AA595: 1486794 | AB595: 26.953 | AC595: 27.52475 | AD595: =IFERROR(AA595/AC595,0) -> 54016.621 | AE595: =K595-Q595-X595 -> 0 | AF595: =Q595-AA595 -> 0 | AG595: 1530159.4 | AH595: =IFERROR(AG595/Q595,0) -> 1.0291671 | AI595: 301000000 | AJ595: =IF(AI595>0,AprCoef/SQRT(AI595),0) -> 0.027320906 | AK595: =AI595*AJ595/365 -> 22530.391 | AL595: =AD595 -> 54016.621 | AM595: =AK595-AL595 -> -31486.231 | AN595: =IF(A595>=Hip3LaunchDate,"YES","") | AO595: =IF(A595<Hip4LaunchDate,"pre-launch","live (zero-fee)") -> pre-launch
A596: 45657 | B596: 3.4505145e+09 | C596: 0 | D596: 225503235 | E596: =B596+C596 -> 3.4505145e+09 | F596: =E596+D596 -> 3.6760177e+09 | G596: =IFERROR(C596/E596,0) -> 0 | H596: 1326087 | I596: 42962 | J596: 41146 | K596: =H596+I596 -> 1369049 | M596: =H596-L596 -> 1326087 | N596: =IFERROR(M596/B596*10000,0) -> 3.8431573 | O596: 1286304 | P596: 41673 | Q596: =O596+P596 -> 1327977 | R596: =IF(A596<HlpChangeDate,HlpSharePre,HlpSharePost) -> 0.03 | S596: =Q596*R596/(1-R596) -> 41071.454 | T596: 41146 | U596: =S596-T596 -> -74.546392 | V596: =Y596-O596*R596/(1-R596) -> 0.40206186 | W596: =Z596-P596*R596/(1-R596) -> 0.1443299 | X596: =S596+V596+W596 -> 41072 | Y596: 39783 | Z596: 1289 | AA596: 1327977 | AB596: 24.007 | AC596: 25.2725 | AD596: =IFERROR(AA596/AC596,0) -> 52546.325 | AE596: =K596-Q596-X596 -> 0 | AF596: =Q596-AA596 -> 0 | AG596: 1371530.6 | AH596: =IFERROR(AG596/Q596,0) -> 1.032797 | AI596: 3.0171698e+08 | AJ596: =IF(AI596>0,AprCoef/SQRT(AI596),0) -> 0.027288425 | AK596: =AI596*AJ596/365 -> 22557.209 | AL596: =AD596 -> 52546.325 | AM596: =AK596-AL596 -> -29989.117 | AN596: =IF(A596>=Hip3LaunchDate,"YES","") | AO596: =IF(A596<Hip4LaunchDate,"pre-launch","live (zero-fee)") -> pre-launch
A597: 45658 | B597: 2.1572568e+09 | C597: 0 | D597: 256438336 | E597: =B597+C597 -> 2.1572568e+09 | F597: =E597+D597 -> 2.4136952e+09 | G597: =IFERROR(C597/E597,0) -> 0 | H597: 483299 | I597: 30141 | J597: 15396 | K597: =H597+I597 -> 513440 | M597: =H597-L597 -> 483299 | N597: =IFERROR(M597/B597*10000,0) -> 2.2403406 | O597: 468800 | P597: 29237 | Q597: =O597+P597 -> 498037 | R597: =IF(A597<HlpChangeDate,HlpSharePre,HlpSharePost) -> 0.03 | S597: =Q597*R597/(1-R597) -> 15403.206 | T597: 15396 | U597: =S597-T597 -> 7.2061856 | V597: =Y597-O597*R597/(1-R597) -> 0.030927835 | W597: =Z597-P597*R597/(1-R597) -> -0.2371134 | X597: =S597+V597+W597 -> 15403 | Y597: 14499 | Z597: 904 | AA597: 498037 | AB597: 26.315 | AC597: 25.052 | AD597: =IFERROR(AA597/AC597,0) -> 19880.129 | AE597: =K597-Q597-X597 -> 0 | AF597: =Q597-AA597 -> 0 | AG597: 513195.56 | AH597: =IFERROR(AG597/Q597,0) -> 1.0304366 | AI597: 3.0243396e+08 | AJ597: =IF(AI597>0,AprCoef/SQRT(AI597),0) -> 0.027256059 | AK597: =AI597*AJ597/365 -> 22583.994 | AL597: =AD597 -> 19880.129 | AM597: =AK597-AL597 -> 2703.865 | AN597: =IF(A597>=Hip3LaunchDate,"YES","") | AO597: =IF(A597<Hip4LaunchDate,"pre-launch","live (zero-fee)") -> pre-launch
A598: 45659 | B598: 3.6458162e+09 | C598: 0 | D598: 267239456 | E598: =B598+C598 -> 3.6458162e+09 | F598: =E598+D598 -> 3.9130556e+09 | G598: =IFERROR(C598/E598,0) -> 0 | H598: 1267839 | I598: 41666 | J598: 39456 | K598: =H598+I598 -> 1309505 | M598: =H598-L598 -> 1267839 | N598: =IFERROR(M598/B598*10000,0) -> 3.4775176 | O598: 1229804 | P598: 40416 | Q598: =O598+P598 -> 1270220 | R598: =IF(A598<HlpChangeDate,HlpSharePre,HlpSharePost) -> 0.03 | S598: =Q598*R598/(1-R598) -> 39285.155 | T598: 39456 | U598: =S598-T598 -> -170.84536 | V598: =Y598-O598*R598/(1-R598) -> -0.17525773 | W598: =Z598-P598*R598/(1-R598) -> 0.020618557 | X598: =S598+V598+W598 -> 39285 | Y598: 38035 | Z598: 1250 | AA598: 1270220 | AB598: 23.163 | AC598: 24.7135 | AD598: =IFERROR(AA598/AC598,0) -> 51397.819 | AE598: =K598-Q598-X598 -> 0 | AF598: =Q598-AA598 -> 0 | AG598: 1315214.8 | AH598: =IFERROR(AG598/Q598,0) -> 1.0354228 | AI598: 3.0315094e+08 | AJ598: =IF(AI598>0,AprCoef/SQRT(AI598),0) -> 0.027223808 | AK598: =AI598*AJ598/365 -> 22610.748 | AL598: =AD598 -> 51397.819 | AM598: =AK598-AL598 -> -28787.071 | AN598: =IF(A598>=Hip3LaunchDate,"YES","") | AO598: =IF(A598<Hip4LaunchDate,"pre-launch","live (zero-fee)") -> pre-launch
A599: 45660 | B599: 3.5731603e+09 | C599: 0 | D599: 176550030 | E599: =B599+C599 -> 3.5731603e+09 | F599: =E599+D599 -> 3.7497103e+09 | G599: =IFERROR(C599/E599,0) -> 0 | H599: 1374850 | I599: 37005 | J599: 42237 | K599: =H599+I599 -> 1411855 | M599: =H599-L599 -> 1374850 | N599: =IFERROR(M599/B599*10000,0) -> 3.8477143 | O599: 1333605 | P599: 35895 | Q599: =O599+P599 -> 1369500 | R599: =IF(A599<HlpChangeDate,HlpSharePre,HlpSharePost) -> 0.03 | S599: =Q599*R599/(1-R599) -> 42355.67 | T599: 42237 | U599: =S599-T599 -> 118.6701 | V599: =Y599-O599*R599/(1-R599) -> 0.48453608 | W599: =Z599-P599*R599/(1-R599) -> -0.15463918 | X599: =S599+V599+W599 -> 42356 | Y599: 41246 | Z599: 1110 | AA599: 1369500 | AB599: 24.442 | AC599: 23.553 | AD599: =IFERROR(AA599/AC599,0) -> 58145.459 | AE599: =K599-Q599-X599 -> -1 | AF599: =Q599-AA599 -> 0 | AG599: 1407906.3 | AH599: =IFERROR(AG599/Q599,0) -> 1.0280441 | AI599: 3.0386792e+08 | AJ599: =IF(AI599>0,AprCoef/SQRT(AI599),0) -> 0.027191672 | AK599: =AI599*AJ599/365 -> 22637.471 | AL599: =AD599 -> 58145.459 | AM599: =AK599-AL599 -> -35507.988 | AN599: =IF(A599>=Hip3LaunchDate,"YES","") | AO599: =IF(A599<Hip4LaunchDate,"pre-launch","live (zero-fee)") -> pre-launch
... A607: 45668 | B607: 1.9752201e+09 | C607: 0 | D607: 104729289 | E607: =B607+C607 -> 1.9752201e+09 | F607: =E607+D607 -> 2.0799494e+09 | G607: =IFERROR(C607/E607,0) -> 0 | H607: 457618 | I607: 14961 | J607: 14177 | K607: =H607+I607 -> 472579 | M607: =H607-L607 -> 457618 | N607: =IFERROR(M607/B607*10000,0) -> 2.316795 | O607: 443890 | P607: 14512 | Q607: =O607+P607 -> 458402 | R607: =IF(A607<HlpChangeDate,HlpSharePre,HlpSharePost) -> 0.03 | S607: =Q607*R607/(1-R607) -> 14177.381 | T607: 14177 | U607: =S607-T607 -> 0.3814433 | V607: =Y607-O607*R607/(1-R607) -> 0.44329897 | W607: =Z607-P607*R607/(1-R607) -> 0.17525773 | X607: =S607+V607+W607 -> 14178 | Y607: 13729 | Z607: 449 | AA607: 458402 | AB607: 20.884 | AC607: 20.54925 | AD607: =IFERROR(AA607/AC607,0) -> 22307.481 | AE607: =K607-Q607-X607 -> -1 | AF607: =Q607-AA607 -> 0 | AG607: 472579.05 | AH607: =IFERROR(AG607/Q607,0) -> 1.0309271 | AI607: 3.0960377e+08 | AJ607: =IF(AI607>0,AprCoef/SQRT(AI607),0) -> 0.026938612 | AK607: =AI607*AJ607/365 -> 22850.126 | AL607: =AD607 -> 22307.481 | AM607: =AK607-AL607 -> 542.64523 | AN607: =IF(A607>=Hip3LaunchDate,"YES","") | AO607: =IF(A607<Hip4LaunchDate,"pre-launch","live (zero-fee)") -> pre-launch
A608: 45669 | B608: 1.8688233e+09 | C608: 0 | D608: 230154418 | E608: =B608+C608 -> 1.8688233e+09 | F608: =E608+D608 -> 2.0989777e+09 | G608: =IFERROR(C608/E608,0) -> 0 | K608: =H608+I608 -> 0 | M608: =H608-L608 -> 0 | N608: =IFERROR(M608/B608*10000,0) -> 0 | Q608: =O608+P608 -> 0 | R608: =IF(A608<HlpChangeDate,HlpSharePre,HlpSharePost) -> 0.03 | S608: =Q608*R608/(1-R608) -> 0 | U608: =S608-T608 -> 0 | V608: =Y608-O608*R608/(1-R608) -> 0 | W608: =Z608-P608*R608/(1-R608) -> 0 | X608: =S608+V608+W608 -> 0 | AA608: 0 | AB608: 21.117 | AC608: 20.9875 | AD608: =IFERROR(AA608/AC608,0) -> 0 | AE608: =K608-Q608-X608 -> 0 | AF608: =Q608-AA608 -> 0 | AG608: 479173.59 | AH608: =IFERROR(AG608/Q608,0) -> 0 | AI608: 3.1032075e+08 | AJ608: =IF(AI608>0,AprCoef/SQRT(AI608),0) -> 0.026907474 | AK608: =AI608*AJ608/365 -> 22876.569 | AL608: =AD608 -> 0 | AM608: =AK608-AL608 -> 22876.569 | AN608: =IF(A608>=Hip3LaunchDate,"YES","") | AO608: =IF(A608<Hip4LaunchDate,"pre-launch","live (zero-fee)") -> pre-launch
A609: 45670 | B609: 7.6148894e+09 | C609: 0 | D609: 195123318 | E609: =B609+C609 -> 7.6148894e+09 | F609: =E609+D609 -> 7.8100127e+09 | G609: =IFERROR(C609/E609,0) -> 0 | K609: =H609+I609 -> 0 | M609: =H609-L609 -> 0 | N609: =IFERROR(M609/B609*10000,0) -> 0 | Q609: =O609+P609 -> 0 | R609: =IF(A609<HlpChangeDate,HlpSharePre,HlpSharePost) -> 0.03 | S609: =Q609*R609/(1-R609) -> 0 | U609: =S609-T609 -> 0 | V609: =Y609-O609*R609/(1-R609) -> 0 | W609: =Z609-P609*R609/(1-R609) -> 0 | X609: =S609+V609+W609 -> 0 | AA609: 0 | AB609: 21.629 | AC609: 21.24875 | AD609: =IFERROR(AA609/AC609,0) -> 0 | AE609: =K609-Q609-X609 -> 0 | AF609: =Q609-AA609 -> 0 | AG609: 2330484.8 | AH609: =IFERROR(AG609/Q609,0) -> 0 | AI609: 3.1103774e+08 | AJ609: =IF(AI609>0,AprCoef/SQRT(AI609),0) -> 0.026876444 | AK609: =AI609*AJ609/365 -> 22902.981 | AL609: =AD609 -> 0 | AM609: =AK609-AL609 -> 22902.981 | AN609: =IF(A609>=Hip3LaunchDate,"YES","") | AO609: =IF(A609<Hip4LaunchDate,"pre-launch","live (zero-fee)") -> pre-launch
A610: 45671 | B610: 4.1645346e+09 | C610: 0 | D610: 186174573 | E610: =B610+C610 -> 4.1645346e+09 | F610: =E610+D610 -> 4.3507092e+09 | G610: =IFERROR(C610/E610,0) -> 0 | H610: 1243879 | I610: 24324 | J610: 38194 | K610: =H610+I610 -> 1268203 | M610: =H610-L610 -> 1243879 | N610: =IFERROR(M610/B610*10000,0) -> 2.9868379 | O610: 1206563 | P610: 23594 | Q610: =O610+P610 -> 1230157 | R610: =IF(A610<HlpChangeDate,HlpSharePre,HlpSharePost) -> 0.03 | S610: =Q610*R610/(1-R610) -> 38046.093 | T610: 38194 | U610: =S610-T610 -> -147.90722 | V610: =Y610-O610*R610/(1-R610) -> -0.3814433 | W610: =Z610-P610*R610/(1-R610) -> 0.28865979 | X610: =S610+V610+W610 -> 38046 | Y610: 37316 | Z610: 730 | AA610: 1230157 | AB610: 22.999 | AC610: 22.35025 | AD610: =IFERROR(AA610/AC610,0) -> 55039.966 | AE610: =K610-Q610-X610 -> 0 | AF610: =Q610-AA610 -> 0 | AG610: 1273120.8 | AH610: =IFERROR(AG610/Q610,0) -> 1.0349255 | AI610: 3.1175472e+08 | AJ610: =IF(AI610>0,AprCoef/SQRT(AI610),0) -> 0.02684552 | AK610: =AI610*AJ610/365 -> 22929.363 | AL610: =AD610 -> 55039.966 | AM610: =AK610-AL610 -> -32110.603 | AN610: =IF(A610>=Hip3LaunchDate,"YES","") | AO610: =IF(A610<Hip4LaunchDate,"pre-launch","live (zero-fee)") -> pre-launch
A611: 45672 | B611: 5.3154076e+09 | C611: 0 | D611: 125668891 | E611: =B611+C611 -> 5.3154076e+09 | F611: =E611+D611 -> 5.4410765e+09 | G611: =IFERROR(C611/E611,0) -> 0 | H611: 1245669 | I611: 23915 | J611: 37801 | K611: =H611+I611 -> 1269584 | M611: =H611-L611 -> 1245669 | N611: =IFERROR(M611/B611*10000,0) -> 2.3435061 | O611: 1208299 | P611: 23198 | Q611: =O611+P611 -> 1231497 | R611: =IF(A611<HlpChangeDate,HlpSharePre,HlpSharePost) -> 0.03 | S611: =Q611*R611/(1-R611) -> 38087.536 | T611: 37801 | U611: =S611-T611 -> 286.53608 | V611: =Y611-O611*R611/(1-R611) -> -0.072164948 | W611: =Z611-P611*R611/(1-R611) -> -0.46391753 | X611: =S611+V611+W611 -> 38087 | Y611: 37370 | Z611: 717 | AA611: 1231497 | AB611: 24.376 | AC611: 23.4695 | AD611: =IFERROR(AA611/AC611,0) -> 52472.23 | AE611: =K611-Q611-X611 -> 0 | AF611: =Q611-AA611 -> 0 | AG611: 1260041.5 | AH611: =IFERROR(AG611/Q611,0) -> 1.0231787 | AI611: 3.124717e+08 | AJ611: =IF(AI611>0,AprCoef/SQRT(AI611),0) -> 0.026814703 | AK611: =AI611*AJ611/365 -> 22955.715 | AL611: =AD611 -> 52472.23 | AM611: =AK611-AL611 -> -29516.515 | AN611: =IF(A611>=Hip3LaunchDate,"YES","") | AO611: =IF(A611<Hip4LaunchDate,"pre-launch","live (zero-fee)") -> pre-launch
A612: 45673 | B612: 5.7136112e+09 | C612: 0 | D612: 148144621 | E612: =B612+C612 -> 5.7136112e+09 | F612: =E612+D612 -> 5.8617559e+09 | G612: =IFERROR(C612/E612,0) -> 0 | H612: 1677266 | I612: 18602 | J612: 51162 | K612: =H612+I612 -> 1695868 | M612: =H612-L612 -> 1677266 | N612: =IFERROR(M612/B612*10000,0) -> 2.935562 | O612: 1626948 | P612: 18044 | Q612: =O612+P612 -> 1644992 | R612: =IF(A612<HlpChangeDate,HlpSharePre,HlpSharePost) -> 0.03 | S612: =Q612*R612/(1-R612) -> 50876.041 | T612: 51162 | U612: =S612-T612 -> -285.95876 | V612: =Y612-O612*R612/(1-R612) -> 0.020618557 | W612: =Z612-P612*R612/(1-R612) -> -0.06185567 | X612: =S612+V612+W612 -> 50876 | Y612: 50318 | Z612: 558 | AA612: 1644992 | AB612: 23.469 | AC612: 23.84675 | AD612: =IFERROR(AA612/AC612,0) -> 68981.811 | AE612: =K612-Q612-X612 -> 0 | AF612: =Q612-AA612 -> 0 | AG612: 1705410 | AH612: =IFERROR(AG612/Q612,0) -> 1.0367285 | AI612: 3.1318868e+08 | AJ612: =IF(AI612>0,AprCoef/SQRT(AI612),0) -> 0.026783992 | AK612: =AI612*AJ612/365 -> 22982.036 | AL612: =AD612 -> 68981.811 | AM612: =AK612-AL612 -> -45999.775 | AN612: =IF(A612>=Hip3LaunchDate,"YES","") | AO612: =IF(A612<Hip4LaunchDate,"pre-launch","live (zero-fee)") -> pre-launch
A613: 45674 | B613: 5.4612772e+09 | C613: 0 | D613: 342126938 | E613: =B613+C613 -> 5.4612772e+09 | F613: =E613+D613 -> 5.8034042e+09 | G613: =IFERROR(C613/E613,0) -> 0 | H613: 1677802 | I613: 20485 | J613: 50949 | K613: =H613+I613 -> 1698287 | M613: =H613-L613 -> 1677802 | N613: =IFERROR(M613/B613*10000,0) -> 3.0721788 | O613: 1627468 | P613: 19870 | Q613: =O613+P613 -> 1647338 | R613: =IF(A613<HlpChangeDate,HlpSharePre,HlpSharePost) -> 0.03 | S613: =Q613*R613/(1-R613) -> 50948.598 | T613: 50949 | U613: =S613-T613 -> -0.40206186 | V613: =Y613-O613*R613/(1-R613) -> -0.06185567 | W613: =Z613-P613*R613/(1-R613) -> 0.46391753 | X613: =S613+V613+W613 -> 50949 | Y613: 50334 | Z613: 615 | AA613: 1647338 | AB613: 23.09 | AC613: 23.36875 | AD613: =IFERROR(AA613/AC613,0) -> 70493.201 | AE613: =K613-Q613-X613 -> 0 | AF613: =Q613-AA613 -> 0 | AG613: 1698286.7 | AH613: =IFERROR(AG613/Q613,0) -> 1.0309279 | AI613: 3.1390566e+08 | AJ613: =IF(AI613>0,AprCoef/SQRT(AI613),0) -> 0.026753387 | AK613: =AI613*AJ613/365 -> 23008.328 | AL613: =AD613 -> 70493.201 | AM613: =AK613-AL613 -> -47484.874 | AN613: =IF(A613>=Hip3LaunchDate,"YES","") | AO613: =IF(A613<Hip4LaunchDate,"pre-launch","live (zero-fee)") -> pre-launch
A614: 45675 | B614: 9.6789601e+09 | C614: 0 | D614: 452915269 | E614: =B614+C614 -> 9.6789601e+09 | F614: =E614+D614 -> 1.0131875e+10 | G614: =IFERROR(C614/E614,0) -> 0 | H614: 2787442 | I614: 52413 | J614: 84875 | K614: =H614+I614 -> 2839855 | M614: =H614-L614 -> 2787442 | N614: =IFERROR(M614/B614*10000,0) -> 2.8798982 | O614: 2703819 | P614: 50841 | Q614: =O614+P614 -> 2754660 | R614: =IF(A614<HlpChangeDate,HlpSharePre,HlpSharePost) -> 0.03 | S614: =Q614*R614/(1-R614) -> 85195.67 | T614: 84875 | U614: =S614-T614 -> 320.6701 | V614: =Y614-O614*R614/(1-R614) -> -0.26804124 | W614: =Z614-P614*R614/(1-R614) -> -0.40206186 | X614: =S614+V614+W614 -> 85195 | Y614: 83623 | Z614: 1572 | AA614: 2754660 | AB614: 21.937 | AC614: 21.7835 | AD614: =IFERROR(AA614/AC614,0) -> 126456.26 | AE614: =K614-Q614-X614 -> 0 | AF614: =Q614-AA614 -> 0 | AG614: 2829175.9 | AH614: =IFERROR(AG614/Q614,0) -> 1.0270509 | AI614: 3.1462264e+08 | AJ614: =IF(AI614>0,AprCoef/SQRT(AI614),0) -> 0.026722886 | AK614: =AI614*AJ614/365 -> 23034.589 | AL614: =AD614 -> 126456.26 | AM614: =AK614-AL614 -> -103421.67 | AN614: =IF(A614>=Hip3LaunchDate,"YES","") | AO614: =IF(A614<Hip4LaunchDate,"pre-launch","live (zero-fee)") -> pre-launch
A615: 45676 | B615: 1.775022e+10 | C615: 0 | D615: 234451715 | E615: =B615+C615 -> 1.775022e+10 | F615: =E615+D615 -> 1.7984671e+10 | G615: =IFERROR(C615/E615,0) -> 0 | H615: 4250373 | I615: 61521 | J615: 128368 | K615: =H615+I615 -> 4311894 | M615: =H615-L615 -> 4250373 | N615: =IFERROR(M615/B615*10000,0) -> 2.3945467 | O615: 4122862 | P615: 59675 | Q615: =O615+P615 -> 4182537 | R615: =IF(A615<HlpChangeDate,HlpSharePre,HlpSharePost) -> 0.03 | S615: =Q615*R615/(1-R615) -> 129356.81 | T615: 128368 | U615: =S615-T615 -> 988.81443 | V615: =Y615-O615*R615/(1-R615) -> -0.19587629 | W615: =Z615-P615*R615/(1-R615) -> 0.3814433 | X615: =S615+V615+W615 -> 129357 | Y615: 127511 | Z615: 1846 | AA615: 4182537 | AB615: 20.198 | AC615: 21.25875 | AD615: =IFERROR(AA615/AC615,0) -> 196744.26 | AE615: =K615-Q615-X615 -> 0 | AF615: =Q615-AA615 -> 0 | AG615: 4278948 | AH615: =IFERROR(AG615/Q615,0) -> 1.0230508 | AI615: 3.1533962e+08 | AJ615: =IF(AI615>0,AprCoef/SQRT(AI615),0) -> 0.026692489 | AK615: =AI615*AJ615/365 -> 23060.82 | AL615: =AD615 -> 196744.26 | AM615: =AK615-AL615 -> -173683.44 | AN615: =IF(A615>=Hip3LaunchDate,"YES","") | AO615: =IF(A615<Hip4LaunchDate,"pre-launch","live (zero-fee)") -> pre-launch
A616: 45677 | B616: 1.6339005e+10 | C616: 0 | D616: 255573062 | E616: =B616+C616 -> 1.6339005e+10 | F616: =E616+D616 -> 1.6594578e+10 | G616: =IFERROR(C616/E616,0) -> 0 | H616: 4044525 | I616: 34279 | J616: 122933 | K616: =H616+I616 -> 4078804 | M616: =H616-L616 -> 4044525 | N616: =IFERROR(M616/B616*10000,0) -> 2.4753802 | O616: 3923189 | P616: 33251 | Q616: =O616+P616 -> 3956440 | R616: =IF(A616<HlpChangeDate,HlpSharePre,HlpSharePost) -> 0.03 | S616: =Q616*R616/(1-R616) -> 122364.12 | T616: 122933 | U616: =S616-T616 -> -568.87629 | V616: =Y616-O616*R616/(1-R616) -> 0.25773196 | W616: =Z616-P616*R616/(1-R616) -> -0.3814433 | X616: =S616+V616+W616 -> 122364 | Y616: 121336 | Z616: 1028 | AA616: 3956440 | AB616: 20.547 | AC616: 20.6965 | AD616: =IFERROR(AA616/AC616,0) -> 191164.69 | AE616: =K616-Q616-X616 -> 0 | AF616: =Q616-AA616 -> 0 | AG616: 4097777 | AH616: =IFERROR(AG616/Q616,0) -> 1.0357233 | AI616: 3.160566e+08 | AJ616: =IF(AI616>0,AprCoef/SQRT(AI616),0) -> 0.026662195 | AK616: =AI616*AJ616/365 -> 23087.022 | AL616: =AD616 -> 191164.69 | AM616: =AK616-AL616 -> -168077.67 | AN616: =IF(A616>=Hip3LaunchDate,"YES","") | AO616: =IF(A616<Hip4LaunchDate,"pre-launch","live (zero-fee)") -> pre-launch
A617: 45678 | B617: 8.3419449e+09 | C617: 0 | D617: 217426990 | E617: =B617+C617 -> 8.3419449e+09 | F617: =E617+D617 -> 8.5593719e+09 | G617: =IFERROR(C617/E617,0) -> 0 | H617: 2031876 | I617: 34069 | J617: 62718 | K617: =H617+I617 -> 2065945 | M617: =H617-L617 -> 2031876 | N617: =IFERROR(M617/B617*10000,0) -> 2.4357341 | O617: 1970920 | P617: 33047 | Q617: =O617+P617 -> 2003967 | R617: =IF(A617<HlpChangeDate,HlpSharePre,HlpSharePost) -> 0.03 | S617: =Q617*R617/(1-R617) -> 61978.361 | T617: 62718 | U617: =S617-T617 -> -739.63918 | V617: =Y617-O617*R617/(1-R617) -> -0.28865979 | W617: =Z617-P617*R617/(1-R617) -> -0.072164948 | X617: =S617+V617+W617 -> 61978 | Y617: 60956 | Z617: 1022 | AA617: 2003967 | AB617: 23.183 | AC617: 22.1905 | AD617: =IFERROR(AA617/AC617,0) -> 90307.429 | AE617: =K617-Q617-X617 -> 0 | AF617: =Q617-AA617 -> 0 | AG617: 2090596.9 | AH617: =IFERROR(AG617/Q617,0) -> 1.0432292 | AI617: 3.1677358e+08 | AJ617: =IF(AI617>0,AprCoef/SQRT(AI617),0) -> 0.026632005 | AK617: =AI617*AJ617/365 -> 23113.194 | AL617: =AD617 -> 90307.429 | AM617: =AK617-AL617 -> -67194.235 | AN617: =IF(A617>=Hip3LaunchDate,"YES","") | AO617: =IF(A617<Hip4LaunchDate,"pre-launch","live (zero-fee)") -> pre-launch
A618: 45679 | B618: 5.2815512e+09 | C618: 0 | D618: 268190024 | E618: =B618+C618 -> 5.2815512e+09 | F618: =E618+D618 -> 5.5497412e+09 | G618: =IFERROR(C618/E618,0) -> 0 | H618: 1405006 | I618: 30418 | J618: 43063 | K618: =H618+I618 -> 1435424 | M618: =H618-L618 -> 1405006 | N618: =IFERROR(M618/B618*10000,0) -> 2.6602147 | O618: 1362855 | P618: 29505 | Q618: =O618+P618 -> 1392360 | R618: =IF(A618<HlpChangeDate,HlpSharePre,HlpSharePost) -> 0.03 | S618: =Q618*R618/(1-R618) -> 43062.68 | T618: 43063 | U618: =S618-T618 -> -0.31958763 | V618: =Y618-O618*R618/(1-R618) -> -0.15463918 | W618: =Z618-P618*R618/(1-R618) -> 0.4742268 | X618: =S618+V618+W618 -> 43063 | Y618: 42150 | Z618: 913 | AA618: 1392360 | AB618: 24.3 | AC618: 24.38725 | AD618: =IFERROR(AA618/AC618,0) -> 57093.768 | AE618: =K618-Q618-X618 -> 1 | AF618: =Q618-AA618 -> 0 | AG618: 1435423.4 | AH618: =IFERROR(AG618/Q618,0) -> 1.0309284 | AI618: 3.1749057e+08 | AJ618: =IF(AI618>0,AprCoef/SQRT(AI618),0) -> 0.026601917 | AK618: =AI618*AJ618/365 -> 23139.336 | AL618: =AD618 -> 57093.768 | AM618: =AK618-AL618 -> -33954.432 | AN618: =IF(A618>=Hip3LaunchDate,"YES","") | AO618: =IF(A618<Hip4LaunchDate,"pre-launch","live (zero-fee)") -> pre-launch
A619: 45680 | B619: 1.1321581e+10 | C619: 0 | D619: 178140305 | E619: =B619+C619 -> 1.1321581e+10 | F619: =E619+D619 -> 1.1499721e+10 | G619: =IFERROR(C619/E619,0) -> 0 | H619: 2783278 | I619: 38159 | J619: 84643 | K619: =H619+I619 -> 2821437 | M619: =H619-L619 -> 2783278 | N619: =IFERROR(M619/B619*10000,0) -> 2.4583828 | O619: 2699780 | P619: 37014 | Q619: =O619+P619 -> 2736794 | R619: =IF(A619<HlpChangeDate,HlpSharePre,HlpSharePost) -> 0.03 | S619: =Q619*R619/(1-R619) -> 84643.113 | T619: 84643 | U619: =S619-T619 -> 0.11340206 | V619: =Y619-O619*R619/(1-R619) -> -0.35051546 | W619: =Z619-P619*R619/(1-R619) -> 0.2371134 | X619: =S619+V619+W619 -> 84643 | Y619: 83498 | Z619: 1145 | AA619: 2736794 | AB619: 21.975 | AC619: 23.1755 | AD619: =IFERROR(AA619/AC619,0) -> 118089.97 | AE619: =K619-Q619-X619 -> 0 | AF619: =Q619-AA619 -> 0 | AG619: 2821436.6 | AH619: =IFERROR(AG619/Q619,0) -> 1.0309277 | AI619: 3.1820755e+08 | AJ619: =IF(AI619>0,AprCoef/SQRT(AI619),0) -> 0.02657193 | AK619: =AI619*AJ619/365 -> 23165.449 | AL619: =AD619 -> 118089.97 | AM619: =AK619-AL619 -> -94924.517 | AN619: =IF(A619>=Hip3LaunchDate,"YES","") | AO619: =IF(A619<Hip4LaunchDate,"pre-launch","live (zero-fee)") -> pre-launch
A620: 45681 | B620: 5.7847318e+09 | C620: 0 | D620: 93192677 | E620: =B620+C620 -> 5.7847318e+09 | F620: =E620+D620 -> 5.8779245e+09 | G620: =IFERROR(C620/E620,0) -> 0 | H620: 1284164 | I620: 23999 | J620: 38987 | K620: =H620+I620 -> 1308163 | M620: =H620-L620 -> 1284164 | N620: =IFERROR(M620/B620*10000,0) -> 2.2199197 | O620: 1245639 | P620: 23279 | Q620: =O620+P620 -> 1268918 | R620: =IF(A620<HlpChangeDate,HlpSharePre,HlpSharePost) -> 0.03 | S620: =Q620*R620/(1-R620) -> 39244.887 | T620: 38987 | U620: =S620-T620 -> 257.8866 | V620: =Y620-O620*R620/(1-R620) -> 0.082474227 | W620: =Z620-P620*R620/(1-R620) -> 0.030927835 | X620: =S620+V620+W620 -> 39245 | Y620: 38525 | Z620: 720 | AA620: 1268918 | AB620: 23.059 | AC620: 22.792 | AD620: =IFERROR(AA620/AC620,0) -> 55673.833 | AE620: =K620-Q620-X620 -> 0 | AF620: =Q620-AA620 -> 0 | AG620: 1299579.9 | AH620: =IFERROR(AG620/Q620,0) -> 1.0241638 | AI620: 3.1892453e+08 | AJ620: =IF(AI620>0,AprCoef/SQRT(AI620),0) -> 0.026542045 | AK620: =AI620*AJ620/365 -> 23191.532 | AL620: =AD620 -> 55673.833 | AM620: =AK620-AL620 -> -32482.301 | AN620: =IF(A620>=Hip3LaunchDate,"YES","") | AO620: =IF(A620<Hip4LaunchDate,"pre-launch","live (zero-fee)") -> pre-launch
A621: 45682 | B621: 3.5167284e+09 | C621: 0 | D621: 138875526 | E621: =B621+C621 -> 3.5167284e+09 | F621: =E621+D621 -> 3.655604e+09 | G621: =IFERROR(C621/E621,0) -> 0 | H621: 1061042 | I621: 14317 | J621: 32324 | K621: =H621+I621 -> 1075359 | M621: =H621-L621 -> 1061042 | N621: =IFERROR(M621/B621*10000,0) -> 3.0171281 | O621: 1029211 | P621: 13888 | Q621: =O621+P621 -> 1043099 | R621: =IF(A621<HlpChangeDate,HlpSharePre,HlpSharePost) -> 0.03 | S621: =Q621*R621/(1-R621) -> 32260.794 | T621: 32324 | U621: =S621-T621 -> -63.206186 | V621: =Y621-O621*R621/(1-R621) -> -0.26804124 | W621: =Z621-P621*R621/(1-R621) -> 0.4742268 | X621: =S621+V621+W621 -> 32261 | Y621: 31831 | Z621: 430 | AA621: 1043099 | AB621: 23.152 | AC621: 22.95925 | AD621: =IFERROR(AA621/AC621,0) -> 45432.625 | AE621: =K621-Q621-X621 -> -1 | AF621: =Q621-AA621 -> 0 | AG621: 1077471.9 | AH621: =IFERROR(AG621/Q621,0) -> 1.0329527 | AI621: 3.1964151e+08 | AJ621: =IF(AI621>0,AprCoef/SQRT(AI621),0) -> 0.02651226 | AK621: =AI621*AJ621/365 -> 23217.586 | AL621: =AD621 -> 45432.625 | AM621: =AK621-AL621 -> -22215.039 | AN621: =IF(A621>=Hip3LaunchDate,"YES","") | AO621: =IF(A621<Hip4LaunchDate,"pre-launch","live (zero-fee)") -> pre-launch
... A754: 45815 | B754: 3.033733e+09 | C754: 0 | D754: 137044111 | E754: =B754+C754 -> 3.033733e+09 | F754: =E754+D754 -> 3.1707771e+09 | G754: =IFERROR(C754/E754,0) -> 0 | H754: 888062 | I754: 30975 | J754: 27571 | K754: =H754+I754 -> 919037 | M754: =H754-L754 -> 888062 | N754: =IFERROR(M754/B754*10000,0) -> 2.9272913 | O754: 861420 | P754: 30046 | Q754: =O754+P754 -> 891466 | R754: =IF(A754<HlpChangeDate,HlpSharePre,HlpSharePost) -> 0.03 | S754: =Q754*R754/(1-R754) -> 27571.113 | T754: 27571 | U754: =S754-T754 -> 0.11340206 | V754: =Y754-O754*R754/(1-R754) -> 0.1443299 | W754: =Z754-P754*R754/(1-R754) -> -0.25773196 | X754: =S754+V754+W754 -> 27571 | Y754: 26642 | Z754: 929 | AA754: 891466 | AB754: 34.913 | AC754: 34.08975 | AD754: =IFERROR(AA754/AC754,0) -> 26150.558 | AE754: =K754-Q754-X754 -> 0 | AF754: =Q754-AA754 -> 0 | AG754: 919036.56 | AH754: =IFERROR(AG754/Q754,0) -> 1.0309272 | AI754: 3.8424044e+08 | AJ754: =IF(AI754>0,AprCoef/SQRT(AI754),0) -> 0.024181142 | AK754: =AI754*AJ754/365 -> 25455.815 | AL754: =AD754 -> 26150.558 | AM754: =AK754-AL754 -> -694.74316 | AN754: =IF(A754>=Hip3LaunchDate,"YES","") | AO754: =IF(A754<Hip4LaunchDate,"pre-launch","live (zero-fee)") -> pre-launch
A755: 45816 | B755: 3.1217007e+09 | C755: 0 | D755: 151362843 | E755: =B755+C755 -> 3.1217007e+09 | F755: =E755+D755 -> 3.2730635e+09 | G755: =IFERROR(C755/E755,0) -> 0 | K755: =H755+I755 -> 0 | M755: =H755-L755 -> 0 | N755: =IFERROR(M755/B755*10000,0) -> 0 | Q755: =O755+P755 -> 0 | R755: =IF(A755<HlpChangeDate,HlpSharePre,HlpSharePost) -> 0.03 | S755: =Q755*R755/(1-R755) -> 0 | U755: =S755-T755 -> 0 | V755: =Y755-O755*R755/(1-R755) -> 0 | W755: =Z755-P755*R755/(1-R755) -> 0 | X755: =S755+V755+W755 -> 0 | AA755: 0 | AB755: 34.983 | AC755: 35.171 | AD755: =IFERROR(AA755/AC755,0) -> 0 | AE755: =K755-Q755-X755 -> 0 | AF755: =Q755-AA755 -> 0 | AG755: 278826.03 | AH755: =IFERROR(AG755/Q755,0) -> 0 | AI755: 3.8437705e+08 | AJ755: =IF(AI755>0,AprCoef/SQRT(AI755),0) -> 0.024176845 | AK755: =AI755*AJ755/365 -> 25460.34 | AL755: =AD755 -> 0 | AM755: =AK755-AL755 -> 25460.34 | AN755: =IF(A755>=Hip3LaunchDate,"YES","") | AO755: =IF(A755<Hip4LaunchDate,"pre-launch","live (zero-fee)") -> pre-launch
A756: 45817 | B756: 7.9469529e+09 | C756: 0 | D756: 359240055 | E756: =B756+C756 -> 7.9469529e+09 | F756: =E756+D756 -> 8.306193e+09 | G756: =IFERROR(C756/E756,0) -> 0 | K756: =H756+I756 -> 0 | M756: =H756-L756 -> 0 | N756: =IFERROR(M756/B756*10000,0) -> 0 | Q756: =O756+P756 -> 0 | R756: =IF(A756<HlpChangeDate,HlpSharePre,HlpSharePost) -> 0.03 | S756: =Q756*R756/(1-R756) -> 0 | U756: =S756-T756 -> 0 | V756: =Y756-O756*R756/(1-R756) -> 0 | W756: =Z756-P756*R756/(1-R756) -> 0 | X756: =S756+V756+W756 -> 0 | AA756: 0 | AB756: 38.855 | AC756: 36.87175 | AD756: =IFERROR(AA756/AC756,0) -> 0 | AE756: =K756-Q756-X756 -> 0 | AF756: =Q756-AA756 -> 0 | AG756: 3169213.6 | AH756: =IFERROR(AG756/Q756,0) -> 0 | AI756: 3.8451366e+08 | AJ756: =IF(AI756>0,AprCoef/SQRT(AI756),0) -> 0.024172549 | AK756: =AI756*AJ756/365 -> 25464.864 | AL756: =AD756 -> 0 | AM756: =AK756-AL756 -> 25464.864 | AN756: =IF(A756>=Hip3LaunchDate,"YES","") | AO756: =IF(A756<Hip4LaunchDate,"pre-launch","live (zero-fee)") -> pre-launch
A757: 45818 | B757: 8.8680623e+09 | C757: 0 | D757: 493501254 | E757: =B757+C757 -> 8.8680623e+09 | F757: =E757+D757 -> 9.3615636e+09 | G757: =IFERROR(C757/E757,0) -> 0 | H757: 2654323 | I757: 115467 | J757: 83094 | K757: =H757+I757 -> 2769790 | M757: =H757-L757 -> 2654323 | N757: =IFERROR(M757/B757*10000,0) -> 2.9931262 | O757: 2574693 | P757: 112003 | Q757: =O757+P757 -> 2686696 | R757: =IF(A757<HlpChangeDate,HlpSharePre,HlpSharePost) -> 0.03 | S757: =Q757*R757/(1-R757) -> 83093.691 | T757: 83094 | U757: =S757-T757 -> -0.30927835 | V757: =Y757-O757*R757/(1-R757) -> 0.31958763 | W757: =Z757-P757*R757/(1-R757) -> -0.010309278 | X757: =S757+V757+W757 -> 83094 | Y757: 79630 | Z757: 3464 | AA757: 2686696 | AB757: 42.186 | AC757: 40.454 | AD757: =IFERROR(AA757/AC757,0) -> 66413.606 | AE757: =K757-Q757-X757 -> 0 | AF757: =Q757-AA757 -> 0 | AG757: 2769790.3 | AH757: =IFERROR(AG757/Q757,0) -> 1.030928 | AI757: 3.8465027e+08 | AJ757: =IF(AI757>0,AprCoef/SQRT(AI757),0) -> 0.024168256 | AK757: =AI757*AJ757/365 -> 25469.387 | AL757: =AD757 -> 66413.606 | AM757: =AK757-AL757 -> -40944.218 | AN757: =IF(A757>=Hip3LaunchDate,"YES","") | AO757: =IF(A757<Hip4LaunchDate,"pre-launch","live (zero-fee)") -> pre-launch
A758: 45819 | B758: 8.8808494e+09 | C758: 0 | D758: 491823654 | E758: =B758+C758 -> 8.8808494e+09 | F758: =E758+D758 -> 9.372673e+09 | G758: =IFERROR(C758/E758,0) -> 0 | H758: 2653604 | I758: 105920 | J758: 82298 | K758: =H758+I758 -> 2759524 | M758: =H758-L758 -> 2653604 | N758: =IFERROR(M758/B758*10000,0) -> 2.988007 | O758: 2573996 | P758: 102743 | Q758: =O758+P758 -> 2676739 | R758: =IF(A758<HlpChangeDate,HlpSharePre,HlpSharePost) -> 0.03 | S758: =Q758*R758/(1-R758) -> 82785.742 | T758: 82298 | U758: =S758-T758 -> 487.74227 | V758: =Y758-O758*R758/(1-R758) -> -0.12371134 | W758: =Z758-P758*R758/(1-R758) -> 0.3814433 | X758: =S758+V758+W758 -> 82786 | Y758: 79608 | Z758: 3178 | AA758: 2676739 | AB758: 41.805 | AC758: 42.156 | AD758: =IFERROR(AA758/AC758,0) -> 63496.039 | AE758: =K758-Q758-X758 -> -1 | AF758: =Q758-AA758 -> 0 | AG758: 2743278.6 | AH758: =IFERROR(AG758/Q758,0) -> 1.0248585 | AI758: 3.8478689e+08 | AJ758: =IF(AI758>0,AprCoef/SQRT(AI758),0) -> 0.024163966 | AK758: =AI758*AJ758/365 -> 25473.91 | AL758: =AD758 -> 63496.039 | AM758: =AK758-AL758 -> -38022.129 | AN758: =IF(A758>=Hip3LaunchDate,"YES","") | AO758: =IF(A758<Hip4LaunchDate,"pre-launch","live (zero-fee)") -> pre-launch
A759: 45820 | B759: 9.8599768e+09 | C759: 0 | D759: 499156091 | E759: =B759+C759 -> 9.8599768e+09 | F759: =E759+D759 -> 1.0359133e+10 | G759: =IFERROR(C759/E759,0) -> 0 | H759: 2909648 | I759: 95479 | J759: 90641 | K759: =H759+I759 -> 3005127 | M759: =H759-L759 -> 2909648 | N759: =IFERROR(M759/B759*10000,0) -> 2.9509684 | O759: 2822358 | P759: 92615 | Q759: =O759+P759 -> 2914973 | R759: =IF(A759<HlpChangeDate,HlpSharePre,HlpSharePost) -> 0.03 | S759: =Q759*R759/(1-R759) -> 90153.804 | T759: 90641 | U759: =S759-T759 -> -487.19588 | V759: =Y759-O759*R759/(1-R759) -> -0.42268041 | W759: =Z759-P759*R759/(1-R759) -> -0.3814433 | X759: =S759+V759+W759 -> 90153 | Y759: 87289 | Z759: 2864 | AA759: 2914973 | AB759: 40.509 | AC759: 41.621 | AD759: =IFERROR(AA759/AC759,0) -> 70036.112 | AE759: =K759-Q759-X759 -> 1 | AF759: =Q759-AA759 -> 0 | AG759: 3021373.1 | AH759: =IFERROR(AG759/Q759,0) -> 1.0365012 | AI759: 3.849235e+08 | AJ759: =IF(AI759>0,AprCoef/SQRT(AI759),0) -> 0.024159677 | AK759: =AI759*AJ759/365 -> 25478.432 | AL759: =AD759 -> 70036.112 | AM759: =AK759-AL759 -> -44557.68 | AN759: =IF(A759>=Hip3LaunchDate,"YES","") | AO759: =IF(A759<Hip4LaunchDate,"pre-launch","live (zero-fee)") -> pre-launch
A760: 45821 | B760: 1.3286057e+10 | C760: 0 | D760: 642044619 | E760: =B760+C760 -> 1.3286057e+10 | F760: =E760+D760 -> 1.3928101e+10 | G760: =IFERROR(C760/E760,0) -> 0 | H760: 3887429 | I760: 148721 | J760: 120410 | K760: =H760+I760 -> 4036150 | M760: =H760-L760 -> 3887429 | N760: =IFERROR(M760/B760*10000,0) -> 2.9259464 | O760: 3770806 | P760: 144260 | Q760: =O760+P760 -> 3915066 | R760: =IF(A760<HlpChangeDate,HlpSharePre,HlpSharePost) -> 0.03 | S760: =Q760*R760/(1-R760) -> 121084.52 | T760: 120410 | U760: =S760-T760 -> 674.51546 | V760: =Y760-O760*R760/(1-R760) -> 0.13402062 | W760: =Z760-P760*R760/(1-R760) -> 0.35051546 | X760: =S760+V760+W760 -> 121085 | Y760: 116623 | Z760: 4462 | AA760: 3915066 | AB760: 42.277 | AC760: 40.66175 | AD760: =IFERROR(AA760/AC760,0) -> 96283.756 | AE760: =K760-Q760-X760 -> -1 | AF760: =Q760-AA760 -> 0 | AG760: 4013650.9 | AH760: =IFERROR(AG760/Q760,0) -> 1.0251809 | AI760: 3.8506011e+08 | AJ760: =IF(AI760>0,AprCoef/SQRT(AI760),0) -> 0.024155391 | AK760: =AI760*AJ760/365 -> 25482.952 | AL760: =AD760 -> 96283.756 | AM760: =AK760-AL760 -> -70800.803 | AN760: =IF(A760>=Hip3LaunchDate,"YES","") | AO760: =IF(A760<Hip4LaunchDate,"pre-launch","live (zero-fee)") -> pre-launch
A761: 45822 | B761: 4.4904691e+09 | C761: 0 | D761: 223313776 | E761: =B761+C761 -> 4.4904691e+09 | F761: =E761+D761 -> 4.7137829e+09 | G761: =IFERROR(C761/E761,0) -> 0 | H761: 1261527 | I761: 53146 | J761: 39815 | K761: =H761+I761 -> 1314673 | M761: =H761-L761 -> 1261527 | N761: =IFERROR(M761/B761*10000,0) -> 2.8093434 | O761: 1223682 | P761: 51552 | Q761: =O761+P761 -> 1275234 | R761: =IF(A761<HlpChangeDate,HlpSharePre,HlpSharePost) -> 0.03 | S761: =Q761*R761/(1-R761) -> 39440.227 | T761: 39815 | U761: =S761-T761 -> -374.7732 | V761: =Y761-O761*R761/(1-R761) -> 0.16494845 | W761: =Z761-P761*R761/(1-R761) -> -0.39175258 | X761: =S761+V761+W761 -> 39440 | Y761: 37846 | Z761: 1594 | AA761: 1275234 | AB761: 40.107 | AC761: 40.9635 | AD761: =IFERROR(AA761/AC761,0) -> 31130.982 | AE761: =K761-Q761-X761 -> -1 | AF761: =Q761-AA761 -> 0 | AG761: 1327158.2 | AH761: =IFERROR(AG761/Q761,0) -> 1.0407174 | AI761: 3.8519672e+08 | AJ761: =IF(AI761>0,AprCoef/SQRT(AI761),0) -> 0.024151107 | AK761: =AI761*AJ761/365 -> 25487.472 | AL761: =AD761 -> 31130.982 | AM761: =AK761-AL761 -> -5643.5101 | AN761: =IF(A761>=Hip3LaunchDate,"YES","") | AO761: =IF(A761<Hip4LaunchDate,"pre-launch","live (zero-fee)") -> pre-launch
A762: 45823 | B762: 4.1205593e+09 | C762: 0 | D762: 208088792 | E762: =B762+C762 -> 4.1205593e+09 | F762: =E762+D762 -> 4.3286481e+09 | G762: =IFERROR(C762/E762,0) -> 0 | H762: 1158797 | I762: 39647 | J762: 36254 | K762: =H762+I762 -> 1198444 | M762: =H762-L762 -> 1158797 | N762: =IFERROR(M762/B762*10000,0) -> 2.8122323 | O762: 1124033 | P762: 38458 | Q762: =O762+P762 -> 1162491 | R762: =IF(A762<HlpChangeDate,HlpSharePre,HlpSharePost) -> 0.03 | S762: =Q762*R762/(1-R762) -> 35953.33 | T762: 36254 | U762: =S762-T762 -> -300.6701 | V762: =Y762-O762*R762/(1-R762) -> 0.092783505 | W762: =Z762-P762*R762/(1-R762) -> -0.42268041 | X762: =S762+V762+W762 -> 35953 | Y762: 34764 | Z762: 1189 | AA762: 1162491 | AB762: 41.166 | AC762: 40.5925 | AD762: =IFERROR(AA762/AC762,0) -> 28638.074 | AE762: =K762-Q762-X762 -> 0 | AF762: =Q762-AA762 -> 0 | AG762: 1208458.3 | AH762: =IFERROR(AG762/Q762,0) -> 1.0395421 | AI762: 3.8533333e+08 | AJ762: =IF(AI762>0,AprCoef/SQRT(AI762),0) -> 0.024146826 | AK762: =AI762*AJ762/365 -> 25491.992 | AL762: =AD762 -> 28638.074 | AM762: =AK762-AL762 -> -3146.0819 | AN762: =IF(A762>=Hip3LaunchDate,"YES","") | AO762: =IF(A762<Hip4LaunchDate,"pre-launch","live (zero-fee)") -> pre-launch
A763: 45824 | B763: 9.9104451e+09 | C763: 0 | D763: 500000932 | E763: =B763+C763 -> 9.9104451e+09 | F763: =E763+D763 -> 1.0410446e+10 | G763: =IFERROR(C763/E763,0) -> 0 | H763: 2838831 | I763: 103884 | J763: 86131 | K763: =H763+I763 -> 2942715 | M763: =H763-L763 -> 2838831 | N763: =IFERROR(M763/B763*10000,0) -> 2.8644839 | O763: 2753666 | P763: 100767 | Q763: =O763+P763 -> 2854433 | R763: =IF(A763<HlpChangeDate,HlpSharePre,HlpSharePost) -> 0.03 | S763: =Q763*R763/(1-R763) -> 88281.433 | T763: 86131 | U763: =S763-T763 -> 2150.433 | V763: =Y763-O763*R763/(1-R763) -> 0.072164948 | W763: =Z763-P763*R763/(1-R763) -> 0.49484536 | X763: =S763+V763+W763 -> 88282 | Y763: 85165 | Z763: 3117 | AA763: 2854433 | AB763: 41.899 | AC763: 42.375 | AD763: =IFERROR(AA763/AC763,0) -> 67361.251 | AE763: =K763-Q763-X763 -> 0 | AF763: =Q763-AA763 -> 0 | AG763: 2871026.7 | AH763: =IFERROR(AG763/Q763,0) -> 1.0058133 | AI763: 3.8546995e+08 | AJ763: =IF(AI763>0,AprCoef/SQRT(AI763),0) -> 0.024142547 | AK763: =AI763*AJ763/365 -> 25496.51 | AL763: =AD763 -> 67361.251 | AM763: =AK763-AL763 -> -41864.741 | AN763: =IF(A763>=Hip3LaunchDate,"YES","") | AO763: =IF(A763<Hip4LaunchDate,"pre-launch","live (zero-fee)") -> pre-launch
A764: 45825 | B764: 1.1324626e+10 | C764: 0 | D764: 481779486 | E764: =B764+C764 -> 1.1324626e+10 | F764: =E764+D764 -> 1.1806405e+10 | G764: =IFERROR(C764/E764,0) -> 0 | H764: 3268752 | I764: 119116 | J764: 103787 | K764: =H764+I764 -> 3387868 | M764: =H764-L764 -> 3268752 | N764: =IFERROR(M764/B764*10000,0) -> 2.8864106 | O764: 3170689 | P764: 115542 | Q764: =O764+P764 -> 3286231 | R764: =IF(A764<HlpChangeDate,HlpSharePre,HlpSharePost) -> 0.03 | S764: =Q764*R764/(1-R764) -> 101636.01 | T764: 103787 | U764: =S764-T764 -> -2150.9897 | V764: =Y764-O764*R764/(1-R764) -> 0.45360825 | W764: =Z764-P764*R764/(1-R764) -> -0.46391753 | X764: =S764+V764+W764 -> 101636 | Y764: 98063 | Z764: 3573 | AA764: 3286231 | AB764: 39.98 | AC764: 40.90975 | AD764: =IFERROR(AA764/AC764,0) -> 80328.797 | AE764: =K764-Q764-X764 -> 1 | AF764: =Q764-AA764 -> 0 | AG764: 3459555.5 | AH764: =IFERROR(AG764/Q764,0) -> 1.0527426 | AI764: 3.8560656e+08 | AJ764: =IF(AI764>0,AprCoef/SQRT(AI764),0) -> 0.02413827 | AK764: =AI764*AJ764/365 -> 25501.028 | AL764: =AD764 -> 80328.797 | AM764: =AK764-AL764 -> -54827.769 | AN764: =IF(A764>=Hip3LaunchDate,"YES","") | AO764: =IF(A764<Hip4LaunchDate,"pre-launch","live (zero-fee)") -> pre-launch
A765: 45826 | B765: 7.99953e+09 | C765: 0 | D765: 420606916 | E765: =B765+C765 -> 7.99953e+09 | F765: =E765+D765 -> 8.4201369e+09 | G765: =IFERROR(C765/E765,0) -> 0 | H765: 2288124 | I765: 88887 | J765: 71154 | K765: =H765+I765 -> 2377011 | M765: =H765-L765 -> 2288124 | N765: =IFERROR(M765/B765*10000,0) -> 2.860323 | O765: 2219481 | P765: 86220 | Q765: =O765+P765 -> 2305701 | R765: =IF(A765<HlpChangeDate,HlpSharePre,HlpSharePost) -> 0.03 | S765: =Q765*R765/(1-R765) -> 71310.34 | T765: 71154 | U765: =S765-T765 -> 156.34021 | V765: =Y765-O765*R765/(1-R765) -> 0.25773196 | W765: =Z765-P765*R765/(1-R765) -> 0.40206186 | X765: =S765+V765+W765 -> 71311 | Y765: 68644 | Z765: 2667 | AA765: 2305701 | AB765: 39.45 | AC765: 39.52 | AD765: =IFERROR(AA765/AC765,0) -> 58342.637 | AE765: =K765-Q765-X765 -> -1 | AF765: =Q765-AA765 -> 0 | AG765: 2371798.7 | AH765: =IFERROR(AG765/Q765,0) -> 1.0286671 | AI765: 3.8574317e+08 | AJ765: =IF(AI765>0,AprCoef/SQRT(AI765),0) -> 0.024133995 | AK765: =AI765*AJ765/365 -> 25505.545 | AL765: =AD765 -> 58342.637 | AM765: =AK765-AL765 -> -32837.092 | AN765: =IF(A765>=Hip3LaunchDate,"YES","") | AO765: =IF(A765<Hip4LaunchDate,"pre-launch","live (zero-fee)") -> pre-launch
A766: 45827 | B766: 5.3097062e+09 | C766: 0 | D766: 309275966 | E766: =B766+C766 -> 5.3097062e+09 | F766: =E766+D766 -> 5.6189821e+09 | G766: =IFERROR(C766/E766,0) -> 0 | H766: 1469442 | I766: 73911 | J766: 46457 | K766: =H766+I766 -> 1543353 | M766: =H766-L766 -> 1469442 | N766: =IFERROR(M766/B766*10000,0) -> 2.7674639 | O766: 1425358 | P766: 71693 | Q766: =O766+P766 -> 1497051 | R766: =IF(A766<HlpChangeDate,HlpSharePre,HlpSharePost) -> 0.03 | S766: =Q766*R766/(1-R766) -> 46300.546 | T766: 46457 | U766: =S766-T766 -> -156.45361 | V766: =Y766-O766*R766/(1-R766) -> -0.2371134 | W766: =Z766-P766*R766/(1-R766) -> -0.30927835 | X766: =S766+V766+W766 -> 46300 | Y766: 44083 | Z766: 2217 | AA766: 1497051 | AB766: 36.872 | AC766: 38.016 | AD766: =IFERROR(AA766/AC766,0) -> 39379.498 | AE766: =K766-Q766-X766 -> 2 | AF766: =Q766-AA766 -> 0 | AG766: 1548564.8 | AH766: =IFERROR(AG766/Q766,0) -> 1.0344102 | AI766: 3.8587978e+08 | AJ766: =IF(AI766>0,AprCoef/SQRT(AI766),0) -> 0.024129723 | AK766: =AI766*AJ766/365 -> 25510.061 | AL766: =AD766 -> 39379.498 | AM766: =AK766-AL766 -> -13869.438 | AN766: =IF(A766>=Hip3LaunchDate,"YES","") | AO766: =IF(A766<Hip4LaunchDate,"pre-launch","live (zero-fee)") -> pre-launch
A767: 45828 | B767: 8.9847656e+09 | C767: 0 | D767: 390870684 | E767: =B767+C767 -> 8.9847656e+09 | F767: =E767+D767 -> 9.3756363e+09 | G767: =IFERROR(C767/E767,0) -> 0 | H767: 2544445 | I767: 93536 | J767: 79000 | K767: =H767+I767 -> 2637981 | M767: =H767-L767 -> 2544445 | N767: =IFERROR(M767/B767*10000,0) -> 2.8319548 | O767: 2468112 | P767: 90730 | Q767: =O767+P767 -> 2558842 | R767: =IF(A767<HlpChangeDate,HlpSharePre,HlpSharePost) -> 0.03 | S767: =Q767*R767/(1-R767) -> 79139.443 | T767: 79000 | U767: =S767-T767 -> 139.4433 | V767: =Y767-O767*R767/(1-R767) -> -0.36082474 | W767: =Z767-P767*R767/(1-R767) -> -0.082474227 | X767: =S767+V767+W767 -> 79139 | Y767: 76333 | Z767: 2806 | AA767: 2558842 | AB767: 33.338 | AC767: 35.29225 | AD767: =IFERROR(AA767/AC767,0) -> 72504.36 | AE767: =K767-Q767-X767 -> 0 | AF767: =Q767-AA767 -> 0 | AG767: 2633335.6 | AH767: =IFERROR(AG767/Q767,0) -> 1.0291122 | AI767: 3.8601639e+08 | AJ767: =IF(AI767>0,AprCoef/SQRT(AI767),0) -> 0.024125452 | AK767: =AI767*AJ767/365 -> 25514.576 | AL767: =AD767 -> 72504.36 | AM767: =AK767-AL767 -> -46989.784 | AN767: =IF(A767>=Hip3LaunchDate,"YES","") | AO767: =IF(A767<Hip4LaunchDate,"pre-launch","live (zero-fee)") -> pre-launch
A768: 45829 | B768: 5.8535617e+09 | C768: 0 | D768: 325856019 | E768: =B768+C768 -> 5.8535617e+09 | F768: =E768+D768 -> 6.1794177e+09 | G768: =IFERROR(C768/E768,0) -> 0 | H768: 1614659 | I768: 69112 | J768: 50652 | K768: =H768+I768 -> 1683771 | M768: =H768-L768 -> 1614659 | N768: =IFERROR(M768/B768*10000,0) -> 2.7584214 | O768: 1566219 | P768: 67039 | Q768: =O768+P768 -> 1633258 | R768: =IF(A768<HlpChangeDate,HlpSharePre,HlpSharePost) -> 0.03 | S768: =Q768*R768/(1-R768) -> 50513.134 | T768: 50652 | U768: =S768-T768 -> -138.86598 | V768: =Y768-O768*R768/(1-R768) -> 0.2371134 | W768: =Z768-P768*R768/(1-R768) -> -0.37113402 | X768: =S768+V768+W768 -> 50513 | Y768: 48440 | Z768: 2073 | AA768: 1633258 | AB768: 34.396 | AC768: 33.5625 | AD768: =IFERROR(AA768/AC768,0) -> 48663.181 | AE768: =K768-Q768-X768 -> 0 | AF768: =Q768-AA768 -> 0 | AG768: 1688416.6 | AH768: =IFERROR(AG768/Q768,0) -> 1.0337721 | AI768: 3.8615301e+08 | AJ768: =IF(AI768>0,AprCoef/SQRT(AI768),0) -> 0.024121185 | AK768: =AI768*AJ768/365 -> 25519.09 | AL768: =AD768 -> 48663.181 | AM768: =AK768-AL768 -> -23144.09 | AN768: =IF(A768>=Hip3LaunchDate,"YES","") | AO768: =IF(A768<Hip4LaunchDate,"pre-launch","live (zero-fee)") -> pre-launch
... A881: 45942 | B881: 1.1787565e+10 | C881: 0 | D881: 484211693 | E881: =B881+C881 -> 1.1787565e+10 | F881: =E881+D881 -> 1.2271776e+10 | G881: =IFERROR(C881/E881,0) -> 0 | H881: 3799559 | I881: 257362 | J881: 36538 | K881: =H881+I881 -> 4056921 | M881: =H881-L881 -> 3799559 | N881: =IFERROR(M881/B881*10000,0) -> 3.2233622 | O881: 3440902 | P881: 176358 | Q881: =O881+P881 -> 3617260 | R881: =IF(A881<HlpChangeDate,HlpSharePre,HlpSharePost) -> 0.01 | S881: =Q881*R881/(1-R881) -> 36537.98 | T881: 36538 | U881: =S881-T881 -> -0.02020202 | V881: =Y881-O881*R881/(1-R881) -> 323900.41 | W881: =Z881-P881*R881/(1-R881) -> 79222.606 | X881: =S881+V881+W881 -> 439661 | Y881: 358657 | Z881: 81004 | AA881: 3617260 | AB881: 39.651 | AC881: 38.37225 | AD881: =IFERROR(AA881/AC881,0) -> 94267.602 | AE881: =K881-Q881-X881 -> 0 | AF881: =Q881-AA881 -> 0 | AG881: 3306971.2 | AH881: =IFERROR(AG881/Q881,0) -> 0.91421993 | AI881: 4.0159016e+08 | AJ881: =IF(AI881>0,AprCoef/SQRT(AI881),0) -> 0.023653031 | AK881: =AI881*AJ881/365 -> 26024.177 | AL881: =AD881 -> 94267.602 | AM881: =AK881-AL881 -> -68243.425 | AN881: =IF(A881>=Hip3LaunchDate,"YES","") | AO881: =IF(A881<Hip4LaunchDate,"pre-launch","live (zero-fee)") -> pre-launch
A882: 45943 | B882: 9.5875348e+09 | C882: 24137313 | D882: 433769946 | E882: =B882+C882 -> 9.6116721e+09 | F882: =E882+D882 -> 1.0045442e+10 | G882: =IFERROR(C882/E882,0) -> 0.0025112501 | H882: 2991680 | I882: 217963 | J882: 28869 | K882: =H882+I882 -> 3209643 | L882: 6992.5795 | M882: =H882-L882 -> 2984687.4 | N882: =IFERROR(M882/B882*10000,0) -> 3.1130916 | O882: 2695086 | P882: 162992 | Q882: =O882+P882 -> 2858078 | R882: =IF(A882<HlpChangeDate,HlpSharePre,HlpSharePost) -> 0.01 | S882: =Q882*R882/(1-R882) -> 28869.475 | T882: 28869 | U882: =S882-T882 -> 0.47474747 | V882: =Y882-O882*R882/(1-R882) -> 269370.91 | W882: =Z882-P882*R882/(1-R882) -> 53324.616 | X882: =S882+V882+W882 -> 351565 | Y882: 296594 | Z882: 54971 | AA882: 2858078 | AB882: 42.489 | AC882: 40.98825 | AD882: =IFERROR(AA882/AC882,0) -> 69729.203 | AE882: =K882-Q882-X882 -> 0 | AF882: =Q882-AA882 -> 0 | AG882: 2766599.5 | AH882: =IFERROR(AG882/Q882,0) -> 0.96799298 | AI882: 4.0172678e+08 | AJ882: =IF(AI882>0,AprCoef/SQRT(AI882),0) -> 0.023649009 | AK882: =AI882*AJ882/365 -> 26028.603 | AL882: =AD882 -> 69729.203 | AM882: =AK882-AL882 -> -43700.599 | AN882: =IF(A882>=Hip3LaunchDate,"YES","") -> YES | AO882: =IF(A882<Hip4LaunchDate,"pre-launch","live (zero-fee)") -> pre-launch | AP882: 1 | AQ882: 0 | AR882: 6992.5795
...

Sheet HIP-3 Model
A1: HIP-3 Per-Asset Fee Model — Hyperliquid's slice only (matches DL Perps)
A2: Hyperliquid's slice on any HIP-3 market = base × growthModeFactor × 1 (HL always keeps the equivalent of 1x base, regardless of deployerFeeScale).
A3: Note: This sheet shows what enters DL Hyperliquid Perps fees from HIP-3. The deployer's slice is tracked SEPARATELY in DL (e.g. tradeXYZ, Felix, etc.) and is NOT in Hyperliquid totals.
A5: Asset | B5: Dex | C5: deployerFeeScale | D5: scaleIfHip3 | E5: HL retained share | F5: Deployer share | G5: growthMode | H5: gmChangeDate | I5: HL slice bps (GM on) | J5: HL slice bps (GM off) | K5: Deployer slice bps (GM on, info)
A6: abcd:USA500 | B6: abcd | C6: 1 | D6: 2 | E6: 0.5 | F6: 0.5 | G6: N/A | I6: =CoreBpsBlended*GrowthModeFactor*D6*E6 -> 0.2897 | J6: =CoreBpsBlended*D6*E6 -> 2.897 | K6: =CoreBpsBlended*GrowthModeFactor*D6*F6 -> 0.2897
A7: cash:AMZN | B7: cash | C7: 1 | D7: 2 | E7: 0.5 | F7: 0.5 | G7: enabled | H7: 46049 | I7: =CoreBpsBlended*GrowthModeFactor*D7*E7 -> 0.2897 | J7: =CoreBpsBlended*D7*E7 -> 2.897 | K7: =CoreBpsBlended*GrowthModeFactor*D7*F7 -> 0.2897
A8: cash:BTC | B8: cash | C8: 1 | D8: 2 | E8: 0.5 | F8: 0.5 | G8: N/A | I8: =CoreBpsBlended*GrowthModeFactor*D8*E8 -> 0.2897 | J8: =CoreBpsBlended*D8*E8 -> 2.897 | K8: =CoreBpsBlended*GrowthModeFactor*D8*F8 -> 0.2897
A9: cash:CAR | B9: cash | C9: 1 | D9: 2 | E9: 0.5 | F9: 0.5 | G9: enabled | H9: 46141 | I9: =CoreBpsBlended*GrowthModeFactor*D9*E9 -> 0.2897 | J9: =CoreBpsBlended*D9*E9 -> 2.897 | K9: =CoreBpsBlended*GrowthModeFactor*D9*F9 -> 0.2897
A10: cash:ETH | B10: cash | C10: 1 | D10: 2 | E10: 0.5 | F10: 0.5 | G10: N/A | I10: =CoreBpsBlended*GrowthModeFactor*D10*E10 -> 0.2897 | J10: =CoreBpsBlended*D10*E10 -> 2.897 | K10: =CoreBpsBlended*GrowthModeFactor*D10*F10 -> 0.2897
A11: cash:EWY | B11: cash | C11: 1 | D11: 2 | E11: 0.5 | F11: 0.5 | G11: enabled | H11: 46079 | I11: =CoreBpsBlended*GrowthModeFactor*D11*E11 -> 0.2897 | J11: =CoreBpsBlended*D11*E11 -> 2.897 | K11: =CoreBpsBlended*GrowthModeFactor*D11*F11 -> 0.2897
A12: cash:GOLD | B12: cash | C12: 1 | D12: 2 | E12: 0.5 | F12: 0.5 | G12: N/A | I12: =CoreBpsBlended*GrowthModeFactor*D12*E12 -> 0.2897 | J12: =CoreBpsBlended*D12*E12 -> 2.897 | K12: =CoreBpsBlended*GrowthModeFactor*D12*F12 -> 0.2897
A13: cash:GOOGL | B13: cash | C13: 1 | D13: 2 | E13: 0.5 | F13: 0.5 | G13: enabled | H13: 46049 | I13: =CoreBpsBlended*GrowthModeFactor*D13*E13 -> 0.2897 | J13: =CoreBpsBlended*D13*E13 -> 2.897 | K13: =CoreBpsBlended*GrowthModeFactor*D13*F13 -> 0.2897
A14: cash:HOOD | B14: cash | C14: 1 | D14: 2 | E14: 0.5 | F14: 0.5 | G14: enabled | H14: 46049 | I14: =CoreBpsBlended*GrowthModeFactor*D14*E14 -> 0.2897 | J14: =CoreBpsBlended*D14*E14 -> 2.897 | K14: =CoreBpsBlended*GrowthModeFactor*D14*F14 -> 0.2897
A15: cash:INTC | B15: cash | C15: 1 | D15: 2 | E15: 0.5 | F15: 0.5 | G15: enabled | H15: 46049 | I15: =CoreBpsBlended*GrowthModeFactor*D15*E15 -> 0.2897 | J15: =CoreBpsBlended*D15*E15 -> 2.897 | K15: =CoreBpsBlended*GrowthModeFactor*D15*F15 -> 0.2897
A16: cash:KWEB | B16: cash | C16: 1 | D16: 2 | E16: 0.5 | F16: 0.5 | G16: enabled | H16: 46099 | I16: =CoreBpsBlended*GrowthModeFactor*D16*E16 -> 0.2897 | J16: =CoreBpsBlended*D16*E16 -> 2.897 | K16: =CoreBpsBlended*GrowthModeFactor*D16*F16 -> 0.2897
A17: cash:META | B17: cash | C17: 1 | D17: 2 | E17: 0.5 | F17: 0.5 | G17: enabled | H17: 46049 | I17: =CoreBpsBlended*GrowthModeFactor*D17*E17 -> 0.2897 | J17: =CoreBpsBlended*D17*E17 -> 2.897 | K17: =CoreBpsBlended*GrowthModeFactor*D17*F17 -> 0.2897
A18: cash:MSFT | B18: cash | C18: 1 | D18: 2 | E18: 0.5 | F18: 0.5 | G18: enabled | H18: 46049 | I18: =CoreBpsBlended*GrowthModeFactor*D18*E18 -> 0.2897 | J18: =CoreBpsBlended*D18*E18 -> 2.897 | K18: =CoreBpsBlended*GrowthModeFactor*D18*F18 -> 0.2897
A19: cash:NVDA | B19: cash | C19: 1 | D19: 2 | E19: 0.5 | F19: 0.5 | G19: enabled | H19: 46045 | I19: =CoreBpsBlended*GrowthModeFactor*D19*E19 -> 0.2897 | J19: =CoreBpsBlended*D19*E19 -> 2.897 | K19: =CoreBpsBlended*GrowthModeFactor*D19*F19 -> 0.2897
A20: cash:SILVER | B20: cash | C20: 1 | D20: 2 | E20: 0.5 | F20: 0.5 | G20: enabled | H20: 46059 | I20: =CoreBpsBlended*GrowthModeFactor*D20*E20 -> 0.2897 | J20: =CoreBpsBlended*D20*E20 -> 2.897 | K20: =CoreBpsBlended*GrowthModeFactor*D20*F20 -> 0.2897
A21: cash:TSLA | B21: cash | C21: 1 | D21: 2 | E21: 0.5 | F21: 0.5 | G21: enabled | H21: 46044 | I21: =CoreBpsBlended*GrowthModeFactor*D21*E21 -> 0.2897 | J21: =CoreBpsBlended*D21*E21 -> 2.897 | K21: =CoreBpsBlended*GrowthModeFactor*D21*F21 -> 0.2897
A22: cash:USA500 | B22: cash | C22: 1 | D22: 2 | E22: 0.5 | F22: 0.5 | G22: enabled | H22: 46042 | I22: =CoreBpsBlended*GrowthModeFactor*D22*E22 -> 0.2897 | J22: =CoreBpsBlended*D22*E22 -> 2.897 | K22: =CoreBpsBlended*GrowthModeFactor*D22*F22 -> 0.2897
A23: cash:WTI | B23: cash | C23: 1 | D23: 2 | E23: 0.5 | F23: 0.5 | G23: enabled | H23: 46092 | I23: =CoreBpsBlended*GrowthModeFactor*D23*E23 -> 0.2897 | J23: =CoreBpsBlended*D23*E23 -> 2.897 | K23: =CoreBpsBlended*GrowthModeFactor*D23*F23 -> 0.2897
A24: flx:BTC | B24: flx | C24: 1 | D24: 2 | E24: 0.5 | F24: 0.5 | G24: N/A | I24: =CoreBpsBlended*GrowthModeFactor*D24*E24 -> 0.2897 | J24: =CoreBpsBlended*D24*E24 -> 2.897 | K24: =CoreBpsBlended*GrowthModeFactor*D24*F24 -> 0.2897
A25: flx:COIN | B25: flx | C25: 1 | D25: 2 | E25: 0.5 | F25: 0.5 | G25: enabled | H25: 45985 | I25: =CoreBpsBlended*GrowthModeFactor*D25*E25 -> 0.2897 | J25: =CoreBpsBlended*D25*E25 -> 2.897 | K25: =CoreBpsBlended*GrowthModeFactor*D25*F25 -> 0.2897
A26: flx:COPPER | B26: flx | C26: 1 | D26: 2 | E26: 0.5 | F26: 0.5 | G26: enabled | H26: 46051 | I26: =CoreBpsBlended*GrowthModeFactor*D26*E26 -> 0.2897 | J26: =CoreBpsBlended*D26*E26 -> 2.897 | K26: =CoreBpsBlended*GrowthModeFactor*D26*F26 -> 0.2897
A27: flx:CRCL | B27: flx | C27: 1 | D27: 2 | E27: 0.5 | F27: 0.5 | G27: enabled | H27: 45985 | I27: =CoreBpsBlended*GrowthModeFactor*D27*E27 -> 0.2897 | J27: =CoreBpsBlended*D27*E27 -> 2.897 | K27: =CoreBpsBlended*GrowthModeFactor*D27*F27 -> 0.2897
A28: flx:GAS | B28: flx | C28: 1 | D28: 2 | E28: 0.5 | F28: 0.5 | G28: enabled | H28: 46112 | I28: =CoreBpsBlended*GrowthModeFactor*D28*E28 -> 0.2897 | J28: =CoreBpsBlended*D28*E28 -> 2.897 | K28: =CoreBpsBlended*GrowthModeFactor*D28*F28 -> 0.2897
A29: flx:GOLD | B29: flx | C29: 1 | D29: 2 | E29: 0.5 | F29: 0.5 | G29: N/A | I29: =CoreBpsBlended*GrowthModeFactor*D29*E29 -> 0.2897 | J29: =CoreBpsBlended*D29*E29 -> 2.897 | K29: =CoreBpsBlended*GrowthModeFactor*D29*F29 -> 0.2897
A30: flx:NVDA | B30: flx | C30: 1 | D30: 2 | E30: 0.5 | F30: 0.5 | G30: enabled | H30: 46089 | I30: =CoreBpsBlended*GrowthModeFactor*D30*E30 -> 0.2897 | J30: =CoreBpsBlended*D30*E30 -> 2.897 | K30: =CoreBpsBlended*GrowthModeFactor*D30*F30 -> 0.2897
A31: flx:OIL | B31: flx | C31: 1 | D31: 2 | E31: 0.5 | F31: 0.5 | G31: enabled | H31: 46051 | I31: =CoreBpsBlended*GrowthModeFactor*D31*E31 -> 0.2897 | J31: =CoreBpsBlended*D31*E31 -> 2.897 | K31: =CoreBpsBlended*GrowthModeFactor*D31*F31 -> 0.2897
A32: flx:PALLADIUM | B32: flx | C32: 1 | D32: 2 | E32: 0.5 | F32: 0.5 | G32: enabled | H32: 46051 | I32: =CoreBpsBlended*GrowthModeFactor*D32*E32 -> 0.2897 | J32: =CoreBpsBlended*D32*E32 -> 2.897 | K32: =CoreBpsBlended*GrowthModeFactor*D32*F32 -> 0.2897
A33: flx:PLATINUM | B33: flx | C33: 1 | D33: 2 | E33: 0.5 | F33: 0.5 | G33: enabled | H33: 46051 | I33: =CoreBpsBlended*GrowthModeFactor*D33*E33 -> 0.2897 | J33: =CoreBpsBlended*D33*E33 -> 2.897 | K33: =CoreBpsBlended*GrowthModeFactor*D33*F33 -> 0.2897
A34: flx:SILVER | B34: flx | C34: 1 | D34: 2 | E34: 0.5 | F34: 0.5 | G34: enabled | H34: 46051 | I34: =CoreBpsBlended*GrowthModeFactor*D34*E34 -> 0.2897 | J34: =CoreBpsBlended*D34*E34 -> 2.897 | K34: =CoreBpsBlended*GrowthModeFactor*D34*F34 -> 0.2897
A35: flx:TSLA | B35: flx | C35: 1 | D35: 2 | E35: 0.5 | F35: 0.5 | G35: enabled | H35: 45985 | I35: =CoreBpsBlended*GrowthModeFactor*D35*E35 -> 0.2897 | J35: =CoreBpsBlended*D35*E35 -> 2.897 | K35: =CoreBpsBlended*GrowthModeFactor*D35*F35 -> 0.2897
A36: flx:USA100 | B36: flx | C36: 1 | D36: 2 | E36: 0.5 | F36: 0.5 | G36: enabled | H36: 46111 | I36: =CoreBpsBlended*GrowthModeFactor*D36*E36 -> 0.2897 | J36: =CoreBpsBlended*D36*E36 -> 2.897 | K36: =CoreBpsBlended*GrowthModeFactor*D36*F36 -> 0.2897
A37: flx:USA500 | B37: flx | C37: 1 | D37: 2 | E37: 0.5 | F37: 0.5 | G37: enabled | H37: 46091 | I37: =CoreBpsBlended*GrowthModeFactor*D37*E37 -> 0.2897 | J37: =CoreBpsBlended*D37*E37 -> 2.897 | K37: =CoreBpsBlended*GrowthModeFactor*D37*F37 -> 0.2897
A38: flx:USDE | B38: flx | C38: 1 | D38: 2 | E38: 0.5 | F38: 0.5 | G38: N/A | I38: =CoreBpsBlended*GrowthModeFactor*D38*E38 -> 0.2897 | J38: =CoreBpsBlended*D38*E38 -> 2.897 | K38: =CoreBpsBlended*GrowthModeFactor*D38*F38 -> 0.2897
A39: flx:XMR | B39: flx | C39: 1 | D39: 2 | E39: 0.5 | F39: 0.5 | G39: N/A | I39: =CoreBpsBlended*GrowthModeFactor*D39*E39 -> 0.2897 | J39: =CoreBpsBlended*D39*E39 -> 2.897 | K39: =CoreBpsBlended*GrowthModeFactor*D39*F39 -> 0.2897
A40: hyna:1000PEPE | B40: hyna | C40: 0.1111 | D40: 1.1111 | E40: 0.900009 | F40: 0.099991 | G40: N/A | I40: =CoreBpsBlended*GrowthModeFactor*D40*E40 -> 0.2897 | J40: =CoreBpsBlended*D40*E40 -> 2.897 | K40: =CoreBpsBlended*GrowthModeFactor*D40*F40 -> 0.03218567
A41: hyna:ADA | B41: hyna | C41: 0.1111 | D41: 1.1111 | E41: 0.900009 | F41: 0.099991 | G41: N/A | I41: =CoreBpsBlended*GrowthModeFactor*D41*E41 -> 0.2897 | J41: =CoreBpsBlended*D41*E41 -> 2.897 | K41: =CoreBpsBlended*GrowthModeFactor*D41*F41 -> 0.03218567
A42: hyna:BASED | B42: hyna | C42: 0.1111 | D42: 1.1111 | E42: 0.900009 | F42: 0.099991 | G42: N/A | I42: =CoreBpsBlended*GrowthModeFactor*D42*E42 -> 0.2897 | J42: =CoreBpsBlended*D42*E42 -> 2.897 | K42: =CoreBpsBlended*GrowthModeFactor*D42*F42 -> 0.03218567
A43: hyna:BCH | B43: hyna | C43: 0.1111 | D43: 1.1111 | E43: 0.900009 | F43: 0.099991 | G43: N/A | I43: =CoreBpsBlended*GrowthModeFactor*D43*E43 -> 0.2897 | J43: =CoreBpsBlended*D43*E43 -> 2.897 | K43: =CoreBpsBlended*GrowthModeFactor*D43*F43 -> 0.03218567
A44: hyna:BNB | B44: hyna | C44: 0.1111 | D44: 1.1111 | E44: 0.900009 | F44: 0.099991 | G44: N/A | I44: =CoreBpsBlended*GrowthModeFactor*D44*E44 -> 0.2897 | J44: =CoreBpsBlended*D44*E44 -> 2.897 | K44: =CoreBpsBlended*GrowthModeFactor*D44*F44 -> 0.03218567
A45: hyna:BTC | B45: hyna | C45: 0.1111 | D45: 1.1111 | E45: 0.900009 | F45: 0.099991 | G45: N/A | I45: =CoreBpsBlended*GrowthModeFactor*D45*E45 -> 0.2897 | J45: =CoreBpsBlended*D45*E45 -> 2.897 | K45: =CoreBpsBlended*GrowthModeFactor*D45*F45 -> 0.03218567
A46: hyna:DOGE | B46: hyna | C46: 0.1111 | D46: 1.1111 | E46: 0.900009 | F46: 0.099991 | G46: N/A | I46: =CoreBpsBlended*GrowthModeFactor*D46*E46 -> 0.2897 | J46: =CoreBpsBlended*D46*E46 -> 2.897 | K46: =CoreBpsBlended*GrowthModeFactor*D46*F46 -> 0.03218567
A47: hyna:ENA | B47: hyna | C47: 0.1111 | D47: 1.1111 | E47: 0.900009 | F47: 0.099991 | G47: N/A | I47: =CoreBpsBlended*GrowthModeFactor*D47*E47 -> 0.2897 | J47: =CoreBpsBlended*D47*E47 -> 2.897 | K47: =CoreBpsBlended*GrowthModeFactor*D47*F47 -> 0.03218567
A48: hyna:ETH | B48: hyna | C48: 0.1111 | D48: 1.1111 | E48: 0.900009 | F48: 0.099991 | G48: N/A | I48: =CoreBpsBlended*GrowthModeFactor*D48*E48 -> 0.2897 | J48: =CoreBpsBlended*D48*E48 -> 2.897 | K48: =CoreBpsBlended*GrowthModeFactor*D48*F48 -> 0.03218567
A49: hyna:FARTCOIN | B49: hyna | C49: 0.1111 | D49: 1.1111 | E49: 0.900009 | F49: 0.099991 | G49: N/A | I49: =CoreBpsBlended*GrowthModeFactor*D49*E49 -> 0.2897 | J49: =CoreBpsBlended*D49*E49 -> 2.897 | K49: =CoreBpsBlended*GrowthModeFactor*D49*F49 -> 0.03218567
... A57: hyna:PUMP | B57: hyna | C57: 0.1111 | D57: 1.1111 | E57: 0.900009 | F57: 0.099991 | G57: N/A | I57: =CoreBpsBlended*GrowthModeFactor*D57*E57 -> 0.2897 | J57: =CoreBpsBlended*D57*E57 -> 2.897 | K57: =CoreBpsBlended*GrowthModeFactor*D57*F57 -> 0.03218567
A58: hyna:SILVER | B58: hyna | C58: 0.1111 | D58: 1.1111 | E58: 0.900009 | F58: 0.099991 | G58: enabled | H58: 46094 | I58: =CoreBpsBlended*GrowthModeFactor*D58*E58 -> 0.2897 | J58: =CoreBpsBlended*D58*E58 -> 2.897 | K58: =CoreBpsBlended*GrowthModeFactor*D58*F58 -> 0.03218567
A59: hyna:SOL | B59: hyna | C59: 0.1111 | D59: 1.1111 | E59: 0.900009 | F59: 0.099991 | G59: N/A | I59: =CoreBpsBlended*GrowthModeFactor*D59*E59 -> 0.2897 | J59: =CoreBpsBlended*D59*E59 -> 2.897 | K59: =CoreBpsBlended*GrowthModeFactor*D59*F59 -> 0.03218567
A60: hyna:SUI | B60: hyna | C60: 0.1111 | D60: 1.1111 | E60: 0.900009 | F60: 0.099991 | G60: N/A | I60: =CoreBpsBlended*GrowthModeFactor*D60*E60 -> 0.2897 | J60: =CoreBpsBlended*D60*E60 -> 2.897 | K60: =CoreBpsBlended*GrowthModeFactor*D60*F60 -> 0.03218567
A61: hyna:XMR | B61: hyna | C61: 0.1111 | D61: 1.1111 | E61: 0.900009 | F61: 0.099991 | G61: N/A | I61: =CoreBpsBlended*GrowthModeFactor*D61*E61 -> 0.2897 | J61: =CoreBpsBlended*D61*E61 -> 2.897 | K61: =CoreBpsBlended*GrowthModeFactor*D61*F61 -> 0.03218567
A62: hyna:XPL | B62: hyna | C62: 0.1111 | D62: 1.1111 | E62: 0.900009 | F62: 0.099991 | G62: N/A | I62: =CoreBpsBlended*GrowthModeFactor*D62*E62 -> 0.2897 | J62: =CoreBpsBlended*D62*E62 -> 2.897 | K62: =CoreBpsBlended*GrowthModeFactor*D62*F62 -> 0.03218567
A63: hyna:XRP | B63: hyna | C63: 0.1111 | D63: 1.1111 | E63: 0.900009 | F63: 0.099991 | G63: N/A | I63: =CoreBpsBlended*GrowthModeFactor*D63*E63 -> 0.2897 | J63: =CoreBpsBlended*D63*E63 -> 2.897 | K63: =CoreBpsBlended*GrowthModeFactor*D63*F63 -> 0.03218567
A64: hyna:ZEC | B64: hyna | C64: 0.1111 | D64: 1.1111 | E64: 0.900009 | F64: 0.099991 | G64: N/A | I64: =CoreBpsBlended*GrowthModeFactor*D64*E64 -> 0.2897 | J64: =CoreBpsBlended*D64*E64 -> 2.897 | K64: =CoreBpsBlended*GrowthModeFactor*D64*F64 -> 0.03218567
A65: km:AAPL | B65: km | C65: 1 | D65: 2 | E65: 0.5 | F65: 0.5 | G65: enabled | H65: 46051 | I65: =CoreBpsBlended*GrowthModeFactor*D65*E65 -> 0.2897 | J65: =CoreBpsBlended*D65*E65 -> 2.897 | K65: =CoreBpsBlended*GrowthModeFactor*D65*F65 -> 0.2897
A66: km:BABA | B66: km | C66: 1 | D66: 2 | E66: 0.5 | F66: 0.5 | G66: enabled | H66: 46037 | I66: =CoreBpsBlended*GrowthModeFactor*D66*E66 -> 0.2897 | J66: =CoreBpsBlended*D66*E66 -> 2.897 | K66: =CoreBpsBlended*GrowthModeFactor*D66*F66 -> 0.2897
A67: km:BMNR | B67: km | C67: 1 | D67: 2 | E67: 0.5 | F67: 0.5 | G67: N/A | H67: 46123 | I67: =CoreBpsBlended*GrowthModeFactor*D67*E67 -> 0.2897 | J67: =CoreBpsBlended*D67*E67 -> 2.897 | K67: =CoreBpsBlended*GrowthModeFactor*D67*F67 -> 0.2897
A68: km:EUR | B68: km | C68: 1 | D68: 2 | E68: 0.5 | F68: 0.5 | G68: enabled | H68: 46135 | I68: =CoreBpsBlended*GrowthModeFactor*D68*E68 -> 0.2897 | J68: =CoreBpsBlended*D68*E68 -> 2.897 | K68: =CoreBpsBlended*GrowthModeFactor*D68*F68 -> 0.2897
A69: km:GLDMINE | B69: km | C69: 1 | D69: 2 | E69: 0.5 | F69: 0.5 | G69: enabled | H69: 46078 | I69: =CoreBpsBlended*GrowthModeFactor*D69*E69 -> 0.2897 | J69: =CoreBpsBlended*D69*E69 -> 2.897 | K69: =CoreBpsBlended*GrowthModeFactor*D69*F69 -> 0.2897
A70: km:GOLD | B70: km | C70: 1 | D70: 2 | E70: 0.5 | F70: 0.5 | G70: N/A | I70: =CoreBpsBlended*GrowthModeFactor*D70*E70 -> 0.2897 | J70: =CoreBpsBlended*D70*E70 -> 2.897 | K70: =CoreBpsBlended*GrowthModeFactor*D70*F70 -> 0.2897
A71: km:GOOGL | B71: km | C71: 1 | D71: 2 | E71: 0.5 | F71: 0.5 | G71: enabled | H71: 46051 | I71: =CoreBpsBlended*GrowthModeFactor*D71*E71 -> 0.2897 | J71: =CoreBpsBlended*D71*E71 -> 2.897 | K71: =CoreBpsBlended*GrowthModeFactor*D71*F71 -> 0.2897
A72: km:JPN225 | B72: km | C72: 1 | D72: 2 | E72: 0.5 | F72: 0.5 | G72: N/A | I72: =CoreBpsBlended*GrowthModeFactor*D72*E72 -> 0.2897 | J72: =CoreBpsBlended*D72*E72 -> 2.897 | K72: =CoreBpsBlended*GrowthModeFactor*D72*F72 -> 0.2897
A73: km:MU | B73: km | C73: 1 | D73: 2 | E73: 0.5 | F73: 0.5 | G73: enabled | H73: 46077 | I73: =CoreBpsBlended*GrowthModeFactor*D73*E73 -> 0.2897 | J73: =CoreBpsBlended*D73*E73 -> 2.897 | K73: =CoreBpsBlended*GrowthModeFactor*D73*F73 -> 0.2897
A74: km:NVDA | B74: km | C74: 1 | D74: 2 | E74: 0.5 | F74: 0.5 | G74: enabled | H74: 46064 | I74: =CoreBpsBlended*GrowthModeFactor*D74*E74 -> 0.2897 | J74: =CoreBpsBlended*D74*E74 -> 2.897 | K74: =CoreBpsBlended*GrowthModeFactor*D74*F74 -> 0.2897
A75: km:PLTR | B75: km | C75: 1 | D75: 2 | E75: 0.5 | F75: 0.5 | G75: enabled | H75: 46077 | I75: =CoreBpsBlended*GrowthModeFactor*D75*E75 -> 0.2897 | J75: =CoreBpsBlended*D75*E75 -> 2.897 | K75: =CoreBpsBlended*GrowthModeFactor*D75*F75 -> 0.2897
A76: km:RTX | B76: km | C76: 1 | D76: 2 | E76: 0.5 | F76: 0.5 | G76: enabled | H76: 46091 | I76: =CoreBpsBlended*GrowthModeFactor*D76*E76 -> 0.2897 | J76: =CoreBpsBlended*D76*E76 -> 2.897 | K76: =CoreBpsBlended*GrowthModeFactor*D76*F76 -> 0.2897
A77: km:SEMI | B77: km | C77: 1 | D77: 2 | E77: 0.5 | F77: 0.5 | G77: enabled | H77: 46078 | I77: =CoreBpsBlended*GrowthModeFactor*D77*E77 -> 0.2897 | J77: =CoreBpsBlended*D77*E77 -> 2.897 | K77: =CoreBpsBlended*GrowthModeFactor*D77*F77 -> 0.2897
A78: km:SILVER | B78: km | C78: 1 | D78: 2 | E78: 0.5 | F78: 0.5 | G78: enabled | H78: 46050 | I78: =CoreBpsBlended*GrowthModeFactor*D78*E78 -> 0.2897 | J78: =CoreBpsBlended*D78*E78 -> 2.897 | K78: =CoreBpsBlended*GrowthModeFactor*D78*F78 -> 0.2897
A79: km:SMALL2000 | B79: km | C79: 1 | D79: 2 | E79: 0.5 | F79: 0.5 | G79: enabled | H79: 46029 | I79: =CoreBpsBlended*GrowthModeFactor*D79*E79 -> 0.2897 | J79: =CoreBpsBlended*D79*E79 -> 2.897 | K79: =CoreBpsBlended*GrowthModeFactor*D79*F79 -> 0.2897
A80: km:TENCENT | B80: km | C80: 1 | D80: 2 | E80: 0.5 | F80: 0.5 | G80: enabled | H80: 46121 | I80: =CoreBpsBlended*GrowthModeFactor*D80*E80 -> 0.2897 | J80: =CoreBpsBlended*D80*E80 -> 2.897 | K80: =CoreBpsBlended*GrowthModeFactor*D80*F80 -> 0.2897
A81: km:TSLA | B81: km | C81: 1 | D81: 2 | E81: 0.5 | F81: 0.5 | G81: enabled | H81: 46038 | I81: =CoreBpsBlended*GrowthModeFactor*D81*E81 -> 0.2897 | J81: =CoreBpsBlended*D81*E81 -> 2.897 | K81: =CoreBpsBlended*GrowthModeFactor*D81*F81 -> 0.2897
A82: km:US500 | B82: km | C82: 1 | D82: 2 | E82: 0.5 | F82: 0.5 | G82: enabled | H82: 46029 | I82: =CoreBpsBlended*GrowthModeFactor*D82*E82 -> 0.2897 | J82: =CoreBpsBlended*D82*E82 -> 2.897 | K82: =CoreBpsBlended*GrowthModeFactor*D82*F82 -> 0.2897
A83: km:USBOND | B83: km | C83: 1 | D83: 2 | E83: 0.5 | F83: 0.5 | G83: enabled | H83: 46043 | I83: =CoreBpsBlended*GrowthModeFactor*D83*E83 -> 0.2897 | J83: =CoreBpsBlended*D83*E83 -> 2.897 | K83: =CoreBpsBlended*GrowthModeFactor*D83*F83 -> 0.2897
A84: km:USENERGY | B84: km | C84: 1 | D84: 2 | E84: 0.5 | F84: 0.5 | G84: enabled | H84: 46057 | I84: =CoreBpsBlended*GrowthModeFactor*D84*E84 -> 0.2897 | J84: =CoreBpsBlended*D84*E84 -> 2.897 | K84: =CoreBpsBlended*GrowthModeFactor*D84*F84 -> 0.2897
... A87: km:XIAOMI | B87: km | C87: 1 | D87: 2 | E87: 0.5 | F87: 0.5 | G87: enabled | H87: 46121 | I87: =CoreBpsBlended*GrowthModeFactor*D87*E87 -> 0.2897 | J87: =CoreBpsBlended*D87*E87 -> 2.897 | K87: =CoreBpsBlended*GrowthModeFactor*D87*F87 -> 0.2897
A88: para:BTCD | B88: para | C88: 1 | D88: 2 | E88: 0.5 | F88: 0.5 | G88: N/A | I88: =CoreBpsBlended*GrowthModeFactor*D88*E88 -> 0.2897 | J88: =CoreBpsBlended*D88*E88 -> 2.897 | K88: =CoreBpsBlended*GrowthModeFactor*D88*F88 -> 0.2897
A89: para:H100 | B89: para | C89: 1 | D89: 2 | E89: 0.5 | F89: 0.5 | G89: N/A | I89: =CoreBpsBlended*GrowthModeFactor*D89*E89 -> 0.2897 | J89: =CoreBpsBlended*D89*E89 -> 2.897 | K89: =CoreBpsBlended*GrowthModeFactor*D89*F89 -> 0.2897
A90: para:OTHERS | B90: para | C90: 1 | D90: 2 | E90: 0.5 | F90: 0.5 | G90: N/A | I90: =CoreBpsBlended*GrowthModeFactor*D90*E90 -> 0.2897 | J90: =CoreBpsBlended*D90*E90 -> 2.897 | K90: =CoreBpsBlended*GrowthModeFactor*D90*F90 -> 0.2897
A91: para:TOTAL2 | B91: para | C91: 1 | D91: 2 | E91: 0.5 | F91: 0.5 | G91: N/A | I91: =CoreBpsBlended*GrowthModeFactor*D91*E91 -> 0.2897 | J91: =CoreBpsBlended*D91*E91 -> 2.897 | K91: =CoreBpsBlended*GrowthModeFactor*D91*F91 -> 0.2897
A92: vntl:ANTHROPIC | B92: vntl | C92: 1 | D92: 2 | E92: 0.5 | F92: 0.5 | G92: N/A | I92: =CoreBpsBlended*GrowthModeFactor*D92*E92 -> 0.2897 | J92: =CoreBpsBlended*D92*E92 -> 2.897 | K92: =CoreBpsBlended*GrowthModeFactor*D92*F92 -> 0.2897
A93: vntl:BIOTECH | B93: vntl | C93: 1 | D93: 2 | E93: 0.5 | F93: 0.5 | G93: enabled | H93: 46056 | I93: =CoreBpsBlended*GrowthModeFactor*D93*E93 -> 0.2897 | J93: =CoreBpsBlended*D93*E93 -> 2.897 | K93: =CoreBpsBlended*GrowthModeFactor*D93*F93 -> 0.2897
A94: vntl:DEFENSE | B94: vntl | C94: 1 | D94: 2 | E94: 0.5 | F94: 0.5 | G94: enabled | H94: 46056 | I94: =CoreBpsBlended*GrowthModeFactor*D94*E94 -> 0.2897 | J94: =CoreBpsBlended*D94*E94 -> 2.897 | K94: =CoreBpsBlended*GrowthModeFactor*D94*F94 -> 0.2897
A95: vntl:ENERGY | B95: vntl | C95: 1 | D95: 2 | E95: 0.5 | F95: 0.5 | G95: enabled | H95: 46056 | I95: =CoreBpsBlended*GrowthModeFactor*D95*E95 -> 0.2897 | J95: =CoreBpsBlended*D95*E95 -> 2.897 | K95: =CoreBpsBlended*GrowthModeFactor*D95*F95 -> 0.2897
A96: vntl:GOLDJM | B96: vntl | C96: 1 | D96: 2 | E96: 0.5 | F96: 0.5 | G96: N/A | I96: =CoreBpsBlended*GrowthModeFactor*D96*E96 -> 0.2897 | J96: =CoreBpsBlended*D96*E96 -> 2.897 | K96: =CoreBpsBlended*GrowthModeFactor*D96*F96 -> 0.2897
A97: vntl:INFOTECH | B97: vntl | C97: 1 | D97: 2 | E97: 0.5 | F97: 0.5 | G97: enabled | H97: 46056 | I97: =CoreBpsBlended*GrowthModeFactor*D97*E97 -> 0.2897 | J97: =CoreBpsBlended*D97*E97 -> 2.897 | K97: =CoreBpsBlended*GrowthModeFactor*D97*F97 -> 0.2897
A98: vntl:MAG7 | B98: vntl | C98: 1 | D98: 2 | E98: 0.5 | F98: 0.5 | G98: enabled | H98: 46056 | I98: =CoreBpsBlended*GrowthModeFactor*D98*E98 -> 0.2897 | J98: =CoreBpsBlended*D98*E98 -> 2.897 | K98: =CoreBpsBlended*GrowthModeFactor*D98*F98 -> 0.2897
A99: vntl:NUCLEAR | B99: vntl | C99: 1 | D99: 2 | E99: 0.5 | F99: 0.5 | G99: enabled | H99: 46056 | I99: =CoreBpsBlended*GrowthModeFactor*D99*E99 -> 0.2897 | J99: =CoreBpsBlended*D99*E99 -> 2.897 | K99: =CoreBpsBlended*GrowthModeFactor*D99*F99 -> 0.2897
A100: vntl:OPENAI | B100: vntl | C100: 1 | D100: 2 | E100: 0.5 | F100: 0.5 | G100: N/A | I100: =CoreBpsBlended*GrowthModeFactor*D100*E100 -> 0.2897 | J100: =CoreBpsBlended*D100*E100 -> 2.897 | K100: =CoreBpsBlended*GrowthModeFactor*D100*F100 -> 0.2897
A101: vntl:ROBOT | B101: vntl | C101: 1 | D101: 2 | E101: 0.5 | F101: 0.5 | G101: enabled | H101: 46056 | I101: =CoreBpsBlended*GrowthModeFactor*D101*E101 -> 0.2897 | J101: =CoreBpsBlended*D101*E101 -> 2.897 | K101: =CoreBpsBlended*GrowthModeFactor*D101*F101 -> 0.2897
A102: vntl:SEMIS | B102: vntl | C102: 1 | D102: 2 | E102: 0.5 | F102: 0.5 | G102: enabled | H102: 46056 | I102: =CoreBpsBlended*GrowthModeFactor*D102*E102 -> 0.2897 | J102: =CoreBpsBlended*D102*E102 -> 2.897 | K102: =CoreBpsBlended*GrowthModeFactor*D102*F102 -> 0.2897
A103: vntl:SILVERJM | B103: vntl | C103: 1 | D103: 2 | E103: 0.5 | F103: 0.5 | G103: N/A | I103: =CoreBpsBlended*GrowthModeFactor*D103*E103 -> 0.2897 | J103: =CoreBpsBlended*D103*E103 -> 2.897 | K103: =CoreBpsBlended*GrowthModeFactor*D103*F103 -> 0.2897
A104: vntl:SOY | B104: vntl | C104: 1 | D104: 2 | E104: 0.5 | F104: 0.5 | G104: enabled | H104: 46132 | I104: =CoreBpsBlended*GrowthModeFactor*D104*E104 -> 0.2897 | J104: =CoreBpsBlended*D104*E104 -> 2.897 | K104: =CoreBpsBlended*GrowthModeFactor*D104*F104 -> 0.2897
A105: vntl:SPACEX | B105: vntl | C105: 1 | D105: 2 | E105: 0.5 | F105: 0.5 | G105: N/A | I105: =CoreBpsBlended*GrowthModeFactor*D105*E105 -> 0.2897 | J105: =CoreBpsBlended*D105*E105 -> 2.897 | K105: =CoreBpsBlended*GrowthModeFactor*D105*F105 -> 0.2897
A106: vntl:WHEAT | B106: vntl | C106: 1 | D106: 2 | E106: 0.5 | F106: 0.5 | G106: enabled | H106: 46119 | I106: =CoreBpsBlended*GrowthModeFactor*D106*E106 -> 0.2897 | J106: =CoreBpsBlended*D106*E106 -> 2.897 | K106: =CoreBpsBlended*GrowthModeFactor*D106*F106 -> 0.2897
A107: xyz:AAPL | B107: xyz | C107: 1 | D107: 2 | E107: 0.5 | F107: 0.5 | G107: enabled | H107: 45984 | I107: =CoreBpsBlended*GrowthModeFactor*D107*E107 -> 0.2897 | J107: =CoreBpsBlended*D107*E107 -> 2.897 | K107: =CoreBpsBlended*GrowthModeFactor*D107*F107 -> 0.2897
A108: xyz:ALUMINIUM | B108: xyz | C108: 1 | D108: 2 | E108: 0.5 | F108: 0.5 | G108: enabled | H108: 46043 | I108: =CoreBpsBlended*GrowthModeFactor*D108*E108 -> 0.2897 | J108: =CoreBpsBlended*D108*E108 -> 2.897 | K108: =CoreBpsBlended*GrowthModeFactor*D108*F108 -> 0.2897
A109: xyz:AMD | B109: xyz | C109: 1 | D109: 2 | E109: 0.5 | F109: 0.5 | G109: enabled | H109: 45984 | I109: =CoreBpsBlended*GrowthModeFactor*D109*E109 -> 0.2897 | J109: =CoreBpsBlended*D109*E109 -> 2.897 | K109: =CoreBpsBlended*GrowthModeFactor*D109*F109 -> 0.2897
A110: xyz:AMZN | B110: xyz | C110: 1 | D110: 2 | E110: 0.5 | F110: 0.5 | G110: enabled | H110: 45984 | I110: =CoreBpsBlended*GrowthModeFactor*D110*E110 -> 0.2897 | J110: =CoreBpsBlended*D110*E110 -> 2.897 | K110: =CoreBpsBlended*GrowthModeFactor*D110*F110 -> 0.2897
...

Sheet HIP-3 by Category
A1: HIP-3 Daily — Volume & Modeled HL Slice by Asset Category
A2: Volume from Hyperliquid info API candleSnapshot per asset; HL slice modeled per growth-mode-aware formula.
A4: VOLUME BY CATEGORY ($)
A5: Date | B5: Agriculture | C5: Bonds | D5: Crypto | E5: Energy | F5: Equities — Crypto-related | G5: Equities — Single Name | H5: Equity Indices/ETF | I5: FX | J5: Industrial Metals | K5: Pre-IPO / Private | L5: Precious Metals | M5: Total HIP-3
A6: 45943 | B6: 0 | C6: 0 | D6: 0 | E6: 0 | F6: 0 | G6: 0 | H6: 24137313 | I6: 0 | J6: 0 | K6: 0 | L6: 0 | M6: =SUM(B6:L6) -> 24137313
A7: 45944 | B7: 0 | C7: 0 | D7: 0 | E7: 0 | F7: 0 | G7: 0 | H7: 21893628 | I7: 0 | J7: 0 | K7: 0 | L7: 0 | M7: =SUM(B7:L7) -> 21893628
A8: 45945 | B8: 0 | C8: 0 | D8: 0 | E8: 0 | F8: 0 | G8: 0 | H8: 20602638 | I8: 0 | J8: 0 | K8: 0 | L8: 0 | M8: =SUM(B8:L8) -> 20602638
A9: 45946 | B9: 0 | C9: 0 | D9: 0 | E9: 0 | F9: 0 | G9: 0 | H9: 19139744 | I9: 0 | J9: 0 | K9: 0 | L9: 0 | M9: =SUM(B9:L9) -> 19139744
A10: 45947 | B10: 0 | C10: 0 | D10: 0 | E10: 0 | F10: 0 | G10: 0 | H10: 15100795 | I10: 0 | J10: 0 | K10: 0 | L10: 0 | M10: =SUM(B10:L10) -> 15100795
A11: 45948 | B11: 0 | C11: 0 | D11: 0 | E11: 0 | F11: 0 | G11: 0 | H11: 6243638.8 | I11: 0 | J11: 0 | K11: 0 | L11: 0 | M11: =SUM(B11:L11) -> 6243638.8
A12: 45949 | B12: 0 | C12: 0 | D12: 0 | E12: 0 | F12: 0 | G12: 0 | H12: 7838676.4 | I12: 0 | J12: 0 | K12: 0 | L12: 0 | M12: =SUM(B12:L12) -> 7838676.4
A13: 45950 | B13: 0 | C13: 0 | D13: 0 | E13: 0 | F13: 0 | G13: 0 | H13: 10597513 | I13: 0 | J13: 0 | K13: 0 | L13: 0 | M13: =SUM(B13:L13) -> 10597513
A14: 45951 | B14: 0 | C14: 0 | D14: 0 | E14: 0 | F14: 0 | G14: 0 | H14: 23304373 | I14: 0 | J14: 0 | K14: 0 | L14: 0 | M14: =SUM(B14:L14) -> 23304373
A15: 45952 | B15: 0 | C15: 0 | D15: 0 | E15: 0 | F15: 0 | G15: 0 | H15: 36702797 | I15: 0 | J15: 0 | K15: 0 | L15: 0 | M15: =SUM(B15:L15) -> 36702797
A16: 45953 | B16: 0 | C16: 0 | D16: 0 | E16: 0 | F16: 0 | G16: 0 | H16: 30181937 | I16: 0 | J16: 0 | K16: 0 | L16: 0 | M16: =SUM(B16:L16) -> 30181937
A17: 45954 | B17: 0 | C17: 0 | D17: 0 | E17: 0 | F17: 0 | G17: 0 | H17: 27291720 | I17: 0 | J17: 0 | K17: 0 | L17: 0 | M17: =SUM(B17:L17) -> 27291720
... A225: 46162 | B225: 87327.911 | C225: 9993.4427 | D225: 2115097.8 | E225: 39845360 | F225: 2922661.3 | G225: 46698955 | H225: 99407571 | I225: 414539.84 | J225: 608633.1 | K225: 896499.64 | L225: 52653089 | M225: =SUM(B225:L225) -> 2.4565973e+08
A228: MODELED HL SLICE BY CATEGORY ($)
A229: Date | B229: Agriculture | C229: Bonds | D229: Crypto | E229: Energy | F229: Equities — Crypto-related | G229: Equities — Single Name | H229: Equity Indices/ETF | I229: FX | J229: Industrial Metals | K229: Pre-IPO / Private | L229: Precious Metals | M229: Total HL HIP-3 Slice
A230: 45943 | B230: 0 | C230: 0 | D230: 0 | E230: 0 | F230: 0 | G230: 0 | H230: 6992.5795 | I230: 0 | J230: 0 | K230: 0 | L230: 0 | M230: =SUM(B230:L230) -> 6992.5795
A231: 45944 | B231: 0 | C231: 0 | D231: 0 | E231: 0 | F231: 0 | G231: 0 | H231: 6342.584 | I231: 0 | J231: 0 | K231: 0 | L231: 0 | M231: =SUM(B231:L231) -> 6342.584
A232: 45945 | B232: 0 | C232: 0 | D232: 0 | E232: 0 | F232: 0 | G232: 0 | H232: 5968.5843 | I232: 0 | J232: 0 | K232: 0 | L232: 0 | M232: =SUM(B232:L232) -> 5968.5843
A233: 45946 | B233: 0 | C233: 0 | D233: 0 | E233: 0 | F233: 0 | G233: 0 | H233: 5544.7837 | I233: 0 | J233: 0 | K233: 0 | L233: 0 | M233: =SUM(B233:L233) -> 5544.7837
A234: 45947 | B234: 0 | C234: 0 | D234: 0 | E234: 0 | F234: 0 | G234: 0 | H234: 4374.7005 | I234: 0 | J234: 0 | K234: 0 | L234: 0 | M234: =SUM(B234:L234) -> 4374.7005
A235: 45948 | B235: 0 | C235: 0 | D235: 0 | E235: 0 | F235: 0 | G235: 0 | H235: 1808.7822 | I235: 0 | J235: 0 | K235: 0 | L235: 0 | M235: =SUM(B235:L235) -> 1808.7822
A236: 45949 | B236: 0 | C236: 0 | D236: 0 | E236: 0 | F236: 0 | G236: 0 | H236: 2270.8645 | I236: 0 | J236: 0 | K236: 0 | L236: 0 | M236: =SUM(B236:L236) -> 2270.8645
A237: 45950 | B237: 0 | C237: 0 | D237: 0 | E237: 0 | F237: 0 | G237: 0 | H237: 3070.0995 | I237: 0 | J237: 0 | K237: 0 | L237: 0 | M237: =SUM(B237:L237) -> 3070.0995
A238: 45951 | B238: 0 | C238: 0 | D238: 0 | E238: 0 | F238: 0 | G238: 0 | H238: 6751.2769 | I238: 0 | J238: 0 | K238: 0 | L238: 0 | M238: =SUM(B238:L238) -> 6751.2769
A239: 45952 | B239: 0 | C239: 0 | D239: 0 | E239: 0 | F239: 0 | G239: 0 | H239: 10632.8 | I239: 0 | J239: 0 | K239: 0 | L239: 0 | M239: =SUM(B239:L239) -> 10632.8
A240: 45953 | B240: 0 | C240: 0 | D240: 0 | E240: 0 | F240: 0 | G240: 0 | H240: 8743.7071 | I240: 0 | J240: 0 | K240: 0 | L240: 0 | M240: =SUM(B240:L240) -> 8743.7071
A241: 45954 | B241: 0 | C241: 0 | D241: 0 | E241: 0 | F241: 0 | G241: 0 | H241: 7906.4112 | I241: 0 | J241: 0 | K241: 0 | L241: 0 | M241: =SUM(B241:L241) -> 7906.4112
... A449: 46162 | B449: 2.5298896 | C449: 0.28951003 | D449: 336.80203 | E449: 1154.3201 | F449: 195.09318 | G449: 1352.8687 | H449: 2879.8373 | I449: 12.009219 | J449: 17.632101 | K449: 64.08414 | L449: 4368.8672 | M449: =SUM(B449:L449) -> 10384.333

Sheet Reconciliation
A1: Reconciliation & Cross-Source Checks (formula-driven)
A4: --- DEFILLAMA COVERAGE ---
A5: First date with DefiLlama fees | B5: ='Daily Master'!A588 -> 45649
A6: Last date with DefiLlama fees | B6: ='Daily Master'!A1100 -> 46161
A7: Number of days | B7: =1100-588+1 -> 513
A9: --- PERPS IDENTITY: Perp fees = Perp rev + Perp supplyside ---
A10: Cum perp fees ($) | B10: =SUM('Daily Master'!H588:H1100) -> 1204675054
A11: Cum perp revenue ($) | B11: =SUM('Daily Master'!O588:O1100) -> 1117945937
A12: Cum perp supplyside ($) | B12: =SUM('Daily Master'!Y588:Y1100) -> 86729113
A13: Diff (fees − rev − supply) | B13: =SUM('Daily Master'!H588:H1100)-SUM('Daily Master'!O588:O1100)-SUM('Daily Master'!Y588:Y1100) -> 4
A15: --- SPOT IDENTITY: Spot fees = Spot rev + Spot supplyside ---
A16: Cum spot fees ($) | B16: =SUM('Daily Master'!I588:I1100) -> 56270819
A17: Cum spot revenue ($) | B17: =SUM('Daily Master'!P588:P1100) -> 43695138
A18: Cum spot supplyside ($) | B18: =SUM('Daily Master'!Z588:Z1100) -> 12575680
A19: Diff (fees − rev − supply) | B19: =SUM('Daily Master'!I588:I1100)-SUM('Daily Master'!P588:P1100)-SUM('Daily Master'!Z588:Z1100) -> 1
A21: --- CORE IDENTITY: Total fees = Revenue + Supplyside ---
A22: Sum of daily identity diffs | B22: =SUM('Daily Master'!AE588:AE1100) -> 5
A23: -> Should be ≈ 0 (integer rounding only)
A25: --- AF BUYBACK = HOLDERS REVENUE ---
A26: Sum of (revenue − buyback) diffs | B26: =SUM('Daily Master'!AF588:AF1100) -> 0
A27: -> Should be 0 (same DL metric)
A29: --- HLP FORMULA vs DL ---
A30: Cum formula HLP slice ($) | B30: =SUM('Daily Master'!S588:S1100) -> 22746844
A31: Cum DL reported HLP slice ($) | B31: =SUM('Daily Master'!T588:T1100) -> 22189875
A32: Diff ($) | B32: =SUM('Daily Master'!S588:S1100)-SUM('Daily Master'!T588:T1100) -> 556968.68
A33: -> Small diff explained by gaps in DL HLP coverage on early dates
A35: --- SUPPLYSIDE BREAKDOWN ---
A36: Cum DL total supplyside ($) | B36: =SUM('Daily Master'!Y588:Y1100)+SUM('Daily Master'!Z588:Z1100) -> 99304793
A37: Cum HLP depositors slice | B37: =SUM('Daily Master'!T588:T1100) -> 22189875
A38: Cum Builder Code Distribution (perp) [FROM FORMULA] | B38: =SUM('Daily Master'!V588:V1100) -> 64744542
A39: Cum Unit Revenue (spot) [FROM FORMULA] | B39: =SUM('Daily Master'!W588:W1100) -> 11813407
A40: Check sum: HLP + Builders + Unit | B40: =SUM('Daily Master'!T588:T1100)+SUM('Daily Master'!V588:V1100)+SUM('Daily Master'!W588:W1100) -> 98747824
A41: Diff to total supplyside (should ≈ 0) | B41: =(SUM('Daily Master'!Y588:Y1100)+SUM('Daily Master'!Z588:Z1100))-(SUM('Daily Master'!T588:T1100)+SUM('Daily Master'!V588:V1100)+SUM('Daily Master'!W588:W1100)) -> 556968.68
A43: --- BUILDER CODES CROSS-CHECK ---
A44: Cum builder codes (derived from DL) | B44: =SUM('Daily Master'!V588:V1100) -> 64744542
A45: Cross-ref: Dwellir blog (Jan 2026) reported $40M+ since launch
A46: Cross-ref: Hyperdash (Jan 2026): "top builders incl Based/Phantom/PVP earned $31M+"
A47: Builder codes as % of perp fees | B47: =SUM('Daily Master'!V588:V1100)/SUM('Daily Master'!H588:H1100) -> 0.053744403
A49: --- HYPURRSCAN CROSS-CHECK ---
A50: Cum DL revenue | B50: =SUM('Daily Master'!Q588:Q1100) -> 1161641075
A51: Cum HP total fees | B51: =SUM('Daily Master'!AG588:AG1100) -> 1.0682216e+09
A52: HP/DL ratio (median = ~92%) | B52: =SUM('Daily Master'!AG588:AG1100)/SUM('Daily Master'!Q588:Q1100) -> 0.91957971
A54: --- BUYBACKS ---
A55: Cum HYPE bought (#) | B55: =SUM('Daily Master'!AD588:AD1100) -> 36433808
A56: Cum AF buyback $ | B56: =SUM('Daily Master'!AA588:AA1100) -> 1161641075
A57: Cross-ref: Dec 2025 Defiant article reported ~37M HYPE bought since AF inception
A59: --- SUPPLY DYNAMICS ---
A60: Cum modeled HYPE issuance to stakers | B60: =SUM('Daily Master'!AK588:AK1100) -> 12987405
A61: Cum net HYPE supply change | B61: =SUM('Daily Master'!AM588:AM1100) -> -23446403
A62: -> Negative = net deflation

Sheet Sources & Methodology
A1: Sources & Methodology — v3 (CORRECTED)
A3: CORRECTIONS FROM v2
A4: 1. DL Hyperliquid Perps fees does NOT include the HIP-3 deployer's 50% slice. Only Hyperliquid's 1x retained slice is in there. The deployer's slice is tracked SEPARATELY in DefiLlama as individual protocols (tradeXYZ, Felix, Ventuals, HyENA, etc.).
A5: 2. The Perps supplyside line breaks down into: HLP slice + Builder Code Distribution (NOT HIP-3 deployer fees).
A6: 3. The Spot supplyside line breaks down into: HLP slice + Unit Protocol Revenue.
A7: 4. Builder codes (third-party frontend kickbacks like Phantom, Hyperdash, PVP.trade) are now broken out as a dedicated column.
A9: PRIMARY SOURCES
A10: 21Shares Dune query 6874521 (existing user file) | B10: Daily core + HIP-3 perp volume; cross-checked vs Hyperliquid info API (matches within 0.03%)
A11: DefiLlama Fees API | B11: https://api.llama.fi/summary/fees/hyperliquid?dataType={dailyFees|dailyRevenue|dailyHoldersRevenue|dailySupplySideRevenue}
A12: DefiLlama DEX volume | B12: https://api.llama.fi/summary/dexs/hyperliquid?dataType=dailyVolume — spot orderbook volume
A13: Hyperliquid Info API — perpDexs | B13: POST /info {"type":"perpDexs"} — HIP-3 dex list with deployerFeeScale
A14: Hyperliquid Info API — meta per dex | B14: POST /info {"type":"meta","dex":"<name>"} — per-asset growthMode + lastGrowthModeChangeTime
A15: Hyperliquid Info API — candleSnapshot | B15: Per-asset daily candles for HIP-3; HYPE/USDC spot price
A16: Hypurrscan API | B16: https://api.hypurrscan.io/fees — independent on-chain cumulative fees for cross-check
A17: Hyperliquid Fees doc | B17: https://hyperliquid.gitbook.io/hyperliquid-docs/trading/fees
A18: Hyperliquid Builder Codes doc | B18: https://hyperliquid.gitbook.io/hyperliquid-docs/trading/builder-codes
A19: Hyperliquid HIP-3 doc | B19: https://hyperliquid.gitbook.io/hyperliquid-docs/hyperliquid-improvement-proposals-hips/hip-3
A20: Hyperliquid HIP-4 doc | B20: https://hyperliquid.gitbook.io/hyperliquid-docs/hyperliquid-improvement-proposals-hips/hip-4-outcome-markets
A21: DefiLlama adapter source | B21: https://github.com/DefiLlama/dimension-adapters/blob/master/fees/hyperliquid-hlp.ts — flagged `doublecounted: true`
A23: CORRECTED FEE FLOW
A24: FOR CORE PERP MARKETS:
A25: trader_fee = base_taker_rate (tier-adjusted, often discounted by staking/referrals)
A26: Of that fee: builder_code (0-10 bps cap) → frontend if user opted in
A27: remainder × hlp_pct → HLP depositors (1% post Aug 31 2025, 3% before)
A28: remainder × (1 − hlp_pct) → AF (~99% to HYPE buybacks)
A30: FOR HIP-3 PERP MARKETS:
A31: trader_fee = base × scaleIfHip3 × growthModeFactor (0.1× if GM enabled)
A32: scaleIfHip3 = 2.0 for deployers with deployerFeeScale=1 (trade.xyz, Felix, Ventuals, Kinetiq, dreamcash, Paragon)
A33: = 1.111 for HyENA (deployerFeeScale=0.1111)
A34: Of that fee:
A35: Deployer (trade.xyz etc.) keeps: 50% (or 10% for HyENA)
... A106: 5. Hypurrscan vs DefiLlama daily fees agree to ~92% on median (snapshot-timing noise, not methodology disagreement).
