Workbook

Sheet Daily Model
A1: HYPERLIQUID (HYPE) — DAILY MODEL. Volumes -> Gross Fees -> Fee→Revenue bridge (−HLP, −Unit, −HIP-3/HIP-4 deployer; builder is on-top) -> Revenue per segment (sum = HyperCore = hyperscreener) -> + HyperEVM + Auction = Total Revenue. Then AF/supply & OTS. Daily 2024-11-30 → 2026-09-21. Hover headers for source. blue=ASXN/primary source · black=formula · green=derived, cross-check or SECONDARY-SOURCE fill · amber shading=NOT ASXN (spot volume: DefiLlama fill; revenue: DefiLlama pre-2025-03-20; categories: pre-2025-11-27 backfill) (revenue: DefiLlama pre-2025-03-20; team unlocks & the two supply-split columns: held flat after 2026-09-06).
B2: VOLUME ($) | F2: HIP-3 VOLUME BY CATEGORY ($) | N2: GROSS FEES ($) [user-paid] | S2: FEE → REVENUE BRIDGE [deductions, $] | AC2: REVENUE TO HYPERCORE ($) | AJ2: IMPLIED TAKE-RATE (bps) | AN2: OTHER REVENUE ($) | AQ2: ASSISTANCE FUND & SUPPLY | AZ2: OTS (Hyperliquid Strategies basis)
A3: Date | B3: Core Crypto Perp Vol ($) | C3: HIP-3 Perp Vol ($) | D3: Spot Vol ($) | E3: HIP-4 Vol ($) | F3: HIP-3 Commodities ($) | G3: HIP-3 Crypto ($) | H3: HIP-3 FX ($) | I3: HIP-3 Indices ($) | J3: HIP-3 Pre-IPO ($) | K3: HIP-3 Equities ($) | L3: HIP-3 Cat Total ($) | M3: Pro-rate Factor Applied | N3: Core Crypto Perp Fees ($) | O3: HIP-3 Gross Fees ($) | P3: Spot Fees incl Unit ($) | Q3: HIP-4 Fees ($) | R3: Total Gross Fees ($) | S3: HLP Rate | T3: (-) HLP on Core Perp ($) | U3: (-) HLP on HIP-3 ($) | V3: (-) HLP on Spot ($) | W3: (-) HLP on HIP-4 ($) | X3: (-) Unit Protocol Fees ($) | Y3: (-) HIP-3 Deployer Fees ($) | Z3: (-) HIP-4 Deployer Fees ($) | AA3: Total Deductions ($) | AB3: Builder Code Fees [on-top, not deducted] ($) | AC3: Core Crypto Perp Revenue ($) | AD3: HIP-3 Revenue ($) | AE3: Spot Revenue ($) | AF3: HIP-4 Revenue ($) | AG3: = HyperCore Revenue (model) ($) | AH3: HyperCore Revenue ($) | AI3: Accrual less Buyback ($) | AJ3: Core Perp Take-Rate (bps) | AK3: HIP-3 Take-Rate (bps) | AL3: Spot Take-Rate (bps) | AM3: HIP-4 Take-Rate (bps) | AN3: HyperEVM Burn ($) | AO3: Auction Burn ($) | AP3: Total Revenue ($) | AQ3: Revenue -> AF ($) | AR3: Buyback HYPE | AS3: Buyback Avg Price ($) | AT3: AF HYPE Balance | AU3: Staking Emissions (HYPE) | AV3: Fee Burn (HYPE) | AW3: Team Tokens Unlocked (HYPE) | AX3: HYPE Staked (M) | AY3: Implied Staking Yield | AZ3: (-) Future Emissions & CR (HYPE) | BA3: (-) Hyper Foundation (HYPE) | BB3: (-) Assistance Fund (HYPE) | BC3: (-) Community Grants (HYPE) | BD3: (-) HC&EVM Fee Burns (HYPE) | BE3: = OTS (HYPE) | BF3: Core Contributors Locked (M) | BG3: Circulating Token Supply (M) | BH3: OTS Value ($)
A4: 45626 | B4: 1927839627 | D4: 460835741 | S4: 0.03 | AJ4: =IF(OR(B4="",B4=0,N4=""),"",N4/B4*10000) | AK4: =IF(OR(C4="",C4=0),"",O4/C4*10000) | AL4: =IF(OR(D4="",D4=0),"",P4/D4*10000) | AM4: =IF(OR(E4="",E4=0),"",Q4/E4*10000) | AT4: 8714980.2 | AU4: 0 | AV4: 32364.464 | AY4: =IF(OR(AX4="",AX4=0,AU4=""),"",AU4*365/(AX4*1000000)) | AZ4: 0 | BA4: 60487233 | BB4: 8714980.2 | BC4: 2971663 | BD4: =1000000000-999967635.536+0.0000 | BE4: =1000000000-AZ4-BA4-BB4-BC4-BD4 | BF4: 238 | BG4: =BE4/1000000-BF4 | BH4: =BE4*8.64
A5: 45627 | B5: 2230952304 | D5: 382137710 | S5: 0.03 | AJ5: =IF(OR(B5="",B5=0,N5=""),"",N5/B5*10000) | AK5: =IF(OR(C5="",C5=0),"",O5/C5*10000) | AL5: =IF(OR(D5="",D5=0),"",P5/D5*10000) | AM5: =IF(OR(E5="",E5=0),"",Q5/E5*10000) | AT5: 9336088.4 | AU5: 0 | AV5: 10604.896 | AY5: =IF(OR(AX5="",AX5=0,AU5=""),"",AU5*365/(AX5*1000000)) | AZ5: 0 | BA5: 60487233 | BB5: 9336088.4 | BC5: 2971663 | BD5: =1000000000-999957030.64+0.0000 | BE5: =1000000000-AZ5-BA5-BB5-BC5-BD5 | BF5: 238 | BG5: =BE5/1000000-BF5 | BH5: =BE5*8.9
A6: 45628 | B6: 5333125841 | D6: 320571512 | S6: 0.03 | AJ6: =IF(OR(B6="",B6=0,N6=""),"",N6/B6*10000) | AK6: =IF(OR(C6="",C6=0),"",O6/C6*10000) | AL6: =IF(OR(D6="",D6=0),"",P6/D6*10000) | AM6: =IF(OR(E6="",E6=0),"",Q6/E6*10000) | AT6: 9336088.4 | AU6: 0 | AV6: 2916.6523 | AY6: =IF(OR(AX6="",AX6=0,AU6=""),"",AU6*365/(AX6*1000000)) | AZ6: 0 | BA6: 60487233 | BB6: 9336088.4 | BC6: 2971663 | BD6: =1000000000-999954113.9877+0.0000 | BE6: =1000000000-AZ6-BA6-BB6-BC6-BD6 | BF6: 238 | BG6: =BE6/1000000-BF6 | BH6: =BE6*8.66
A7: 45629 | B7: 4881981857 | D7: 302890343 | S7: 0.03 | AJ7: =IF(OR(B7="",B7=0,N7=""),"",N7/B7*10000) | AK7: =IF(OR(C7="",C7=0),"",O7/C7*10000) | AL7: =IF(OR(D7="",D7=0),"",P7/D7*10000) | AM7: =IF(OR(E7="",E7=0),"",Q7/E7*10000) | AT7: 9933598.1 | AU7: 0 | AV7: 3632.1998 | AY7: =IF(OR(AX7="",AX7=0,AU7=""),"",AU7*365/(AX7*1000000)) | AZ7: 0 | BA7: 60487233 | BB7: 9933598.1 | BC7: 2971663 | BD7: =1000000000-999950481.7879+0.0000 | BE7: =1000000000-AZ7-BA7-BB7-BC7-BD7 | BF7: 238 | BG7: =BE7/1000000-BF7 | BH7: =BE7*8.96
A8: 45630 | B8: 6225918535 | D8: 318696984 | S8: 0.03 | AJ8: =IF(OR(B8="",B8=0,N8=""),"",N8/B8*10000) | AK8: =IF(OR(C8="",C8=0),"",O8/C8*10000) | AL8: =IF(OR(D8="",D8=0),"",P8/D8*10000) | AM8: =IF(OR(E8="",E8=0),"",Q8/E8*10000) | AT8: 10009960 | AU8: 0 | AV8: 3743.7999 | AY8: =IF(OR(AX8="",AX8=0,AU8=""),"",AU8*365/(AX8*1000000)) | AZ8: 0 | BA8: 60487233 | BB8: 10009960 | BC8: 2971663 | BD8: =1000000000-999946737.988+0.0000 | BE8: =1000000000-AZ8-BA8-BB8-BC8-BD8 | BF8: 238 | BG8: =BE8/1000000-BF8 | BH8: =BE8*11.08
A9: 45631 | B9: 9789562819 | D9: 323114172 | S9: 0.03 | AJ9: =IF(OR(B9="",B9=0,N9=""),"",N9/B9*10000) | AK9: =IF(OR(C9="",C9=0),"",O9/C9*10000) | AL9: =IF(OR(D9="",D9=0),"",P9/D9*10000) | AM9: =IF(OR(E9="",E9=0),"",Q9/E9*10000) | AT9: 10009960 | AU9: 0 | AV9: 4041.2964 | AY9: =IF(OR(AX9="",AX9=0,AU9=""),"",AU9*365/(AX9*1000000)) | AZ9: 0 | BA9: 60487233 | BB9: 10009960 | BC9: 2971663 | BD9: =1000000000-999942696.6916+0.0000 | BE9: =1000000000-AZ9-BA9-BB9-BC9-BD9 | BF9: 238 | BG9: =BE9/1000000-BF9 | BH9: =BE9*11.4
A10: 45632 | B10: 7811474440 | D10: 218646771 | S10: 0.03 | AJ10: =IF(OR(B10="",B10=0,N10=""),"",N10/B10*10000) | AK10: =IF(OR(C10="",C10=0),"",O10/C10*10000) | AL10: =IF(OR(D10="",D10=0),"",P10/D10*10000) | AM10: =IF(OR(E10="",E10=0),"",Q10/E10*10000) | AT10: 10428491 | AU10: 0 | AV10: 3472.5047 | AY10: =IF(OR(AX10="",AX10=0,AU10=""),"",AU10*365/(AX10*1000000)) | AZ10: 0 | BA10: 60487233 | BB10: 10428491 | BC10: 2971663 | BD10: =1000000000-999939224.1869+0.0000 | BE10: =1000000000-AZ10-BA10-BB10-BC10-BD10 | BF10: 238 | BG10: =BE10/1000000-BF10 | BH10: =BE10*12.69
A11: 45633 | B11: 2862437941 | D11: 182104753 | S11: 0.03 | AJ11: =IF(OR(B11="",B11=0,N11=""),"",N11/B11*10000) | AK11: =IF(OR(C11="",C11=0),"",O11/C11*10000) | AL11: =IF(OR(D11="",D11=0),"",P11/D11*10000) | AM11: =IF(OR(E11="",E11=0),"",Q11/E11*10000) | AT11: 10428491 | AU11: 0 | AV11: 2255.2254 | AY11: =IF(OR(AX11="",AX11=0,AU11=""),"",AU11*365/(AX11*1000000)) | AZ11: 0 | BA11: 60487233 | BB11: 10428491 | BC11: 2971663 | BD11: =1000000000-999936968.9615+0.0000 | BE11: =1000000000-AZ11-BA11-BB11-BC11-BD11 | BF11: 238 | BG11: =BE11/1000000-BF11 | BH11: =BE11*13.83
A12: 45634 | B12: 3252798818 | D12: 136064768 | S12: 0.03 | AJ12: =IF(OR(B12="",B12=0,N12=""),"",N12/B12*10000) | AK12: =IF(OR(C12="",C12=0),"",O12/C12*10000) | AL12: =IF(OR(D12="",D12=0),"",P12/D12*10000) | AM12: =IF(OR(E12="",E12=0),"",Q12/E12*10000) | AT12: 10428491 | AU12: 0 | AV12: 1897.8347 | AY12: =IF(OR(AX12="",AX12=0,AU12=""),"",AU12*365/(AX12*1000000)) | AZ12: 0 | BA12: 60487233 | BB12: 10428491 | BC12: 2971663 | BD12: =1000000000-999935071.1268+0.0000 | BE12: =1000000000-AZ12-BA12-BB12-BC12-BD12 | BF12: 238 | BG12: =BE12/1000000-BF12 | BH12: =BE12*14.12
A13: 45635 | B13: 5306358932 | D13: 270676721 | S13: 0.03 | AJ13: =IF(OR(B13="",B13=0,N13=""),"",N13/B13*10000) | AK13: =IF(OR(C13="",C13=0),"",O13/C13*10000) | AL13: =IF(OR(D13="",D13=0),"",P13/D13*10000) | AM13: =IF(OR(E13="",E13=0),"",Q13/E13*10000) | AT13: 10654299 | AU13: 0 | AV13: 1284.1908 | AY13: =IF(OR(AX13="",AX13=0,AU13=""),"",AU13*365/(AX13*1000000)) | AZ13: 0 | BA13: 60487233 | BB13: 10654299 | BC13: 2971663 | BD13: =1000000000-999933786.9361+0.0000 | BE13: =1000000000-AZ13-BA13-BB13-BC13-BD13 | BF13: 238 | BG13: =BE13/1000000-BF13 | BH13: =BE13*14.02
A14: 45636 | B14: 10009953607 | D14: 208129108 | S14: 0.03 | AJ14: =IF(OR(B14="",B14=0,N14=""),"",N14/B14*10000) | AK14: =IF(OR(C14="",C14=0),"",O14/C14*10000) | AL14: =IF(OR(D14="",D14=0),"",P14/D14*10000) | AM14: =IF(OR(E14="",E14=0),"",Q14/E14*10000) | AT14: 10654299 | AU14: 0 | AV14: 2527.2104 | AY14: =IF(OR(AX14="",AX14=0,AU14=""),"",AU14*365/(AX14*1000000)) | AZ14: 0 | BA14: 60487233 | BB14: 10654299 | BC14: 2971663 | BD14: =1000000000-999931259.7256+0.0000 | BE14: =1000000000-AZ14-BA14-BB14-BC14-BD14 | BF14: 238 | BG14: =BE14/1000000-BF14 | BH14: =BE14*13.54
A15: 45637 | B15: 3979399218 | D15: 211797447 | S15: 0.03 | AJ15: =IF(OR(B15="",B15=0,N15=""),"",N15/B15*10000) | AK15: =IF(OR(C15="",C15=0),"",O15/C15*10000) | AL15: =IF(OR(D15="",D15=0),"",P15/D15*10000) | AM15: =IF(OR(E15="",E15=0),"",Q15/E15*10000) | AT15: 10654299 | AU15: 0 | AV15: 2003.998 | AY15: =IF(OR(AX15="",AX15=0,AU15=""),"",AU15*365/(AX15*1000000)) | AZ15: 0 | BA15: 60487233 | BB15: 10654299 | BC15: 2971663 | BD15: =1000000000-999929255.7277+0.0000 | BE15: =1000000000-AZ15-BA15-BB15-BC15-BD15 | BF15: 238 | BG15: =BE15/1000000-BF15 | BH15: =BE15*13.56
A16: 45638 | B16: 4839045908 | D16: 324908474 | S16: 0.03 | AJ16: =IF(OR(B16="",B16=0,N16=""),"",N16/B16*10000) | AK16: =IF(OR(C16="",C16=0),"",O16/C16*10000) | AL16: =IF(OR(D16="",D16=0),"",P16/D16*10000) | AM16: =IF(OR(E16="",E16=0),"",Q16/E16*10000) | AT16: 10654299 | AU16: 0 | AV16: 1932.7073 | AY16: =IF(OR(AX16="",AX16=0,AU16=""),"",AU16*365/(AX16*1000000)) | AZ16: 0 | BA16: 60487233 | BB16: 10654299 | BC16: 2971663 | BD16: =1000000000-999927323.0204+0.0000 | BE16: =1000000000-AZ16-BA16-BB16-BC16-BD16 | BF16: 238 | BG16: =BE16/1000000-BF16 | BH16: =BE16*16.11
A17: 45639 | B17: 4253319332 | D17: 334237923 | S17: 0.03 | AJ17: =IF(OR(B17="",B17=0,N17=""),"",N17/B17*10000) | AK17: =IF(OR(C17="",C17=0),"",O17/C17*10000) | AL17: =IF(OR(D17="",D17=0),"",P17/D17*10000) | AM17: =IF(OR(E17="",E17=0),"",Q17/E17*10000) | AT17: 10662922 | AU17: 0 | AV17: 2435.2699 | AY17: =IF(OR(AX17="",AX17=0,AU17=""),"",AU17*365/(AX17*1000000)) | AZ17: 0 | BA17: 60487233 | BB17: 10662922 | BC17: 2971663 | BD17: =1000000000-999924887.7505+0.0000 | BE17: =1000000000-AZ17-BA17-BB17-BC17-BD17 | BF17: 238 | BG17: =BE17/1000000-BF17 | BH17: =BE17*18.04
A18: 45640 | B18: 3170522123 | D18: 546075604 | S18: 0.03 | AJ18: =IF(OR(B18="",B18=0,N18=""),"",N18/B18*10000) | AK18: =IF(OR(C18="",C18=0),"",O18/C18*10000) | AL18: =IF(OR(D18="",D18=0),"",P18/D18*10000) | AM18: =IF(OR(E18="",E18=0),"",Q18/E18*10000) | AT18: 10761181 | AU18: 0 | AV18: 1602.2514 | AY18: =IF(OR(AX18="",AX18=0,AU18=""),"",AU18*365/(AX18*1000000)) | AZ18: 0 | BA18: 60487233 | BB18: 10761181 | BC18: 2971663 | BD18: =1000000000-999923285.4991+0.0000 | BE18: =1000000000-AZ18-BA18-BB18-BC18-BD18 | BF18: 238 | BG18: =BE18/1000000-BF18 | BH18: =BE18*19.49
A19: 45641 | B19: 3786628959 | D19: 517821521 | S19: 0.03 | AJ19: =IF(OR(B19="",B19=0,N19=""),"",N19/B19*10000) | AK19: =IF(OR(C19="",C19=0),"",O19/C19*10000) | AL19: =IF(OR(D19="",D19=0),"",P19/D19*10000) | AM19: =IF(OR(E19="",E19=0),"",Q19/E19*10000) | AT19: 10761181 | AU19: 0 | AV19: 2857.882 | AY19: =IF(OR(AX19="",AX19=0,AU19=""),"",AU19*365/(AX19*1000000)) | AZ19: 0 | BA19: 60487233 | BB19: 10761181 | BC19: 2971663 | BD19: =1000000000-999920427.6171+0.0000 | BE19: =1000000000-AZ19-BA19-BB19-BC19-BD19 | BF19: 238 | BG19: =BE19/1000000-BF19 | BH19: =BE19*24.15
A20: 45642 | B20: 6267294833 | D20: 552491542 | S20: 0.03 | AJ20: =IF(OR(B20="",B20=0,N20=""),"",N20/B20*10000) | AK20: =IF(OR(C20="",C20=0),"",O20/C20*10000) | AL20: =IF(OR(D20="",D20=0),"",P20/D20*10000) | AM20: =IF(OR(E20="",E20=0),"",Q20/E20*10000) | AT20: 10761181 | AU20: 0 | AV20: 2419.5935 | AY20: =IF(OR(AX20="",AX20=0,AU20=""),"",AU20*365/(AX20*1000000)) | AZ20: 0 | BA20: 60487233 | BB20: 10761181 | BC20: 2971663 | BD20: =1000000000-999918008.0235+0.0000 | BE20: =1000000000-AZ20-BA20-BB20-BC20-BD20 | BF20: 238 | BG20: =BE20/1000000-BF20 | BH20: =BE20*23.88
A21: 45643 | B21: 5593864857 | D21: 533018011 | S21: 0.03 | AJ21: =IF(OR(B21="",B21=0,N21=""),"",N21/B21*10000) | AK21: =IF(OR(C21="",C21=0),"",O21/C21*10000) | AL21: =IF(OR(D21="",D21=0),"",P21/D21*10000) | AM21: =IF(OR(E21="",E21=0),"",Q21/E21*10000) | AT21: 10789059 | AU21: 0 | AV21: 2278.9176 | AY21: =IF(OR(AX21="",AX21=0,AU21=""),"",AU21*365/(AX21*1000000)) | AZ21: 0 | BA21: 60487233 | BB21: 10789059 | BC21: 2971663 | BD21: =1000000000-999915729.1059+0.0000 | BE21: =1000000000-AZ21-BA21-BB21-BC21-BD21 | BF21: 238 | BG21: =BE21/1000000-BF21 | BH21: =BE21*27.24
A22: 45644 | B22: 8540539048 | D22: 472394527 | S22: 0.03 | AJ22: =IF(OR(B22="",B22=0,N22=""),"",N22/B22*10000) | AK22: =IF(OR(C22="",C22=0),"",O22/C22*10000) | AL22: =IF(OR(D22="",D22=0),"",P22/D22*10000) | AM22: =IF(OR(E22="",E22=0),"",Q22/E22*10000) | AT22: 10927485 | AU22: 0 | AV22: 2263.4293 | AY22: =IF(OR(AX22="",AX22=0,AU22=""),"",AU22*365/(AX22*1000000)) | AZ22: 0 | BA22: 60487233 | BB22: 10927485 | BC22: 2971663 | BD22: =1000000000-999913465.6766+0.0000 | BE22: =1000000000-AZ22-BA22-BB22-BC22-BD22 | BF22: 238 | BG22: =BE22/1000000-BF22 | BH22: =BE22*25.57
A23: 45645 | B23: 11512982470 | D23: 564194362 | S23: 0.03 | AJ23: =IF(OR(B23="",B23=0,N23=""),"",N23/B23*10000) | AK23: =IF(OR(C23="",C23=0),"",O23/C23*10000) | AL23: =IF(OR(D23="",D23=0),"",P23/D23*10000) | AM23: =IF(OR(E23="",E23=0),"",Q23/E23*10000) | AT23: 11039806 | AU23: 0 | AV23: 2427.0823 | AY23: =IF(OR(AX23="",AX23=0,AU23=""),"",AU23*365/(AX23*1000000)) | AZ23: 0 | BA23: 60487233 | BB23: 11039806 | BC23: 2971663 | BD23: =1000000000-999911038.5943+0.0000 | BE23: =1000000000-AZ23-BA23-BB23-BC23-BD23 | BF23: 238 | BG23: =BE23/1000000-BF23 | BH23: =BE23*23.22
A24: 45646 | B24: 9878521131 | D24: 703781781 | S24: 0.03 | AJ24: =IF(OR(B24="",B24=0,N24=""),"",N24/B24*10000) | AK24: =IF(OR(C24="",C24=0),"",O24/C24*10000) | AL24: =IF(OR(D24="",D24=0),"",P24/D24*10000) | AM24: =IF(OR(E24="",E24=0),"",Q24/E24*10000) | AT24: 11180484 | AU24: 0 | AV24: 2863.6836 | AY24: =IF(OR(AX24="",AX24=0,AU24=""),"",AU24*365/(AX24*1000000)) | AZ24: 0 | BA24: 60487233 | BB24: 11180484 | BC24: 2971663 | BD24: =1000000000-999908174.9107+0.0000 | BE24: =1000000000-AZ24-BA24-BB24-BC24-BD24 | BF24: 238 | BG24: =BE24/1000000-BF24 | BH24: =BE24*24.92
A25: 45647 | B25: 5203028237 | D25: 527191283 | S25: 0.03 | AJ25: =IF(OR(B25="",B25=0,N25=""),"",N25/B25*10000) | AK25: =IF(OR(C25="",C25=0),"",O25/C25*10000) | AL25: =IF(OR(D25="",D25=0),"",P25/D25*10000) | AM25: =IF(OR(E25="",E25=0),"",Q25/E25*10000) | AT25: 11244814 | AU25: 0 | AV25: 3033.9608 | AY25: =IF(OR(AX25="",AX25=0,AU25=""),"",AU25*365/(AX25*1000000)) | AZ25: 0 | BA25: 60487233 | BB25: 11244814 | BC25: 2971663 | BD25: =1000000000-999905140.9499+0.0000 | BE25: =1000000000-AZ25-BA25-BB25-BC25-BD25 | BF25: 238 | BG25: =BE25/1000000-BF25 | BH25: =BE25*29.74
A26: 45648 | B26: 4686731738 | D26: 471634786 | S26: 0.03 | AJ26: =IF(OR(B26="",B26=0,N26=""),"",N26/B26*10000) | AK26: =IF(OR(C26="",C26=0),"",O26/C26*10000) | AL26: =IF(OR(D26="",D26=0),"",P26/D26*10000) | AM26: =IF(OR(E26="",E26=0),"",Q26/E26*10000) | AT26: 11290999 | AU26: 0 | AV26: 2044.5791 | AY26: =IF(OR(AX26="",AX26=0,AU26=""),"",AU26*365/(AX26*1000000)) | AZ26: 0 | BA26: 60487233 | BB26: 11290999 | BC26: 2971663 | BD26: =1000000000-999903096.3708+0.0000 | BE26: =1000000000-AZ26-BA26-BB26-BC26-BD26 | BF26: 238 | BG26: =BE26/1000000-BF26 | BH26: =BE26*32.02
A27: 45649 | B27: 6168463522 | D27: 375034673 | N27: 1372264 | P27: 96254 | R27: =N27+O27+P27+N(Q27) | S27: 0.03 | T27: =N(AC27)*S27 | U27: =N(AD27)*S27 | V27: =N(AE27)*S27 | W27: =IF(Q27="","",N(AF27)*S27) | X27: 0 | AA27: =T27+U27+V27+N(W27)+X27+Y27+N(Z27) | AC27: 1331096 | AD27: =O27-Y27 | AE27: =P27-X27 | AF27: =IF(Q27="","",Q27-Z27) | AG27: =AC27+AD27+AE27+N(AF27) | AH27: 1424462 | AI27: =AG27-AH27 | AJ27: =IF(OR(B27="",B27=0,N27=""),"",N27/B27*10000) | AK27: =IF(OR(C27="",C27=0),"",O27/C27*10000) | AL27: =IF(OR(D27="",D27=0),"",P27/D27*10000) | AM27: =IF(OR(E27="",E27=0),"",Q27/E27*10000) | AN27: 0 | AO27: 0 | AP27: =AH27+AN27+AO27 | AQ27: =AH27 | AR27: 55522.13 | AS27: 28.47 | AT27: 11346521 | AU27: 0 | AV27: 2041.5641 | AY27: =IF(OR(AX27="",AX27=0,AU27=""),"",AU27*365/(AX27*1000000)) | AZ27: 0 | BA27: 60487233 | BB27: 11346521 | BC27: 2971663 | BD27: =1000000000-999901054.8066+0.0000 | BE27: =1000000000-AZ27-BA27-BB27-BC27-BD27 | BF27: 238 | BG27: =BE27/1000000-BF27 | BH27: =BE27*28.47
A28: 45650 | B28: 4401565233 | D28: 319403848 | N28: 1296670 | P28: 47315 | R28: =N28+O28+P28+N(Q28) | S28: 0.03 | T28: =N(AC28)*S28 | U28: =N(AD28)*S28 | V28: =N(AE28)*S28 | W28: =IF(Q28="","",N(AF28)*S28) | X28: 0 | AA28: =T28+U28+V28+N(W28)+X28+Y28+N(Z28) | AC28: 1257770 | AD28: =O28-Y28 | AE28: =P28-X28 | AF28: =IF(Q28="","",Q28-Z28) | AG28: =AC28+AD28+AE28+N(AF28) | AH28: 1303665 | AI28: =AG28-AH28 | AJ28: =IF(OR(B28="",B28=0,N28=""),"",N28/B28*10000) | AK28: =IF(OR(C28="",C28=0),"",O28/C28*10000) | AL28: =IF(OR(D28="",D28=0),"",P28/D28*10000) | AM28: =IF(OR(E28="",E28=0),"",Q28/E28*10000) | AN28: 0 | AO28: 0 | AP28: =AH28+AN28+AO28 | AQ28: =AH28 | AR28: 49941.64 | AS28: 28.6 | AT28: 11396463 | AU28: 0 | AV28: 3190.5125 | AY28: =IF(OR(AX28="",AX28=0,AU28=""),"",AU28*365/(AX28*1000000)) | AZ28: 0 | BA28: 60487233 | BB28: 11396463 | BC28: 2971663 | BD28: =1000000000-999897864.2941+0.0000 | BE28: =1000000000-AZ28-BA28-BB28-BC28-BD28 | BF28: 238 | BG28: =BE28/1000000-BF28 | BH28: =BE28*28.6
A29: 45651 | B29: 3090026720 | D29: 310480616 | N29: 1002334 | P29: 43561 | R29: =N29+O29+P29+N(Q29) | S29: 0.03 | T29: =N(AC29)*S29 | U29: =N(AD29)*S29 | V29: =N(AE29)*S29 | W29: =IF(Q29="","",N(AF29)*S29) | X29: 0 | AA29: =T29+U29+V29+N(W29)+X29+Y29+N(Z29) | AC29: 972264 | AD29: =O29-Y29 | AE29: =P29-X29 | AF29: =IF(Q29="","",Q29-Z29) | AG29: =AC29+AD29+AE29+N(AF29) | AH29: 1014518 | AI29: =AG29-AH29 | AJ29: =IF(OR(B29="",B29=0,N29=""),"",N29/B29*10000) | AK29: =IF(OR(C29="",C29=0),"",O29/C29*10000) | AL29: =IF(OR(D29="",D29=0),"",P29/D29*10000) | AM29: =IF(OR(E29="",E29=0),"",Q29/E29*10000) | AN29: 0 | AO29: 0 | AP29: =AH29+AN29+AO29 | AQ29: =AH29 | AR29: 42906.81 | AS29: 29.78 | AT29: 11439370 | AU29: 0 | AV29: 1832.8323 | AY29: =IF(OR(AX29="",AX29=0,AU29=""),"",AU29*365/(AX29*1000000)) | AZ29: 0 | BA29: 60487233 | BB29: 11439370 | BC29: 2971663 | BD29: =1000000000-999896031.4618+0.0000 | BE29: =1000000000-AZ29-BA29-BB29-BC29-BD29 | BF29: 238 | BG29: =BE29/1000000-BF29 | BH29: =BE29*29.78
A30: 45652 | B30: 3897465234 | D30: 214091088 | N30: 1269042 | P30: 44254 | R30: =N30+O30+P30+N(Q30) | S30: 0.03 | T30: =N(AC30)*S30 | U30: =N(AD30)*S30 | V30: =N(AE30)*S30 | W30: =IF(Q30="","",N(AF30)*S30) | X30: 0 | AA30: =T30+U30+V30+N(W30)+X30+Y30+N(Z30) | AC30: 1230971 | AD30: =O30-Y30 | AE30: =P30-X30 | AF30: =IF(Q30="","",Q30-Z30) | AG30: =AC30+AD30+AE30+N(AF30) | AH30: 1273897 | AI30: =AG30-AH30 | AJ30: =IF(OR(B30="",B30=0,N30=""),"",N30/B30*10000) | AK30: =IF(OR(C30="",C30=0),"",O30/C30*10000) | AL30: =IF(OR(D30="",D30=0),"",P30/D30*10000) | AM30: =IF(OR(E30="",E30=0),"",Q30/E30*10000) | AN30: 0 | AO30: 0 | AP30: =AH30+AN30+AO30 | AQ30: =AH30 | AR30: 28772.87 | AS30: 26.55 | AT30: 11468143 | AU30: 0 | AV30: 1373.0965 | AY30: =IF(OR(AX30="",AX30=0,AU30=""),"",AU30*365/(AX30*1000000)) | AZ30: 0 | BA30: 60487233 | BB30: 11468143 | BC30: 2971663 | BD30: =1000000000-999894658.3653+0.0000 | BE30: =1000000000-AZ30-BA30-BB30-BC30-BD30 | BF30: 238 | BG30: =BE30/1000000-BF30 | BH30: =BE30*26.55
A31: 45653 | B31: 3889473141 | D31: 216391282 | N31: 1268921 | P31: 28523 | R31: =N31+O31+P31+N(Q31) | S31: 0.03 | T31: =N(AC31)*S31 | U31: =N(AD31)*S31 | V31: =N(AE31)*S31 | W31: =IF(Q31="","",N(AF31)*S31) | X31: 0 | AA31: =T31+U31+V31+N(W31)+X31+Y31+N(Z31) | AC31: 1230853 | AD31: =O31-Y31 | AE31: =P31-X31 | AF31: =IF(Q31="","",Q31-Z31) | AG31: =AC31+AD31+AE31+N(AF31) | AH31: 1258520 | AI31: =AG31-AH31 | AJ31: =IF(OR(B31="",B31=0,N31=""),"",N31/B31*10000) | AK31: =IF(OR(C31="",C31=0),"",O31/C31*10000) | AL31: =IF(OR(D31="",D31=0),"",P31/D31*10000) | AM31: =IF(OR(E31="",E31=0),"",Q31/E31*10000) | AN31: 0 | AO31: 0 | AP31: =AH31+AN31+AO31 | AQ31: =AH31 | AR31: 45393.95 | AS31: 27.22 | AT31: 11513537 | AU31: 0 | AV31: 1476.4802 | AY31: =IF(OR(AX31="",AX31=0,AU31=""),"",AU31*365/(AX31*1000000)) | AZ31: 0 | BA31: 60487233 | BB31: 11513537 | BC31: 2971663 | BD31: =1000000000-999893181.8852+0.0000 | BE31: =1000000000-AZ31-BA31-BB31-BC31-BD31 | BF31: 238 | BG31: =BE31/1000000-BF31 | BH31: =BE31*27.22
A32: 45654 | B32: 2077191362 | D32: 212391739 | N32: 950246 | P32: 28430 | R32: =N32+O32+P32+N(Q32) | S32: 0.03 | T32: =N(AC32)*S32 | U32: =N(AD32)*S32 | V32: =N(AE32)*S32 | W32: =IF(Q32="","",N(AF32)*S32) | X32: 0 | AA32: =T32+U32+V32+N(W32)+X32+Y32+N(Z32) | AC32: 921738 | AD32: =O32-Y32 | AE32: =P32-X32 | AF32: =IF(Q32="","",Q32-Z32) | AG32: =AC32+AD32+AE32+N(AF32) | AH32: 949315 | AI32: =AG32-AH32 | AJ32: =IF(OR(B32="",B32=0,N32=""),"",N32/B32*10000) | AK32: =IF(OR(C32="",C32=0),"",O32/C32*10000) | AL32: =IF(OR(D32="",D32=0),"",P32/D32*10000) | AM32: =IF(OR(E32="",E32=0),"",Q32/E32*10000) | AN32: 0 | AO32: 0 | AP32: =AH32+AN32+AO32 | AQ32: =AH32 | AR32: 46697.63 | AS32: 27.11 | AT32: 11560234 | AU32: 0 | AV32: 1019.7076 | AX32: 301.00122 | AY32: =IF(OR(AX32="",AX32=0,AU32=""),"",AU32*365/(AX32*1000000)) | AZ32: 0 | BA32: 60487233 | BB32: 11560234 | BC32: 2971663 | BD32: =1000000000-999892162.1776+0.0000 | BE32: =1000000000-AZ32-BA32-BB32-BC32-BD32 | BF32: 238 | BG32: =BE32/1000000-BF32 | BH32: =BE32*27.11
A33: 45655 | B33: 1965931600 | D33: 342862746 | N33: 454244 | P33: 31496 | R33: =N33+O33+P33+N(Q33) | S33: 0.03 | T33: =N(AC33)*S33 | U33: =N(AD33)*S33 | V33: =N(AE33)*S33 | W33: =IF(Q33="","",N(AF33)*S33) | X33: 0 | AA33: =T33+U33+V33+N(W33)+X33+Y33+N(Z33) | AC33: 440616 | AD33: =O33-Y33 | AE33: =P33-X33 | AF33: =IF(Q33="","",Q33-Z33) | AG33: =AC33+AD33+AE33+N(AF33) | AH33: 471167 | AI33: =AG33-AH33 | AJ33: =IF(OR(B33="",B33=0,N33=""),"",N33/B33*10000) | AK33: =IF(OR(C33="",C33=0),"",O33/C33*10000) | AL33: =IF(OR(D33="",D33=0),"",P33/D33*10000) | AM33: =IF(OR(E33="",E33=0),"",Q33/E33*10000) | AN33: 0 | AO33: 0 | AP33: =AH33+AN33+AO33 | AQ33: =AH33 | AR33: 33952.54 | AS33: 29.26 | AT33: 11594187 | AU33: 0 | AV33: 774.4857 | AX33: 301.02439 | AY33: =IF(OR(AX33="",AX33=0,AU33=""),"",AU33*365/(AX33*1000000)) | AZ33: 4.2805004e+08 | BA33: 60487233 | BB33: 11594187 | BC33: 2971663 | BD33: =1000000000-999891387.692+0.0000 | BE33: =1000000000-AZ33-BA33-BB33-BC33-BD33 | BF33: 238 | BG33: =BE33/1000000-BF33 | BH33: =BE33*29.26
A34: 45656 | B34: 4697171102 | D34: 267028183 | N34: 1483664 | P34: 49113 | R34: =N34+O34+P34+N(Q34) | S34: 0.03 | T34: =N(AC34)*S34 | U34: =N(AD34)*S34 | V34: =N(AE34)*S34 | W34: =IF(Q34="","",N(AF34)*S34) | X34: 0 | AA34: =T34+U34+V34+N(W34)+X34+Y34+N(Z34) | AC34: 1439154 | AD34: =O34-Y34 | AE34: =P34-X34 | AF34: =IF(Q34="","",Q34-Z34) | AG34: =AC34+AD34+AE34+N(AF34) | AH34: 1486794 | AI34: =AG34-AH34 | AJ34: =IF(OR(B34="",B34=0,N34=""),"",N34/B34*10000) | AK34: =IF(OR(C34="",C34=0),"",O34/C34*10000) | AL34: =IF(OR(D34="",D34=0),"",P34/D34*10000) | AM34: =IF(OR(E34="",E34=0),"",Q34/E34*10000) | AN34: 0 | AO34: 0 | AP34: =AH34+AN34+AO34 | AQ34: =AH34 | AR34: 32031.98 | AS34: 27.44 | AT34: 11626219 | AU34: 22225.362 | AV34: 611.8805 | AX34: 301.10728 | AY34: =IF(OR(AX34="",AX34=0,AU34=""),"",AU34*365/(AX34*1000000)) | AZ34: 4.2802781e+08 | BA34: 60487233 | BB34: 11626219 | BC34: 2971663 | BD34: =1000000000-999890775.8115+0.0000 | BE34: =1000000000-AZ34-BA34-BB34-BC34-BD34 | BF34: 238 | BG34: =BE34/1000000-BF34 | BH34: =BE34*27.44
A35: 45657 | B35: 3450514508 | D35: 225503235 | N35: 1326087 | P35: 42962 | R35: =N35+O35+P35+N(Q35) | S35: 0.03 | T35: =N(AC35)*S35 | U35: =N(AD35)*S35 | V35: =N(AE35)*S35 | W35: =IF(Q35="","",N(AF35)*S35) | X35: 0 | AA35: =T35+U35+V35+N(W35)+X35+Y35+N(Z35) | AC35: 1286304 | AD35: =O35-Y35 | AE35: =P35-X35 | AF35: =IF(Q35="","",Q35-Z35) | AG35: =AC35+AD35+AE35+N(AF35) | AH35: 1327977 | AI35: =AG35-AH35 | AJ35: =IF(OR(B35="",B35=0,N35=""),"",N35/B35*10000) | AK35: =IF(OR(C35="",C35=0),"",O35/C35*10000) | AL35: =IF(OR(D35="",D35=0),"",P35/D35*10000) | AM35: =IF(OR(E35="",E35=0),"",Q35/E35*10000) | AN35: 0 | AO35: 0 | AP35: =AH35+AN35+AO35 | AQ35: =AH35 | AR35: 44578.73 | AS35: 26.95 | AT35: 11670797 | AU35: 23028.588 | AV35: 870.4787 | AX35: 352.79856 | AY35: =IF(OR(AX35="",AX35=0,AU35=""),"",AU35*365/(AX35*1000000)) | AZ35: 4.2800478e+08 | BA35: 60487233 | BB35: 11670797 | BC35: 2971663 | BD35: =1000000000-999889905.3328+0.0000 | BE35: =1000000000-AZ35-BA35-BB35-BC35-BD35 | BF35: 238 | BG35: =BE35/1000000-BF35 | BH35: =BE35*26.95
A36: 45658 | B36: 2157256818 | D36: 256438336 | N36: 483299 | P36: 30141 | R36: =N36+O36+P36+N(Q36) | S36: 0.03 | T36: =N(AC36)*S36 | U36: =N(AD36)*S36 | V36: =N(AE36)*S36 | W36: =IF(Q36="","",N(AF36)*S36) | X36: 0 | AA36: =T36+U36+V36+N(W36)+X36+Y36+N(Z36) | AC36: 468800 | AD36: =O36-Y36 | AE36: =P36-X36 | AF36: =IF(Q36="","",Q36-Z36) | AG36: =AC36+AD36+AE36+N(AF36) | AH36: 498037 | AI36: =AG36-AH36 | AJ36: =IF(OR(B36="",B36=0,N36=""),"",N36/B36*10000) | AK36: =IF(OR(C36="",C36=0),"",O36/C36*10000) | AL36: =IF(OR(D36="",D36=0),"",P36/D36*10000) | AM36: =IF(OR(E36="",E36=0),"",Q36/E36*10000) | AN36: 0 | AO36: 0 | AP36: =AH36+AN36+AO36 | AQ36: =AH36 | AR36: 48753.47 | AS36: 24 | AT36: 11719551 | AU36: 24499.354 | AV36: 941.1022 | AX36: 372.98553 | AY36: =IF(OR(AX36="",AX36=0,AU36=""),"",AU36*365/(AX36*1000000)) | AZ36: 4.2798028e+08 | BA36: 60487233 | BB36: 11719551 | BC36: 2971663 | BD36: =1000000000-999888964.2307+0.0000 | BE36: =1000000000-AZ36-BA36-BB36-BC36-BD36 | BF36: 238 | BG36: =BE36/1000000-BF36 | BH36: =BE36*24
A37: 45659 | B37: 3645816159 | D37: 267239456 | N37: 1267839 | P37: 41666 | R37: =N37+O37+P37+N(Q37) | S37: 0.03 | T37: =N(AC37)*S37 | U37: =N(AD37)*S37 | V37: =N(AE37)*S37 | W37: =IF(Q37="","",N(AF37)*S37) | X37: 0 | AA37: =T37+U37+V37+N(W37)+X37+Y37+N(Z37) | AC37: 1229804 | AD37: =O37-Y37 | AE37: =P37-X37 | AF37: =IF(Q37="","",Q37-Z37) | AG37: =AC37+AD37+AE37+N(AF37) | AH37: 1270220 | AI37: =AG37-AH37 | AJ37: =IF(OR(B37="",B37=0,N37=""),"",N37/B37*10000) | AK37: =IF(OR(C37="",C37=0),"",O37/C37*10000) | AL37: =IF(OR(D37="",D37=0),"",P37/D37*10000) | AM37: =IF(OR(E37="",E37=0),"",Q37/E37*10000) | AN37: 0 | AO37: 0 | AP37: =AH37+AN37+AO37 | AQ37: =AH37 | AR37: 37230.03 | AS37: 26.31 | AT37: 11756781 | AU37: 24851.902 | AV37: 920.9016 | AX37: 380.75278 | AY37: =IF(OR(AX37="",AX37=0,AU37=""),"",AU37*365/(AX37*1000000)) | AZ37: 4.2795543e+08 | BA37: 60487233 | BB37: 11756781 | BC37: 2971663 | BD37: =1000000000-999888043.3291+0.0000 | BE37: =1000000000-AZ37-BA37-BB37-BC37-BD37 | BF37: 238 | BG37: =BE37/1000000-BF37 | BH37: =BE37*26.31
A38: 45660 | B38: 3573160271 | D38: 176550030 | N38: 1374850 | P38: 37005 | R38: =N38+O38+P38+N(Q38) | S38: 0.03 | T38: =N(AC38)*S38 | U38: =N(AD38)*S38 | V38: =N(AE38)*S38 | W38: =IF(Q38="","",N(AF38)*S38) | X38: 0 | AA38: =T38+U38+V38+N(W38)+X38+Y38+N(Z38) | AC38: 1333605 | AD38: =O38-Y38 | AE38: =P38-X38 | AF38: =IF(Q38="","",Q38-Z38) | AG38: =AC38+AD38+AE38+N(AF38) | AH38: 1369500 | AI38: =AG38-AH38 | AJ38: =IF(OR(B38="",B38=0,N38=""),"",N38/B38*10000) | AK38: =IF(OR(C38="",C38=0),"",O38/C38*10000) | AL38: =IF(OR(D38="",D38=0),"",P38/D38*10000) | AM38: =IF(OR(E38="",E38=0),"",Q38/E38*10000) | AN38: 0 | AO38: 0 | AP38: =AH38+AN38+AO38 | AQ38: =AH38 | AR38: 55732.01 | AS38: 23.15 | AT38: 11812513 | AU38: 25219.868 | AV38: 905.5316 | AX38: 390.38936 | AY38: =IF(OR(AX38="",AX38=0,AU38=""),"",AU38*365/(AX38*1000000)) | AZ38: 4.2793021e+08 | BA38: 60487233 | BB38: 11812513 | BC38: 2971663 | BD38: =1000000000-999887137.7975+0.0000 | BE38: =1000000000-AZ38-BA38-BB38-BC38-BD38 | BF38: 238 | BG38: =BE38/1000000-BF38 | BH38: =BE38*23.15
A39: 45661 | B39: 2506267603 | D39: 119410641 | N39: 1049852 | P39: 25377 | R39: =N39+O39+P39+N(Q39) | S39: 0.03 | T39: =N(AC39)*S39 | U39: =N(AD39)*S39 | V39: =N(AE39)*S39 | W39: =IF(Q39="","",N(AF39)*S39) | X39: 0 | AA39: =T39+U39+V39+N(W39)+X39+Y39+N(Z39) | AC39: 1018356 | AD39: =O39-Y39 | AE39: =P39-X39 | AF39: =IF(Q39="","",Q39-Z39) | AG39: =AC39+AD39+AE39+N(AF39) | AH39: 1042972 | AI39: =AG39-AH39 | AJ39: =IF(OR(B39="",B39=0,N39=""),"",N39/B39*10000) | AK39: =IF(OR(C39="",C39=0),"",O39/C39*10000) | AL39: =IF(OR(D39="",D39=0),"",P39/D39*10000) | AM39: =IF(OR(E39="",E39=0),"",Q39/E39*10000) | AN39: 0 | AO39: 0 | AP39: =AH39+AN39+AO39 | AQ39: =AH39 | AR39: 34281.41 | AS39: 24.43 | AT39: 11846794 | AU39: 25452.778 | AV39: 1232.8801 | AX39: 395.40416 | AY39: =IF(OR(AX39="",AX39=0,AU39=""),"",AU39*365/(AX39*1000000)) | AZ39: 4.2790476e+08 | BA39: 60487233 | BB39: 11846794 | BC39: 2971663 | BD39: =1000000000-999885904.9174+0.0000 | BE39: =1000000000-AZ39-BA39-BB39-BC39-BD39 | BF39: 238 | BG39: =BE39/1000000-BF39 | BH39: =BE39*24.43
A40: 45662 | B40: 2149149006 | D40: 174388254 | N40: 996395 | P40: 19262 | R40: =N40+O40+P40+N(Q40) | S40: 0.03 | T40: =N(AC40)*S40 | U40: =N(AD40)*S40 | V40: =N(AE40)*S40 | W40: =IF(Q40="","",N(AF40)*S40) | X40: 0 | AA40: =T40+U40+V40+N(W40)+X40+Y40+N(Z40) | AC40: 966503 | AD40: =O40-Y40 | AE40: =P40-X40 | AF40: =IF(Q40="","",Q40-Z40) | AG40: =AC40+AD40+AE40+N(AF40) | AH40: 985187 | AI40: =AG40-AH40 | AJ40: =IF(OR(B40="",B40=0,N40=""),"",N40/B40*10000) | AK40: =IF(OR(C40="",C40=0),"",O40/C40*10000) | AL40: =IF(OR(D40="",D40=0),"",P40/D40*10000) | AM40: =IF(OR(E40="",E40=0),"",Q40/E40*10000) | AN40: 0 | AO40: 0 | AP40: =AH40+AN40+AO40 | AQ40: =AH40 | AR40: 42553.47 | AS40: 25.02 | AT40: 11889348 | AU40: 25665.111 | AV40: 617.3145 | AX40: 401.89251 | AY40: =IF(OR(AX40="",AX40=0,AU40=""),"",AU40*365/(AX40*1000000)) | AZ40: 4.2787909e+08 | BA40: 60487233 | BB40: 11889348 | BC40: 2971663 | BD40: =1000000000-999885287.603+0.0000 | BE40: =1000000000-AZ40-BA40-BB40-BC40-BD40 | BF40: 238 | BG40: =BE40/1000000-BF40 | BH40: =BE40*25.02
A41: 45663 | B41: 4404918704 | D41: 194364069 | N41: 1045371 | P41: 23453 | R41: =N41+O41+P41+N(Q41) | S41: 0.03 | T41: =N(AC41)*S41 | U41: =N(AD41)*S41 | V41: =N(AE41)*S41 | W41: =IF(Q41="","",N(AF41)*S41) | X41: 0 | AA41: =T41+U41+V41+N(W41)+X41+Y41+N(Z41) | AC41: 1014010 | AD41: =O41-Y41 | AE41: =P41-X41 | AF41: =IF(Q41="","",Q41-Z41) | AG41: =AC41+AD41+AE41+N(AF41) | AH41: 1036760 | AI41: =AG41-AH41 | AJ41: =IF(OR(B41="",B41=0,N41=""),"",N41/B41*10000) | AK41: =IF(OR(C41="",C41=0),"",O41/C41*10000) | AL41: =IF(OR(D41="",D41=0),"",P41/D41*10000) | AM41: =IF(OR(E41="",E41=0),"",Q41/E41*10000) | AN41: 0 | AO41: 0 | AP41: =AH41+AN41+AO41 | AQ41: =AH41 | AR41: 43787.34 | AS41: 24.4 | AT41: 11933135 | AU41: 25789.885 | AV41: 447.5855 | AX41: 404.49525 | AY41: =IF(OR(AX41="",AX41=0,AU41=""),"",AU41*365/(AX41*1000000)) | AZ41: 4.278533e+08 | BA41: 60487233 | BB41: 11933135 | BC41: 2971663 | BD41: =1000000000-999884840.0175+0.0000 | BE41: =1000000000-AZ41-BA41-BB41-BC41-BD41 | BF41: 238 | BG41: =BE41/1000000-BF41 | BH41: =BE41*24.4
A42: 45664 | B42: 7004545547 | D42: 298520602 | N42: 2149311 | P42: 30214 | R42: =N42+O42+P42+N(Q42) | S42: 0.03 | T42: =N(AC42)*S42 | U42: =N(AD42)*S42 | V42: =N(AE42)*S42 | W42: =IF(Q42="","",N(AF42)*S42) | X42: 0 | AA42: =T42+U42+V42+N(W42)+X42+Y42+N(Z42) | AC42: 2084832 | AD42: =O42-Y42 | AE42: =P42-X42 | AF42: =IF(Q42="","",Q42-Z42) | AG42: =AC42+AD42+AE42+N(AF42) | AH42: 2114140 | AI42: =AG42-AH42 | AJ42: =IF(OR(B42="",B42=0,N42=""),"",N42/B42*10000) | AK42: =IF(OR(C42="",C42=0),"",O42/C42*10000) | AL42: =IF(OR(D42="",D42=0),"",P42/D42*10000) | AM42: =IF(OR(E42="",E42=0),"",Q42/E42*10000) | AN42: 0 | AO42: 0 | AP42: =AH42+AN42+AO42 | AQ42: =AH42 | AR42: 58651.7 | AS42: 25.23 | AT42: 11991787 | AU42: 25854.611 | AV42: 718.7295 | AX42: 407.40015 | AY42: =IF(OR(AX42="",AX42=0,AU42=""),"",AU42*365/(AX42*1000000)) | AZ42: 4.2782745e+08 | BA42: 60487233 | BB42: 11991787 | BC42: 2971663 | BD42: =1000000000-999884121.288+0.0000 | BE42: =1000000000-AZ42-BA42-BB42-BC42-BD42 | BF42: 238 | BG42: =BE42/1000000-BF42 | BH42: =BE42*25.23
A43: 45665 | B43: 6019784667 | D43: 325463853 | N43: 1767943 | P43: 45273 | R43: =N43+O43+P43+N(Q43) | S43: 0.03 | T43: =N(AC43)*S43 | U43: =N(AD43)*S43 | V43: =N(AE43)*S43 | W43: =IF(Q43="","",N(AF43)*S43) | X43: 0 | AA43: =T43+U43+V43+N(W43)+X43+Y43+N(Z43) | AC43: 1714904 | AD43: =O43-Y43 | AE43: =P43-X43 | AF43: =IF(Q43="","",Q43-Z43) | AG43: =AC43+AD43+AE43+N(AF43) | AH43: 1758819 | AI43: =AG43-AH43 | AJ43: =IF(OR(B43="",B43=0,N43=""),"",N43/B43*10000) | AK43: =IF(OR(C43="",C43=0),"",O43/C43*10000) | AL43: =IF(OR(D43="",D43=0),"",P43/D43*10000) | AM43: =IF(OR(E43="",E43=0),"",Q43/E43*10000) | AN43: 0 | AO43: 0 | AP43: =AH43+AN43+AO43 | AQ43: =AH43 | AR43: 84543.47 | AS43: 23.5 | AT43: 12076330 | AU43: 25924.42 | AV43: 744.9065 | AX43: 409.06593 | AY43: =IF(OR(AX43="",AX43=0,AU43=""),"",AU43*365/(AX43*1000000)) | AZ43: 4.2780152e+08 | BA43: 60487233 | BB43: 12076330 | BC43: 2971663 | BD43: =1000000000-999883376.3815+0.0000 | BE43: =1000000000-AZ43-BA43-BB43-BC43-BD43 | BF43: 238 | BG43: =BE43/1000000-BF43 | BH43: =BE43*23.5
A44: 45666 | B44: 7123327274 | D44: 194078337 | N44: 1933268 | P44: 47391 | R44: =N44+O44+P44+N(Q44) | S44: 0.03 | T44: =N(AC44)*S44 | U44: =N(AD44)*S44 | V44: =N(AE44)*S44 | W44: =IF(Q44="","",N(AF44)*S44) | X44: 0 | AA44: =T44+U44+V44+N(W44)+X44+Y44+N(Z44) | AC44: 1875270 | AD44: =O44-Y44 | AE44: =P44-X44 | AF44: =IF(Q44="","",Q44-Z44) | AG44: =AC44+AD44+AE44+N(AF44) | AH44: 1921239 | AI44: =AG44-AH44 | AJ44: =IF(OR(B44="",B44=0,N44=""),"",N44/B44*10000) | AK44: =IF(OR(C44="",C44=0),"",O44/C44*10000) | AL44: =IF(OR(D44="",D44=0),"",P44/D44*10000) | AM44: =IF(OR(E44="",E44=0),"",Q44/E44*10000) | AN44: 0 | AO44: 0 | AP44: =AH44+AN44+AO44 | AQ44: =AH44 | AR44: 80644.52 | AS44: 22.51 | AT44: 12156975 | AU44: 25984.345 | AV44: 1579.5356 | AX44: 410.2463 | AY44: =IF(OR(AX44="",AX44=0,AU44=""),"",AU44*365/(AX44*1000000)) | AZ44: 4.2777554e+08 | BA44: 60487233 | BB44: 12156975 | BC44: 2971663 | BD44: =1000000000-999881796.8459+0.0000 | BE44: =1000000000-AZ44-BA44-BB44-BC44-BD44 | BF44: 238 | BG44: =BE44/1000000-BF44 | BH44: =BE44*22.51
A45: 45667 | B45: 5110006120 | D45: 104484914 | N45: 1492881 | P45: 27771 | R45: =N45+O45+P45+N(Q45) | S45: 0.03 | T45: =N(AC45)*S45 | U45: =N(AD45)*S45 | V45: =N(AE45)*S45 | W45: =IF(Q45="","",N(AF45)*S45) | X45: 0 | AA45: =T45+U45+V45+N(W45)+X45+Y45+N(Z45) | AC45: 1448094 | AD45: =O45-Y45 | AE45: =P45-X45 | AF45: =IF(Q45="","",Q45-Z45) | AG45: =AC45+AD45+AE45+N(AF45) | AH45: 1475032 | AI45: =AG45-AH45 | AJ45: =IF(OR(B45="",B45=0,N45=""),"",N45/B45*10000) | AK45: =IF(OR(C45="",C45=0),"",O45/C45*10000) | AL45: =IF(OR(D45="",D45=0),"",P45/D45*10000) | AM45: =IF(OR(E45="",E45=0),"",Q45/E45*10000) | AN45: 0 | AO45: 0 | AP45: =AH45+AN45+AO45 | AQ45: =AH45 | AR45: 84058.36 | AS45: 20.28 | AT45: 12241033 | AU45: 26008.903 | AV45: 1664.9046 | AX45: 410.55517 | AY45: =IF(OR(AX45="",AX45=0,AU45=""),"",AU45*365/(AX45*1000000)) | AZ45: 4.2774953e+08 | BA45: 60487233 | BB45: 12241033 | BC45: 2971663 | BD45: =1000000000-999880131.9413+0.0000 | BE45: =1000000000-AZ45-BA45-BB45-BC45-BD45 | BF45: 238 | BG45: =BE45/1000000-BF45 | BH45: =BE45*20.28
A46: 45668 | B46: 1975220111 | D46: 104729289 | N46: 457618 | P46: 14961 | R46: =N46+O46+P46+N(Q46) | S46: 0.03 | T46: =N(AC46)*S46 | U46: =N(AD46)*S46 | V46: =N(AE46)*S46 | W46: =IF(Q46="","",N(AF46)*S46) | X46: 0 | AA46: =T46+U46+V46+N(W46)+X46+Y46+N(Z46) | AC46: 443890 | AD46: =O46-Y46 | AE46: =P46-X46 | AF46: =IF(Q46="","",Q46-Z46) | AG46: =AC46+AD46+AE46+N(AF46) | AH46: 458402 | AI46: =AG46-AH46 | AJ46: =IF(OR(B46="",B46=0,N46=""),"",N46/B46*10000) | AK46: =IF(OR(C46="",C46=0),"",O46/C46*10000) | AL46: =IF(OR(D46="",D46=0),"",P46/D46*10000) | AM46: =IF(OR(E46="",E46=0),"",Q46/E46*10000) | AN46: 0 | AO46: 0 | AP46: =AH46+AN46+AO46 | AQ46: =AH46 | AR46: 64375.7 | AS46: 20.65 | AT46: 12305409 | AU46: 26032.719 | AV46: 984.8383 | AX46: 411.89327 | AY46: =IF(OR(AX46="",AX46=0,AU46=""),"",AU46*365/(AX46*1000000)) | AZ46: 4.277235e+08 | BA46: 60487233 | BB46: 12305409 | BC46: 2971663 | BD46: =1000000000-999879147.103+0.0000 | BE46: =1000000000-AZ46-BA46-BB46-BC46-BD46 | BF46: 238 | BG46: =BE46/1000000-BF46 | BH46: =BE46*20.65
A47: 45669 | B47: 1868823314 | D47: 230154418 | S47: 0.03 | AJ47: =IF(OR(B47="",B47=0,N47=""),"",N47/B47*10000) | AK47: =IF(OR(C47="",C47=0),"",O47/C47*10000) | AL47: =IF(OR(D47="",D47=0),"",P47/D47*10000) | AM47: =IF(OR(E47="",E47=0),"",Q47/E47*10000) | AT47: 12323093 | AU47: 26062.989 | AV47: 555.3528 | AX47: 412.63036 | AY47: =IF(OR(AX47="",AX47=0,AU47=""),"",AU47*365/(AX47*1000000)) | AZ47: 4.2769743e+08 | BA47: 60487233 | BB47: 12323093 | BC47: 2971663 | BD47: =1000000000-999878591.7502+0.0000 | BE47: =1000000000-AZ47-BA47-BB47-BC47-BD47 | BF47: 238 | BG47: =BE47/1000000-BF47 | BH47: =BE47*20.88
A48: 45670 | B48: 7614889368 | D48: 195123318 | S48: 0.03 | AJ48: =IF(OR(B48="",B48=0,N48=""),"",N48/B48*10000) | AK48: =IF(OR(C48="",C48=0),"",O48/C48*10000) | AL48: =IF(OR(D48="",D48=0),"",P48/D48*10000) | AM48: =IF(OR(E48="",E48=0),"",Q48/E48*10000) | AT48: 12366458 | AU48: 26085.585 | AV48: 490.8274 | AX48: 414.40353 | AY48: =IF(OR(AX48="",AX48=0,AU48=""),"",AU48*365/(AX48*1000000)) | AZ48: 4.2767135e+08 | BA48: 60487233 | BB48: 12366458 | BC48: 2971663 | BD48: =1000000000-999878100.9228+0.0000 | BE48: =1000000000-AZ48-BA48-BB48-BC48-BD48 | BF48: 238 | BG48: =BE48/1000000-BF48 | BH48: =BE48*21.12
A49: 45671 | B49: 4164534612 | D49: 186174573 | N49: 1243879 | P49: 24324 | R49: =N49+O49+P49+N(Q49) | S49: 0.03 | T49: =N(AC49)*S49 | U49: =N(AD49)*S49 | V49: =N(AE49)*S49 | W49: =IF(Q49="","",N(AF49)*S49) | X49: 0 | AA49: =T49+U49+V49+N(W49)+X49+Y49+N(Z49) | AC49: 1206563 | AD49: =O49-Y49 | AE49: =P49-X49 | AF49: =IF(Q49="","",Q49-Z49) | AG49: =AC49+AD49+AE49+N(AF49) | AH49: 1230157 | AI49: =AG49-AH49 | AJ49: =IF(OR(B49="",B49=0,N49=""),"",N49/B49*10000) | AK49: =IF(OR(C49="",C49=0),"",O49/C49*10000) | AL49: =IF(OR(D49="",D49=0),"",P49/D49*10000) | AM49: =IF(OR(E49="",E49=0),"",Q49/E49*10000) | AN49: 0 | AO49: 0 | AP49: =AH49+AN49+AO49 | AQ49: =AH49 | AR49: 101362.91 | AS49: 21.63 | AT49: 12467821 | AU49: 26275.62 | AV49: 1292.8946 | AX49: 422.39819 | AY49: =IF(OR(AX49="",AX49=0,AU49=""),"",AU49*365/(AX49*1000000)) | AZ49: 4.2764507e+08 | BA49: 60487233 | BB49: 12467821 | BC49: 2971663 | BD49: =1000000000-999876808.0282+0.0000 | BE49: =1000000000-AZ49-BA49-BB49-BC49-BD49 | BF49: 238 | BG49: =BE49/1000000-BF49 | BH49: =BE49*21.63
A50: 45672 | B50: 5315407561 | D50: 125668891 | N50: 1245669 | P50: 23915 | R50: =N50+O50+P50+N(Q50) | S50: 0.03 | T50: =N(AC50)*S50 | U50: =N(AD50)*S50 | V50: =N(AE50)*S50 | W50: =IF(Q50="","",N(AF50)*S50) | X50: 0 | AA50: =T50+U50+V50+N(W50)+X50+Y50+N(Z50) | AC50: 1208299 | AD50: =O50-Y50 | AE50: =P50-X50 | AF50: =IF(Q50="","",Q50-Z50) | AG50: =AC50+AD50+AE50+N(AF50) | AH50: 1231497 | AI50: =AG50-AH50 | AJ50: =IF(OR(B50="",B50=0,N50=""),"",N50/B50*10000) | AK50: =IF(OR(C50="",C50=0),"",O50/C50*10000) | AL50: =IF(OR(D50="",D50=0),"",P50/D50*10000) | AM50: =IF(OR(E50="",E50=0),"",Q50/E50*10000) | AN50: 0 | AO50: 0 | AP50: =AH50+AN50+AO50 | AQ50: =AH50 | AR50: 54953.16 | AS50: 23 | AT50: 12522774 | AU50: 26404.186 | AV50: 1035.8599 | AX50: 425.11787 | AY50: =IF(OR(AX50="",AX50=0,AU50=""),"",AU50*365/(AX50*1000000)) | AZ50: 4.2761867e+08 | BA50: 60487233 | BB50: 12522774 | BC50: 2971663 | BD50: =1000000000-999875772.1684+0.0000 | BE50: =1000000000-AZ50-BA50-BB50-BC50-BD50 | BF50: 238 | BG50: =BE50/1000000-BF50 | BH50: =BE50*23
A51: 45673 | B51: 5713611240 | D51: 148144621 | N51: 1677266 | P51: 18602 | R51: =N51+O51+P51+N(Q51) | S51: 0.03 | T51: =N(AC51)*S51 | U51: =N(AD51)*S51 | V51: =N(AE51)*S51 | W51: =IF(Q51="","",N(AF51)*S51) | X51: 0 | AA51: =T51+U51+V51+N(W51)+X51+Y51+N(Z51) | AC51: 1626948 | AD51: =O51-Y51 | AE51: =P51-X51 | AF51: =IF(Q51="","",Q51-Z51) | AG51: =AC51+AD51+AE51+N(AF51) | AH51: 1644992 | AI51: =AG51-AH51 | AJ51: =IF(OR(B51="",B51=0,N51=""),"",N51/B51*10000) | AK51: =IF(OR(C51="",C51=0),"",O51/C51*10000) | AL51: =IF(OR(D51="",D51=0),"",P51/D51*10000) | AM51: =IF(OR(E51="",E51=0),"",Q51/E51*10000) | AN51: 0 | AO51: 0 | AP51: =AH51+AN51+AO51 | AQ51: =AH51 | AR51: 69142.86 | AS51: 24.38 | AT51: 12591917 | AU51: 26508.232 | AV51: 883.4029 | AX51: 427.00147 | AY51: =IF(OR(AX51="",AX51=0,AU51=""),"",AU51*365/(AX51*1000000)) | AZ51: 4.2759216e+08 | BA51: 60487233 | BB51: 12591917 | BC51: 2971663 | BD51: =1000000000-999874888.7655+0.0000 | BE51: =1000000000-AZ51-BA51-BB51-BC51-BD51 | BF51: 238 | BG51: =BE51/1000000-BF51 | BH51: =BE51*24.38
A52: 45674 | B52: 5461277249 | D52: 342126938 | N52: 1677802 | P52: 20485 | R52: =N52+O52+P52+N(Q52) | S52: 0.03 | T52: =N(AC52)*S52 | U52: =N(AD52)*S52 | V52: =N(AE52)*S52 | W52: =IF(Q52="","",N(AF52)*S52) | X52: 0 | AA52: =T52+U52+V52+N(W52)+X52+Y52+N(Z52) | AC52: 1627468 | AD52: =O52-Y52 | AE52: =P52-X52 | AF52: =IF(Q52="","",Q52-Z52) | AG52: =AC52+AD52+AE52+N(AF52) | AH52: 1647338 | AI52: =AG52-AH52 | AJ52: =IF(OR(B52="",B52=0,N52=""),"",N52/B52*10000) | AK52: =IF(OR(C52="",C52=0),"",O52/C52*10000) | AL52: =IF(OR(D52="",D52=0),"",P52/D52*10000) | AM52: =IF(OR(E52="",E52=0),"",Q52/E52*10000) | AN52: 0 | AO52: 0 | AP52: =AH52+AN52+AO52 | AQ52: =AH52 | AR52: 65564.57 | AS52: 23.47 | AT52: 12657482 | AU52: 26562.754 | AV52: 560.1256 | AX52: 429.33507 | AY52: =IF(OR(AX52="",AX52=0,AU52=""),"",AU52*365/(AX52*1000000)) | AZ52: 4.275656e+08 | BA52: 60487233 | BB52: 12657482 | BC52: 2971663 | BD52: =1000000000-999874328.6399+0.0000 | BE52: =1000000000-AZ52-BA52-BB52-BC52-BD52 | BF52: 238 | BG52: =BE52/1000000-BF52 | BH52: =BE52*23.47
A53: 45675 | B53: 9678960135 | D53: 452915269 | N53: 2787442 | P53: 52413 | R53: =N53+O53+P53+N(Q53) | S53: 0.03 | T53: =N(AC53)*S53 | U53: =N(AD53)*S53 | V53: =N(AE53)*S53 | W53: =IF(Q53="","",N(AF53)*S53) | X53: 0 | AA53: =T53+U53+V53+N(W53)+X53+Y53+N(Z53) | AC53: 2703819 | AD53: =O53-Y53 | AE53: =P53-X53 | AF53: =IF(Q53="","",Q53-Z53) | AG53: =AC53+AD53+AE53+N(AF53) | AH53: 2754660 | AI53: =AG53-AH53 | AJ53: =IF(OR(B53="",B53=0,N53=""),"",N53/B53*10000) | AK53: =IF(OR(C53="",C53=0),"",O53/C53*10000) | AL53: =IF(OR(D53="",D53=0),"",P53/D53*10000) | AM53: =IF(OR(E53="",E53=0),"",Q53/E53*10000) | AN53: 0 | AO53: 0 | AP53: =AH53+AN53+AO53 | AQ53: =AH53 | AR53: 88780.82 | AS53: 23.09 | AT53: 12746262 | AU53: 26584.013 | AV53: 614.0791 | AX53: 430.01937 | AY53: =IF(OR(AX53="",AX53=0,AU53=""),"",AU53*365/(AX53*1000000)) | AZ53: 4.2753901e+08 | BA53: 60487233 | BB53: 12746262 | BC53: 2971663 | BD53: =1000000000-999873714.5608+0.0000 | BE53: =1000000000-AZ53-BA53-BB53-BC53-BD53 | BF53: 238 | BG53: =BE53/1000000-BF53 | BH53: =BE53*23.09
A54: 45676 | B54: 17750219553 | D54: 234451715 | N54: 4250373 | P54: 61521 | R54: =N54+O54+P54+N(Q54) | S54: 0.03 | T54: =N(AC54)*S54 | U54: =N(AD54)*S54 | V54: =N(AE54)*S54 | W54: =IF(Q54="","",N(AF54)*S54) | X54: 0 | AA54: =T54+U54+V54+N(W54)+X54+Y54+N(Z54) | AC54: 4122862 | AD54: =O54-Y54 | AE54: =P54-X54 | AF54: =IF(Q54="","",Q54-Z54) | AG54: =AC54+AD54+AE54+N(AF54) | AH54: 4182537 | AI54: =AG54-AH54 | AJ54: =IF(OR(B54="",B54=0,N54=""),"",N54/B54*10000) | AK54: =IF(OR(C54="",C54=0),"",O54/C54*10000) | AL54: =IF(OR(D54="",D54=0),"",P54/D54*10000) | AM54: =IF(OR(E54="",E54=0),"",Q54/E54*10000) | AN54: 0 | AO54: 0 | AP54: =AH54+AN54+AO54 | AQ54: =AH54 | AR54: 143340.27 | AS54: 21.94 | AT54: 12889603 | AU54: 26576.453 | AV54: 1549.2138 | AX54: 428.25571 | AY54: =IF(OR(AX54="",AX54=0,AU54=""),"",AU54*365/(AX54*1000000)) | AZ54: 4.2751244e+08 | BA54: 60487233 | BB54: 12889603 | BC54: 2971663 | BD54: =1000000000-999872165.347+0.0000 | BE54: =1000000000-AZ54-BA54-BB54-BC54-BD54 | BF54: 238 | BG54: =BE54/1000000-BF54 | BH54: =BE54*21.94
A55: 45677 | B55: 16339004972 | D55: 255573062 | N55: 4044525 | P55: 34279 | R55: =N55+O55+P55+N(Q55) | S55: 0.03 | T55: =N(AC55)*S55 | U55: =N(AD55)*S55 | V55: =N(AE55)*S55 | W55: =IF(Q55="","",N(AF55)*S55) | X55: 0 | AA55: =T55+U55+V55+N(W55)+X55+Y55+N(Z55) | AC55: 3923189 | AD55: =O55-Y55 | AE55: =P55-X55 | AF55: =IF(Q55="","",Q55-Z55) | AG55: =AC55+AD55+AE55+N(AF55) | AH55: 3956440 | AI55: =AG55-AH55 | AJ55: =IF(OR(B55="",B55=0,N55=""),"",N55/B55*10000) | AK55: =IF(OR(C55="",C55=0),"",O55/C55*10000) | AL55: =IF(OR(D55="",D55=0),"",P55/D55*10000) | AM55: =IF(OR(E55="",E55=0),"",Q55/E55*10000) | AN55: 0 | AO55: 0 | AP55: =AH55+AN55+AO55 | AQ55: =AH55 | AR55: 228527.25 | AS55: 20.19 | AT55: 13118130 | AU55: 26541.273 | AV55: 2127.3129 | AX55: 426.49034 | AY55: =IF(OR(AX55="",AX55=0,AU55=""),"",AU55*365/(AX55*1000000)) | AZ55: 4.274859e+08 | BA55: 60487233 | BB55: 13118130 | BC55: 2971663 | BD55: =1000000000-999870038.0341+0.0000 | BE55: =1000000000-AZ55-BA55-BB55-BC55-BD55 | BF55: 238 | BG55: =BE55/1000000-BF55 | BH55: =BE55*20.19
A56: 45678 | B56: 8341944948 | D56: 217426990 | N56: 2031876 | P56: 34069 | R56: =N56+O56+P56+N(Q56) | S56: 0.03 | T56: =N(AC56)*S56 | U56: =N(AD56)*S56 | V56: =N(AE56)*S56 | W56: =IF(Q56="","",N(AF56)*S56) | X56: 0 | AA56: =T56+U56+V56+N(W56)+X56+Y56+N(Z56) | AC56: 1970920 | AD56: =O56-Y56 | AE56: =P56-X56 | AF56: =IF(Q56="","",Q56-Z56) | AG56: =AC56+AD56+AE56+N(AF56) | AH56: 2003967 | AI56: =AG56-AH56 | AJ56: =IF(OR(B56="",B56=0,N56=""),"",N56/B56*10000) | AK56: =IF(OR(C56="",C56=0),"",O56/C56*10000) | AL56: =IF(OR(D56="",D56=0),"",P56/D56*10000) | AM56: =IF(OR(E56="",E56=0),"",Q56/E56*10000) | AN56: 0 | AO56: 0 | AP56: =AH56+AN56+AO56 | AQ56: =AH56 | AR56: 133128.89 | AS56: 20.55 | AT56: 13251259 | AU56: 26530.748 | AV56: 1392.5278 | AX56: 428.3282 | AY56: =IF(OR(AX56="",AX56=0,AU56=""),"",AU56*365/(AX56*1000000)) | AZ56: 4.2745937e+08 | BA56: 60487233 | BB56: 13251259 | BC56: 2971663 | BD56: =1000000000-999868645.5063+0.0000 | BE56: =1000000000-AZ56-BA56-BB56-BC56-BD56 | BF56: 238 | BG56: =BE56/1000000-BF56 | BH56: =BE56*20.55
A57: 45679 | B57: 5281551151 | D57: 268190024 | N57: 1405006 | P57: 30418 | R57: =N57+O57+P57+N(Q57) | S57: 0.03 | T57: =N(AC57)*S57 | U57: =N(AD57)*S57 | V57: =N(AE57)*S57 | W57: =IF(Q57="","",N(AF57)*S57) | X57: 0 | AA57: =T57+U57+V57+N(W57)+X57+Y57+N(Z57) | AC57: 1362855 | AD57: =O57-Y57 | AE57: =P57-X57 | AF57: =IF(Q57="","",Q57-Z57) | AG57: =AC57+AD57+AE57+N(AF57) | AH57: 1392360 | AI57: =AG57-AH57 | AJ57: =IF(OR(B57="",B57=0,N57=""),"",N57/B57*10000) | AK57: =IF(OR(C57="",C57=0),"",O57/C57*10000) | AL57: =IF(OR(D57="",D57=0),"",P57/D57*10000) | AM57: =IF(OR(E57="",E57=0),"",Q57/E57*10000) | AN57: 0 | AO57: 0 | AP57: =AH57+AN57+AO57 | AQ57: =AH57 | AR57: 71129.96 | AS57: 23.18 | AT57: 13322389 | AU57: 26567.346 | AV57: 1404.8497 | AX57: 428.48155 | AY57: =IF(OR(AX57="",AX57=0,AU57=""),"",AU57*365/(AX57*1000000)) | AZ57: 4.274328e+08 | BA57: 60487233 | BB57: 13322389 | BC57: 2971663 | BD57: =1000000000-999867240.6567+0.0000 | BE57: =1000000000-AZ57-BA57-BB57-BC57-BD57 | BF57: 238 | BG57: =BE57/1000000-BF57 | BH57: =BE57*23.18
A58: 45680 | B58: 11321580803 | D58: 178140305 | N58: 2783278 | P58: 38159 | R58: =N58+O58+P58+N(Q58) | S58: 0.03 | T58: =N(AC58)*S58 | U58: =N(AD58)*S58 | V58: =N(AE58)*S58 | W58: =IF(Q58="","",N(AF58)*S58) | X58: 0 | AA58: =T58+U58+V58+N(W58)+X58+Y58+N(Z58) | AC58: 2699780 | AD58: =O58-Y58 | AE58: =P58-X58 | AF58: =IF(Q58="","",Q58-Z58) | AG58: =AC58+AD58+AE58+N(AF58) | AH58: 2736794 | AI58: =AG58-AH58 | AJ58: =IF(OR(B58="",B58=0,N58=""),"",N58/B58*10000) | AK58: =IF(OR(C58="",C58=0),"",O58/C58*10000) | AL58: =IF(OR(D58="",D58=0),"",P58/D58*10000) | AM58: =IF(OR(E58="",E58=0),"",Q58/E58*10000) | AN58: 0 | AO58: 0 | AP58: =AH58+AN58+AO58 | AQ58: =AH58 | AR58: 62060.42 | AS58: 24.31 | AT58: 13384449 | AU58: 26581.533 | AV58: 923.5959 | AX58: 428.62572 | AY58: =IF(OR(AX58="",AX58=0,AU58=""),"",AU58*365/(AX58*1000000)) | AZ58: 4.2740622e+08 | BA58: 60487233 | BB58: 13384449 | BC58: 2971663 | BD58: =1000000000-999866317.0608+0.0000 | BE58: =1000000000-AZ58-BA58-BB58-BC58-BD58 | BF58: 238 | BG58: =BE58/1000000-BF58 | BH58: =BE58*24.31
A59: 45681 | B59: 5784731819 | D59: 93192677 | N59: 1284164 | P59: 23999 | R59: =N59+O59+P59+N(Q59) | S59: 0.03 | T59: =N(AC59)*S59 | U59: =N(AD59)*S59 | V59: =N(AE59)*S59 | W59: =IF(Q59="","",N(AF59)*S59) | X59: 0 | AA59: =T59+U59+V59+N(W59)+X59+Y59+N(Z59) | AC59: 1245639 | AD59: =O59-Y59 | AE59: =P59-X59 | AF59: =IF(Q59="","",Q59-Z59) | AG59: =AC59+AD59+AE59+N(AF59) | AH59: 1268918 | AI59: =AG59-AH59 | AJ59: =IF(OR(B59="",B59=0,N59=""),"",N59/B59*10000) | AK59: =IF(OR(C59="",C59=0),"",O59/C59*10000) | AL59: =IF(OR(D59="",D59=0),"",P59/D59*10000) | AM59: =IF(OR(E59="",E59=0),"",Q59/E59*10000) | AN59: 0 | AO59: 0 | AP59: =AH59+AN59+AO59 | AQ59: =AH59 | AR59: 115997.07 | AS59: 21.97 | AT59: 13500446 | AU59: 26552.402 | AV59: 1425.0715 | AX59: 427.50931 | AY59: =IF(OR(AX59="",AX59=0,AU59=""),"",AU59*365/(AX59*1000000)) | AZ59: 4.2737966e+08 | BA59: 60487233 | BB59: 13500446 | BC59: 2971663 | BD59: =1000000000-999864891.9893+0.0000 | BE59: =1000000000-AZ59-BA59-BB59-BC59-BD59 | BF59: 238 | BG59: =BE59/1000000-BF59 | BH59: =BE59*21.97
A60: 45682 | B60: 3516728432 | D60: 138875526 | N60: 1061042 | P60: 14317 | R60: =N60+O60+P60+N(Q60) | S60: 0.03 | T60: =N(AC60)*S60 | U60: =N(AD60)*S60 | V60: =N(AE60)*S60 | W60: =IF(Q60="","",N(AF60)*S60) | X60: 0 | AA60: =T60+U60+V60+N(W60)+X60+Y60+N(Z60) | AC60: 1029211 | AD60: =O60-Y60 | AE60: =P60-X60 | AF60: =IF(Q60="","",Q60-Z60) | AG60: =AC60+AD60+AE60+N(AF60) | AH60: 1043099 | AI60: =AG60-AH60 | AJ60: =IF(OR(B60="",B60=0,N60=""),"",N60/B60*10000) | AK60: =IF(OR(C60="",C60=0),"",O60/C60*10000) | AL60: =IF(OR(D60="",D60=0),"",P60/D60*10000) | AM60: =IF(OR(E60="",E60=0),"",Q60/E60*10000) | AN60: 0 | AO60: 0 | AP60: =AH60+AN60+AO60 | AQ60: =AH60 | AR60: 59234.43 | AS60: 23.06 | AT60: 13559681 | AU60: 26530.811 | AV60: 909.6107 | AX60: 427.32622 | AY60: =IF(OR(AX60="",AX60=0,AU60=""),"",AU60*365/(AX60*1000000)) | AZ60: 4.2735313e+08 | BA60: 60487233 | BB60: 13559681 | BC60: 2971663 | BD60: =1000000000-999863982.3786+0.0000 | BE60: =1000000000-AZ60-BA60-BB60-BC60-BD60 | BF60: 238 | BG60: =BE60/1000000-BF60 | BH60: =BE60*23.06
A61: 45683 | B61: 3597386933 | D61: 229716868 | N61: 1066098 | P61: 16865 | R61: =N61+O61+P61+N(Q61) | S61: 0.03 | T61: =N(AC61)*S61 | U61: =N(AD61)*S61 | V61: =N(AE61)*S61 | W61: =IF(Q61="","",N(AF61)*S61) | X61: 0 | AA61: =T61+U61+V61+N(W61)+X61+Y61+N(Z61) | AC61: 1034115 | AD61: =O61-Y61 | AE61: =P61-X61 | AF61: =IF(Q61="","",Q61-Z61) | AG61: =AC61+AD61+AE61+N(AF61) | AH61: 1050474 | AI61: =AG61-AH61 | AJ61: =IF(OR(B61="",B61=0,N61=""),"",N61/B61*10000) | AK61: =IF(OR(C61="",C61=0),"",O61/C61*10000) | AL61: =IF(OR(D61="",D61=0),"",P61/D61*10000) | AM61: =IF(OR(E61="",E61=0),"",Q61/E61*10000) | AN61: 0 | AO61: 0 | AP61: =AH61+AN61+AO61 | AQ61: =AH61 | AR61: 29767.31 | AS61: 23.15 | AT61: 13589448 | AU61: 26541.029 | AV61: 462.2589 | AX61: 427.62726 | AY61: =IF(OR(AX61="",AX61=0,AU61=""),"",AU61*365/(AX61*1000000)) | AZ61: 4.2732659e+08 | BA61: 60487233 | BB61: 13589448 | BC61: 2971663 | BD61: =1000000000-999863520.1197+0.0000 | BE61: =1000000000-AZ61-BA61-BB61-BC61-BD61 | BF61: 238 | BG61: =BE61/1000000-BF61 | BH61: =BE61*23.15
A62: 45684 | B62: 10972896197 | D62: 185620600 | N62: 2661614 | P62: 37573 | R62: =N62+O62+P62+N(Q62) | S62: 0.03 | T62: =N(AC62)*S62 | U62: =N(AD62)*S62 | V62: =N(AE62)*S62 | W62: =IF(Q62="","",N(AF62)*S62) | X62: 0 | AA62: =T62+U62+V62+N(W62)+X62+Y62+N(Z62) | AC62: 2581765 | AD62: =O62-Y62 | AE62: =P62-X62 | AF62: =IF(Q62="","",Q62-Z62) | AG62: =AC62+AD62+AE62+N(AF62) | AH62: 2618211 | AI62: =AG62-AH62 | AJ62: =IF(OR(B62="",B62=0,N62=""),"",N62/B62*10000) | AK62: =IF(OR(C62="",C62=0),"",O62/C62*10000) | AL62: =IF(OR(D62="",D62=0),"",P62/D62*10000) | AM62: =IF(OR(E62="",E62=0),"",Q62/E62*10000) | AN62: 0 | AO62: 0 | AP62: =AH62+AN62+AO62 | AQ62: =AH62 | AR62: 76325.71 | AS62: 22.08 | AT62: 13665774 | AU62: 26557.334 | AV62: 515.1838 | AX62: 428.24228 | AY62: =IF(OR(AX62="",AX62=0,AU62=""),"",AU62*365/(AX62*1000000)) | AZ62: 4.2730004e+08 | BA62: 60487233 | BB62: 13665774 | BC62: 2971663 | BD62: =1000000000-999863004.9359+0.0000 | BE62: =1000000000-AZ62-BA62-BB62-BC62-BD62 | BF62: 238 | BG62: =BE62/1000000-BF62 | BH62: =BE62*22.08
A63: 45685 | B63: 6689142363 | D63: 170638730 | N63: 1502080 | P63: 26779 | R63: =N63+O63+P63+N(Q63) | S63: 0.03 | T63: =N(AC63)*S63 | U63: =N(AD63)*S63 | V63: =N(AE63)*S63 | W63: =IF(Q63="","",N(AF63)*S63) | X63: 0 | AA63: =T63+U63+V63+N(W63)+X63+Y63+N(Z63) | AC63: 1457018 | AD63: =O63-Y63 | AE63: =P63-X63 | AF63: =IF(Q63="","",Q63-Z63) | AG63: =AC63+AD63+AE63+N(AF63) | AH63: 1482994 | AI63: =AG63-AH63 | AJ63: =IF(OR(B63="",B63=0,N63=""),"",N63/B63*10000) | AK63: =IF(OR(C63="",C63=0),"",O63/C63*10000) | AL63: =IF(OR(D63="",D63=0),"",P63/D63*10000) | AM63: =IF(OR(E63="",E63=0),"",Q63/E63*10000) | AN63: 0 | AO63: 0 | AP63: =AH63+AN63+AO63 | AQ63: =AH63 | AR63: 98548.05 | AS63: 23.38 | AT63: 13764322 | AU63: 26537.844 | AV63: 1494.8576 | AX63: 427.08438 | AY63: =IF(OR(AX63="",AX63=0,AU63=""),"",AU63*365/(AX63*1000000)) | AZ63: 4.272735e+08 | BA63: 60487233 | BB63: 13764322 | BC63: 2971663 | BD63: =1000000000-999861510.0783+0.0000 | BE63: =1000000000-AZ63-BA63-BB63-BC63-BD63 | BF63: 238 | BG63: =BE63/1000000-BF63 | BH63: =BE63*23.38
A64: 45686 | B64: 7487288905 | D64: 283645800 | N64: 1858964 | P64: 20016 | R64: =N64+O64+P64+N(Q64) | S64: 0.03 | T64: =N(AC64)*S64 | U64: =N(AD64)*S64 | V64: =N(AE64)*S64 | W64: =IF(Q64="","",N(AF64)*S64) | X64: 0 | AA64: =T64+U64+V64+N(W64)+X64+Y64+N(Z64) | AC64: 1803195 | AD64: =O64-Y64 | AE64: =P64-X64 | AF64: =IF(Q64="","",Q64-Z64) | AG64: =AC64+AD64+AE64+N(AF64) | AH64: 1822611 | AI64: =AG64-AH64 | AJ64: =IF(OR(B64="",B64=0,N64=""),"",N64/B64*10000) | AK64: =IF(OR(C64="",C64=0),"",O64/C64*10000) | AL64: =IF(OR(D64="",D64=0),"",P64/D64*10000) | AM64: =IF(OR(E64="",E64=0),"",Q64/E64*10000) | AN64: 0 | AO64: 0 | AP64: =AH64+AN64+AO64 | AQ64: =AH64 | AR64: 65908.88 | AS64: 22.28 | AT64: 13830231 | AU64: 26534.291 | AV64: 925.2888 | AX64: 427.49321 | AY64: =IF(OR(AX64="",AX64=0,AU64=""),"",AU64*365/(AX64*1000000)) | AZ64: 4.2724696e+08 | BA64: 60487233 | BB64: 13830231 | BC64: 2971663 | BD64: =1000000000-999860584.7895+0.0000 | BE64: =1000000000-AZ64-BA64-BB64-BC64-BD64 | BF64: 238 | BG64: =BE64/1000000-BF64 | BH64: =BE64*22.28
A65: 45687 | B65: 5319626691 | D65: 212136745 | N65: 1410913 | P65: 38508 | R65: =N65+O65+P65+N(Q65) | S65: 0.03 | T65: =N(AC65)*S65 | U65: =N(AD65)*S65 | V65: =N(AE65)*S65 | W65: =IF(Q65="","",N(AF65)*S65) | X65: 0 | AA65: =T65+U65+V65+N(W65)+X65+Y65+N(Z65) | AC65: 1368586 | AD65: =O65-Y65 | AE65: =P65-X65 | AF65: =IF(Q65="","",Q65-Z65) | AG65: =AC65+AD65+AE65+N(AF65) | AH65: 1405939 | AI65: =AG65-AH65 | AJ65: =IF(OR(B65="",B65=0,N65=""),"",N65/B65*10000) | AK65: =IF(OR(C65="",C65=0),"",O65/C65*10000) | AL65: =IF(OR(D65="",D65=0),"",P65/D65*10000) | AM65: =IF(OR(E65="",E65=0),"",Q65/E65*10000) | AN65: 0 | AO65: 0 | AP65: =AH65+AN65+AO65 | AQ65: =AH65 | AR65: 86710.35 | AS65: 23.75 | AT65: 13916941 | AU65: 26544.879 | AV65: 730.3546 | AX65: 427.68581 | AY65: =IF(OR(AX65="",AX65=0,AU65=""),"",AU65*365/(AX65*1000000)) | AZ65: 4.2722042e+08 | BA65: 60487233 | BB65: 13916941 | BC65: 2971663 | BD65: =1000000000-999859854.4349+0.0000 | BE65: =1000000000-AZ65-BA65-BB65-BC65-BD65 | BF65: 238 | BG65: =BE65/1000000-BF65 | BH65: =BE65*23.75
A66: 45688 | B66: 7089116487 | D66: 263781612 | N66: 1745764 | P66: 30778 | R66: =N66+O66+P66+N(Q66) | S66: 0.03 | T66: =N(AC66)*S66 | U66: =N(AD66)*S66 | V66: =N(AE66)*S66 | W66: =IF(Q66="","",N(AF66)*S66) | X66: 0 | AA66: =T66+U66+V66+N(W66)+X66+Y66+N(Z66) | AC66: 1693391 | AD66: =O66-Y66 | AE66: =P66-X66 | AF66: =IF(Q66="","",Q66-Z66) | AG66: =AC66+AD66+AE66+N(AF66) | AH66: 1723246 | AI66: =AG66-AH66 | AJ66: =IF(OR(B66="",B66=0,N66=""),"",N66/B66*10000) | AK66: =IF(OR(C66="",C66=0),"",O66/C66*10000) | AL66: =IF(OR(D66="",D66=0),"",P66/D66*10000) | AM66: =IF(OR(E66="",E66=0),"",Q66/E66*10000) | AN66: 0 | AO66: 0 | AP66: =AH66+AN66+AO66 | AQ66: =AH66 | AR66: 39113.9 | AS66: 26.19 | AT66: 13956055 | AU66: 32252.715 | AV66: 1669.5925 | AX66: 427.82029 | AY66: =IF(OR(AX66="",AX66=0,AU66=""),"",AU66*365/(AX66*1000000)) | AZ66: 4.2718817e+08 | BA66: 60487233 | BB66: 13956055 | BC66: 2971663 | BD66: =1000000000-999858184.8425+0.0000 | BE66: =1000000000-AZ66-BA66-BB66-BC66-BD66 | BF66: 238 | BG66: =BE66/1000000-BF66 | BH66: =BE66*26.19
A67: 45689 | B67: 5335486363 | D67: 305083845 | N67: 1393440 | P67: 40422 | R67: =N67+O67+P67+N(Q67) | S67: 0.03 | T67: =N(AC67)*S67 | U67: =N(AD67)*S67 | V67: =N(AE67)*S67 | W67: =IF(Q67="","",N(AF67)*S67) | X67: 0 | AA67: =T67+U67+V67+N(W67)+X67+Y67+N(Z67) | AC67: 1351636 | AD67: =O67-Y67 | AE67: =P67-X67 | AF67: =IF(Q67="","",Q67-Z67) | AG67: =AC67+AD67+AE67+N(AF67) | AH67: 1390845 | AI67: =AG67-AH67 | AJ67: =IF(OR(B67="",B67=0,N67=""),"",N67/B67*10000) | AK67: =IF(OR(C67="",C67=0),"",O67/C67*10000) | AL67: =IF(OR(D67="",D67=0),"",P67/D67*10000) | AM67: =IF(OR(E67="",E67=0),"",Q67/E67*10000) | AN67: 0 | AO67: 0 | AP67: =AH67+AN67+AO67 | AQ67: =AH67 | AR67: 68264.31 | AS67: 26.92 | AT67: 14024319 | AU67: 20850.625 | AV67: 797.4358 | AX67: 427.55556 | AY67: =IF(OR(AX67="",AX67=0,AU67=""),"",AU67*365/(AX67*1000000)) | AZ67: 4.2716732e+08 | BA67: 60487233 | BB67: 14024319 | BC67: 2971663 | BD67: =1000000000-999857387.4067+0.0000 | BE67: =1000000000-AZ67-BA67-BB67-BC67-BD67 | BF67: 238 | BG67: =BE67/1000000-BF67 | BH67: =BE67*26.92
A68: 45690 | B68: 9044821754 | D68: 443687078 | N68: 2019665 | P68: 44496 | R68: =N68+O68+P68+N(Q68) | S68: 0.03 | T68: =N(AC68)*S68 | U68: =N(AD68)*S68 | V68: =N(AE68)*S68 | W68: =IF(Q68="","",N(AF68)*S68) | X68: 0 | AA68: =T68+U68+V68+N(W68)+X68+Y68+N(Z68) | AC68: 1959076 | AD68: =O68-Y68 | AE68: =P68-X68 | AF68: =IF(Q68="","",Q68-Z68) | AG68: =AC68+AD68+AE68+N(AF68) | AH68: 2002237 | AI68: =AG68-AH68 | AJ68: =IF(OR(B68="",B68=0,N68=""),"",N68/B68*10000) | AK68: =IF(OR(C68="",C68=0),"",O68/C68*10000) | AL68: =IF(OR(D68="",D68=0),"",P68/D68*10000) | AM68: =IF(OR(E68="",E68=0),"",Q68/E68*10000) | AN68: 0 | AO68: 0 | AP68: =AH68+AN68+AO68 | AQ68: =AH68 | AR68: 65528.55 | AS68: 23.17 | AT68: 14089848 | AU68: 26556.909 | AV68: 1144.1562 | AX68: 428.02669 | AY68: =IF(OR(AX68="",AX68=0,AU68=""),"",AU68*365/(AX68*1000000)) | AZ68: 4.2714076e+08 | BA68: 60487233 | BB68: 14089848 | BC68: 2971663 | BD68: =1000000000-999856243.2505+0.0000 | BE68: =1000000000-AZ68-BA68-BB68-BC68-BD68 | BF68: 238 | BG68: =BE68/1000000-BF68 | BH68: =BE68*23.17
A69: 45691 | B69: 18072547242 | D69: 263016289 | N69: 4197988 | P69: 63480 | R69: =N69+O69+P69+N(Q69) | S69: 0.03 | T69: =N(AC69)*S69 | U69: =N(AD69)*S69 | V69: =N(AE69)*S69 | W69: =IF(Q69="","",N(AF69)*S69) | X69: 0 | AA69: =T69+U69+V69+N(W69)+X69+Y69+N(Z69) | AC69: 4072048 | AD69: =O69-Y69 | AE69: =P69-X69 | AF69: =IF(Q69="","",Q69-Z69) | AG69: =AC69+AD69+AE69+N(AF69) | AH69: 4133623 | AI69: =AG69-AH69 | AJ69: =IF(OR(B69="",B69=0,N69=""),"",N69/B69*10000) | AK69: =IF(OR(C69="",C69=0),"",O69/C69*10000) | AL69: =IF(OR(D69="",D69=0),"",P69/D69*10000) | AM69: =IF(OR(E69="",E69=0),"",Q69/E69*10000) | AN69: 0 | AO69: 0 | AP69: =AH69+AN69+AO69 | AQ69: =AH69 | AR69: 170472.46 | AS69: 22.32 | AT69: 14260320 | AU69: 26546.419 | AV69: 1529.404 | AX69: 427.38822 | AY69: =IF(OR(AX69="",AX69=0,AU69=""),"",AU69*365/(AX69*1000000)) | AZ69: 4.2711421e+08 | BA69: 60487233 | BB69: 14260320 | BC69: 2971663 | BD69: =1000000000-999854713.8465+0.0000 | BE69: =1000000000-AZ69-BA69-BB69-BC69-BD69 | BF69: 238 | BG69: =BE69/1000000-BF69 | BH69: =BE69*22.32
A70: 45692 | B70: 10231406266 | D70: 208560749 | N70: 2474308 | P70: 37612 | R70: =N70+O70+P70+N(Q70) | S70: 0.03 | T70: =N(AC70)*S70 | U70: =N(AD70)*S70 | V70: =N(AE70)*S70 | W70: =IF(Q70="","",N(AF70)*S70) | X70: 0 | AA70: =T70+U70+V70+N(W70)+X70+Y70+N(Z70) | AC70: 2400078 | AD70: =O70-Y70 | AE70: =P70-X70 | AF70: =IF(Q70="","",Q70-Z70) | AG70: =AC70+AD70+AE70+N(AF70) | AH70: 2436561 | AI70: =AG70-AH70 | AJ70: =IF(OR(B70="",B70=0,N70=""),"",N70/B70*10000) | AK70: =IF(OR(C70="",C70=0),"",O70/C70*10000) | AL70: =IF(OR(D70="",D70=0),"",P70/D70*10000) | AM70: =IF(OR(E70="",E70=0),"",Q70/E70*10000) | AN70: 0 | AO70: 0 | AP70: =AH70+AN70+AO70 | AQ70: =AH70 | AR70: 107026.56 | AS70: 25.19 | AT70: 14367347 | AU70: 26535.168 | AV70: 2737.9562 | AX70: 427.17774 | AY70: =IF(OR(AX70="",AX70=0,AU70=""),"",AU70*365/(AX70*1000000)) | AZ70: 4.2708768e+08 | BA70: 60487233 | BB70: 14367347 | BC70: 2971663 | BD70: =1000000000-999851975.8903+0.0000 | BE70: =1000000000-AZ70-BA70-BB70-BC70-BD70 | BF70: 238 | BG70: =BE70/1000000-BF70 | BH70: =BE70*25.19
A71: 45693 | B71: 5694608356 | D71: 168626713 | N71: 1415160 | P71: 28216 | R71: =N71+O71+P71+N(Q71) | S71: 0.03 | T71: =N(AC71)*S71 | U71: =N(AD71)*S71 | V71: =N(AE71)*S71 | W71: =IF(Q71="","",N(AF71)*S71) | X71: 0 | AA71: =T71+U71+V71+N(W71)+X71+Y71+N(Z71) | AC71: 1372705 | AD71: =O71-Y71 | AE71: =P71-X71 | AF71: =IF(Q71="","",Q71-Z71) | AG71: =AC71+AD71+AE71+N(AF71) | AH71: 1400074 | AI71: =AG71-AH71 | AJ71: =IF(OR(B71="",B71=0,N71=""),"",N71/B71*10000) | AK71: =IF(OR(C71="",C71=0),"",O71/C71*10000) | AL71: =IF(OR(D71="",D71=0),"",P71/D71*10000) | AM71: =IF(OR(E71="",E71=0),"",Q71/E71*10000) | AN71: 0 | AO71: 0 | AP71: =AH71+AN71+AO71 | AQ71: =AH71 | AR71: 79638.15 | AS71: 25.14 | AT71: 14446985 | AU71: 26543.473 | AV71: 1264.3163 | AX71: 427.62767 | AY71: =IF(OR(AX71="",AX71=0,AU71=""),"",AU71*365/(AX71*1000000)) | AZ71: 4.2706113e+08 | BA71: 60487233 | BB71: 14446985 | BC71: 2971663 | BD71: =1000000000-999850711.5739+0.0000 | BE71: =1000000000-AZ71-BA71-BB71-BC71-BD71 | BF71: 238 | BG71: =BE71/1000000-BF71 | BH71: =BE71*25.14
A72: 45694 | B72: 5904659695 | D72: 178176120 | N72: 1316367 | P72: 24592 | R72: =N72+O72+P72+N(Q72) | S72: 0.03 | T72: =N(AC72)*S72 | U72: =N(AD72)*S72 | V72: =N(AE72)*S72 | W72: =IF(Q72="","",N(AF72)*S72) | X72: 0 | AA72: =T72+U72+V72+N(W72)+X72+Y72+N(Z72) | AC72: 1276876 | AD72: =O72-Y72 | AE72: =P72-X72 | AF72: =IF(Q72="","",Q72-Z72) | AG72: =AC72+AD72+AE72+N(AF72) | AH72: 1300731 | AI72: =AG72-AH72 | AJ72: =IF(OR(B72="",B72=0,N72=""),"",N72/B72*10000) | AK72: =IF(OR(C72="",C72=0),"",O72/C72*10000) | AL72: =IF(OR(D72="",D72=0),"",P72/D72*10000) | AM72: =IF(OR(E72="",E72=0),"",Q72/E72*10000) | AN72: 0 | AO72: 0 | AP72: =AH72+AN72+AO72 | AQ72: =AH72 | AR72: 49755.99 | AS72: 24.75 | AT72: 14496741 | AU72: 26548.785 | AV72: 989.8233 | AX72: 427.57185 | AY72: =IF(OR(AX72="",AX72=0,AU72=""),"",AU72*365/(AX72*1000000)) | AZ72: 4.2703458e+08 | BA72: 60487233 | BB72: 14496741 | BC72: 2971663 | BD72: =1000000000-999849721.7506+0.0000 | BE72: =1000000000-AZ72-BA72-BB72-BC72-BD72 | BF72: 238 | BG72: =BE72/1000000-BF72 | BH72: =BE72*24.75
A73: 45695 | B73: 6189394337 | D73: 86858735 | N73: 1531085 | P73: 26352 | R73: =N73+O73+P73+N(Q73) | S73: 0.03 | T73: =N(AC73)*S73 | U73: =N(AD73)*S73 | V73: =N(AE73)*S73 | W73: =IF(Q73="","",N(AF73)*S73) | X73: 0 | AA73: =T73+U73+V73+N(W73)+X73+Y73+N(Z73) | AC73: 1485152 | AD73: =O73-Y73 | AE73: =P73-X73 | AF73: =IF(Q73="","",Q73-Z73) | AG73: =AC73+AD73+AE73+N(AF73) | AH73: 1510714 | AI73: =AG73-AH73 | AJ73: =IF(OR(B73="",B73=0,N73=""),"",N73/B73*10000) | AK73: =IF(OR(C73="",C73=0),"",O73/C73*10000) | AL73: =IF(OR(D73="",D73=0),"",P73/D73*10000) | AM73: =IF(OR(E73="",E73=0),"",Q73/E73*10000) | AN73: 0 | AO73: 0 | AP73: =AH73+AN73+AO73 | AQ73: =AH73 | AR73: 60283.51 | AS73: 23.83 | AT73: 14557024 | AU73: 26612.271 | AV73: 827.2076 | AX73: 429.46034 | AY73: =IF(OR(AX73="",AX73=0,AU73=""),"",AU73*365/(AX73*1000000)) | AZ73: 4.2700797e+08 | BA73: 60487233 | BB73: 14557024 | BC73: 2971663 | BD73: =1000000000-999848894.5431+0.0000 | BE73: =1000000000-AZ73-BA73-BB73-BC73-BD73 | BF73: 238 | BG73: =BE73/1000000-BF73 | BH73: =BE73*23.83
A74: 45696 | B74: 3006719559 | D74: 75118825 | N74: 782416 | P74: 12064 | R74: =N74+O74+P74+N(Q74) | S74: 0.03 | T74: =N(AC74)*S74 | U74: =N(AD74)*S74 | V74: =N(AE74)*S74 | W74: =IF(Q74="","",N(AF74)*S74) | X74: 0 | AA74: =T74+U74+V74+N(W74)+X74+Y74+N(Z74) | AC74: 758944 | AD74: =O74-Y74 | AE74: =P74-X74 | AF74: =IF(Q74="","",Q74-Z74) | AG74: =AC74+AD74+AE74+N(AF74) | AH74: 770646 | AI74: =AG74-AH74 | AJ74: =IF(OR(B74="",B74=0,N74=""),"",N74/B74*10000) | AK74: =IF(OR(C74="",C74=0),"",O74/C74*10000) | AL74: =IF(OR(D74="",D74=0),"",P74/D74*10000) | AM74: =IF(OR(E74="",E74=0),"",Q74/E74*10000) | AN74: 0 | AO74: 0 | AP74: =AH74+AN74+AO74 | AQ74: =AH74 | AR74: 56388.99 | AS74: 22.83 | AT74: 14613413 | AU74: 26577.922 | AV74: 996.1893 | AX74: 428.28436 | AY74: =IF(OR(AX74="",AX74=0,AU74=""),"",AU74*365/(AX74*1000000)) | AZ74: 4.2698139e+08 | BA74: 60487233 | BB74: 14613413 | BC74: 2971663 | BD74: =1000000000-999847898.3538+0.0000 | BE74: =1000000000-AZ74-BA74-BB74-BC74-BD74 | BF74: 238 | BG74: =BE74/1000000-BF74 | BH74: =BE74*22.83
A75: 45697 | B75: 3754601891 | D75: 91079022 | N75: 983799 | P75: 10683 | R75: =N75+O75+P75+N(Q75) | S75: 0.03 | T75: =N(AC75)*S75 | U75: =N(AD75)*S75 | V75: =N(AE75)*S75 | W75: =IF(Q75="","",N(AF75)*S75) | X75: 0 | AA75: =T75+U75+V75+N(W75)+X75+Y75+N(Z75) | AC75: 954285 | AD75: =O75-Y75 | AE75: =P75-X75 | AF75: =IF(Q75="","",Q75-Z75) | AG75: =AC75+AD75+AE75+N(AF75) | AH75: 964647 | AI75: =AG75-AH75 | AJ75: =IF(OR(B75="",B75=0,N75=""),"",N75/B75*10000) | AK75: =IF(OR(C75="",C75=0),"",O75/C75*10000) | AL75: =IF(OR(D75="",D75=0),"",P75/D75*10000) | AM75: =IF(OR(E75="",E75=0),"",Q75/E75*10000) | AN75: 0 | AO75: 0 | AP75: =AH75+AN75+AO75 | AQ75: =AH75 | AR75: 30535.93 | AS75: 23.4 | AT75: 14643949 | AU75: 26528.153 | AV75: 470.7789 | AX75: 426.85498 | AY75: =IF(OR(AX75="",AX75=0,AU75=""),"",AU75*365/(AX75*1000000)) | AZ75: 4.2695487e+08 | BA75: 60487233 | BB75: 14643949 | BC75: 2971663 | BD75: =1000000000-999847427.5749+0.0000 | BE75: =1000000000-AZ75-BA75-BB75-BC75-BD75 | BF75: 238 | BG75: =BE75/1000000-BF75 | BH75: =BE75*23.4
A76: 45698 | B76: 5178632081 | D76: 107918816 | N76: 1123138 | P76: 11999 | R76: =N76+O76+P76+N(Q76) | S76: 0.03 | T76: =N(AC76)*S76 | U76: =N(AD76)*S76 | V76: =N(AE76)*S76 | W76: =IF(Q76="","",N(AF76)*S76) | X76: 0 | AA76: =T76+U76+V76+N(W76)+X76+Y76+N(Z76) | AC76: 1089443 | AD76: =O76-Y76 | AE76: =P76-X76 | AF76: =IF(Q76="","",Q76-Z76) | AG76: =AC76+AD76+AE76+N(AF76) | AH76: 1101082 | AI76: =AG76-AH76 | AJ76: =IF(OR(B76="",B76=0,N76=""),"",N76/B76*10000) | AK76: =IF(OR(C76="",C76=0),"",O76/C76*10000) | AL76: =IF(OR(D76="",D76=0),"",P76/D76*10000) | AM76: =IF(OR(E76="",E76=0),"",Q76/E76*10000) | AN76: 0 | AO76: 0 | AP76: =AH76+AN76+AO76 | AQ76: =AH76 | AR76: 55150.03 | AS76: 22.98 | AT76: 14699099 | AU76: 26525.199 | AV76: 358.1593 | AX76: 426.91151 | AY76: =IF(OR(AX76="",AX76=0,AU76=""),"",AU76*365/(AX76*1000000)) | AZ76: 4.2692834e+08 | BA76: 60487233 | BB76: 14699099 | BC76: 2971663 | BD76: =1000000000-999847069.4156+0.0000 | BE76: =1000000000-AZ76-BA76-BB76-BC76-BD76 | BF76: 238 | BG76: =BE76/1000000-BF76 | BH76: =BE76*22.98
A77: 45699 | B77: 6593863803 | D77: 142810624 | N77: 1538904 | P77: 15656 | R77: =N77+O77+P77+N(Q77) | S77: 0.03 | T77: =N(AC77)*S77 | U77: =N(AD77)*S77 | V77: =N(AE77)*S77 | W77: =IF(Q77="","",N(AF77)*S77) | X77: 0 | AA77: =T77+U77+V77+N(W77)+X77+Y77+N(Z77) | AC77: 1492737 | AD77: =O77-Y77 | AE77: =P77-X77 | AF77: =IF(Q77="","",Q77-Z77) | AG77: =AC77+AD77+AE77+N(AF77) | AH77: 1507923 | AI77: =AG77-AH77 | AJ77: =IF(OR(B77="",B77=0,N77=""),"",N77/B77*10000) | AK77: =IF(OR(C77="",C77=0),"",O77/C77*10000) | AL77: =IF(OR(D77="",D77=0),"",P77/D77*10000) | AM77: =IF(OR(E77="",E77=0),"",Q77/E77*10000) | AN77: 0 | AO77: 0 | AP77: =AH77+AN77+AO77 | AQ77: =AH77 | AR77: 43822.3 | AS77: 23.32 | AT77: 14742922 | AU77: 26523.32 | AV77: 521.8924 | AX77: 426.80892 | AY77: =IF(OR(AX77="",AX77=0,AU77=""),"",AU77*365/(AX77*1000000)) | AZ77: 4.2690182e+08 | BA77: 60487233 | BB77: 14742922 | BC77: 2971663 | BD77: =1000000000-999846547.5232+0.0000 | BE77: =1000000000-AZ77-BA77-BB77-BC77-BD77 | BF77: 238 | BG77: =BE77/1000000-BF77 | BH77: =BE77*23.32
A78: 45700 | B78: 7575580366 | D78: 122695803 | N78: 1791221 | P78: 18209 | R78: =N78+O78+P78+N(Q78) | S78: 0.03 | T78: =N(AC78)*S78 | U78: =N(AD78)*S78 | V78: =N(AE78)*S78 | W78: =IF(Q78="","",N(AF78)*S78) | X78: 0 | AA78: =T78+U78+V78+N(W78)+X78+Y78+N(Z78) | AC78: 1737484 | AD78: =O78-Y78 | AE78: =P78-X78 | AF78: =IF(Q78="","",Q78-Z78) | AG78: =AC78+AD78+AE78+N(AF78) | AH78: 1755146 | AI78: =AG78-AH78 | AJ78: =IF(OR(B78="",B78=0,N78=""),"",N78/B78*10000) | AK78: =IF(OR(C78="",C78=0),"",O78/C78*10000) | AL78: =IF(OR(D78="",D78=0),"",P78/D78*10000) | AM78: =IF(OR(E78="",E78=0),"",Q78/E78*10000) | AN78: 0 | AO78: 0 | AP78: =AH78+AN78+AO78 | AQ78: =AH78 | AR78: 63989.91 | AS78: 23.49 | AT78: 14806912 | AU78: 26541.339 | AV78: 579.0042 | AX78: 427.89424 | AY78: =IF(OR(AX78="",AX78=0,AU78=""),"",AU78*365/(AX78*1000000)) | AZ78: 4.2687528e+08 | BA78: 60487233 | BB78: 14806912 | BC78: 2971663 | BD78: =1000000000-999845968.519+0.0000 | BE78: =1000000000-AZ78-BA78-BB78-BC78-BD78 | BF78: 238 | BG78: =BE78/1000000-BF78 | BH78: =BE78*23.49
A79: 45701 | B79: 5121162004 | D79: 199613305 | N79: 1388068 | P79: 18585 | R79: =N79+O79+P79+N(Q79) | S79: 0.03 | T79: =N(AC79)*S79 | U79: =N(AD79)*S79 | V79: =N(AE79)*S79 | W79: =IF(Q79="","",N(AF79)*S79) | X79: 0 | AA79: =T79+U79+V79+N(W79)+X79+Y79+N(Z79) | AC79: 1346426 | AD79: =O79-Y79 | AE79: =P79-X79 | AF79: =IF(Q79="","",Q79-Z79) | AG79: =AC79+AD79+AE79+N(AF79) | AH79: 1364454 | AI79: =AG79-AH79 | AJ79: =IF(OR(B79="",B79=0,N79=""),"",N79/B79*10000) | AK79: =IF(OR(C79="",C79=0),"",O79/C79*10000) | AL79: =IF(OR(D79="",D79=0),"",P79/D79*10000) | AM79: =IF(OR(E79="",E79=0),"",Q79/E79*10000) | AN79: 0 | AO79: 0 | AP79: =AH79+AN79+AO79 | AQ79: =AH79 | AR79: 61012.65 | AS79: 25.84 | AT79: 14867924 | AU79: 26562.25 | AV79: 792.7335 | AX79: 428.77533 | AY79: =IF(OR(AX79="",AX79=0,AU79=""),"",AU79*365/(AX79*1000000)) | AZ79: 4.2684871e+08 | BA79: 60487233 | BB79: 14867924 | BC79: 2971663 | BD79: =1000000000-999845175.7854+0.0000 | BE79: =1000000000-AZ79-BA79-BB79-BC79-BD79 | BF79: 238 | BG79: =BE79/1000000-BF79 | BH79: =BE79*25.84
A80: 45702 | B80: 5071294404 | D80: 103410352 | N80: 1000308 | P80: 25753 | R80: =N80+O80+P80+N(Q80) | S80: 0.03 | T80: =N(AC80)*S80 | U80: =N(AD80)*S80 | V80: =N(AE80)*S80 | W80: =IF(Q80="","",N(AF80)*S80) | X80: 0 | AA80: =T80+U80+V80+N(W80)+X80+Y80+N(Z80) | AC80: 970299 | AD80: =O80-Y80 | AE80: =P80-X80 | AF80: =IF(Q80="","",Q80-Z80) | AG80: =AC80+AD80+AE80+N(AF80) | AH80: 995279 | AI80: =AG80-AH80 | AJ80: =IF(OR(B80="",B80=0,N80=""),"",N80/B80*10000) | AK80: =IF(OR(C80="",C80=0),"",O80/C80*10000) | AL80: =IF(OR(D80="",D80=0),"",P80/D80*10000) | AM80: =IF(OR(E80="",E80=0),"",Q80/E80*10000) | AN80: 0 | AO80: 0 | AP80: =AH80+AN80+AO80 | AQ80: =AH80 | AR80: 46816.71 | AS80: 26.26 | AT80: 14914741 | AU80: 26581.329 | AV80: 591.6068 | AX80: 428.77106 | AY80: =IF(OR(AX80="",AX80=0,AU80=""),"",AU80*365/(AX80*1000000)) | AZ80: 4.2682213e+08 | BA80: 60487233 | BB80: 14914741 | BC80: 2971663 | BD80: =1000000000-999844584.1786+0.0000 | BE80: =1000000000-AZ80-BA80-BB80-BC80-BD80 | BF80: 238 | BG80: =BE80/1000000-BF80 | BH80: =BE80*26.26
A81: 45703 | B81: 2569566271 | D81: 78021652 | N81: 724327 | P81: 17622 | R81: =N81+O81+P81+N(Q81) | S81: 0.03 | T81: =N(AC81)*S81 | U81: =N(AD81)*S81 | V81: =N(AE81)*S81 | W81: =IF(Q81="","",N(AF81)*S81) | X81: 0 | AA81: =T81+U81+V81+N(W81)+X81+Y81+N(Z81) | AC81: 702597 | AD81: =O81-Y81 | AE81: =P81-X81 | AF81: =IF(Q81="","",Q81-Z81) | AG81: =AC81+AD81+AE81+N(AF81) | AH81: 719690 | AI81: =AG81-AH81 | AJ81: =IF(OR(B81="",B81=0,N81=""),"",N81/B81*10000) | AK81: =IF(OR(C81="",C81=0),"",O81/C81*10000) | AL81: =IF(OR(D81="",D81=0),"",P81/D81*10000) | AM81: =IF(OR(E81="",E81=0),"",Q81/E81*10000) | AN81: 0 | AO81: 0 | AP81: =AH81+AN81+AO81 | AQ81: =AH81 | AR81: 50322.14 | AS81: 26.2 | AT81: 14965063 | AU81: 26587.268 | AV81: 978.1297 | AX81: 429.01678 | AY81: =IF(OR(AX81="",AX81=0,AU81=""),"",AU81*365/(AX81*1000000)) | AZ81: 4.2679555e+08 | BA81: 60487233 | BB81: 14965063 | BC81: 2971663 | BD81: =1000000000-999843606.0489+0.0000 | BE81: =1000000000-AZ81-BA81-BB81-BC81-BD81 | BF81: 238 | BG81: =BE81/1000000-BF81 | BH81: =BE81*26.2
A82: 45704 | B82: 2576463335 | D82: 120737014 | N82: 599409 | P82: 8856 | R82: =N82+O82+P82+N(Q82) | S82: 0.03 | T82: =N(AC82)*S82 | U82: =N(AD82)*S82 | V82: =N(AE82)*S82 | W82: =IF(Q82="","",N(AF82)*S82) | X82: 0 | AA82: =T82+U82+V82+N(W82)+X82+Y82+N(Z82) | AC82: 581427 | AD82: =O82-Y82 | AE82: =P82-X82 | AF82: =IF(Q82="","",Q82-Z82) | AG82: =AC82+AD82+AE82+N(AF82) | AH82: 590017 | AI82: =AG82-AH82 | AJ82: =IF(OR(B82="",B82=0,N82=""),"",N82/B82*10000) | AK82: =IF(OR(C82="",C82=0),"",O82/C82*10000) | AL82: =IF(OR(D82="",D82=0),"",P82/D82*10000) | AM82: =IF(OR(E82="",E82=0),"",Q82/E82*10000) | AN82: 0 | AO82: 0 | AP82: =AH82+AN82+AO82 | AQ82: =AH82 | AR82: 22361.35 | AS82: 25.72 | AT82: 14987424 | AU82: 26607.02 | AV82: 420.737 | AX82: 430.11068 | AY82: =IF(OR(AX82="",AX82=0,AU82=""),"",AU82*365/(AX82*1000000)) | AZ82: 4.2676894e+08 | BA82: 60487233 | BB82: 14987424 | BC82: 2971663 | BD82: =1000000000-999843185.3119+0.0000 | BE82: =1000000000-AZ82-BA82-BB82-BC82-BD82 | BF82: 238 | BG82: =BE82/1000000-BF82 | BH82: =BE82*25.72
A83: 45705 | B83: 5049366131 | D83: 360271474 | N83: 1305683 | P83: 18954 | R83: =N83+O83+P83+N(Q83) | S83: 0.03 | T83: =N(AC83)*S83 | U83: =N(AD83)*S83 | V83: =N(AE83)*S83 | W83: =IF(Q83="","",N(AF83)*S83) | X83: 0 | AA83: =T83+U83+V83+N(W83)+X83+Y83+N(Z83) | AC83: 1266513 | AD83: =O83-Y83 | AE83: =P83-X83 | AF83: =IF(Q83="","",Q83-Z83) | AG83: =AC83+AD83+AE83+N(AF83) | AH83: 1284898 | AI83: =AG83-AH83 | AJ83: =IF(OR(B83="",B83=0,N83=""),"",N83/B83*10000) | AK83: =IF(OR(C83="",C83=0),"",O83/C83*10000) | AL83: =IF(OR(D83="",D83=0),"",P83/D83*10000) | AM83: =IF(OR(E83="",E83=0),"",Q83/E83*10000) | AN83: 0 | AO83: 0 | AP83: =AH83+AN83+AO83 | AQ83: =AH83 | AR83: 30930.4 | AS83: 26.8 | AT83: 15018355 | AU83: 26613.699 | AV83: 311.4459 | AX83: 429.38031 | AY83: =IF(OR(AX83="",AX83=0,AU83=""),"",AU83*365/(AX83*1000000)) | AZ83: 4.2674232e+08 | BA83: 60487233 | BB83: 15018355 | BC83: 2971663 | BD83: =1000000000-999842873.8661+0.0000 | BE83: =1000000000-AZ83-BA83-BB83-BC83-BD83 | BF83: 238 | BG83: =BE83/1000000-BF83 | BH83: =BE83*26.8
A84: 45706 | B84: 6787245918 | D84: 146705782 | N84: 1594393 | P84: 55805 | R84: =N84+O84+P84+N(Q84) | S84: 0.03 | T84: =N(AC84)*S84 | U84: =N(AD84)*S84 | V84: =N(AE84)*S84 | W84: =IF(Q84="","",N(AF84)*S84) | X84: 0 | AA84: =T84+U84+V84+N(W84)+X84+Y84+N(Z84) | AC84: 1546561 | AD84: =O84-Y84 | AE84: =P84-X84 | AF84: =IF(Q84="","",Q84-Z84) | AG84: =AC84+AD84+AE84+N(AF84) | AH84: 1600692 | AI84: =AG84-AH84 | AJ84: =IF(OR(B84="",B84=0,N84=""),"",N84/B84*10000) | AK84: =IF(OR(C84="",C84=0),"",O84/C84*10000) | AL84: =IF(OR(D84="",D84=0),"",P84/D84*10000) | AM84: =IF(OR(E84="",E84=0),"",Q84/E84*10000) | AN84: 0 | AO84: 0 | AP84: =AH84+AN84+AO84 | AQ84: =AH84 | AR84: 56574.91 | AS84: 25.38 | AT84: 15074930 | AU84: 26591.793 | AV84: 491.1939 | AX84: 429.55342 | AY84: =IF(OR(AX84="",AX84=0,AU84=""),"",AU84*365/(AX84*1000000)) | AZ84: 4.2671573e+08 | BA84: 60487233 | BB84: 15074930 | BC84: 2971663 | BD84: =1000000000-999842382.6722+0.0000 | BE84: =1000000000-AZ84-BA84-BB84-BC84-BD84 | BF84: 238 | BG84: =BE84/1000000-BF84 | BH84: =BE84*25.38
A85: 45707 | B85: 3901859791 | D85: 136622361 | N85: 987639 | P85: 22056 | R85: =N85+O85+P85+N(Q85) | S85: 0.03 | T85: =N(AC85)*S85 | U85: =N(AD85)*S85 | V85: =N(AE85)*S85 | W85: =IF(Q85="","",N(AF85)*S85) | X85: 0 | AA85: =T85+U85+V85+N(W85)+X85+Y85+N(Z85) | AC85: 958010 | AD85: =O85-Y85 | AE85: =P85-X85 | AF85: =IF(Q85="","",Q85-Z85) | AG85: =AC85+AD85+AE85+N(AF85) | AH85: 979405 | AI85: =AG85-AH85 | AJ85: =IF(OR(B85="",B85=0,N85=""),"",N85/B85*10000) | AK85: =IF(OR(C85="",C85=0),"",O85/C85*10000) | AL85: =IF(OR(D85="",D85=0),"",P85/D85*10000) | AM85: =IF(OR(E85="",E85=0),"",Q85/E85*10000) | AN85: 0 | AO85: 0 | AP85: =AH85+AN85+AO85 | AQ85: =AH85 | AR85: 55665.71 | AS85: 24.08 | AT85: 15130595 | AU85: 26568.731 | AV85: 1766.3576 | AX85: 428.44817 | AY85: =IF(OR(AX85="",AX85=0,AU85=""),"",AU85*365/(AX85*1000000)) | AZ85: 4.2668916e+08 | BA85: 60487233 | BB85: 15130595 | BC85: 2971663 | BD85: =1000000000-999840616.3146+0.0000 | BE85: =1000000000-AZ85-BA85-BB85-BC85-BD85 | BF85: 238 | BG85: =BE85/1000000-BF85 | BH85: =BE85*24.08
A86: 45708 | B86: 5037378691 | D86: 206747279 | N86: 1174903 | P86: 20113 | R86: =N86+O86+P86+N(Q86) | S86: 0.03 | T86: =N(AC86)*S86 | U86: =N(AD86)*S86 | V86: =N(AE86)*S86 | W86: =IF(Q86="","",N(AF86)*S86) | X86: 0 | AA86: =T86+U86+V86+N(W86)+X86+Y86+N(Z86) | AC86: 1139656 | AD86: =O86-Y86 | AE86: =P86-X86 | AF86: =IF(Q86="","",Q86-Z86) | AG86: =AC86+AD86+AE86+N(AF86) | AH86: 1159166 | AI86: =AG86-AH86 | AJ86: =IF(OR(B86="",B86=0,N86=""),"",N86/B86*10000) | AK86: =IF(OR(C86="",C86=0),"",O86/C86*10000) | AL86: =IF(OR(D86="",D86=0),"",P86/D86*10000) | AM86: =IF(OR(E86="",E86=0),"",Q86/E86*10000) | AN86: 0 | AO86: 0 | AP86: =AH86+AN86+AO86 | AQ86: =AH86 | AR86: 42610.07 | AS86: 24.06 | AT86: 15173205 | AU86: 26580.86 | AV86: 672.5468 | AX86: 427.90059 | AY86: =IF(OR(AX86="",AX86=0,AU86=""),"",AU86*365/(AX86*1000000)) | AZ86: 4.2666258e+08 | BA86: 60487233 | BB86: 15173205 | BC86: 2971663 | BD86: =1000000000-999839943.7678+0.0000 | BE86: =1000000000-AZ86-BA86-BB86-BC86-BD86 | BF86: 238 | BG86: =BE86/1000000-BF86 | BH86: =BE86*24.06
A87: 45709 | B87: 10385529202 | D87: 71766053 | N87: 2360338 | P87: 27835 | R87: =N87+O87+P87+N(Q87) | S87: 0.03 | T87: =N(AC87)*S87 | U87: =N(AD87)*S87 | V87: =N(AE87)*S87 | W87: =IF(Q87="","",N(AF87)*S87) | X87: 0 | AA87: =T87+U87+V87+N(W87)+X87+Y87+N(Z87) | AC87: 2289528 | AD87: =O87-Y87 | AE87: =P87-X87 | AF87: =IF(Q87="","",Q87-Z87) | AG87: =AC87+AD87+AE87+N(AF87) | AH87: 2316528 | AI87: =AG87-AH87 | AJ87: =IF(OR(B87="",B87=0,N87=""),"",N87/B87*10000) | AK87: =IF(OR(C87="",C87=0),"",O87/C87*10000) | AL87: =IF(OR(D87="",D87=0),"",P87/D87*10000) | AM87: =IF(OR(E87="",E87=0),"",Q87/E87*10000) | AN87: 0 | AO87: 0 | AP87: =AH87+AN87+AO87 | AQ87: =AH87 | AR87: 53987.02 | AS87: 24.45 | AT87: 15227193 | AU87: 26551.304 | AV87: 563.1262 | AX87: 427.61213 | AY87: =IF(OR(AX87="",AX87=0,AU87=""),"",AU87*365/(AX87*1000000)) | AZ87: 4.2663603e+08 | BA87: 60487233 | BB87: 15227193 | BC87: 2971663 | BD87: =1000000000-999839380.6415+0.0000 | BE87: =1000000000-AZ87-BA87-BB87-BC87-BD87 | BF87: 238 | BG87: =BE87/1000000-BF87 | BH87: =BE87*24.45
A88: 45710 | B88: 3022212830 | D88: 87664629 | N88: 886199 | P88: 12423 | R88: =N88+O88+P88+N(Q88) | S88: 0.03 | T88: =N(AC88)*S88 | U88: =N(AD88)*S88 | V88: =N(AE88)*S88 | W88: =IF(Q88="","",N(AF88)*S88) | X88: 0 | AA88: =T88+U88+V88+N(W88)+X88+Y88+N(Z88) | AC88: 859613 | AD88: =O88-Y88 | AE88: =P88-X88 | AF88: =IF(Q88="","",Q88-Z88) | AG88: =AC88+AD88+AE88+N(AF88) | AH88: 871664 | AI88: =AG88-AH88 | AJ88: =IF(OR(B88="",B88=0,N88=""),"",N88/B88*10000) | AK88: =IF(OR(C88="",C88=0),"",O88/C88*10000) | AL88: =IF(OR(D88="",D88=0),"",P88/D88*10000) | AM88: =IF(OR(E88="",E88=0),"",Q88/E88*10000) | AN88: 0 | AO88: 0 | AP88: =AH88+AN88+AO88 | AQ88: =AH88 | AR88: 87874.72 | AS88: 24.99 | AT88: 15315067 | AU88: 26531.537 | AV88: 957.8834 | AX88: 426.77454 | AY88: =IF(OR(AX88="",AX88=0,AU88=""),"",AU88*365/(AX88*1000000)) | AZ88: 4.266095e+08 | BA88: 60487233 | BB88: 15315067 | BC88: 2971663 | BD88: =1000000000-999838422.7581+0.0000 | BE88: =1000000000-AZ88-BA88-BB88-BC88-BD88 | BF88: 238 | BG88: =BE88/1000000-BF88 | BH88: =BE88*24.99
A89: 45711 | B89: 3357930485 | D89: 313527932 | N89: 739684 | P89: 13884 | R89: =N89+O89+P89+N(Q89) | S89: 0.03 | T89: =N(AC89)*S89 | U89: =N(AD89)*S89 | V89: =N(AE89)*S89 | W89: =IF(Q89="","",N(AF89)*S89) | X89: 0 | AA89: =T89+U89+V89+N(W89)+X89+Y89+N(Z89) | AC89: 717494 | AD89: =O89-Y89 | AE89: =P89-X89 | AF89: =IF(Q89="","",Q89-Z89) | AG89: =AC89+AD89+AE89+N(AF89) | AH89: 730962 | AI89: =AG89-AH89 | AJ89: =IF(OR(B89="",B89=0,N89=""),"",N89/B89*10000) | AK89: =IF(OR(C89="",C89=0),"",O89/C89*10000) | AL89: =IF(OR(D89="",D89=0),"",P89/D89*10000) | AM89: =IF(OR(E89="",E89=0),"",Q89/E89*10000) | AN89: 0 | AO89: 0 | AP89: =AH89+AN89+AO89 | AQ89: =AH89 | AR89: 30681.22 | AS89: 24.79 | AT89: 15345748 | AU89: 26510.007 | AV89: 272.4934 | AX89: 426.16778 | AY89: =IF(OR(AX89="",AX89=0,AU89=""),"",AU89*365/(AX89*1000000)) | AZ89: 4.2658299e+08 | BA89: 60487233 | BB89: 15345748 | BC89: 2971663 | BD89: =1000000000-999838150.2647+0.0000 | BE89: =1000000000-AZ89-BA89-BB89-BC89-BD89 | BF89: 238 | BG89: =BE89/1000000-BF89 | BH89: =BE89*24.79
A90: 45712 | B90: 9442757917 | D90: 403523120 | N90: 1495241 | P90: 36499 | R90: =N90+O90+P90+N(Q90) | S90: 0.03 | T90: =N(AC90)*S90 | U90: =N(AD90)*S90 | V90: =N(AE90)*S90 | W90: =IF(Q90="","",N(AF90)*S90) | X90: 0 | AA90: =T90+U90+V90+N(W90)+X90+Y90+N(Z90) | AC90: 1450384 | AD90: =O90-Y90 | AE90: =P90-X90 | AF90: =IF(Q90="","",Q90-Z90) | AG90: =AC90+AD90+AE90+N(AF90) | AH90: 1485788 | AI90: =AG90-AH90 | AJ90: =IF(OR(B90="",B90=0,N90=""),"",N90/B90*10000) | AK90: =IF(OR(C90="",C90=0),"",O90/C90*10000) | AL90: =IF(OR(D90="",D90=0),"",P90/D90*10000) | AM90: =IF(OR(E90="",E90=0),"",Q90/E90*10000) | AN90: 0 | AO90: 0 | AP90: =AH90+AN90+AO90 | AQ90: =AH90 | AR90: 49548.46 | AS90: 23.15 | AT90: 15395297 | AU90: 26495.592 | AV90: 359.0801 | AX90: 425.75838 | AY90: =IF(OR(AX90="",AX90=0,AU90=""),"",AU90*365/(AX90*1000000)) | AZ90: 4.2655649e+08 | BA90: 60487233 | BB90: 15395297 | BC90: 2971663 | BD90: =1000000000-999837791.1845+0.0000 | BE90: =1000000000-AZ90-BA90-BB90-BC90-BD90 | BF90: 238 | BG90: =BE90/1000000-BF90 | BH90: =BE90*23.15
A91: 45713 | B91: 13212926718 | D91: 252882738 | N91: 3778850 | P91: 76421 | R91: =N91+O91+P91+N(Q91) | S91: 0.03 | T91: =N(AC91)*S91 | U91: =N(AD91)*S91 | V91: =N(AE91)*S91 | W91: =IF(Q91="","",N(AF91)*S91) | X91: 0 | AA91: =T91+U91+V91+N(W91)+X91+Y91+N(Z91) | AC91: 3665484 | AD91: =O91-Y91 | AE91: =P91-X91 | AF91: =IF(Q91="","",Q91-Z91) | AG91: =AC91+AD91+AE91+N(AF91) | AH91: 3739612 | AI91: =AG91-AH91 | AJ91: =IF(OR(B91="",B91=0,N91=""),"",N91/B91*10000) | AK91: =IF(OR(C91="",C91=0),"",O91/C91*10000) | AL91: =IF(OR(D91="",D91=0),"",P91/D91*10000) | AM91: =IF(OR(E91="",E91=0),"",Q91/E91*10000) | AN91: 0 | AO91: 0 | AP91: =AH91+AN91+AO91 | AQ91: =AH91 | AR91: 39290.52 | AS91: 19.88 | AT91: 15434587 | AU91: 26462.362 | AV91: 1448.4853 | AX91: 424.00807 | AY91: =IF(OR(AX91="",AX91=0,AU91=""),"",AU91*365/(AX91*1000000)) | AZ91: 4.2653003e+08 | BA91: 60487233 | BB91: 15434587 | BC91: 2971663 | BD91: =1000000000-999836342.6993+0.0000 | BE91: =1000000000-AZ91-BA91-BB91-BC91-BD91 | BF91: 238 | BG91: =BE91/1000000-BF91 | BH91: =BE91*19.88
A92: 45714 | B92: 9361694444 | D92: 163029559 | N92: 2179082 | P92: 36925 | R92: =N92+O92+P92+N(Q92) | S92: 0.03 | T92: =N(AC92)*S92 | U92: =N(AD92)*S92 | V92: =N(AE92)*S92 | W92: =IF(Q92="","",N(AF92)*S92) | X92: 0 | AA92: =T92+U92+V92+N(W92)+X92+Y92+N(Z92) | AC92: 2113710 | AD92: =O92-Y92 | AE92: =P92-X92 | AF92: =IF(Q92="","",Q92-Z92) | AG92: =AC92+AD92+AE92+N(AF92) | AH92: 2149527 | AI92: =AG92-AH92 | AJ92: =IF(OR(B92="",B92=0,N92=""),"",N92/B92*10000) | AK92: =IF(OR(C92="",C92=0),"",O92/C92*10000) | AL92: =IF(OR(D92="",D92=0),"",P92/D92*10000) | AM92: =IF(OR(E92="",E92=0),"",Q92/E92*10000) | AN92: 0 | AO92: 0 | AP92: =AH92+AN92+AO92 | AQ92: =AH92 | AR92: 206273.87 | AS92: 20.19 | AT92: 15640861 | AU92: 26402.54 | AV92: 2533.9117 | AX92: 422.61334 | AY92: =IF(OR(AX92="",AX92=0,AU92=""),"",AU92*365/(AX92*1000000)) | AZ92: 4.2650363e+08 | BA92: 60487233 | BB92: 15640861 | BC92: 2971663 | BD92: =1000000000-999833808.7876+0.0000 | BE92: =1000000000-AZ92-BA92-BB92-BC92-BD92 | BF92: 238 | BG92: =BE92/1000000-BF92 | BH92: =BE92*20.19
A93: 45715 | B93: 6796939579 | D93: 214669060 | N93: 1537557 | P93: 21492 | R93: =N93+O93+P93+N(Q93) | S93: 0.03 | T93: =N(AC93)*S93 | U93: =N(AD93)*S93 | V93: =N(AE93)*S93 | W93: =IF(Q93="","",N(AF93)*S93) | X93: 0 | AA93: =T93+U93+V93+N(W93)+X93+Y93+N(Z93) | AC93: 1491430 | AD93: =O93-Y93 | AE93: =P93-X93 | AF93: =IF(Q93="","",Q93-Z93) | AG93: =AC93+AD93+AE93+N(AF93) | AH93: 1512278 | AI93: =AG93-AH93 | AJ93: =IF(OR(B93="",B93=0,N93=""),"",N93/B93*10000) | AK93: =IF(OR(C93="",C93=0),"",O93/C93*10000) | AL93: =IF(OR(D93="",D93=0),"",P93/D93*10000) | AM93: =IF(OR(E93="",E93=0),"",Q93/E93*10000) | AN93: 0 | AO93: 0 | AP93: =AH93+AN93+AO93 | AQ93: =AH93 | AR93: 113214.79 | AS93: 19.56 | AT93: 15754076 | AU93: 26370.782 | AV93: 1291.9301 | AX93: 422.10103 | AY93: =IF(OR(AX93="",AX93=0,AU93=""),"",AU93*365/(AX93*1000000)) | AZ93: 4.2647726e+08 | BA93: 60487233 | BB93: 15754076 | BC93: 2971663 | BD93: =1000000000-999832516.8574+0.0000 | BE93: =1000000000-AZ93-BA93-BB93-BC93-BD93 | BF93: 238 | BG93: =BE93/1000000-BF93 | BH93: =BE93*19.56
A94: 45716 | B94: 11157922813 | D94: 87391052 | N94: 2474574 | P94: 33048 | R94: =N94+O94+P94+N(Q94) | S94: 0.03 | T94: =N(AC94)*S94 | U94: =N(AD94)*S94 | V94: =N(AE94)*S94 | W94: =IF(Q94="","",N(AF94)*S94) | X94: 0 | AA94: =T94+U94+V94+N(W94)+X94+Y94+N(Z94) | AC94: 2400337 | AD94: =O94-Y94 | AE94: =P94-X94 | AF94: =IF(Q94="","",Q94-Z94) | AG94: =AC94+AD94+AE94+N(AF94) | AH94: 2432393 | AI94: =AG94-AH94 | AJ94: =IF(OR(B94="",B94=0,N94=""),"",N94/B94*10000) | AK94: =IF(OR(C94="",C94=0),"",O94/C94*10000) | AL94: =IF(OR(D94="",D94=0),"",P94/D94*10000) | AM94: =IF(OR(E94="",E94=0),"",Q94/E94*10000) | AN94: 0 | AO94: 0 | AP94: =AH94+AN94+AO94 | AQ94: =AH94 | AR94: 109659.97 | AS94: 20.87 | AT94: 15863736 | AU94: 26389.878 | AV94: 800.0369 | AX94: 421.8219 | AY94: =IF(OR(AX94="",AX94=0,AU94=""),"",AU94*365/(AX94*1000000)) | AZ94: 4.2645087e+08 | BA94: 60487233 | BB94: 15863736 | BC94: 2971663 | BD94: =1000000000-999831716.8206+0.0000 | BE94: =1000000000-AZ94-BA94-BB94-BC94-BD94 | BF94: 238 | BG94: =BE94/1000000-BF94 | BH94: =BE94*20.87
A95: 45717 | B95: 4300489523 | D95: 230865213 | N95: 1004215 | P95: 12337 | R95: =N95+O95+P95+N(Q95) | S95: 0.03 | T95: =N(AC95)*S95 | U95: =N(AD95)*S95 | V95: =N(AE95)*S95 | W95: =IF(Q95="","",N(AF95)*S95) | X95: 0 | AA95: =T95+U95+V95+N(W95)+X95+Y95+N(Z95) | AC95: 974089 | AD95: =O95-Y95 | AE95: =P95-X95 | AF95: =IF(Q95="","",Q95-Z95) | AG95: =AC95+AD95+AE95+N(AF95) | AH95: 986055 | AI95: =AG95-AH95 | AJ95: =IF(OR(B95="",B95=0,N95=""),"",N95/B95*10000) | AK95: =IF(OR(C95="",C95=0),"",O95/C95*10000) | AL95: =IF(OR(D95="",D95=0),"",P95/D95*10000) | AM95: =IF(OR(E95="",E95=0),"",Q95/E95*10000) | AN95: 0 | AO95: 0 | AP95: =AH95+AN95+AO95 | AQ95: =AH95 | AR95: 92064.7 | AS95: 19.95 | AT95: 15955801 | AU95: 26354.432 | AV95: 1113.9076 | AX95: 421.27242 | AY95: =IF(OR(AX95="",AX95=0,AU95=""),"",AU95*365/(AX95*1000000)) | AZ95: 4.2642451e+08 | BA95: 60487233 | BB95: 15955801 | BC95: 2971663 | BD95: =1000000000-999830602.913+0.0000 | BE95: =1000000000-AZ95-BA95-BB95-BC95-BD95 | BF95: 238 | BG95: =BE95/1000000-BF95 | BH95: =BE95*19.95
A96: 45718 | B96: 11125716133 | D96: 260215664 | N96: 2590972 | P96: 31229 | R96: =N96+O96+P96+N(Q96) | S96: 0.03 | T96: =N(AC96)*S96 | U96: =N(AD96)*S96 | V96: =N(AE96)*S96 | W96: =IF(Q96="","",N(AF96)*S96) | X96: 0 | AA96: =T96+U96+V96+N(W96)+X96+Y96+N(Z96) | AC96: 2513243 | AD96: =O96-Y96 | AE96: =P96-X96 | AF96: =IF(Q96="","",Q96-Z96) | AG96: =AC96+AD96+AE96+N(AF96) | AH96: 2543535 | AI96: =AG96-AH96 | AJ96: =IF(OR(B96="",B96=0,N96=""),"",N96/B96*10000) | AK96: =IF(OR(C96="",C96=0),"",O96/C96*10000) | AL96: =IF(OR(D96="",D96=0),"",P96/D96*10000) | AM96: =IF(OR(E96="",E96=0),"",Q96/E96*10000) | AN96: 0 | AO96: 0 | AP96: =AH96+AN96+AO96 | AQ96: =AH96 | AR96: 42507.7 | AS96: 19.6 | AT96: 15998308 | AU96: 26347.556 | AV96: 456.8228 | AX96: 421.32777 | AY96: =IF(OR(AX96="",AX96=0,AU96=""),"",AU96*365/(AX96*1000000)) | AZ96: 4.2639817e+08 | BA96: 60487233 | BB96: 15998308 | BC96: 2971663 | BD96: =1000000000-999830146.0902+0.0000 | BE96: =1000000000-AZ96-BA96-BB96-BC96-BD96 | BF96: 238 | BG96: =BE96/1000000-BF96 | BH96: =BE96*19.6
A97: 45719 | B97: 11687296549 | D97: 277747349 | N97: 2348731 | P97: 31999 | R97: =N97+O97+P97+N(Q97) | S97: 0.03 | T97: =N(AC97)*S97 | U97: =N(AD97)*S97 | V97: =N(AE97)*S97 | W97: =IF(Q97="","",N(AF97)*S97) | X97: 0 | AA97: =T97+U97+V97+N(W97)+X97+Y97+N(Z97) | AC97: 2278269 | AD97: =O97-Y97 | AE97: =P97-X97 | AF97: =IF(Q97="","",Q97-Z97) | AG97: =AC97+AD97+AE97+N(AF97) | AH97: 2309308 | AI97: =AG97-AH97 | AJ97: =IF(OR(B97="",B97=0,N97=""),"",N97/B97*10000) | AK97: =IF(OR(C97="",C97=0),"",O97/C97*10000) | AL97: =IF(OR(D97="",D97=0),"",P97/D97*10000) | AM97: =IF(OR(E97="",E97=0),"",Q97/E97*10000) | AN97: 0 | AO97: 0 | AP97: =AH97+AN97+AO97 | AQ97: =AH97 | AR97: 156706.33 | AS97: 20.53 | AT97: 16155015 | AU97: 26343.694 | AV97: 1076.7938 | AX97: 420.61561 | AY97: =IF(OR(AX97="",AX97=0,AU97=""),"",AU97*365/(AX97*1000000)) | AZ97: 4.2637182e+08 | BA97: 60487233 | BB97: 16155015 | BC97: 2971663 | BD97: =1000000000-999829069.2964+0.0000 | BE97: =1000000000-AZ97-BA97-BB97-BC97-BD97 | BF97: 238 | BG97: =BE97/1000000-BF97 | BH97: =BE97*20.53
A98: 45720 | B98: 10923024322 | D98: 143679985 | N98: 2789913 | P98: 47916 | R98: =N98+O98+P98+N(Q98) | S98: 0.03 | T98: =N(AC98)*S98 | U98: =N(AD98)*S98 | V98: =N(AE98)*S98 | W98: =IF(Q98="","",N(AF98)*S98) | X98: 0 | AA98: =T98+U98+V98+N(W98)+X98+Y98+N(Z98) | AC98: 2706216 | AD98: =O98-Y98 | AE98: =P98-X98 | AF98: =IF(Q98="","",Q98-Z98) | AG98: =AC98+AD98+AE98+N(AF98) | AH98: 2752695 | AI98: =AG98-AH98 | AJ98: =IF(OR(B98="",B98=0,N98=""),"",N98/B98*10000) | AK98: =IF(OR(C98="",C98=0),"",O98/C98*10000) | AL98: =IF(OR(D98="",D98=0),"",P98/D98*10000) | AM98: =IF(OR(E98="",E98=0),"",Q98/E98*10000) | AN98: 0 | AO98: 0 | AP98: =AH98+AN98+AO98 | AQ98: =AH98 | AR98: 157081.77 | AS98: 17.88 | AT98: 16312097 | AU98: 26300.191 | AV98: 1191.9757 | AX98: 419.72848 | AY98: =IF(OR(AX98="",AX98=0,AU98=""),"",AU98*365/(AX98*1000000)) | AZ98: 4.2634552e+08 | BA98: 60487233 | BB98: 16312097 | BC98: 2971663 | BD98: =1000000000-999827877.3207+0.0000 | BE98: =1000000000-AZ98-BA98-BB98-BC98-BD98 | BF98: 238 | BG98: =BE98/1000000-BF98 | BH98: =BE98*17.88
A99: 45721 | B99: 6393102152 | D99: 171189803 | N99: 1450674 | P99: 20047 | R99: =N99+O99+P99+N(Q99) | S99: 0.03 | T99: =N(AC99)*S99 | U99: =N(AD99)*S99 | V99: =N(AE99)*S99 | W99: =IF(Q99="","",N(AF99)*S99) | X99: 0 | AA99: =T99+U99+V99+N(W99)+X99+Y99+N(Z99) | AC99: 1407154 | AD99: =O99-Y99 | AE99: =P99-X99 | AF99: =IF(Q99="","",Q99-Z99) | AG99: =AC99+AD99+AE99+N(AF99) | AH99: 1426600 | AI99: =AG99-AH99 | AJ99: =IF(OR(B99="",B99=0,N99=""),"",N99/B99*10000) | AK99: =IF(OR(C99="",C99=0),"",O99/C99*10000) | AL99: =IF(OR(D99="",D99=0),"",P99/D99*10000) | AM99: =IF(OR(E99="",E99=0),"",Q99/E99*10000) | AN99: 0 | AO99: 0 | AP99: =AH99+AN99+AO99 | AQ99: =AH99 | AR99: 117418.29 | AS99: 17.09 | AT99: 16429515 | AU99: 26023.156 | AV99: 2036.1675 | AX99: 418.28364 | AY99: =IF(OR(AX99="",AX99=0,AU99=""),"",AU99*365/(AX99*1000000)) | AZ99: 4.263195e+08 | BA99: 60487233 | BB99: 16429515 | BC99: 2971663 | BD99: =1000000000-999825841.1532+0.0000 | BE99: =1000000000-AZ99-BA99-BB99-BC99-BD99 | BF99: 238 | BG99: =BE99/1000000-BF99 | BH99: =BE99*17.09
A100: 45722 | B100: 6898925844 | D100: 199378699 | N100: 1566336 | P100: 24157 | R100: =N100+O100+P100+N(Q100) | S100: 0.03 | T100: =N(AC100)*S100 | U100: =N(AD100)*S100 | V100: =N(AE100)*S100 | W100: =IF(Q100="","",N(AF100)*S100) | X100: 0 | AA100: =T100+U100+V100+N(W100)+X100+Y100+N(Z100) | AC100: 1519346 | AD100: =O100-Y100 | AE100: =P100-X100 | AF100: =IF(Q100="","",Q100-Z100) | AG100: =AC100+AD100+AE100+N(AF100) | AH100: 1542778 | AI100: =AG100-AH100 | AJ100: =IF(OR(B100="",B100=0,N100=""),"",N100/B100*10000) | AK100: =IF(OR(C100="",C100=0),"",O100/C100*10000) | AL100: =IF(OR(D100="",D100=0),"",P100/D100*10000) | AM100: =IF(OR(E100="",E100=0),"",Q100/E100*10000) | AN100: 0 | AO100: 0 | AP100: =AH100+AN100+AO100 | AQ100: =AH100 | AR100: 82700.41 | AS100: 17.18 | AT100: 16512215 | AU100: 26246.193 | AV100: 835.7671 | AX100: 418.42368 | AY100: =IF(OR(AX100="",AX100=0,AU100=""),"",AU100*365/(AX100*1000000)) | AZ100: 4.2629325e+08 | BA100: 60487233 | BB100: 16512215 | BC100: 2971663 | BD100: =1000000000-999825005.3861+0.0000 | BE100: =1000000000-AZ100-BA100-BB100-BC100-BD100 | BF100: 238 | BG100: =BE100/1000000-BF100 | BH100: =BE100*17.18
...

Sheet Quarterly Model
A1: HYPERLIQUID (HYPE) — QUARTERLY MODEL. Same columns as Daily. Flows summed (SUMIFS); stocks/rates at period-end; OTS at quarter-end.
D2: VOLUME ($) | H2: HIP-3 VOLUME BY CATEGORY ($) | P2: GROSS FEES ($) [user-paid] | U2: FEE → REVENUE BRIDGE [deductions, $] | AE2: REVENUE TO HYPERCORE ($) | AL2: IMPLIED TAKE-RATE (bps) | AP2: OTHER REVENUE ($) | AS2: ASSISTANCE FUND & SUPPLY | BB2: OTS (Hyperliquid Strategies basis)
A3: Quarter | B3: Start | C3: End | D3: Core Crypto Perp Vol ($) | E3: HIP-3 Perp Vol ($) | F3: Spot Vol ($) | G3: HIP-4 Vol ($) | H3: HIP-3 Commodities ($) | I3: HIP-3 Crypto ($) | J3: HIP-3 FX ($) | K3: HIP-3 Indices ($) | L3: HIP-3 Pre-IPO ($) | M3: HIP-3 Equities ($) | N3: HIP-3 Cat Total ($) | O3: Pro-rate Factor Applied | P3: Core Crypto Perp Fees ($) | Q3: HIP-3 Gross Fees ($) | R3: Spot Fees incl Unit ($) | S3: HIP-4 Fees ($) | T3: Total Gross Fees ($) | U3: HLP Rate | V3: (-) HLP on Core Perp ($) | W3: (-) HLP on HIP-3 ($) | X3: (-) HLP on Spot ($) | Y3: (-) HLP on HIP-4 ($) | Z3: (-) Unit Protocol Fees ($) | AA3: (-) HIP-3 Deployer Fees ($) | AB3: (-) HIP-4 Deployer Fees ($) | AC3: Total Deductions ($) | AD3: Builder Code Fees [on-top, not deducted] ($) | AE3: Core Crypto Perp Revenue ($) | AF3: HIP-3 Revenue ($) | AG3: Spot Revenue ($) | AH3: HIP-4 Revenue ($) | AI3: = HyperCore Revenue (model) ($) | AJ3: HyperCore Revenue ($) | AK3: Accrual less Buyback ($) | AL3: Core Perp Take-Rate (bps) | AM3: HIP-3 Take-Rate (bps) | AN3: Spot Take-Rate (bps) | AO3: HIP-4 Take-Rate (bps) | AP3: HyperEVM Burn ($) | AQ3: Auction Burn ($) | AR3: Total Revenue ($) | AS3: Revenue -> AF ($) | AT3: Buyback HYPE | AU3: Buyback Avg Price ($) | AV3: AF HYPE Balance | AW3: Staking Emissions (HYPE) | AX3: Fee Burn (HYPE) | AY3: Team Tokens Unlocked (HYPE) | AZ3: HYPE Staked (M) | BA3: Implied Staking Yield | BB3: (-) Future Emissions & CR (HYPE) | BC3: (-) Hyper Foundation (HYPE) | BD3: (-) Assistance Fund (HYPE) | BE3: (-) Community Grants (HYPE) | BF3: (-) HC&EVM Fee Burns (HYPE) | BG3: = OTS (HYPE) | BH3: Core Contributors Locked (M) | BI3: Circulating Token Supply (M) | BJ3: OTS Value ($)
A4: Q4 2024 (Nov-Dec) | B4: 45626 | C4: 45657 | D4: =SUMIFS('Daily Model'!$B$4:$B$664,'Daily Model'!$A$4:$A$664,">="&$B4,'Daily Model'!$A$4:$A$664,"<="&$C4) | E4: =SUMIFS('Daily Model'!$C$4:$C$664,'Daily Model'!$A$4:$A$664,">="&$B4,'Daily Model'!$A$4:$A$664,"<="&$C4) | F4: =SUMIFS('Daily Model'!$D$4:$D$664,'Daily Model'!$A$4:$A$664,">="&$B4,'Daily Model'!$A$4:$A$664,"<="&$C4) | G4: =SUMIFS('Daily Model'!$E$4:$E$664,'Daily Model'!$A$4:$A$664,">="&$B4,'Daily Model'!$A$4:$A$664,"<="&$C4) | H4: =SUMIFS('Daily Model'!$F$4:$F$664,'Daily Model'!$A$4:$A$664,">="&$B4,'Daily Model'!$A$4:$A$664,"<="&$C4) | I4: =SUMIFS('Daily Model'!$G$4:$G$664,'Daily Model'!$A$4:$A$664,">="&$B4,'Daily Model'!$A$4:$A$664,"<="&$C4) | J4: =SUMIFS('Daily Model'!$H$4:$H$664,'Daily Model'!$A$4:$A$664,">="&$B4,'Daily Model'!$A$4:$A$664,"<="&$C4) | K4: =SUMIFS('Daily Model'!$I$4:$I$664,'Daily Model'!$A$4:$A$664,">="&$B4,'Daily Model'!$A$4:$A$664,"<="&$C4) | L4: =SUMIFS('Daily Model'!$J$4:$J$664,'Daily Model'!$A$4:$A$664,">="&$B4,'Daily Model'!$A$4:$A$664,"<="&$C4) | M4: =SUMIFS('Daily Model'!$K$4:$K$664,'Daily Model'!$A$4:$A$664,">="&$B4,'Daily Model'!$A$4:$A$664,"<="&$C4) | N4: =SUMIFS('Daily Model'!$L$4:$L$664,'Daily Model'!$A$4:$A$664,">="&$B4,'Daily Model'!$A$4:$A$664,"<="&$C4) | O4: =IF(E4=0,"",N4/E4) | P4: =SUMIFS('Daily Model'!$N$4:$N$664,'Daily Model'!$A$4:$A$664,">="&$B4,'Daily Model'!$A$4:$A$664,"<="&$C4) | Q4: =SUMIFS('Daily Model'!$O$4:$O$664,'Daily Model'!$A$4:$A$664,">="&$B4,'Daily Model'!$A$4:$A$664,"<="&$C4) | R4: =SUMIFS('Daily Model'!$P$4:$P$664,'Daily Model'!$A$4:$A$664,">="&$B4,'Daily Model'!$A$4:$A$664,"<="&$C4) | S4: =SUMIFS('Daily Model'!$Q$4:$Q$664,'Daily Model'!$A$4:$A$664,">="&$B4,'Daily Model'!$A$4:$A$664,"<="&$C4) | T4: =SUMIFS('Daily Model'!$R$4:$R$664,'Daily Model'!$A$4:$A$664,">="&$B4,'Daily Model'!$A$4:$A$664,"<="&$C4) | V4: =SUMIFS('Daily Model'!$T$4:$T$664,'Daily Model'!$A$4:$A$664,">="&$B4,'Daily Model'!$A$4:$A$664,"<="&$C4) | W4: =SUMIFS('Daily Model'!$U$4:$U$664,'Daily Model'!$A$4:$A$664,">="&$B4,'Daily Model'!$A$4:$A$664,"<="&$C4) | X4: =SUMIFS('Daily Model'!$V$4:$V$664,'Daily Model'!$A$4:$A$664,">="&$B4,'Daily Model'!$A$4:$A$664,"<="&$C4) | Y4: =SUMIFS('Daily Model'!$W$4:$W$664,'Daily Model'!$A$4:$A$664,">="&$B4,'Daily Model'!$A$4:$A$664,"<="&$C4) | Z4: =SUMIFS('Daily Model'!$X$4:$X$664,'Daily Model'!$A$4:$A$664,">="&$B4,'Daily Model'!$A$4:$A$664,"<="&$C4) | AA4: =SUMIFS('Daily Model'!$Y$4:$Y$664,'Daily Model'!$A$4:$A$664,">="&$B4,'Daily Model'!$A$4:$A$664,"<="&$C4) | AB4: =SUMIFS('Daily Model'!$Z$4:$Z$664,'Daily Model'!$A$4:$A$664,">="&$B4,'Daily Model'!$A$4:$A$664,"<="&$C4) | AC4: =SUMIFS('Daily Model'!$AA$4:$AA$664,'Daily Model'!$A$4:$A$664,">="&$B4,'Daily Model'!$A$4:$A$664,"<="&$C4) | AD4: =SUMIFS('Daily Model'!$AB$4:$AB$664,'Daily Model'!$A$4:$A$664,">="&$B4,'Daily Model'!$A$4:$A$664,"<="&$C4) | AE4: =SUMIFS('Daily Model'!$AC$4:$AC$664,'Daily Model'!$A$4:$A$664,">="&$B4,'Daily Model'!$A$4:$A$664,"<="&$C4) | AF4: =SUMIFS('Daily Model'!$AD$4:$AD$664,'Daily Model'!$A$4:$A$664,">="&$B4,'Daily Model'!$A$4:$A$664,"<="&$C4) | AG4: =SUMIFS('Daily Model'!$AE$4:$AE$664,'Daily Model'!$A$4:$A$664,">="&$B4,'Daily Model'!$A$4:$A$664,"<="&$C4) | AH4: =SUMIFS('Daily Model'!$AF$4:$AF$664,'Daily Model'!$A$4:$A$664,">="&$B4,'Daily Model'!$A$4:$A$664,"<="&$C4) | AI4: =SUMIFS('Daily Model'!$AG$4:$AG$664,'Daily Model'!$A$4:$A$664,">="&$B4,'Daily Model'!$A$4:$A$664,"<="&$C4) | AJ4: =SUMIFS('Daily Model'!$AH$4:$AH$664,'Daily Model'!$A$4:$A$664,">="&$B4,'Daily Model'!$A$4:$A$664,"<="&$C4) | AK4: =AI4-AJ4 | AL4: =IF(D4=0,"",P4/D4*10000) | AM4: =IF(E4=0,"",Q4/E4*10000) | AN4: =IF(F4=0,"",R4/F4*10000) | AO4: =IF(G4=0,"",S4/G4*10000) | AP4: =SUMIFS('Daily Model'!$AN$4:$AN$664,'Daily Model'!$A$4:$A$664,">="&$B4,'Daily Model'!$A$4:$A$664,"<="&$C4) | AQ4: =SUMIFS('Daily Model'!$AO$4:$AO$664,'Daily Model'!$A$4:$A$664,">="&$B4,'Daily Model'!$A$4:$A$664,"<="&$C4) | AR4: =SUMIFS('Daily Model'!$AP$4:$AP$664,'Daily Model'!$A$4:$A$664,">="&$B4,'Daily Model'!$A$4:$A$664,"<="&$C4) | AS4: =SUMIFS('Daily Model'!$AQ$4:$AQ$664,'Daily Model'!$A$4:$A$664,">="&$B4,'Daily Model'!$A$4:$A$664,"<="&$C4) | AT4: =SUMIFS('Daily Model'!$AR$4:$AR$664,'Daily Model'!$A$4:$A$664,">="&$B4,'Daily Model'!$A$4:$A$664,"<="&$C4) | AU4: =IF(AT4=0,"",AS4/AT4) | AV4: 11670797 | AW4: =SUMIFS('Daily Model'!$AU$4:$AU$664,'Daily Model'!$A$4:$A$664,">="&$B4,'Daily Model'!$A$4:$A$664,"<="&$C4) | AX4: =SUMIFS('Daily Model'!$AV$4:$AV$664,'Daily Model'!$A$4:$A$664,">="&$B4,'Daily Model'!$A$4:$A$664,"<="&$C4) | AY4: =SUMIFS('Daily Model'!$AW$4:$AW$664,'Daily Model'!$A$4:$A$664,">="&$B4,'Daily Model'!$A$4:$A$664,"<="&$C4) | AZ4: 352.7986 | BA4: 0.0127 | BB4: 4.2800478e+08 | BC4: 60487233 | BD4: 11670797 | BE4: 2971663 | BF4: 110094.67 | BG4: 4.9675543e+08 | BH4: 238 | BI4: 258.7554 | BJ4: 1.3387559e+10
A5: Q1 2025 | B5: 45658 | C5: 45747 | D5: =SUMIFS('Daily Model'!$B$4:$B$664,'Daily Model'!$A$4:$A$664,">="&$B5,'Daily Model'!$A$4:$A$664,"<="&$C5) | E5: =SUMIFS('Daily Model'!$C$4:$C$664,'Daily Model'!$A$4:$A$664,">="&$B5,'Daily Model'!$A$4:$A$664,"<="&$C5) | F5: =SUMIFS('Daily Model'!$D$4:$D$664,'Daily Model'!$A$4:$A$664,">="&$B5,'Daily Model'!$A$4:$A$664,"<="&$C5) | G5: =SUMIFS('Daily Model'!$E$4:$E$664,'Daily Model'!$A$4:$A$664,">="&$B5,'Daily Model'!$A$4:$A$664,"<="&$C5) | H5: =SUMIFS('Daily Model'!$F$4:$F$664,'Daily Model'!$A$4:$A$664,">="&$B5,'Daily Model'!$A$4:$A$664,"<="&$C5) | I5: =SUMIFS('Daily Model'!$G$4:$G$664,'Daily Model'!$A$4:$A$664,">="&$B5,'Daily Model'!$A$4:$A$664,"<="&$C5) | J5: =SUMIFS('Daily Model'!$H$4:$H$664,'Daily Model'!$A$4:$A$664,">="&$B5,'Daily Model'!$A$4:$A$664,"<="&$C5) | K5: =SUMIFS('Daily Model'!$I$4:$I$664,'Daily Model'!$A$4:$A$664,">="&$B5,'Daily Model'!$A$4:$A$664,"<="&$C5) | L5: =SUMIFS('Daily Model'!$J$4:$J$664,'Daily Model'!$A$4:$A$664,">="&$B5,'Daily Model'!$A$4:$A$664,"<="&$C5) | M5: =SUMIFS('Daily Model'!$K$4:$K$664,'Daily Model'!$A$4:$A$664,">="&$B5,'Daily Model'!$A$4:$A$664,"<="&$C5) | N5: =SUMIFS('Daily Model'!$L$4:$L$664,'Daily Model'!$A$4:$A$664,">="&$B5,'Daily Model'!$A$4:$A$664,"<="&$C5) | O5: =IF(E5=0,"",N5/E5) | P5: =SUMIFS('Daily Model'!$N$4:$N$664,'Daily Model'!$A$4:$A$664,">="&$B5,'Daily Model'!$A$4:$A$664,"<="&$C5) | Q5: =SUMIFS('Daily Model'!$O$4:$O$664,'Daily Model'!$A$4:$A$664,">="&$B5,'Daily Model'!$A$4:$A$664,"<="&$C5) | R5: =SUMIFS('Daily Model'!$P$4:$P$664,'Daily Model'!$A$4:$A$664,">="&$B5,'Daily Model'!$A$4:$A$664,"<="&$C5) | S5: =SUMIFS('Daily Model'!$Q$4:$Q$664,'Daily Model'!$A$4:$A$664,">="&$B5,'Daily Model'!$A$4:$A$664,"<="&$C5) | T5: =SUMIFS('Daily Model'!$R$4:$R$664,'Daily Model'!$A$4:$A$664,">="&$B5,'Daily Model'!$A$4:$A$664,"<="&$C5) | V5: =SUMIFS('Daily Model'!$T$4:$T$664,'Daily Model'!$A$4:$A$664,">="&$B5,'Daily Model'!$A$4:$A$664,"<="&$C5) | W5: =SUMIFS('Daily Model'!$U$4:$U$664,'Daily Model'!$A$4:$A$664,">="&$B5,'Daily Model'!$A$4:$A$664,"<="&$C5) | X5: =SUMIFS('Daily Model'!$V$4:$V$664,'Daily Model'!$A$4:$A$664,">="&$B5,'Daily Model'!$A$4:$A$664,"<="&$C5) | Y5: =SUMIFS('Daily Model'!$W$4:$W$664,'Daily Model'!$A$4:$A$664,">="&$B5,'Daily Model'!$A$4:$A$664,"<="&$C5) | Z5: =SUMIFS('Daily Model'!$X$4:$X$664,'Daily Model'!$A$4:$A$664,">="&$B5,'Daily Model'!$A$4:$A$664,"<="&$C5) | AA5: =SUMIFS('Daily Model'!$Y$4:$Y$664,'Daily Model'!$A$4:$A$664,">="&$B5,'Daily Model'!$A$4:$A$664,"<="&$C5) | AB5: =SUMIFS('Daily Model'!$Z$4:$Z$664,'Daily Model'!$A$4:$A$664,">="&$B5,'Daily Model'!$A$4:$A$664,"<="&$C5) | AC5: =SUMIFS('Daily Model'!$AA$4:$AA$664,'Daily Model'!$A$4:$A$664,">="&$B5,'Daily Model'!$A$4:$A$664,"<="&$C5) | AD5: =SUMIFS('Daily Model'!$AB$4:$AB$664,'Daily Model'!$A$4:$A$664,">="&$B5,'Daily Model'!$A$4:$A$664,"<="&$C5) | AE5: =SUMIFS('Daily Model'!$AC$4:$AC$664,'Daily Model'!$A$4:$A$664,">="&$B5,'Daily Model'!$A$4:$A$664,"<="&$C5) | AF5: =SUMIFS('Daily Model'!$AD$4:$AD$664,'Daily Model'!$A$4:$A$664,">="&$B5,'Daily Model'!$A$4:$A$664,"<="&$C5) | AG5: =SUMIFS('Daily Model'!$AE$4:$AE$664,'Daily Model'!$A$4:$A$664,">="&$B5,'Daily Model'!$A$4:$A$664,"<="&$C5) | AH5: =SUMIFS('Daily Model'!$AF$4:$AF$664,'Daily Model'!$A$4:$A$664,">="&$B5,'Daily Model'!$A$4:$A$664,"<="&$C5) | AI5: =SUMIFS('Daily Model'!$AG$4:$AG$664,'Daily Model'!$A$4:$A$664,">="&$B5,'Daily Model'!$A$4:$A$664,"<="&$C5) | AJ5: =SUMIFS('Daily Model'!$AH$4:$AH$664,'Daily Model'!$A$4:$A$664,">="&$B5,'Daily Model'!$A$4:$A$664,"<="&$C5) | AK5: =AI5-AJ5 | AL5: =IF(D5=0,"",P5/D5*10000) | AM5: =IF(E5=0,"",Q5/E5*10000) | AN5: =IF(F5=0,"",R5/F5*10000) | AO5: =IF(G5=0,"",S5/G5*10000) | AP5: =SUMIFS('Daily Model'!$AN$4:$AN$664,'Daily Model'!$A$4:$A$664,">="&$B5,'Daily Model'!$A$4:$A$664,"<="&$C5) | AQ5: =SUMIFS('Daily Model'!$AO$4:$AO$664,'Daily Model'!$A$4:$A$664,">="&$B5,'Daily Model'!$A$4:$A$664,"<="&$C5) | AR5: =SUMIFS('Daily Model'!$AP$4:$AP$664,'Daily Model'!$A$4:$A$664,">="&$B5,'Daily Model'!$A$4:$A$664,"<="&$C5) | AS5: =SUMIFS('Daily Model'!$AQ$4:$AQ$664,'Daily Model'!$A$4:$A$664,">="&$B5,'Daily Model'!$A$4:$A$664,"<="&$C5) | AT5: =SUMIFS('Daily Model'!$AR$4:$AR$664,'Daily Model'!$A$4:$A$664,">="&$B5,'Daily Model'!$A$4:$A$664,"<="&$C5) | AU5: =IF(AT5=0,"",AS5/AT5) | AV5: 18407964 | AW5: =SUMIFS('Daily Model'!$AU$4:$AU$664,'Daily Model'!$A$4:$A$664,">="&$B5,'Daily Model'!$A$4:$A$664,"<="&$C5) | AX5: =SUMIFS('Daily Model'!$AV$4:$AV$664,'Daily Model'!$A$4:$A$664,">="&$B5,'Daily Model'!$A$4:$A$664,"<="&$C5) | AY5: =SUMIFS('Daily Model'!$AW$4:$AW$664,'Daily Model'!$A$4:$A$664,">="&$B5,'Daily Model'!$A$4:$A$664,"<="&$C5) | AZ5: 421.3321 | BA5: 0.0228 | BB5: 4.2563427e+08 | BC5: 60487233 | BD5: 18407964 | BE5: 2971663 | BF5: 195393.45 | BG5: 4.9230348e+08 | BH5: 238 | BI5: 254.3035 | BJ5: 6.1439474e+09
A6: Q2 2025 | B6: 45748 | C6: 45838 | D6: =SUMIFS('Daily Model'!$B$4:$B$664,'Daily Model'!$A$4:$A$664,">="&$B6,'Daily Model'!$A$4:$A$664,"<="&$C6) | E6: =SUMIFS('Daily Model'!$C$4:$C$664,'Daily Model'!$A$4:$A$664,">="&$B6,'Daily Model'!$A$4:$A$664,"<="&$C6) | F6: =SUMIFS('Daily Model'!$D$4:$D$664,'Daily Model'!$A$4:$A$664,">="&$B6,'Daily Model'!$A$4:$A$664,"<="&$C6) | G6: =SUMIFS('Daily Model'!$E$4:$E$664,'Daily Model'!$A$4:$A$664,">="&$B6,'Daily Model'!$A$4:$A$664,"<="&$C6) | H6: =SUMIFS('Daily Model'!$F$4:$F$664,'Daily Model'!$A$4:$A$664,">="&$B6,'Daily Model'!$A$4:$A$664,"<="&$C6) | I6: =SUMIFS('Daily Model'!$G$4:$G$664,'Daily Model'!$A$4:$A$664,">="&$B6,'Daily Model'!$A$4:$A$664,"<="&$C6) | J6: =SUMIFS('Daily Model'!$H$4:$H$664,'Daily Model'!$A$4:$A$664,">="&$B6,'Daily Model'!$A$4:$A$664,"<="&$C6) | K6: =SUMIFS('Daily Model'!$I$4:$I$664,'Daily Model'!$A$4:$A$664,">="&$B6,'Daily Model'!$A$4:$A$664,"<="&$C6) | L6: =SUMIFS('Daily Model'!$J$4:$J$664,'Daily Model'!$A$4:$A$664,">="&$B6,'Daily Model'!$A$4:$A$664,"<="&$C6) | M6: =SUMIFS('Daily Model'!$K$4:$K$664,'Daily Model'!$A$4:$A$664,">="&$B6,'Daily Model'!$A$4:$A$664,"<="&$C6) | N6: =SUMIFS('Daily Model'!$L$4:$L$664,'Daily Model'!$A$4:$A$664,">="&$B6,'Daily Model'!$A$4:$A$664,"<="&$C6) | O6: =IF(E6=0,"",N6/E6) | P6: =SUMIFS('Daily Model'!$N$4:$N$664,'Daily Model'!$A$4:$A$664,">="&$B6,'Daily Model'!$A$4:$A$664,"<="&$C6) | Q6: =SUMIFS('Daily Model'!$O$4:$O$664,'Daily Model'!$A$4:$A$664,">="&$B6,'Daily Model'!$A$4:$A$664,"<="&$C6) | R6: =SUMIFS('Daily Model'!$P$4:$P$664,'Daily Model'!$A$4:$A$664,">="&$B6,'Daily Model'!$A$4:$A$664,"<="&$C6) | S6: =SUMIFS('Daily Model'!$Q$4:$Q$664,'Daily Model'!$A$4:$A$664,">="&$B6,'Daily Model'!$A$4:$A$664,"<="&$C6) | T6: =SUMIFS('Daily Model'!$R$4:$R$664,'Daily Model'!$A$4:$A$664,">="&$B6,'Daily Model'!$A$4:$A$664,"<="&$C6) | V6: =SUMIFS('Daily Model'!$T$4:$T$664,'Daily Model'!$A$4:$A$664,">="&$B6,'Daily Model'!$A$4:$A$664,"<="&$C6) | W6: =SUMIFS('Daily Model'!$U$4:$U$664,'Daily Model'!$A$4:$A$664,">="&$B6,'Daily Model'!$A$4:$A$664,"<="&$C6) | X6: =SUMIFS('Daily Model'!$V$4:$V$664,'Daily Model'!$A$4:$A$664,">="&$B6,'Daily Model'!$A$4:$A$664,"<="&$C6) | Y6: =SUMIFS('Daily Model'!$W$4:$W$664,'Daily Model'!$A$4:$A$664,">="&$B6,'Daily Model'!$A$4:$A$664,"<="&$C6) | Z6: =SUMIFS('Daily Model'!$X$4:$X$664,'Daily Model'!$A$4:$A$664,">="&$B6,'Daily Model'!$A$4:$A$664,"<="&$C6) | AA6: =SUMIFS('Daily Model'!$Y$4:$Y$664,'Daily Model'!$A$4:$A$664,">="&$B6,'Daily Model'!$A$4:$A$664,"<="&$C6) | AB6: =SUMIFS('Daily Model'!$Z$4:$Z$664,'Daily Model'!$A$4:$A$664,">="&$B6,'Daily Model'!$A$4:$A$664,"<="&$C6) | AC6: =SUMIFS('Daily Model'!$AA$4:$AA$664,'Daily Model'!$A$4:$A$664,">="&$B6,'Daily Model'!$A$4:$A$664,"<="&$C6) | AD6: =SUMIFS('Daily Model'!$AB$4:$AB$664,'Daily Model'!$A$4:$A$664,">="&$B6,'Daily Model'!$A$4:$A$664,"<="&$C6) | AE6: =SUMIFS('Daily Model'!$AC$4:$AC$664,'Daily Model'!$A$4:$A$664,">="&$B6,'Daily Model'!$A$4:$A$664,"<="&$C6) | AF6: =SUMIFS('Daily Model'!$AD$4:$AD$664,'Daily Model'!$A$4:$A$664,">="&$B6,'Daily Model'!$A$4:$A$664,"<="&$C6) | AG6: =SUMIFS('Daily Model'!$AE$4:$AE$664,'Daily Model'!$A$4:$A$664,">="&$B6,'Daily Model'!$A$4:$A$664,"<="&$C6) | AH6: =SUMIFS('Daily Model'!$AF$4:$AF$664,'Daily Model'!$A$4:$A$664,">="&$B6,'Daily Model'!$A$4:$A$664,"<="&$C6) | AI6: =SUMIFS('Daily Model'!$AG$4:$AG$664,'Daily Model'!$A$4:$A$664,">="&$B6,'Daily Model'!$A$4:$A$664,"<="&$C6) | AJ6: =SUMIFS('Daily Model'!$AH$4:$AH$664,'Daily Model'!$A$4:$A$664,">="&$B6,'Daily Model'!$A$4:$A$664,"<="&$C6) | AK6: =AI6-AJ6 | AL6: =IF(D6=0,"",P6/D6*10000) | AM6: =IF(E6=0,"",Q6/E6*10000) | AN6: =IF(F6=0,"",R6/F6*10000) | AO6: =IF(G6=0,"",S6/G6*10000) | AP6: =SUMIFS('Daily Model'!$AN$4:$AN$664,'Daily Model'!$A$4:$A$664,">="&$B6,'Daily Model'!$A$4:$A$664,"<="&$C6) | AQ6: =SUMIFS('Daily Model'!$AO$4:$AO$664,'Daily Model'!$A$4:$A$664,">="&$B6,'Daily Model'!$A$4:$A$664,"<="&$C6) | AR6: =SUMIFS('Daily Model'!$AP$4:$AP$664,'Daily Model'!$A$4:$A$664,">="&$B6,'Daily Model'!$A$4:$A$664,"<="&$C6) | AS6: =SUMIFS('Daily Model'!$AQ$4:$AQ$664,'Daily Model'!$A$4:$A$664,">="&$B6,'Daily Model'!$A$4:$A$664,"<="&$C6) | AT6: =SUMIFS('Daily Model'!$AR$4:$AR$664,'Daily Model'!$A$4:$A$664,">="&$B6,'Daily Model'!$A$4:$A$664,"<="&$C6) | AU6: =IF(AT6=0,"",AS6/AT6) | AV6: 25508876 | AW6: =SUMIFS('Daily Model'!$AU$4:$AU$664,'Daily Model'!$A$4:$A$664,">="&$B6,'Daily Model'!$A$4:$A$664,"<="&$C6) | AX6: =SUMIFS('Daily Model'!$AV$4:$AV$664,'Daily Model'!$A$4:$A$664,">="&$B6,'Daily Model'!$A$4:$A$664,"<="&$C6) | AY6: =SUMIFS('Daily Model'!$AW$4:$AW$664,'Daily Model'!$A$4:$A$664,">="&$B6,'Daily Model'!$A$4:$A$664,"<="&$C6) | AZ6: 422.0714 | BA6: 0.0226 | BB6: 4.2324595e+08 | BC6: 60487233 | BD6: 25508876 | BE6: 2971663 | BF6: 355352.02 | BG6: 4.8743093e+08 | BH6: 238 | BI6: 249.4309 | BJ6: 1.9268144e+10
A7: Q3 2025 | B7: 45839 | C7: 45930 | D7: =SUMIFS('Daily Model'!$B$4:$B$664,'Daily Model'!$A$4:$A$664,">="&$B7,'Daily Model'!$A$4:$A$664,"<="&$C7) | E7: =SUMIFS('Daily Model'!$C$4:$C$664,'Daily Model'!$A$4:$A$664,">="&$B7,'Daily Model'!$A$4:$A$664,"<="&$C7) | F7: =SUMIFS('Daily Model'!$D$4:$D$664,'Daily Model'!$A$4:$A$664,">="&$B7,'Daily Model'!$A$4:$A$664,"<="&$C7) | G7: =SUMIFS('Daily Model'!$E$4:$E$664,'Daily Model'!$A$4:$A$664,">="&$B7,'Daily Model'!$A$4:$A$664,"<="&$C7) | H7: =SUMIFS('Daily Model'!$F$4:$F$664,'Daily Model'!$A$4:$A$664,">="&$B7,'Daily Model'!$A$4:$A$664,"<="&$C7) | I7: =SUMIFS('Daily Model'!$G$4:$G$664,'Daily Model'!$A$4:$A$664,">="&$B7,'Daily Model'!$A$4:$A$664,"<="&$C7) | J7: =SUMIFS('Daily Model'!$H$4:$H$664,'Daily Model'!$A$4:$A$664,">="&$B7,'Daily Model'!$A$4:$A$664,"<="&$C7) | K7: =SUMIFS('Daily Model'!$I$4:$I$664,'Daily Model'!$A$4:$A$664,">="&$B7,'Daily Model'!$A$4:$A$664,"<="&$C7) | L7: =SUMIFS('Daily Model'!$J$4:$J$664,'Daily Model'!$A$4:$A$664,">="&$B7,'Daily Model'!$A$4:$A$664,"<="&$C7) | M7: =SUMIFS('Daily Model'!$K$4:$K$664,'Daily Model'!$A$4:$A$664,">="&$B7,'Daily Model'!$A$4:$A$664,"<="&$C7) | N7: =SUMIFS('Daily Model'!$L$4:$L$664,'Daily Model'!$A$4:$A$664,">="&$B7,'Daily Model'!$A$4:$A$664,"<="&$C7) | O7: =IF(E7=0,"",N7/E7) | P7: =SUMIFS('Daily Model'!$N$4:$N$664,'Daily Model'!$A$4:$A$664,">="&$B7,'Daily Model'!$A$4:$A$664,"<="&$C7) | Q7: =SUMIFS('Daily Model'!$O$4:$O$664,'Daily Model'!$A$4:$A$664,">="&$B7,'Daily Model'!$A$4:$A$664,"<="&$C7) | R7: =SUMIFS('Daily Model'!$P$4:$P$664,'Daily Model'!$A$4:$A$664,">="&$B7,'Daily Model'!$A$4:$A$664,"<="&$C7) | S7: =SUMIFS('Daily Model'!$Q$4:$Q$664,'Daily Model'!$A$4:$A$664,">="&$B7,'Daily Model'!$A$4:$A$664,"<="&$C7) | T7: =SUMIFS('Daily Model'!$R$4:$R$664,'Daily Model'!$A$4:$A$664,">="&$B7,'Daily Model'!$A$4:$A$664,"<="&$C7) | V7: =SUMIFS('Daily Model'!$T$4:$T$664,'Daily Model'!$A$4:$A$664,">="&$B7,'Daily Model'!$A$4:$A$664,"<="&$C7) | W7: =SUMIFS('Daily Model'!$U$4:$U$664,'Daily Model'!$A$4:$A$664,">="&$B7,'Daily Model'!$A$4:$A$664,"<="&$C7) | X7: =SUMIFS('Daily Model'!$V$4:$V$664,'Daily Model'!$A$4:$A$664,">="&$B7,'Daily Model'!$A$4:$A$664,"<="&$C7) | Y7: =SUMIFS('Daily Model'!$W$4:$W$664,'Daily Model'!$A$4:$A$664,">="&$B7,'Daily Model'!$A$4:$A$664,"<="&$C7) | Z7: =SUMIFS('Daily Model'!$X$4:$X$664,'Daily Model'!$A$4:$A$664,">="&$B7,'Daily Model'!$A$4:$A$664,"<="&$C7) | AA7: =SUMIFS('Daily Model'!$Y$4:$Y$664,'Daily Model'!$A$4:$A$664,">="&$B7,'Daily Model'!$A$4:$A$664,"<="&$C7) | AB7: =SUMIFS('Daily Model'!$Z$4:$Z$664,'Daily Model'!$A$4:$A$664,">="&$B7,'Daily Model'!$A$4:$A$664,"<="&$C7) | AC7: =SUMIFS('Daily Model'!$AA$4:$AA$664,'Daily Model'!$A$4:$A$664,">="&$B7,'Daily Model'!$A$4:$A$664,"<="&$C7) | AD7: =SUMIFS('Daily Model'!$AB$4:$AB$664,'Daily Model'!$A$4:$A$664,">="&$B7,'Daily Model'!$A$4:$A$664,"<="&$C7) | AE7: =SUMIFS('Daily Model'!$AC$4:$AC$664,'Daily Model'!$A$4:$A$664,">="&$B7,'Daily Model'!$A$4:$A$664,"<="&$C7) | AF7: =SUMIFS('Daily Model'!$AD$4:$AD$664,'Daily Model'!$A$4:$A$664,">="&$B7,'Daily Model'!$A$4:$A$664,"<="&$C7) | AG7: =SUMIFS('Daily Model'!$AE$4:$AE$664,'Daily Model'!$A$4:$A$664,">="&$B7,'Daily Model'!$A$4:$A$664,"<="&$C7) | AH7: =SUMIFS('Daily Model'!$AF$4:$AF$664,'Daily Model'!$A$4:$A$664,">="&$B7,'Daily Model'!$A$4:$A$664,"<="&$C7) | AI7: =SUMIFS('Daily Model'!$AG$4:$AG$664,'Daily Model'!$A$4:$A$664,">="&$B7,'Daily Model'!$A$4:$A$664,"<="&$C7) | AJ7: =SUMIFS('Daily Model'!$AH$4:$AH$664,'Daily Model'!$A$4:$A$664,">="&$B7,'Daily Model'!$A$4:$A$664,"<="&$C7) | AK7: =AI7-AJ7 | AL7: =IF(D7=0,"",P7/D7*10000) | AM7: =IF(E7=0,"",Q7/E7*10000) | AN7: =IF(F7=0,"",R7/F7*10000) | AO7: =IF(G7=0,"",S7/G7*10000) | AP7: =SUMIFS('Daily Model'!$AN$4:$AN$664,'Daily Model'!$A$4:$A$664,">="&$B7,'Daily Model'!$A$4:$A$664,"<="&$C7) | AQ7: =SUMIFS('Daily Model'!$AO$4:$AO$664,'Daily Model'!$A$4:$A$664,">="&$B7,'Daily Model'!$A$4:$A$664,"<="&$C7) | AR7: =SUMIFS('Daily Model'!$AP$4:$AP$664,'Daily Model'!$A$4:$A$664,">="&$B7,'Daily Model'!$A$4:$A$664,"<="&$C7) | AS7: =SUMIFS('Daily Model'!$AQ$4:$AQ$664,'Daily Model'!$A$4:$A$664,">="&$B7,'Daily Model'!$A$4:$A$664,"<="&$C7) | AT7: =SUMIFS('Daily Model'!$AR$4:$AR$664,'Daily Model'!$A$4:$A$664,">="&$B7,'Daily Model'!$A$4:$A$664,"<="&$C7) | AU7: =IF(AT7=0,"",AS7/AT7) | AV7: 31785059 | AW7: =SUMIFS('Daily Model'!$AU$4:$AU$664,'Daily Model'!$A$4:$A$664,">="&$B7,'Daily Model'!$A$4:$A$664,"<="&$C7) | AX7: =SUMIFS('Daily Model'!$AV$4:$AV$664,'Daily Model'!$A$4:$A$664,">="&$B7,'Daily Model'!$A$4:$A$664,"<="&$C7) | AY7: =SUMIFS('Daily Model'!$AW$4:$AW$664,'Daily Model'!$A$4:$A$664,">="&$B7,'Daily Model'!$A$4:$A$664,"<="&$C7) | AZ7: 425.4931 | BA7: 0.0224 | BB7: 4.2082436e+08 | BC7: 60487233 | BD7: 31785059 | BE7: 2971663 | BF7: 529777.17 | BG7: 4.8340191e+08 | BH7: 238 | BI7: 245.4019 | BJ7: 2.2289662e+10
A8: Q4 2025 | B8: 45931 | C8: 46022 | D8: =SUMIFS('Daily Model'!$B$4:$B$664,'Daily Model'!$A$4:$A$664,">="&$B8,'Daily Model'!$A$4:$A$664,"<="&$C8) | E8: =SUMIFS('Daily Model'!$C$4:$C$664,'Daily Model'!$A$4:$A$664,">="&$B8,'Daily Model'!$A$4:$A$664,"<="&$C8) | F8: =SUMIFS('Daily Model'!$D$4:$D$664,'Daily Model'!$A$4:$A$664,">="&$B8,'Daily Model'!$A$4:$A$664,"<="&$C8) | G8: =SUMIFS('Daily Model'!$E$4:$E$664,'Daily Model'!$A$4:$A$664,">="&$B8,'Daily Model'!$A$4:$A$664,"<="&$C8) | H8: =SUMIFS('Daily Model'!$F$4:$F$664,'Daily Model'!$A$4:$A$664,">="&$B8,'Daily Model'!$A$4:$A$664,"<="&$C8) | I8: =SUMIFS('Daily Model'!$G$4:$G$664,'Daily Model'!$A$4:$A$664,">="&$B8,'Daily Model'!$A$4:$A$664,"<="&$C8) | J8: =SUMIFS('Daily Model'!$H$4:$H$664,'Daily Model'!$A$4:$A$664,">="&$B8,'Daily Model'!$A$4:$A$664,"<="&$C8) | K8: =SUMIFS('Daily Model'!$I$4:$I$664,'Daily Model'!$A$4:$A$664,">="&$B8,'Daily Model'!$A$4:$A$664,"<="&$C8) | L8: =SUMIFS('Daily Model'!$J$4:$J$664,'Daily Model'!$A$4:$A$664,">="&$B8,'Daily Model'!$A$4:$A$664,"<="&$C8) | M8: =SUMIFS('Daily Model'!$K$4:$K$664,'Daily Model'!$A$4:$A$664,">="&$B8,'Daily Model'!$A$4:$A$664,"<="&$C8) | N8: =SUMIFS('Daily Model'!$L$4:$L$664,'Daily Model'!$A$4:$A$664,">="&$B8,'Daily Model'!$A$4:$A$664,"<="&$C8) | O8: =IF(E8=0,"",N8/E8) | P8: =SUMIFS('Daily Model'!$N$4:$N$664,'Daily Model'!$A$4:$A$664,">="&$B8,'Daily Model'!$A$4:$A$664,"<="&$C8) | Q8: =SUMIFS('Daily Model'!$O$4:$O$664,'Daily Model'!$A$4:$A$664,">="&$B8,'Daily Model'!$A$4:$A$664,"<="&$C8) | R8: =SUMIFS('Daily Model'!$P$4:$P$664,'Daily Model'!$A$4:$A$664,">="&$B8,'Daily Model'!$A$4:$A$664,"<="&$C8) | S8: =SUMIFS('Daily Model'!$Q$4:$Q$664,'Daily Model'!$A$4:$A$664,">="&$B8,'Daily Model'!$A$4:$A$664,"<="&$C8) | T8: =SUMIFS('Daily Model'!$R$4:$R$664,'Daily Model'!$A$4:$A$664,">="&$B8,'Daily Model'!$A$4:$A$664,"<="&$C8) | V8: =SUMIFS('Daily Model'!$T$4:$T$664,'Daily Model'!$A$4:$A$664,">="&$B8,'Daily Model'!$A$4:$A$664,"<="&$C8) | W8: =SUMIFS('Daily Model'!$U$4:$U$664,'Daily Model'!$A$4:$A$664,">="&$B8,'Daily Model'!$A$4:$A$664,"<="&$C8) | X8: =SUMIFS('Daily Model'!$V$4:$V$664,'Daily Model'!$A$4:$A$664,">="&$B8,'Daily Model'!$A$4:$A$664,"<="&$C8) | Y8: =SUMIFS('Daily Model'!$W$4:$W$664,'Daily Model'!$A$4:$A$664,">="&$B8,'Daily Model'!$A$4:$A$664,"<="&$C8) | Z8: =SUMIFS('Daily Model'!$X$4:$X$664,'Daily Model'!$A$4:$A$664,">="&$B8,'Daily Model'!$A$4:$A$664,"<="&$C8) | AA8: =SUMIFS('Daily Model'!$Y$4:$Y$664,'Daily Model'!$A$4:$A$664,">="&$B8,'Daily Model'!$A$4:$A$664,"<="&$C8) | AB8: =SUMIFS('Daily Model'!$Z$4:$Z$664,'Daily Model'!$A$4:$A$664,">="&$B8,'Daily Model'!$A$4:$A$664,"<="&$C8) | AC8: =SUMIFS('Daily Model'!$AA$4:$AA$664,'Daily Model'!$A$4:$A$664,">="&$B8,'Daily Model'!$A$4:$A$664,"<="&$C8) | AD8: =SUMIFS('Daily Model'!$AB$4:$AB$664,'Daily Model'!$A$4:$A$664,">="&$B8,'Daily Model'!$A$4:$A$664,"<="&$C8) | AE8: =SUMIFS('Daily Model'!$AC$4:$AC$664,'Daily Model'!$A$4:$A$664,">="&$B8,'Daily Model'!$A$4:$A$664,"<="&$C8) | AF8: =SUMIFS('Daily Model'!$AD$4:$AD$664,'Daily Model'!$A$4:$A$664,">="&$B8,'Daily Model'!$A$4:$A$664,"<="&$C8) | AG8: =SUMIFS('Daily Model'!$AE$4:$AE$664,'Daily Model'!$A$4:$A$664,">="&$B8,'Daily Model'!$A$4:$A$664,"<="&$C8) | AH8: =SUMIFS('Daily Model'!$AF$4:$AF$664,'Daily Model'!$A$4:$A$664,">="&$B8,'Daily Model'!$A$4:$A$664,"<="&$C8) | AI8: =SUMIFS('Daily Model'!$AG$4:$AG$664,'Daily Model'!$A$4:$A$664,">="&$B8,'Daily Model'!$A$4:$A$664,"<="&$C8) | AJ8: =SUMIFS('Daily Model'!$AH$4:$AH$664,'Daily Model'!$A$4:$A$664,">="&$B8,'Daily Model'!$A$4:$A$664,"<="&$C8) | AK8: =AI8-AJ8 | AL8: =IF(D8=0,"",P8/D8*10000) | AM8: =IF(E8=0,"",Q8/E8*10000) | AN8: =IF(F8=0,"",R8/F8*10000) | AO8: =IF(G8=0,"",S8/G8*10000) | AP8: =SUMIFS('Daily Model'!$AN$4:$AN$664,'Daily Model'!$A$4:$A$664,">="&$B8,'Daily Model'!$A$4:$A$664,"<="&$C8) | AQ8: =SUMIFS('Daily Model'!$AO$4:$AO$664,'Daily Model'!$A$4:$A$664,">="&$B8,'Daily Model'!$A$4:$A$664,"<="&$C8) | AR8: =SUMIFS('Daily Model'!$AP$4:$AP$664,'Daily Model'!$A$4:$A$664,">="&$B8,'Daily Model'!$A$4:$A$664,"<="&$C8) | AS8: =SUMIFS('Daily Model'!$AQ$4:$AQ$664,'Daily Model'!$A$4:$A$664,">="&$B8,'Daily Model'!$A$4:$A$664,"<="&$C8) | AT8: =SUMIFS('Daily Model'!$AR$4:$AR$664,'Daily Model'!$A$4:$A$664,">="&$B8,'Daily Model'!$A$4:$A$664,"<="&$C8) | AU8: =IF(AT8=0,"",AS8/AT8) | AV8: 37855112 | AW8: =SUMIFS('Daily Model'!$AU$4:$AU$664,'Daily Model'!$A$4:$A$664,">="&$B8,'Daily Model'!$A$4:$A$664,"<="&$C8) | AX8: =SUMIFS('Daily Model'!$AV$4:$AV$664,'Daily Model'!$A$4:$A$664,">="&$B8,'Daily Model'!$A$4:$A$664,"<="&$C8) | AY8: =SUMIFS('Daily Model'!$AW$4:$AW$664,'Daily Model'!$A$4:$A$664,">="&$B8,'Daily Model'!$A$4:$A$664,"<="&$C8) | AZ8: 432.3217 | BA8: 0.0223 | BB8: 4.1841903e+08 | BC8: 60487233 | BD8: 37855112 | BE8: 2971663 | BF8: 744540.86 | BG8: 4.7952242e+08 | BH8: 236.2543 | BI8: 243.2682 | BJ8: 1.240045e+10
A9: Q1 2026 | B9: 46023 | C9: 46112 | D9: =SUMIFS('Daily Model'!$B$4:$B$664,'Daily Model'!$A$4:$A$664,">="&$B9,'Daily Model'!$A$4:$A$664,"<="&$C9) | E9: =SUMIFS('Daily Model'!$C$4:$C$664,'Daily Model'!$A$4:$A$664,">="&$B9,'Daily Model'!$A$4:$A$664,"<="&$C9) | F9: =SUMIFS('Daily Model'!$D$4:$D$664,'Daily Model'!$A$4:$A$664,">="&$B9,'Daily Model'!$A$4:$A$664,"<="&$C9) | G9: =SUMIFS('Daily Model'!$E$4:$E$664,'Daily Model'!$A$4:$A$664,">="&$B9,'Daily Model'!$A$4:$A$664,"<="&$C9) | H9: =SUMIFS('Daily Model'!$F$4:$F$664,'Daily Model'!$A$4:$A$664,">="&$B9,'Daily Model'!$A$4:$A$664,"<="&$C9) | I9: =SUMIFS('Daily Model'!$G$4:$G$664,'Daily Model'!$A$4:$A$664,">="&$B9,'Daily Model'!$A$4:$A$664,"<="&$C9) | J9: =SUMIFS('Daily Model'!$H$4:$H$664,'Daily Model'!$A$4:$A$664,">="&$B9,'Daily Model'!$A$4:$A$664,"<="&$C9) | K9: =SUMIFS('Daily Model'!$I$4:$I$664,'Daily Model'!$A$4:$A$664,">="&$B9,'Daily Model'!$A$4:$A$664,"<="&$C9) | L9: =SUMIFS('Daily Model'!$J$4:$J$664,'Daily Model'!$A$4:$A$664,">="&$B9,'Daily Model'!$A$4:$A$664,"<="&$C9) | M9: =SUMIFS('Daily Model'!$K$4:$K$664,'Daily Model'!$A$4:$A$664,">="&$B9,'Daily Model'!$A$4:$A$664,"<="&$C9) | N9: =SUMIFS('Daily Model'!$L$4:$L$664,'Daily Model'!$A$4:$A$664,">="&$B9,'Daily Model'!$A$4:$A$664,"<="&$C9) | O9: =IF(E9=0,"",N9/E9) | P9: =SUMIFS('Daily Model'!$N$4:$N$664,'Daily Model'!$A$4:$A$664,">="&$B9,'Daily Model'!$A$4:$A$664,"<="&$C9) | Q9: =SUMIFS('Daily Model'!$O$4:$O$664,'Daily Model'!$A$4:$A$664,">="&$B9,'Daily Model'!$A$4:$A$664,"<="&$C9) | R9: =SUMIFS('Daily Model'!$P$4:$P$664,'Daily Model'!$A$4:$A$664,">="&$B9,'Daily Model'!$A$4:$A$664,"<="&$C9) | S9: =SUMIFS('Daily Model'!$Q$4:$Q$664,'Daily Model'!$A$4:$A$664,">="&$B9,'Daily Model'!$A$4:$A$664,"<="&$C9) | T9: =SUMIFS('Daily Model'!$R$4:$R$664,'Daily Model'!$A$4:$A$664,">="&$B9,'Daily Model'!$A$4:$A$664,"<="&$C9) | V9: =SUMIFS('Daily Model'!$T$4:$T$664,'Daily Model'!$A$4:$A$664,">="&$B9,'Daily Model'!$A$4:$A$664,"<="&$C9) | W9: =SUMIFS('Daily Model'!$U$4:$U$664,'Daily Model'!$A$4:$A$664,">="&$B9,'Daily Model'!$A$4:$A$664,"<="&$C9) | X9: =SUMIFS('Daily Model'!$V$4:$V$664,'Daily Model'!$A$4:$A$664,">="&$B9,'Daily Model'!$A$4:$A$664,"<="&$C9) | Y9: =SUMIFS('Daily Model'!$W$4:$W$664,'Daily Model'!$A$4:$A$664,">="&$B9,'Daily Model'!$A$4:$A$664,"<="&$C9) | Z9: =SUMIFS('Daily Model'!$X$4:$X$664,'Daily Model'!$A$4:$A$664,">="&$B9,'Daily Model'!$A$4:$A$664,"<="&$C9) | AA9: =SUMIFS('Daily Model'!$Y$4:$Y$664,'Daily Model'!$A$4:$A$664,">="&$B9,'Daily Model'!$A$4:$A$664,"<="&$C9) | AB9: =SUMIFS('Daily Model'!$Z$4:$Z$664,'Daily Model'!$A$4:$A$664,">="&$B9,'Daily Model'!$A$4:$A$664,"<="&$C9) | AC9: =SUMIFS('Daily Model'!$AA$4:$AA$664,'Daily Model'!$A$4:$A$664,">="&$B9,'Daily Model'!$A$4:$A$664,"<="&$C9) | AD9: =SUMIFS('Daily Model'!$AB$4:$AB$664,'Daily Model'!$A$4:$A$664,">="&$B9,'Daily Model'!$A$4:$A$664,"<="&$C9) | AE9: =SUMIFS('Daily Model'!$AC$4:$AC$664,'Daily Model'!$A$4:$A$664,">="&$B9,'Daily Model'!$A$4:$A$664,"<="&$C9) | AF9: =SUMIFS('Daily Model'!$AD$4:$AD$664,'Daily Model'!$A$4:$A$664,">="&$B9,'Daily Model'!$A$4:$A$664,"<="&$C9) | AG9: =SUMIFS('Daily Model'!$AE$4:$AE$664,'Daily Model'!$A$4:$A$664,">="&$B9,'Daily Model'!$A$4:$A$664,"<="&$C9) | AH9: =SUMIFS('Daily Model'!$AF$4:$AF$664,'Daily Model'!$A$4:$A$664,">="&$B9,'Daily Model'!$A$4:$A$664,"<="&$C9) | AI9: =SUMIFS('Daily Model'!$AG$4:$AG$664,'Daily Model'!$A$4:$A$664,">="&$B9,'Daily Model'!$A$4:$A$664,"<="&$C9) | AJ9: =SUMIFS('Daily Model'!$AH$4:$AH$664,'Daily Model'!$A$4:$A$664,">="&$B9,'Daily Model'!$A$4:$A$664,"<="&$C9) | AK9: =AI9-AJ9 | AL9: =IF(D9=0,"",P9/D9*10000) | AM9: =IF(E9=0,"",Q9/E9*10000) | AN9: =IF(F9=0,"",R9/F9*10000) | AO9: =IF(G9=0,"",S9/G9*10000) | AP9: =SUMIFS('Daily Model'!$AN$4:$AN$664,'Daily Model'!$A$4:$A$664,">="&$B9,'Daily Model'!$A$4:$A$664,"<="&$C9) | AQ9: =SUMIFS('Daily Model'!$AO$4:$AO$664,'Daily Model'!$A$4:$A$664,">="&$B9,'Daily Model'!$A$4:$A$664,"<="&$C9) | AR9: =SUMIFS('Daily Model'!$AP$4:$AP$664,'Daily Model'!$A$4:$A$664,">="&$B9,'Daily Model'!$A$4:$A$664,"<="&$C9) | AS9: =SUMIFS('Daily Model'!$AQ$4:$AQ$664,'Daily Model'!$A$4:$A$664,">="&$B9,'Daily Model'!$A$4:$A$664,"<="&$C9) | AT9: =SUMIFS('Daily Model'!$AR$4:$AR$664,'Daily Model'!$A$4:$A$664,">="&$B9,'Daily Model'!$A$4:$A$664,"<="&$C9) | AU9: =IF(AT9=0,"",AS9/AT9) | AV9: 42797055 | AW9: =SUMIFS('Daily Model'!$AU$4:$AU$664,'Daily Model'!$A$4:$A$664,">="&$B9,'Daily Model'!$A$4:$A$664,"<="&$C9) | AX9: =SUMIFS('Daily Model'!$AV$4:$AV$664,'Daily Model'!$A$4:$A$664,">="&$B9,'Daily Model'!$A$4:$A$664,"<="&$C9) | AY9: =SUMIFS('Daily Model'!$AW$4:$AW$664,'Daily Model'!$A$4:$A$664,">="&$B9,'Daily Model'!$A$4:$A$664,"<="&$C9) | AZ9: 434.6766 | BA9: 0.0222 | BB9: 4.1603739e+08 | BC9: 60487233 | BD9: 42797055 | BE9: 2971663 | BF9: 974830.65 | BG9: 4.7673183e+08 | BH9: 234.8149 | BI9: 241.9169 | BJ9: 1.7567568e+10
A10: Q2 2026 | B10: 46113 | C10: 46203 | D10: =SUMIFS('Daily Model'!$B$4:$B$664,'Daily Model'!$A$4:$A$664,">="&$B10,'Daily Model'!$A$4:$A$664,"<="&$C10) | E10: =SUMIFS('Daily Model'!$C$4:$C$664,'Daily Model'!$A$4:$A$664,">="&$B10,'Daily Model'!$A$4:$A$664,"<="&$C10) | F10: =SUMIFS('Daily Model'!$D$4:$D$664,'Daily Model'!$A$4:$A$664,">="&$B10,'Daily Model'!$A$4:$A$664,"<="&$C10) | G10: =SUMIFS('Daily Model'!$E$4:$E$664,'Daily Model'!$A$4:$A$664,">="&$B10,'Daily Model'!$A$4:$A$664,"<="&$C10) | H10: =SUMIFS('Daily Model'!$F$4:$F$664,'Daily Model'!$A$4:$A$664,">="&$B10,'Daily Model'!$A$4:$A$664,"<="&$C10) | I10: =SUMIFS('Daily Model'!$G$4:$G$664,'Daily Model'!$A$4:$A$664,">="&$B10,'Daily Model'!$A$4:$A$664,"<="&$C10) | J10: =SUMIFS('Daily Model'!$H$4:$H$664,'Daily Model'!$A$4:$A$664,">="&$B10,'Daily Model'!$A$4:$A$664,"<="&$C10) | K10: =SUMIFS('Daily Model'!$I$4:$I$664,'Daily Model'!$A$4:$A$664,">="&$B10,'Daily Model'!$A$4:$A$664,"<="&$C10) | L10: =SUMIFS('Daily Model'!$J$4:$J$664,'Daily Model'!$A$4:$A$664,">="&$B10,'Daily Model'!$A$4:$A$664,"<="&$C10) | M10: =SUMIFS('Daily Model'!$K$4:$K$664,'Daily Model'!$A$4:$A$664,">="&$B10,'Daily Model'!$A$4:$A$664,"<="&$C10) | N10: =SUMIFS('Daily Model'!$L$4:$L$664,'Daily Model'!$A$4:$A$664,">="&$B10,'Daily Model'!$A$4:$A$664,"<="&$C10) | O10: =IF(E10=0,"",N10/E10) | P10: =SUMIFS('Daily Model'!$N$4:$N$664,'Daily Model'!$A$4:$A$664,">="&$B10,'Daily Model'!$A$4:$A$664,"<="&$C10) | Q10: =SUMIFS('Daily Model'!$O$4:$O$664,'Daily Model'!$A$4:$A$664,">="&$B10,'Daily Model'!$A$4:$A$664,"<="&$C10) | R10: =SUMIFS('Daily Model'!$P$4:$P$664,'Daily Model'!$A$4:$A$664,">="&$B10,'Daily Model'!$A$4:$A$664,"<="&$C10) | S10: =SUMIFS('Daily Model'!$Q$4:$Q$664,'Daily Model'!$A$4:$A$664,">="&$B10,'Daily Model'!$A$4:$A$664,"<="&$C10) | T10: =SUMIFS('Daily Model'!$R$4:$R$664,'Daily Model'!$A$4:$A$664,">="&$B10,'Daily Model'!$A$4:$A$664,"<="&$C10) | V10: =SUMIFS('Daily Model'!$T$4:$T$664,'Daily Model'!$A$4:$A$664,">="&$B10,'Daily Model'!$A$4:$A$664,"<="&$C10) | W10: =SUMIFS('Daily Model'!$U$4:$U$664,'Daily Model'!$A$4:$A$664,">="&$B10,'Daily Model'!$A$4:$A$664,"<="&$C10) | X10: =SUMIFS('Daily Model'!$V$4:$V$664,'Daily Model'!$A$4:$A$664,">="&$B10,'Daily Model'!$A$4:$A$664,"<="&$C10) | Y10: =SUMIFS('Daily Model'!$W$4:$W$664,'Daily Model'!$A$4:$A$664,">="&$B10,'Daily Model'!$A$4:$A$664,"<="&$C10) | Z10: =SUMIFS('Daily Model'!$X$4:$X$664,'Daily Model'!$A$4:$A$664,">="&$B10,'Daily Model'!$A$4:$A$664,"<="&$C10) | AA10: =SUMIFS('Daily Model'!$Y$4:$Y$664,'Daily Model'!$A$4:$A$664,">="&$B10,'Daily Model'!$A$4:$A$664,"<="&$C10) | AB10: =SUMIFS('Daily Model'!$Z$4:$Z$664,'Daily Model'!$A$4:$A$664,">="&$B10,'Daily Model'!$A$4:$A$664,"<="&$C10) | AC10: =SUMIFS('Daily Model'!$AA$4:$AA$664,'Daily Model'!$A$4:$A$664,">="&$B10,'Daily Model'!$A$4:$A$664,"<="&$C10) | AD10: =SUMIFS('Daily Model'!$AB$4:$AB$664,'Daily Model'!$A$4:$A$664,">="&$B10,'Daily Model'!$A$4:$A$664,"<="&$C10) | AE10: =SUMIFS('Daily Model'!$AC$4:$AC$664,'Daily Model'!$A$4:$A$664,">="&$B10,'Daily Model'!$A$4:$A$664,"<="&$C10) | AF10: =SUMIFS('Daily Model'!$AD$4:$AD$664,'Daily Model'!$A$4:$A$664,">="&$B10,'Daily Model'!$A$4:$A$664,"<="&$C10) | AG10: =SUMIFS('Daily Model'!$AE$4:$AE$664,'Daily Model'!$A$4:$A$664,">="&$B10,'Daily Model'!$A$4:$A$664,"<="&$C10) | AH10: =SUMIFS('Daily Model'!$AF$4:$AF$664,'Daily Model'!$A$4:$A$664,">="&$B10,'Daily Model'!$A$4:$A$664,"<="&$C10) | AI10: =SUMIFS('Daily Model'!$AG$4:$AG$664,'Daily Model'!$A$4:$A$664,">="&$B10,'Daily Model'!$A$4:$A$664,"<="&$C10) | AJ10: =SUMIFS('Daily Model'!$AH$4:$AH$664,'Daily Model'!$A$4:$A$664,">="&$B10,'Daily Model'!$A$4:$A$664,"<="&$C10) | AK10: =AI10-AJ10 | AL10: =IF(D10=0,"",P10/D10*10000) | AM10: =IF(E10=0,"",Q10/E10*10000) | AN10: =IF(F10=0,"",R10/F10*10000) | AO10: =IF(G10=0,"",S10/G10*10000) | AP10: =SUMIFS('Daily Model'!$AN$4:$AN$664,'Daily Model'!$A$4:$A$664,">="&$B10,'Daily Model'!$A$4:$A$664,"<="&$C10) | AQ10: =SUMIFS('Daily Model'!$AO$4:$AO$664,'Daily Model'!$A$4:$A$664,">="&$B10,'Daily Model'!$A$4:$A$664,"<="&$C10) | AR10: =SUMIFS('Daily Model'!$AP$4:$AP$664,'Daily Model'!$A$4:$A$664,">="&$B10,'Daily Model'!$A$4:$A$664,"<="&$C10) | AS10: =SUMIFS('Daily Model'!$AQ$4:$AQ$664,'Daily Model'!$A$4:$A$664,">="&$B10,'Daily Model'!$A$4:$A$664,"<="&$C10) | AT10: =SUMIFS('Daily Model'!$AR$4:$AR$664,'Daily Model'!$A$4:$A$664,">="&$B10,'Daily Model'!$A$4:$A$664,"<="&$C10) | AU10: =IF(AT10=0,"",AS10/AT10) | AV10: 45564842 | AW10: =SUMIFS('Daily Model'!$AU$4:$AU$664,'Daily Model'!$A$4:$A$664,">="&$B10,'Daily Model'!$A$4:$A$664,"<="&$C10) | AX10: =SUMIFS('Daily Model'!$AV$4:$AV$664,'Daily Model'!$A$4:$A$664,">="&$B10,'Daily Model'!$A$4:$A$664,"<="&$C10) | AY10: =SUMIFS('Daily Model'!$AW$4:$AW$664,'Daily Model'!$A$4:$A$664,">="&$B10,'Daily Model'!$A$4:$A$664,"<="&$C10) | AZ10: 438.1081 | BA10: 0.0223 | BB10: 4.1362535e+08 | BC10: 60487233 | BD10: 45564842 | BE10: 2971663 | BF10: 1131534.2 | BG10: 4.7621938e+08 | BH10: 233.5293 | BI10: 242.6901 | BJ10: 3.145429e+10
A11: Q3 2026 (to 09-21) | B11: 46204 | C11: 46286 | D11: =SUMIFS('Daily Model'!$B$4:$B$664,'Daily Model'!$A$4:$A$664,">="&$B11,'Daily Model'!$A$4:$A$664,"<="&$C11) | E11: =SUMIFS('Daily Model'!$C$4:$C$664,'Daily Model'!$A$4:$A$664,">="&$B11,'Daily Model'!$A$4:$A$664,"<="&$C11) | F11: =SUMIFS('Daily Model'!$D$4:$D$664,'Daily Model'!$A$4:$A$664,">="&$B11,'Daily Model'!$A$4:$A$664,"<="&$C11) | G11: =SUMIFS('Daily Model'!$E$4:$E$664,'Daily Model'!$A$4:$A$664,">="&$B11,'Daily Model'!$A$4:$A$664,"<="&$C11) | H11: =SUMIFS('Daily Model'!$F$4:$F$664,'Daily Model'!$A$4:$A$664,">="&$B11,'Daily Model'!$A$4:$A$664,"<="&$C11) | I11: =SUMIFS('Daily Model'!$G$4:$G$664,'Daily Model'!$A$4:$A$664,">="&$B11,'Daily Model'!$A$4:$A$664,"<="&$C11) | J11: =SUMIFS('Daily Model'!$H$4:$H$664,'Daily Model'!$A$4:$A$664,">="&$B11,'Daily Model'!$A$4:$A$664,"<="&$C11) | K11: =SUMIFS('Daily Model'!$I$4:$I$664,'Daily Model'!$A$4:$A$664,">="&$B11,'Daily Model'!$A$4:$A$664,"<="&$C11) | L11: =SUMIFS('Daily Model'!$J$4:$J$664,'Daily Model'!$A$4:$A$664,">="&$B11,'Daily Model'!$A$4:$A$664,"<="&$C11) | M11: =SUMIFS('Daily Model'!$K$4:$K$664,'Daily Model'!$A$4:$A$664,">="&$B11,'Daily Model'!$A$4:$A$664,"<="&$C11) | N11: =SUMIFS('Daily Model'!$L$4:$L$664,'Daily Model'!$A$4:$A$664,">="&$B11,'Daily Model'!$A$4:$A$664,"<="&$C11) | O11: =IF(E11=0,"",N11/E11) | P11: =SUMIFS('Daily Model'!$N$4:$N$664,'Daily Model'!$A$4:$A$664,">="&$B11,'Daily Model'!$A$4:$A$664,"<="&$C11) | Q11: =SUMIFS('Daily Model'!$O$4:$O$664,'Daily Model'!$A$4:$A$664,">="&$B11,'Daily Model'!$A$4:$A$664,"<="&$C11) | R11: =SUMIFS('Daily Model'!$P$4:$P$664,'Daily Model'!$A$4:$A$664,">="&$B11,'Daily Model'!$A$4:$A$664,"<="&$C11) | S11: =SUMIFS('Daily Model'!$Q$4:$Q$664,'Daily Model'!$A$4:$A$664,">="&$B11,'Daily Model'!$A$4:$A$664,"<="&$C11) | T11: =SUMIFS('Daily Model'!$R$4:$R$664,'Daily Model'!$A$4:$A$664,">="&$B11,'Daily Model'!$A$4:$A$664,"<="&$C11) | V11: =SUMIFS('Daily Model'!$T$4:$T$664,'Daily Model'!$A$4:$A$664,">="&$B11,'Daily Model'!$A$4:$A$664,"<="&$C11) | W11: =SUMIFS('Daily Model'!$U$4:$U$664,'Daily Model'!$A$4:$A$664,">="&$B11,'Daily Model'!$A$4:$A$664,"<="&$C11) | X11: =SUMIFS('Daily Model'!$V$4:$V$664,'Daily Model'!$A$4:$A$664,">="&$B11,'Daily Model'!$A$4:$A$664,"<="&$C11) | Y11: =SUMIFS('Daily Model'!$W$4:$W$664,'Daily Model'!$A$4:$A$664,">="&$B11,'Daily Model'!$A$4:$A$664,"<="&$C11) | Z11: =SUMIFS('Daily Model'!$X$4:$X$664,'Daily Model'!$A$4:$A$664,">="&$B11,'Daily Model'!$A$4:$A$664,"<="&$C11) | AA11: =SUMIFS('Daily Model'!$Y$4:$Y$664,'Daily Model'!$A$4:$A$664,">="&$B11,'Daily Model'!$A$4:$A$664,"<="&$C11) | AB11: =SUMIFS('Daily Model'!$Z$4:$Z$664,'Daily Model'!$A$4:$A$664,">="&$B11,'Daily Model'!$A$4:$A$664,"<="&$C11) | AC11: =SUMIFS('Daily Model'!$AA$4:$AA$664,'Daily Model'!$A$4:$A$664,">="&$B11,'Daily Model'!$A$4:$A$664,"<="&$C11) | AD11: =SUMIFS('Daily Model'!$AB$4:$AB$664,'Daily Model'!$A$4:$A$664,">="&$B11,'Daily Model'!$A$4:$A$664,"<="&$C11) | AE11: =SUMIFS('Daily Model'!$AC$4:$AC$664,'Daily Model'!$A$4:$A$664,">="&$B11,'Daily Model'!$A$4:$A$664,"<="&$C11) | AF11: =SUMIFS('Daily Model'!$AD$4:$AD$664,'Daily Model'!$A$4:$A$664,">="&$B11,'Daily Model'!$A$4:$A$664,"<="&$C11) | AG11: =SUMIFS('Daily Model'!$AE$4:$AE$664,'Daily Model'!$A$4:$A$664,">="&$B11,'Daily Model'!$A$4:$A$664,"<="&$C11) | AH11: =SUMIFS('Daily Model'!$AF$4:$AF$664,'Daily Model'!$A$4:$A$664,">="&$B11,'Daily Model'!$A$4:$A$664,"<="&$C11) | AI11: =SUMIFS('Daily Model'!$AG$4:$AG$664,'Daily Model'!$A$4:$A$664,">="&$B11,'Daily Model'!$A$4:$A$664,"<="&$C11) | AJ11: =SUMIFS('Daily Model'!$AH$4:$AH$664,'Daily Model'!$A$4:$A$664,">="&$B11,'Daily Model'!$A$4:$A$664,"<="&$C11) | AK11: =AI11-AJ11 | AL11: =IF(D11=0,"",P11/D11*10000) | AM11: =IF(E11=0,"",Q11/E11*10000) | AN11: =IF(F11=0,"",R11/F11*10000) | AO11: =IF(G11=0,"",S11/G11*10000) | AP11: =SUMIFS('Daily Model'!$AN$4:$AN$664,'Daily Model'!$A$4:$A$664,">="&$B11,'Daily Model'!$A$4:$A$664,"<="&$C11) | AQ11: =SUMIFS('Daily Model'!$AO$4:$AO$664,'Daily Model'!$A$4:$A$664,">="&$B11,'Daily Model'!$A$4:$A$664,"<="&$C11) | AR11: =SUMIFS('Daily Model'!$AP$4:$AP$664,'Daily Model'!$A$4:$A$664,">="&$B11,'Daily Model'!$A$4:$A$664,"<="&$C11) | AS11: =SUMIFS('Daily Model'!$AQ$4:$AQ$664,'Daily Model'!$A$4:$A$664,">="&$B11,'Daily Model'!$A$4:$A$664,"<="&$C11) | AT11: =SUMIFS('Daily Model'!$AR$4:$AR$664,'Daily Model'!$A$4:$A$664,">="&$B11,'Daily Model'!$A$4:$A$664,"<="&$C11) | AU11: =IF(AT11=0,"",AS11/AT11) | AV11: 47393279 | AW11: =SUMIFS('Daily Model'!$AU$4:$AU$664,'Daily Model'!$A$4:$A$664,">="&$B11,'Daily Model'!$A$4:$A$664,"<="&$C11) | AX11: =SUMIFS('Daily Model'!$AV$4:$AV$664,'Daily Model'!$A$4:$A$664,">="&$B11,'Daily Model'!$A$4:$A$664,"<="&$C11) | AY11: =SUMIFS('Daily Model'!$AW$4:$AW$664,'Daily Model'!$A$4:$A$664,">="&$B11,'Daily Model'!$A$4:$A$664,"<="&$C11) | AZ11: 441.9145 | BA11: 0.0224 | BB11: 4.1139847e+08 | BC11: 60487233 | BD11: 47393279 | BE11: 2971663 | BF11: 1382097.4 | BG11: 4.7636726e+08 | BH11: 232.2109 | BI11: 244.1564 | BJ11: 4.480234e+10

Sheet HIP-4
A1: HIP-4 — OUTCOME / PREDICTION MARKETS. Volume by deployer venue: Hyperliquid-canonical vs third-party. Daily 2026-05-02 → 2026-09-21
A2: Source: Loris (api.loris.tools/hip4-analytics/dashboard?range=all, plus &venue=out|skew|txyz for the split). Deployer addresses from Hyperliquid POST /info type=outcomeMeta. Volume is TRADING volume on the same basis as the Daily Model; settlement is shown separately and is NOT in the daily bridge.
A4: SUMMARY
A5: Cumulative HIP-4 trading volume | B5: $344,834,404
A6: of which in-house (Hyperliquid-canonical) | B6: $305,323,436 (88.5%)
A7: of which third-party deployers | B7: $39,510,968 (11.5%)
A8: First day with third-party volume | B8: 2026-08-29 — permissionless deployment went live on mainnet 2026-08-29
A9: Third-party share, last 7 days (2026-09-15..2026-09-21) | B9: 90.4%
A10: Cumulative HIP-4 fees (trading, in the daily bridge) | B10: $35,005
A11: Cumulative settlement volume (NOT in the daily bridge) | B11: $102,002,333
A12: Cumulative settlement fees (NOT in the daily bridge) | B12: $12,521
A14: Date | B14: HIP-4 Vol ($) | C14: In-House Vol ($) | D14: 3rd-Party Vol ($) | E14: 3rd-Party Share | F14: Outcome.xyz (out) ($) | G14: skew ($) | H14: txyz ($) | I14: HIP-4 Fees ($) | J14: Settlement Vol ($) | K14: Settlement Fees ($)
A15: 46144 | B15: 2351355.4 | C15: 2351355.4 | D15: 0 | E15: =IF(B15=0,"",D15/B15) | F15: 0 | G15: 0 | H15: 0 | I15: 9.240006 | J15: 0 | K15: 0
A16: 46145 | B16: 2722692.4 | C16: 2722692.4 | D16: 0 | E16: =IF(B16=0,"",D16/B16) | F16: 0 | G16: 0 | H16: 0 | I16: 9.6472306 | J16: 873624 | K16: 0
A17: 46146 | B17: 2879142.2 | C17: 2879142.2 | D17: 0 | E17: =IF(B17=0,"",D17/B17) | F17: 0 | G17: 0 | H17: 0 | I17: 23.490365 | J17: 1031587 | K17: 0
A18: 46147 | B18: 2867489.7 | C18: 2867489.7 | D18: 0 | E18: =IF(B18=0,"",D18/B18) | F18: 0 | G18: 0 | H18: 0 | I18: 16.281623 | J18: 941630 | K18: 0
A19: 46148 | B19: 2094825.8 | C19: 2094825.8 | D19: 0 | E19: =IF(B19=0,"",D19/B19) | F19: 0 | G19: 0 | H19: 0 | I19: 10.13372 | J19: 750149 | K19: 0
A20: 46149 | B20: 2513035.4 | C20: 2513035.4 | D20: 0 | E20: =IF(B20=0,"",D20/B20) | F20: 0 | G20: 0 | H20: 0 | I20: 11.282943 | J20: 673066 | K20: 0
A21: 46150 | B21: 2324793.9 | C21: 2324793.9 | D21: 0 | E21: =IF(B21=0,"",D21/B21) | F21: 0 | G21: 0 | H21: 0 | I21: 27.708242 | J21: 741321 | K21: 0
A22: 46151 | B22: 1434595.9 | C22: 1434595.9 | D22: 0 | E22: =IF(B22=0,"",D22/B22) | F22: 0 | G22: 0 | H22: 0 | I22: 20.778882 | J22: 477646 | K22: 0
A23: 46152 | B23: 4011109.2 | C23: 4011109.2 | D23: 0 | E23: =IF(B23=0,"",D23/B23) | F23: 0 | G23: 0 | H23: 0 | I23: 28.428475 | J23: 511978 | K23: 0
A24: 46153 | B24: 3473040.4 | C24: 3473040.4 | D24: 0 | E24: =IF(B24=0,"",D24/B24) | F24: 0 | G24: 0 | H24: 0 | I24: 22.839277 | J24: 634930 | K24: 0
A25: 46154 | B25: 2855754 | C25: 2855754 | D25: 0 | E25: =IF(B25=0,"",D25/B25) | F25: 0 | G25: 0 | H25: 0 | I25: 21.429722 | J25: 542305 | K25: 0
A26: 46155 | B26: 2724369.3 | C26: 2724369.3 | D26: 0 | E26: =IF(B26=0,"",D26/B26) | F26: 0 | G26: 0 | H26: 0 | I26: 29.16884 | J26: 522032 | K26: 0
... A157: 46286 | B157: 2202325.7 | C157: 141186.6 | D157: 2061139.1 | E157: =IF(B157=0,"",D157/B157) | F157: 1948163 | G157: 23097.159 | H157: 89878.954 | I157: 1022.2419 | J157: 820103 | K157: 582.33794
A159: NOTES
A160: IN-HOUSE vs THIRD-PARTY. Loris serves its HIP-4 dashboard per deployer venue, so the split is SOURCED, not inferred: third-party = venue out + venue skew + venue txyz, in-house = total minus those three. Deployer addresses, from Hyperliquid POST api.hyperliquid.xyz/info type=outcomeMeta -> deployers: out = 0x0c46eb73fae2816f219fcf11f50d6d3c59b5819e (Outcome.xyz, the first permissionless HIP-4 builder and much the largest), skew = 0x08e9c89f46dccee91bdb85c6532eb93a4c335efe, txyz = 0x7aca09667816a4817b8bc697fb239ad42ff9f553.
A161: THE SPLIT DATES THE LAUNCH BY ITSELF. Third-party volume is EXACTLY ZERO on every day before 2026-08-29 and non-zero from that day on, which confirms the mainnet permissionless-deployment date without relying on any announcement. A deployer must stake 500,000 HYPE for at least six months and call activateOutcomeDeployer.
A162: WHY LORIS AND NOT ASXN. ASXN publishes an HIP-4 daily series (outcome-coins/analytics/daily) that runs about 2.2x higher. Tested against Hyperliquid's own outcome-coin candles - outcome coins ARE retrievable as #<outcomeId><side>, e.g. #12090 - using trade-count as the coverage control, ASXN's total_volume_usdc lands at ~1.0x contract COUNT and ~2.0x USDC notional, i.e. it appears to count contracts at $1 rather than at traded price. Outcome tokens average about $0.50 because a binary pair's two legs sum to $1, which is exactly the observed gap. NOT AIRTIGHT: settled outcome coins are purged from the HL API, so the May-Aug window cannot be rebuilt from primary data and the coverage control is approximate.
A163: SETTLEMENT IS SHOWN BUT EXCLUDED FROM THE DAILY BRIDGE (amber). Loris reports settlement separately from trading. The Daily Model uses trading volume and trading fees only, which is the same basis v6-v8 used; settlement is surfaced here so the omission is visible rather than silent. Adding it would raise cumulative HIP-4 fees by roughly a third.
A164: TRADING VOLUME INCLUDES PRIMARY MINT/REDEEM. Of $343.1M of Loris trading volume to 2026-09-21, only $90.6M is standard secondary trading - $203.2M is split (minting a Yes+No pair from $1) and $49.3M is merge. Read the volume as gross market activity, not as secondary turnover.
A165: DEPLOYER REVENUE SHARE IS MODELLED AT $0 IN THE DAILY SHEET, AS AN ASSUMPTION. Hyperliquid's fee docs grant an explicit up-to-50% deployer share to SPOT and HIP-3 PERP deployers and do not extend that sentence to outcome markets, and neither Loris nor ASXN publishes an HIP-4 deployer fee line. outcomeMeta does carry deployerFeeScale 1.0 on 151 of 201 live outcomes. With third-party venues now around 90% of volume, this is the assumption most likely to need revisiting.

Sheet Sources
A1: SOURCES & METHODOLOGY — refreshed 2026-09-23, data through 2026-09-21
A2: • CORE CRYPTO PERP IS A SOURCED COLUMN, NOT A PLUG, AND ITS EARLY HISTORY IS A DEFILLAMA FILL. Revenue and Fees both take ASXN income-statement fees_perp (ASXN publishes a single protocol-bound perp fee line, so the two columns carry the same value - that is ASXN's structure, not a copy error). ASXN's reconstruction begins 2025-08-17, which left 2024-11-30..2025-08-16 BLANK in v6-v8. Those days now come from DefiLlama hyperliquid-perps (dailyRevenue -> Revenue, dailyFees -> Fees), shaded AMBER with green text. The join is clean in kind: HIP-3 did not launch until 2025-10-13, so DefiLlama's hyperliquid-perps IS core crypto perps across the entire filled window, and on the 400-day overlap DL dailyRevenue runs at a median 0.952x of ASXN fees_perp - close, but a visible level difference at the seam, not scaled or smoothed. 27 DAYS REMAIN BLANK AND ARE NOT FABRICATED: 2024-11-30..2024-12-22 predate DefiLlama's own series start of 2024-12-23, and DefiLlama skips 2025-01-12, 2025-01-13, 2025-06-08 and 2025-06-09. Note buyback revenue does not exist before 2025-03-20 either, so the whole pre-March-2025 stretch is thin by nature.
A3: • WHAT CHANGED IN THIS REFRESH (pulled 2026-09-23, data through 2026-09-21), vs the v8 workbook. (1) 29 NEW ROWS, 2026-08-24..2026-09-21. The cut-off is 09-21 because ASXN's fee pipeline had only a partial 09-22 at pull time ($116,444 of perp fees, 0.17bps against a 3.52-3.83bps norm). (2) v8's OWN LAST ROW WAS PARTIAL for the same reason and is corrected: 2026-08-23 core perp fees/revenue move from $107,203 to $2,643,931, HIP-3 gross fees from $2,386 to $91,542. (3) SPOT VOLUME DATE FIX: ASXN's spot feed is dated one day late and is shifted back one day, which moves 344 historical cells - re-verified on this pull (corr 0.962 shifted vs 0.251 unshifted against DefiLlama over the last 31 days). (4) CORE PERP GAP CLOSED: ASXN fees_perp only starts 2025-08-17, so 2024-12-23..2025-08-16 is now filled from DefiLlama (amber); 233 previously-BLANK cells are now populated and 27 days remain blank because neither source covers them. (5) NEW HIP-4 SHEET with the deployer split (in-house vs third-party out/skew/txyz) plus settlement volume and fees. HIP-4 in the Daily Model stays on LORIS and its history is unchanged from v8 - ASXN's series was trialled and rejected as ~2.2x too high (it counts contracts, not USDC notional). (6) HIP-4 permissionless third-party deployment went live on mainnet 2026-08-29; third-party venues are now the large majority of HIP-4 volume. (7) Team unlocks extended on-chain through the 2026-09-06 claim of 433,419 HYPE (no October claim yet). (8) Hyper Foundation and Community Grants re-read from hypestrat - they drift every refresh, and since v8 have moved +57,693 and +5,101 HYPE, lowering OTS by 62,794 on every row. (9) AF gap-fill: ASXN's assistance-fund feed has a single hole at 2026-08-24 which blanked the whole supply block that day; it is reconstructed from the balance identity and shaded amber. (10) HIP-4 DEPLOYER FEE SHARE IS NO LONGER ZERO: it was hardcoded 0 through v10 and is now 50% of fees on the venues whose deployerFeeScale is 1.0 (out, skew), which cuts cumulative HIP-4 revenue by about $12.5K. See the HIP-4 deployer note. (11) ASXN restates some of its own recent history between pulls - spot fees, Unit fees, builder fees (a 90-day rolling window) and auction burn all move slightly, none by more than 0.3%.
A4: • SPOT VOLUME: ASXN'S FEED IS DATED ONE DAY LATE AND IS SHIFTED BACK ONE DAY IN v9. The value ASXN labels 2026-09-19 is really 2026-09-18's. Proven three ways: (1) PRIMARY - Hyperliquid's own spot candles (candleSnapshot, coin @107 HYPE/USDC, explicit UTC-midnight timestamps) correlate 0.905 on a -1 shift vs 0.565 unshifted over 2026-08-21..09-21, and HL's peak day 2026-08-21 shows up in ASXN as 2026-08-22; (2) INDEPENDENT - vs DefiLlama the -1 shift wins in EVERY month from 2025-12 to 2026-09 (0.945-0.993 shifted vs 0.199-0.850 unshifted), while DefiLlama itself sits at lag 0 against the HL candles; (3) ASXN-INTERNAL - ASXN's own income-statement fees_spot lines up with DefiLlama at lag 0 but with this volume feed only on a -1 shift, so ASXN's two pipelines disagree and the fee one is correctly dated. Left unfixed (the v6-v8 behaviour) Spot Vol sat one day away from Spot Fees, so every daily spot take-rate was computed across two different days. Same class of defect as the HIP-3 volume offset fixed in v8, opposite direction. CONSEQUENCE: spot volume now differs from the ASXN dashboard by one day everywhere. AND, SEPARATELY, THE FORMATTING TELLS YOU THE SOURCE. Primary source is ASXN spot-ecosystem/hl-spot-ecosystem, summed across ALL listed tokens each day (307 listings = the 8 named coins PLUS the Others bucket) - this reproduces ASXN's own Spot Volume chart exactly, month by month and token by token. But that feed only begins 2025-07-16 and skips days inside its own range, so every remaining day is filled from DefiLlama /summary/dexs/hyperliquid-spot-orderbook dailyVolume to leave NO holes in the series. HOW TO READ IT: plain BLUE text = ASXN; AMBER-shaded cell with GREEN text = DefiLlama fill. 291 of 632 days are DefiLlama - all of 2024-11-30..2025-07-15 (pre-ASXN) plus ASXN's internal gaps, the worst being Oct-2025 (ASXN had 1 day of 31) and Nov-2025 (8 of 30). TRADE-OFF, DELIBERATE: because those months are now complete rather than partial, they NO LONGER match the ASXN dashboard - Oct-2025 and Nov-2025 move the most. Months where ASXN is day-complete (Dec-2025 onward) still tie to the chart exactly. NOTE the two providers also differ in level on days where both exist, so the join is not seamless; no scaling or smoothing has been applied to hide that.
A5: • SPOT FEES ARE ASXN-PRIMARY, DEFILLAMA ONLY AS GAP-FILL. The ASXN income statement gives fees_spot (protocol-bound spot revenue, net) and fees_spot_unit (the Hyperunit deployer cut). It publishes no gross spot-fee line, so gross is derived as fees_spot/(1-HLP) + fees_spot_unit, the one form that makes the bridge (gross - Unit - HLP) reproduce ASXN's own fees_spot exactly. ASXN's fee reconstruction starts 2025-08-17; everything before that is DefiLlama hyperliquid-spot-orderbook dailyFees and is shaded amber. (This supersedes the v6/v7 note that said spot fees were DefiLlama throughout - they have not been since v8.)
A6: • ASXN CHART DATES ARE SHIFTED ONE DAY FORWARD vs its API. Every monthly bar on the hyperscreener dashboard buckets from the 2nd of the month to the 1st of the next - its 'July' bar is 2 Jul to 1 Aug, not 1-31 Jul. Proven on HIP-3: the API gives $114.79B for calendar July while the chart tooltip reads $111.75B, and the shifted window reproduces the tooltip on all five deployer DEXs to the cent (xyz $111.49B, mkts $167.39M, hyna $60.38M, para $30.17M, cash $778.35K). The same offset applies to the category chart ($108.22B calendar vs $105.19B displayed). This workbook uses the API's raw date strings, i.e. TRUE CALENDAR MONTHS, so any month cross-checked against an ASXN chart will differ by one boundary day at each end. Their income-statement TABLE uses calendar months and does tie directly. Separately, ASXN charts also let the user toggle deployer DEXs on and off, so a chart total may exclude DEXs this workbook includes.
A7: • BRIDGE (per segment): Gross Fees − HLP − (Unit on spot) − (deployer on HIP-3 / HIP-4) = Revenue to HyperCore. Builder code fees are ON-TOP (paid by users to front-ends) and are NOT deducted. Sum of segment revenues = HyperCore Revenue = hyperscreener "HyperCore Buybacks" (north star). + HyperEVM + Auction burn = Total Revenue.
A8: • Core crypto perp is the residual segment: Core Revenue = HyperCore − Spot − HIP-3 − HIP-4; Core Fees = Core Revenue / (1 − HLP). This makes the bridge tie exactly to the north star (Check column ≈ 0).
A9: • HLP share: 1% of perp+spot fees from 2025-08-30 (3% before); on spot it applies to (fees − Unit). ASSUMPTION: HIP-4 is modelled on the same HLP share — Hyperliquid has not published an HIP-4-specific HLP split. The amounts are immaterial (<$100 cumulative), and any accrual-vs-buyback timing difference is absorbed by the core-perp residual.
A10: • HIP-4 IS MONETISED AND THIRD-PARTY DEPLOYMENT IS NOW LIVE - AND IT NOW DOMINATES. Launch 2026-05-02 was effectively zero-fee. Fees are 7bps taker / 4bps maker charged ONLY on CLOSE / SETTLE, so the realised take-rate sits far below the nominal schedule. PERMISSIONLESS THIRD-PARTY DEPLOYMENT SHIPPED TO MAINNET ON 2026-08-29 (network upgrade ~08:39 UTC); a deployer stakes 500,000 HYPE for six months and calls activateOutcomeDeployer. SEE THE DEDICATED HIP-4 SHEET for the deployer split (it is deliberately NOT on the Daily Model, which carries only the four HIP-4 lines that feed the bridge: volume, fees, HLP and deployer share). Third-party volume is EXACTLY ZERO on every day before 2026-08-29 and non-zero from that day on - an independent confirmation of the date that does not rely on any announcement. In-house (Hyperliquid-canonical) was 100% of HIP-4 through 2026-08-28; over 2026-09-13..09-19 third-party venues were 89.7% of volume. Cumulative to 2026-09-19: $340.5M total, $305.0M in-house (89.6%), $35.5M third-party (10.4%) - the cumulative still looks in-house-heavy only because third-party is three weeks old. Market types also broadened from BTC price buckets alone to football (UEFA, La Liga), company-IPO and policy-rate templates.
A11: • HIP-4 DEPLOYER FEE SHARE IS NOW DEDUCTED (it was hardcoded ZERO through v10, which the on-chain data contradicts). WHICH VENUES: deployerFeeScale in Hyperliquid's outcomeMeta tracks venue exactly - out 1.0 (97 outcomes), skew 1.0 (52), txyz unset (69), canonical unset (8) - so the deduction hits out and skew only and is zero before 2026-08-29. WHERE THE 50% COMES FROM - the deployer addresses' own USDC balances, not a read-across from HIP-3. Deployer fees credit the balance with no transfer event (as HIP-3 feeRecipient accrual does), so the balance IS the accrued share. Against Loris's per-venue fees (trading + settlement): out $17,090.87 on $31,238.19 = 54.7%; skew $409.60 on $773.56 = 52.9%; txyz, flag unset, $0.00 on $883.85 = 0.0%. Two venues with the flag land independently either side of 50% and the control is exactly zero. They read slightly above 50% because balances are point-in-time and include accrual after the Loris snapshot, and skew carries a small pre-HIP-4 residue; out's ledger predates HIP-4 entirely so out is the clean read. CORRECTION TO AN EARLIER DRAFT: this does NOT rest on HIP-3 reusing deployerFeeScale - perpDexs exposes no such field, only a setDeployerFees permission, so HIP-3 cannot calibrate it. BASE: applied to TRADING fees only, matching the HIP-4 Fees column. Deployers also take a share of SETTLEMENT fees, but settlement is not in this model's fee base at all, so deducting it would subtract revenue never credited - which is why the modelled deduction (~$11.4K) is deliberately smaller than the deployers' true take (~$17.5K). STILL AN ESTIMATE, hence amber: no provider publishes an HIP-4 deployer fee line and the docs still name only spot and HIP-3 perp deployers. Cumulative effect about -$11.4K of HIP-4 revenue - a third of that line, 0.001% of total protocol revenue.
A12: • HIP-3 VOLUME AND FEES NOW BOTH COME FROM ASXN . Volume: /api/meta/hip3/daily-volume-chart. Fees: /api/income-statement fees_hip3 (protocol) + fees_hip3_deployer (deployer), which ASXN reconstructs from HL node_fills (S3) using each dex's per-day deployerShare. VOLUME BARELY MOVED (+0.12% cumulative vs Loris over the 310-day overlap) - the swap is about the FEES.
... A25: FIELD MAP — what each model line reads, and exactly where it comes from
A26: Model line | B26: Endpoint | C26: Field | D26: Basis / note
A27: HyperCore Revenue | B27: api/buyback/revenues | C27: data[].'HyperCore Buybacks' | D27: Source value, taken as given. The north star. 522 days from 2025-03-20.
A28: HyperEVM Burn | B28: api/buyback/revenues | C28: data[].'HyperEVM Burn' | D28: Source value.
A29: Auction Burn | B29: api/buyback/revenues | C29: data[].'Auction Burn' | D29: Source value.
A30: Core Crypto Perp Revenue | B30: ASXN income-statement | C30: fees_perp | D30: SOURCE from 2025-08-17; DefiLlama hyperliquid-perps fill before that (amber); 27 days blank, covered by neither.
A31: Spot Revenue | B31: api/income-statement | C31: fees_spot | D31: ASXN labels it "Spot Markets". Already net of Unit and HLP. Bridge reproduces it to $0.00 over 372 days.
A32: HIP-3 Revenue | B32: api/income-statement | C32: fees_hip3 | D32: ASXN labels it "HIP-3" under Perp Revenue. Already net of deployer and HLP. Bridge reproduces it to $0.00 over 315 days.
A33: (-) Unit Protocol Fees | B33: api/income-statement | C33: fees_spot_unit | D33: Hyperunit deployer cut. DefiLlama /summary/fees/unit before 2025-08-17 (amber).
A34: (-) HIP-3 Deployer Fees | B34: api/income-statement | C34: fees_hip3_deployer | D34: Third-party DEX operator cut; never reaches the AF. JSON only - not shown in ASXN UI.
A35: (-) HLP (all segments) | B35: ASXN UI only — NOT in the JSON | C35: Revenue tab > Costs > HLP | D35: COMPUTED CLIENT-SIDE by ASXN as exactly 1% of NET revenue. Model uses rate/(1+rate) on the grossed-up base and matches their row to the cent across 9 months.
A36: Spot Fees incl Unit | B36: DERIVED | C36: =Spot Revenue x (1+HLP) + Unit | D36: ASXN publishes no gross spot-fee line. DefiLlama dailyFees before 2025-08-17 (amber).
A37: HIP-3 Gross Fees | B37: DERIVED | C37: =HIP-3 Revenue x (1+HLP) + Deployer | D37: ASXN publishes no gross HIP-3 fee line.
A38: Core Crypto Perp Vol | B38: api/cloudfront/total_volume | C38: sum of all coins less dex: coins | D38: Single-sided notional. Ties to api/cloudfront/hip3_percentage total at ratio 1.0000.
A39: HIP-3 Perp Vol | B39: api/meta/hip3/daily-volume-chart | C39: total_volume | D39: Date-realigned +1 day through 2025-11-26; see the column comment.
A40: Spot Vol | B40: api/spot-ecosystem/hl-spot-ecosystem | C40: marketData[date][].'Daily Volume' | D40: Summed across all 307 listings. DefiLlama fill on 293 of 632 days (amber).
A41: HIP-4 Vol / Fees | B41: Loris | C41: api.loris.tools/hip4-analytics/dashboard?range=all -> timeseries.volume, timeseries.total_fees | D41: Loris, not ASXN - ASXN runs ~2.2x high (counts contracts, not USDC notional). Needs a logged-in loris.tools session.
A42: HIP-3 categories | B42: api/categories/hip3-categories/historical | C42: commodities, crypto, fx, indices, preipo, stocks | D42: Pre-2025-11-27 backfilled from ASXN per-symbol map (amber).
A43: Buyback HYPE / price | B43: api/buyback/hl-buybacks | C43: sz, average_price | D43: Source values.
A44: AF HYPE Balance | B44: api/buyback/assistance-fund-holdings | C44: balance | D44: Month/period-end.
A45: Supply & fee burns | B45: api/buyback/daily-burn | C45: dailyBurn, currentDaySupply | D45: HyperCore burns only; HyperEVM leg added separately.
A46: Emissions / circulating | B46: api/validators/daily-emissions | C46: dailyEmission, currentDayFutureEmission, currentDaySupply | D46: Source values.
A47: HYPE Staked | B47: api/validators/hype-staking/metrics | C47: stakeSupplyTimeseries[].totalStake | D47: Period-end.
A48: HYPE Price | B48: api/buyback/hype-price | C48: close | D48: Daily OHLCV.
A49: Hyper Foundation / Community Grants | B49: hypestrat.xyz/hype-tokenomics | C49: 60,429,540 / 2,966,562 | D49: Fixed constants, NOT ASXN.
A51: Data | B51: Source | C51: Endpoint / URL | D51: Notes
A54: FIELD MAP — every model line traced to its exact endpoint and field
A55: Model line | B55: Endpoint | C55: Field / formula | D55: Type
A56: HyperCore Revenue ($) | B56: /api/buyback/revenues | C56: data[].'HyperCore Buybacks' | D56: SOURCE (north star)
A57: HyperEVM Burn ($) | B57: /api/buyback/revenues | C57: data[].'HyperEVM Burn' | D57: SOURCE
A58: Auction Burn ($) | B58: /api/buyback/revenues | C58: data[].'Auction Burn' | D58: SOURCE
A59: Total Revenue ($) | B59: — | C59: =HyperCore Revenue + HyperEVM Burn + Auction Burn | D59: FORMULA (cash basis)
A60: Core Crypto Perp Revenue ($) | B60: /api/income-statement?time_range=all&granularity=daily | C60: fees_perp | D60: SOURCE
A61: HIP-3 Revenue ($) | B61: /api/income-statement | C61: =HIP-3 Gross - Deployer (= fees_hip3) | D61: FORMULA -> ties to ASXN
A62: Spot Revenue ($) | B62: /api/income-statement | C62: =Spot Fees - Unit (= fees_spot) | D62: FORMULA -> ties to ASXN
A63: HIP-4 Revenue ($) | B63: Loris /hip4 | C63: =HIP-4 Fees - HIP-4 Deployer | D63: FORMULA
A64: =HyperCore Revenue (model) | B64: — | C64: =Core + HIP-3 + Spot + HIP-4 | D64: FORMULA (accrual basis)
A65: Check: model - hyperscreener | B65: — | C65: =accrual - cash. NOT zero: real accrual-vs-buyback gap | D65: FORMULA (diagnostic)
A66: HIP-3 Gross Fees ($) | B66: /api/income-statement | C66: =fees_hip3 + fees_hip3_deployer | D66: DERIVED
A67: (-) HIP-3 Deployer Fees ($) | B67: /api/income-statement | C67: fees_hip3_deployer | D67: SOURCE
A68: Spot Fees incl Unit ($) | B68: /api/income-statement | C68: =fees_spot + fees_spot_unit | D68: DERIVED
A69: (-) Unit Protocol Fees ($) | B69: /api/income-statement | C69: fees_spot_unit | D69: SOURCE
A70: (-) HLP on each segment | B70: UI-only (Revenue tab > Costs > HLP) | C70: =segment revenue x HLP Rate | D70: DERIVED, validated vs UI
A71: HLP Rate | B71: DefiLlama methodology | C71: 1% from 2025-08-30, 3% before | D71: ASSUMPTION
A72: Core Crypto Perp Vol ($) | B72: /api/cloudfront/total_volume | C72: sum(all coins) - sum(dex: coins) | D72: DERIVED
A73: HIP-3 Perp Vol ($) | B73: /api/meta/hip3/daily-volume-chart?timeframe=all | C73: total_volume (date-realigned pre-2025-11-27) | D73: SOURCE
A74: Spot Vol ($) | B74: /api/spot-ecosystem/hl-spot-ecosystem | C74: sum of all tokens' 'Daily Volume' | D74: SOURCE (DefiLlama fills gaps)
A75: HIP-4 Vol / Fees ($) | B75: Loris /hip4 timeseries | C75: volume, total_fees (trading only) | D75: SOURCE (not ASXN)
A76: (-) HIP-4 Deployer Fees ($) | B76: Loris per-venue fees x 50% | C76: fees_out + fees_skew, the venues with deployerFeeScale=1.0 | D76: DERIVED (amber)
A77: HIP-3 categories | B77: /api/categories/hip3-categories/historical | C77: 6 categories, pro-rated to HIP-3 volume | D77: SOURCE + pro-rate
A78: Buyback HYPE / Price | B78: /api/buyback/hl-buybacks | C78: sz, average_price | D78: SOURCE
A79: AF HYPE Balance | B79: /api/buyback/assistance-fund-holdings | C79: balance | D79: SOURCE
A80: Staking Emissions / Supply | B80: /api/validators/daily-emissions | C80: dailyEmission, currentDayFutureEmission | D80: SOURCE
A81: Fee Burn / Total Supply | B81: /api/buyback/daily-burn | C81: dailyBurn, currentDaySupply | D81: SOURCE
A82: HYPE Staked | B82: /api/validators/hype-staking/metrics | C82: stakeSupplyTimeseries[].totalStake | D82: SOURCE
... A104: Perp revenue (cross-check only) | B104: DefiLlama | C104: https://api.llama.fi/summary/fees/hyperliquid-perps | D104: Accrual basis; runs above the hyperscreener buyback cumulatively (timing).
