Workbook
Name AfShare: Assumptions!$B$18
Name AprCoef: Assumptions!$B$25
Name BaseMakerRate: Assumptions!$B$6
Name BaseTakerRate: Assumptions!$B$5
Name CoreBpsBlended: Assumptions!$B$7
Name GrowthModeDate: Assumptions!$B$21
Name GrowthModeFactor: Assumptions!$B$8
Name HIP3DeployerShare_50: Assumptions!$B$10
Name HIP3DeployerShare_Hyna: Assumptions!$B$12
Name Hip3LaunchDate: Assumptions!$B$20
Name HIP3TraderScale_50: Assumptions!$B$9
Name HIP3TraderScale_Hyna: Assumptions!$B$11
Name Hip4LaunchDate: Assumptions!$B$22
Name Hip4Rate: Assumptions!$B$23
Name HlpChangeDate: Assumptions!$B$16
Name HlpSharePost: Assumptions!$B$15
Name HlpSharePre: Assumptions!$B$14

Sheet Assumptions
A1: Hyperliquid Master Model — Assumptions
A2: Edit yellow cells to flex the model. All Daily Master formulas reference these names.
A3: Parameter | B3: Value | C3: Format | D3: Source / Note | E3: Defined Name
A4: FEE FLOW (from Hyperliquid docs)
A5: Base perp taker rate (tier 0) | B5: 0.00045 | C5: 0.0000% | D5: Source: Hyperliquid docs > Trading > Fees: tier 0 taker = 0.045% | E5: BaseTakerRate
A6: Base perp maker rate (tier 0) | B6: 0.00015 | C6: 0.0000% | D6: Source: Hyperliquid docs > Trading > Fees: tier 0 maker = 0.015% | E6: BaseMakerRate
A7: Empirical blended core bps (vol-weighted, pre-HIP-3) | B7: 2.897 | C7: 0.000 | D7: Derived from Dec 23 2024 - Oct 12 2025 data: total_perp_fees / total_perp_volume × 10000 | E7: CoreBpsBlended
A8: Growth mode discount factor | B8: 0.1 | C8: 0.0% | D8: Source: Hyperliquid HIP-3 Growth Mode (Nov 19 2025): 90% fee reduction | E8: GrowthModeFactor
A9: HIP-3 trader scale (deployerFeeScale=1, most dexes) | B9: 2 | C9: 0.00 | D9: Source: Hyperliquid fee formula: scaleIfHip3 = deployerFeeScale × 2 when ≥ 1 | E9: HIP3TraderScale_50
A10: HIP-3 deployer share (50/50 case) | B10: 0.5 | C10: 0.0% | D10: Source: Hyperliquid fee formula: deployerShare = 0.5 when deployerFeeScale ≥ 1 | E10: HIP3DeployerShare_50
A11: HyENA trader scale (deployerFeeScale=0.1111) | B11: 1.1111 | C11: 0.0000 | D11: HyENA-specific: 1 + 0.1111 | E11: HIP3TraderScale_Hyna
A12: HyENA deployer share | B12: 0.1 | C12: 0.0% | D12: 0.1111 / (1 + 0.1111) | E12: HIP3DeployerShare_Hyna
A14: HLP REVENUE SHARE — pre Aug 30 2025 | B14: 0.03 | C14: 0.0% | D14: Source: Hyperliquid Fees docs + DefiLlama HLP adapter notes | E14: HlpSharePre
A15: HLP REVENUE SHARE — post Aug 30 2025 | B15: 0.01 | C15: 0.0% | D15: Source: Hyperliquid Fees docs + DefiLlama HLP adapter notes | E15: HlpSharePost
A16: HLP share change date | B16: 45900 | C16: yyyy-mm-dd | D16: Source: empirical observation from DefiLlama data — HLP_fee/revenue ratio dropped from 3.0928% (= 3/97) to 1.0101% (= 1/99) on 2025-08-31 | E16: HlpChangeDate
A18: AF REVENUE SHARE (post HLP cut) | B18: 0.99 | C18: 0.0% | D18: Source: Hyperliquid docs: 99% of fees go to AF for HYPE buybacks (excluding builders/Unit/deployers) | E18: AfShare
... A25: STAKING — APR formula coefficient | B25: 474 | C25: 0 | D25: Source: Hyperliquid docs: at 400M staked, APR ≈ 2.37%. Formula: APR(S) = 474/sqrt(S) | E25: AprCoef

Sheet Daily Master
A1: Daily Master — formulas reference Assumptions sheet
A2: Yellow cells are raw API data. Blue text = formula. All HLP/buyback splits computed dynamically from Assumptions.
A3: Yellow = raw API data; Blue text = Excel formula. Hover over cells for details.
A4: Date | B4: Core perp volume ($) | C4: HIP-3 perp volume ($) | D4: Spot volume ($) | E4: Total perp volume ($) | F4: Total volume incl spot ($) | G4: HIP-3 vol share % | H4: DL Perps fees ($) [raw API] | I4: DL Spot fees ($) [raw API] | J4: DL HLP fees [doublecounted] ($) | K4: Total fees (corrected, Perps+Spot) ($) | L4: Modeled HIP-3 gross fees ($) | M4: Modeled HIP-3 protocol fees ($) | N4: Modeled HIP-3 deployer fees ($) | O4: Implied core fees (Perps - modeled HIP-3 gross) ($) | P4: Implied core bps | Q4: DL Perps revenue (raw API) ($) | R4: DL Spot revenue (raw API) ($) | S4: Total revenue to AF ($) | T4: Effective HLP share % | U4: Implied HLP slice via formula ($) | V4: DL HLP slice (from supplyside_hlp) ($) | W4: HLP slice diff (formula - DL) ($) | X4: DL supplyside total (Y+Z) ($) | Y4: supplyside_perps_usd | Z4: supplyside_spot_usd | AA4: Builders + Unit fees ($) [= X-V] | AB4: DL Holders revenue = AF buyback ($) | AC4: HYPE close price ($) | AD4: HYPE VWAP proxy ($) | AE4: HYPE bought daily (#) | AF4: CHECK: fees=rev+supplyside (=K-S-X) | AG4: CHECK: rev=buyback (=S-AB) | AH4: HP daily total fees ($, indep on-chain) | AI4: HP/DL revenue ratio | AJ4: Total staked HYPE (#) | AK4: Staking APR formula = AprCoef/sqrt(staked) | AL4: Daily HYPE issuance to stakers (#) | AM4: Daily HYPE burned via AF (#) | AN4: Net daily HYPE supply change (#) | AO4: HIP-3 live? | AP4: HIP-4 status | AQ4: # HIP-3 assets active | AR4: # w/ growth mode active
A5: 45066 | B5: 1.4896434e+08 | C5: 0 | E5: =B5+C5 -> 1.4896434e+08 | F5: =E5+D5 -> 1.4896434e+08 | G5: =IFERROR(C5/E5,0) -> 0 | K5: =H5+I5 -> 0 | O5: =IF(H5=0,0,H5-L5) -> 0 | P5: =IF(B5=0,0,O5/B5*10000) -> 0 | S5: =Q5+R5 -> 0 | T5: =IF(A5<HlpChangeDate,HlpSharePre,HlpSharePost) -> 0.03 | U5: =S5*T5/(1-T5) -> 0 | W5: =U5-V5 -> 0 | X5: =Y5+Z5 -> 0 | AA5: =X5-V5 -> 0 | AB5: 0 | AE5: =IFERROR(AB5/AD5,0) -> 0 | AF5: =K5-S5-X5 -> 0 | AG5: =S5-AB5 -> 0 | AI5: =IFERROR(AH5/S5,0) -> 0 | AJ5: 0 | AK5: =IF(AJ5>0,AprCoef/SQRT(AJ5),0) -> 0 | AL5: =AJ5*AK5/365 -> 0 | AM5: =AE5 -> 0 | AN5: =AL5-AM5 -> 0 | AO5: =IF(A5>=Hip3LaunchDate,"YES","") | AP5: =IF(A5<Hip4LaunchDate,"pre-launch","live (zero-fee)") -> pre-launch
A6: 45067 | B6: 1.7817381e+08 | C6: 0 | E6: =B6+C6 -> 1.7817381e+08 | F6: =E6+D6 -> 1.7817381e+08 | G6: =IFERROR(C6/E6,0) -> 0 | K6: =H6+I6 -> 0 | O6: =IF(H6=0,0,H6-L6) -> 0 | P6: =IF(B6=0,0,O6/B6*10000) -> 0 | S6: =Q6+R6 -> 0 | T6: =IF(A6<HlpChangeDate,HlpSharePre,HlpSharePost) -> 0.03 | U6: =S6*T6/(1-T6) -> 0 | W6: =U6-V6 -> 0 | X6: =Y6+Z6 -> 0 | AA6: =X6-V6 -> 0 | AB6: 0 | AE6: =IFERROR(AB6/AD6,0) -> 0 | AF6: =K6-S6-X6 -> 0 | AG6: =S6-AB6 -> 0 | AI6: =IFERROR(AH6/S6,0) -> 0 | AJ6: 0 | AK6: =IF(AJ6>0,AprCoef/SQRT(AJ6),0) -> 0 | AL6: =AJ6*AK6/365 -> 0 | AM6: =AE6 -> 0 | AN6: =AL6-AM6 -> 0 | AO6: =IF(A6>=Hip3LaunchDate,"YES","") | AP6: =IF(A6<Hip4LaunchDate,"pre-launch","live (zero-fee)") -> pre-launch
A7: 45068 | B7: 2.0381289e+08 | C7: 0 | E7: =B7+C7 -> 2.0381289e+08 | F7: =E7+D7 -> 2.0381289e+08 | G7: =IFERROR(C7/E7,0) -> 0 | K7: =H7+I7 -> 0 | O7: =IF(H7=0,0,H7-L7) -> 0 | P7: =IF(B7=0,0,O7/B7*10000) -> 0 | S7: =Q7+R7 -> 0 | T7: =IF(A7<HlpChangeDate,HlpSharePre,HlpSharePost) -> 0.03 | U7: =S7*T7/(1-T7) -> 0 | W7: =U7-V7 -> 0 | X7: =Y7+Z7 -> 0 | AA7: =X7-V7 -> 0 | AB7: 0 | AE7: =IFERROR(AB7/AD7,0) -> 0 | AF7: =K7-S7-X7 -> 0 | AG7: =S7-AB7 -> 0 | AI7: =IFERROR(AH7/S7,0) -> 0 | AJ7: 0 | AK7: =IF(AJ7>0,AprCoef/SQRT(AJ7),0) -> 0 | AL7: =AJ7*AK7/365 -> 0 | AM7: =AE7 -> 0 | AN7: =AL7-AM7 -> 0 | AO7: =IF(A7>=Hip3LaunchDate,"YES","") | AP7: =IF(A7<Hip4LaunchDate,"pre-launch","live (zero-fee)") -> pre-launch
A8: 45069 | B8: 2.3846318e+08 | C8: 0 | E8: =B8+C8 -> 2.3846318e+08 | F8: =E8+D8 -> 2.3846318e+08 | G8: =IFERROR(C8/E8,0) -> 0 | K8: =H8+I8 -> 0 | O8: =IF(H8=0,0,H8-L8) -> 0 | P8: =IF(B8=0,0,O8/B8*10000) -> 0 | S8: =Q8+R8 -> 0 | T8: =IF(A8<HlpChangeDate,HlpSharePre,HlpSharePost) -> 0.03 | U8: =S8*T8/(1-T8) -> 0 | W8: =U8-V8 -> 0 | X8: =Y8+Z8 -> 0 | AA8: =X8-V8 -> 0 | AB8: 0 | AE8: =IFERROR(AB8/AD8,0) -> 0 | AF8: =K8-S8-X8 -> 0 | AG8: =S8-AB8 -> 0 | AI8: =IFERROR(AH8/S8,0) -> 0 | AJ8: 0 | AK8: =IF(AJ8>0,AprCoef/SQRT(AJ8),0) -> 0 | AL8: =AJ8*AK8/365 -> 0 | AM8: =AE8 -> 0 | AN8: =AL8-AM8 -> 0 | AO8: =IF(A8>=Hip3LaunchDate,"YES","") | AP8: =IF(A8<Hip4LaunchDate,"pre-launch","live (zero-fee)") -> pre-launch
A9: 45070 | B9: 4.6949197e+08 | C9: 0 | E9: =B9+C9 -> 4.6949197e+08 | F9: =E9+D9 -> 4.6949197e+08 | G9: =IFERROR(C9/E9,0) -> 0 | K9: =H9+I9 -> 0 | O9: =IF(H9=0,0,H9-L9) -> 0 | P9: =IF(B9=0,0,O9/B9*10000) -> 0 | S9: =Q9+R9 -> 0 | T9: =IF(A9<HlpChangeDate,HlpSharePre,HlpSharePost) -> 0.03 | U9: =S9*T9/(1-T9) -> 0 | W9: =U9-V9 -> 0 | X9: =Y9+Z9 -> 0 | AA9: =X9-V9 -> 0 | AB9: 0 | AE9: =IFERROR(AB9/AD9,0) -> 0 | AF9: =K9-S9-X9 -> 0 | AG9: =S9-AB9 -> 0 | AI9: =IFERROR(AH9/S9,0) -> 0 | AJ9: 0 | AK9: =IF(AJ9>0,AprCoef/SQRT(AJ9),0) -> 0 | AL9: =AJ9*AK9/365 -> 0 | AM9: =AE9 -> 0 | AN9: =AL9-AM9 -> 0 | AO9: =IF(A9>=Hip3LaunchDate,"YES","") | AP9: =IF(A9<Hip4LaunchDate,"pre-launch","live (zero-fee)") -> pre-launch
A10: 45071 | B10: 6.5181124e+08 | C10: 0 | E10: =B10+C10 -> 6.5181124e+08 | F10: =E10+D10 -> 6.5181124e+08 | G10: =IFERROR(C10/E10,0) -> 0 | K10: =H10+I10 -> 0 | O10: =IF(H10=0,0,H10-L10) -> 0 | P10: =IF(B10=0,0,O10/B10*10000) -> 0 | S10: =Q10+R10 -> 0 | T10: =IF(A10<HlpChangeDate,HlpSharePre,HlpSharePost) -> 0.03 | U10: =S10*T10/(1-T10) -> 0 | W10: =U10-V10 -> 0 | X10: =Y10+Z10 -> 0 | AA10: =X10-V10 -> 0 | AB10: 0 | AE10: =IFERROR(AB10/AD10,0) -> 0 | AF10: =K10-S10-X10 -> 0 | AG10: =S10-AB10 -> 0 | AI10: =IFERROR(AH10/S10,0) -> 0 | AJ10: 0 | AK10: =IF(AJ10>0,AprCoef/SQRT(AJ10),0) -> 0 | AL10: =AJ10*AK10/365 -> 0 | AM10: =AE10 -> 0 | AN10: =AL10-AM10 -> 0 | AO10: =IF(A10>=Hip3LaunchDate,"YES","") | AP10: =IF(A10<Hip4LaunchDate,"pre-launch","live (zero-fee)") -> pre-launch
A11: 45072 | B11: 6.3554324e+08 | C11: 0 | E11: =B11+C11 -> 6.3554324e+08 | F11: =E11+D11 -> 6.3554324e+08 | G11: =IFERROR(C11/E11,0) -> 0 | K11: =H11+I11 -> 0 | O11: =IF(H11=0,0,H11-L11) -> 0 | P11: =IF(B11=0,0,O11/B11*10000) -> 0 | S11: =Q11+R11 -> 0 | T11: =IF(A11<HlpChangeDate,HlpSharePre,HlpSharePost) -> 0.03 | U11: =S11*T11/(1-T11) -> 0 | W11: =U11-V11 -> 0 | X11: =Y11+Z11 -> 0 | AA11: =X11-V11 -> 0 | AB11: 0 | AE11: =IFERROR(AB11/AD11,0) -> 0 | AF11: =K11-S11-X11 -> 0 | AG11: =S11-AB11 -> 0 | AI11: =IFERROR(AH11/S11,0) -> 0 | AJ11: 0 | AK11: =IF(AJ11>0,AprCoef/SQRT(AJ11),0) -> 0 | AL11: =AJ11*AK11/365 -> 0 | AM11: =AE11 -> 0 | AN11: =AL11-AM11 -> 0 | AO11: =IF(A11>=Hip3LaunchDate,"YES","") | AP11: =IF(A11<Hip4LaunchDate,"pre-launch","live (zero-fee)") -> pre-launch
A12: 45073 | B12: 6.2926637e+08 | C12: 0 | E12: =B12+C12 -> 6.2926637e+08 | F12: =E12+D12 -> 6.2926637e+08 | G12: =IFERROR(C12/E12,0) -> 0 | K12: =H12+I12 -> 0 | O12: =IF(H12=0,0,H12-L12) -> 0 | P12: =IF(B12=0,0,O12/B12*10000) -> 0 | S12: =Q12+R12 -> 0 | T12: =IF(A12<HlpChangeDate,HlpSharePre,HlpSharePost) -> 0.03 | U12: =S12*T12/(1-T12) -> 0 | W12: =U12-V12 -> 0 | X12: =Y12+Z12 -> 0 | AA12: =X12-V12 -> 0 | AB12: 0 | AE12: =IFERROR(AB12/AD12,0) -> 0 | AF12: =K12-S12-X12 -> 0 | AG12: =S12-AB12 -> 0 | AI12: =IFERROR(AH12/S12,0) -> 0 | AJ12: 0 | AK12: =IF(AJ12>0,AprCoef/SQRT(AJ12),0) -> 0 | AL12: =AJ12*AK12/365 -> 0 | AM12: =AE12 -> 0 | AN12: =AL12-AM12 -> 0 | AO12: =IF(A12>=Hip3LaunchDate,"YES","") | AP12: =IF(A12<Hip4LaunchDate,"pre-launch","live (zero-fee)") -> pre-launch
A13: 45074 | B13: 1.0302869e+09 | C13: 0 | E13: =B13+C13 -> 1.0302869e+09 | F13: =E13+D13 -> 1.0302869e+09 | G13: =IFERROR(C13/E13,0) -> 0 | K13: =H13+I13 -> 0 | O13: =IF(H13=0,0,H13-L13) -> 0 | P13: =IF(B13=0,0,O13/B13*10000) -> 0 | S13: =Q13+R13 -> 0 | T13: =IF(A13<HlpChangeDate,HlpSharePre,HlpSharePost) -> 0.03 | U13: =S13*T13/(1-T13) -> 0 | W13: =U13-V13 -> 0 | X13: =Y13+Z13 -> 0 | AA13: =X13-V13 -> 0 | AB13: 0 | AE13: =IFERROR(AB13/AD13,0) -> 0 | AF13: =K13-S13-X13 -> 0 | AG13: =S13-AB13 -> 0 | AI13: =IFERROR(AH13/S13,0) -> 0 | AJ13: 0 | AK13: =IF(AJ13>0,AprCoef/SQRT(AJ13),0) -> 0 | AL13: =AJ13*AK13/365 -> 0 | AM13: =AE13 -> 0 | AN13: =AL13-AM13 -> 0 | AO13: =IF(A13>=Hip3LaunchDate,"YES","") | AP13: =IF(A13<Hip4LaunchDate,"pre-launch","live (zero-fee)") -> pre-launch
A14: 45075 | B14: 1.6653697e+09 | C14: 0 | E14: =B14+C14 -> 1.6653697e+09 | F14: =E14+D14 -> 1.6653697e+09 | G14: =IFERROR(C14/E14,0) -> 0 | K14: =H14+I14 -> 0 | O14: =IF(H14=0,0,H14-L14) -> 0 | P14: =IF(B14=0,0,O14/B14*10000) -> 0 | S14: =Q14+R14 -> 0 | T14: =IF(A14<HlpChangeDate,HlpSharePre,HlpSharePost) -> 0.03 | U14: =S14*T14/(1-T14) -> 0 | W14: =U14-V14 -> 0 | X14: =Y14+Z14 -> 0 | AA14: =X14-V14 -> 0 | AB14: 0 | AE14: =IFERROR(AB14/AD14,0) -> 0 | AF14: =K14-S14-X14 -> 0 | AG14: =S14-AB14 -> 0 | AI14: =IFERROR(AH14/S14,0) -> 0 | AJ14: 0 | AK14: =IF(AJ14>0,AprCoef/SQRT(AJ14),0) -> 0 | AL14: =AJ14*AK14/365 -> 0 | AM14: =AE14 -> 0 | AN14: =AL14-AM14 -> 0 | AO14: =IF(A14>=Hip3LaunchDate,"YES","") | AP14: =IF(A14<Hip4LaunchDate,"pre-launch","live (zero-fee)") -> pre-launch
A15: 45076 | B15: 7.9048504e+08 | C15: 0 | E15: =B15+C15 -> 7.9048504e+08 | F15: =E15+D15 -> 7.9048504e+08 | G15: =IFERROR(C15/E15,0) -> 0 | K15: =H15+I15 -> 0 | O15: =IF(H15=0,0,H15-L15) -> 0 | P15: =IF(B15=0,0,O15/B15*10000) -> 0 | S15: =Q15+R15 -> 0 | T15: =IF(A15<HlpChangeDate,HlpSharePre,HlpSharePost) -> 0.03 | U15: =S15*T15/(1-T15) -> 0 | W15: =U15-V15 -> 0 | X15: =Y15+Z15 -> 0 | AA15: =X15-V15 -> 0 | AB15: 0 | AE15: =IFERROR(AB15/AD15,0) -> 0 | AF15: =K15-S15-X15 -> 0 | AG15: =S15-AB15 -> 0 | AI15: =IFERROR(AH15/S15,0) -> 0 | AJ15: 0 | AK15: =IF(AJ15>0,AprCoef/SQRT(AJ15),0) -> 0 | AL15: =AJ15*AK15/365 -> 0 | AM15: =AE15 -> 0 | AN15: =AL15-AM15 -> 0 | AO15: =IF(A15>=Hip3LaunchDate,"YES","") | AP15: =IF(A15<Hip4LaunchDate,"pre-launch","live (zero-fee)") -> pre-launch
A16: 45077 | B16: 6.9786168e+08 | C16: 0 | E16: =B16+C16 -> 6.9786168e+08 | F16: =E16+D16 -> 6.9786168e+08 | G16: =IFERROR(C16/E16,0) -> 0 | K16: =H16+I16 -> 0 | O16: =IF(H16=0,0,H16-L16) -> 0 | P16: =IF(B16=0,0,O16/B16*10000) -> 0 | S16: =Q16+R16 -> 0 | T16: =IF(A16<HlpChangeDate,HlpSharePre,HlpSharePost) -> 0.03 | U16: =S16*T16/(1-T16) -> 0 | W16: =U16-V16 -> 0 | X16: =Y16+Z16 -> 0 | AA16: =X16-V16 -> 0 | AB16: 0 | AE16: =IFERROR(AB16/AD16,0) -> 0 | AF16: =K16-S16-X16 -> 0 | AG16: =S16-AB16 -> 0 | AI16: =IFERROR(AH16/S16,0) -> 0 | AJ16: 0 | AK16: =IF(AJ16>0,AprCoef/SQRT(AJ16),0) -> 0 | AL16: =AJ16*AK16/365 -> 0 | AM16: =AE16 -> 0 | AN16: =AL16-AM16 -> 0 | AO16: =IF(A16>=Hip3LaunchDate,"YES","") | AP16: =IF(A16<Hip4LaunchDate,"pre-launch","live (zero-fee)") -> pre-launch
... A492: 45553 | B492: 1.3098399e+09 | C492: 0 | E492: =B492+C492 -> 1.3098399e+09 | F492: =E492+D492 -> 1.3098399e+09 | G492: =IFERROR(C492/E492,0) -> 0 | K492: =H492+I492 -> 0 | O492: =IF(H492=0,0,H492-L492) -> 0 | P492: =IF(B492=0,0,O492/B492*10000) -> 0 | S492: =Q492+R492 -> 0 | T492: =IF(A492<HlpChangeDate,HlpSharePre,HlpSharePost) -> 0.03 | U492: =S492*T492/(1-T492) -> 0 | W492: =U492-V492 -> 0 | X492: =Y492+Z492 -> 0 | AA492: =X492-V492 -> 0 | AB492: 0 | AE492: =IFERROR(AB492/AD492,0) -> 0 | AF492: =K492-S492-X492 -> 0 | AG492: =S492-AB492 -> 0 | AI492: =IFERROR(AH492/S492,0) -> 0 | AJ492: 0 | AK492: =IF(AJ492>0,AprCoef/SQRT(AJ492),0) -> 0 | AL492: =AJ492*AK492/365 -> 0 | AM492: =AE492 -> 0 | AN492: =AL492-AM492 -> 0 | AO492: =IF(A492>=Hip3LaunchDate,"YES","") | AP492: =IF(A492<Hip4LaunchDate,"pre-launch","live (zero-fee)") -> pre-launch
A493: 45554 | B493: 1.7619522e+09 | C493: 0 | D493: 3260099 | E493: =B493+C493 -> 1.7619522e+09 | F493: =E493+D493 -> 1.7652123e+09 | G493: =IFERROR(C493/E493,0) -> 0 | K493: =H493+I493 -> 0 | O493: =IF(H493=0,0,H493-L493) -> 0 | P493: =IF(B493=0,0,O493/B493*10000) -> 0 | S493: =Q493+R493 -> 0 | T493: =IF(A493<HlpChangeDate,HlpSharePre,HlpSharePost) -> 0.03 | U493: =S493*T493/(1-T493) -> 0 | W493: =U493-V493 -> 0 | X493: =Y493+Z493 -> 0 | AA493: =X493-V493 -> 0 | AB493: 0 | AE493: =IFERROR(AB493/AD493,0) -> 0 | AF493: =K493-S493-X493 -> 0 | AG493: =S493-AB493 -> 0 | AI493: =IFERROR(AH493/S493,0) -> 0 | AJ493: 0 | AK493: =IF(AJ493>0,AprCoef/SQRT(AJ493),0) -> 0 | AL493: =AJ493*AK493/365 -> 0 | AM493: =AE493 -> 0 | AN493: =AL493-AM493 -> 0 | AO493: =IF(A493>=Hip3LaunchDate,"YES","") | AP493: =IF(A493<Hip4LaunchDate,"pre-launch","live (zero-fee)") -> pre-launch
A494: 45555 | B494: 1.1603466e+09 | C494: 0 | D494: 4801770 | E494: =B494+C494 -> 1.1603466e+09 | F494: =E494+D494 -> 1.1651484e+09 | G494: =IFERROR(C494/E494,0) -> 0 | K494: =H494+I494 -> 0 | O494: =IF(H494=0,0,H494-L494) -> 0 | P494: =IF(B494=0,0,O494/B494*10000) -> 0 | S494: =Q494+R494 -> 0 | T494: =IF(A494<HlpChangeDate,HlpSharePre,HlpSharePost) -> 0.03 | U494: =S494*T494/(1-T494) -> 0 | W494: =U494-V494 -> 0 | X494: =Y494+Z494 -> 0 | AA494: =X494-V494 -> 0 | AB494: 0 | AE494: =IFERROR(AB494/AD494,0) -> 0 | AF494: =K494-S494-X494 -> 0 | AG494: =S494-AB494 -> 0 | AI494: =IFERROR(AH494/S494,0) -> 0 | AJ494: 0 | AK494: =IF(AJ494>0,AprCoef/SQRT(AJ494),0) -> 0 | AL494: =AJ494*AK494/365 -> 0 | AM494: =AE494 -> 0 | AN494: =AL494-AM494 -> 0 | AO494: =IF(A494>=Hip3LaunchDate,"YES","") | AP494: =IF(A494<Hip4LaunchDate,"pre-launch","live (zero-fee)") -> pre-launch
A495: 45556 | B495: 4.5167684e+08 | C495: 0 | D495: 4983173 | E495: =B495+C495 -> 4.5167684e+08 | F495: =E495+D495 -> 4.5666001e+08 | G495: =IFERROR(C495/E495,0) -> 0 | K495: =H495+I495 -> 0 | O495: =IF(H495=0,0,H495-L495) -> 0 | P495: =IF(B495=0,0,O495/B495*10000) -> 0 | S495: =Q495+R495 -> 0 | T495: =IF(A495<HlpChangeDate,HlpSharePre,HlpSharePost) -> 0.03 | U495: =S495*T495/(1-T495) -> 0 | W495: =U495-V495 -> 0 | X495: =Y495+Z495 -> 0 | AA495: =X495-V495 -> 0 | AB495: 0 | AE495: =IFERROR(AB495/AD495,0) -> 0 | AF495: =K495-S495-X495 -> 0 | AG495: =S495-AB495 -> 0 | AI495: =IFERROR(AH495/S495,0) -> 0 | AJ495: 0 | AK495: =IF(AJ495>0,AprCoef/SQRT(AJ495),0) -> 0 | AL495: =AJ495*AK495/365 -> 0 | AM495: =AE495 -> 0 | AN495: =AL495-AM495 -> 0 | AO495: =IF(A495>=Hip3LaunchDate,"YES","") | AP495: =IF(A495<Hip4LaunchDate,"pre-launch","live (zero-fee)") -> pre-launch
A496: 45557 | B496: 6.6972587e+08 | C496: 0 | D496: 4441106 | E496: =B496+C496 -> 6.6972587e+08 | F496: =E496+D496 -> 6.7416697e+08 | G496: =IFERROR(C496/E496,0) -> 0 | K496: =H496+I496 -> 0 | O496: =IF(H496=0,0,H496-L496) -> 0 | P496: =IF(B496=0,0,O496/B496*10000) -> 0 | S496: =Q496+R496 -> 0 | T496: =IF(A496<HlpChangeDate,HlpSharePre,HlpSharePost) -> 0.03 | U496: =S496*T496/(1-T496) -> 0 | W496: =U496-V496 -> 0 | X496: =Y496+Z496 -> 0 | AA496: =X496-V496 -> 0 | AB496: 0 | AE496: =IFERROR(AB496/AD496,0) -> 0 | AF496: =K496-S496-X496 -> 0 | AG496: =S496-AB496 -> 0 | AI496: =IFERROR(AH496/S496,0) -> 0 | AJ496: 0 | AK496: =IF(AJ496>0,AprCoef/SQRT(AJ496),0) -> 0 | AL496: =AJ496*AK496/365 -> 0 | AM496: =AE496 -> 0 | AN496: =AL496-AM496 -> 0 | AO496: =IF(A496>=Hip3LaunchDate,"YES","") | AP496: =IF(A496<Hip4LaunchDate,"pre-launch","live (zero-fee)") -> pre-launch
A497: 45558 | B497: 1.4264579e+09 | C497: 0 | D497: 9787031 | E497: =B497+C497 -> 1.4264579e+09 | F497: =E497+D497 -> 1.4362449e+09 | G497: =IFERROR(C497/E497,0) -> 0 | K497: =H497+I497 -> 0 | O497: =IF(H497=0,0,H497-L497) -> 0 | P497: =IF(B497=0,0,O497/B497*10000) -> 0 | S497: =Q497+R497 -> 0 | T497: =IF(A497<HlpChangeDate,HlpSharePre,HlpSharePost) -> 0.03 | U497: =S497*T497/(1-T497) -> 0 | W497: =U497-V497 -> 0 | X497: =Y497+Z497 -> 0 | AA497: =X497-V497 -> 0 | AB497: 0 | AE497: =IFERROR(AB497/AD497,0) -> 0 | AF497: =K497-S497-X497 -> 0 | AG497: =S497-AB497 -> 0 | AI497: =IFERROR(AH497/S497,0) -> 0 | AJ497: 0 | AK497: =IF(AJ497>0,AprCoef/SQRT(AJ497),0) -> 0 | AL497: =AJ497*AK497/365 -> 0 | AM497: =AE497 -> 0 | AN497: =AL497-AM497 -> 0 | AO497: =IF(A497>=Hip3LaunchDate,"YES","") | AP497: =IF(A497<Hip4LaunchDate,"pre-launch","live (zero-fee)") -> pre-launch
A498: 45559 | B498: 1.2194153e+09 | C498: 0 | D498: 4003448 | E498: =B498+C498 -> 1.2194153e+09 | F498: =E498+D498 -> 1.2234187e+09 | G498: =IFERROR(C498/E498,0) -> 0 | K498: =H498+I498 -> 0 | O498: =IF(H498=0,0,H498-L498) -> 0 | P498: =IF(B498=0,0,O498/B498*10000) -> 0 | S498: =Q498+R498 -> 0 | T498: =IF(A498<HlpChangeDate,HlpSharePre,HlpSharePost) -> 0.03 | U498: =S498*T498/(1-T498) -> 0 | W498: =U498-V498 -> 0 | X498: =Y498+Z498 -> 0 | AA498: =X498-V498 -> 0 | AB498: 0 | AE498: =IFERROR(AB498/AD498,0) -> 0 | AF498: =K498-S498-X498 -> 0 | AG498: =S498-AB498 -> 0 | AI498: =IFERROR(AH498/S498,0) -> 0 | AJ498: 0 | AK498: =IF(AJ498>0,AprCoef/SQRT(AJ498),0) -> 0 | AL498: =AJ498*AK498/365 -> 0 | AM498: =AE498 -> 0 | AN498: =AL498-AM498 -> 0 | AO498: =IF(A498>=Hip3LaunchDate,"YES","") | AP498: =IF(A498<Hip4LaunchDate,"pre-launch","live (zero-fee)") -> pre-launch
A499: 45560 | B499: 1.206077e+09 | C499: 0 | D499: 4050062 | E499: =B499+C499 -> 1.206077e+09 | F499: =E499+D499 -> 1.2101271e+09 | G499: =IFERROR(C499/E499,0) -> 0 | K499: =H499+I499 -> 0 | O499: =IF(H499=0,0,H499-L499) -> 0 | P499: =IF(B499=0,0,O499/B499*10000) -> 0 | S499: =Q499+R499 -> 0 | T499: =IF(A499<HlpChangeDate,HlpSharePre,HlpSharePost) -> 0.03 | U499: =S499*T499/(1-T499) -> 0 | W499: =U499-V499 -> 0 | X499: =Y499+Z499 -> 0 | AA499: =X499-V499 -> 0 | AB499: 0 | AE499: =IFERROR(AB499/AD499,0) -> 0 | AF499: =K499-S499-X499 -> 0 | AG499: =S499-AB499 -> 0 | AI499: =IFERROR(AH499/S499,0) -> 0 | AJ499: 0 | AK499: =IF(AJ499>0,AprCoef/SQRT(AJ499),0) -> 0 | AL499: =AJ499*AK499/365 -> 0 | AM499: =AE499 -> 0 | AN499: =AL499-AM499 -> 0 | AO499: =IF(A499>=Hip3LaunchDate,"YES","") | AP499: =IF(A499<Hip4LaunchDate,"pre-launch","live (zero-fee)") -> pre-launch
A500: 45561 | B500: 1.6520725e+09 | C500: 0 | D500: 2720909 | E500: =B500+C500 -> 1.6520725e+09 | F500: =E500+D500 -> 1.6547934e+09 | G500: =IFERROR(C500/E500,0) -> 0 | K500: =H500+I500 -> 0 | O500: =IF(H500=0,0,H500-L500) -> 0 | P500: =IF(B500=0,0,O500/B500*10000) -> 0 | S500: =Q500+R500 -> 0 | T500: =IF(A500<HlpChangeDate,HlpSharePre,HlpSharePost) -> 0.03 | U500: =S500*T500/(1-T500) -> 0 | W500: =U500-V500 -> 0 | X500: =Y500+Z500 -> 0 | AA500: =X500-V500 -> 0 | AB500: 0 | AE500: =IFERROR(AB500/AD500,0) -> 0 | AF500: =K500-S500-X500 -> 0 | AG500: =S500-AB500 -> 0 | AI500: =IFERROR(AH500/S500,0) -> 0 | AJ500: 0 | AK500: =IF(AJ500>0,AprCoef/SQRT(AJ500),0) -> 0 | AL500: =AJ500*AK500/365 -> 0 | AM500: =AE500 -> 0 | AN500: =AL500-AM500 -> 0 | AO500: =IF(A500>=Hip3LaunchDate,"YES","") | AP500: =IF(A500<Hip4LaunchDate,"pre-launch","live (zero-fee)") -> pre-launch
A501: 45562 | B501: 1.3608713e+09 | C501: 0 | D501: 3014452 | E501: =B501+C501 -> 1.3608713e+09 | F501: =E501+D501 -> 1.3638857e+09 | G501: =IFERROR(C501/E501,0) -> 0 | K501: =H501+I501 -> 0 | O501: =IF(H501=0,0,H501-L501) -> 0 | P501: =IF(B501=0,0,O501/B501*10000) -> 0 | S501: =Q501+R501 -> 0 | T501: =IF(A501<HlpChangeDate,HlpSharePre,HlpSharePost) -> 0.03 | U501: =S501*T501/(1-T501) -> 0 | W501: =U501-V501 -> 0 | X501: =Y501+Z501 -> 0 | AA501: =X501-V501 -> 0 | AB501: 0 | AE501: =IFERROR(AB501/AD501,0) -> 0 | AF501: =K501-S501-X501 -> 0 | AG501: =S501-AB501 -> 0 | AI501: =IFERROR(AH501/S501,0) -> 0 | AJ501: 0 | AK501: =IF(AJ501>0,AprCoef/SQRT(AJ501),0) -> 0 | AL501: =AJ501*AK501/365 -> 0 | AM501: =AE501 -> 0 | AN501: =AL501-AM501 -> 0 | AO501: =IF(A501>=Hip3LaunchDate,"YES","") | AP501: =IF(A501<Hip4LaunchDate,"pre-launch","live (zero-fee)") -> pre-launch
A502: 45563 | B502: 6.2587922e+08 | C502: 0 | D502: 2447124 | E502: =B502+C502 -> 6.2587922e+08 | F502: =E502+D502 -> 6.2832635e+08 | G502: =IFERROR(C502/E502,0) -> 0 | K502: =H502+I502 -> 0 | O502: =IF(H502=0,0,H502-L502) -> 0 | P502: =IF(B502=0,0,O502/B502*10000) -> 0 | S502: =Q502+R502 -> 0 | T502: =IF(A502<HlpChangeDate,HlpSharePre,HlpSharePost) -> 0.03 | U502: =S502*T502/(1-T502) -> 0 | W502: =U502-V502 -> 0 | X502: =Y502+Z502 -> 0 | AA502: =X502-V502 -> 0 | AB502: 0 | AE502: =IFERROR(AB502/AD502,0) -> 0 | AF502: =K502-S502-X502 -> 0 | AG502: =S502-AB502 -> 0 | AI502: =IFERROR(AH502/S502,0) -> 0 | AJ502: 0 | AK502: =IF(AJ502>0,AprCoef/SQRT(AJ502),0) -> 0 | AL502: =AJ502*AK502/365 -> 0 | AM502: =AE502 -> 0 | AN502: =AL502-AM502 -> 0 | AO502: =IF(A502>=Hip3LaunchDate,"YES","") | AP502: =IF(A502<Hip4LaunchDate,"pre-launch","live (zero-fee)") -> pre-launch
A503: 45564 | B503: 5.6653266e+08 | C503: 0 | D503: 1971820 | E503: =B503+C503 -> 5.6653266e+08 | F503: =E503+D503 -> 5.6850448e+08 | G503: =IFERROR(C503/E503,0) -> 0 | K503: =H503+I503 -> 0 | O503: =IF(H503=0,0,H503-L503) -> 0 | P503: =IF(B503=0,0,O503/B503*10000) -> 0 | S503: =Q503+R503 -> 0 | T503: =IF(A503<HlpChangeDate,HlpSharePre,HlpSharePost) -> 0.03 | U503: =S503*T503/(1-T503) -> 0 | W503: =U503-V503 -> 0 | X503: =Y503+Z503 -> 0 | AA503: =X503-V503 -> 0 | AB503: 0 | AE503: =IFERROR(AB503/AD503,0) -> 0 | AF503: =K503-S503-X503 -> 0 | AG503: =S503-AB503 -> 0 | AI503: =IFERROR(AH503/S503,0) -> 0 | AJ503: 0 | AK503: =IF(AJ503>0,AprCoef/SQRT(AJ503),0) -> 0 | AL503: =AJ503*AK503/365 -> 0 | AM503: =AE503 -> 0 | AN503: =AL503-AM503 -> 0 | AO503: =IF(A503>=Hip3LaunchDate,"YES","") | AP503: =IF(A503<Hip4LaunchDate,"pre-launch","live (zero-fee)") -> pre-launch
A504: 45565 | B504: 1.4412132e+09 | C504: 0 | D504: 2992524 | E504: =B504+C504 -> 1.4412132e+09 | F504: =E504+D504 -> 1.4442057e+09 | G504: =IFERROR(C504/E504,0) -> 0 | K504: =H504+I504 -> 0 | O504: =IF(H504=0,0,H504-L504) -> 0 | P504: =IF(B504=0,0,O504/B504*10000) -> 0 | S504: =Q504+R504 -> 0 | T504: =IF(A504<HlpChangeDate,HlpSharePre,HlpSharePost) -> 0.03 | U504: =S504*T504/(1-T504) -> 0 | W504: =U504-V504 -> 0 | X504: =Y504+Z504 -> 0 | AA504: =X504-V504 -> 0 | AB504: 0 | AE504: =IFERROR(AB504/AD504,0) -> 0 | AF504: =K504-S504-X504 -> 0 | AG504: =S504-AB504 -> 0 | AI504: =IFERROR(AH504/S504,0) -> 0 | AJ504: 0 | AK504: =IF(AJ504>0,AprCoef/SQRT(AJ504),0) -> 0 | AL504: =AJ504*AK504/365 -> 0 | AM504: =AE504 -> 0 | AN504: =AL504-AM504 -> 0 | AO504: =IF(A504>=Hip3LaunchDate,"YES","") | AP504: =IF(A504<Hip4LaunchDate,"pre-launch","live (zero-fee)") -> pre-launch
... A559: 45620 | B559: 2.2105278e+09 | C559: 0 | D559: 2473310 | E559: =B559+C559 -> 2.2105278e+09 | F559: =E559+D559 -> 2.2130012e+09 | G559: =IFERROR(C559/E559,0) -> 0 | K559: =H559+I559 -> 0 | O559: =IF(H559=0,0,H559-L559) -> 0 | P559: =IF(B559=0,0,O559/B559*10000) -> 0 | S559: =Q559+R559 -> 0 | T559: =IF(A559<HlpChangeDate,HlpSharePre,HlpSharePost) -> 0.03 | U559: =S559*T559/(1-T559) -> 0 | W559: =U559-V559 -> 0 | X559: =Y559+Z559 -> 0 | AA559: =X559-V559 -> 0 | AB559: 0 | AE559: =IFERROR(AB559/AD559,0) -> 0 | AF559: =K559-S559-X559 -> 0 | AG559: =S559-AB559 -> 0 | AI559: =IFERROR(AH559/S559,0) -> 0 | AJ559: 0 | AK559: =IF(AJ559>0,AprCoef/SQRT(AJ559),0) -> 0 | AL559: =AJ559*AK559/365 -> 0 | AM559: =AE559 -> 0 | AN559: =AL559-AM559 -> 0 | AO559: =IF(A559>=Hip3LaunchDate,"YES","") | AP559: =IF(A559<Hip4LaunchDate,"pre-launch","live (zero-fee)") -> pre-launch
A560: 45621 | B560: 3.2691508e+09 | C560: 0 | D560: 5628946 | E560: =B560+C560 -> 3.2691508e+09 | F560: =E560+D560 -> 3.2747798e+09 | G560: =IFERROR(C560/E560,0) -> 0 | K560: =H560+I560 -> 0 | O560: =IF(H560=0,0,H560-L560) -> 0 | P560: =IF(B560=0,0,O560/B560*10000) -> 0 | S560: =Q560+R560 -> 0 | T560: =IF(A560<HlpChangeDate,HlpSharePre,HlpSharePost) -> 0.03 | U560: =S560*T560/(1-T560) -> 0 | W560: =U560-V560 -> 0 | X560: =Y560+Z560 -> 0 | AA560: =X560-V560 -> 0 | AB560: 0 | AE560: =IFERROR(AB560/AD560,0) -> 0 | AF560: =K560-S560-X560 -> 0 | AG560: =S560-AB560 -> 0 | AH560: 4585090.2 | AI560: =IFERROR(AH560/S560,0) -> 0 | AJ560: 0 | AK560: =IF(AJ560>0,AprCoef/SQRT(AJ560),0) -> 0 | AL560: =AJ560*AK560/365 -> 0 | AM560: =AE560 -> 0 | AN560: =AL560-AM560 -> 0 | AO560: =IF(A560>=Hip3LaunchDate,"YES","") | AP560: =IF(A560<Hip4LaunchDate,"pre-launch","live (zero-fee)") -> pre-launch
A561: 45622 | B561: 3.3938162e+09 | C561: 0 | D561: 7041832 | E561: =B561+C561 -> 3.3938162e+09 | F561: =E561+D561 -> 3.4008581e+09 | G561: =IFERROR(C561/E561,0) -> 0 | K561: =H561+I561 -> 0 | O561: =IF(H561=0,0,H561-L561) -> 0 | P561: =IF(B561=0,0,O561/B561*10000) -> 0 | S561: =Q561+R561 -> 0 | T561: =IF(A561<HlpChangeDate,HlpSharePre,HlpSharePost) -> 0.03 | U561: =S561*T561/(1-T561) -> 0 | W561: =U561-V561 -> 0 | X561: =Y561+Z561 -> 0 | AA561: =X561-V561 -> 0 | AB561: 0 | AE561: =IFERROR(AB561/AD561,0) -> 0 | AF561: =K561-S561-X561 -> 0 | AG561: =S561-AB561 -> 0 | AI561: =IFERROR(AH561/S561,0) -> 0 | AJ561: 0 | AK561: =IF(AJ561>0,AprCoef/SQRT(AJ561),0) -> 0 | AL561: =AJ561*AK561/365 -> 0 | AM561: =AE561 -> 0 | AN561: =AL561-AM561 -> 0 | AO561: =IF(A561>=Hip3LaunchDate,"YES","") | AP561: =IF(A561<Hip4LaunchDate,"pre-launch","live (zero-fee)") -> pre-launch
A562: 45623 | B562: 2.2108559e+09 | C562: 0 | D562: 4131241 | E562: =B562+C562 -> 2.2108559e+09 | F562: =E562+D562 -> 2.2149872e+09 | G562: =IFERROR(C562/E562,0) -> 0 | K562: =H562+I562 -> 0 | O562: =IF(H562=0,0,H562-L562) -> 0 | P562: =IF(B562=0,0,O562/B562*10000) -> 0 | S562: =Q562+R562 -> 0 | T562: =IF(A562<HlpChangeDate,HlpSharePre,HlpSharePost) -> 0.03 | U562: =S562*T562/(1-T562) -> 0 | W562: =U562-V562 -> 0 | X562: =Y562+Z562 -> 0 | AA562: =X562-V562 -> 0 | AB562: 0 | AE562: =IFERROR(AB562/AD562,0) -> 0 | AF562: =K562-S562-X562 -> 0 | AG562: =S562-AB562 -> 0 | AI562: =IFERROR(AH562/S562,0) -> 0 | AJ562: 0 | AK562: =IF(AJ562>0,AprCoef/SQRT(AJ562),0) -> 0 | AL562: =AJ562*AK562/365 -> 0 | AM562: =AE562 -> 0 | AN562: =AL562-AM562 -> 0 | AO562: =IF(A562>=Hip3LaunchDate,"YES","") | AP562: =IF(A562<Hip4LaunchDate,"pre-launch","live (zero-fee)") -> pre-launch
A563: 45624 | B563: 1.7653393e+09 | C563: 0 | D563: 19036485 | E563: =B563+C563 -> 1.7653393e+09 | F563: =E563+D563 -> 1.7843758e+09 | G563: =IFERROR(C563/E563,0) -> 0 | K563: =H563+I563 -> 0 | O563: =IF(H563=0,0,H563-L563) -> 0 | P563: =IF(B563=0,0,O563/B563*10000) -> 0 | S563: =Q563+R563 -> 0 | T563: =IF(A563<HlpChangeDate,HlpSharePre,HlpSharePost) -> 0.03 | U563: =S563*T563/(1-T563) -> 0 | W563: =U563-V563 -> 0 | X563: =Y563+Z563 -> 0 | AA563: =X563-V563 -> 0 | AB563: 0 | AE563: =IFERROR(AB563/AD563,0) -> 0 | AF563: =K563-S563-X563 -> 0 | AG563: =S563-AB563 -> 0 | AI563: =IFERROR(AH563/S563,0) -> 0 | AJ563: 0 | AK563: =IF(AJ563>0,AprCoef/SQRT(AJ563),0) -> 0 | AL563: =AJ563*AK563/365 -> 0 | AM563: =AE563 -> 0 | AN563: =AL563-AM563 -> 0 | AO563: =IF(A563>=Hip3LaunchDate,"YES","") | AP563: =IF(A563<Hip4LaunchDate,"pre-launch","live (zero-fee)") -> pre-launch
A564: 45625 | B564: 1.8146872e+09 | C564: 0 | D564: 951196324 | E564: =B564+C564 -> 1.8146872e+09 | F564: =E564+D564 -> 2.7658836e+09 | G564: =IFERROR(C564/E564,0) -> 0 | K564: =H564+I564 -> 0 | O564: =IF(H564=0,0,H564-L564) -> 0 | P564: =IF(B564=0,0,O564/B564*10000) -> 0 | S564: =Q564+R564 -> 0 | T564: =IF(A564<HlpChangeDate,HlpSharePre,HlpSharePost) -> 0.03 | U564: =S564*T564/(1-T564) -> 0 | W564: =U564-V564 -> 0 | X564: =Y564+Z564 -> 0 | AA564: =X564-V564 -> 0 | AB564: 0 | AC564: 6.252 | AD564: 4.2155 | AE564: =IFERROR(AB564/AD564,0) -> 0 | AF564: =K564-S564-X564 -> 0 | AG564: =S564-AB564 -> 0 | AH564: 2497425.1 | AI564: =IFERROR(AH564/S564,0) -> 0 | AJ564: 0 | AK564: =IF(AJ564>0,AprCoef/SQRT(AJ564),0) -> 0 | AL564: =AJ564*AK564/365 -> 0 | AM564: =AE564 -> 0 | AN564: =AL564-AM564 -> 0 | AO564: =IF(A564>=Hip3LaunchDate,"YES","") | AP564: =IF(A564<Hip4LaunchDate,"pre-launch","live (zero-fee)") -> pre-launch
A565: 45626 | B565: 1.9278396e+09 | C565: 0 | D565: 460835741 | E565: =B565+C565 -> 1.9278396e+09 | F565: =E565+D565 -> 2.3886754e+09 | G565: =IFERROR(C565/E565,0) -> 0 | K565: =H565+I565 -> 0 | O565: =IF(H565=0,0,H565-L565) -> 0 | P565: =IF(B565=0,0,O565/B565*10000) -> 0 | S565: =Q565+R565 -> 0 | T565: =IF(A565<HlpChangeDate,HlpSharePre,HlpSharePost) -> 0.03 | U565: =S565*T565/(1-T565) -> 0 | W565: =U565-V565 -> 0 | X565: =Y565+Z565 -> 0 | AA565: =X565-V565 -> 0 | AB565: 0 | AC565: 8.4985 | AD565: 7.454675 | AE565: =IFERROR(AB565/AD565,0) -> 0 | AF565: =K565-S565-X565 -> 0 | AG565: =S565-AB565 -> 0 | AI565: =IFERROR(AH565/S565,0) -> 0 | AJ565: 0 | AK565: =IF(AJ565>0,AprCoef/SQRT(AJ565),0) -> 0 | AL565: =AJ565*AK565/365 -> 0 | AM565: =AE565 -> 0 | AN565: =AL565-AM565 -> 0 | AO565: =IF(A565>=Hip3LaunchDate,"YES","") | AP565: =IF(A565<Hip4LaunchDate,"pre-launch","live (zero-fee)") -> pre-launch
A566: 45627 | B566: 2.2309523e+09 | C566: 0 | D566: 382137710 | E566: =B566+C566 -> 2.2309523e+09 | F566: =E566+D566 -> 2.61309e+09 | G566: =IFERROR(C566/E566,0) -> 0 | K566: =H566+I566 -> 0 | O566: =IF(H566=0,0,H566-L566) -> 0 | P566: =IF(B566=0,0,O566/B566*10000) -> 0 | S566: =Q566+R566 -> 0 | T566: =IF(A566<HlpChangeDate,HlpSharePre,HlpSharePost) -> 0.03 | U566: =S566*T566/(1-T566) -> 0 | W566: =U566-V566 -> 0 | X566: =Y566+Z566 -> 0 | AA566: =X566-V566 -> 0 | AB566: 0 | AC566: 9.4686 | AD566: 8.98335 | AE566: =IFERROR(AB566/AD566,0) -> 0 | AF566: =K566-S566-X566 -> 0 | AG566: =S566-AB566 -> 0 | AI566: =IFERROR(AH566/S566,0) -> 0 | AJ566: 0 | AK566: =IF(AJ566>0,AprCoef/SQRT(AJ566),0) -> 0 | AL566: =AJ566*AK566/365 -> 0 | AM566: =AE566 -> 0 | AN566: =AL566-AM566 -> 0 | AO566: =IF(A566>=Hip3LaunchDate,"YES","") | AP566: =IF(A566<Hip4LaunchDate,"pre-launch","live (zero-fee)") -> pre-launch
A567: 45628 | B567: 5.3331258e+09 | C567: 0 | D567: 320571512 | E567: =B567+C567 -> 5.3331258e+09 | F567: =E567+D567 -> 5.6536974e+09 | G567: =IFERROR(C567/E567,0) -> 0 | K567: =H567+I567 -> 0 | O567: =IF(H567=0,0,H567-L567) -> 0 | P567: =IF(B567=0,0,O567/B567*10000) -> 0 | S567: =Q567+R567 -> 0 | T567: =IF(A567<HlpChangeDate,HlpSharePre,HlpSharePost) -> 0.03 | U567: =S567*T567/(1-T567) -> 0 | W567: =U567-V567 -> 0 | X567: =Y567+Z567 -> 0 | AA567: =X567-V567 -> 0 | AB567: 0 | AC567: 8.4277 | AD567: 8.68185 | AE567: =IFERROR(AB567/AD567,0) -> 0 | AF567: =K567-S567-X567 -> 0 | AG567: =S567-AB567 -> 0 | AH567: 2313969.7 | AI567: =IFERROR(AH567/S567,0) -> 0 | AJ567: 0 | AK567: =IF(AJ567>0,AprCoef/SQRT(AJ567),0) -> 0 | AL567: =AJ567*AK567/365 -> 0 | AM567: =AE567 -> 0 | AN567: =AL567-AM567 -> 0 | AO567: =IF(A567>=Hip3LaunchDate,"YES","") | AP567: =IF(A567<Hip4LaunchDate,"pre-launch","live (zero-fee)") -> pre-launch
A568: 45629 | B568: 4.8819819e+09 | C568: 0 | D568: 302890343 | E568: =B568+C568 -> 4.8819819e+09 | F568: =E568+D568 -> 5.1848722e+09 | G568: =IFERROR(C568/E568,0) -> 0 | K568: =H568+I568 -> 0 | O568: =IF(H568=0,0,H568-L568) -> 0 | P568: =IF(B568=0,0,O568/B568*10000) -> 0 | S568: =Q568+R568 -> 0 | T568: =IF(A568<HlpChangeDate,HlpSharePre,HlpSharePost) -> 0.03 | U568: =S568*T568/(1-T568) -> 0 | W568: =U568-V568 -> 0 | X568: =Y568+Z568 -> 0 | AA568: =X568-V568 -> 0 | AB568: 0 | AC568: 11.082 | AD568: 9.76005 | AE568: =IFERROR(AB568/AD568,0) -> 0 | AF568: =K568-S568-X568 -> 0 | AG568: =S568-AB568 -> 0 | AI568: =IFERROR(AH568/S568,0) -> 0 | AJ568: 0 | AK568: =IF(AJ568>0,AprCoef/SQRT(AJ568),0) -> 0 | AL568: =AJ568*AK568/365 -> 0 | AM568: =AE568 -> 0 | AN568: =AL568-AM568 -> 0 | AO568: =IF(A568>=Hip3LaunchDate,"YES","") | AP568: =IF(A568<Hip4LaunchDate,"pre-launch","live (zero-fee)") -> pre-launch
A569: 45630 | B569: 6.2259185e+09 | C569: 0 | D569: 318696984 | E569: =B569+C569 -> 6.2259185e+09 | F569: =E569+D569 -> 6.5446155e+09 | G569: =IFERROR(C569/E569,0) -> 0 | K569: =H569+I569 -> 0 | O569: =IF(H569=0,0,H569-L569) -> 0 | P569: =IF(B569=0,0,O569/B569*10000) -> 0 | S569: =Q569+R569 -> 0 | T569: =IF(A569<HlpChangeDate,HlpSharePre,HlpSharePost) -> 0.03 | U569: =S569*T569/(1-T569) -> 0 | W569: =U569-V569 -> 0 | X569: =Y569+Z569 -> 0 | AA569: =X569-V569 -> 0 | AB569: 0 | AC569: 11.403 | AD569: 11.6015 | AE569: =IFERROR(AB569/AD569,0) -> 0 | AF569: =K569-S569-X569 -> 0 | AG569: =S569-AB569 -> 0 | AI569: =IFERROR(AH569/S569,0) -> 0 | AJ569: 0 | AK569: =IF(AJ569>0,AprCoef/SQRT(AJ569),0) -> 0 | AL569: =AJ569*AK569/365 -> 0 | AM569: =AE569 -> 0 | AN569: =AL569-AM569 -> 0 | AO569: =IF(A569>=Hip3LaunchDate,"YES","") | AP569: =IF(A569<Hip4LaunchDate,"pre-launch","live (zero-fee)") -> pre-launch
A570: 45631 | B570: 9.7895628e+09 | C570: 0 | D570: 323114172 | E570: =B570+C570 -> 9.7895628e+09 | F570: =E570+D570 -> 1.0112677e+10 | G570: =IFERROR(C570/E570,0) -> 0 | K570: =H570+I570 -> 0 | O570: =IF(H570=0,0,H570-L570) -> 0 | P570: =IF(B570=0,0,O570/B570*10000) -> 0 | S570: =Q570+R570 -> 0 | T570: =IF(A570<HlpChangeDate,HlpSharePre,HlpSharePost) -> 0.03 | U570: =S570*T570/(1-T570) -> 0 | W570: =U570-V570 -> 0 | X570: =Y570+Z570 -> 0 | AA570: =X570-V570 -> 0 | AB570: 0 | AC570: 12.71 | AD570: 12.115 | AE570: =IFERROR(AB570/AD570,0) -> 0 | AF570: =K570-S570-X570 -> 0 | AG570: =S570-AB570 -> 0 | AI570: =IFERROR(AH570/S570,0) -> 0 | AJ570: 0 | AK570: =IF(AJ570>0,AprCoef/SQRT(AJ570),0) -> 0 | AL570: =AJ570*AK570/365 -> 0 | AM570: =AE570 -> 0 | AN570: =AL570-AM570 -> 0 | AO570: =IF(A570>=Hip3LaunchDate,"YES","") | AP570: =IF(A570<Hip4LaunchDate,"pre-launch","live (zero-fee)") -> pre-launch
A571: 45632 | B571: 7.8114744e+09 | C571: 0 | D571: 218646771 | E571: =B571+C571 -> 7.8114744e+09 | F571: =E571+D571 -> 8.0301212e+09 | G571: =IFERROR(C571/E571,0) -> 0 | K571: =H571+I571 -> 0 | O571: =IF(H571=0,0,H571-L571) -> 0 | P571: =IF(B571=0,0,O571/B571*10000) -> 0 | S571: =Q571+R571 -> 0 | T571: =IF(A571<HlpChangeDate,HlpSharePre,HlpSharePost) -> 0.03 | U571: =S571*T571/(1-T571) -> 0 | W571: =U571-V571 -> 0 | X571: =Y571+Z571 -> 0 | AA571: =X571-V571 -> 0 | AB571: 0 | AC571: 13.829 | AD571: 13.2985 | AE571: =IFERROR(AB571/AD571,0) -> 0 | AF571: =K571-S571-X571 -> 0 | AG571: =S571-AB571 -> 0 | AI571: =IFERROR(AH571/S571,0) -> 0 | AJ571: 0 | AK571: =IF(AJ571>0,AprCoef/SQRT(AJ571),0) -> 0 | AL571: =AJ571*AK571/365 -> 0 | AM571: =AE571 -> 0 | AN571: =AL571-AM571 -> 0 | AO571: =IF(A571>=Hip3LaunchDate,"YES","") | AP571: =IF(A571<Hip4LaunchDate,"pre-launch","live (zero-fee)") -> pre-launch
A572: 45633 | B572: 2.8624379e+09 | C572: 0 | D572: 182104753 | E572: =B572+C572 -> 2.8624379e+09 | F572: =E572+D572 -> 3.0445427e+09 | G572: =IFERROR(C572/E572,0) -> 0 | K572: =H572+I572 -> 0 | O572: =IF(H572=0,0,H572-L572) -> 0 | P572: =IF(B572=0,0,O572/B572*10000) -> 0 | S572: =Q572+R572 -> 0 | T572: =IF(A572<HlpChangeDate,HlpSharePre,HlpSharePost) -> 0.03 | U572: =S572*T572/(1-T572) -> 0 | W572: =U572-V572 -> 0 | X572: =Y572+Z572 -> 0 | AA572: =X572-V572 -> 0 | AB572: 0 | AC572: 14.117 | AD572: 14.1115 | AE572: =IFERROR(AB572/AD572,0) -> 0 | AF572: =K572-S572-X572 -> 0 | AG572: =S572-AB572 -> 0 | AI572: =IFERROR(AH572/S572,0) -> 0 | AJ572: 0 | AK572: =IF(AJ572>0,AprCoef/SQRT(AJ572),0) -> 0 | AL572: =AJ572*AK572/365 -> 0 | AM572: =AE572 -> 0 | AN572: =AL572-AM572 -> 0 | AO572: =IF(A572>=Hip3LaunchDate,"YES","") | AP572: =IF(A572<Hip4LaunchDate,"pre-launch","live (zero-fee)") -> pre-launch
A573: 45634 | B573: 3.2527988e+09 | C573: 0 | D573: 136064768 | E573: =B573+C573 -> 3.2527988e+09 | F573: =E573+D573 -> 3.3888636e+09 | G573: =IFERROR(C573/E573,0) -> 0 | K573: =H573+I573 -> 0 | O573: =IF(H573=0,0,H573-L573) -> 0 | P573: =IF(B573=0,0,O573/B573*10000) -> 0 | S573: =Q573+R573 -> 0 | T573: =IF(A573<HlpChangeDate,HlpSharePre,HlpSharePost) -> 0.03 | U573: =S573*T573/(1-T573) -> 0 | W573: =U573-V573 -> 0 | X573: =Y573+Z573 -> 0 | AA573: =X573-V573 -> 0 | AB573: 0 | AC573: 14.02 | AD573: 14.07775 | AE573: =IFERROR(AB573/AD573,0) -> 0 | AF573: =K573-S573-X573 -> 0 | AG573: =S573-AB573 -> 0 | AI573: =IFERROR(AH573/S573,0) -> 0 | AJ573: 0 | AK573: =IF(AJ573>0,AprCoef/SQRT(AJ573),0) -> 0 | AL573: =AJ573*AK573/365 -> 0 | AM573: =AE573 -> 0 | AN573: =AL573-AM573 -> 0 | AO573: =IF(A573>=Hip3LaunchDate,"YES","") | AP573: =IF(A573<Hip4LaunchDate,"pre-launch","live (zero-fee)") -> pre-launch
A574: 45635 | B574: 5.3063589e+09 | C574: 0 | D574: 270676721 | E574: =B574+C574 -> 5.3063589e+09 | F574: =E574+D574 -> 5.5770357e+09 | G574: =IFERROR(C574/E574,0) -> 0 | K574: =H574+I574 -> 0 | O574: =IF(H574=0,0,H574-L574) -> 0 | P574: =IF(B574=0,0,O574/B574*10000) -> 0 | S574: =Q574+R574 -> 0 | T574: =IF(A574<HlpChangeDate,HlpSharePre,HlpSharePost) -> 0.03 | U574: =S574*T574/(1-T574) -> 0 | W574: =U574-V574 -> 0 | X574: =Y574+Z574 -> 0 | AA574: =X574-V574 -> 0 | AB574: 0 | AC574: 13.541 | AD574: 13.4875 | AE574: =IFERROR(AB574/AD574,0) -> 0 | AF574: =K574-S574-X574 -> 0 | AG574: =S574-AB574 -> 0 | AI574: =IFERROR(AH574/S574,0) -> 0 | AJ574: 0 | AK574: =IF(AJ574>0,AprCoef/SQRT(AJ574),0) -> 0 | AL574: =AJ574*AK574/365 -> 0 | AM574: =AE574 -> 0 | AN574: =AL574-AM574 -> 0 | AO574: =IF(A574>=Hip3LaunchDate,"YES","") | AP574: =IF(A574<Hip4LaunchDate,"pre-launch","live (zero-fee)") -> pre-launch
A575: 45636 | B575: 1.0009954e+10 | C575: 0 | D575: 208129108 | E575: =B575+C575 -> 1.0009954e+10 | F575: =E575+D575 -> 1.0218083e+10 | G575: =IFERROR(C575/E575,0) -> 0 | K575: =H575+I575 -> 0 | O575: =IF(H575=0,0,H575-L575) -> 0 | P575: =IF(B575=0,0,O575/B575*10000) -> 0 | S575: =Q575+R575 -> 0 | T575: =IF(A575<HlpChangeDate,HlpSharePre,HlpSharePost) -> 0.03 | U575: =S575*T575/(1-T575) -> 0 | W575: =U575-V575 -> 0 | X575: =Y575+Z575 -> 0 | AA575: =X575-V575 -> 0 | AB575: 0 | AC575: 13.562 | AD575: 13.54725 | AE575: =IFERROR(AB575/AD575,0) -> 0 | AF575: =K575-S575-X575 -> 0 | AG575: =S575-AB575 -> 0 | AI575: =IFERROR(AH575/S575,0) -> 0 | AJ575: 0 | AK575: =IF(AJ575>0,AprCoef/SQRT(AJ575),0) -> 0 | AL575: =AJ575*AK575/365 -> 0 | AM575: =AE575 -> 0 | AN575: =AL575-AM575 -> 0 | AO575: =IF(A575>=Hip3LaunchDate,"YES","") | AP575: =IF(A575<Hip4LaunchDate,"pre-launch","live (zero-fee)") -> pre-launch
A576: 45637 | B576: 3.9793992e+09 | C576: 0 | D576: 211797447 | E576: =B576+C576 -> 3.9793992e+09 | F576: =E576+D576 -> 4.1911967e+09 | G576: =IFERROR(C576/E576,0) -> 0 | K576: =H576+I576 -> 0 | O576: =IF(H576=0,0,H576-L576) -> 0 | P576: =IF(B576=0,0,O576/B576*10000) -> 0 | S576: =Q576+R576 -> 0 | T576: =IF(A576<HlpChangeDate,HlpSharePre,HlpSharePost) -> 0.03 | U576: =S576*T576/(1-T576) -> 0 | W576: =U576-V576 -> 0 | X576: =Y576+Z576 -> 0 | AA576: =X576-V576 -> 0 | AB576: 0 | AC576: 16.115 | AD576: 14.80575 | AE576: =IFERROR(AB576/AD576,0) -> 0 | AF576: =K576-S576-X576 -> 0 | AG576: =S576-AB576 -> 0 | AI576: =IFERROR(AH576/S576,0) -> 0 | AJ576: 0 | AK576: =IF(AJ576>0,AprCoef/SQRT(AJ576),0) -> 0 | AL576: =AJ576*AK576/365 -> 0 | AM576: =AE576 -> 0 | AN576: =AL576-AM576 -> 0 | AO576: =IF(A576>=Hip3LaunchDate,"YES","") | AP576: =IF(A576<Hip4LaunchDate,"pre-launch","live (zero-fee)") -> pre-launch
A577: 45638 | B577: 4.8390459e+09 | C577: 0 | D577: 324908474 | E577: =B577+C577 -> 4.8390459e+09 | F577: =E577+D577 -> 5.1639544e+09 | G577: =IFERROR(C577/E577,0) -> 0 | K577: =H577+I577 -> 0 | O577: =IF(H577=0,0,H577-L577) -> 0 | P577: =IF(B577=0,0,O577/B577*10000) -> 0 | S577: =Q577+R577 -> 0 | T577: =IF(A577<HlpChangeDate,HlpSharePre,HlpSharePost) -> 0.03 | U577: =S577*T577/(1-T577) -> 0 | W577: =U577-V577 -> 0 | X577: =Y577+Z577 -> 0 | AA577: =X577-V577 -> 0 | AB577: 0 | AC577: 18.041 | AD577: 17.1275 | AE577: =IFERROR(AB577/AD577,0) -> 0 | AF577: =K577-S577-X577 -> 0 | AG577: =S577-AB577 -> 0 | AI577: =IFERROR(AH577/S577,0) -> 0 | AJ577: 0 | AK577: =IF(AJ577>0,AprCoef/SQRT(AJ577),0) -> 0 | AL577: =AJ577*AK577/365 -> 0 | AM577: =AE577 -> 0 | AN577: =AL577-AM577 -> 0 | AO577: =IF(A577>=Hip3LaunchDate,"YES","") | AP577: =IF(A577<Hip4LaunchDate,"pre-launch","live (zero-fee)") -> pre-launch
A578: 45639 | B578: 4.2533193e+09 | C578: 0 | D578: 334237923 | E578: =B578+C578 -> 4.2533193e+09 | F578: =E578+D578 -> 4.5875573e+09 | G578: =IFERROR(C578/E578,0) -> 0 | K578: =H578+I578 -> 0 | O578: =IF(H578=0,0,H578-L578) -> 0 | P578: =IF(B578=0,0,O578/B578*10000) -> 0 | S578: =Q578+R578 -> 0 | T578: =IF(A578<HlpChangeDate,HlpSharePre,HlpSharePost) -> 0.03 | U578: =S578*T578/(1-T578) -> 0 | W578: =U578-V578 -> 0 | X578: =Y578+Z578 -> 0 | AA578: =X578-V578 -> 0 | AB578: 0 | AC578: 19.48 | AD578: 18.50825 | AE578: =IFERROR(AB578/AD578,0) -> 0 | AF578: =K578-S578-X578 -> 0 | AG578: =S578-AB578 -> 0 | AI578: =IFERROR(AH578/S578,0) -> 0 | AJ578: 0 | AK578: =IF(AJ578>0,AprCoef/SQRT(AJ578),0) -> 0 | AL578: =AJ578*AK578/365 -> 0 | AM578: =AE578 -> 0 | AN578: =AL578-AM578 -> 0 | AO578: =IF(A578>=Hip3LaunchDate,"YES","") | AP578: =IF(A578<Hip4LaunchDate,"pre-launch","live (zero-fee)") -> pre-launch
A579: 45640 | B579: 3.1705221e+09 | C579: 0 | D579: 546075604 | E579: =B579+C579 -> 3.1705221e+09 | F579: =E579+D579 -> 3.7165977e+09 | G579: =IFERROR(C579/E579,0) -> 0 | K579: =H579+I579 -> 0 | O579: =IF(H579=0,0,H579-L579) -> 0 | P579: =IF(B579=0,0,O579/B579*10000) -> 0 | S579: =Q579+R579 -> 0 | T579: =IF(A579<HlpChangeDate,HlpSharePre,HlpSharePost) -> 0.03 | U579: =S579*T579/(1-T579) -> 0 | W579: =U579-V579 -> 0 | X579: =Y579+Z579 -> 0 | AA579: =X579-V579 -> 0 | AB579: 0 | AC579: 24.151 | AD579: 21.7505 | AE579: =IFERROR(AB579/AD579,0) -> 0 | AF579: =K579-S579-X579 -> 0 | AG579: =S579-AB579 -> 0 | AI579: =IFERROR(AH579/S579,0) -> 0 | AJ579: 0 | AK579: =IF(AJ579>0,AprCoef/SQRT(AJ579),0) -> 0 | AL579: =AJ579*AK579/365 -> 0 | AM579: =AE579 -> 0 | AN579: =AL579-AM579 -> 0 | AO579: =IF(A579>=Hip3LaunchDate,"YES","") | AP579: =IF(A579<Hip4LaunchDate,"pre-launch","live (zero-fee)") -> pre-launch
... A582: 45643 | B582: 5.5938649e+09 | C582: 0 | D582: 533018011 | E582: =B582+C582 -> 5.5938649e+09 | F582: =E582+D582 -> 6.1268829e+09 | G582: =IFERROR(C582/E582,0) -> 0 | K582: =H582+I582 -> 0 | O582: =IF(H582=0,0,H582-L582) -> 0 | P582: =IF(B582=0,0,O582/B582*10000) -> 0 | S582: =Q582+R582 -> 0 | T582: =IF(A582<HlpChangeDate,HlpSharePre,HlpSharePost) -> 0.03 | U582: =S582*T582/(1-T582) -> 0 | W582: =U582-V582 -> 0 | X582: =Y582+Z582 -> 0 | AA582: =X582-V582 -> 0 | AB582: 0 | AC582: 25.583 | AD582: 26.38125 | AE582: =IFERROR(AB582/AD582,0) -> 0 | AF582: =K582-S582-X582 -> 0 | AG582: =S582-AB582 -> 0 | AI582: =IFERROR(AH582/S582,0) -> 0 | AJ582: 0 | AK582: =IF(AJ582>0,AprCoef/SQRT(AJ582),0) -> 0 | AL582: =AJ582*AK582/365 -> 0 | AM582: =AE582 -> 0 | AN582: =AL582-AM582 -> 0 | AO582: =IF(A582>=Hip3LaunchDate,"YES","") | AP582: =IF(A582<Hip4LaunchDate,"pre-launch","live (zero-fee)") -> pre-launch
A583: 45644 | B583: 8.540539e+09 | C583: 0 | D583: 472394527 | E583: =B583+C583 -> 8.540539e+09 | F583: =E583+D583 -> 9.0129336e+09 | G583: =IFERROR(C583/E583,0) -> 0 | K583: =H583+I583 -> 0 | O583: =IF(H583=0,0,H583-L583) -> 0 | P583: =IF(B583=0,0,O583/B583*10000) -> 0 | S583: =Q583+R583 -> 0 | T583: =IF(A583<HlpChangeDate,HlpSharePre,HlpSharePost) -> 0.03 | U583: =S583*T583/(1-T583) -> 0 | W583: =U583-V583 -> 0 | X583: =Y583+Z583 -> 0 | AA583: =X583-V583 -> 0 | AB583: 0 | AC583: 23.218 | AD583: 24.74275 | AE583: =IFERROR(AB583/AD583,0) -> 0 | AF583: =K583-S583-X583 -> 0 | AG583: =S583-AB583 -> 0 | AH583: 23328960 | AI583: =IFERROR(AH583/S583,0) -> 0 | AJ583: 0 | AK583: =IF(AJ583>0,AprCoef/SQRT(AJ583),0) -> 0 | AL583: =AJ583*AK583/365 -> 0 | AM583: =AE583 -> 0 | AN583: =AL583-AM583 -> 0 | AO583: =IF(A583>=Hip3LaunchDate,"YES","") | AP583: =IF(A583<Hip4LaunchDate,"pre-launch","live (zero-fee)") -> pre-launch
A584: 45645 | B584: 1.1512982e+10 | C584: 0 | D584: 564194362 | E584: =B584+C584 -> 1.1512982e+10 | F584: =E584+D584 -> 1.2077177e+10 | G584: =IFERROR(C584/E584,0) -> 0 | K584: =H584+I584 -> 0 | O584: =IF(H584=0,0,H584-L584) -> 0 | P584: =IF(B584=0,0,O584/B584*10000) -> 0 | S584: =Q584+R584 -> 0 | T584: =IF(A584<HlpChangeDate,HlpSharePre,HlpSharePost) -> 0.03 | U584: =S584*T584/(1-T584) -> 0 | W584: =U584-V584 -> 0 | X584: =Y584+Z584 -> 0 | AA584: =X584-V584 -> 0 | AB584: 0 | AC584: 24.92 | AD584: 24.34625 | AE584: =IFERROR(AB584/AD584,0) -> 0 | AF584: =K584-S584-X584 -> 0 | AG584: =S584-AB584 -> 0 | AI584: =IFERROR(AH584/S584,0) -> 0 | AJ584: 0 | AK584: =IF(AJ584>0,AprCoef/SQRT(AJ584),0) -> 0 | AL584: =AJ584*AK584/365 -> 0 | AM584: =AE584 -> 0 | AN584: =AL584-AM584 -> 0 | AO584: =IF(A584>=Hip3LaunchDate,"YES","") | AP584: =IF(A584<Hip4LaunchDate,"pre-launch","live (zero-fee)") -> pre-launch
A585: 45646 | B585: 9.8785211e+09 | C585: 0 | D585: 703781781 | E585: =B585+C585 -> 9.8785211e+09 | F585: =E585+D585 -> 1.0582303e+10 | G585: =IFERROR(C585/E585,0) -> 0 | K585: =H585+I585 -> 0 | O585: =IF(H585=0,0,H585-L585) -> 0 | P585: =IF(B585=0,0,O585/B585*10000) -> 0 | S585: =Q585+R585 -> 0 | T585: =IF(A585<HlpChangeDate,HlpSharePre,HlpSharePost) -> 0.03 | U585: =S585*T585/(1-T585) -> 0 | W585: =U585-V585 -> 0 | X585: =Y585+Z585 -> 0 | AA585: =X585-V585 -> 0 | AB585: 0 | AC585: 29.749 | AD585: 27.3575 | AE585: =IFERROR(AB585/AD585,0) -> 0 | AF585: =K585-S585-X585 -> 0 | AG585: =S585-AB585 -> 0 | AI585: =IFERROR(AH585/S585,0) -> 0 | AJ585: 0 | AK585: =IF(AJ585>0,AprCoef/SQRT(AJ585),0) -> 0 | AL585: =AJ585*AK585/365 -> 0 | AM585: =AE585 -> 0 | AN585: =AL585-AM585 -> 0 | AO585: =IF(A585>=Hip3LaunchDate,"YES","") | AP585: =IF(A585<Hip4LaunchDate,"pre-launch","live (zero-fee)") -> pre-launch
A586: 45647 | B586: 5.2030282e+09 | C586: 0 | D586: 527191283 | E586: =B586+C586 -> 5.2030282e+09 | F586: =E586+D586 -> 5.7302195e+09 | G586: =IFERROR(C586/E586,0) -> 0 | K586: =H586+I586 -> 0 | O586: =IF(H586=0,0,H586-L586) -> 0 | P586: =IF(B586=0,0,O586/B586*10000) -> 0 | S586: =Q586+R586 -> 0 | T586: =IF(A586<HlpChangeDate,HlpSharePre,HlpSharePost) -> 0.03 | U586: =S586*T586/(1-T586) -> 0 | W586: =U586-V586 -> 0 | X586: =Y586+Z586 -> 0 | AA586: =X586-V586 -> 0 | AB586: 0 | AC586: 32.029 | AD586: 31.49625 | AE586: =IFERROR(AB586/AD586,0) -> 0 | AF586: =K586-S586-X586 -> 0 | AG586: =S586-AB586 -> 0 | AI586: =IFERROR(AH586/S586,0) -> 0 | AJ586: 0 | AK586: =IF(AJ586>0,AprCoef/SQRT(AJ586),0) -> 0 | AL586: =AJ586*AK586/365 -> 0 | AM586: =AE586 -> 0 | AN586: =AL586-AM586 -> 0 | AO586: =IF(A586>=Hip3LaunchDate,"YES","") | AP586: =IF(A586<Hip4LaunchDate,"pre-launch","live (zero-fee)") -> pre-launch
A587: 45648 | B587: 4.6867317e+09 | C587: 0 | D587: 471634786 | E587: =B587+C587 -> 4.6867317e+09 | F587: =E587+D587 -> 5.1583665e+09 | G587: =IFERROR(C587/E587,0) -> 0 | K587: =H587+I587 -> 0 | O587: =IF(H587=0,0,H587-L587) -> 0 | P587: =IF(B587=0,0,O587/B587*10000) -> 0 | S587: =Q587+R587 -> 0 | T587: =IF(A587<HlpChangeDate,HlpSharePre,HlpSharePost) -> 0.03 | U587: =S587*T587/(1-T587) -> 0 | W587: =U587-V587 -> 0 | X587: =Y587+Z587 -> 0 | AA587: =X587-V587 -> 0 | AB587: 0 | AC587: 28.459 | AD587: 30.707 | AE587: =IFERROR(AB587/AD587,0) -> 0 | AF587: =K587-S587-X587 -> 0 | AG587: =S587-AB587 -> 0 | AH587: 10580501 | AI587: =IFERROR(AH587/S587,0) -> 0 | AJ587: 0 | AK587: =IF(AJ587>0,AprCoef/SQRT(AJ587),0) -> 0 | AL587: =AJ587*AK587/365 -> 0 | AM587: =AE587 -> 0 | AN587: =AL587-AM587 -> 0 | AO587: =IF(A587>=Hip3LaunchDate,"YES","") | AP587: =IF(A587<Hip4LaunchDate,"pre-launch","live (zero-fee)") -> pre-launch
A588: 45649 | B588: 6.1684635e+09 | C588: 0 | D588: 375034673 | E588: =B588+C588 -> 6.1684635e+09 | F588: =E588+D588 -> 6.5434982e+09 | G588: =IFERROR(C588/E588,0) -> 0 | H588: 1372264 | I588: 96254 | J588: 0 | K588: =H588+I588 -> 1468518 | O588: =IF(H588=0,0,H588-L588) -> 1372264 | P588: =IF(B588=0,0,O588/B588*10000) -> 2.2246448 | Q588: 1331096 | R588: 93366 | S588: =Q588+R588 -> 1424462 | T588: =IF(A588<HlpChangeDate,HlpSharePre,HlpSharePost) -> 0.03 | U588: =S588*T588/(1-T588) -> 44055.526 | V588: 0 | W588: =U588-V588 -> 44055.526 | X588: =Y588+Z588 -> 44056 | Y588: 41168 | Z588: 2888 | AA588: =X588-V588 -> 44056 | AB588: 1424462 | AC588: 28.623 | AD588: 28.0155 | AE588: =IFERROR(AB588/AD588,0) -> 50845.496 | AF588: =K588-S588-X588 -> 0 | AG588: =S588-AB588 -> 0 | AH588: 1461253.2 | AI588: =IFERROR(AH588/S588,0) -> 1.0258282 | AJ588: 0 | AK588: =IF(AJ588>0,AprCoef/SQRT(AJ588),0) -> 0 | AL588: =AJ588*AK588/365 -> 0 | AM588: =AE588 -> 50845.496 | AN588: =AL588-AM588 -> -50845.496 | AO588: =IF(A588>=Hip3LaunchDate,"YES","") | AP588: =IF(A588<Hip4LaunchDate,"pre-launch","live (zero-fee)") -> pre-launch
A589: 45650 | B589: 4.4015652e+09 | C589: 0 | D589: 319403848 | E589: =B589+C589 -> 4.4015652e+09 | F589: =E589+D589 -> 4.7209691e+09 | G589: =IFERROR(C589/E589,0) -> 0 | H589: 1296670 | I589: 47315 | J589: 40320 | K589: =H589+I589 -> 1343985 | O589: =IF(H589=0,0,H589-L589) -> 1296670 | P589: =IF(B589=0,0,O589/B589*10000) -> 2.9459293 | Q589: 1257770 | R589: 45895 | S589: =Q589+R589 -> 1303665 | T589: =IF(A589<HlpChangeDate,HlpSharePre,HlpSharePost) -> 0.03 | U589: =S589*T589/(1-T589) -> 40319.536 | V589: 40320 | W589: =U589-V589 -> -0.46391753 | X589: =Y589+Z589 -> 40319 | Y589: 38900 | Z589: 1419 | AA589: =X589-V589 -> -1 | AB589: 1303665 | AC589: 29.783 | AD589: 29.311 | AE589: =IFERROR(AB589/AD589,0) -> 44476.988 | AF589: =K589-S589-X589 -> 1 | AG589: =S589-AB589 -> 0 | AH589: 1368596.4 | AI589: =IFERROR(AH589/S589,0) -> 1.0498068 | AJ589: 0 | AK589: =IF(AJ589>0,AprCoef/SQRT(AJ589),0) -> 0 | AL589: =AJ589*AK589/365 -> 0 | AM589: =AE589 -> 44476.988 | AN589: =AL589-AM589 -> -44476.988 | AO589: =IF(A589>=Hip3LaunchDate,"YES","") | AP589: =IF(A589<Hip4LaunchDate,"pre-launch","live (zero-fee)") -> pre-launch
A590: 45651 | B590: 3.0900267e+09 | C590: 0 | D590: 310480616 | E590: =B590+C590 -> 3.0900267e+09 | F590: =E590+D590 -> 3.4005073e+09 | G590: =IFERROR(C590/E590,0) -> 0 | H590: 1002334 | I590: 43561 | J590: 31377 | K590: =H590+I590 -> 1045895 | O590: =IF(H590=0,0,H590-L590) -> 1002334 | P590: =IF(B590=0,0,O590/B590*10000) -> 3.2437713 | Q590: 972264 | R590: 42254 | S590: =Q590+R590 -> 1014518 | T590: =IF(A590<HlpChangeDate,HlpSharePre,HlpSharePost) -> 0.03 | U590: =S590*T590/(1-T590) -> 31376.845 | V590: 31377 | W590: =U590-V590 -> -0.15463918 | X590: =Y590+Z590 -> 31377 | Y590: 30070 | Z590: 1307 | AA590: =X590-V590 -> 0 | AB590: 1014518 | AC590: 26.544 | AD590: 28.2515 | AE590: =IFERROR(AB590/AD590,0) -> 35910.235 | AF590: =K590-S590-X590 -> 0 | AG590: =S590-AB590 -> 0 | AH590: 1047430.9 | AI590: =IFERROR(AH590/S590,0) -> 1.0324419 | AJ590: 0 | AK590: =IF(AJ590>0,AprCoef/SQRT(AJ590),0) -> 0 | AL590: =AJ590*AK590/365 -> 0 | AM590: =AE590 -> 35910.235 | AN590: =AL590-AM590 -> -35910.235 | AO590: =IF(A590>=Hip3LaunchDate,"YES","") | AP590: =IF(A590<Hip4LaunchDate,"pre-launch","live (zero-fee)") -> pre-launch
A591: 45652 | B591: 3.8974652e+09 | C591: 0 | D591: 214091088 | E591: =B591+C591 -> 3.8974652e+09 | F591: =E591+D591 -> 4.1115563e+09 | G591: =IFERROR(C591/E591,0) -> 0 | H591: 1269042 | I591: 44254 | J591: 39399 | K591: =H591+I591 -> 1313296 | O591: =IF(H591=0,0,H591-L591) -> 1269042 | P591: =IF(B591=0,0,O591/B591*10000) -> 3.2560701 | Q591: 1230971 | R591: 42926 | S591: =Q591+R591 -> 1273897 | T591: =IF(A591<HlpChangeDate,HlpSharePre,HlpSharePost) -> 0.03 | U591: =S591*T591/(1-T591) -> 39398.876 | V591: 39399 | W591: =U591-V591 -> -0.12371134 | X591: =Y591+Z591 -> 39399 | Y591: 38071 | Z591: 1328 | AA591: =X591-V591 -> 0 | AB591: 1273897 | AC591: 27.217 | AD591: 26.22475 | AE591: =IFERROR(AB591/AD591,0) -> 48576.135 | AF591: =K591-S591-X591 -> 0 | AG591: =S591-AB591 -> 0 | AH591: 1019238 | AI591: =IFERROR(AH591/S591,0) -> 0.80009451 | AJ591: 0 | AK591: =IF(AJ591>0,AprCoef/SQRT(AJ591),0) -> 0 | AL591: =AJ591*AK591/365 -> 0 | AM591: =AE591 -> 48576.135 | AN591: =AL591-AM591 -> -48576.135 | AO591: =IF(A591>=Hip3LaunchDate,"YES","") | AP591: =IF(A591<Hip4LaunchDate,"pre-launch","live (zero-fee)") -> pre-launch
A592: 45653 | B592: 3.8894731e+09 | C592: 0 | D592: 216391282 | E592: =B592+C592 -> 3.8894731e+09 | F592: =E592+D592 -> 4.1058644e+09 | G592: =IFERROR(C592/E592,0) -> 0 | H592: 1268921 | I592: 28523 | J592: 38923 | K592: =H592+I592 -> 1297444 | O592: =IF(H592=0,0,H592-L592) -> 1268921 | P592: =IF(B592=0,0,O592/B592*10000) -> 3.2624496 | Q592: 1230853 | R592: 27667 | S592: =Q592+R592 -> 1258520 | T592: =IF(A592<HlpChangeDate,HlpSharePre,HlpSharePost) -> 0.03 | U592: =S592*T592/(1-T592) -> 38923.299 | V592: 38923 | W592: =U592-V592 -> 0.29896907 | X592: =Y592+Z592 -> 38924 | Y592: 38068 | Z592: 856 | AA592: =X592-V592 -> 1 | AB592: 1258520 | AC592: 27.111 | AD592: 27.21625 | AE592: =IFERROR(AB592/AD592,0) -> 46241.492 | AF592: =K592-S592-X592 -> 0 | AG592: =S592-AB592 -> 0 | AH592: 1633333.4 | AI592: =IFERROR(AH592/S592,0) -> 1.2978208 | AJ592: 0 | AK592: =IF(AJ592>0,AprCoef/SQRT(AJ592),0) -> 0 | AL592: =AJ592*AK592/365 -> 0 | AM592: =AE592 -> 46241.492 | AN592: =AL592-AM592 -> -46241.492 | AO592: =IF(A592>=Hip3LaunchDate,"YES","") | AP592: =IF(A592<Hip4LaunchDate,"pre-launch","live (zero-fee)") -> pre-launch
A593: 45654 | B593: 2.0771914e+09 | C593: 0 | D593: 212391739 | E593: =B593+C593 -> 2.0771914e+09 | F593: =E593+D593 -> 2.2895831e+09 | G593: =IFERROR(C593/E593,0) -> 0 | H593: 950246 | I593: 28430 | J593: 29360 | K593: =H593+I593 -> 978676 | O593: =IF(H593=0,0,H593-L593) -> 950246 | P593: =IF(B593=0,0,O593/B593*10000) -> 4.5746676 | Q593: 921738 | R593: 27577 | S593: =Q593+R593 -> 949315 | T593: =IF(A593<HlpChangeDate,HlpSharePre,HlpSharePost) -> 0.03 | U593: =S593*T593/(1-T593) -> 29360.258 | V593: 29360 | W593: =U593-V593 -> 0.25773196 | X593: =Y593+Z593 -> 29360 | Y593: 28507 | Z593: 853 | AA593: =X593-V593 -> 0 | AB593: 949315 | AC593: 29.265 | AD593: 27.85575 | AE593: =IFERROR(AB593/AD593,0) -> 34079.678 | AF593: =K593-S593-X593 -> 1 | AG593: =S593-AB593 -> 0 | AH593: 978675.75 | AI593: =IFERROR(AH593/S593,0) -> 1.0309284 | AJ593: 0 | AK593: =IF(AJ593>0,AprCoef/SQRT(AJ593),0) -> 0 | AL593: =AJ593*AK593/365 -> 0 | AM593: =AE593 -> 34079.678 | AN593: =AL593-AM593 -> -34079.678 | AO593: =IF(A593>=Hip3LaunchDate,"YES","") | AP593: =IF(A593<Hip4LaunchDate,"pre-launch","live (zero-fee)") -> pre-launch
A594: 45655 | B594: 1.9659316e+09 | C594: 0 | D594: 342862746 | E594: =B594+C594 -> 1.9659316e+09 | F594: =E594+D594 -> 2.3087943e+09 | G594: =IFERROR(C594/E594,0) -> 0 | H594: 454244 | I594: 31496 | J594: 14412 | K594: =H594+I594 -> 485740 | O594: =IF(H594=0,0,H594-L594) -> 454244 | P594: =IF(B594=0,0,O594/B594*10000) -> 2.3105789 | Q594: 440616 | R594: 30551 | S594: =Q594+R594 -> 471167 | T594: =IF(A594<HlpChangeDate,HlpSharePre,HlpSharePost) -> 0.03 | U594: =S594*T594/(1-T594) -> 14572.175 | V594: 14412 | W594: =U594-V594 -> 160.17526 | X594: =Y594+Z594 -> 14572 | Y594: 13627 | Z594: 945 | AA594: =X594-V594 -> 160 | AB594: 471167 | AC594: 27.446 | AD594: 28.20625 | AE594: =IFERROR(AB594/AD594,0) -> 16704.347 | AF594: =K594-S594-X594 -> 1 | AG594: =S594-AB594 -> 0 | AH594: 480409.76 | AI594: =IFERROR(AH594/S594,0) -> 1.0196167 | AJ594: 0 | AK594: =IF(AJ594>0,AprCoef/SQRT(AJ594),0) -> 0 | AL594: =AJ594*AK594/365 -> 0 | AM594: =AE594 -> 16704.347 | AN594: =AL594-AM594 -> -16704.347 | AO594: =IF(A594>=Hip3LaunchDate,"YES","") | AP594: =IF(A594<Hip4LaunchDate,"pre-launch","live (zero-fee)") -> pre-launch
A595: 45656 | B595: 4.6971711e+09 | C595: 0 | D595: 267028183 | E595: =B595+C595 -> 4.6971711e+09 | F595: =E595+D595 -> 4.9641993e+09 | G595: =IFERROR(C595/E595,0) -> 0 | H595: 1483664 | I595: 49113 | J595: 45905 | K595: =H595+I595 -> 1532777 | O595: =IF(H595=0,0,H595-L595) -> 1483664 | P595: =IF(B595=0,0,O595/B595*10000) -> 3.1586331 | Q595: 1439154 | R595: 47640 | S595: =Q595+R595 -> 1486794 | T595: =IF(A595<HlpChangeDate,HlpSharePre,HlpSharePost) -> 0.03 | U595: =S595*T595/(1-T595) -> 45983.32 | V595: 45905 | W595: =U595-V595 -> 78.319588 | X595: =Y595+Z595 -> 45983 | Y595: 44510 | Z595: 1473 | AA595: =X595-V595 -> 78 | AB595: 1486794 | AC595: 26.953 | AD595: 27.52475 | AE595: =IFERROR(AB595/AD595,0) -> 54016.621 | AF595: =K595-S595-X595 -> 0 | AG595: =S595-AB595 -> 0 | AH595: 1530159.4 | AI595: =IFERROR(AH595/S595,0) -> 1.0291671 | AJ595: 301000000 | AK595: =IF(AJ595>0,AprCoef/SQRT(AJ595),0) -> 0.027320906 | AL595: =AJ595*AK595/365 -> 22530.391 | AM595: =AE595 -> 54016.621 | AN595: =AL595-AM595 -> -31486.231 | AO595: =IF(A595>=Hip3LaunchDate,"YES","") | AP595: =IF(A595<Hip4LaunchDate,"pre-launch","live (zero-fee)") -> pre-launch
A596: 45657 | B596: 3.4505145e+09 | C596: 0 | D596: 225503235 | E596: =B596+C596 -> 3.4505145e+09 | F596: =E596+D596 -> 3.6760177e+09 | G596: =IFERROR(C596/E596,0) -> 0 | H596: 1326087 | I596: 42962 | J596: 41146 | K596: =H596+I596 -> 1369049 | O596: =IF(H596=0,0,H596-L596) -> 1326087 | P596: =IF(B596=0,0,O596/B596*10000) -> 3.8431573 | Q596: 1286304 | R596: 41673 | S596: =Q596+R596 -> 1327977 | T596: =IF(A596<HlpChangeDate,HlpSharePre,HlpSharePost) -> 0.03 | U596: =S596*T596/(1-T596) -> 41071.454 | V596: 41146 | W596: =U596-V596 -> -74.546392 | X596: =Y596+Z596 -> 41072 | Y596: 39783 | Z596: 1289 | AA596: =X596-V596 -> -74 | AB596: 1327977 | AC596: 24.007 | AD596: 25.2725 | AE596: =IFERROR(AB596/AD596,0) -> 52546.325 | AF596: =K596-S596-X596 -> 0 | AG596: =S596-AB596 -> 0 | AH596: 1371530.6 | AI596: =IFERROR(AH596/S596,0) -> 1.032797 | AJ596: 3.0171698e+08 | AK596: =IF(AJ596>0,AprCoef/SQRT(AJ596),0) -> 0.027288425 | AL596: =AJ596*AK596/365 -> 22557.209 | AM596: =AE596 -> 52546.325 | AN596: =AL596-AM596 -> -29989.117 | AO596: =IF(A596>=Hip3LaunchDate,"YES","") | AP596: =IF(A596<Hip4LaunchDate,"pre-launch","live (zero-fee)") -> pre-launch
A597: 45658 | B597: 2.1572568e+09 | C597: 0 | D597: 256438336 | E597: =B597+C597 -> 2.1572568e+09 | F597: =E597+D597 -> 2.4136952e+09 | G597: =IFERROR(C597/E597,0) -> 0 | H597: 483299 | I597: 30141 | J597: 15396 | K597: =H597+I597 -> 513440 | O597: =IF(H597=0,0,H597-L597) -> 483299 | P597: =IF(B597=0,0,O597/B597*10000) -> 2.2403406 | Q597: 468800 | R597: 29237 | S597: =Q597+R597 -> 498037 | T597: =IF(A597<HlpChangeDate,HlpSharePre,HlpSharePost) -> 0.03 | U597: =S597*T597/(1-T597) -> 15403.206 | V597: 15396 | W597: =U597-V597 -> 7.2061856 | X597: =Y597+Z597 -> 15403 | Y597: 14499 | Z597: 904 | AA597: =X597-V597 -> 7 | AB597: 498037 | AC597: 26.315 | AD597: 25.052 | AE597: =IFERROR(AB597/AD597,0) -> 19880.129 | AF597: =K597-S597-X597 -> 0 | AG597: =S597-AB597 -> 0 | AH597: 513195.56 | AI597: =IFERROR(AH597/S597,0) -> 1.0304366 | AJ597: 3.0243396e+08 | AK597: =IF(AJ597>0,AprCoef/SQRT(AJ597),0) -> 0.027256059 | AL597: =AJ597*AK597/365 -> 22583.994 | AM597: =AE597 -> 19880.129 | AN597: =AL597-AM597 -> 2703.865 | AO597: =IF(A597>=Hip3LaunchDate,"YES","") | AP597: =IF(A597<Hip4LaunchDate,"pre-launch","live (zero-fee)") -> pre-launch
A598: 45659 | B598: 3.6458162e+09 | C598: 0 | D598: 267239456 | E598: =B598+C598 -> 3.6458162e+09 | F598: =E598+D598 -> 3.9130556e+09 | G598: =IFERROR(C598/E598,0) -> 0 | H598: 1267839 | I598: 41666 | J598: 39456 | K598: =H598+I598 -> 1309505 | O598: =IF(H598=0,0,H598-L598) -> 1267839 | P598: =IF(B598=0,0,O598/B598*10000) -> 3.4775176 | Q598: 1229804 | R598: 40416 | S598: =Q598+R598 -> 1270220 | T598: =IF(A598<HlpChangeDate,HlpSharePre,HlpSharePost) -> 0.03 | U598: =S598*T598/(1-T598) -> 39285.155 | V598: 39456 | W598: =U598-V598 -> -170.84536 | X598: =Y598+Z598 -> 39285 | Y598: 38035 | Z598: 1250 | AA598: =X598-V598 -> -171 | AB598: 1270220 | AC598: 23.163 | AD598: 24.7135 | AE598: =IFERROR(AB598/AD598,0) -> 51397.819 | AF598: =K598-S598-X598 -> 0 | AG598: =S598-AB598 -> 0 | AH598: 1315214.8 | AI598: =IFERROR(AH598/S598,0) -> 1.0354228 | AJ598: 3.0315094e+08 | AK598: =IF(AJ598>0,AprCoef/SQRT(AJ598),0) -> 0.027223808 | AL598: =AJ598*AK598/365 -> 22610.748 | AM598: =AE598 -> 51397.819 | AN598: =AL598-AM598 -> -28787.071 | AO598: =IF(A598>=Hip3LaunchDate,"YES","") | AP598: =IF(A598<Hip4LaunchDate,"pre-launch","live (zero-fee)") -> pre-launch
A599: 45660 | B599: 3.5731603e+09 | C599: 0 | D599: 176550030 | E599: =B599+C599 -> 3.5731603e+09 | F599: =E599+D599 -> 3.7497103e+09 | G599: =IFERROR(C599/E599,0) -> 0 | H599: 1374850 | I599: 37005 | J599: 42237 | K599: =H599+I599 -> 1411855 | O599: =IF(H599=0,0,H599-L599) -> 1374850 | P599: =IF(B599=0,0,O599/B599*10000) -> 3.8477143 | Q599: 1333605 | R599: 35895 | S599: =Q599+R599 -> 1369500 | T599: =IF(A599<HlpChangeDate,HlpSharePre,HlpSharePost) -> 0.03 | U599: =S599*T599/(1-T599) -> 42355.67 | V599: 42237 | W599: =U599-V599 -> 118.6701 | X599: =Y599+Z599 -> 42356 | Y599: 41246 | Z599: 1110 | AA599: =X599-V599 -> 119 | AB599: 1369500 | AC599: 24.442 | AD599: 23.553 | AE599: =IFERROR(AB599/AD599,0) -> 58145.459 | AF599: =K599-S599-X599 -> -1 | AG599: =S599-AB599 -> 0 | AH599: 1407906.3 | AI599: =IFERROR(AH599/S599,0) -> 1.0280441 | AJ599: 3.0386792e+08 | AK599: =IF(AJ599>0,AprCoef/SQRT(AJ599),0) -> 0.027191672 | AL599: =AJ599*AK599/365 -> 22637.471 | AM599: =AE599 -> 58145.459 | AN599: =AL599-AM599 -> -35507.988 | AO599: =IF(A599>=Hip3LaunchDate,"YES","") | AP599: =IF(A599<Hip4LaunchDate,"pre-launch","live (zero-fee)") -> pre-launch
... A607: 45668 | B607: 1.9752201e+09 | C607: 0 | D607: 104729289 | E607: =B607+C607 -> 1.9752201e+09 | F607: =E607+D607 -> 2.0799494e+09 | G607: =IFERROR(C607/E607,0) -> 0 | H607: 457618 | I607: 14961 | J607: 14177 | K607: =H607+I607 -> 472579 | O607: =IF(H607=0,0,H607-L607) -> 457618 | P607: =IF(B607=0,0,O607/B607*10000) -> 2.316795 | Q607: 443890 | R607: 14512 | S607: =Q607+R607 -> 458402 | T607: =IF(A607<HlpChangeDate,HlpSharePre,HlpSharePost) -> 0.03 | U607: =S607*T607/(1-T607) -> 14177.381 | V607: 14177 | W607: =U607-V607 -> 0.3814433 | X607: =Y607+Z607 -> 14178 | Y607: 13729 | Z607: 449 | AA607: =X607-V607 -> 1 | AB607: 458402 | AC607: 20.884 | AD607: 20.54925 | AE607: =IFERROR(AB607/AD607,0) -> 22307.481 | AF607: =K607-S607-X607 -> -1 | AG607: =S607-AB607 -> 0 | AH607: 472579.05 | AI607: =IFERROR(AH607/S607,0) -> 1.0309271 | AJ607: 3.0960377e+08 | AK607: =IF(AJ607>0,AprCoef/SQRT(AJ607),0) -> 0.026938612 | AL607: =AJ607*AK607/365 -> 22850.126 | AM607: =AE607 -> 22307.481 | AN607: =AL607-AM607 -> 542.64523 | AO607: =IF(A607>=Hip3LaunchDate,"YES","") | AP607: =IF(A607<Hip4LaunchDate,"pre-launch","live (zero-fee)") -> pre-launch
A608: 45669 | B608: 1.8688233e+09 | C608: 0 | D608: 230154418 | E608: =B608+C608 -> 1.8688233e+09 | F608: =E608+D608 -> 2.0989777e+09 | G608: =IFERROR(C608/E608,0) -> 0 | K608: =H608+I608 -> 0 | O608: =IF(H608=0,0,H608-L608) -> 0 | P608: =IF(B608=0,0,O608/B608*10000) -> 0 | S608: =Q608+R608 -> 0 | T608: =IF(A608<HlpChangeDate,HlpSharePre,HlpSharePost) -> 0.03 | U608: =S608*T608/(1-T608) -> 0 | W608: =U608-V608 -> 0 | X608: =Y608+Z608 -> 0 | AA608: =X608-V608 -> 0 | AB608: 0 | AC608: 21.117 | AD608: 20.9875 | AE608: =IFERROR(AB608/AD608,0) -> 0 | AF608: =K608-S608-X608 -> 0 | AG608: =S608-AB608 -> 0 | AH608: 479173.59 | AI608: =IFERROR(AH608/S608,0) -> 0 | AJ608: 3.1032075e+08 | AK608: =IF(AJ608>0,AprCoef/SQRT(AJ608),0) -> 0.026907474 | AL608: =AJ608*AK608/365 -> 22876.569 | AM608: =AE608 -> 0 | AN608: =AL608-AM608 -> 22876.569 | AO608: =IF(A608>=Hip3LaunchDate,"YES","") | AP608: =IF(A608<Hip4LaunchDate,"pre-launch","live (zero-fee)") -> pre-launch
A609: 45670 | B609: 7.6148894e+09 | C609: 0 | D609: 195123318 | E609: =B609+C609 -> 7.6148894e+09 | F609: =E609+D609 -> 7.8100127e+09 | G609: =IFERROR(C609/E609,0) -> 0 | K609: =H609+I609 -> 0 | O609: =IF(H609=0,0,H609-L609) -> 0 | P609: =IF(B609=0,0,O609/B609*10000) -> 0 | S609: =Q609+R609 -> 0 | T609: =IF(A609<HlpChangeDate,HlpSharePre,HlpSharePost) -> 0.03 | U609: =S609*T609/(1-T609) -> 0 | W609: =U609-V609 -> 0 | X609: =Y609+Z609 -> 0 | AA609: =X609-V609 -> 0 | AB609: 0 | AC609: 21.629 | AD609: 21.24875 | AE609: =IFERROR(AB609/AD609,0) -> 0 | AF609: =K609-S609-X609 -> 0 | AG609: =S609-AB609 -> 0 | AH609: 2330484.8 | AI609: =IFERROR(AH609/S609,0) -> 0 | AJ609: 3.1103774e+08 | AK609: =IF(AJ609>0,AprCoef/SQRT(AJ609),0) -> 0.026876444 | AL609: =AJ609*AK609/365 -> 22902.981 | AM609: =AE609 -> 0 | AN609: =AL609-AM609 -> 22902.981 | AO609: =IF(A609>=Hip3LaunchDate,"YES","") | AP609: =IF(A609<Hip4LaunchDate,"pre-launch","live (zero-fee)") -> pre-launch
A610: 45671 | B610: 4.1645346e+09 | C610: 0 | D610: 186174573 | E610: =B610+C610 -> 4.1645346e+09 | F610: =E610+D610 -> 4.3507092e+09 | G610: =IFERROR(C610/E610,0) -> 0 | H610: 1243879 | I610: 24324 | J610: 38194 | K610: =H610+I610 -> 1268203 | O610: =IF(H610=0,0,H610-L610) -> 1243879 | P610: =IF(B610=0,0,O610/B610*10000) -> 2.9868379 | Q610: 1206563 | R610: 23594 | S610: =Q610+R610 -> 1230157 | T610: =IF(A610<HlpChangeDate,HlpSharePre,HlpSharePost) -> 0.03 | U610: =S610*T610/(1-T610) -> 38046.093 | V610: 38194 | W610: =U610-V610 -> -147.90722 | X610: =Y610+Z610 -> 38046 | Y610: 37316 | Z610: 730 | AA610: =X610-V610 -> -148 | AB610: 1230157 | AC610: 22.999 | AD610: 22.35025 | AE610: =IFERROR(AB610/AD610,0) -> 55039.966 | AF610: =K610-S610-X610 -> 0 | AG610: =S610-AB610 -> 0 | AH610: 1273120.8 | AI610: =IFERROR(AH610/S610,0) -> 1.0349255 | AJ610: 3.1175472e+08 | AK610: =IF(AJ610>0,AprCoef/SQRT(AJ610),0) -> 0.02684552 | AL610: =AJ610*AK610/365 -> 22929.363 | AM610: =AE610 -> 55039.966 | AN610: =AL610-AM610 -> -32110.603 | AO610: =IF(A610>=Hip3LaunchDate,"YES","") | AP610: =IF(A610<Hip4LaunchDate,"pre-launch","live (zero-fee)") -> pre-launch
A611: 45672 | B611: 5.3154076e+09 | C611: 0 | D611: 125668891 | E611: =B611+C611 -> 5.3154076e+09 | F611: =E611+D611 -> 5.4410765e+09 | G611: =IFERROR(C611/E611,0) -> 0 | H611: 1245669 | I611: 23915 | J611: 37801 | K611: =H611+I611 -> 1269584 | O611: =IF(H611=0,0,H611-L611) -> 1245669 | P611: =IF(B611=0,0,O611/B611*10000) -> 2.3435061 | Q611: 1208299 | R611: 23198 | S611: =Q611+R611 -> 1231497 | T611: =IF(A611<HlpChangeDate,HlpSharePre,HlpSharePost) -> 0.03 | U611: =S611*T611/(1-T611) -> 38087.536 | V611: 37801 | W611: =U611-V611 -> 286.53608 | X611: =Y611+Z611 -> 38087 | Y611: 37370 | Z611: 717 | AA611: =X611-V611 -> 286 | AB611: 1231497 | AC611: 24.376 | AD611: 23.4695 | AE611: =IFERROR(AB611/AD611,0) -> 52472.23 | AF611: =K611-S611-X611 -> 0 | AG611: =S611-AB611 -> 0 | AH611: 1260041.5 | AI611: =IFERROR(AH611/S611,0) -> 1.0231787 | AJ611: 3.124717e+08 | AK611: =IF(AJ611>0,AprCoef/SQRT(AJ611),0) -> 0.026814703 | AL611: =AJ611*AK611/365 -> 22955.715 | AM611: =AE611 -> 52472.23 | AN611: =AL611-AM611 -> -29516.515 | AO611: =IF(A611>=Hip3LaunchDate,"YES","") | AP611: =IF(A611<Hip4LaunchDate,"pre-launch","live (zero-fee)") -> pre-launch
A612: 45673 | B612: 5.7136112e+09 | C612: 0 | D612: 148144621 | E612: =B612+C612 -> 5.7136112e+09 | F612: =E612+D612 -> 5.8617559e+09 | G612: =IFERROR(C612/E612,0) -> 0 | H612: 1677266 | I612: 18602 | J612: 51162 | K612: =H612+I612 -> 1695868 | O612: =IF(H612=0,0,H612-L612) -> 1677266 | P612: =IF(B612=0,0,O612/B612*10000) -> 2.935562 | Q612: 1626948 | R612: 18044 | S612: =Q612+R612 -> 1644992 | T612: =IF(A612<HlpChangeDate,HlpSharePre,HlpSharePost) -> 0.03 | U612: =S612*T612/(1-T612) -> 50876.041 | V612: 51162 | W612: =U612-V612 -> -285.95876 | X612: =Y612+Z612 -> 50876 | Y612: 50318 | Z612: 558 | AA612: =X612-V612 -> -286 | AB612: 1644992 | AC612: 23.469 | AD612: 23.84675 | AE612: =IFERROR(AB612/AD612,0) -> 68981.811 | AF612: =K612-S612-X612 -> 0 | AG612: =S612-AB612 -> 0 | AH612: 1705410 | AI612: =IFERROR(AH612/S612,0) -> 1.0367285 | AJ612: 3.1318868e+08 | AK612: =IF(AJ612>0,AprCoef/SQRT(AJ612),0) -> 0.026783992 | AL612: =AJ612*AK612/365 -> 22982.036 | AM612: =AE612 -> 68981.811 | AN612: =AL612-AM612 -> -45999.775 | AO612: =IF(A612>=Hip3LaunchDate,"YES","") | AP612: =IF(A612<Hip4LaunchDate,"pre-launch","live (zero-fee)") -> pre-launch
A613: 45674 | B613: 5.4612772e+09 | C613: 0 | D613: 342126938 | E613: =B613+C613 -> 5.4612772e+09 | F613: =E613+D613 -> 5.8034042e+09 | G613: =IFERROR(C613/E613,0) -> 0 | H613: 1677802 | I613: 20485 | J613: 50949 | K613: =H613+I613 -> 1698287 | O613: =IF(H613=0,0,H613-L613) -> 1677802 | P613: =IF(B613=0,0,O613/B613*10000) -> 3.0721788 | Q613: 1627468 | R613: 19870 | S613: =Q613+R613 -> 1647338 | T613: =IF(A613<HlpChangeDate,HlpSharePre,HlpSharePost) -> 0.03 | U613: =S613*T613/(1-T613) -> 50948.598 | V613: 50949 | W613: =U613-V613 -> -0.40206186 | X613: =Y613+Z613 -> 50949 | Y613: 50334 | Z613: 615 | AA613: =X613-V613 -> 0 | AB613: 1647338 | AC613: 23.09 | AD613: 23.36875 | AE613: =IFERROR(AB613/AD613,0) -> 70493.201 | AF613: =K613-S613-X613 -> 0 | AG613: =S613-AB613 -> 0 | AH613: 1698286.7 | AI613: =IFERROR(AH613/S613,0) -> 1.0309279 | AJ613: 3.1390566e+08 | AK613: =IF(AJ613>0,AprCoef/SQRT(AJ613),0) -> 0.026753387 | AL613: =AJ613*AK613/365 -> 23008.328 | AM613: =AE613 -> 70493.201 | AN613: =AL613-AM613 -> -47484.874 | AO613: =IF(A613>=Hip3LaunchDate,"YES","") | AP613: =IF(A613<Hip4LaunchDate,"pre-launch","live (zero-fee)") -> pre-launch
A614: 45675 | B614: 9.6789601e+09 | C614: 0 | D614: 452915269 | E614: =B614+C614 -> 9.6789601e+09 | F614: =E614+D614 -> 1.0131875e+10 | G614: =IFERROR(C614/E614,0) -> 0 | H614: 2787442 | I614: 52413 | J614: 84875 | K614: =H614+I614 -> 2839855 | O614: =IF(H614=0,0,H614-L614) -> 2787442 | P614: =IF(B614=0,0,O614/B614*10000) -> 2.8798982 | Q614: 2703819 | R614: 50841 | S614: =Q614+R614 -> 2754660 | T614: =IF(A614<HlpChangeDate,HlpSharePre,HlpSharePost) -> 0.03 | U614: =S614*T614/(1-T614) -> 85195.67 | V614: 84875 | W614: =U614-V614 -> 320.6701 | X614: =Y614+Z614 -> 85195 | Y614: 83623 | Z614: 1572 | AA614: =X614-V614 -> 320 | AB614: 2754660 | AC614: 21.937 | AD614: 21.7835 | AE614: =IFERROR(AB614/AD614,0) -> 126456.26 | AF614: =K614-S614-X614 -> 0 | AG614: =S614-AB614 -> 0 | AH614: 2829175.9 | AI614: =IFERROR(AH614/S614,0) -> 1.0270509 | AJ614: 3.1462264e+08 | AK614: =IF(AJ614>0,AprCoef/SQRT(AJ614),0) -> 0.026722886 | AL614: =AJ614*AK614/365 -> 23034.589 | AM614: =AE614 -> 126456.26 | AN614: =AL614-AM614 -> -103421.67 | AO614: =IF(A614>=Hip3LaunchDate,"YES","") | AP614: =IF(A614<Hip4LaunchDate,"pre-launch","live (zero-fee)") -> pre-launch
A615: 45676 | B615: 1.775022e+10 | C615: 0 | D615: 234451715 | E615: =B615+C615 -> 1.775022e+10 | F615: =E615+D615 -> 1.7984671e+10 | G615: =IFERROR(C615/E615,0) -> 0 | H615: 4250373 | I615: 61521 | J615: 128368 | K615: =H615+I615 -> 4311894 | O615: =IF(H615=0,0,H615-L615) -> 4250373 | P615: =IF(B615=0,0,O615/B615*10000) -> 2.3945467 | Q615: 4122862 | R615: 59675 | S615: =Q615+R615 -> 4182537 | T615: =IF(A615<HlpChangeDate,HlpSharePre,HlpSharePost) -> 0.03 | U615: =S615*T615/(1-T615) -> 129356.81 | V615: 128368 | W615: =U615-V615 -> 988.81443 | X615: =Y615+Z615 -> 129357 | Y615: 127511 | Z615: 1846 | AA615: =X615-V615 -> 989 | AB615: 4182537 | AC615: 20.198 | AD615: 21.25875 | AE615: =IFERROR(AB615/AD615,0) -> 196744.26 | AF615: =K615-S615-X615 -> 0 | AG615: =S615-AB615 -> 0 | AH615: 4278948 | AI615: =IFERROR(AH615/S615,0) -> 1.0230508 | AJ615: 3.1533962e+08 | AK615: =IF(AJ615>0,AprCoef/SQRT(AJ615),0) -> 0.026692489 | AL615: =AJ615*AK615/365 -> 23060.82 | AM615: =AE615 -> 196744.26 | AN615: =AL615-AM615 -> -173683.44 | AO615: =IF(A615>=Hip3LaunchDate,"YES","") | AP615: =IF(A615<Hip4LaunchDate,"pre-launch","live (zero-fee)") -> pre-launch
A616: 45677 | B616: 1.6339005e+10 | C616: 0 | D616: 255573062 | E616: =B616+C616 -> 1.6339005e+10 | F616: =E616+D616 -> 1.6594578e+10 | G616: =IFERROR(C616/E616,0) -> 0 | H616: 4044525 | I616: 34279 | J616: 122933 | K616: =H616+I616 -> 4078804 | O616: =IF(H616=0,0,H616-L616) -> 4044525 | P616: =IF(B616=0,0,O616/B616*10000) -> 2.4753802 | Q616: 3923189 | R616: 33251 | S616: =Q616+R616 -> 3956440 | T616: =IF(A616<HlpChangeDate,HlpSharePre,HlpSharePost) -> 0.03 | U616: =S616*T616/(1-T616) -> 122364.12 | V616: 122933 | W616: =U616-V616 -> -568.87629 | X616: =Y616+Z616 -> 122364 | Y616: 121336 | Z616: 1028 | AA616: =X616-V616 -> -569 | AB616: 3956440 | AC616: 20.547 | AD616: 20.6965 | AE616: =IFERROR(AB616/AD616,0) -> 191164.69 | AF616: =K616-S616-X616 -> 0 | AG616: =S616-AB616 -> 0 | AH616: 4097777 | AI616: =IFERROR(AH616/S616,0) -> 1.0357233 | AJ616: 3.160566e+08 | AK616: =IF(AJ616>0,AprCoef/SQRT(AJ616),0) -> 0.026662195 | AL616: =AJ616*AK616/365 -> 23087.022 | AM616: =AE616 -> 191164.69 | AN616: =AL616-AM616 -> -168077.67 | AO616: =IF(A616>=Hip3LaunchDate,"YES","") | AP616: =IF(A616<Hip4LaunchDate,"pre-launch","live (zero-fee)") -> pre-launch
A617: 45678 | B617: 8.3419449e+09 | C617: 0 | D617: 217426990 | E617: =B617+C617 -> 8.3419449e+09 | F617: =E617+D617 -> 8.5593719e+09 | G617: =IFERROR(C617/E617,0) -> 0 | H617: 2031876 | I617: 34069 | J617: 62718 | K617: =H617+I617 -> 2065945 | O617: =IF(H617=0,0,H617-L617) -> 2031876 | P617: =IF(B617=0,0,O617/B617*10000) -> 2.4357341 | Q617: 1970920 | R617: 33047 | S617: =Q617+R617 -> 2003967 | T617: =IF(A617<HlpChangeDate,HlpSharePre,HlpSharePost) -> 0.03 | U617: =S617*T617/(1-T617) -> 61978.361 | V617: 62718 | W617: =U617-V617 -> -739.63918 | X617: =Y617+Z617 -> 61978 | Y617: 60956 | Z617: 1022 | AA617: =X617-V617 -> -740 | AB617: 2003967 | AC617: 23.183 | AD617: 22.1905 | AE617: =IFERROR(AB617/AD617,0) -> 90307.429 | AF617: =K617-S617-X617 -> 0 | AG617: =S617-AB617 -> 0 | AH617: 2090596.9 | AI617: =IFERROR(AH617/S617,0) -> 1.0432292 | AJ617: 3.1677358e+08 | AK617: =IF(AJ617>0,AprCoef/SQRT(AJ617),0) -> 0.026632005 | AL617: =AJ617*AK617/365 -> 23113.194 | AM617: =AE617 -> 90307.429 | AN617: =AL617-AM617 -> -67194.235 | AO617: =IF(A617>=Hip3LaunchDate,"YES","") | AP617: =IF(A617<Hip4LaunchDate,"pre-launch","live (zero-fee)") -> pre-launch
A618: 45679 | B618: 5.2815512e+09 | C618: 0 | D618: 268190024 | E618: =B618+C618 -> 5.2815512e+09 | F618: =E618+D618 -> 5.5497412e+09 | G618: =IFERROR(C618/E618,0) -> 0 | H618: 1405006 | I618: 30418 | J618: 43063 | K618: =H618+I618 -> 1435424 | O618: =IF(H618=0,0,H618-L618) -> 1405006 | P618: =IF(B618=0,0,O618/B618*10000) -> 2.6602147 | Q618: 1362855 | R618: 29505 | S618: =Q618+R618 -> 1392360 | T618: =IF(A618<HlpChangeDate,HlpSharePre,HlpSharePost) -> 0.03 | U618: =S618*T618/(1-T618) -> 43062.68 | V618: 43063 | W618: =U618-V618 -> -0.31958763 | X618: =Y618+Z618 -> 43063 | Y618: 42150 | Z618: 913 | AA618: =X618-V618 -> 0 | AB618: 1392360 | AC618: 24.3 | AD618: 24.38725 | AE618: =IFERROR(AB618/AD618,0) -> 57093.768 | AF618: =K618-S618-X618 -> 1 | AG618: =S618-AB618 -> 0 | AH618: 1435423.4 | AI618: =IFERROR(AH618/S618,0) -> 1.0309284 | AJ618: 3.1749057e+08 | AK618: =IF(AJ618>0,AprCoef/SQRT(AJ618),0) -> 0.026601917 | AL618: =AJ618*AK618/365 -> 23139.336 | AM618: =AE618 -> 57093.768 | AN618: =AL618-AM618 -> -33954.432 | AO618: =IF(A618>=Hip3LaunchDate,"YES","") | AP618: =IF(A618<Hip4LaunchDate,"pre-launch","live (zero-fee)") -> pre-launch
A619: 45680 | B619: 1.1321581e+10 | C619: 0 | D619: 178140305 | E619: =B619+C619 -> 1.1321581e+10 | F619: =E619+D619 -> 1.1499721e+10 | G619: =IFERROR(C619/E619,0) -> 0 | H619: 2783278 | I619: 38159 | J619: 84643 | K619: =H619+I619 -> 2821437 | O619: =IF(H619=0,0,H619-L619) -> 2783278 | P619: =IF(B619=0,0,O619/B619*10000) -> 2.4583828 | Q619: 2699780 | R619: 37014 | S619: =Q619+R619 -> 2736794 | T619: =IF(A619<HlpChangeDate,HlpSharePre,HlpSharePost) -> 0.03 | U619: =S619*T619/(1-T619) -> 84643.113 | V619: 84643 | W619: =U619-V619 -> 0.11340206 | X619: =Y619+Z619 -> 84643 | Y619: 83498 | Z619: 1145 | AA619: =X619-V619 -> 0 | AB619: 2736794 | AC619: 21.975 | AD619: 23.1755 | AE619: =IFERROR(AB619/AD619,0) -> 118089.97 | AF619: =K619-S619-X619 -> 0 | AG619: =S619-AB619 -> 0 | AH619: 2821436.6 | AI619: =IFERROR(AH619/S619,0) -> 1.0309277 | AJ619: 3.1820755e+08 | AK619: =IF(AJ619>0,AprCoef/SQRT(AJ619),0) -> 0.02657193 | AL619: =AJ619*AK619/365 -> 23165.449 | AM619: =AE619 -> 118089.97 | AN619: =AL619-AM619 -> -94924.517 | AO619: =IF(A619>=Hip3LaunchDate,"YES","") | AP619: =IF(A619<Hip4LaunchDate,"pre-launch","live (zero-fee)") -> pre-launch
A620: 45681 | B620: 5.7847318e+09 | C620: 0 | D620: 93192677 | E620: =B620+C620 -> 5.7847318e+09 | F620: =E620+D620 -> 5.8779245e+09 | G620: =IFERROR(C620/E620,0) -> 0 | H620: 1284164 | I620: 23999 | J620: 38987 | K620: =H620+I620 -> 1308163 | O620: =IF(H620=0,0,H620-L620) -> 1284164 | P620: =IF(B620=0,0,O620/B620*10000) -> 2.2199197 | Q620: 1245639 | R620: 23279 | S620: =Q620+R620 -> 1268918 | T620: =IF(A620<HlpChangeDate,HlpSharePre,HlpSharePost) -> 0.03 | U620: =S620*T620/(1-T620) -> 39244.887 | V620: 38987 | W620: =U620-V620 -> 257.8866 | X620: =Y620+Z620 -> 39245 | Y620: 38525 | Z620: 720 | AA620: =X620-V620 -> 258 | AB620: 1268918 | AC620: 23.059 | AD620: 22.792 | AE620: =IFERROR(AB620/AD620,0) -> 55673.833 | AF620: =K620-S620-X620 -> 0 | AG620: =S620-AB620 -> 0 | AH620: 1299579.9 | AI620: =IFERROR(AH620/S620,0) -> 1.0241638 | AJ620: 3.1892453e+08 | AK620: =IF(AJ620>0,AprCoef/SQRT(AJ620),0) -> 0.026542045 | AL620: =AJ620*AK620/365 -> 23191.532 | AM620: =AE620 -> 55673.833 | AN620: =AL620-AM620 -> -32482.301 | AO620: =IF(A620>=Hip3LaunchDate,"YES","") | AP620: =IF(A620<Hip4LaunchDate,"pre-launch","live (zero-fee)") -> pre-launch
A621: 45682 | B621: 3.5167284e+09 | C621: 0 | D621: 138875526 | E621: =B621+C621 -> 3.5167284e+09 | F621: =E621+D621 -> 3.655604e+09 | G621: =IFERROR(C621/E621,0) -> 0 | H621: 1061042 | I621: 14317 | J621: 32324 | K621: =H621+I621 -> 1075359 | O621: =IF(H621=0,0,H621-L621) -> 1061042 | P621: =IF(B621=0,0,O621/B621*10000) -> 3.0171281 | Q621: 1029211 | R621: 13888 | S621: =Q621+R621 -> 1043099 | T621: =IF(A621<HlpChangeDate,HlpSharePre,HlpSharePost) -> 0.03 | U621: =S621*T621/(1-T621) -> 32260.794 | V621: 32324 | W621: =U621-V621 -> -63.206186 | X621: =Y621+Z621 -> 32261 | Y621: 31831 | Z621: 430 | AA621: =X621-V621 -> -63 | AB621: 1043099 | AC621: 23.152 | AD621: 22.95925 | AE621: =IFERROR(AB621/AD621,0) -> 45432.625 | AF621: =K621-S621-X621 -> -1 | AG621: =S621-AB621 -> 0 | AH621: 1077471.9 | AI621: =IFERROR(AH621/S621,0) -> 1.0329527 | AJ621: 3.1964151e+08 | AK621: =IF(AJ621>0,AprCoef/SQRT(AJ621),0) -> 0.02651226 | AL621: =AJ621*AK621/365 -> 23217.586 | AM621: =AE621 -> 45432.625 | AN621: =AL621-AM621 -> -22215.039 | AO621: =IF(A621>=Hip3LaunchDate,"YES","") | AP621: =IF(A621<Hip4LaunchDate,"pre-launch","live (zero-fee)") -> pre-launch
... A754: 45815 | B754: 3.033733e+09 | C754: 0 | D754: 137044111 | E754: =B754+C754 -> 3.033733e+09 | F754: =E754+D754 -> 3.1707771e+09 | G754: =IFERROR(C754/E754,0) -> 0 | H754: 888062 | I754: 30975 | J754: 27571 | K754: =H754+I754 -> 919037 | O754: =IF(H754=0,0,H754-L754) -> 888062 | P754: =IF(B754=0,0,O754/B754*10000) -> 2.9272913 | Q754: 861420 | R754: 30046 | S754: =Q754+R754 -> 891466 | T754: =IF(A754<HlpChangeDate,HlpSharePre,HlpSharePost) -> 0.03 | U754: =S754*T754/(1-T754) -> 27571.113 | V754: 27571 | W754: =U754-V754 -> 0.11340206 | X754: =Y754+Z754 -> 27571 | Y754: 26642 | Z754: 929 | AA754: =X754-V754 -> 0 | AB754: 891466 | AC754: 34.913 | AD754: 34.08975 | AE754: =IFERROR(AB754/AD754,0) -> 26150.558 | AF754: =K754-S754-X754 -> 0 | AG754: =S754-AB754 -> 0 | AH754: 919036.56 | AI754: =IFERROR(AH754/S754,0) -> 1.0309272 | AJ754: 3.8424044e+08 | AK754: =IF(AJ754>0,AprCoef/SQRT(AJ754),0) -> 0.024181142 | AL754: =AJ754*AK754/365 -> 25455.815 | AM754: =AE754 -> 26150.558 | AN754: =AL754-AM754 -> -694.74316 | AO754: =IF(A754>=Hip3LaunchDate,"YES","") | AP754: =IF(A754<Hip4LaunchDate,"pre-launch","live (zero-fee)") -> pre-launch
A755: 45816 | B755: 3.1217007e+09 | C755: 0 | D755: 151362843 | E755: =B755+C755 -> 3.1217007e+09 | F755: =E755+D755 -> 3.2730635e+09 | G755: =IFERROR(C755/E755,0) -> 0 | K755: =H755+I755 -> 0 | O755: =IF(H755=0,0,H755-L755) -> 0 | P755: =IF(B755=0,0,O755/B755*10000) -> 0 | S755: =Q755+R755 -> 0 | T755: =IF(A755<HlpChangeDate,HlpSharePre,HlpSharePost) -> 0.03 | U755: =S755*T755/(1-T755) -> 0 | W755: =U755-V755 -> 0 | X755: =Y755+Z755 -> 0 | AA755: =X755-V755 -> 0 | AB755: 0 | AC755: 34.983 | AD755: 35.171 | AE755: =IFERROR(AB755/AD755,0) -> 0 | AF755: =K755-S755-X755 -> 0 | AG755: =S755-AB755 -> 0 | AH755: 278826.03 | AI755: =IFERROR(AH755/S755,0) -> 0 | AJ755: 3.8437705e+08 | AK755: =IF(AJ755>0,AprCoef/SQRT(AJ755),0) -> 0.024176845 | AL755: =AJ755*AK755/365 -> 25460.34 | AM755: =AE755 -> 0 | AN755: =AL755-AM755 -> 25460.34 | AO755: =IF(A755>=Hip3LaunchDate,"YES","") | AP755: =IF(A755<Hip4LaunchDate,"pre-launch","live (zero-fee)") -> pre-launch
A756: 45817 | B756: 7.9469529e+09 | C756: 0 | D756: 359240055 | E756: =B756+C756 -> 7.9469529e+09 | F756: =E756+D756 -> 8.306193e+09 | G756: =IFERROR(C756/E756,0) -> 0 | K756: =H756+I756 -> 0 | O756: =IF(H756=0,0,H756-L756) -> 0 | P756: =IF(B756=0,0,O756/B756*10000) -> 0 | S756: =Q756+R756 -> 0 | T756: =IF(A756<HlpChangeDate,HlpSharePre,HlpSharePost) -> 0.03 | U756: =S756*T756/(1-T756) -> 0 | W756: =U756-V756 -> 0 | X756: =Y756+Z756 -> 0 | AA756: =X756-V756 -> 0 | AB756: 0 | AC756: 38.855 | AD756: 36.87175 | AE756: =IFERROR(AB756/AD756,0) -> 0 | AF756: =K756-S756-X756 -> 0 | AG756: =S756-AB756 -> 0 | AH756: 3169213.6 | AI756: =IFERROR(AH756/S756,0) -> 0 | AJ756: 3.8451366e+08 | AK756: =IF(AJ756>0,AprCoef/SQRT(AJ756),0) -> 0.024172549 | AL756: =AJ756*AK756/365 -> 25464.864 | AM756: =AE756 -> 0 | AN756: =AL756-AM756 -> 25464.864 | AO756: =IF(A756>=Hip3LaunchDate,"YES","") | AP756: =IF(A756<Hip4LaunchDate,"pre-launch","live (zero-fee)") -> pre-launch
A757: 45818 | B757: 8.8680623e+09 | C757: 0 | D757: 493501254 | E757: =B757+C757 -> 8.8680623e+09 | F757: =E757+D757 -> 9.3615636e+09 | G757: =IFERROR(C757/E757,0) -> 0 | H757: 2654323 | I757: 115467 | J757: 83094 | K757: =H757+I757 -> 2769790 | O757: =IF(H757=0,0,H757-L757) -> 2654323 | P757: =IF(B757=0,0,O757/B757*10000) -> 2.9931262 | Q757: 2574693 | R757: 112003 | S757: =Q757+R757 -> 2686696 | T757: =IF(A757<HlpChangeDate,HlpSharePre,HlpSharePost) -> 0.03 | U757: =S757*T757/(1-T757) -> 83093.691 | V757: 83094 | W757: =U757-V757 -> -0.30927835 | X757: =Y757+Z757 -> 83094 | Y757: 79630 | Z757: 3464 | AA757: =X757-V757 -> 0 | AB757: 2686696 | AC757: 42.186 | AD757: 40.454 | AE757: =IFERROR(AB757/AD757,0) -> 66413.606 | AF757: =K757-S757-X757 -> 0 | AG757: =S757-AB757 -> 0 | AH757: 2769790.3 | AI757: =IFERROR(AH757/S757,0) -> 1.030928 | AJ757: 3.8465027e+08 | AK757: =IF(AJ757>0,AprCoef/SQRT(AJ757),0) -> 0.024168256 | AL757: =AJ757*AK757/365 -> 25469.387 | AM757: =AE757 -> 66413.606 | AN757: =AL757-AM757 -> -40944.218 | AO757: =IF(A757>=Hip3LaunchDate,"YES","") | AP757: =IF(A757<Hip4LaunchDate,"pre-launch","live (zero-fee)") -> pre-launch
A758: 45819 | B758: 8.8808494e+09 | C758: 0 | D758: 491823654 | E758: =B758+C758 -> 8.8808494e+09 | F758: =E758+D758 -> 9.372673e+09 | G758: =IFERROR(C758/E758,0) -> 0 | H758: 2653604 | I758: 105920 | J758: 82298 | K758: =H758+I758 -> 2759524 | O758: =IF(H758=0,0,H758-L758) -> 2653604 | P758: =IF(B758=0,0,O758/B758*10000) -> 2.988007 | Q758: 2573996 | R758: 102743 | S758: =Q758+R758 -> 2676739 | T758: =IF(A758<HlpChangeDate,HlpSharePre,HlpSharePost) -> 0.03 | U758: =S758*T758/(1-T758) -> 82785.742 | V758: 82298 | W758: =U758-V758 -> 487.74227 | X758: =Y758+Z758 -> 82786 | Y758: 79608 | Z758: 3178 | AA758: =X758-V758 -> 488 | AB758: 2676739 | AC758: 41.805 | AD758: 42.156 | AE758: =IFERROR(AB758/AD758,0) -> 63496.039 | AF758: =K758-S758-X758 -> -1 | AG758: =S758-AB758 -> 0 | AH758: 2743278.6 | AI758: =IFERROR(AH758/S758,0) -> 1.0248585 | AJ758: 3.8478689e+08 | AK758: =IF(AJ758>0,AprCoef/SQRT(AJ758),0) -> 0.024163966 | AL758: =AJ758*AK758/365 -> 25473.91 | AM758: =AE758 -> 63496.039 | AN758: =AL758-AM758 -> -38022.129 | AO758: =IF(A758>=Hip3LaunchDate,"YES","") | AP758: =IF(A758<Hip4LaunchDate,"pre-launch","live (zero-fee)") -> pre-launch
A759: 45820 | B759: 9.8599768e+09 | C759: 0 | D759: 499156091 | E759: =B759+C759 -> 9.8599768e+09 | F759: =E759+D759 -> 1.0359133e+10 | G759: =IFERROR(C759/E759,0) -> 0 | H759: 2909648 | I759: 95479 | J759: 90641 | K759: =H759+I759 -> 3005127 | O759: =IF(H759=0,0,H759-L759) -> 2909648 | P759: =IF(B759=0,0,O759/B759*10000) -> 2.9509684 | Q759: 2822358 | R759: 92615 | S759: =Q759+R759 -> 2914973 | T759: =IF(A759<HlpChangeDate,HlpSharePre,HlpSharePost) -> 0.03 | U759: =S759*T759/(1-T759) -> 90153.804 | V759: 90641 | W759: =U759-V759 -> -487.19588 | X759: =Y759+Z759 -> 90153 | Y759: 87289 | Z759: 2864 | AA759: =X759-V759 -> -488 | AB759: 2914973 | AC759: 40.509 | AD759: 41.621 | AE759: =IFERROR(AB759/AD759,0) -> 70036.112 | AF759: =K759-S759-X759 -> 1 | AG759: =S759-AB759 -> 0 | AH759: 3021373.1 | AI759: =IFERROR(AH759/S759,0) -> 1.0365012 | AJ759: 3.849235e+08 | AK759: =IF(AJ759>0,AprCoef/SQRT(AJ759),0) -> 0.024159677 | AL759: =AJ759*AK759/365 -> 25478.432 | AM759: =AE759 -> 70036.112 | AN759: =AL759-AM759 -> -44557.68 | AO759: =IF(A759>=Hip3LaunchDate,"YES","") | AP759: =IF(A759<Hip4LaunchDate,"pre-launch","live (zero-fee)") -> pre-launch
A760: 45821 | B760: 1.3286057e+10 | C760: 0 | D760: 642044619 | E760: =B760+C760 -> 1.3286057e+10 | F760: =E760+D760 -> 1.3928101e+10 | G760: =IFERROR(C760/E760,0) -> 0 | H760: 3887429 | I760: 148721 | J760: 120410 | K760: =H760+I760 -> 4036150 | O760: =IF(H760=0,0,H760-L760) -> 3887429 | P760: =IF(B760=0,0,O760/B760*10000) -> 2.9259464 | Q760: 3770806 | R760: 144260 | S760: =Q760+R760 -> 3915066 | T760: =IF(A760<HlpChangeDate,HlpSharePre,HlpSharePost) -> 0.03 | U760: =S760*T760/(1-T760) -> 121084.52 | V760: 120410 | W760: =U760-V760 -> 674.51546 | X760: =Y760+Z760 -> 121085 | Y760: 116623 | Z760: 4462 | AA760: =X760-V760 -> 675 | AB760: 3915066 | AC760: 42.277 | AD760: 40.66175 | AE760: =IFERROR(AB760/AD760,0) -> 96283.756 | AF760: =K760-S760-X760 -> -1 | AG760: =S760-AB760 -> 0 | AH760: 4013650.9 | AI760: =IFERROR(AH760/S760,0) -> 1.0251809 | AJ760: 3.8506011e+08 | AK760: =IF(AJ760>0,AprCoef/SQRT(AJ760),0) -> 0.024155391 | AL760: =AJ760*AK760/365 -> 25482.952 | AM760: =AE760 -> 96283.756 | AN760: =AL760-AM760 -> -70800.803 | AO760: =IF(A760>=Hip3LaunchDate,"YES","") | AP760: =IF(A760<Hip4LaunchDate,"pre-launch","live (zero-fee)") -> pre-launch
A761: 45822 | B761: 4.4904691e+09 | C761: 0 | D761: 223313776 | E761: =B761+C761 -> 4.4904691e+09 | F761: =E761+D761 -> 4.7137829e+09 | G761: =IFERROR(C761/E761,0) -> 0 | H761: 1261527 | I761: 53146 | J761: 39815 | K761: =H761+I761 -> 1314673 | O761: =IF(H761=0,0,H761-L761) -> 1261527 | P761: =IF(B761=0,0,O761/B761*10000) -> 2.8093434 | Q761: 1223682 | R761: 51552 | S761: =Q761+R761 -> 1275234 | T761: =IF(A761<HlpChangeDate,HlpSharePre,HlpSharePost) -> 0.03 | U761: =S761*T761/(1-T761) -> 39440.227 | V761: 39815 | W761: =U761-V761 -> -374.7732 | X761: =Y761+Z761 -> 39440 | Y761: 37846 | Z761: 1594 | AA761: =X761-V761 -> -375 | AB761: 1275234 | AC761: 40.107 | AD761: 40.9635 | AE761: =IFERROR(AB761/AD761,0) -> 31130.982 | AF761: =K761-S761-X761 -> -1 | AG761: =S761-AB761 -> 0 | AH761: 1327158.2 | AI761: =IFERROR(AH761/S761,0) -> 1.0407174 | AJ761: 3.8519672e+08 | AK761: =IF(AJ761>0,AprCoef/SQRT(AJ761),0) -> 0.024151107 | AL761: =AJ761*AK761/365 -> 25487.472 | AM761: =AE761 -> 31130.982 | AN761: =AL761-AM761 -> -5643.5101 | AO761: =IF(A761>=Hip3LaunchDate,"YES","") | AP761: =IF(A761<Hip4LaunchDate,"pre-launch","live (zero-fee)") -> pre-launch
A762: 45823 | B762: 4.1205593e+09 | C762: 0 | D762: 208088792 | E762: =B762+C762 -> 4.1205593e+09 | F762: =E762+D762 -> 4.3286481e+09 | G762: =IFERROR(C762/E762,0) -> 0 | H762: 1158797 | I762: 39647 | J762: 36254 | K762: =H762+I762 -> 1198444 | O762: =IF(H762=0,0,H762-L762) -> 1158797 | P762: =IF(B762=0,0,O762/B762*10000) -> 2.8122323 | Q762: 1124033 | R762: 38458 | S762: =Q762+R762 -> 1162491 | T762: =IF(A762<HlpChangeDate,HlpSharePre,HlpSharePost) -> 0.03 | U762: =S762*T762/(1-T762) -> 35953.33 | V762: 36254 | W762: =U762-V762 -> -300.6701 | X762: =Y762+Z762 -> 35953 | Y762: 34764 | Z762: 1189 | AA762: =X762-V762 -> -301 | AB762: 1162491 | AC762: 41.166 | AD762: 40.5925 | AE762: =IFERROR(AB762/AD762,0) -> 28638.074 | AF762: =K762-S762-X762 -> 0 | AG762: =S762-AB762 -> 0 | AH762: 1208458.3 | AI762: =IFERROR(AH762/S762,0) -> 1.0395421 | AJ762: 3.8533333e+08 | AK762: =IF(AJ762>0,AprCoef/SQRT(AJ762),0) -> 0.024146826 | AL762: =AJ762*AK762/365 -> 25491.992 | AM762: =AE762 -> 28638.074 | AN762: =AL762-AM762 -> -3146.0819 | AO762: =IF(A762>=Hip3LaunchDate,"YES","") | AP762: =IF(A762<Hip4LaunchDate,"pre-launch","live (zero-fee)") -> pre-launch
A763: 45824 | B763: 9.9104451e+09 | C763: 0 | D763: 500000932 | E763: =B763+C763 -> 9.9104451e+09 | F763: =E763+D763 -> 1.0410446e+10 | G763: =IFERROR(C763/E763,0) -> 0 | H763: 2838831 | I763: 103884 | J763: 86131 | K763: =H763+I763 -> 2942715 | O763: =IF(H763=0,0,H763-L763) -> 2838831 | P763: =IF(B763=0,0,O763/B763*10000) -> 2.8644839 | Q763: 2753666 | R763: 100767 | S763: =Q763+R763 -> 2854433 | T763: =IF(A763<HlpChangeDate,HlpSharePre,HlpSharePost) -> 0.03 | U763: =S763*T763/(1-T763) -> 88281.433 | V763: 86131 | W763: =U763-V763 -> 2150.433 | X763: =Y763+Z763 -> 88282 | Y763: 85165 | Z763: 3117 | AA763: =X763-V763 -> 2151 | AB763: 2854433 | AC763: 41.899 | AD763: 42.375 | AE763: =IFERROR(AB763/AD763,0) -> 67361.251 | AF763: =K763-S763-X763 -> 0 | AG763: =S763-AB763 -> 0 | AH763: 2871026.7 | AI763: =IFERROR(AH763/S763,0) -> 1.0058133 | AJ763: 3.8546995e+08 | AK763: =IF(AJ763>0,AprCoef/SQRT(AJ763),0) -> 0.024142547 | AL763: =AJ763*AK763/365 -> 25496.51 | AM763: =AE763 -> 67361.251 | AN763: =AL763-AM763 -> -41864.741 | AO763: =IF(A763>=Hip3LaunchDate,"YES","") | AP763: =IF(A763<Hip4LaunchDate,"pre-launch","live (zero-fee)") -> pre-launch
A764: 45825 | B764: 1.1324626e+10 | C764: 0 | D764: 481779486 | E764: =B764+C764 -> 1.1324626e+10 | F764: =E764+D764 -> 1.1806405e+10 | G764: =IFERROR(C764/E764,0) -> 0 | H764: 3268752 | I764: 119116 | J764: 103787 | K764: =H764+I764 -> 3387868 | O764: =IF(H764=0,0,H764-L764) -> 3268752 | P764: =IF(B764=0,0,O764/B764*10000) -> 2.8864106 | Q764: 3170689 | R764: 115542 | S764: =Q764+R764 -> 3286231 | T764: =IF(A764<HlpChangeDate,HlpSharePre,HlpSharePost) -> 0.03 | U764: =S764*T764/(1-T764) -> 101636.01 | V764: 103787 | W764: =U764-V764 -> -2150.9897 | X764: =Y764+Z764 -> 101636 | Y764: 98063 | Z764: 3573 | AA764: =X764-V764 -> -2151 | AB764: 3286231 | AC764: 39.98 | AD764: 40.90975 | AE764: =IFERROR(AB764/AD764,0) -> 80328.797 | AF764: =K764-S764-X764 -> 1 | AG764: =S764-AB764 -> 0 | AH764: 3459555.5 | AI764: =IFERROR(AH764/S764,0) -> 1.0527426 | AJ764: 3.8560656e+08 | AK764: =IF(AJ764>0,AprCoef/SQRT(AJ764),0) -> 0.02413827 | AL764: =AJ764*AK764/365 -> 25501.028 | AM764: =AE764 -> 80328.797 | AN764: =AL764-AM764 -> -54827.769 | AO764: =IF(A764>=Hip3LaunchDate,"YES","") | AP764: =IF(A764<Hip4LaunchDate,"pre-launch","live (zero-fee)") -> pre-launch
A765: 45826 | B765: 7.99953e+09 | C765: 0 | D765: 420606916 | E765: =B765+C765 -> 7.99953e+09 | F765: =E765+D765 -> 8.4201369e+09 | G765: =IFERROR(C765/E765,0) -> 0 | H765: 2288124 | I765: 88887 | J765: 71154 | K765: =H765+I765 -> 2377011 | O765: =IF(H765=0,0,H765-L765) -> 2288124 | P765: =IF(B765=0,0,O765/B765*10000) -> 2.860323 | Q765: 2219481 | R765: 86220 | S765: =Q765+R765 -> 2305701 | T765: =IF(A765<HlpChangeDate,HlpSharePre,HlpSharePost) -> 0.03 | U765: =S765*T765/(1-T765) -> 71310.34 | V765: 71154 | W765: =U765-V765 -> 156.34021 | X765: =Y765+Z765 -> 71311 | Y765: 68644 | Z765: 2667 | AA765: =X765-V765 -> 157 | AB765: 2305701 | AC765: 39.45 | AD765: 39.52 | AE765: =IFERROR(AB765/AD765,0) -> 58342.637 | AF765: =K765-S765-X765 -> -1 | AG765: =S765-AB765 -> 0 | AH765: 2371798.7 | AI765: =IFERROR(AH765/S765,0) -> 1.0286671 | AJ765: 3.8574317e+08 | AK765: =IF(AJ765>0,AprCoef/SQRT(AJ765),0) -> 0.024133995 | AL765: =AJ765*AK765/365 -> 25505.545 | AM765: =AE765 -> 58342.637 | AN765: =AL765-AM765 -> -32837.092 | AO765: =IF(A765>=Hip3LaunchDate,"YES","") | AP765: =IF(A765<Hip4LaunchDate,"pre-launch","live (zero-fee)") -> pre-launch
A766: 45827 | B766: 5.3097062e+09 | C766: 0 | D766: 309275966 | E766: =B766+C766 -> 5.3097062e+09 | F766: =E766+D766 -> 5.6189821e+09 | G766: =IFERROR(C766/E766,0) -> 0 | H766: 1469442 | I766: 73911 | J766: 46457 | K766: =H766+I766 -> 1543353 | O766: =IF(H766=0,0,H766-L766) -> 1469442 | P766: =IF(B766=0,0,O766/B766*10000) -> 2.7674639 | Q766: 1425358 | R766: 71693 | S766: =Q766+R766 -> 1497051 | T766: =IF(A766<HlpChangeDate,HlpSharePre,HlpSharePost) -> 0.03 | U766: =S766*T766/(1-T766) -> 46300.546 | V766: 46457 | W766: =U766-V766 -> -156.45361 | X766: =Y766+Z766 -> 46300 | Y766: 44083 | Z766: 2217 | AA766: =X766-V766 -> -157 | AB766: 1497051 | AC766: 36.872 | AD766: 38.016 | AE766: =IFERROR(AB766/AD766,0) -> 39379.498 | AF766: =K766-S766-X766 -> 2 | AG766: =S766-AB766 -> 0 | AH766: 1548564.8 | AI766: =IFERROR(AH766/S766,0) -> 1.0344102 | AJ766: 3.8587978e+08 | AK766: =IF(AJ766>0,AprCoef/SQRT(AJ766),0) -> 0.024129723 | AL766: =AJ766*AK766/365 -> 25510.061 | AM766: =AE766 -> 39379.498 | AN766: =AL766-AM766 -> -13869.438 | AO766: =IF(A766>=Hip3LaunchDate,"YES","") | AP766: =IF(A766<Hip4LaunchDate,"pre-launch","live (zero-fee)") -> pre-launch
A767: 45828 | B767: 8.9847656e+09 | C767: 0 | D767: 390870684 | E767: =B767+C767 -> 8.9847656e+09 | F767: =E767+D767 -> 9.3756363e+09 | G767: =IFERROR(C767/E767,0) -> 0 | H767: 2544445 | I767: 93536 | J767: 79000 | K767: =H767+I767 -> 2637981 | O767: =IF(H767=0,0,H767-L767) -> 2544445 | P767: =IF(B767=0,0,O767/B767*10000) -> 2.8319548 | Q767: 2468112 | R767: 90730 | S767: =Q767+R767 -> 2558842 | T767: =IF(A767<HlpChangeDate,HlpSharePre,HlpSharePost) -> 0.03 | U767: =S767*T767/(1-T767) -> 79139.443 | V767: 79000 | W767: =U767-V767 -> 139.4433 | X767: =Y767+Z767 -> 79139 | Y767: 76333 | Z767: 2806 | AA767: =X767-V767 -> 139 | AB767: 2558842 | AC767: 33.338 | AD767: 35.29225 | AE767: =IFERROR(AB767/AD767,0) -> 72504.36 | AF767: =K767-S767-X767 -> 0 | AG767: =S767-AB767 -> 0 | AH767: 2633335.6 | AI767: =IFERROR(AH767/S767,0) -> 1.0291122 | AJ767: 3.8601639e+08 | AK767: =IF(AJ767>0,AprCoef/SQRT(AJ767),0) -> 0.024125452 | AL767: =AJ767*AK767/365 -> 25514.576 | AM767: =AE767 -> 72504.36 | AN767: =AL767-AM767 -> -46989.784 | AO767: =IF(A767>=Hip3LaunchDate,"YES","") | AP767: =IF(A767<Hip4LaunchDate,"pre-launch","live (zero-fee)") -> pre-launch
A768: 45829 | B768: 5.8535617e+09 | C768: 0 | D768: 325856019 | E768: =B768+C768 -> 5.8535617e+09 | F768: =E768+D768 -> 6.1794177e+09 | G768: =IFERROR(C768/E768,0) -> 0 | H768: 1614659 | I768: 69112 | J768: 50652 | K768: =H768+I768 -> 1683771 | O768: =IF(H768=0,0,H768-L768) -> 1614659 | P768: =IF(B768=0,0,O768/B768*10000) -> 2.7584214 | Q768: 1566219 | R768: 67039 | S768: =Q768+R768 -> 1633258 | T768: =IF(A768<HlpChangeDate,HlpSharePre,HlpSharePost) -> 0.03 | U768: =S768*T768/(1-T768) -> 50513.134 | V768: 50652 | W768: =U768-V768 -> -138.86598 | X768: =Y768+Z768 -> 50513 | Y768: 48440 | Z768: 2073 | AA768: =X768-V768 -> -139 | AB768: 1633258 | AC768: 34.396 | AD768: 33.5625 | AE768: =IFERROR(AB768/AD768,0) -> 48663.181 | AF768: =K768-S768-X768 -> 0 | AG768: =S768-AB768 -> 0 | AH768: 1688416.6 | AI768: =IFERROR(AH768/S768,0) -> 1.0337721 | AJ768: 3.8615301e+08 | AK768: =IF(AJ768>0,AprCoef/SQRT(AJ768),0) -> 0.024121185 | AL768: =AJ768*AK768/365 -> 25519.09 | AM768: =AE768 -> 48663.181 | AN768: =AL768-AM768 -> -23144.09 | AO768: =IF(A768>=Hip3LaunchDate,"YES","") | AP768: =IF(A768<Hip4LaunchDate,"pre-launch","live (zero-fee)") -> pre-launch
... A881: 45942 | B881: 1.1787565e+10 | C881: 0 | D881: 484211693 | E881: =B881+C881 -> 1.1787565e+10 | F881: =E881+D881 -> 1.2271776e+10 | G881: =IFERROR(C881/E881,0) -> 0 | H881: 3799559 | I881: 257362 | J881: 36538 | K881: =H881+I881 -> 4056921 | O881: =IF(H881=0,0,H881-L881) -> 3799559 | P881: =IF(B881=0,0,O881/B881*10000) -> 3.2233622 | Q881: 3440902 | R881: 176358 | S881: =Q881+R881 -> 3617260 | T881: =IF(A881<HlpChangeDate,HlpSharePre,HlpSharePost) -> 0.01 | U881: =S881*T881/(1-T881) -> 36537.98 | V881: 36538 | W881: =U881-V881 -> -0.02020202 | X881: =Y881+Z881 -> 439661 | Y881: 358657 | Z881: 81004 | AA881: =X881-V881 -> 403123 | AB881: 3617260 | AC881: 39.651 | AD881: 38.37225 | AE881: =IFERROR(AB881/AD881,0) -> 94267.602 | AF881: =K881-S881-X881 -> 0 | AG881: =S881-AB881 -> 0 | AH881: 3306971.2 | AI881: =IFERROR(AH881/S881,0) -> 0.91421993 | AJ881: 4.0159016e+08 | AK881: =IF(AJ881>0,AprCoef/SQRT(AJ881),0) -> 0.023653031 | AL881: =AJ881*AK881/365 -> 26024.177 | AM881: =AE881 -> 94267.602 | AN881: =AL881-AM881 -> -68243.425 | AO881: =IF(A881>=Hip3LaunchDate,"YES","") | AP881: =IF(A881<Hip4LaunchDate,"pre-launch","live (zero-fee)") -> pre-launch
A882: 45943 | B882: 9.5875348e+09 | C882: 24137313 | D882: 433769946 | E882: =B882+C882 -> 9.6116721e+09 | F882: =E882+D882 -> 1.0045442e+10 | G882: =IFERROR(C882/E882,0) -> 0.0025112501 | H882: 2991680 | I882: 217963 | J882: 28869 | K882: =H882+I882 -> 3209643 | L882: 13661.719 | M882: 6830.8595 | N882: 6830.8595 | O882: =IF(H882=0,0,H882-L882) -> 2978018.3 | P882: =IF(B882=0,0,O882/B882*10000) -> 3.1061356 | Q882: 2695086 | R882: 162992 | S882: =Q882+R882 -> 2858078 | T882: =IF(A882<HlpChangeDate,HlpSharePre,HlpSharePost) -> 0.01 | U882: =S882*T882/(1-T882) -> 28869.475 | V882: 28869 | W882: =U882-V882 -> 0.47474747 | X882: =Y882+Z882 -> 351565 | Y882: 296594 | Z882: 54971 | AA882: =X882-V882 -> 322696 | AB882: 2858078 | AC882: 42.489 | AD882: 40.98825 | AE882: =IFERROR(AB882/AD882,0) -> 69729.203 | AF882: =K882-S882-X882 -> 0 | AG882: =S882-AB882 -> 0 | AH882: 2766599.5 | AI882: =IFERROR(AH882/S882,0) -> 0.96799298 | AJ882: 4.0172678e+08 | AK882: =IF(AJ882>0,AprCoef/SQRT(AJ882),0) -> 0.023649009 | AL882: =AJ882*AK882/365 -> 26028.603 | AM882: =AE882 -> 69729.203 | AN882: =AL882-AM882 -> -43700.599 | AO882: =IF(A882>=Hip3LaunchDate,"YES","") -> YES | AP882: =IF(A882<Hip4LaunchDate,"pre-launch","live (zero-fee)") -> pre-launch | AQ882: 1 | AR882: 0
...

Sheet HIP-3 Model
A1: HIP-3 Per-Asset Fee Model
A2: Formula: effective_bps = CoreBpsBlended × scaleIfHip3 × growthModeFactor. Gross fee $ = vol × bps/10000.
A4: PER-ASSET METADATA (snapshot from Hyperliquid info API)
A5: Asset | B5: Dex | C5: deployerFeeScale | D5: scaleIfHip3 | E5: deployerShare | F5: growthModeFinal | G5: gmChangeDate | H5: Effective bps (if GM active) | I5: Effective bps (if GM inactive)
A6: abcd:USA500 | B6: abcd | C6: 1 | D6: 2 | E6: 0.5 | F6: N/A | H6: =CoreBpsBlended*D6*GrowthModeFactor -> 0.5794 | I6: =CoreBpsBlended*D6 -> 5.794
A7: cash:AMZN | B7: cash | C7: 1 | D7: 2 | E7: 0.5 | F7: enabled | G7: 46049 | H7: =CoreBpsBlended*D7*GrowthModeFactor -> 0.5794 | I7: =CoreBpsBlended*D7 -> 5.794
A8: cash:BTC | B8: cash | C8: 1 | D8: 2 | E8: 0.5 | F8: N/A | H8: =CoreBpsBlended*D8*GrowthModeFactor -> 0.5794 | I8: =CoreBpsBlended*D8 -> 5.794
A9: cash:CAR | B9: cash | C9: 1 | D9: 2 | E9: 0.5 | F9: enabled | G9: 46141 | H9: =CoreBpsBlended*D9*GrowthModeFactor -> 0.5794 | I9: =CoreBpsBlended*D9 -> 5.794
A10: cash:ETH | B10: cash | C10: 1 | D10: 2 | E10: 0.5 | F10: N/A | H10: =CoreBpsBlended*D10*GrowthModeFactor -> 0.5794 | I10: =CoreBpsBlended*D10 -> 5.794
A11: cash:EWY | B11: cash | C11: 1 | D11: 2 | E11: 0.5 | F11: enabled | G11: 46079 | H11: =CoreBpsBlended*D11*GrowthModeFactor -> 0.5794 | I11: =CoreBpsBlended*D11 -> 5.794
A12: cash:GOLD | B12: cash | C12: 1 | D12: 2 | E12: 0.5 | F12: N/A | H12: =CoreBpsBlended*D12*GrowthModeFactor -> 0.5794 | I12: =CoreBpsBlended*D12 -> 5.794
A13: cash:GOOGL | B13: cash | C13: 1 | D13: 2 | E13: 0.5 | F13: enabled | G13: 46049 | H13: =CoreBpsBlended*D13*GrowthModeFactor -> 0.5794 | I13: =CoreBpsBlended*D13 -> 5.794
A14: cash:HOOD | B14: cash | C14: 1 | D14: 2 | E14: 0.5 | F14: enabled | G14: 46049 | H14: =CoreBpsBlended*D14*GrowthModeFactor -> 0.5794 | I14: =CoreBpsBlended*D14 -> 5.794
A15: cash:INTC | B15: cash | C15: 1 | D15: 2 | E15: 0.5 | F15: enabled | G15: 46049 | H15: =CoreBpsBlended*D15*GrowthModeFactor -> 0.5794 | I15: =CoreBpsBlended*D15 -> 5.794
A16: cash:KWEB | B16: cash | C16: 1 | D16: 2 | E16: 0.5 | F16: enabled | G16: 46099 | H16: =CoreBpsBlended*D16*GrowthModeFactor -> 0.5794 | I16: =CoreBpsBlended*D16 -> 5.794
A17: cash:META | B17: cash | C17: 1 | D17: 2 | E17: 0.5 | F17: enabled | G17: 46049 | H17: =CoreBpsBlended*D17*GrowthModeFactor -> 0.5794 | I17: =CoreBpsBlended*D17 -> 5.794
A18: cash:MSFT | B18: cash | C18: 1 | D18: 2 | E18: 0.5 | F18: enabled | G18: 46049 | H18: =CoreBpsBlended*D18*GrowthModeFactor -> 0.5794 | I18: =CoreBpsBlended*D18 -> 5.794
A19: cash:NVDA | B19: cash | C19: 1 | D19: 2 | E19: 0.5 | F19: enabled | G19: 46045 | H19: =CoreBpsBlended*D19*GrowthModeFactor -> 0.5794 | I19: =CoreBpsBlended*D19 -> 5.794
A20: cash:SILVER | B20: cash | C20: 1 | D20: 2 | E20: 0.5 | F20: enabled | G20: 46059 | H20: =CoreBpsBlended*D20*GrowthModeFactor -> 0.5794 | I20: =CoreBpsBlended*D20 -> 5.794
A21: cash:TSLA | B21: cash | C21: 1 | D21: 2 | E21: 0.5 | F21: enabled | G21: 46044 | H21: =CoreBpsBlended*D21*GrowthModeFactor -> 0.5794 | I21: =CoreBpsBlended*D21 -> 5.794
A22: cash:USA500 | B22: cash | C22: 1 | D22: 2 | E22: 0.5 | F22: enabled | G22: 46042 | H22: =CoreBpsBlended*D22*GrowthModeFactor -> 0.5794 | I22: =CoreBpsBlended*D22 -> 5.794
A23: cash:WTI | B23: cash | C23: 1 | D23: 2 | E23: 0.5 | F23: enabled | G23: 46092 | H23: =CoreBpsBlended*D23*GrowthModeFactor -> 0.5794 | I23: =CoreBpsBlended*D23 -> 5.794
A24: flx:BTC | B24: flx | C24: 1 | D24: 2 | E24: 0.5 | F24: N/A | H24: =CoreBpsBlended*D24*GrowthModeFactor -> 0.5794 | I24: =CoreBpsBlended*D24 -> 5.794
A25: flx:COIN | B25: flx | C25: 1 | D25: 2 | E25: 0.5 | F25: enabled | G25: 45985 | H25: =CoreBpsBlended*D25*GrowthModeFactor -> 0.5794 | I25: =CoreBpsBlended*D25 -> 5.794
A26: flx:COPPER | B26: flx | C26: 1 | D26: 2 | E26: 0.5 | F26: enabled | G26: 46051 | H26: =CoreBpsBlended*D26*GrowthModeFactor -> 0.5794 | I26: =CoreBpsBlended*D26 -> 5.794
A27: flx:CRCL | B27: flx | C27: 1 | D27: 2 | E27: 0.5 | F27: enabled | G27: 45985 | H27: =CoreBpsBlended*D27*GrowthModeFactor -> 0.5794 | I27: =CoreBpsBlended*D27 -> 5.794
A28: flx:GAS | B28: flx | C28: 1 | D28: 2 | E28: 0.5 | F28: enabled | G28: 46112 | H28: =CoreBpsBlended*D28*GrowthModeFactor -> 0.5794 | I28: =CoreBpsBlended*D28 -> 5.794
A29: flx:GOLD | B29: flx | C29: 1 | D29: 2 | E29: 0.5 | F29: N/A | H29: =CoreBpsBlended*D29*GrowthModeFactor -> 0.5794 | I29: =CoreBpsBlended*D29 -> 5.794
A30: flx:NVDA | B30: flx | C30: 1 | D30: 2 | E30: 0.5 | F30: enabled | G30: 46089 | H30: =CoreBpsBlended*D30*GrowthModeFactor -> 0.5794 | I30: =CoreBpsBlended*D30 -> 5.794
A31: flx:OIL | B31: flx | C31: 1 | D31: 2 | E31: 0.5 | F31: enabled | G31: 46051 | H31: =CoreBpsBlended*D31*GrowthModeFactor -> 0.5794 | I31: =CoreBpsBlended*D31 -> 5.794
A32: flx:PALLADIUM | B32: flx | C32: 1 | D32: 2 | E32: 0.5 | F32: enabled | G32: 46051 | H32: =CoreBpsBlended*D32*GrowthModeFactor -> 0.5794 | I32: =CoreBpsBlended*D32 -> 5.794
A33: flx:PLATINUM | B33: flx | C33: 1 | D33: 2 | E33: 0.5 | F33: enabled | G33: 46051 | H33: =CoreBpsBlended*D33*GrowthModeFactor -> 0.5794 | I33: =CoreBpsBlended*D33 -> 5.794
A34: flx:SILVER | B34: flx | C34: 1 | D34: 2 | E34: 0.5 | F34: enabled | G34: 46051 | H34: =CoreBpsBlended*D34*GrowthModeFactor -> 0.5794 | I34: =CoreBpsBlended*D34 -> 5.794
A35: flx:TSLA | B35: flx | C35: 1 | D35: 2 | E35: 0.5 | F35: enabled | G35: 45985 | H35: =CoreBpsBlended*D35*GrowthModeFactor -> 0.5794 | I35: =CoreBpsBlended*D35 -> 5.794
A36: flx:USA100 | B36: flx | C36: 1 | D36: 2 | E36: 0.5 | F36: enabled | G36: 46111 | H36: =CoreBpsBlended*D36*GrowthModeFactor -> 0.5794 | I36: =CoreBpsBlended*D36 -> 5.794
A37: flx:USA500 | B37: flx | C37: 1 | D37: 2 | E37: 0.5 | F37: enabled | G37: 46091 | H37: =CoreBpsBlended*D37*GrowthModeFactor -> 0.5794 | I37: =CoreBpsBlended*D37 -> 5.794
A38: flx:USDE | B38: flx | C38: 1 | D38: 2 | E38: 0.5 | F38: N/A | H38: =CoreBpsBlended*D38*GrowthModeFactor -> 0.5794 | I38: =CoreBpsBlended*D38 -> 5.794
A39: flx:XMR | B39: flx | C39: 1 | D39: 2 | E39: 0.5 | F39: N/A | H39: =CoreBpsBlended*D39*GrowthModeFactor -> 0.5794 | I39: =CoreBpsBlended*D39 -> 5.794
A40: hyna:1000PEPE | B40: hyna | C40: 0.1111 | D40: 1.1111 | E40: 0.099991 | F40: N/A | H40: =CoreBpsBlended*D40*GrowthModeFactor -> 0.32188567 | I40: =CoreBpsBlended*D40 -> 3.2188567
A41: hyna:ADA | B41: hyna | C41: 0.1111 | D41: 1.1111 | E41: 0.099991 | F41: N/A | H41: =CoreBpsBlended*D41*GrowthModeFactor -> 0.32188567 | I41: =CoreBpsBlended*D41 -> 3.2188567
A42: hyna:BASED | B42: hyna | C42: 0.1111 | D42: 1.1111 | E42: 0.099991 | F42: N/A | H42: =CoreBpsBlended*D42*GrowthModeFactor -> 0.32188567 | I42: =CoreBpsBlended*D42 -> 3.2188567
A43: hyna:BCH | B43: hyna | C43: 0.1111 | D43: 1.1111 | E43: 0.099991 | F43: N/A | H43: =CoreBpsBlended*D43*GrowthModeFactor -> 0.32188567 | I43: =CoreBpsBlended*D43 -> 3.2188567
A44: hyna:BNB | B44: hyna | C44: 0.1111 | D44: 1.1111 | E44: 0.099991 | F44: N/A | H44: =CoreBpsBlended*D44*GrowthModeFactor -> 0.32188567 | I44: =CoreBpsBlended*D44 -> 3.2188567
A45: hyna:BTC | B45: hyna | C45: 0.1111 | D45: 1.1111 | E45: 0.099991 | F45: N/A | H45: =CoreBpsBlended*D45*GrowthModeFactor -> 0.32188567 | I45: =CoreBpsBlended*D45 -> 3.2188567
A46: hyna:DOGE | B46: hyna | C46: 0.1111 | D46: 1.1111 | E46: 0.099991 | F46: N/A | H46: =CoreBpsBlended*D46*GrowthModeFactor -> 0.32188567 | I46: =CoreBpsBlended*D46 -> 3.2188567
A47: hyna:ENA | B47: hyna | C47: 0.1111 | D47: 1.1111 | E47: 0.099991 | F47: N/A | H47: =CoreBpsBlended*D47*GrowthModeFactor -> 0.32188567 | I47: =CoreBpsBlended*D47 -> 3.2188567
A48: hyna:ETH | B48: hyna | C48: 0.1111 | D48: 1.1111 | E48: 0.099991 | F48: N/A | H48: =CoreBpsBlended*D48*GrowthModeFactor -> 0.32188567 | I48: =CoreBpsBlended*D48 -> 3.2188567
A49: hyna:FARTCOIN | B49: hyna | C49: 0.1111 | D49: 1.1111 | E49: 0.099991 | F49: N/A | H49: =CoreBpsBlended*D49*GrowthModeFactor -> 0.32188567 | I49: =CoreBpsBlended*D49 -> 3.2188567
... A57: hyna:PUMP | B57: hyna | C57: 0.1111 | D57: 1.1111 | E57: 0.099991 | F57: N/A | H57: =CoreBpsBlended*D57*GrowthModeFactor -> 0.32188567 | I57: =CoreBpsBlended*D57 -> 3.2188567
A58: hyna:SILVER | B58: hyna | C58: 0.1111 | D58: 1.1111 | E58: 0.099991 | F58: enabled | G58: 46094 | H58: =CoreBpsBlended*D58*GrowthModeFactor -> 0.32188567 | I58: =CoreBpsBlended*D58 -> 3.2188567
A59: hyna:SOL | B59: hyna | C59: 0.1111 | D59: 1.1111 | E59: 0.099991 | F59: N/A | H59: =CoreBpsBlended*D59*GrowthModeFactor -> 0.32188567 | I59: =CoreBpsBlended*D59 -> 3.2188567
A60: hyna:SUI | B60: hyna | C60: 0.1111 | D60: 1.1111 | E60: 0.099991 | F60: N/A | H60: =CoreBpsBlended*D60*GrowthModeFactor -> 0.32188567 | I60: =CoreBpsBlended*D60 -> 3.2188567
A61: hyna:XMR | B61: hyna | C61: 0.1111 | D61: 1.1111 | E61: 0.099991 | F61: N/A | H61: =CoreBpsBlended*D61*GrowthModeFactor -> 0.32188567 | I61: =CoreBpsBlended*D61 -> 3.2188567
A62: hyna:XPL | B62: hyna | C62: 0.1111 | D62: 1.1111 | E62: 0.099991 | F62: N/A | H62: =CoreBpsBlended*D62*GrowthModeFactor -> 0.32188567 | I62: =CoreBpsBlended*D62 -> 3.2188567
A63: hyna:XRP | B63: hyna | C63: 0.1111 | D63: 1.1111 | E63: 0.099991 | F63: N/A | H63: =CoreBpsBlended*D63*GrowthModeFactor -> 0.32188567 | I63: =CoreBpsBlended*D63 -> 3.2188567
A64: hyna:ZEC | B64: hyna | C64: 0.1111 | D64: 1.1111 | E64: 0.099991 | F64: N/A | H64: =CoreBpsBlended*D64*GrowthModeFactor -> 0.32188567 | I64: =CoreBpsBlended*D64 -> 3.2188567
A65: km:AAPL | B65: km | C65: 1 | D65: 2 | E65: 0.5 | F65: enabled | G65: 46051 | H65: =CoreBpsBlended*D65*GrowthModeFactor -> 0.5794 | I65: =CoreBpsBlended*D65 -> 5.794
A66: km:BABA | B66: km | C66: 1 | D66: 2 | E66: 0.5 | F66: enabled | G66: 46037 | H66: =CoreBpsBlended*D66*GrowthModeFactor -> 0.5794 | I66: =CoreBpsBlended*D66 -> 5.794
A67: km:BMNR | B67: km | C67: 1 | D67: 2 | E67: 0.5 | F67: N/A | G67: 46123 | H67: =CoreBpsBlended*D67*GrowthModeFactor -> 0.5794 | I67: =CoreBpsBlended*D67 -> 5.794
A68: km:EUR | B68: km | C68: 1 | D68: 2 | E68: 0.5 | F68: enabled | G68: 46135 | H68: =CoreBpsBlended*D68*GrowthModeFactor -> 0.5794 | I68: =CoreBpsBlended*D68 -> 5.794
A69: km:GLDMINE | B69: km | C69: 1 | D69: 2 | E69: 0.5 | F69: enabled | G69: 46078 | H69: =CoreBpsBlended*D69*GrowthModeFactor -> 0.5794 | I69: =CoreBpsBlended*D69 -> 5.794
A70: km:GOLD | B70: km | C70: 1 | D70: 2 | E70: 0.5 | F70: N/A | H70: =CoreBpsBlended*D70*GrowthModeFactor -> 0.5794 | I70: =CoreBpsBlended*D70 -> 5.794
A71: km:GOOGL | B71: km | C71: 1 | D71: 2 | E71: 0.5 | F71: enabled | G71: 46051 | H71: =CoreBpsBlended*D71*GrowthModeFactor -> 0.5794 | I71: =CoreBpsBlended*D71 -> 5.794
A72: km:JPN225 | B72: km | C72: 1 | D72: 2 | E72: 0.5 | F72: N/A | H72: =CoreBpsBlended*D72*GrowthModeFactor -> 0.5794 | I72: =CoreBpsBlended*D72 -> 5.794
A73: km:MU | B73: km | C73: 1 | D73: 2 | E73: 0.5 | F73: enabled | G73: 46077 | H73: =CoreBpsBlended*D73*GrowthModeFactor -> 0.5794 | I73: =CoreBpsBlended*D73 -> 5.794
A74: km:NVDA | B74: km | C74: 1 | D74: 2 | E74: 0.5 | F74: enabled | G74: 46064 | H74: =CoreBpsBlended*D74*GrowthModeFactor -> 0.5794 | I74: =CoreBpsBlended*D74 -> 5.794
A75: km:PLTR | B75: km | C75: 1 | D75: 2 | E75: 0.5 | F75: enabled | G75: 46077 | H75: =CoreBpsBlended*D75*GrowthModeFactor -> 0.5794 | I75: =CoreBpsBlended*D75 -> 5.794
A76: km:RTX | B76: km | C76: 1 | D76: 2 | E76: 0.5 | F76: enabled | G76: 46091 | H76: =CoreBpsBlended*D76*GrowthModeFactor -> 0.5794 | I76: =CoreBpsBlended*D76 -> 5.794
A77: km:SEMI | B77: km | C77: 1 | D77: 2 | E77: 0.5 | F77: enabled | G77: 46078 | H77: =CoreBpsBlended*D77*GrowthModeFactor -> 0.5794 | I77: =CoreBpsBlended*D77 -> 5.794
A78: km:SILVER | B78: km | C78: 1 | D78: 2 | E78: 0.5 | F78: enabled | G78: 46050 | H78: =CoreBpsBlended*D78*GrowthModeFactor -> 0.5794 | I78: =CoreBpsBlended*D78 -> 5.794
A79: km:SMALL2000 | B79: km | C79: 1 | D79: 2 | E79: 0.5 | F79: enabled | G79: 46029 | H79: =CoreBpsBlended*D79*GrowthModeFactor -> 0.5794 | I79: =CoreBpsBlended*D79 -> 5.794
A80: km:TENCENT | B80: km | C80: 1 | D80: 2 | E80: 0.5 | F80: enabled | G80: 46121 | H80: =CoreBpsBlended*D80*GrowthModeFactor -> 0.5794 | I80: =CoreBpsBlended*D80 -> 5.794
A81: km:TSLA | B81: km | C81: 1 | D81: 2 | E81: 0.5 | F81: enabled | G81: 46038 | H81: =CoreBpsBlended*D81*GrowthModeFactor -> 0.5794 | I81: =CoreBpsBlended*D81 -> 5.794
A82: km:US500 | B82: km | C82: 1 | D82: 2 | E82: 0.5 | F82: enabled | G82: 46029 | H82: =CoreBpsBlended*D82*GrowthModeFactor -> 0.5794 | I82: =CoreBpsBlended*D82 -> 5.794
A83: km:USBOND | B83: km | C83: 1 | D83: 2 | E83: 0.5 | F83: enabled | G83: 46043 | H83: =CoreBpsBlended*D83*GrowthModeFactor -> 0.5794 | I83: =CoreBpsBlended*D83 -> 5.794
A84: km:USENERGY | B84: km | C84: 1 | D84: 2 | E84: 0.5 | F84: enabled | G84: 46057 | H84: =CoreBpsBlended*D84*GrowthModeFactor -> 0.5794 | I84: =CoreBpsBlended*D84 -> 5.794
... A87: km:XIAOMI | B87: km | C87: 1 | D87: 2 | E87: 0.5 | F87: enabled | G87: 46121 | H87: =CoreBpsBlended*D87*GrowthModeFactor -> 0.5794 | I87: =CoreBpsBlended*D87 -> 5.794
A88: para:BTCD | B88: para | C88: 1 | D88: 2 | E88: 0.5 | F88: N/A | H88: =CoreBpsBlended*D88*GrowthModeFactor -> 0.5794 | I88: =CoreBpsBlended*D88 -> 5.794
A89: para:H100 | B89: para | C89: 1 | D89: 2 | E89: 0.5 | F89: N/A | H89: =CoreBpsBlended*D89*GrowthModeFactor -> 0.5794 | I89: =CoreBpsBlended*D89 -> 5.794
A90: para:OTHERS | B90: para | C90: 1 | D90: 2 | E90: 0.5 | F90: N/A | H90: =CoreBpsBlended*D90*GrowthModeFactor -> 0.5794 | I90: =CoreBpsBlended*D90 -> 5.794
A91: para:TOTAL2 | B91: para | C91: 1 | D91: 2 | E91: 0.5 | F91: N/A | H91: =CoreBpsBlended*D91*GrowthModeFactor -> 0.5794 | I91: =CoreBpsBlended*D91 -> 5.794
A92: vntl:ANTHROPIC | B92: vntl | C92: 1 | D92: 2 | E92: 0.5 | F92: N/A | H92: =CoreBpsBlended*D92*GrowthModeFactor -> 0.5794 | I92: =CoreBpsBlended*D92 -> 5.794
A93: vntl:BIOTECH | B93: vntl | C93: 1 | D93: 2 | E93: 0.5 | F93: enabled | G93: 46056 | H93: =CoreBpsBlended*D93*GrowthModeFactor -> 0.5794 | I93: =CoreBpsBlended*D93 -> 5.794
A94: vntl:DEFENSE | B94: vntl | C94: 1 | D94: 2 | E94: 0.5 | F94: enabled | G94: 46056 | H94: =CoreBpsBlended*D94*GrowthModeFactor -> 0.5794 | I94: =CoreBpsBlended*D94 -> 5.794
A95: vntl:ENERGY | B95: vntl | C95: 1 | D95: 2 | E95: 0.5 | F95: enabled | G95: 46056 | H95: =CoreBpsBlended*D95*GrowthModeFactor -> 0.5794 | I95: =CoreBpsBlended*D95 -> 5.794
A96: vntl:GOLDJM | B96: vntl | C96: 1 | D96: 2 | E96: 0.5 | F96: N/A | H96: =CoreBpsBlended*D96*GrowthModeFactor -> 0.5794 | I96: =CoreBpsBlended*D96 -> 5.794
A97: vntl:INFOTECH | B97: vntl | C97: 1 | D97: 2 | E97: 0.5 | F97: enabled | G97: 46056 | H97: =CoreBpsBlended*D97*GrowthModeFactor -> 0.5794 | I97: =CoreBpsBlended*D97 -> 5.794
A98: vntl:MAG7 | B98: vntl | C98: 1 | D98: 2 | E98: 0.5 | F98: enabled | G98: 46056 | H98: =CoreBpsBlended*D98*GrowthModeFactor -> 0.5794 | I98: =CoreBpsBlended*D98 -> 5.794
A99: vntl:NUCLEAR | B99: vntl | C99: 1 | D99: 2 | E99: 0.5 | F99: enabled | G99: 46056 | H99: =CoreBpsBlended*D99*GrowthModeFactor -> 0.5794 | I99: =CoreBpsBlended*D99 -> 5.794
A100: vntl:OPENAI | B100: vntl | C100: 1 | D100: 2 | E100: 0.5 | F100: N/A | H100: =CoreBpsBlended*D100*GrowthModeFactor -> 0.5794 | I100: =CoreBpsBlended*D100 -> 5.794
A101: vntl:ROBOT | B101: vntl | C101: 1 | D101: 2 | E101: 0.5 | F101: enabled | G101: 46056 | H101: =CoreBpsBlended*D101*GrowthModeFactor -> 0.5794 | I101: =CoreBpsBlended*D101 -> 5.794
A102: vntl:SEMIS | B102: vntl | C102: 1 | D102: 2 | E102: 0.5 | F102: enabled | G102: 46056 | H102: =CoreBpsBlended*D102*GrowthModeFactor -> 0.5794 | I102: =CoreBpsBlended*D102 -> 5.794
A103: vntl:SILVERJM | B103: vntl | C103: 1 | D103: 2 | E103: 0.5 | F103: N/A | H103: =CoreBpsBlended*D103*GrowthModeFactor -> 0.5794 | I103: =CoreBpsBlended*D103 -> 5.794
A104: vntl:SOY | B104: vntl | C104: 1 | D104: 2 | E104: 0.5 | F104: enabled | G104: 46132 | H104: =CoreBpsBlended*D104*GrowthModeFactor -> 0.5794 | I104: =CoreBpsBlended*D104 -> 5.794
A105: vntl:SPACEX | B105: vntl | C105: 1 | D105: 2 | E105: 0.5 | F105: N/A | H105: =CoreBpsBlended*D105*GrowthModeFactor -> 0.5794 | I105: =CoreBpsBlended*D105 -> 5.794
A106: vntl:WHEAT | B106: vntl | C106: 1 | D106: 2 | E106: 0.5 | F106: enabled | G106: 46119 | H106: =CoreBpsBlended*D106*GrowthModeFactor -> 0.5794 | I106: =CoreBpsBlended*D106 -> 5.794
A107: xyz:AAPL | B107: xyz | C107: 1 | D107: 2 | E107: 0.5 | F107: enabled | G107: 45984 | H107: =CoreBpsBlended*D107*GrowthModeFactor -> 0.5794 | I107: =CoreBpsBlended*D107 -> 5.794
A108: xyz:ALUMINIUM | B108: xyz | C108: 1 | D108: 2 | E108: 0.5 | F108: enabled | G108: 46043 | H108: =CoreBpsBlended*D108*GrowthModeFactor -> 0.5794 | I108: =CoreBpsBlended*D108 -> 5.794
A109: xyz:AMD | B109: xyz | C109: 1 | D109: 2 | E109: 0.5 | F109: enabled | G109: 45984 | H109: =CoreBpsBlended*D109*GrowthModeFactor -> 0.5794 | I109: =CoreBpsBlended*D109 -> 5.794
A110: xyz:AMZN | B110: xyz | C110: 1 | D110: 2 | E110: 0.5 | F110: enabled | G110: 45984 | H110: =CoreBpsBlended*D110*GrowthModeFactor -> 0.5794 | I110: =CoreBpsBlended*D110 -> 5.794
...

Sheet HIP-3 by Category
A1: HIP-3 Daily — Volume & Modeled Fees by Asset Category
A2: Volume from Hyperliquid info API candleSnapshot per asset, aggregated by category.
A3: Fees modeled per-asset using growth-mode-aware formula; aggregated to category. See HIP-3 Model sheet.
A5: VOLUME BY CATEGORY ($)
A6: Date | B6: Agriculture | C6: Bonds | D6: Crypto | E6: Energy | F6: Equities — Crypto-related | G6: Equities — Single Name | H6: Equity Indices/ETF | I6: FX | J6: Industrial Metals | K6: Pre-IPO / Private | L6: Precious Metals | M6: Total HIP-3
A7: 45943 | B7: 0 | C7: 0 | D7: 0 | E7: 0 | F7: 0 | G7: 0 | H7: 24137313 | I7: 0 | J7: 0 | K7: 0 | L7: 0 | M7: =SUM(B7:L7) -> 24137313
A8: 45944 | B8: 0 | C8: 0 | D8: 0 | E8: 0 | F8: 0 | G8: 0 | H8: 21893628 | I8: 0 | J8: 0 | K8: 0 | L8: 0 | M8: =SUM(B8:L8) -> 21893628
A9: 45945 | B9: 0 | C9: 0 | D9: 0 | E9: 0 | F9: 0 | G9: 0 | H9: 20602638 | I9: 0 | J9: 0 | K9: 0 | L9: 0 | M9: =SUM(B9:L9) -> 20602638
A10: 45946 | B10: 0 | C10: 0 | D10: 0 | E10: 0 | F10: 0 | G10: 0 | H10: 19139744 | I10: 0 | J10: 0 | K10: 0 | L10: 0 | M10: =SUM(B10:L10) -> 19139744
A11: 45947 | B11: 0 | C11: 0 | D11: 0 | E11: 0 | F11: 0 | G11: 0 | H11: 15100795 | I11: 0 | J11: 0 | K11: 0 | L11: 0 | M11: =SUM(B11:L11) -> 15100795
A12: 45948 | B12: 0 | C12: 0 | D12: 0 | E12: 0 | F12: 0 | G12: 0 | H12: 6243638.8 | I12: 0 | J12: 0 | K12: 0 | L12: 0 | M12: =SUM(B12:L12) -> 6243638.8
A13: 45949 | B13: 0 | C13: 0 | D13: 0 | E13: 0 | F13: 0 | G13: 0 | H13: 7838676.4 | I13: 0 | J13: 0 | K13: 0 | L13: 0 | M13: =SUM(B13:L13) -> 7838676.4
A14: 45950 | B14: 0 | C14: 0 | D14: 0 | E14: 0 | F14: 0 | G14: 0 | H14: 10597513 | I14: 0 | J14: 0 | K14: 0 | L14: 0 | M14: =SUM(B14:L14) -> 10597513
A15: 45951 | B15: 0 | C15: 0 | D15: 0 | E15: 0 | F15: 0 | G15: 0 | H15: 23304373 | I15: 0 | J15: 0 | K15: 0 | L15: 0 | M15: =SUM(B15:L15) -> 23304373
A16: 45952 | B16: 0 | C16: 0 | D16: 0 | E16: 0 | F16: 0 | G16: 0 | H16: 36702797 | I16: 0 | J16: 0 | K16: 0 | L16: 0 | M16: =SUM(B16:L16) -> 36702797
A17: 45953 | B17: 0 | C17: 0 | D17: 0 | E17: 0 | F17: 0 | G17: 0 | H17: 30181937 | I17: 0 | J17: 0 | K17: 0 | L17: 0 | M17: =SUM(B17:L17) -> 30181937
A18: 45954 | B18: 0 | C18: 0 | D18: 0 | E18: 0 | F18: 0 | G18: 0 | H18: 27291720 | I18: 0 | J18: 0 | K18: 0 | L18: 0 | M18: =SUM(B18:L18) -> 27291720
... A226: 46162 | B226: 87327.911 | C226: 9993.4427 | D226: 2115097.8 | E226: 39845360 | F226: 2922661.3 | G226: 46698955 | H226: 99407571 | I226: 414539.84 | J226: 608633.1 | K226: 896499.64 | L226: 52653089 | M226: =SUM(B226:L226) -> 2.4565973e+08
A229: MODELED PROTOCOL FEES BY CATEGORY ($)
A230: Date | B230: Agriculture | C230: Bonds | D230: Crypto | E230: Energy | F230: Equities — Crypto-related | G230: Equities — Single Name | H230: Equity Indices/ETF | I230: FX | J230: Industrial Metals | K230: Pre-IPO / Private | L230: Precious Metals | M230: Total HIP-3 Protocol Fees
A231: 45943 | B231: 0 | C231: 0 | D231: 0 | E231: 0 | F231: 0 | G231: 0 | H231: 6830.8595 | I231: 0 | J231: 0 | K231: 0 | L231: 0 | M231: =SUM(B231:L231) -> 6830.8595
A232: 45944 | B232: 0 | C232: 0 | D232: 0 | E232: 0 | F232: 0 | G232: 0 | H232: 6195.8967 | I232: 0 | J232: 0 | K232: 0 | L232: 0 | M232: =SUM(B232:L232) -> 6195.8967
A233: 45945 | B233: 0 | C233: 0 | D233: 0 | E233: 0 | F233: 0 | G233: 0 | H233: 5830.5466 | I233: 0 | J233: 0 | K233: 0 | L233: 0 | M233: =SUM(B233:L233) -> 5830.5466
A234: 45946 | B234: 0 | C234: 0 | D234: 0 | E234: 0 | F234: 0 | G234: 0 | H234: 5416.5475 | I234: 0 | J234: 0 | K234: 0 | L234: 0 | M234: =SUM(B234:L234) -> 5416.5475
A235: 45947 | B235: 0 | C235: 0 | D235: 0 | E235: 0 | F235: 0 | G235: 0 | H235: 4273.5251 | I235: 0 | J235: 0 | K235: 0 | L235: 0 | M235: =SUM(B235:L235) -> 4273.5251
A236: 45948 | B236: 0 | C236: 0 | D236: 0 | E236: 0 | F236: 0 | G236: 0 | H236: 1766.9498 | I236: 0 | J236: 0 | K236: 0 | L236: 0 | M236: =SUM(B236:L236) -> 1766.9498
A237: 45949 | B237: 0 | C237: 0 | D237: 0 | E237: 0 | F237: 0 | G237: 0 | H237: 2218.3454 | I237: 0 | J237: 0 | K237: 0 | L237: 0 | M237: =SUM(B237:L237) -> 2218.3454
A238: 45950 | B238: 0 | C238: 0 | D238: 0 | E238: 0 | F238: 0 | G238: 0 | H238: 2999.0962 | I238: 0 | J238: 0 | K238: 0 | L238: 0 | M238: =SUM(B238:L238) -> 2999.0962
A239: 45951 | B239: 0 | C239: 0 | D239: 0 | E239: 0 | F239: 0 | G239: 0 | H239: 6595.1376 | I239: 0 | J239: 0 | K239: 0 | L239: 0 | M239: =SUM(B239:L239) -> 6595.1376
A240: 45952 | B240: 0 | C240: 0 | D240: 0 | E240: 0 | F240: 0 | G240: 0 | H240: 10386.891 | I240: 0 | J240: 0 | K240: 0 | L240: 0 | M240: =SUM(B240:L240) -> 10386.891
A241: 45953 | B241: 0 | C241: 0 | D241: 0 | E241: 0 | F241: 0 | G241: 0 | H241: 8541.4881 | I241: 0 | J241: 0 | K241: 0 | L241: 0 | M241: =SUM(B241:L241) -> 8541.4881
A242: 45954 | B242: 0 | C242: 0 | D242: 0 | E242: 0 | F242: 0 | G242: 0 | H242: 7723.5566 | I242: 0 | J242: 0 | K242: 0 | L242: 0 | M242: =SUM(B242:L242) -> 7723.5566
... A450: 46162 | B450: 2.4713799 | C450: 0.28281443 | D450: 329.01269 | E450: 1127.6237 | F450: 190.58119 | G450: 1321.5804 | H450: 2813.2342 | I450: 11.731477 | J450: 17.224317 | K450: 62.602042 | L450: 4267.8267 | M450: =SUM(B450:L450) -> 10144.171

Sheet Reconciliation
A1: Reconciliation & Cross-Source Checks
A2: All values computed via formulas referencing Daily Master sheet. Identity diffs near $0 = clean reconciliation.
A4: --- DEFILLAMA COVERAGE ---
A5: First date with DefiLlama fees | B5: ='Daily Master'!A588 -> 45649
A6: Last date with DefiLlama fees | B6: ='Daily Master'!A1100 -> 46161
A7: Number of days covered | B7: =(1100-588+1) -> 513
A9: --- CORE IDENTITY: fees = revenue + supplyside ---
A10: Sum of identity diffs across all days | B10: =SUM('Daily Master'!AF588:AF1100) -> 5
A11: Max abs identity diff | B11: =SUMPRODUCT(MAX(ABS('Daily Master'!AF588:AF1100))) -> #VALUE!
A12: Average abs identity diff | B12: =SUMPRODUCT(ABS('Daily Master'!AF588:AF1100))/(1100-588+1) -> 0.46978558
A13: -> Should be near 0 (integer rounding only)
A15: --- AF BUYBACK = HOLDERS REVENUE IDENTITY ---
A16: Sum of rev-buyback diffs | B16: =SUM('Daily Master'!AG588:AG1100) -> 0
A17: Max abs diff | B17: =SUMPRODUCT(MAX(ABS('Daily Master'!AG588:AG1100))) -> #VALUE!
A18: -> Should be exactly 0 (same metric)
A20: --- HLP SHARE FORMULA vs DEFILLAMA ---
A21: Sum of formula HLP slice ($) | B21: =SUM('Daily Master'!U588:U1100) -> 22746844
A22: Sum of DL reported HLP slice ($) | B22: =SUM('Daily Master'!V588:V1100) -> 22189875
A23: Diff ($) | B23: =SUM('Daily Master'!W588:W1100) -> 556968.68
A24: Max abs daily diff ($) | B24: =SUMPRODUCT(MAX(ABS('Daily Master'!W588:W1100))) -> #VALUE!
A25: -> Formula uses 3% pre-Aug30 / 1% post; should match DL closely
A27: --- HYPURRSCAN CROSS-CHECK ---
A28: Cum. DL revenue ($) | B28: =SUM('Daily Master'!S588:S1100) -> 1161641075
A29: Cum. HP total fees ($) | B29: =SUM('Daily Master'!AH588:AH1100) -> 1.0682216e+09
A30: HP/DL revenue ratio | B30: =SUM('Daily Master'!AH588:AH1100)/SUM('Daily Master'!S588:S1100) -> 0.91957971
A32: --- CUMULATIVE FEE BREAKDOWN ---
A33: Cum. total gross fees (Perps+Spot) | B33: =SUM('Daily Master'!K588:K1100) -> 1260945873
A34: Cum. revenue to AF | B34: =SUM('Daily Master'!S588:S1100) -> 1161641075
A35: Cum. HLP depositors share | B35: =SUM('Daily Master'!V588:V1100) -> 22189875
A36: Cum. Builders + Unit share | B36: =SUM('Daily Master'!AA588:AA1100) -> 77114918
A37: Check sum: revenue + HLP + builders+unit | B37: =SUM('Daily Master'!S588:S1100)+SUM('Daily Master'!V588:V1100)+SUM('Daily Master'!AA588:AA1100) -> 1260945868
A38: Diff to total fees (should ~ 0) | B38: =SUM('Daily Master'!K588:K1100)-(SUM('Daily Master'!S588:S1100)+SUM('Daily Master'!V588:V1100)+SUM('Daily Master'!AA588:AA1100)) -> 5
A40: --- MODELED HIP-3 vs IMPLIED HIP-3 ---
A41: Cum. modeled HIP-3 protocol fees | B41: =SUM('Daily Master'!M588:M1100) -> 12473867
A42: Cum. modeled HIP-3 deployer fees | B42: =SUM('Daily Master'!N588:N1100) -> 11522443
A43: Cum. modeled HIP-3 gross fees | B43: =SUM('Daily Master'!L588:L1100) -> 23996311
A44: Cum. implied core fees (DL Perps - modeled HIP-3 gross) | B44: =SUM('Daily Master'!O588:O1100) -> 1.1806787e+09
A45: -> Model imperfect (fee tiers vary). Best-effort estimate.
A47: --- BUYBACKS ---
A48: Cum. HYPE bought daily (#) | B48: =SUM('Daily Master'!AE588:AE1100) -> 36433808
A49: Cum. AF buyback $ | B49: =SUM('Daily Master'!AB588:AB1100) -> 1161641075
A50: -> Public reporting: ~36-37M HYPE bought since AF inception
A52: --- SUPPLY ---
A53: Cum. modeled HYPE issuance to stakers | B53: =SUM('Daily Master'!AL588:AL1100) -> 12987405
A54: Cum. net HYPE supply change | B54: =SUM('Daily Master'!AN588:AN1100) -> -23446403
A55: -> Negative = net deflation

Sheet Sources & Methodology
A1: Sources & Methodology
A3: PRIMARY SOURCES
A4: Existing user file (21Shares Dune query 6874521) | B4: Daily core & HIP-3 perp volume + 21Shares fee proxy
A5: DefiLlama Fees API | B5: https://api.llama.fi/summary/fees/hyperliquid?dataType=dailyFees / dailyRevenue / dailyHoldersRevenue / dailySupplySideRevenue
A6: DefiLlama DEX volume | B6: https://api.llama.fi/summary/dexs/hyperliquid?dataType=dailyVolume — spot orderbook volume
A7: Hyperliquid Info API — perpDexs | B7: POST https://api.hyperliquid.xyz/info {"type":"perpDexs"} — HIP-3 dex list + deployerFeeScale per dex
A8: Hyperliquid Info API — meta per dex | B8: POST .../info {"type":"meta","dex":"<name>"} — per-asset growthMode + lastGrowthModeChangeTime
A9: Hyperliquid Info API — candleSnapshot | B9: Per-asset daily candles for HIP-3 assets AND HYPE/USDC spot price (@107)
A10: Hyperliquid Info API — validatorSummaries | B10: Current total HYPE staked, predicted APR
A11: Hypurrscan Fees API | B11: https://api.hypurrscan.io/fees — independent cumulative on-chain fees (cross-check)
A12: Hyperliquid Fees doc | B12: https://hyperliquid.gitbook.io/hyperliquid-docs/trading/fees — fee schedule, tiers, formula
A13: Hyperliquid HIP-3 doc | B13: https://hyperliquid.gitbook.io/hyperliquid-docs/hyperliquid-improvement-proposals-hips/hip-3
A14: Hyperliquid HIP-4 doc | B14: https://hyperliquid.gitbook.io/hyperliquid-docs/hyperliquid-improvement-proposals-hips/hip-4-outcome-markets
A15: Hyperliquid Staking doc | B15: https://hyperliquid.gitbook.io/hyperliquid-docs/hypercore/staking — APR formula
A17: HIP-3 FEE MECHANICS — THE CORRECTED PICTURE
A18: Per the official Hyperliquid fee formula in docs:
A19: scaleIfHip3 = (deployerFeeScale × 2) if deployerFeeScale ≥ 1
A20: = (deployerFeeScale + 1) if deployerFeeScale < 1
A21: deployerShare = 0.5 if deployerFeeScale ≥ 1
A22: = deployerFeeScale / (1 + deployerFeeScale) if < 1
A23: trader pays: base_taker × scaleIfHip3 × growthModeScale × (1 - referralDiscount)
A24: growthModeScale = 0.1 if growth mode enabled on that asset, else 1.0
A26: SNAPSHOT (as of May 20, 2026) FROM HYPERLIQUID INFO API:
A27: trade.xyz (xyz): deployerFeeScale=1.0 → trader pays 2x base, 50/50 split
A28: Felix (flx): deployerFeeScale=1.0 → trader pays 2x base, 50/50 split
A29: Ventuals (vntl): deployerFeeScale=1.0 → trader pays 2x base, 50/50 split
... A75: Only one market (daily BTC binary outcome) initially live.
