Workbook

Sheet README
A1: India Data Centre Power - Public-Document Dataset (v3 - multi-state)
A3: Compiled | B3: 19-Oct-2026, from publicly available documents. v2 adds a Maharashtra permit sweep: all 2025-26 SEIAA/SEAC agendas (266 docs), OCR of 66 scanned SEIAA minutes, all MPCB Consent Appraisal Committee reports (132 docs), MERC Case 88/2026, and Parliament answers on DC power demand.
A4: What changed in v3 | B4: Added AP, Telangana, Tamil Nadu, Karnataka, UP, Odisha. New CTU_Bulk_Register sheet: every bulk-consumer (>=50 MW) application for direct central-grid access, classified for data-centre use. New States_Evidence sheet: GOs, ECs, grid sanctions and state dashboards outside Maharashtra. 18 new project rows.
A5: What changed in v2 | B5: New MH_Permits sheet (45 permit records with connected load, DG sets, capital investment). 14 new permit-backed projects (Google x2, AWS Thane & Powai, Microsoft/AdaniConneX Pune, Iron Mountain MUM-3, Chandivali DC, MAHAPREIT, etc.). MERC Ambernath order and Rajya Sabha answers now read in full (tier A1). Lodha/Ambernath, CapitaLand, Digital Edge, STT, Yotta, AirTrunk rows enriched.
A6: Purpose | B6: Test whether planned data-centre power in India (especially Navi Mumbai) is materially higher than press announcements suggest, using government, regulator, utility, permit and company-filing evidence.
A7: Sheets | B7: Projects - one row per campus/project. Grid_Power - transmission, substation, utility and regulatory evidence. CTU_Bulk_Register - CTUIL national grid-access register (bulk consumers). States_Evidence - non-Maharashtra GOs/ECs/grid evidence. MH_Permits - Maharashtra environmental clearances and pollution-board consents for data centres, with power data. Govt_Aggregates - official and operator-level totals. Summary - formula-driven roll-ups and gap check. To_Pull - primary documents still to retrieve. Sources - every link used.
A8: Units | B8: IT MW = critical IT load. 'Grid / facility power' is quoted as the source states it (MW or MVA); facility power is typically 1.3-1.6x IT load. Investment in Rs crore.
A9: Include in totals | B9: 'N' marks rows excluded from Summary sums to avoid double counting (e.g., tenants inside a park; umbrella MoUs; potential-only site capacity). Change the flag to re-cut totals.
A10: Read in source? | B10: 'Y' = the figure was checked in the primary document itself during compilation. 'N' = taken from a report of that document; verify before external use.
A11: Highlighting | B11: Yellow rows = Navi Mumbai / MMR focus.
A12: Caveat | B12: Sources often conflict (IT vs facility MW, campus potential vs build). Conflicts are noted per row. MoU/LoI capacity is intent, not committed build.
A14: Evidence tiers
A15: A1 | B15: Government / regulator / utility document - retrieved and read for this dataset
A16: A2 | B16: Government / regulator action (GO, MoU, LoI, permit application, regulatory order) - reported; primary document not yet retrieved
A17: B | B17: Statutory company disclosure - exchange filing, investor presentation, DRHP, credit-rating rationale
A18: C | B18: Company announcement / company website
A19: D | B19: Third-party only - press, aggregator, research house

Sheet Summary
A1: Summary - tracked IT MW (Projects sheet, rows with Include = Y)
A2: All figures are formulas over the Projects sheet; edit Projects and these update.
A4: State | B4: A1 | C4: A2 | D4: B | E4: C | F4: D | G4: Total planned IT MW | H4: Operational IT MW | I4: UC / contracted IT MW
A5: Maharashtra | B5: =SUMIFS(Projects!$J$2:$J$293,Projects!$B$2:$B$293,$A5,Projects!$O$2:$O$293,"A1",Projects!$W$2:$W$293,"Y") -> 3372 | C5: =SUMIFS(Projects!$J$2:$J$293,Projects!$B$2:$B$293,$A5,Projects!$O$2:$O$293,"A2",Projects!$W$2:$W$293,"Y") -> 4250 | D5: =SUMIFS(Projects!$J$2:$J$293,Projects!$B$2:$B$293,$A5,Projects!$O$2:$O$293,"B",Projects!$W$2:$W$293,"Y") -> 244 | E5: =SUMIFS(Projects!$J$2:$J$293,Projects!$B$2:$B$293,$A5,Projects!$O$2:$O$293,"C",Projects!$W$2:$W$293,"Y") -> 3216 | F5: =SUMIFS(Projects!$J$2:$J$293,Projects!$B$2:$B$293,$A5,Projects!$O$2:$O$293,"D",Projects!$W$2:$W$293,"Y") -> 165.5 | G5: =SUM(B5:F5) -> 11247.5 | H5: =SUMIFS(Projects!$H$2:$H$293,Projects!$B$2:$B$293,$A5,Projects!$W$2:$W$293,"Y") -> 472.2 | I5: =SUMIFS(Projects!$I$2:$I$293,Projects!$B$2:$B$293,$A5,Projects!$W$2:$W$293,"Y") -> 2454.1
A6: Andhra Pradesh | B6: =SUMIFS(Projects!$J$2:$J$293,Projects!$B$2:$B$293,$A6,Projects!$O$2:$O$293,"A1",Projects!$W$2:$W$293,"Y") -> 1000 | C6: =SUMIFS(Projects!$J$2:$J$293,Projects!$B$2:$B$293,$A6,Projects!$O$2:$O$293,"A2",Projects!$W$2:$W$293,"Y") -> 4148 | D6: =SUMIFS(Projects!$J$2:$J$293,Projects!$B$2:$B$293,$A6,Projects!$O$2:$O$293,"B",Projects!$W$2:$W$293,"Y") -> 0 | E6: =SUMIFS(Projects!$J$2:$J$293,Projects!$B$2:$B$293,$A6,Projects!$O$2:$O$293,"C",Projects!$W$2:$W$293,"Y") -> 0 | F6: =SUMIFS(Projects!$J$2:$J$293,Projects!$B$2:$B$293,$A6,Projects!$O$2:$O$293,"D",Projects!$W$2:$W$293,"Y") -> 0 | G6: =SUM(B6:F6) -> 5148 | H6: =SUMIFS(Projects!$H$2:$H$293,Projects!$B$2:$B$293,$A6,Projects!$W$2:$W$293,"Y") -> 0 | I6: =SUMIFS(Projects!$I$2:$I$293,Projects!$B$2:$B$293,$A6,Projects!$W$2:$W$293,"Y") -> 0
A7: Telangana | B7: =SUMIFS(Projects!$J$2:$J$293,Projects!$B$2:$B$293,$A7,Projects!$O$2:$O$293,"A1",Projects!$W$2:$W$293,"Y") -> 0 | C7: =SUMIFS(Projects!$J$2:$J$293,Projects!$B$2:$B$293,$A7,Projects!$O$2:$O$293,"A2",Projects!$W$2:$W$293,"Y") -> 1000 | D7: =SUMIFS(Projects!$J$2:$J$293,Projects!$B$2:$B$293,$A7,Projects!$O$2:$O$293,"B",Projects!$W$2:$W$293,"Y") -> 406 | E7: =SUMIFS(Projects!$J$2:$J$293,Projects!$B$2:$B$293,$A7,Projects!$O$2:$O$293,"C",Projects!$W$2:$W$293,"Y") -> 2200 | F7: =SUMIFS(Projects!$J$2:$J$293,Projects!$B$2:$B$293,$A7,Projects!$O$2:$O$293,"D",Projects!$W$2:$W$293,"Y") -> 0 | G7: =SUM(B7:F7) -> 3606 | H7: =SUMIFS(Projects!$H$2:$H$293,Projects!$B$2:$B$293,$A7,Projects!$W$2:$W$293,"Y") -> 19.2 | I7: =SUMIFS(Projects!$I$2:$I$293,Projects!$B$2:$B$293,$A7,Projects!$W$2:$W$293,"Y") -> 100
A8: Tamil Nadu | B8: =SUMIFS(Projects!$J$2:$J$293,Projects!$B$2:$B$293,$A8,Projects!$O$2:$O$293,"A1",Projects!$W$2:$W$293,"Y") -> 70 | C8: =SUMIFS(Projects!$J$2:$J$293,Projects!$B$2:$B$293,$A8,Projects!$O$2:$O$293,"A2",Projects!$W$2:$W$293,"Y") -> 0 | D8: =SUMIFS(Projects!$J$2:$J$293,Projects!$B$2:$B$293,$A8,Projects!$O$2:$O$293,"B",Projects!$W$2:$W$293,"Y") -> 33 | E8: =SUMIFS(Projects!$J$2:$J$293,Projects!$B$2:$B$293,$A8,Projects!$O$2:$O$293,"C",Projects!$W$2:$W$293,"Y") -> 200 | F8: =SUMIFS(Projects!$J$2:$J$293,Projects!$B$2:$B$293,$A8,Projects!$O$2:$O$293,"D",Projects!$W$2:$W$293,"Y") -> 145 | G8: =SUM(B8:F8) -> 448 | H8: =SUMIFS(Projects!$H$2:$H$293,Projects!$B$2:$B$293,$A8,Projects!$W$2:$W$293,"Y") -> 86.1 | I8: =SUMIFS(Projects!$I$2:$I$293,Projects!$B$2:$B$293,$A8,Projects!$W$2:$W$293,"Y") -> 34
A9: Uttar Pradesh | B9: =SUMIFS(Projects!$J$2:$J$293,Projects!$B$2:$B$293,$A9,Projects!$O$2:$O$293,"A1",Projects!$W$2:$W$293,"Y") -> 0 | C9: =SUMIFS(Projects!$J$2:$J$293,Projects!$B$2:$B$293,$A9,Projects!$O$2:$O$293,"A2",Projects!$W$2:$W$293,"Y") -> 370 | D9: =SUMIFS(Projects!$J$2:$J$293,Projects!$B$2:$B$293,$A9,Projects!$O$2:$O$293,"B",Projects!$W$2:$W$293,"Y") -> 50 | E9: =SUMIFS(Projects!$J$2:$J$293,Projects!$B$2:$B$293,$A9,Projects!$O$2:$O$293,"C",Projects!$W$2:$W$293,"Y") -> 52.8 | F9: =SUMIFS(Projects!$J$2:$J$293,Projects!$B$2:$B$293,$A9,Projects!$O$2:$O$293,"D",Projects!$W$2:$W$293,"Y") -> 0 | G9: =SUM(B9:F9) -> 472.8 | H9: =SUMIFS(Projects!$H$2:$H$293,Projects!$B$2:$B$293,$A9,Projects!$W$2:$W$293,"Y") -> 10 | I9: =SUMIFS(Projects!$I$2:$I$293,Projects!$B$2:$B$293,$A9,Projects!$W$2:$W$293,"Y") -> 40
A10: Gujarat | B10: =SUMIFS(Projects!$J$2:$J$293,Projects!$B$2:$B$293,$A10,Projects!$O$2:$O$293,"A1",Projects!$W$2:$W$293,"Y") -> 0 | C10: =SUMIFS(Projects!$J$2:$J$293,Projects!$B$2:$B$293,$A10,Projects!$O$2:$O$293,"A2",Projects!$W$2:$W$293,"Y") -> 0 | D10: =SUMIFS(Projects!$J$2:$J$293,Projects!$B$2:$B$293,$A10,Projects!$O$2:$O$293,"B",Projects!$W$2:$W$293,"Y") -> 0 | E10: =SUMIFS(Projects!$J$2:$J$293,Projects!$B$2:$B$293,$A10,Projects!$O$2:$O$293,"C",Projects!$W$2:$W$293,"Y") -> 168 | F10: =SUMIFS(Projects!$J$2:$J$293,Projects!$B$2:$B$293,$A10,Projects!$O$2:$O$293,"D",Projects!$W$2:$W$293,"Y") -> 0 | G10: =SUM(B10:F10) -> 168 | H10: =SUMIFS(Projects!$H$2:$H$293,Projects!$B$2:$B$293,$A10,Projects!$W$2:$W$293,"Y") -> 0 | I10: =SUMIFS(Projects!$I$2:$I$293,Projects!$B$2:$B$293,$A10,Projects!$W$2:$W$293,"Y") -> 168
A11: Odisha | B11: =SUMIFS(Projects!$J$2:$J$293,Projects!$B$2:$B$293,$A11,Projects!$O$2:$O$293,"A1",Projects!$W$2:$W$293,"Y") -> 0 | C11: =SUMIFS(Projects!$J$2:$J$293,Projects!$B$2:$B$293,$A11,Projects!$O$2:$O$293,"A2",Projects!$W$2:$W$293,"Y") -> 1120 | D11: =SUMIFS(Projects!$J$2:$J$293,Projects!$B$2:$B$293,$A11,Projects!$O$2:$O$293,"B",Projects!$W$2:$W$293,"Y") -> 0 | E11: =SUMIFS(Projects!$J$2:$J$293,Projects!$B$2:$B$293,$A11,Projects!$O$2:$O$293,"C",Projects!$W$2:$W$293,"Y") -> 0 | F11: =SUMIFS(Projects!$J$2:$J$293,Projects!$B$2:$B$293,$A11,Projects!$O$2:$O$293,"D",Projects!$W$2:$W$293,"Y") -> 0 | G11: =SUM(B11:F11) -> 1120 | H11: =SUMIFS(Projects!$H$2:$H$293,Projects!$B$2:$B$293,$A11,Projects!$W$2:$W$293,"Y") -> 0 | I11: =SUMIFS(Projects!$I$2:$I$293,Projects!$B$2:$B$293,$A11,Projects!$W$2:$W$293,"Y") -> 0
A12: West Bengal | B12: =SUMIFS(Projects!$J$2:$J$293,Projects!$B$2:$B$293,$A12,Projects!$O$2:$O$293,"A1",Projects!$W$2:$W$293,"Y") -> 0 | C12: =SUMIFS(Projects!$J$2:$J$293,Projects!$B$2:$B$293,$A12,Projects!$O$2:$O$293,"A2",Projects!$W$2:$W$293,"Y") -> 0 | D12: =SUMIFS(Projects!$J$2:$J$293,Projects!$B$2:$B$293,$A12,Projects!$O$2:$O$293,"B",Projects!$W$2:$W$293,"Y") -> 0 | E12: =SUMIFS(Projects!$J$2:$J$293,Projects!$B$2:$B$293,$A12,Projects!$O$2:$O$293,"C",Projects!$W$2:$W$293,"Y") -> 40 | F12: =SUMIFS(Projects!$J$2:$J$293,Projects!$B$2:$B$293,$A12,Projects!$O$2:$O$293,"D",Projects!$W$2:$W$293,"Y") -> 250 | G12: =SUM(B12:F12) -> 290 | H12: =SUMIFS(Projects!$H$2:$H$293,Projects!$B$2:$B$293,$A12,Projects!$W$2:$W$293,"Y") -> 0 | I12: =SUMIFS(Projects!$I$2:$I$293,Projects!$B$2:$B$293,$A12,Projects!$W$2:$W$293,"Y") -> 0
A13: Haryana | B13: =SUMIFS(Projects!$J$2:$J$293,Projects!$B$2:$B$293,$A13,Projects!$O$2:$O$293,"A1",Projects!$W$2:$W$293,"Y") -> 0 | C13: =SUMIFS(Projects!$J$2:$J$293,Projects!$B$2:$B$293,$A13,Projects!$O$2:$O$293,"A2",Projects!$W$2:$W$293,"Y") -> 0 | D13: =SUMIFS(Projects!$J$2:$J$293,Projects!$B$2:$B$293,$A13,Projects!$O$2:$O$293,"B",Projects!$W$2:$W$293,"Y") -> 307 | E13: =SUMIFS(Projects!$J$2:$J$293,Projects!$B$2:$B$293,$A13,Projects!$O$2:$O$293,"C",Projects!$W$2:$W$293,"Y") -> 0 | F13: =SUMIFS(Projects!$J$2:$J$293,Projects!$B$2:$B$293,$A13,Projects!$O$2:$O$293,"D",Projects!$W$2:$W$293,"Y") -> 0 | G13: =SUM(B13:F13) -> 307 | H13: =SUMIFS(Projects!$H$2:$H$293,Projects!$B$2:$B$293,$A13,Projects!$W$2:$W$293,"Y") -> 28 | I13: =SUMIFS(Projects!$I$2:$I$293,Projects!$B$2:$B$293,$A13,Projects!$W$2:$W$293,"Y") -> 35
A14: Karnataka | B14: =SUMIFS(Projects!$J$2:$J$293,Projects!$B$2:$B$293,$A14,Projects!$O$2:$O$293,"A1",Projects!$W$2:$W$293,"Y") -> 120 | C14: =SUMIFS(Projects!$J$2:$J$293,Projects!$B$2:$B$293,$A14,Projects!$O$2:$O$293,"A2",Projects!$W$2:$W$293,"Y") -> 500 | D14: =SUMIFS(Projects!$J$2:$J$293,Projects!$B$2:$B$293,$A14,Projects!$O$2:$O$293,"B",Projects!$W$2:$W$293,"Y") -> 0 | E14: =SUMIFS(Projects!$J$2:$J$293,Projects!$B$2:$B$293,$A14,Projects!$O$2:$O$293,"C",Projects!$W$2:$W$293,"Y") -> 0 | F14: =SUMIFS(Projects!$J$2:$J$293,Projects!$B$2:$B$293,$A14,Projects!$O$2:$O$293,"D",Projects!$W$2:$W$293,"Y") -> 0 | G14: =SUM(B14:F14) -> 620 | H14: =SUMIFS(Projects!$H$2:$H$293,Projects!$B$2:$B$293,$A14,Projects!$W$2:$W$293,"Y") -> 0 | I14: =SUMIFS(Projects!$I$2:$I$293,Projects!$B$2:$B$293,$A14,Projects!$W$2:$W$293,"Y") -> 0
A15: All India (tracked) | B15: =SUM(B5:B14) -> 4562 | C15: =SUM(C5:C14) -> 11388 | D15: =SUM(D5:D14) -> 1040 | E15: =SUM(E5:E14) -> 5876.8 | F15: =SUM(F5:F14) -> 560.5 | G15: =SUM(G5:G14) -> 23427.3 | H15: =SUM(H5:H14) -> 615.5 | I15: =SUM(I5:I14) -> 2831.1
A17: Maharashtra by cluster (Include = Y)
A18: Cluster | B18: Total planned IT MW | C18: Operational IT MW | D18: UC / contracted IT MW | E18: Of which tier A1/A2/B
A19: Navi Mumbai - Taloja/Panvel | B19: =SUMIFS(Projects!$J$2:$J$293,Projects!$C$2:$C$293,$A19,Projects!$W$2:$W$293,"Y") -> 1480 | C19: =SUMIFS(Projects!$H$2:$H$293,Projects!$C$2:$C$293,$A19,Projects!$W$2:$W$293,"Y") -> 52 | D19: =SUMIFS(Projects!$I$2:$I$293,Projects!$C$2:$C$293,$A19,Projects!$W$2:$W$293,"Y") -> 292 | E19: =SUMIFS(Projects!$J$2:$J$293,Projects!$C$2:$C$293,$A19,Projects!$W$2:$W$293,"Y",Projects!$O$2:$O$293,"A1")+SUMIFS(Projects!$J$2:$J$293,Projects!$C$2:$C$293,$A19,Projects!$W$2:$W$293,"Y",Projects!$O$2:$O$293,"A2")+SUMIFS(Projects!$J$2:$J$293,Projects!$C$2:$C$293,$A19,Projects!$W$2:$W$293,"Y",Projects!$O$2:$O$293,"B") -> 750
A20: Maharashtra - multiple | B20: =SUMIFS(Projects!$J$2:$J$293,Projects!$C$2:$C$293,$A20,Projects!$W$2:$W$293,"Y") -> 0 | C20: =SUMIFS(Projects!$H$2:$H$293,Projects!$C$2:$C$293,$A20,Projects!$W$2:$W$293,"Y") -> 0 | D20: =SUMIFS(Projects!$I$2:$I$293,Projects!$C$2:$C$293,$A20,Projects!$W$2:$W$293,"Y") -> 0 | E20: =SUMIFS(Projects!$J$2:$J$293,Projects!$C$2:$C$293,$A20,Projects!$W$2:$W$293,"Y",Projects!$O$2:$O$293,"A1")+SUMIFS(Projects!$J$2:$J$293,Projects!$C$2:$C$293,$A20,Projects!$W$2:$W$293,"Y",Projects!$O$2:$O$293,"A2")+SUMIFS(Projects!$J$2:$J$293,Projects!$C$2:$C$293,$A20,Projects!$W$2:$W$293,"Y",Projects!$O$2:$O$293,"B") -> 0
A21: MMR - Palava/Ambernath/Taloja edge | B21: =SUMIFS(Projects!$J$2:$J$293,Projects!$C$2:$C$293,$A21,Projects!$W$2:$W$293,"Y") -> 2500 | C21: =SUMIFS(Projects!$H$2:$H$293,Projects!$C$2:$C$293,$A21,Projects!$W$2:$W$293,"Y") -> 0 | D21: =SUMIFS(Projects!$I$2:$I$293,Projects!$C$2:$C$293,$A21,Projects!$W$2:$W$293,"Y") -> 1450 | E21: =SUMIFS(Projects!$J$2:$J$293,Projects!$C$2:$C$293,$A21,Projects!$W$2:$W$293,"Y",Projects!$O$2:$O$293,"A1")+SUMIFS(Projects!$J$2:$J$293,Projects!$C$2:$C$293,$A21,Projects!$W$2:$W$293,"Y",Projects!$O$2:$O$293,"A2")+SUMIFS(Projects!$J$2:$J$293,Projects!$C$2:$C$293,$A21,Projects!$W$2:$W$293,"Y",Projects!$O$2:$O$293,"B") -> 2500
A22: MMR - Raigad/Pen | B22: =SUMIFS(Projects!$J$2:$J$293,Projects!$C$2:$C$293,$A22,Projects!$W$2:$W$293,"Y") -> 3000 | C22: =SUMIFS(Projects!$H$2:$H$293,Projects!$C$2:$C$293,$A22,Projects!$W$2:$W$293,"Y") -> 0 | D22: =SUMIFS(Projects!$I$2:$I$293,Projects!$C$2:$C$293,$A22,Projects!$W$2:$W$293,"Y") -> 0 | E22: =SUMIFS(Projects!$J$2:$J$293,Projects!$C$2:$C$293,$A22,Projects!$W$2:$W$293,"Y",Projects!$O$2:$O$293,"A1")+SUMIFS(Projects!$J$2:$J$293,Projects!$C$2:$C$293,$A22,Projects!$W$2:$W$293,"Y",Projects!$O$2:$O$293,"A2")+SUMIFS(Projects!$J$2:$J$293,Projects!$C$2:$C$293,$A22,Projects!$W$2:$W$293,"Y",Projects!$O$2:$O$293,"B") -> 3000
A23: Navi Mumbai - TTC/Thane-Belapur | B23: =SUMIFS(Projects!$J$2:$J$293,Projects!$C$2:$C$293,$A23,Projects!$W$2:$W$293,"Y") -> 2794 | C23: =SUMIFS(Projects!$H$2:$H$293,Projects!$C$2:$C$293,$A23,Projects!$W$2:$W$293,"Y") -> 397 | D23: =SUMIFS(Projects!$I$2:$I$293,Projects!$C$2:$C$293,$A23,Projects!$W$2:$W$293,"Y") -> 697 | E23: =SUMIFS(Projects!$J$2:$J$293,Projects!$C$2:$C$293,$A23,Projects!$W$2:$W$293,"Y",Projects!$O$2:$O$293,"A1")+SUMIFS(Projects!$J$2:$J$293,Projects!$C$2:$C$293,$A23,Projects!$W$2:$W$293,"Y",Projects!$O$2:$O$293,"A2")+SUMIFS(Projects!$J$2:$J$293,Projects!$C$2:$C$293,$A23,Projects!$W$2:$W$293,"Y",Projects!$O$2:$O$293,"B") -> 548
A24: Navi Mumbai - unspecified | B24: =SUMIFS(Projects!$J$2:$J$293,Projects!$C$2:$C$293,$A24,Projects!$W$2:$W$293,"Y") -> 245.5 | C24: =SUMIFS(Projects!$H$2:$H$293,Projects!$C$2:$C$293,$A24,Projects!$W$2:$W$293,"Y") -> 0 | D24: =SUMIFS(Projects!$I$2:$I$293,Projects!$C$2:$C$293,$A24,Projects!$W$2:$W$293,"Y") -> 5.5 | E24: =SUMIFS(Projects!$J$2:$J$293,Projects!$C$2:$C$293,$A24,Projects!$W$2:$W$293,"Y",Projects!$O$2:$O$293,"A1")+SUMIFS(Projects!$J$2:$J$293,Projects!$C$2:$C$293,$A24,Projects!$W$2:$W$293,"Y",Projects!$O$2:$O$293,"A2")+SUMIFS(Projects!$J$2:$J$293,Projects!$C$2:$C$293,$A24,Projects!$W$2:$W$293,"Y",Projects!$O$2:$O$293,"B") -> 0
A25: Maharashtra - unspecified | B25: =SUMIFS(Projects!$J$2:$J$293,Projects!$C$2:$C$293,$A25,Projects!$W$2:$W$293,"Y") -> 700 | C25: =SUMIFS(Projects!$H$2:$H$293,Projects!$C$2:$C$293,$A25,Projects!$W$2:$W$293,"Y") -> 0 | D25: =SUMIFS(Projects!$I$2:$I$293,Projects!$C$2:$C$293,$A25,Projects!$W$2:$W$293,"Y") -> 0 | E25: =SUMIFS(Projects!$J$2:$J$293,Projects!$C$2:$C$293,$A25,Projects!$W$2:$W$293,"Y",Projects!$O$2:$O$293,"A1")+SUMIFS(Projects!$J$2:$J$293,Projects!$C$2:$C$293,$A25,Projects!$W$2:$W$293,"Y",Projects!$O$2:$O$293,"A2")+SUMIFS(Projects!$J$2:$J$293,Projects!$C$2:$C$293,$A25,Projects!$W$2:$W$293,"Y",Projects!$O$2:$O$293,"B") -> 700
A26: MMR - Thane | B26: =SUMIFS(Projects!$J$2:$J$293,Projects!$C$2:$C$293,$A26,Projects!$W$2:$W$293,"Y") -> 272 | C26: =SUMIFS(Projects!$H$2:$H$293,Projects!$C$2:$C$293,$A26,Projects!$W$2:$W$293,"Y") -> 0 | D26: =SUMIFS(Projects!$I$2:$I$293,Projects!$C$2:$C$293,$A26,Projects!$W$2:$W$293,"Y") -> 0 | E26: =SUMIFS(Projects!$J$2:$J$293,Projects!$C$2:$C$293,$A26,Projects!$W$2:$W$293,"Y",Projects!$O$2:$O$293,"A1")+SUMIFS(Projects!$J$2:$J$293,Projects!$C$2:$C$293,$A26,Projects!$W$2:$W$293,"Y",Projects!$O$2:$O$293,"A2")+SUMIFS(Projects!$J$2:$J$293,Projects!$C$2:$C$293,$A26,Projects!$W$2:$W$293,"Y",Projects!$O$2:$O$293,"B") -> 272
A27: Mumbai (island/suburbs) | B27: =SUMIFS(Projects!$J$2:$J$293,Projects!$C$2:$C$293,$A27,Projects!$W$2:$W$293,"Y") -> 0 | C27: =SUMIFS(Projects!$H$2:$H$293,Projects!$C$2:$C$293,$A27,Projects!$W$2:$W$293,"Y") -> 0 | D27: =SUMIFS(Projects!$I$2:$I$293,Projects!$C$2:$C$293,$A27,Projects!$W$2:$W$293,"Y") -> 0 | E27: =SUMIFS(Projects!$J$2:$J$293,Projects!$C$2:$C$293,$A27,Projects!$W$2:$W$293,"Y",Projects!$O$2:$O$293,"A1")+SUMIFS(Projects!$J$2:$J$293,Projects!$C$2:$C$293,$A27,Projects!$W$2:$W$293,"Y",Projects!$O$2:$O$293,"A2")+SUMIFS(Projects!$J$2:$J$293,Projects!$C$2:$C$293,$A27,Projects!$W$2:$W$293,"Y",Projects!$O$2:$O$293,"B") -> 0
A28: Pune | B28: =SUMIFS(Projects!$J$2:$J$293,Projects!$C$2:$C$293,$A28,Projects!$W$2:$W$293,"Y") -> 256 | C28: =SUMIFS(Projects!$H$2:$H$293,Projects!$C$2:$C$293,$A28,Projects!$W$2:$W$293,"Y") -> 23.2 | D28: =SUMIFS(Projects!$I$2:$I$293,Projects!$C$2:$C$293,$A28,Projects!$W$2:$W$293,"Y") -> 9.6 | E28: =SUMIFS(Projects!$J$2:$J$293,Projects!$C$2:$C$293,$A28,Projects!$W$2:$W$293,"Y",Projects!$O$2:$O$293,"A1")+SUMIFS(Projects!$J$2:$J$293,Projects!$C$2:$C$293,$A28,Projects!$W$2:$W$293,"Y",Projects!$O$2:$O$293,"A2")+SUMIFS(Projects!$J$2:$J$293,Projects!$C$2:$C$293,$A28,Projects!$W$2:$W$293,"Y",Projects!$O$2:$O$293,"B") -> 96
A29: Maharashtra total | B29: =SUM(B19:B28) -> 11247.5 | C29: =SUM(C19:C28) -> 472.2 | D29: =SUM(D19:D28) -> 2454.1 | E29: =SUM(E19:E28) -> 7866
A31: Gap check - official totals vs. what this dataset can name
A32: Comparison | B32: Official / govt figure (MW) | C32: Tracked here (MW) | D32: Unnamed gap (MW) | E32: Tracked as % of official
A33: India: CEA projected additional DC demand by FY32 vs all tracked planned IT MW | B33: =Govt_Aggregates!$E$2 -> 26300 | C33: =G15 -> 23427.3 | D33: =B33-C33 -> 2872.7 | E33: =IF(B33=0,"-",C33/B33) -> 0.89077186
A34: Maharashtra: Industries/MIDC 44-project IT capacity vs tracked Maharashtra | B34: =Govt_Aggregates!$E$12 -> 23800 | C34: =B29 -> 11247.5 | D34: =B34-C34 -> 12552.5 | E34: =IF(B34=0,"-",C34/B34) -> 0.47258403
A35: Navi Mumbai Hub + Taloja Corridor (MIDC) vs tracked Navi Mumbai clusters | B35: =Govt_Aggregates!$E$15+Govt_Aggregates!$E$16 -> 7810 | C35: =B19+B23+B24 -> 4519.5 | D35: =B35-C35 -> 3290.5 | E35: =IF(B35=0,"-",C35/B35) -> 0.57868118
A36: Andhra Pradesh: 16 projects IT load (APTRANSCO) vs tracked AP | B36: =Govt_Aggregates!$E$18 -> 9100 | C36: =G6 -> 5148 | D36: =B36-C36 -> 3952 | E36: =IF(B36=0,"-",C36/B36) -> 0.56571429
A37: India installed today (MeitY) vs tracked operational IT MW | B37: =Govt_Aggregates!$E$6 -> 1575 | C37: =H15 -> 615.5 | D37: =B37-C37 -> 959.5 | E37: =IF(B37=0,"-",C37/B37) -> 0.39079365
A39: Reading the gap: a positive 'Unnamed gap' means government/utility documents point to more capacity than can be tied to named projects in this first pass - consistent with the client view.
A40: Tracked operational MW is far below MeitY's 1,575 MW because this pass focuses on new/large campuses, not the full installed base.
A41: Navi Mumbai cluster rows exclude Palava/Ambernath and Raigad-Pen (separate clusters); MIDC's 'Navi Mumbai Hub' definition is not published, so the comparison is indicative.
A43: Permit evidence - Maharashtra (MH_Permits sheet)
A44: Connected load in SEIAA/SEAC permit records (MW) | B44: =MH_Permits!M49 -> 644.622
A45: DG back-up in permit records (MVA) | B45: =MH_Permits!M50 -> 886.9
A46: Capital investment in MPCB consent records (Rs cr) | B46: =MH_Permits!M51 -> 29774.24
A47: STU grid connectivity granted at Ambernath alone (MW) | B47: =MH_Permits!M52 -> 1450
A48: Number of permit records | B48: =MH_Permits!M53 -> 45
A49: Six permit records alone (Google/EverYondr, CapitaLand, Iron Mountain, AWS Powai, Chandivali DC, Adani-Microsoft Bhosari) carry ~645 MW of connected load - several of these are absent from press trackers.
A50: National grid filings - CTUIL bulk-consumer GNA register (CTU_Bulk_Register sheet)
A51: State | B51: DC - named | C51: DC - likely (SPV pattern) | D51: Possible (purpose not stated) | E51: DC named + likely | F51: of which APPROVED
A52: Maharashtra | B52: =SUMIFS(CTU_Bulk_Register!$F$2:$F$184,CTU_Bulk_Register!$I$2:$I$184,$A52,CTU_Bulk_Register!$J$2:$J$184,"DC - named") -> 100 | C52: =SUMIFS(CTU_Bulk_Register!$F$2:$F$184,CTU_Bulk_Register!$I$2:$I$184,$A52,CTU_Bulk_Register!$J$2:$J$184,"DC - likely (SPV pattern)") -> 1968 | D52: =SUMIFS(CTU_Bulk_Register!$F$2:$F$184,CTU_Bulk_Register!$I$2:$I$184,$A52,CTU_Bulk_Register!$J$2:$J$184,"Possible (purpose not stated)") -> 50 | E52: =B52+C52 -> 2068 | F52: =SUMIFS(CTU_Bulk_Register!$F$2:$F$184,CTU_Bulk_Register!$I$2:$I$184,$A52,CTU_Bulk_Register!$J$2:$J$184,"DC*",CTU_Bulk_Register!$H$2:$H$184,"Approved") -> 1468
A53: Andhra Pradesh | B53: =SUMIFS(CTU_Bulk_Register!$F$2:$F$184,CTU_Bulk_Register!$I$2:$I$184,$A53,CTU_Bulk_Register!$J$2:$J$184,"DC - named") -> 2323 | C53: =SUMIFS(CTU_Bulk_Register!$F$2:$F$184,CTU_Bulk_Register!$I$2:$I$184,$A53,CTU_Bulk_Register!$J$2:$J$184,"DC - likely (SPV pattern)") -> 250 | D53: =SUMIFS(CTU_Bulk_Register!$F$2:$F$184,CTU_Bulk_Register!$I$2:$I$184,$A53,CTU_Bulk_Register!$J$2:$J$184,"Possible (purpose not stated)") -> 0 | E53: =B53+C53 -> 2573 | F53: =SUMIFS(CTU_Bulk_Register!$F$2:$F$184,CTU_Bulk_Register!$I$2:$I$184,$A53,CTU_Bulk_Register!$J$2:$J$184,"DC*",CTU_Bulk_Register!$H$2:$H$184,"Approved") -> 0
A54: Telangana | B54: =SUMIFS(CTU_Bulk_Register!$F$2:$F$184,CTU_Bulk_Register!$I$2:$I$184,$A54,CTU_Bulk_Register!$J$2:$J$184,"DC - named") -> 1700 | C54: =SUMIFS(CTU_Bulk_Register!$F$2:$F$184,CTU_Bulk_Register!$I$2:$I$184,$A54,CTU_Bulk_Register!$J$2:$J$184,"DC - likely (SPV pattern)") -> 2402 | D54: =SUMIFS(CTU_Bulk_Register!$F$2:$F$184,CTU_Bulk_Register!$I$2:$I$184,$A54,CTU_Bulk_Register!$J$2:$J$184,"Possible (purpose not stated)") -> 0 | E54: =B54+C54 -> 4102 | F54: =SUMIFS(CTU_Bulk_Register!$F$2:$F$184,CTU_Bulk_Register!$I$2:$I$184,$A54,CTU_Bulk_Register!$J$2:$J$184,"DC*",CTU_Bulk_Register!$H$2:$H$184,"Approved") -> 0
A55: Tamil Nadu | B55: =SUMIFS(CTU_Bulk_Register!$F$2:$F$184,CTU_Bulk_Register!$I$2:$I$184,$A55,CTU_Bulk_Register!$J$2:$J$184,"DC - named") -> 70 | C55: =SUMIFS(CTU_Bulk_Register!$F$2:$F$184,CTU_Bulk_Register!$I$2:$I$184,$A55,CTU_Bulk_Register!$J$2:$J$184,"DC - likely (SPV pattern)") -> 0 | D55: =SUMIFS(CTU_Bulk_Register!$F$2:$F$184,CTU_Bulk_Register!$I$2:$I$184,$A55,CTU_Bulk_Register!$J$2:$J$184,"Possible (purpose not stated)") -> 0 | E55: =B55+C55 -> 70 | F55: =SUMIFS(CTU_Bulk_Register!$F$2:$F$184,CTU_Bulk_Register!$I$2:$I$184,$A55,CTU_Bulk_Register!$J$2:$J$184,"DC*",CTU_Bulk_Register!$H$2:$H$184,"Approved") -> 0
A56: Karnataka | B56: =SUMIFS(CTU_Bulk_Register!$F$2:$F$184,CTU_Bulk_Register!$I$2:$I$184,$A56,CTU_Bulk_Register!$J$2:$J$184,"DC - named") -> 120 | C56: =SUMIFS(CTU_Bulk_Register!$F$2:$F$184,CTU_Bulk_Register!$I$2:$I$184,$A56,CTU_Bulk_Register!$J$2:$J$184,"DC - likely (SPV pattern)") -> 0 | D56: =SUMIFS(CTU_Bulk_Register!$F$2:$F$184,CTU_Bulk_Register!$I$2:$I$184,$A56,CTU_Bulk_Register!$J$2:$J$184,"Possible (purpose not stated)") -> 0 | E56: =B56+C56 -> 120 | F56: =SUMIFS(CTU_Bulk_Register!$F$2:$F$184,CTU_Bulk_Register!$I$2:$I$184,$A56,CTU_Bulk_Register!$J$2:$J$184,"DC*",CTU_Bulk_Register!$H$2:$H$184,"Approved") -> 0
A57: Gujarat | B57: =SUMIFS(CTU_Bulk_Register!$F$2:$F$184,CTU_Bulk_Register!$I$2:$I$184,$A57,CTU_Bulk_Register!$J$2:$J$184,"DC - named") -> 0 | C57: =SUMIFS(CTU_Bulk_Register!$F$2:$F$184,CTU_Bulk_Register!$I$2:$I$184,$A57,CTU_Bulk_Register!$J$2:$J$184,"DC - likely (SPV pattern)") -> 2130 | D57: =SUMIFS(CTU_Bulk_Register!$F$2:$F$184,CTU_Bulk_Register!$I$2:$I$184,$A57,CTU_Bulk_Register!$J$2:$J$184,"Possible (purpose not stated)") -> 14600 | E57: =B57+C57 -> 2130 | F57: =SUMIFS(CTU_Bulk_Register!$F$2:$F$184,CTU_Bulk_Register!$I$2:$I$184,$A57,CTU_Bulk_Register!$J$2:$J$184,"DC*",CTU_Bulk_Register!$H$2:$H$184,"Approved") -> 0
A58: Rajasthan | B58: =SUMIFS(CTU_Bulk_Register!$F$2:$F$184,CTU_Bulk_Register!$I$2:$I$184,$A58,CTU_Bulk_Register!$J$2:$J$184,"DC - named") -> 100 | C58: =SUMIFS(CTU_Bulk_Register!$F$2:$F$184,CTU_Bulk_Register!$I$2:$I$184,$A58,CTU_Bulk_Register!$J$2:$J$184,"DC - likely (SPV pattern)") -> 0 | D58: =SUMIFS(CTU_Bulk_Register!$F$2:$F$184,CTU_Bulk_Register!$I$2:$I$184,$A58,CTU_Bulk_Register!$J$2:$J$184,"Possible (purpose not stated)") -> 0 | E58: =B58+C58 -> 100 | F58: =SUMIFS(CTU_Bulk_Register!$F$2:$F$184,CTU_Bulk_Register!$I$2:$I$184,$A58,CTU_Bulk_Register!$J$2:$J$184,"DC*",CTU_Bulk_Register!$H$2:$H$184,"Approved") -> 0
A59: Haryana | B59: =SUMIFS(CTU_Bulk_Register!$F$2:$F$184,CTU_Bulk_Register!$I$2:$I$184,$A59,CTU_Bulk_Register!$J$2:$J$184,"DC - named") -> 0 | C59: =SUMIFS(CTU_Bulk_Register!$F$2:$F$184,CTU_Bulk_Register!$I$2:$I$184,$A59,CTU_Bulk_Register!$J$2:$J$184,"DC - likely (SPV pattern)") -> 50 | D59: =SUMIFS(CTU_Bulk_Register!$F$2:$F$184,CTU_Bulk_Register!$I$2:$I$184,$A59,CTU_Bulk_Register!$J$2:$J$184,"Possible (purpose not stated)") -> 0 | E59: =B59+C59 -> 50 | F59: =SUMIFS(CTU_Bulk_Register!$F$2:$F$184,CTU_Bulk_Register!$I$2:$I$184,$A59,CTU_Bulk_Register!$J$2:$J$184,"DC*",CTU_Bulk_Register!$H$2:$H$184,"Approved") -> 0
A60: Total | B60: =SUM(B52:B59) -> 4413 | C60: =SUM(C52:C59) -> 6800 | D60: =SUM(D52:D59) -> 14650 | E60: =SUM(E52:E59) -> 11213 | F60: =SUM(F52:F59) -> 1468
A61: Every applicant here has asked the central grid for >= 50 MW. Data-centre SPVs alone (named + likely) have filed for multi-GW of direct ISTS access - most of it from SPVs that do not appear in press trackers. Reliance's 14.65 GW is shown separately because its purpose is not stated.

Sheet Projects
A1: ID | B1: State | C1: Cluster | D1: Micro-location | E1: Developer / operator | F1: Partner / tenant | G1: Project / campus | H1: IT MW - operational | I1: IT MW - under construction / contracted | J1: IT MW - total planned (campus) | K1: Grid / facility power (as stated) | L1: Investment (Rs crore) | M1: Status | N1: Timeline | O1: Evidence tier | P1: Source type | Q1: Primary source | R1: Link 1 | S1: Link 2 | T1: Source date | U1: Key data point (as stated in source) | V1: Read in source document? (Y/N) | W1: Include in totals (Y/N) | X1: Notes / conflicts / double-count | Y1: Navi Mumbai / MMR focus
A2: P001 | B2: Maharashtra | C2: Navi Mumbai - Taloja/Panvel | D2: Taloja campus | E2: AdaniConneX (Adani Ent.-EdgeConneX 50:50 JV) | F2: CoreWeave (sole tenant) | G2: AdaniConneX Taloja - CoreWeave AI campus | I2: 240 | J2: 480 | K2: 3 x 80 MW buildings; DLC GPU halls | M2: Contracted / under development | N2: First phase mid-2028 | O2: C | P2: Company press release | Q2: CoreWeave investor release: CoreWeave enters India with AdaniConneX | R2: https://investors.coreweave.com/news/news-details/2026/CoreWeave-Enters-India-Expanding-AI-Cloud-Platform-With-AdaniConneX/default.aspx | S2: https://inc42.com/buzz/coreweave-enters-india-partners-adaniconnex-for-240-mw-data-centre-capacity/ | T2: 2026-10-06 | U2: 240 MW across three 80 MW buildings at Taloja; option for further 240 MW (480 MW total) | V2: N | W2: Y | X2: Overlaps with AdaniConneX 'Navi Mumbai 110 MW' (30 + 80 MW buildings) in Adani Ent. Q1 FY27 deck - the 80 MW building is likely the first CoreWeave building. Counted here, not in the AEL row. | Y2: Y
A3: P002 | B3: Maharashtra | C3: Navi Mumbai - Taloja/Panvel | D3: Navi Mumbai | E3: AdaniConneX | F3: - | G3: AdaniConneX Navi Mumbai (per AEL filing) | H3: 0 | I3: 110 | J3: 110 | M3: Under construction | N3: - | O3: B | P3: Investor presentation (exchange filing) | Q3: Adani Enterprises Q1 FY27 earnings presentation, slide 15 | R3: https://www.adanienterprises.com/-/media/Project/Enterprises/Investors/Investor-Downloads/Results-Presentations/AEL_Investor_Presentation.pdf | T3: 2026-07 | U3: 'Navi Mumbai - Execution started for 2 buildings - 30 & 80* MW'; total 110 MW; *80 MW revised down from 136 MW | V3: Y | W3: N | X3: Excluded from totals to avoid double counting with CoreWeave 240 MW row. | Y3: Y
A4: P003 | B4: Maharashtra | C4: Navi Mumbai - Taloja/Panvel | D4: Navi Mumbai site (aggregator) | E4: AdaniConneX | F4: - | G4: AdaniConneX 'Navi' site - potential IT load | J4: 1000 | M4: Planned (potential) | N4: RFS Dec 2026 onwards | O4: D | P4: Aggregator listing | Q4: datacenters.com listing | R4: https://www.datacenters.com/adaniconnex-navi | T4: n.d. | U4: 1,000 MW potential IT load | V4: N | W4: N | X4: Potential site capacity only; shown for reference. Adani's 2024 Maharashtra MoU (1 GW, Rs 50,000 cr) is the umbrella commitment. | Y4: Y
A5: P004 | B5: Maharashtra | C5: Maharashtra - multiple | D5: Mumbai/Navi Mumbai & Pune | E5: Adani Group | F5: - | G5: Adani Maharashtra hyperscale MoU (Davos 2024) | J5: 1000 | L5: 50000 | M5: MoU | N5: 10 years | O5: A2 | P5: State MoU (reported) | Q5: Adani newsroom: Govt of Maharashtra MoU | R5: https://www.adani.com/newsroom/media-releases/government-of-maharashtra | T5: 2024-01 | U5: MoU for 1 GW hyperscale data infrastructure, Rs 50,000 crore over 10 years | V5: N | W5: N | X5: Umbrella MoU; AdaniConneX Navi Mumbai / Pune rows sit within it. | Y5: Y
A6: P005 | B6: Maharashtra | C6: MMR - Palava/Ambernath/Taloja edge | D6: Asode & Burdul villages (near Taloja; ex-Lodha land) | E6: Amazon Data Services India (AWS) | F6: - | G6: AWS Taloja/Palava data centre campus | J6: 473 | K6: 473 MW electricity requirement (per SEIAA application as reported) | L6: 4000 | M6: EC application filed with SEIAA | N6: Groundbreaking Mar 2026 | O6: A2 | P6: SEIAA environmental clearance application (reported) | Q6: Blitz India Media report on SEIAA application | R6: https://blitzindiamedia.com/west/amazon-taloja-data-center-environmental-clearance-seiaa-2026/ | S6: https://www.datacenterdynamics.com/en/news/aws-plans-430m-data-center-in-navi-mumbai-india/ | T6: 2026-04-28 | U6: 48.85 acres (197,692 sq m); BUA 393,938 sq m; 6 buildings (4 x 7-storey DCs); 473 MW; ~Rs 4,000 cr; land bought Nov-2024 from Macrotech (Lodha) for Rs 450 cr | V6: N | W6: N | X6: Land was bought from Lodha (Macrotech) -> sits inside/adjacent to Lodha Palava DC park; excluded to avoid double count with Lodha park row. Pull PARIVESH proposal for DG/power annexure. 473 MW figure appears to be facility power, not IT. | Y6: Y
A7: P006 | B7: Maharashtra | C7: MMR - Palava/Ambernath/Taloja edge | D7: Palava City, Thane/Raigad (approx. 370-400 acres) | E7: Lodha Developers (Macrotech) | F7: AWS, STT GDC, Digital Edge (land buyers) | G7: Lodha Green Integrated Data Centre Park, Palava | I7: 1450 | J7: 2500 | K7: MERC Case 88/2026: 400/220 kV GIS Ambernath S/S, 4 x 500 MVA ICT (DDF, Lodha-funded); STU connectivity granted ~1,450 MW (AWS, STT) + ~1,500 MW under process = 2,950 MW by 2028 | L7: 130000 | M7: MERC order 01-Jun-2026; STU connectivity granted; land being sold | N7: Substation & DC load by 2028 | O7: A1 | P7: MERC order (read) + State MoUs | Q7: MERC order in Case No. 88 of 2026 & IA 78 of 2026 (01-06-2026) | R7: https://merc.gov.in/wp-content/uploads/2026/06/Order-88-of-2026.pdf | S7: https://www.saurenergy.com/solar-energy-news/maharashtra-approves-transmission-infrastructure-for-13-lakh-crore-data-centre-park-11902218 | T7: 2026-06-01 | U7: Order para 7.6: 'STU has already granted grid connectivity to Amazon Web Services (AWS) and ST Telemedia Global Data Centres (STT), while the connectivity application of another Data Center is under process'; para 7.15: ~1450 MW granted, ~1500 MW under consideration, 2950 MW by 2028 | V7: Y | W7: Y | X7: 'UC/contracted' column holds the ~1,450 MW of grid connectivity granted per the MERC order. Capacity cited as 2 / 2.5 / 3 GW across sources. Tenants AWS (473 MW), Digital Edge (~270 MW) and STT (24 acres) are inside this total. | Y7: Y
A8: P007 | B8: Maharashtra | C8: MMR - Palava/Ambernath/Taloja edge | D8: Palava (~30 acres) | E8: Digital Edge India (Digital Edge-NIIF JV) | F8: - | G8: Digital Edge second Mumbai campus (Palava) | J8: 270 | M8: Land acquired | N8: - | O8: D | P8: Press | Q8: W.Media: Palava land deal points to Digital Edge's second India DC | R8: https://w.media/palava-land-deal-points-to-digital-edges-second-india-data-center/ | S8: https://finimize.com/content/lodha-confirms-palava-land-sale-to-data-center-builder | T8: 2026-07 | U8: ~30 acres bought at ~Rs 42 cr/acre; ~270 MW reported (not confirmed by Lodha) | V8: N | W8: N | X8: Inside Lodha park - excluded from totals. | Y8: Y
A9: P008 | B9: Maharashtra | C9: MMR - Palava/Ambernath/Taloja edge | D9: Palava (24+ acres) | E9: STT GDC India | F9: - | G9: STT GDC Palava land | L9: 500 | M9: Land acquired | N9: - | O9: D | P9: Press / Wikipedia | Q9: Data centre industry in India (Wikipedia, citing press) | R9: https://en.wikipedia.org/wiki/Data_centre_industry_in_India | T9: 2025-09 | U9: 24+ acres for ~Rs 500 cr | V9: N | W9: N | X9: Inside Lodha park; MW not disclosed. | Y9: Y
A10: P009 | B10: Maharashtra | C10: MMR - Raigad/Pen | D10: Raigad Pen Growth Centre ('Orange City'), Pen taluka | E10: AirTrunk (Blackstone/CPP) | F10: - | G10: AirTrunk Raigad mega-campus | J10: 3000 | L10: 200000 | M10: Letter of Intent for land allotment | N10: - | O10: A2 | P10: State LoI (announced by CM) | Q10: ANI: Maharashtra issues LoI to AirTrunk for Rs 2 lakh crore DC project in Raigad | R10: https://www.aninews.in/news/business/maharashtra-issues-letter-of-intent-to-airtrunk-for-rs-2-lakh-crore-data-centre-project-in-raigad20260601123602/ | S10: https://techcrunch.com/2026/06/05/airtrunk-commits-30b-to-build-5gw-of-ai-data-centers-in-india/ | T10: 2026-06-01 | U10: 3 GW IT capacity, Rs 2 lakh crore (~US$21bn); part of AirTrunk's US$30bn / 5 GW India plan | V10: N | W10: Y | X10: MMRDA secured 216 acres for Raigad-Pen Growth Centre (MMRDA PR 17/2026). Unverified aggregator reports of Mapletree (100 acres) also at Raigad-Pen. | Y10: Y
A11: P010 | B11: Maharashtra | C11: Navi Mumbai - TTC/Thane-Belapur | D11: Mahape | E11: NTT Global Data Centers | F11: - | G11: NTT NAV2 campus | J11: 336 | K11: 500 MW campus power | M11: Planned / under development | N11: - | O11: C | P11: Company announcement (via DCD) | Q11: DCD: NTT announces 500MW NAV2 data center in Navi Mumbai | R11: https://www.datacenterdynamics.com/en/news/ntt-announces-500mw-nav2-data-center-in-navi-mumbai-india/ | S11: https://www.globaldatacenterhub.com/p/the-new-center-of-gravity-inside | T11: 2026 | U11: 500 MW power; 336 MW IT across three facilities | V11: N | W11: Y | X11: ICRA (2025) puts NTT GDC India total at ~280 MW; capex Rs 1,200-1,500 cr/yr FY26-28. | Y11: Y
A12: P011 | B12: Maharashtra | C12: Navi Mumbai - TTC/Thane-Belapur | D12: Mahape (NAV1A) | E12: NTT Global Data Centers | F12: - | G12: NTT NAV1A | H12: 30 | J12: 30 | M12: Operational | N12: - | O12: C | P12: Company website | Q12: NTT Navi Mumbai data center page | R12: https://services.global.ntt/en-us/services-and-products/global-data-centers/global-locations/india/navi-mumbai-data-center | T12: n.d. | U12: 37,000 m2; 5,000 racks; 30 MW IT | V12: N | W12: Y | Y12: Y
A13: P012 | B13: Maharashtra | C13: Navi Mumbai - TTC/Thane-Belapur | D13: Plot IT-07, TTC Industrial Area, Mahape | E13: Nxtra Data Ltd (Bharti Airtel) | F13: - | G13: Nxtra Mahape DC-02 expansion | K13: Not in cover pages - see EC annexure on PARIVESH | M13: Environmental clearance granted (expansion) | N13: - | O13: A1 | P13: SEIAA Maharashtra environmental clearance | Q13: EC letter, proposal SIA/MH/INFRA2/490756/2025, EC id EC24C3802MH5926451N | R13: https://assets.airtel.in/nxtra/pdf/EC_Environmental_Clearance_Certificate_Nxtra%20Mahape_DC-02_25.11.25.pdf | T13: 2025-11-21 | U13: EC for expansion of IT/ITeS (datacenter) unit; SEIAA meeting 14/10/2025; Category B2, item 8(a) | V13: Y | W13: N | X13: MW not yet extracted (scanned PDF; salient features in Annexure). Nxtra Mumbai page lists Mahape hyperscale sites at 4/7/18/42 MW IT. Nxtra group: ~250-300 MW, target 1 GW. | Y13: Y
A14: P013 | B14: Maharashtra | C14: Navi Mumbai - TTC/Thane-Belapur | D14: Survey 238/2, Kalwa / Ghansoli, Thane-Belapur Rd | E14: Digital Edge DC (India) | F14: NIIF | G14: Digital Edge BOM campus (BOM1-BOM3) | H14: 40 | I14: 48 | J14: 400 | K14: 83 MW solar PPA (Hexa) | M14: BOM1 operational; BOM2 topped out; BOM3 started | N14: - | O14: A1 | P14: SEIAA EC + company | Q14: SEIAA EC letter, proposal SIA/MH/INFRA2/449922/2023, EC id EC24B039MH149609 | R14: https://www.digitaledgedc.com/wp-content/uploads/2025/07/EC-Letter-Data-Center.pdf | S14: https://www.digitaledgedc.com/digital-edge-india/ | T14: 2024-02-08 | U14: EC granted for 'BOM' data center (Cat B, 8(b)); company: 400 MW Navi Mumbai campus, ~47 acres; BOM2 48.4 MW | V14: Y | W14: Y | X14: Campus sized at 300 / 350 / 400 MW in different company materials. MPCB CTE 0000195775 (3rd CAC 2024-25) for 'BOM 2 & BOM 3', Dighe S.No. 47/2-49/2: plot 172,354 m2, BUA 390,772 m2, 8 buildings, CI Rs 3,000 cr (EC dated 08-02-2024 matches this EC). CTO 0000225726 issued 03-04-2025. See MH_Permits. | Y14: Y
A15: P014 | B15: Maharashtra | C15: Navi Mumbai - TTC/Thane-Belapur | D15: TTC Rabale (Plot R-847) | E15: Sify Infinit Spaces | F15: - | G15: Sify Rabale hyperscale campus | H15: 85 | I15: 40 | J15: 377 | M15: 5 towers live; 7 more planned | N15: - | O15: C | P15: Company website / IR deck | Q15: Sify Rabale campus page | R15: https://www.sifytechnologies.com/data-center/rabale-data-center/ | S15: https://sifyinfinitspaces.com/wp-content/uploads/2025/07/Sify-Infinit-Spaces-IR-2025.pdf | T15: 2025-26 | U15: Designed for 377+ MW IT across 12 towers (earlier 240+ MW); 2022 factsheet: 5 towers / 85 MW | V15: N | W15: Y | X15: IFC SLL (Jun-2026) for two new DCs in Navi Mumbai + Chennai totalling 103 MW. DRHP (Oct-2025): 188 MW built IT India-wide. | Y15: Y
A16: P015 | B16: Maharashtra | C16: Navi Mumbai - Taloja/Panvel | D16: Panvel (Hiranandani Fortune City) | E16: Yotta Infrastructure (Hiranandani) | F16: - | G16: Yotta NM1 / NM2 DC park | H16: 52 | I16: 52 | J16: 250 | M16: NM1 operational; NM2 operational/fit-out | N16: - | O16: C | P16: Company website | Q16: Yotta NM1 page | R16: https://colocation.yotta.com/data-center/nm1-datacenter-mumbai-region-maharashtra/ | S16: https://dcpulse.com/project/yotta-nm2-navi-mumbai-datacenter | T16: 2026 | U16: NM1 52 MW IT; park 5 buildings ~210-250 MW; 'scalable to 1 GW' | V16: N | W16: Y | X16: NM2 cited at 52 or 65 MW. REALITY CHECK: CRISIL rationale (15-Apr-2025) on NMDC Data Centre Pvt Ltd (Hiranandani/Yotta SPV for NM1) shows ~13.1 MW colocation operational, rising to ~17.2 MW by FY27, rest for Shakti Cloud GPUs; holds captive discom licence. MPCB renewal 0000223122 (May-2025) covers Bhokarpada (Panvel) AND Talegaon Panshil (Khalapur) - a second site. | Y16: Y
A17: P016 | B17: Maharashtra | C17: Navi Mumbai - TTC/Thane-Belapur | D17: Mahape | E17: CtrlS Datacenters | F17: - | G17: CtrlS Mumbai DC1-DC7 | H17: 119 | I17: 95 | J17: 700 | M17: DC1-DC5 operational; DC6-DC7 upcoming | N17: - | O17: C | P17: Company website | Q17: CtrlS homepage / Mumbai visit page | R17: https://www.ctrls.com/ | S17: https://www.ctrls.com/dc-visit-mumbai/ | T17: 2025-26 | U17: DC1/2 40 MW, DC3 10, DC4 36.8, DC5 32; DC6+DC7 95 MW upcoming; campus '13 buildings, 700 MW IT' | V17: N | W17: Y | X17: 700 MW is a marketing claim. | Y17: Y
A18: P017 | B18: Maharashtra | C18: Navi Mumbai - TTC/Thane-Belapur | D18: Mahape (11.5 acres) + new TTC parcel | E18: STT GDC India | F18: - | G18: STT Navi Mumbai campus | H18: 53 | I18: 80 | J18: 133 | K18: Dual 220 kV & 400 kV substation feed | M18: 2 x 40 MW buildings due 2026 | N18: 2026 | O18: C | P18: Company website / brochure | Q18: STT GDC Mumbai locations page | R18: https://www.sttelemediagdc.com/in-en/locations/mumbai | S18: https://www.communicationstoday.co.in/stt-gdc-india-buys-navi-mumbai-land-for-%E2%82%B9282-crore-data-centre-project/ | T18: 2024-26 | U18: Total 133 MW after 3 new buildings; separate TTC land parcel bought May/Jun 2026 for Rs 282 cr (MW not disclosed) | V18: N | W18: Y | X18: Operational figure derived (133 minus 80 under construction). MPCB: CTE 0000175818 (Dec-2023) & CTO part 0000209776 for Gen-50/1, TTC Khairane; consent amended to REMOVE 31 x 2,000 kVA DG sets (13th CAC 2024-25). STU also granted STT grid connectivity at Ambernath (MERC Case 88/2026). | Y18: Y
A19: P018 | B19: Maharashtra | C19: Navi Mumbai - TTC/Thane-Belapur | D19: Airoli (MU1) & Navi Mumbai (MU2, 10 acres) | E19: Princeton Digital Group | F19: - | G19: PDG MU1 expansion + MU2 | H19: 48 | I19: 100 | J19: 220 | M19: MU1 phase-1 of 100 MW expansion UC; MU2 construction Apr 2026 | N19: - | O19: C | P19: Company (via DCD) | Q19: DCD: PDG breaks ground on latest Mumbai data center | R19: https://www.datacenterdynamics.com/en/news/pdg-breaks-ground-on-latest-mumbai-data-center/ | S19: https://www.datacentermap.com/india/navi-mumbai/princeton-digital-mu2/ | T19: 2026-04 | U19: MU2 120 MW IT; MU1 100 MW expansion | V19: N | W19: Y | X19: 48 MW operational = MU1 launch (DCD). | Y19: Y
A20: P019 | B20: Maharashtra | C20: Navi Mumbai - TTC/Thane-Belapur | D20: Airoli | E20: CapitaLand Investment | F20: - | G20: CapitaLand Data Centre Navi Mumbai 1 (+NM2) | I20: 108 | J20: 108 | K20: 108 MW power; on-site 220 kV GIS | M20: Under development | N20: Q4 2026 (first phase) | O20: C | P20: Company website | Q20: CapitaLand DC Navi Mumbai 1 listing | R20: https://www.capitaland.com/en/find-a-property/global-property-listing/data-centres/capitaland-s-datacentrenavimumbai1.html | T20: 2026 | U20: 108 MW; MPCB Consent to Establish listed among project documents | V20: N | W20: Y | X20: Some listings: 37 MW IT for first phase. CapitaLand's local SPV is Datascape Realty Pvt Ltd (Digha, TTC plots 14/2, 15 & 37): MPCB CTE 0000155369 CI Rs 3,211.9 cr; CTO (part) 0000231516 issued 09-02-2025; SEIAA EC proposal SIA/MH/INFRA2/466218/2024. See MH_Permits. | Y20: Y
A21: P020 | B21: Maharashtra | C21: Navi Mumbai - TTC/Thane-Belapur | D21: Mahape (5.4 ha) / Airoli | E21: AirTrunk (ex-Lumina CloudInfra) | F21: - | G21: AirTrunk BOM1 + BOM2 | I21: 62 | J21: 182 | K21: Dedicated 220 kV substations | M21: BOM1 under build (ex-Lumina, 60 MW Airoli); BOM2 planned | N21: - | O21: C | P21: Company website | Q21: AirTrunk BOM2 page | R21: https://airtrunk.com/location/bom2-mumbai/ | S21: https://www.datacenterdynamics.com/en/news/apac-data-center-firm-airtrunk-enters-india-acquires-lumina-cloudinfra/ | T21: 2026 | U21: BOM2 120+ MW, 5.4 ha, 220 kV S/S, PUE<1.4; BOM1 62+ MW, 2.4 ha | V21: N | W21: Y | X21: Lumina's Airoli SPV is Gramercy Techpark Pvt Ltd (Plot 7 & 7A, TTC Airoli): MPCB CTE 0000145905 - plot 24,350 m2, BUA 86,044 m2, CI Rs 1,495 cr; CTO (part) 13-05-2025; SEIAA EC expansion SIA/MH/INFRA2/484959/2024 (Oct/Nov-2025 agendas). | Y21: Y
A22: P021 | B22: Maharashtra | C22: Navi Mumbai - TTC/Thane-Belapur | D22: Thane-Belapur belt (15.4 acres) | E22: Data Center Holdings India LLP (Colt DCS-RMZ 50:50) | F22: - | G22: Colt DCS Navi Mumbai campus (Mumbai 1-3) | H22: 22 | I22: 64 | J22: 148 | K22: 220 kV GIS on campus | L22: 2016 | M22: Ph-1 22 MW (4 MW live Jul-2023); Mumbai 3 64 MW UC, fully pre-let | N22: - | O22: B | P22: Credit rating rationale | Q22: ICRA rationale - Data Center Holdings India LLP (Rs 1,440 cr TL, A-) | R22: https://www.icra.in/Rating/ShowRationalReportFilePdf/141442 | S22: https://indianinfrastructure.com/2026/10/16/colt-dcs-and-rmz-begin-construction-of-third-data-centre-in-mumbai/ | T22: 2026-03-09 | U22: ICRA: 142 MW expected across 3 phases; Ph-1 cost Rs 2,016 cr (71:29 D/E); 82% of Ph-1 unleased (Sep-2025). Oct-2026: Mumbai 3 (64 MW) started => campus 86 MW, 148 MW potential | V22: Y | W22: Y | X22: Same LLP received AP GO for 486 MW Vizag campus (see AP rows). | Y22: Y
A23: P022 | B23: Maharashtra | C23: Navi Mumbai - TTC/Thane-Belapur | D23: Navi Mumbai | E23: L&T-Vyoma | F23: - | G23: L&T Vyoma Navi Mumbai AI DC | I23: 40 | J23: 100 | M23: Under construction | N23: - | O23: C | P23: Company press release | Q23: L&T press release 21-Jan-2026 | R23: https://www.larsentoubro.com/pressreleases/2026/2026-01-21-larsen-toubro-vyoma-breaks-ground-on-40-mw-green-ai-ready-data-centre-in-navi-mumbai | T23: 2026-01-21 | U23: 40 MW phase-1 of 100 MW campus; direct-to-chip liquid cooling | V23: N | W23: Y | X23: Site is Plot EL-200, TTC Mahape: SEIAA EC proposal SIA/MH/INFRA2/517940/2025 (309th agenda, Oct-2025). | Y23: Y
A24: P023 | B24: Maharashtra | C24: Navi Mumbai - TTC/Thane-Belapur | D24: Rabale | E24: ESR | F24: - | G24: ESR Rabale DC | I24: 60 | J24: 60 | K24: Facility load up to 60 MW | M24: Under construction | N24: - | O24: D | P24: Press | Q24: CRN Asia: ESR enters India DC market with 60 MW facility | R24: https://www.crnasia.com/india/news/2026/esr-enters-india-data-centre-market-with-60-mw-facility-in-mumbai | T24: 2026 | U24: 60 MW facility load | V24: N | W24: Y | X24: Facility load, not IT load. | Y24: Y
A25: P024 | B25: Maharashtra | C25: Navi Mumbai - unspecified | D25: Navi Mumbai (29 acres, freehold) | E25: Zerra (AGPDC Global Holdings) | F25: - | G25: Zerra Navi Mumbai campus | J25: 240 | K25: 220 kV / 300 MVA + 100 kV / 40 MVA substations | M25: Construction commenced; power & pre-construction approvals received | N25: Oct 2026 start | O25: C | P25: Company website | Q25: Zerra Navi Mumbai project page | R25: https://zerradc.com/projects/navi-mumbai/ | T25: 2026-10 | U25: 240 MW IT; two independent substations; 'initial development consents received' | V25: N | W25: Y | X25: Relatively unknown developer; no press coverage found - an example of capacity not in mainstream announcements. | Y25: Y
A26: P025 | B26: Maharashtra | C26: Navi Mumbai - Taloja/Panvel | D26: Taloja | E26: Prestige Group | F26: - | G26: Prestige Taloja data centre | L26: 5000 | M26: State MoU | N26: Construction from 2026 | O26: A2 | P26: State MoU (reported) | Q26: DCD: Maharashtra partners with Prestige for Navi Mumbai DC | R26: https://www.datacenterdynamics.com/en/news/maharashtra-state-govt-partners-with-prestige-to-develop-data-center-in/ | T26: 2025-08 | U26: Rs 5,000 cr of Rs 12,500 cr MoU earmarked for DC at Taloja; 1,200 jobs | V26: N | W26: N | X26: MW not disclosed. | Y26: Y
A27: P026 | B27: Maharashtra | C27: Navi Mumbai - Taloja/Panvel | D27: Panvel, Khalapur, Taloja, Bhokharpada | E27: ReNew (ReNew Wind Energy) | F27: - | G27: ReNew Green Integrated DC Park (MMR) | J27: 750 | K27: Min. 51% green power | L27: 70000 | M27: State MoU | N27: Phased from 2028 | O27: A2 | P27: State MoU (reported) | Q27: Business Standard: ReNew signs MoU for Rs 70,000 cr green DC park | R27: https://www.business-standard.com/industry/news/renew-signs-mou-with-maharashtra-for-70-000-crore-green-data-centre-park-126100801226_1.html | S27: https://indianinfrastructure.com/2026/10/13/renew-signs-rs-700-billion-mou-with-maharashtra-government-to-develop-green-integrated-data-centre-park-in-mmr/ | T27: 2026-10-08 | U27: 750 MW, Rs 70,000 cr, multiple MMR sites | V27: N | W27: Y | Y27: Y
A28: P027 | B28: Maharashtra | C28: Maharashtra - unspecified | D28: Not disclosed | E28: Trentar Pvt Ltd (Dorf Ketal Group) | F28: - | G28: Trentar Green Integrated Hyperscale DC Park | J28: 500 | K28: Min. 51% RE + storage | L28: 30000 | M28: State LoI + MoU | N28: - | O28: A2 | P28: State LoI/MoU (company release) | Q28: PR Newswire: Trentar signs Rs 30,000 cr MoU | R28: https://www.prnewswire.com/in/news-releases/trentar-signs-30-000-crore-3-3-bn-mou-with-maharashtra-for-500-mw-green-integrated-data-center-park-302899623.html | T28: 2026-10-06 | U28: 500 MW; LoI received from state | V28: N | W28: Y | X28: Location not disclosed. | Y28: Y
A29: P028 | B29: Maharashtra | C29: Navi Mumbai - unspecified | D29: Navi Mumbai | E29: Avisirah Technologies | F29: - | G29: Avisirah Navi Mumbai DC | I29: 5.5 | J29: 5.5 | L29: 75 | M29: Financed | N29: - | O29: D | P29: Press | Q29: PropNewsTime: Avisirah raises Rs 75 cr | R29: https://propnewstime.com/latestnewsstories/MzY3MDg=/avisirah-raises-inr-75-crore-for-navi-mumbai-data-centre | T29: 2026 | U29: ~5.5 MW IT; Rs 75 cr loan | V29: N | W29: Y | X29: Small/enterprise example. | Y29: Y
A30: P029 | B30: Maharashtra | C30: Navi Mumbai - TTC/Thane-Belapur | D30: Plot D-31 & D-32, TTC Turbhe (EverYondr 'Mumbai 1') | E30: Amanthin Info Parks Pvt Ltd (EverYondr = Everstone + Yondr) | F30: Raiden Infotech India (Google) - 28-yr lease, ~3.81 lakh sq ft, Rs 8.83 cr/month (registered Oct-2022) | G30: Google / EverYondr Turbhe data centre | K30: Form-1A: connected load 103,367 kW; demand 108,807 kVA; 4 x 220/22 kV 60 MVA transformers; 58 x 2,200 kVA DG sets | M30: Under construction (target 2025-27) | N30: - | O30: A1 | P30: SEAC-II Form-1A (EC application) | Q30: Form 1A - Data Center by Amanthin Info Parks Pvt Ltd, Plot D-31 & D-32, TTC Turbhe | R30: https://environmentclearance.nic.in/DownloadPfdFile.aspx?FileName=Kwy+a1Xl%2FGHp2kMbJYBd8GPrFSz%2FNzzr1mrm87hA6RfsBvasy5U%2FhwjR4PRxBwwupD8Lw8MExL5FqtSFZLEOTQ%3D%3D&FilePath=93ZZBm8LWEXfg+HAlQix2fE2t8z%2FpgnoBhDlYdZCxzXTbTpOQqzWjBW0IF63rxBVcDlG0LKdfbGNs0Ou%2FTEvAA%3D%3D | S30: https://housing.com/news/google-rents-data-centre-space-in-navi-mumbai-midc/ | T30: n.d. (c.2022-23) | U30: Plot 39,980 m2; BUA 55,432 m2; ~103 MW connected load; 127.6 MVA of DG back-up | V30: Y | W30: N | X30: ~103 MW facility load => roughly 65-75 MW IT (assumes PUE 1.4-1.6) - IT MW left blank because not stated. Google's presence in Navi Mumbai is barely covered in the press. | Y30: Y
A31: P030 | B31: Maharashtra | C31: Navi Mumbai - TTC/Thane-Belapur | D31: GEN-2/1/A/1, D-Block, TTC Turbhe (ex-Gramercy Trade 'Gold Craft' plot) | E31: Raiden Infotech India Pvt Ltd (Google) | F31: - | G31: Google (Raiden) Turbhe data centre - own plot | K31: Not in agenda - see EC file | L31: 1895 | M31: MPCB Consent to Establish granted 26-08-2025; SEIAA EC proposal listed Oct-2025 | N31: - | O31: A1 | P31: MPCB CAC + SEIAA agenda | Q31: MPCB 5th CAC 2025-26 Action Taken Report (consent 0000249841); SEIAA 310th agenda (SIA/MH/INFRA2/531703/2025) | R31: https://mpcb.gov.in/en/cac-meetings | S31: https://www.ecmpcb.in/login/download_ec_document/ODY2MDg5MDRCMzNGNDNCN0JEMTFBNDUzNEI4MjlGNEQucGRm | T31: 2025-08-26 | U31: CTE approved for Raiden (Google) at Turbhe; same plot previously had CTE for 'Gold Craft by Gramercy Trade Industries' with CI Rs 1,895 cr (14th CAC 2023-24) | V31: Y | W31: N | X31: Investment shown is the earlier Gramercy CTE CI on the same plot - indicative only. Second Google site in Navi Mumbai. | Y31: Y
A32: P031 | B32: Maharashtra | C32: MMR - Thane | D32: Balkum & Majiwada villages, Thane (54.73 acres; ex-Kalpataru land) | E32: Amazon Data Services India (AWS) | F32: - | G32: AWS Thane (Balkum-Majiwada) campus | J32: 272 | L32: 7203 | M32: MPCB CTE granted 14-12-2023; SEIAA EC proposal SIA/MH/INFRA2/477127/2024 on agendas Nov-2024 & Sep-2025 | N32: - | O32: A1 | P32: MPCB CAC + SEIAA agendas | Q32: MPCB 16th CAC 2023-24 index & ATR (consent 0000178616); SEIAA 304th agenda | R32: https://mpcb.gov.in/en/cac-meetings | S32: https://www.ecmpcb.in/login/download_ec_document/RTE1NjUyREEwNzhCNEQ1MzkwRTZDQUVFOTNEQUIyRjYucGRm | T32: 2023-12-14 | U32: MPCB: 'Data Center by Amazon ... Balkum & Majiwada', CI Rs 7,203.29 cr, CTE approved. EC application (per public post of the filing): 54.73 acres, 272 MW total IT load | V32: Y | W32: Y | X32: 272 MW IT is from a social-media summary of the EC filing (https://x.com/cbdhage/status/1762797367529480646) - verify in EC file. Local political opposition (NCP-SP 'Out of Thane' campaign). | Y32: Y
A33: P032 | B33: Maharashtra | C33: Mumbai (island/suburbs) | D33: CTS 86 pt, Paspoli & CTS 115 pt Tungwa, Powai | E33: Amazon Data Services India (AWS) | F33: - | G33: AWS Powai data centre | L33: 2627 | M33: MPCB CTE granted 11-02-2025 (earlier SCN Dec-2023); SEIAA EC proposal SIA/MH/INFRA2/416132/2023 | N33: - | O33: A1 | P33: MPCB CAC | Q33: MPCB 15th CAC 2024-25 ATR (consent 0000217236) | R33: https://mpcb.gov.in/en/cac-meetings | T33: 2025-02-11 | U33: CI Rs 2,626.63 cr; CTE approved | V33: Y | W33: N | X33: MW not disclosed in CAC record. | Y33: N
A34: P033 | B34: Maharashtra | C34: Navi Mumbai - TTC/Thane-Belapur | D34: Plot ES-05, TTC Mahape | E34: Bearys Properties & Developments (build-to-suit; NTT NAV1A/1B developer) | F34: NTT (likely) | G34: Bearys ES-05 Mahape data centre | M34: SEIAA EC proposal Oct-2025 | N34: - | O34: A1 | P34: SEIAA agenda | Q34: SEIAA additional agenda, 310th meeting (SIA/MH/INFRA2/533354/2025) | R34: https://www.ecmpcb.in/login/download_ec_document/QjJCMzlBQzg5M0MzNDZERjg1NDQxQTZGN0YzQzE0MjMucGRm | S34: https://bearysgroup.com/wp-content/uploads/2024/01/Bearys-Data-Centre-e-brochure.pdf | T34: 2025-10-29 | U34: New EC application for data centre at ES-05 Mahape | V34: Y | W34: N | X34: Tenant not confirmed. | Y34: Y
A35: P034 | B35: Maharashtra | C35: Navi Mumbai - Taloja/Panvel | D35: S.No./Gut 39, 42, 49, Bhokarpada, Panvel | E35: Larsen & Toubro Ltd | F35: - | G35: L&T Bhokarpada data centre + residential | M35: SEIAA EC proposal (Sep & Dec-2025 agendas) | N35: - | O35: A1 | P35: SEIAA agendas | Q35: SEIAA 304th & 313th agendas (SIA/MH/INFRA2/502320/2024) | R35: https://www.ecmpcb.in/login/download_ec_document/MzMzQzM2MDM3QkQ5NEYxQUIyOTNEMjAyNEE2NUNFODgucGRm | T35: 2025-12-02 | U35: 'Proposed Data Centre and Residential development with retail and commercial components', Bhokarpada | V35: Y | W35: N | X35: Separate from L&T-Vyoma Mahape (EL-200, SIA/MH/INFRA2/517940/2025). Bhokarpada also hosts Yotta/Hiranandani and is a ReNew park site. | Y35: Y
A36: P035 | B36: Maharashtra | C36: Navi Mumbai - TTC/Thane-Belapur | D36: Plot A-GEN-4, TTC Rabale / Ghansoli | E36: Support Properties Pvt Ltd (K Raheja Corp group) for AdaniConneX ('ACXNMI-01') | F36: - | G36: AdaniConneX NMI-01 Rabale | M36: MPCB CTE 21-02-2024; SEIAA EC expansion proposal Oct-2025 | N36: - | O36: A1 | P36: MPCB CAC + SEIAA agenda | Q36: SEIAA 308th agenda (SIA/MH/INFRA2/509611/2024); MPCB 21st CAC 2023-24 (0000185134) | R36: https://www.ecmpcb.in/login/download_ec_document/MjMyMTI2NEMzMjYzNDM5M0IxRTJDRDY5MENBNDZFODcucGRm | S36: https://www.scribd.com/document/1014690774/Adaniconnex-Navi-Mumbai | T36: 2025-10-03 | U36: 'Expansion in EC for Proposed Data Center Project ACXNMI-01' | V36: Y | W36: N | X36: 'ACX' project code = AdaniConneX (inference). A Scribd document describes ACXNMI-02 as 3 buildings / 400 MW IT. Overlaps AdaniConneX rows above - excluded. | Y36: Y
A37: P036 | B37: Maharashtra | C37: Navi Mumbai - TTC/Thane-Belapur | D37: Plot R-978, Sector 8, Rabale MIDC | E37: Gargantuan Industrial Space Solutions Pvt Ltd | F37: Unknown | G37: Gargantuan Rabale data centre expansion | M37: SEIAA EC expansion proposal Oct-2025 | N37: - | O37: A1 | P37: SEIAA agenda | Q37: SEIAA 310th agenda (SIA/MH/INFRA2/496938/2024) | R37: https://www.ecmpcb.in/login/download_ec_document/ODY2MDg5MDRCMzNGNDNCN0JEMTFBNDUzNEI4MjlGNEQucGRm | T37: 2025-10-26 | U37: 'Proposed expansion in Data Centre [IT/ITeS] Project' | V37: Y | W37: N | X37: Owner/tenant not identified - candidate 'unannounced' project; check MCA filings. | Y37: Y
A38: P037 | B38: Maharashtra | C38: Navi Mumbai - TTC/Thane-Belapur | D38: IT-5 Airoli Knowledge Park (Gigaplex) & Gen 2/1/D-F Juinagar (Newfound) | E38: K Raheja Corp / Mindspace REIT SPVs (Gigaplex Estate; Newfound Properties & Leasing) | F38: - | G38: Data-centre buildings inside K Raheja IT parks | L38: 174 | M38: Gigaplex Bldg 8 (DC) CTO applied 2025-26; Newfound Bldg 5A (DC) CTO Part-I granted (17th CAC 2024-25) | N38: - | O38: A1 | P38: MPCB CAC + SEIAA agendas | Q38: MPCB 4th CAC 2025-26 index (0000232277) & 17th CAC 2024-25 ATR (0000227513); SEIAA 309th/310th/318th agendas | R38: https://mpcb.gov.in/en/cac-meetings | S38: https://environmentclearance.nic.in/writereaddata/FormB/agenda/2801202685869228318FinalAgenda.pdf | T38: 2025-26 | U38: Gigaplex Bldg 8 (Data Centre) CI Rs 173.99 cr; Newfound Bldg 5A data centre BUA 32,971 m2 | V38: Y | W38: N | X38: Powered-shell DC buildings leased to hyperscalers (tenants not disclosed). | Y38: Y
A39: P038 | B39: Maharashtra | C39: Navi Mumbai - TTC/Thane-Belapur | D39: TTC Rabale | E39: Web Werks India (Iron Mountain) | F39: - | G39: Web Werks / Iron Mountain Rabale | M39: MPCB CTE 28-09-2024 | N39: - | O39: A1 | P39: MPCB CAC | Q39: MPCB 6th CAC 2024-25 ATR (0000215272) | R39: https://mpcb.gov.in/en/cac-meetings | T39: 2024-09-28 | U39: CTE approved | V39: Y | W39: N | X39: MW not stated. | Y39: Y
A40: P039 | B40: Maharashtra | C40: Navi Mumbai - TTC/Thane-Belapur | D40: Plot 13, Kalwa Industrial Area, Digha | E40: Bridge Data Centres (Mumbai) LLP | F40: - | G40: Bridge Data Centres Mumbai | L40: 599 | M40: Operating (CTO renewals 2024, 2025) | N40: - | O40: A1 | P40: MPCB CAC | Q40: MPCB 15th CAC 2023-24 index (0000171036); 13th CAC 2024-25 ATR | R40: https://mpcb.gov.in/en/cac-meetings | T40: 2025-02-09 | U40: CI Rs 598.52 cr | V40: Y | W40: N | X40: Operator rarely in Indian press. | Y40: Y
A41: P040 | B41: Maharashtra | C41: Maharashtra - unspecified | D41: Site to be finalised | E41: MAHAPREIT (Govt of Maharashtra undertaking) | F41: Private developer via EOI | G41: MAHAPREIT 200 MW data centre | J41: 200 | K41: 200 MW total load | L41: 15000 | M41: EOI for transaction advisor/PMU (rolling to 15-Oct-2026) | N41: - | O41: A1 | P41: State PSU tender | Q41: MAHAPREIT EOI MHP/CGM(TP)/2026/02 & Corrigendum-1 (13-08-2026) | R41: https://mahapreit.in/assets/uploads/tender-ext-65-1786725791.pdf | T41: 2026-08-13 | U41: 200 MW total load (changed from 'IT load'); est. cost Rs 15,000 cr | V41: Y | W41: Y | X41: State-led DC project. | Y41: N
A42: P041 | B42: Maharashtra | C42: Pune | D42: Plot D-I-10-1, MIDC Pimpri Waghere ('PNQ06', 'ACXPNQ27/29') | E42: Microsoft India (filings by 'Pune Data Center Two Ltd') | F42: AdaniConneX (inferred from 'ACX' project codes) | G42: Microsoft Pune - Pimpri campus | L42: 5228 | M42: MPCB CTE (15th CAC 2022-23); SEIAA EC proposals 2025 | N42: - | O42: A1 | P42: MPCB CAC + SEIAA agendas | Q42: MPCB 15th CAC 2022-23 minutes/index (0000138540); SEIAA 296th & 313th agendas (SIA/MH/INFRA2/517690/2025, 543691/2025) | R42: https://mpcb.gov.in/en/cac-meetings | S42: https://www.ecmpcb.in/login/download_ec_document/MzMzQzM2MDM3QkQ5NEYxQUIyOTNEMjAyNEE2NUNFODgucGRm | T42: 2025 | U42: 'Data Center PNQ06 for Microsoft India': plot 101,182 m2, BUA 82,827 m2, CI Rs 5,227.84 cr | V42: Y | W42: N | X42: The 25-acre ex-Finolex plot ('could host 100 MW'). AdaniConneX Pune I/II (96 MW, B-tier row) may be this campus - excluded to avoid double count. | Y42: N
A43: P042 | B43: Maharashtra | C43: Pune | D43: BG 80/B, Bhosari ('PNQ04', 'ACXPNQ26') | E43: Microsoft Corporation India (filings by 'Pune Data Center Ltd') | F43: AdaniConneX (inferred) | G43: Microsoft Pune - Bhosari campus | L43: 2015 | M43: MPCB CTE (15th CAC 2022-23); SEIAA EC proposals 2025-26 | N43: - | O43: A1 | P43: MPCB CAC + SEIAA agendas | Q43: MPCB 15th CAC 2022-23 minutes (0000148492); SEIAA 296th/319th agendas (SIA/MH/INFRA2/517762/2025, 562044/2025) | R43: https://mpcb.gov.in/en/cac-meetings | S43: https://www.ecmpcb.in/login/download_ec_document/MEE0OEVGQjI1RjNDNENERjhCMDEwNkI0NjI1Njg2MjYucGRm | T43: 2025-26 | U43: Plot 44,499 m2, BUA 40,140 m2, CI Rs 2,014.74 cr | V43: Y | W43: N | Y43: N
A44: P043 | B44: Maharashtra | C44: Pune | D44: Pune I & II | E44: AdaniConneX | F44: - | G44: AdaniConneX Pune (48 MW x 2) | H44: 19.2 | I44: 9.6 | J44: 96 | M44: Pune I Ph I-II live; Pune II Ph I 98% | N44: - | O44: B | P44: Investor presentation (exchange filing) | Q44: Adani Enterprises Q1 FY27 presentation, slide 15 | R44: https://www.adanienterprises.com/-/media/Project/Enterprises/Investors/Investor-Downloads/Results-Presentations/AEL_Investor_Presentation.pdf | T44: 2026-07 | U44: Total 96 MW; operational 19.2 MW; 9.6 MW handed over 28-May-2026 | V44: Y | W44: Y | Y44: N
A45: P044 | B45: Maharashtra | C45: Pune | D45: Hinjewadi (2 x 16.4 acres) + Pimpri (25 acres) | E45: Microsoft | F45: - | G45: Microsoft Pune land bank | J45: 100 | L45: 973 | M45: Land acquired | N45: - | O45: D | P45: Press (land registrations) | Q45: DCD: Microsoft acquires 16-acre plot in Pune | R45: https://www.datacenterdynamics.com/en/news/microsoft-acquires-16-acre-plot-in-pune-india-for-data-center-expansion/ | S45: https://www.businessworld.in/article/microsoft-acquires-land-in-pune-for-rs-453-cr-to-expand-data-center-operations-533028 | T45: 2024-08/09 | U45: Rs 520 cr + Rs 453 cr Hinjewadi parcels; 25-acre Pimpri plot 'could host 100 MW' | V45: N | W45: Y | X45: 100 MW relates to Pimpri plot only. | Y45: N
A46: P045 | B46: Maharashtra | C46: Pune | D46: Rajiv Gandhi Infotech Park, Hinjewadi | E46: TCC Concept / NES Data | F46: - | G46: NES Data Hinjewadi campus | H46: 4 | J46: 60 | M46: MoU for land | N46: - | O46: C | P46: Listed company announcement (press) | Q46: Construction World: TCC Concept plans 60 MW campus | R46: https://www.constructionworld.in/policy-updates-and-economic-news/tcc-concept-plans-60-mw-data-centre-campus-in-pune/95832 | T46: 2026-08 | U46: Up to 60 MW IT; 4 MW existing Pune facility | V46: N | W46: Y | X46: Subject to due diligence/approvals. | Y46: N
A47: P046 | B47: Andhra Pradesh | C47: Visakhapatnam / Anakapalli | D47: Adavivaram-Mudasarlova (120 ac), Tarluvada (200 ac), Rambilli (160 ac) | E47: Raiden Infotech India (Google) | F47: Adani Infra, AdaniConneX, Adani Power, Bharti Airtel, Nxtra | G47: Google AI hub Vizag | J47: 1000 | M47: Land allotted by GO; ground broken Apr-2026 | N47: Ops 2028 | O47: A1 | P47: Government Order | Q47: AP ITE&C G.O.Ms.No.66 dt 02.12.2025 (ref. G.O.Ms.No.40 dt 11.10.2025) | R47: https://cdn.prod.website-files.com/5d70c9269b8d7bd25d8b1696/6a7eb3b63aaa0bf811886bd4_C5dmjgRvarnSVWAcsazFlsX-Tk7A3FFIaxfaW49XR8g.pdf | S47: https://www.googlecloudpresscorner.com/2026-04-28-Google-Breaks-Ground-on-India-AI-Hub,-Launching-a-National-Industrial-Ecosystem-Alongside-Indias-Digital-Infrastructure-Milestone | T47: 2025-12-02 | U47: 480 acres for AI DCs 'total capacity of around 1000 MW', US$15bn; notified partners incl. AdaniConneX & Nxtra | V47: Y | W47: Y | X47: AdaniConneX's 400 MW Vizag hyperscale order (Q1 FY27) is very likely part of this - excluded separately. | Y47: N
A48: P047 | B48: Andhra Pradesh | C48: Visakhapatnam / Anakapalli | D48: Vizag | E48: AdaniConneX | F48: Hyperscale customer (unnamed) | G48: AdaniConneX Vizag 400 MW order | I48: 400 | J48: 400 | M48: Execution started - 2 buildings (core & shell) | N48: - | O48: B | P48: Investor presentation (exchange filing) | Q48: Adani Enterprises Q1 FY27 presentation, slide 15 | R48: https://www.adanienterprises.com/-/media/Project/Enterprises/Investors/Investor-Downloads/Results-Presentations/AEL_Investor_Presentation.pdf | T48: 2026-07 | U48: 'During the quarter, 400 MW order signed with hyperscale customer for Vizag' | V48: Y | W48: N | X48: Likely inside Google/Raiden 1 GW - excluded. | Y48: N
A49: P048 | B49: Andhra Pradesh | C49: Visakhapatnam / Vizianagaram | D49: Vizianagaram district (per GO amendment reporting) | E49: Reliance Industries | F49: - | G49: Reliance giga-scale AI DC (AP) | J49: 1500 | L49: 108010 | M49: SIPB cleared; GO amended Jul-2026 | N49: - | O49: A2 | P49: SIPB approval / GO (reported) | Q49: Deccan Herald: Andhra SIPB clears RIL's Rs 1,08,010 cr Vizag DC | R49: https://www.deccanherald.com/india/andhra-pradesh/andhra-sipb-clears-rils-rs-108010-crore-vizag-data-centre-proposal-3993372 | S49: https://www.medianama.com/2026/08/223-andhra-pradesh-ai-data-centres/ | T49: 2026-05 | U49: Rs 1,08,010 cr; MW not stated | V49: N | W49: Y | X49: 1,500 MW is DERIVED (MediaNama total 3,498 MW minus 1,000+486+512) - verify against GO. | Y49: N
A50: P049 | B50: Andhra Pradesh | C50: Visakhapatnam / Anakapalli | D50: Makavaripalem, Anakapalli | E50: ReNew (Renew AP Green Data Center) | F50: - | G50: Renew AP Green Data Center | J50: 1000 | L50: 85200 | M50: GO issued (Aug-2026) | N50: - | O50: A2 | P50: Government Order (reported) | Q50: MediaNama: AP clears four data centres worth Rs 2.83 lakh cr | R50: https://www.medianama.com/2026/08/223-andhra-pradesh-ai-data-centres/ | T50: 2026-08 | U50: 1,000 MW, Rs 85,200 cr; incentives up to Rs 14,400 cr | V50: N | W50: Y | Y50: N
A51: P050 | B51: Andhra Pradesh | C51: Visakhapatnam / Anakapalli | D51: Jagnadhapuram, Anandapuram (200 acres) | E51: Data Center Holdings India LLP (Colt DCS-RMZ) | F51: - | G51: DCHI Vizag campus | J51: 486 | L51: 58743 | M51: GO issued | N51: - | O51: A2 | P51: Government Order (reported) | Q51: AP G.O.Ms.No.56 dt 21.08.2026 (reported) | R51: https://www.medianama.com/2026/08/223-andhra-pradesh-ai-data-centres/ | T51: 2026-08-21 | U51: 486 MW, Rs 58,743 cr, 200 acres | V51: N | W51: Y | X51: GO link on stopdirtydatacenters.org returned 404 - pull from AP ITE&C site. | Y51: N
A52: P051 | B52: Andhra Pradesh | C52: Visakhapatnam / Anakapalli | D52: Amanam, Bheemunipatnam | E52: AM AI Factory (Vizag) Pvt Ltd | F52: - | G52: AM AI Factory | J52: 512 | L52: 31387 | M52: SIPB 20th meeting 12.08.2026; GO issued | N52: - | O52: A2 | P52: SIPB approval / GO (reported) | Q52: Business Standard: Andhra approves Rs 31,387 cr green AI DC | R52: https://www.business-standard.com/amp/technology/artificial-intelligence/andhra-approves-31-387-crore-green-ai-data-centre-project-in-visakhapatnam-126082200884_1.html | T52: 2026-08-22 | U52: 512 MW, Rs 31,387 cr; Mega project under DC Policy 4.0 | V52: N | W52: Y | Y52: N
A53: P052 | B53: Andhra Pradesh | C53: Visakhapatnam / Anakapalli | D53: Various | E53: TCS (HyperVault), CtrlS, GMR, others | F53: - | G53: Other APTRANSCO-listed DC projects | K53: Part of 9.1 GW IT across 16 projects | M53: Various | N53: - | O53: A2 | P53: State energy dept statement (reported) | Q53: Telangana Today (PTI): AP plans 15 GW transmission network for DCs | R53: https://telanganatoday.com/andhra-pradesh-plans-15-gw-transmission-network-for-data-centres | T53: 2026-06-10 | U53: 16 projects, 9.1 GW IT load in Vizag region | V53: N | W53: N | X53: Placeholder for remaining AP projects - MW unknown. | Y53: N
A54: P053 | B54: Telangana | C54: Hyderabad | D54: Ranga Reddy district (170 acres) | E54: Fortune (Fortune Hospitality) | F54: - | G54: Fortune hyperscale AI DC park | J54: 1200 | K54: 2,000 MVA sanctioned by TGTRANSCO (400 MVA Dec-2027; full by Dec-2034) | L54: 60000 | M54: Proposal; power sanctioned per developer | N54: 2027-2034 | O54: C | P54: Company announcement | Q54: Business Standard: Fortune to set up Rs 60,000 cr AI DC park | R54: https://www.business-standard.com/companies/news/fortune-to-set-up-60-000-cr-hyperscale-ai-data-centre-park-in-telangana-126091000632_1.html | T54: 2026-09-10 | U54: 1,200-1,600 MW IT; next to POWERGRID 765/400 kV and TGTRANSCO 400/220 kV | V54: N | W54: Y | X54: Grid sanction claimed by developer - seek TGTRANSCO letter. | Y54: N
A55: P054 | B55: Telangana | C55: Hyderabad | D55: Bharat Future City (264 acres) | E55: TCS HyperVault | F55: OpenAI (first customer, 100 MW) | G55: TCS HyperVault Hyderabad | I55: 100 | J55: 1000 | L55: 70000 | M55: Planned | N55: - | O55: C | P55: Company / press | Q55: MediaNama: TCS plans Rs 70,000 cr AI DC in Telangana | R55: https://www.medianama.com/2026/09/223-tcs-hypervault-ai-data-centre-telangana/ | S55: https://techcrunch.com/2026/02/18/openai-taps-tata-for-100mw-ai-data-center-capacity-in-india-eyes-1gw/ | T55: 2026-09 | U55: Up to 1 GW; OpenAI 100 MW (scaling to 1 GW, Stargate) | V55: N | W55: Y | X55: OpenAI capacity may be split across TCS sites. | Y55: N
A56: P055 | B56: Telangana | C56: Hyderabad | D56: Hyderabad | E56: CtrlS Datacenters | F56: - | G56: CtrlS Hyderabad 400 MW cluster | J56: 400 | M56: State MoU (2025) | N56: - | O56: A2 | P56: State MoU (reported) | Q56: w.media: Telangana 1,500-acre DC city | R56: https://w.media/telangana-reveals-plans-to-build-a-1500-acre-data-center-city/ | T56: 2025 | U56: 400 MW cluster MoU | V56: N | W56: Y | Y56: N
A57: P056 | B57: Telangana | C57: Hyderabad | D57: Hyderabad | E57: NTT Data / Neysa Networks | F57: - | G57: NTT Data-Neysa 400 MW AI cluster | J57: 400 | M57: State MoU (2025) | N57: - | O57: A2 | P57: State MoU (reported) | Q57: w.media: Telangana 1,500-acre DC city | R57: https://w.media/telangana-reveals-plans-to-build-a-1500-acre-data-center-city/ | T57: 2025 | U57: 400 MW cluster MoU | V57: N | W57: Y | Y57: N
A58: P057 | B58: Telangana | C58: Hyderabad | D58: Hyderabad | E58: AdaniConneX | F58: - | G58: AdaniConneX Hyderabad | H58: 19.2 | J58: 406 | M58: Ph I & II (9.6 MW each) complete | N58: - | O58: B | P58: Investor presentation (exchange filing) | Q58: Adani Enterprises Q1 FY27 presentation, slide 15 | R58: https://www.adanienterprises.com/-/media/Project/Enterprises/Investors/Investor-Downloads/Results-Presentations/AEL_Investor_Presentation.pdf | T58: 2026-07 | U58: Total 406 MW; 19.2 MW operational | V58: Y | W58: Y | Y58: N
A59: P058 | B59: Telangana | C59: Hyderabad | D59: Hyderabad | E59: AWS | F59: - | G59: AWS Hyderabad region expansion | M59: Under construction | N59: 14-yr investment | O59: C | P59: Company announcement | Q59: DCD: AWS to invest $7bn in Hyderabad | R59: https://www.datacenterdynamics.com/en/news/aws-to-invest-7bn-in-data-centers-in-hyderabad-india/ | S59: https://www.aboutamazon.in/news/aws/aws-data-centre-hyderabad | T59: 2026 | U59: US$7bn over 14 years under Telangana agreement | V59: N | W59: N | X59: MW not disclosed. | Y59: N
A60: P059 | B60: Tamil Nadu | C60: Chennai | D60: Ambattur | E60: CapitaLand India Trust | F60: - | G60: CapitaLand Data Centre Chennai 01 | I60: 34 | J60: 34 | K60: 53 MW gross; dedicated 110 kV substation | L60: 1940 | M60: Under construction | N60: End-2026 | O60: C | P60: Company press release | Q60: CapitaLand release, Oct-2026 | R60: https://www.capitaland.com/content/dam/capitaland-newsroom/International/2026/october/cli-affirms-long-term-commitment-to-tamil-nadu/CapitaLand%20Investment%20reaffirms%20long-term%20commitment%20to%20Tamil%20Nadu%20with%20unveiling%20of%20new%20Chennai%20data%20centre.pdf | T60: 2026-10-16 | U60: 34 MW IT, 13 halls, 53 MW gross, 110 kV S/S | V60: N | W60: Y | Y60: N
A61: P060 | B61: Tamil Nadu | C61: Chennai | D61: Chennai | E61: AdaniConneX | F61: - | G61: AdaniConneX Chennai | H61: 17 | J61: 33 | M61: Phase I 17 MW complete | N61: - | O61: B | P61: Investor presentation (exchange filing) | Q61: Adani Enterprises Q1 FY27 presentation, slide 15 | R61: https://www.adanienterprises.com/-/media/Project/Enterprises/Investors/Investor-Downloads/Results-Presentations/AEL_Investor_Presentation.pdf | T61: 2026-07 | U61: Total 33 MW; 17 MW operational | V61: Y | W61: Y | Y61: N
A62: P061 | B62: Tamil Nadu | C62: Chennai | D62: Siruseri | E62: Sify Infinit Spaces | F62: - | G62: Sify Chennai 02 campus | H62: 25.9 | J62: 130 | M62: Partly built; Tower B by 2028 | N62: 2028 | O62: C | P62: Company website | Q62: Sify Chennai 02 page | R62: https://www.sifytechnologies.com/data-center/chennai02-data-center/ | T62: 2025-26 | U62: 25.92 MW built (Jun-2025); 130+ MW at full build | V62: N | W62: Y | Y62: N
A63: P062 | B63: Tamil Nadu | C63: Chennai | D63: Siruseri | E63: STT GDC India | F63: - | G63: STT Chennai 7 | H63: 7.2 | J63: 45 | M63: Phase 1 live Feb-2026 | N63: - | O63: D | P63: Press / aggregator | Q63: ArusGrid / press | R63: https://arusgrid.com/project/in-maa-sify-siruseri | T63: 2026-02 | U63: 7.2 MW initial of 45 MW campus | V63: N | W63: Y | X63: Link is a tracker page; replace with STT release. | Y63: N
A64: P063 | B64: Tamil Nadu | C64: Chennai | D64: Ambattur | E64: Digital Connexion (Reliance-Brookfield-Digital Realty) | F64: - | G64: Digital Connexion MAA10 | J64: 100 | M64: Operational/expanding | N64: - | O64: D | P64: Press | Q64: ThePrint: Inside Chennai's data centres | R64: https://theprint.in/ground-reports/inside-chennais-data-centres-fortresses-of-the-ai-era/2856488/ | T64: 2026 | U64: 100 MW hyperscale facility | V64: N | W64: Y | Y64: N
A65: P064 | B65: Uttar Pradesh | C65: Noida / Greater Noida | D65: Noida | E65: AdaniConneX | F65: - | G65: AdaniConneX Noida | H65: 10 | I65: 40 | J65: 50 | M65: 40 MW: C&S done, MEP in progress | N65: - | O65: B | P65: Investor presentation (exchange filing) | Q65: Adani Enterprises Q1 FY27 presentation, slide 15 | R65: https://www.adanienterprises.com/-/media/Project/Enterprises/Investors/Investor-Downloads/Results-Presentations/AEL_Investor_Presentation.pdf | T65: 2026-07 | U65: Total 50 MW; 10 MW operational | V65: Y | W65: Y | Y65: N
A66: P065 | B66: Uttar Pradesh | C66: Noida / Greater Noida | D66: Greater Noida | E66: Hiranandani (NIDP / Yotta) | F66: - | G66: Yotta D1/D2 - NIDP park | J66: 250 | M66: Partly operational | N66: - | O66: A2 | P66: State policy dashboard (reported) | Q66: Invest UP / UPLC data centre policy page | R66: https://uplc.up.gov.in/en/page/uttar-pradesh-data-center-policy | S66: https://invest.up.gov.in/uttar-pradesh-data-centre-policy-2026/ | T66: 2025-06 | U66: Dashboard lists Hiranandani NIDP 250 MW | V66: N | W66: Y | Y66: N
A67: P066 | B67: Uttar Pradesh | C67: Noida / Greater Noida | D67: UP | E67: SKVR | F67: - | G67: SKVR data centre park | J67: 120 | M67: MoU under UP DC policy 2021 | N67: - | O67: A2 | P67: State policy dashboard (reported) | Q67: Invest UP / UPLC data centre policy page | R67: https://uplc.up.gov.in/en/page/uttar-pradesh-data-center-policy | T67: 2025-06 | U67: 120 MW | V67: N | W67: Y | Y67: N
A68: P067 | B68: Uttar Pradesh | C68: Noida / Greater Noida | D68: Noida | E68: NTT Global Data Centers | F68: - | G68: NTT Noida 2 | J68: 52.8 | M68: Building out | N68: - | O68: C | P68: Company website | Q68: NTT Noida 2 page | R68: https://services.global.ntt/en-us/services-and-products/global-data-centers/global-locations/india/noida-2-data-center | T68: n.d. | U68: 52.8 MW critical IT at full build | V68: N | W68: Y | Y68: N
A69: P068 | B69: Gujarat | C69: Jamnagar | D69: Jamnagar | E69: Reliance Industries | F69: Meta (tenant) | G69: Reliance-Meta AI DC Jamnagar | I69: 168 | J69: 168 | K69: Renewable power; seawater desal cooling | M69: Under development | N69: ~2028 | O69: C | P69: Company announcement | Q69: pv magazine India: Reliance, Meta to develop 168 MW AI DC | R69: https://www.pv-magazine-india.com/2026/06/10/reliance-meta-to-develop-168-mw-ai-data-centre-powered-by-renewable-energy-in-jamnagar/ | T69: 2026-06-10 | U69: 168 MW, option to scale; Jamnagar campus reported at 1-3 GW | V69: N | W69: Y | X69: Reliance has ISTS GNA applications at Jam Khambhaliya for 300/600/350 MW as 'bulk consumer' - purpose not stated (see Grid sheet). | Y69: N
A70: P069 | B70: Odisha | C70: Cuttack / Naraj | D70: Naraj (~250 acres) | E70: High Density Data Centre Ltd (Adani Group) | F70: - | G70: Adani Odisha AI DC park | J70: 1000 | L70: 104000 | M70: State approval (HLCA) | N70: - | O70: A2 | P70: State investment approval (reported) | Q70: BW Businessworld: Adani arm gets Odisha nod for Rs 1.04 lakh cr DC park | R70: https://www.businessworld.in/article/adani-arm-gets-odisha-nod-for-rs-1-04-lakh-cr-data-centre-park-625673 | S70: https://indianinfrastructure.com/2026/08/04/adani-group-proposes-rs-1-trillion-ai-data-centre-in-odisha/ | T70: 2026-08 | U70: 1 GW, Rs 1.04 lakh cr | V70: N | W70: Y | Y70: N
A71: P070 | B71: Odisha | C71: Bhubaneswar | D71: Odisha AI Park | E71: HCLTech + Sarvam AI | F71: - | G71: Sovereign AI DC Bhubaneswar | L71: 14257 | M71: State approval | N71: 2028 | O71: A2 | P71: State investment approval (reported) | Q71: TechPillow summary | R71: https://www.techpillow.co/blog/hcltech-sarvam-odisha-sovereign-ai-data-centre-2026 | T71: 2026 | U71: Rs 14,257 cr; MW not disclosed | V71: N | W71: N | Y71: N
A72: P071 | B72: West Bengal | C72: Kolkata | D72: Uttarpara | E72: Yotta / Hiranandani | F72: - | G72: Yotta Kolkata DC park | J72: 250 | M72: Planned (2021 MoU) | N72: - | O72: D | P72: Press | Q72: DCD: Hiranandani to build six hyperscale DCs in Bengal | R72: https://www.datacenterdynamics.com/en/news/hiranandani-group-build-six-hyperscale-data-centers-bengal/ | T72: 2021 | U72: 6 buildings, 250 MW | V72: N | W72: Y | X72: Old announcement; status uncertain. | Y72: N
A73: P072 | B73: West Bengal | C73: Kolkata | D73: New Town | E73: NTT Global Data Centers | F73: - | G73: NTT Kolkata 1 campus | J73: 40 | M73: Operational phase 1 | N73: - | O73: C | P73: Company website | Q73: NTT Kolkata 1 page | R73: https://services.global.ntt/en-us/services-and-products/global-data-centers/global-locations/india/kolkata-1-data-center | T73: n.d. | U73: 40 MW at full build | V73: N | W73: Y | Y73: N
A74: P073 | B74: Haryana | C74: NCR - Haryana | D74: Manesar, Panchkula, Rai (Sonipat) | E74: Anant Raj (to be demerged as Ashok Cloud) | F74: RailTel (Rai park operator, per directory) | G74: Anant Raj DC portfolio | H74: 28 | I74: 35 | J74: 307 | M74: 28 MW operating; 63 MW target Dec-2026 | N74: 307 MW by FY32 | O74: B | P74: Listed company disclosures (via press) | Q74: Value Research: Anant Raj execution review | R74: https://www.valueresearchonline.com/stories/228694/anant-raj-data-centre-execution-delay-investment-risk/ | S74: https://www.ziromarket.com/blog/anant-raj-data-centre-haryana-mou-2026 | T74: 2026 | U74: 28 MW operating; 307 MW target (Rai ~200 MW); Haryana MoU Jun-2026 Rs 25,000 cr (additional) | V74: N | W74: Y | X74: Pull Anant Raj Q2 FY27 investor presentation to confirm. | Y74: N
A75: P074 | B75: Karnataka | C75: Bengaluru | D75: Hoskote | E75: Govt of Karnataka (park) | F75: - | G75: Hoskote sustainable DC park | J75: 500 | M75: State decision (May-2026) | N75: - | O75: A2 | P75: State decision (reported) | Q75: w.media: Karnataka plans three DC parks, 1 GW | R75: https://w.media/karnataka-plans-three-sustainable-data-center-parks-with-combined-capacity-of-1-gw/ | T75: 2026-05 | U75: 500 MW park near Hoskote; 1 GW across Bengaluru, Mysuru, Mangaluru | V75: N | W75: Y | Y75: N
A76: P075 | B76: Andhra Pradesh | C76: Visakhapatnam / Anakapalli | D76: Paradesipalem & Madhurawada, Visakhapatnam | E76: Sify Infinit Spaces | F76: Meta (reported) | G76: Sify Vizag hyperscale campus | J76: 550 | L76: 15266 | M76: Land allotted (53.6 + 25 acres); incentive package approved | N76: Phased | O76: A2 | P76: AP G.O.Ms.No.29 (2025, ITC) & G.O.Ms.No.37 (2026, ITC) - reported | Q76: Deccan Chronicle: AP approves Sify's Rs 15,266 cr DC expansion | R76: https://www.deccanchronicle.com/southern-states/andhra-pradesh/ap-approves-sifys-rs-15266-crore-data-centre-expansion-clears-3-other-tech-projects-1967167 | S76: https://w.media/andhra-pradesh-allocates-extra-25-acres-for-sifys-500-mw-dc/ | T76: 2026 | U76: GO: 53.6 acres for '550 MW Data Centers in a phased manner'; additional 25 acres; Rs 15,266 cr | V76: N | W76: Y | X76: Activist registry also lists a 50 MW Sify site at Madhurawada (3.6 acres). | Y76: N
A77: P076 | B77: Andhra Pradesh | C77: Visakhapatnam / Anakapalli | D77: APIIC Industrial Park, Rambilli (49.93 acres) | E77: CtrlS Datacenters | F77: - | G77: CtrlS Rambilli | J77: 100 | L77: 2788 | M77: Land allotted; incentive package approved | N77: - | O77: A2 | P77: AP G.O.Ms.No.33 (2026, ITC) - reported | Q77: Deccan Chronicle (same report) | R77: https://www.deccanchronicle.com/southern-states/andhra-pradesh/ap-approves-sifys-rs-15266-crore-data-centre-expansion-clears-3-other-tech-projects-1967167 | T77: 2026 | U77: 49.93 acres for 100 MW; Rs 2,788.3 cr | V77: N | W77: Y | Y77: N
A78: P077 | B78: Andhra Pradesh | C78: Visakhapatnam / Anakapalli | D78: Rambilli (~200 acres) | E78: TCS (HyperVault) | F78: OpenAI (expected anchor) | G78: TCS / OpenAI Rambilli | J78: 1000 | M78: Land allotted (reported) | N78: - | O78: D | P78: Press + activist registry | Q78: Analytics India Mag: TCS acquires land in Vizag, Pune for OpenAI DCs | R78: https://analyticsindiamag.com/ai-news/tcs-acquires-land-in-vizag-pune-for-openai-data-centres | S78: https://stopdirtydatacenters.org/ | T78: 2026 | U78: ~200 acres allotted near Google Rambilli; registry lists 1 GW | V78: N | W78: N | X78: 1 GW from activist registry only; TCS has not confirmed - excluded from totals. | Y78: N
A79: P078 | B79: Andhra Pradesh | C79: Visakhapatnam / Anakapalli | D79: Madhurawada (130 acres) | E79: Adani Group (AdaniConneX) | F79: - | G79: Adani Madhurawada DC park | J79: 200 | M79: Land allotted (2021 incentive GOs) | N79: - | O79: D | P79: Activist registry citing AP GOs (G.O.Ms.No.3/2021 ITC) | Q79: stopdirtydatacenters.org registry | R79: https://stopdirtydatacenters.org/ | T79: 2021-26 | U79: 200 MW, 130 acres | V79: N | W79: N | X79: Older Adani Vizag commitment; may be subsumed in the Vizag 400 MW AdaniConneX order - excluded. | Y79: N
A80: P079 | B80: Andhra Pradesh | C80: Vijayawada | D80: Vijayawada ISTS S/S | E80: Qubitiq Ventures Pvt Ltd; Distinguished Consultancy Solutions Pvt Ltd | F80: Unknown | G80: Vijayawada data-centre grid applications | K80: CTUIL GNA bulk-consumer applications: 150 MW + 100 MW (Aug-Oct 2026) | M80: GNA under process | N80: - | O80: A1 | P80: CTUIL GNA register | Q80: CTUIL - Status of applications under GNA Regulation (stage-II) | R80: https://ctuil.in/nswsapi/gna | T80: 2026-10-06 | U80: Qubitiq 150 MW (App 2200004324); Distinguished Consultancy 100 MW (App 2200004188) | V80: Y | W80: N | X80: Sponsors unidentified; DC use inferred from bulk-consumer filing pattern - see CTU_Bulk_Register. | Y80: N
A81: P080 | B81: Telangana | C81: Hyderabad | D81: Bharat Future City (202 acres) & Chandanvelly (98 acres) | E81: Amazon Data Services (AWS) | F81: - | G81: AWS Telangana mega-campus | L81: 60000 | M81: Foundation stone 15-Jul-2026; framework agreement Dec-2025 | N81: Phase 1 in 24 months | O81: C | P81: Company / state announcement | Q81: ThePrint: Telangana secures Amazon's biggest India DC project | R81: https://theprint.in/india/governance/telangana-secures-amazons-biggest-india-data-centre-project-months-after-google-announced-ai-hub-in-ap/2987492/ | T81: 2026-07-15 | U81: Rs 60,000 cr; 300 acres; Rs 125 cr incentives | V81: N | W81: N | X81: MW not disclosed. CTUIL shows 'Chandenvalle Infra Park Ltd' and 'Madhuvanti Build Estate Ltd' each seeking 528 MW at Doma 400 kV (near Chandanvelly) - sponsor not confirmed. | Y81: N
A82: P081 | B82: Telangana | C82: Hyderabad | D82: Meerkhanpet | E82: STT GDC India | F82: - | G82: STT Hyderabad (Meerkhanpet) | J82: 100 | L82: 3500 | M82: State MoU Jan-2026 | N82: - | O82: A2 | P82: State MoU (reported) | Q82: Tribune: Telangana signs Rs 3,500 cr MoU with ST Telemedia | R82: https://www.tribuneindia.com/news/world/telangana-govt-signs-rs-3500-crore-mou-with-st-telemedia-for-ai-ready-data-centre-in-hyderabad/ | T82: 2026-01 | U82: Up to 100 MW | V82: N | W82: Y | Y82: N
A83: P082 | B83: Telangana | C83: Hyderabad | D83: Peddavedu | E83: Amazon Data Services / CtrlS (one of the two - not specified) | F83: - | G83: Peddavedu hyperscale DC (EC appraisal) | K83: 278 MW power demand; 110 x 3,500 kVA DG sets (per EC documents as reported) | M83: EC granted / under challenge | N83: - | O83: A2 | P83: SEIAA Telangana EC (reported by Scientists for People) | Q83: Counterview: Scientists flag omissions in Telangana DC ECs | R83: https://www.counterview.net/2026/05/scientists-flag-serious-omissions-in.html | T83: 2026-05-08 | U83: 278 MW; 110 DG sets; 302 KLD water | V83: N | W83: N | X83: Other EC'd sites named: Raviryal, Chandanvelly, Meerkhanpet, Manchanpally (no MW reported). | Y83: N
A84: P083 | B84: Telangana | C84: Hyderabad | D84: Maheshwaram / Bidar-Maheshwaram 765 kV LILO | E84: Giridhari Build Estate Ltd; Granthik Realtors Pvt Ltd | F84: Unknown | G84: Maheshwaram DC-pattern grid applications | K84: CTUIL GNA: Giridhari 1,172 MW (8 apps); Granthik 174 MW (3 apps) | M84: GNA under process | N84: - | O84: A1 | P84: CTUIL GNA register | Q84: CTUIL - Status of applications under GNA Regulation (stage-II) | R84: https://ctuil.in/nswsapi/gna | T84: 2026-08-03 | U84: 1,346 MW of bulk-consumer GNA at Maheshwaram by two real-estate SPVs | V84: Y | W84: N | X84: Sponsors unidentified - strong candidate 'unannounced' capacity. | Y84: N
A85: P084 | B85: Telangana | C85: Hyderabad | D85: Bharat Future City | E85: UPC-Volt | F85: - | G85: UPC-Volt AI DC | J85: 100 | M85: State MoU Jan-2026 | N85: - | O85: A2 | P85: State MoU (reported) | Q85: w.media / state releases | R85: https://w.media/telangana-reveals-plans-to-build-a-1500-acre-data-center-city/ | T85: 2026-01 | U85: 100 MW | V85: N | W85: Y | Y85: N
A86: P085 | B86: Tamil Nadu | C86: Chennai | D86: SIPCOT IT Park, Siruseri | E86: Techno Digital (Techno Electric) | F86: - | G86: Techno Digital TD-1 Siruseri | H86: 36 | J86: 36 | M86: Operational | N86: - | O86: C | P86: Company (via DCD) | Q86: DCD: Techno Digital opens 36 MW DC | R86: https://www.datacenterdynamics.com/en/news/indias-techno-digital-opens-36mw-data-center/ | T86: 2026 | U86: 36 MW | V86: N | W86: Y | Y86: N
A87: P086 | B87: Tamil Nadu | C87: Thoothukudi | D87: Tuticorin-II ISTS S/S | E87: Sitac DC Infra Pvt Ltd | F87: Unknown | G87: Sitac Tuticorin DC (grid application) | J87: 70 | K87: CTUIL GNA 70 MW (App 2200004114, 12-Aug-2026) | M87: GNA under process | N87: - | O87: A1 | P87: CTUIL GNA register | Q87: CTUIL GNA register | R87: https://ctuil.in/nswsapi/gna | T87: 2026-08-12 | U87: 70 MW bulk-consumer GNA | V87: Y | W87: Y | X87: Cable-landing / coastal DC pattern. | Y87: N
A88: P087 | B88: Karnataka | C88: Karnataka (non-Bengaluru) | D88: Tumakuru & Bidar ISTS S/S | E88: Sitac DC Pvt Ltd / Sitac DC Infra Pvt Ltd | F88: Unknown | G88: Sitac Tumakuru & Bidar DCs (grid applications) | J88: 120 | K88: CTUIL GNA: Tumkur 50 MW (2200004189); Bidar 70 MW (2200004115) | M88: GNA under process | N88: - | O88: A1 | P88: CTUIL GNA register | Q88: CTUIL GNA register | R88: https://ctuil.in/nswsapi/gna | T88: 2026-08-26 | U88: 120 MW across two sites | V88: Y | W88: Y | X88: Only Karnataka DC grid filings found - Karnataka pipeline is thin relative to AP/TG/MH. | Y88: N
A89: P088 | B89: Odisha | C89: Puri | D89: Puri | E89: Sentraforge AI | F89: - | G89: Sentraforge sovereign AI campus | J89: 120 | L89: 22634 | M89: State approval (reported) | N89: - | O89: A2 | P89: State approval (reported) | Q89: Business Standard / state approvals coverage | R89: https://www.business-standard.com/amp/companies/news/hcltech-ai-data-centre-odisha-sarvam-rs-14257-crore-investment-126072400775_1.html | T89: 2026 | U89: 120 MW; Rs 22,634 cr | V89: N | W89: Y | Y89: N
A90: P089 | B90: Odisha | C90: Cuttack / Naraj | D90: Cuttack district | E90: RKD Construction | F90: - | G90: RKD Cuttack data centre | L90: 1500 | M90: State approval (reported) | N90: - | O90: A2 | P90: State approval (reported) | Q90: DMC Education summary of Odisha approvals | R90: https://dmc-education.com/2026/10/04/odisha-adani-group-gets-approval-for-%E2%82%B91-04-lakh-crore-1-gw-data-centre-park-at-naraj/ | T90: 2026 | U90: Rs 1,500 cr | V90: N | W90: N | X90: MW not disclosed. | Y90: N
A91: P090 | B91: Uttar Pradesh | C91: Noida / Greater Noida | D91: Noida | E91: Adani Enterprises (Projects 1 & 2) | F91: - | G91: Adani UP data centres (policy dashboard) | H91: 35 | J91: 100 | L91: 5129 | M91: P1 commercialised (35 MW); P2 proposed | N91: - | O91: A1 | P91: State policy dashboard | Q91: UPLC - UP Data Center Policy page (as on Jun-2025) | R91: https://uplc.up.gov.in/en/page/uttar-pradesh-data-center-policy | T91: 2025-06 | U91: Adani P1 Rs 2,416 cr / 50 MW; P2 Rs 2,713 cr / 50 MW; 35 MW commercialised | V91: Y | W91: N | X91: Likely the same as AdaniConneX Noida (50 MW) row - excluded. | Y91: N
A92: P091 | B92: Gujarat | C92: Jamnagar | D92: New S/S near RIL Jamnagar | E92: Reliance Industries | F92: - | G92: Reliance Jamnagar - ISTS bulk-consumer filings (purpose not stated) | K92: CTUIL GNA: 10 x 1,200 MW at 'New S/s near RIL Jamnagar' (26-Aug-2026) + 2,650 MW at Jam Khambhaliya | M92: GNA under process | N92: - | O92: A1 | P92: CTUIL GNA register | Q92: CTUIL GNA register | R92: https://ctuil.in/nswsapi/gna | T92: 2026-08-26 | U92: 14,650 MW total RIL bulk-consumer GNA; purpose not disclosed (Jamnagar hosts AI DC + giga-factories) | V92: Y | W92: N | X92: Do NOT treat as DC load without confirmation. | Y92: N
A93: P092 | B93: Gujarat | C93: Gujarat - Vataman | D93: LILO of 765 kV Halvad-Vataman | E93: Blueparrot Pedestal Ltd | F93: Unknown | G93: Blueparrot Pedestal 80 MW-block grid applications | K93: CTUIL GNA: 26 applications x 80 MW = 2,080 MW (Sep-2026) | M93: GNA under process | N93: - | O93: A1 | P93: CTUIL GNA register | Q93: CTUIL GNA register | R93: https://ctuil.in/nswsapi/gna | T93: 2026-09-04 | U93: Identical 80 MW blocks - same pattern as DC building filings (e.g. Vizag SPVs filed 54 MW blocks) | V93: Y | W93: N | X93: Sponsor unidentified; could be DC or other bulk load. Adani Infra also filed 50 MW at Vataman. | Y93: N

Sheet Grid_Power
A1: ID | B1: State | C1: Utility / body | D1: Asset / item | E1: Voltage / capacity | F1: Data-centre link | G1: Status / date in plan | H1: Evidence tier | I1: Source | J1: Link | K1: Source date | L1: Read in source? (Y/N) | M1: Notes | N1: Navi Mumbai / MMR focus
A2: G001 | B2: Maharashtra | C2: MSETCL (State Transmission Utility) | D2: New 765/400/220 kV Mahape substation (Navi Mumbai) | E2: 4 x 1500 MVA 765/400 kV ICT (6,000 MVA) + 4 x 500 MVA 400/220 kV ICT (2,000 MVA); 765 kV D/C Mahape-Padghe (PG) 120 km; 240 MVAr reactor | F2: Scheme 'Type' = 'Data Center'; '400 kV connectivity to Datacenter Consumers' and '220 kV connectivity to Datacenter Consumers' | G2: Padghe line 2026-27; Apta line 2028-29 | H2: A1 | I2: MSETCL STU Five-Year Plan 2024-25 to 2033-34, Annexure-E 'New Corridor Schemes', row 4 (PDF p.36) | J2: https://www.mahatransco.in/uploads/docs/STU%20Plan%202024-25%20to%202033-24.pdf | K2: 2024-25 | L2: Y | M2: Strongest single piece of evidence: the STU is planning a dedicated 765 kV node with up to ~6 GVA purely for data-centre consumers at Mahape. | N2: Y
A3: G002 | B3: Maharashtra | C3: MSETCL | D3: 400 kV Hinjewadi bays - data-centre connectivity (Pune) | E3: 2 x 400 kV bays at Hinjewadi | F3: '400 kV connectivity to Datacenter Consumers' | G3: Plan period | H3: A1 | I3: MSETCL STU Plan 2024-34, Annexure-E (PDF p.38) | J3: https://www.mahatransco.in/uploads/docs/STU%20Plan%202024-25%20to%202033-24.pdf | K3: 2024-25 | L3: Y | M3: Pune data-centre load explicitly planned. | N3: N
A4: G003 | B4: Maharashtra | C4: MSETCL | D4: Vashi-zone new EHV substations (Taloja/Panvel/Uran belt) | E4: 400/220 kV Kalwa-II GIS (2x500 MVA); 220 kV Panchanand/Taloja (BR sanctioned); 220 kV Rohinjan (Taloja) NEW; 220 kV Palaspe; 220 kV Uran (Dronagiri) NEW; Panvel-II GIS (WIP) | F4: Not labelled as DC, but sit in the Taloja/Panvel data-centre corridor | G4: 2024-34 | H4: A1 | I4: MSETCL STU Plan 2024-34, Vashi zone table (PDF p.25) | J4: https://www.mahatransco.in/uploads/docs/STU%20Plan%202024-25%20to%202033-24.pdf | K4: 2024-25 | L4: Y | M4: Cross-check which DC campuses these serve via MSETCL/MSEDCL HT connection lists. | N4: Y
A5: G004 | B5: Maharashtra | C5: MERC / MSETCL (STU) / Lodha | D5: 400/220 kV GIS Ambernath (Palava) substation - Dedicated Distribution Facility | E5: 4 x 500 MVA 400/220 kV ICT + line bays, bus reactor, LILO; Lodha-funded capex & lifetime O&M | F5: STU has granted connectivity to AWS and STT; another DC application under process; ~1,450 MW granted + ~1,500 MW under consideration = 2,950 MW expected on grid by 2028; feeds from ISTS 400 kV Padghe(PG)-Navi Mumbai(PG) and Padghe-Kharghar | G5: Order 01-06-2026; TBCB annulled Apr-2026; Empowered Committee 12-05-2026 | H5: A1 | I5: MERC order, Case No. 88 of 2026 & IA No. 78 of 2026 | J5: https://merc.gov.in/wp-content/uploads/2026/06/Order-88-of-2026.pdf | K5: 2026-06-01 | L5: Y | M5: Read in full. Order says global DC clients could move elsewhere if power is late - regulator treats DC load as committed. | N5: Y
A6: G005 | B6: Maharashtra | C6: Bajel Projects (EPC) - client undisclosed | D6: 400/220/33 kV GIS substation for a Mumbai data-centre project | E6: Rs 300-400 cr EPC; 24 months | F6: Dedicated EHV substation for an unnamed domestic DC developer | G6: Order Jun-2026 | H6: B | I6: SEBI Reg. 30 disclosure (via Business Standard) | J6: https://www.business-standard.com/markets/capital-market-news/bajel-projects-gains-on-bagging-mega-order-for-gis-substation-in-mumbai-126060300276_1.html | K6: 2026-06-03 | L6: N | M6: 400 kV + timing suggests the Lodha Ambernath DDF; unconfirmed. | N6: Y
A7: G006 | B7: Maharashtra | C7: Tata Power (Mumbai licensee) | D7: Data-centre opportunity pipeline | E7: ~2.8 GW: ~430 MW distribution load; 1,236 MW transmission-linked; 1,150 MW green energy | F7: 18 operators, 29 active workstreams; Rs 15,000 cr Mumbai grid plan; 400 kV ring | G7: Oct-2026 | H7: B | I7: Tata Power release (via TaxGuru / Trade Brains) | J7: https://taxguru.in/finance/business/tata-power-expands-data-centre-opportunities-with-2-8-gw-pipeline.html | K7: 2026-10-14 | L7: N | M7: Pipeline, not contracts. Get the exchange filing/investor deck. | N7: Y
A8: G007 | B8: Maharashtra | C8: AEML (Adani Electricity Mumbai) | D8: Distribution demand projection incl. data centres | E8: 50 MW (FY23) -> 638 MW by 2027; 354 MW of the increase from proposed DCs | F8: Proposed DCs in AEML licence area | G8: MERC filing (reported) | H8: A2 | I8: TechPolicy.Press citing AEML filing | J8: https://www.techpolicy.press/mumbais-data-center-dreams-run-on-coal-and-inequality/ | K8: 2025-26 | L8: N | M8: Identify the exact MERC case. | N8: Y
A9: G008 | B9: Maharashtra | C9: AEML (transmission) | D9: Transmission licence amendment petition | E9: Mumbai peak 4,306 MW (FY25) -> ~6,000 MW (FY30); DCs/EVs/infra ~800 MW | F9: DC load cited as a driver | G9: MERC petition | H9: A2 | I9: EQ Mag summary of AEML petition | J9: https://www.eqmagpro.com/petition-for-application-of-adani-electricity-mumbai-infra-limited-for-the-first-amendment-of-transmission-licence-eq/ | K9: 2026 | L9: N | N9: Y
A10: G009 | B10: Maharashtra | C10: MSEDCL | D10: Grid capacity allocated to DCs in Navi Mumbai cluster | E10: ~6 GW | F10: Committed + under-construction capacity said to be approaching this ceiling; new builds moving to Panvel/Taloja/Rasayani | G10: 2026 | H10: D | I10: Structure Research Mumbai+Pune report 2026 (abstract) | J10: https://www.structureresearch.net/product/mumbai-pune-dcai-report-2026-data-centre-colocation-hyperscale-cloud-ai-interconnection/ | K10: 2026 | L10: N | M10: High-value claim; try to corroborate via MSEDCL / RTI. | N10: Y
A11: G010 | B11: Maharashtra | C11: CTUIL / POWERGRID | D11: 400/220 kV Navi Mumbai (PG) substation - drawal margin | E11: 2 x 315 MVA | F11: 'No margins for drawal of power exist at existing 400/220kV Navi Mumbai S/s' (bulk-consumer GNA diverted to Murbad/Pune) | G11: 26th CMETS-WR, 28.02.2024 | H11: A1 | I11: CTUIL minutes, 26th CMETS-WR | J11: https://www.ctuil.in/uploads/ists_consultation_meeting/minutes/171076102952Minutes%20of%2026th%20CMETS-WR_final.pdf | K11: 2024-02-28 | L11: Y | M11: Grid constraint in Navi Mumbai. | N11: Y
A12: G011 | B12: Maharashtra | C12: CTUIL / POWERGRID | D12: Additional ISTS feed to Navi Mumbai 400/220 kV S/S | E12: Padghe-Kharghar / Vikhroli 400 kV LILO at Navi Mumbai GIS; LILO of Apta-Taloja/Kalwa 220 kV | F12: Mumbai corridor demand expected to rise to 4,000-4,200 MW; jack-bus/line-trap upgrades and SPS at Navi Mumbai (PG) | G12: Common system Mar-26 (29th); upgrade discussed 02.02.2026 (41st) | H12: A1 | I12: CTUIL minutes, 29th & 41st CMETS-WR | J12: https://www.ctuil.in/uploads/ists_consultation_meeting/minutes/17718323234441st%20WR%20CMETS%20MOM.pdf | K12: 2026-02-02 | L12: Y | N12: Y
A13: G012 | B13: Gujarat | C13: CTUIL | D13: Reliance Industries - ISTS GNA as 'bulk consumer' at Jam Khambhaliya | E13: 300 MW (from 01-12-2027), 600 MW (from 01-12-2028), 350 MW (from 01-06-2029) | F13: Purpose not stated; timing/location coincides with the Jamnagar AI DC build-out | G13: 41st CMETS-WR, 02.02.2026 | H13: A1 | I13: CTUIL minutes, 41st CMETS-WR (applications 2200002406-08, dated 09-09-2025) | J13: https://www.ctuil.in/uploads/ists_consultation_meeting/minutes/17718323234441st%20WR%20CMETS%20MOM.pdf | K13: 2026-02-02 | L13: Y | M13: Possible DC load - NOT confirmed. Total 1,250 MW. | N13: N
A14: G013 | B14: Uttar Pradesh | C14: CTUIL | D14: STT Global Data Centres India - GNA-RE | E14: 7 MW GNA-RE (outside region); UPPTCL NoC for 2 MW | F14: Data-centre operator procuring RE via ISTS | G14: 41st CMETS-NR, 10.10.2025 | H14: A2 | I14: CTUIL minutes, 41st CMETS-NR | J14: https://www.ctuil.in/uploads/ists_consultation_meeting/minutes/176242143922Minutes%20of%2041st%20CMETS%20NR%20meeting%20held%20on%2010-10-2025.pdf | K14: 2025-10-10 | L14: N | M14: Shows DC operators now appear in CTUIL minutes; scan all regions' CMETS minutes in the next pass. | N14: N
A15: G014 | B15: Andhra Pradesh | C15: APTRANSCO / AP Energy Dept | D15: Data-centre transmission roadmap | E15: 765/400/220 kV network for >15 GW DC load by 2034; new 400/220 kV Rambilli S/S | F15: 16 DC projects, 9.1 GW IT load; substations Pendurthi, Maradam, Achyutapuram, Palasa, Padmanabham, Makavaripalem | G15: Jun-2026 | H15: A2 | I15: PTI via Telangana Today | J15: https://telanganatoday.com/andhra-pradesh-plans-15-gw-transmission-network-for-data-centres | K15: 2026-06-10 | L15: N | N15: N
A16: G015 | B16: Telangana | C16: TGTRANSCO | D16: Power sanction to Fortune DC park | E16: 2,000 MVA (400 MVA by Dec-2027; full by Dec-2034) | F16: Fortune hyperscale DC park, Ranga Reddy | G16: 2026 | H16: C | I16: Developer statement (Business Standard) | J16: https://www.business-standard.com/companies/news/fortune-to-set-up-60-000-cr-hyperscale-ai-data-centre-park-in-telangana-126091000632_1.html | K16: 2026-09-10 | L16: N | N16: N
A17: G016 | B17: Maharashtra | C17: Govt of Maharashtra (Industries) | D17: GR on Integrated Green Data Centre Parks | E17: Parks allowed 3 -> 20, statewide; Re 1/unit tariff subsidy 10 yrs (Rs 30,000 cr+) / 20 yrs (Rs 60,000 cr+); 4% interest subvention | F17: Policy driver for Lodha / ReNew / Trentar parks | G17: GR 09-Jun-2026 (CSC 22-Apr-2026) | H17: A2 | I17: PowerPeak Digest summary of GR | J17: https://powerpeakdigest.com/maharashtra-green-data-center-policy-expansion/ | K17: 2026-06-09 | L17: N | M17: Pull GR from maharashtra.gov.in. | N17: Y
A18: G017 | B18: Maharashtra | C18: MERC | D18: Green-energy LTOA application delays (Case 220 & 226 of 2025) | E18: n/a | F18: Affects DC green-power procurement in MSEDCL area | G18: Order Jul-2026 | H18: A2 | I18: SolarQuarter | J18: https://solarquarter.com/2026/07/06/merc-pulls-up-msedcl-msetcl-over-delays-in-green-energy-long-term-open-access-applications/ | K18: 2026-07-06 | L18: N | N18: Y

Sheet MH_Permits
A1: ID | B1: Authority | C1: Reference no. | D1: Meeting / document | E1: Date | F1: Applicant (as filed) | G1: Operator / end-user (mapped) | H1: Mapping basis | I1: Location | J1: Cluster | K1: Permit stage | L1: Decision | M1: Connected load (MW) | N1: Demand load (as stated) | O1: DG unit size (kVA) | P1: DG count | Q1: DG back-up (MVA) | R1: Capital investment (Rs cr) | S1: Plot / BUA (m2) | T1: Link | U1: Read in document? (Y/N) | V1: Notes
A2: M001 | B2: SEAC-II | C2: Form-1A (EC application) | D2: Form-1A submitted to SEAC-II | E2: c.2022-23 | F2: Amanthin Info Parks Pvt Ltd | G2: Google (Raiden Infotech) via EverYondr | H2: Lease Amanthin->Raiden registered Oct-2022 (CRE Matrix / Housing.com); Amanthin = EverYondr subsidiary | I2: Plot D-31 & D-32, TTC Turbhe | J2: Navi Mumbai - TTC/Thane-Belapur | K2: EC application | L2: n/a | M2: 103.367 | N2: 108,807 kVA demand; 4 x 220/22 kV 60 MVA transformers | O2: 2200 | P2: 58 | Q2: =IF(AND(ISNUMBER(O2),ISNUMBER(P2)),O2*P2/1000,"") -> 127.6 | S2: Plot 39,980; BUA 55,432 | T2: https://environmentclearance.nic.in/DownloadPfdFile.aspx?FileName=Kwy+a1Xl%2FGHp2kMbJYBd8GPrFSz%2FNzzr1mrm87hA6RfsBvasy5U%2FhwjR4PRxBwwupD8Lw8MExL5FqtSFZLEOTQ%3D%3D&FilePath=93ZZBm8LWEXfg+HAlQix2fE2t8z%2FpgnoBhDlYdZCxzXTbTpOQqzWjBW0IF63rxBVcDlG0LKdfbGNs0Ou%2FTEvAA%3D%3D | U2: Y
A3: M002 | B3: MPCB | C3: CTE 0000249841 | D3: 5th CAC 2025-26 (ATR) | E3: 2025-08-26 | F3: Raiden Infotech India Pvt Ltd | G3: Google | H3: Raiden = Google's Indian DC entity (AP G.O.Ms.66) | I3: GEN-2/1/A/1, D-Block, TTC Turbhe | J3: Navi Mumbai - TTC/Thane-Belapur | K3: Consent to Establish | L3: Approved | Q3: =IF(AND(ISNUMBER(O3),ISNUMBER(P3)),O3*P3/1000,"") | T3: https://mpcb.gov.in/sites/default/files/inline-files/Action_Taken_report_of_5th_CAC_Booklet_no_5_0.pdf | U3: Y | V3: Second Google site in Navi Mumbai
A4: M003 | B4: SEIAA | C4: SIA/MH/INFRA2/531703/2025 | D4: 310th SEIAA agenda | E4: 2025-10-26 | F4: Raiden Infotech India Pvt Ltd | G4: Google | H4: as above | I4: GEN-2/1/A/1, D-Block, TTC Turbhe | J4: Navi Mumbai - TTC/Thane-Belapur | K4: EC application | L4: On agenda | Q4: =IF(AND(ISNUMBER(O4),ISNUMBER(P4)),O4*P4/1000,"") | T4: https://www.ecmpcb.in/login/download_ec_document/ODY2MDg5MDRCMzNGNDNCN0JEMTFBNDUzNEI4MjlGNEQucGRm | U4: Y
A5: M004 | B5: MPCB | C5: CTE 0000167765 | D5: 14th CAC 2023-24 (agenda index) | E5: 2023-24 | F5: Gold Craft by Gramercy Trade Industries Pvt Ltd | G5: (prior applicant on Google plot) | H5: Same plot GEN-2/1/A/1 | I5: GEN-2/1/A/1, Turbhe | J5: Navi Mumbai - TTC/Thane-Belapur | K5: Consent to Establish | L5: Listed | Q5: =IF(AND(ISNUMBER(O5),ISNUMBER(P5)),O5*P5/1000,"") | R5: 1895 | T5: https://mpcb.gov.in/sites/default/files/inline-files/Agenda%20Index%20of%2014th%20CAC%20Meeting.pdf | U5: Y | V5: Gramercy group earlier applied on the plot now with Raiden
A6: M005 | B6: SEIAA | C6: SIA/MH/INFRA2/466218/2024 | D6: 301st SEIAA minutes (Day-4, table item 01) | E6: 2025-08-14 | F6: Datascape Realty Pvt Ltd | G6: CapitaLand (DC Navi Mumbai 1) | H6: TIA listing names Datascape as CapitaLand Group | I6: Plots 14/2, 15 & 37, TTC Digha (ex-Precision Fasteners) | J6: Navi Mumbai - TTC/Thane-Belapur | K6: EC (expansion) | L6: Discussed | M6: 135 | N6: 120 MVA max demand (process + non-process) | O6: 2500 | P6: 65 | Q6: =IF(AND(ISNUMBER(O6),ISNUMBER(P6)),O6*P6/1000,"") -> 162.5 | T6: https://environmentclearance.nic.in/writereaddata/FormB/agenda/1509202585756580%28740114%29MINUTESOF301DAY-4TABLEITEM-Copy.pdf | U6: Y | V6: OCR of scanned minutes
A7: M006 | B7: MPCB | C7: CTE 0000155369 | D7: 5th CAC 2023-24 (agenda index) | E7: 2023-24 | F7: Datascape Realty Pvt Ltd | G7: CapitaLand | H7: as above | I7: Plots 14/2, 15 & 37, TTC Digha | J7: Navi Mumbai - TTC/Thane-Belapur | K7: Consent to Establish | L7: Listed | Q7: =IF(AND(ISNUMBER(O7),ISNUMBER(P7)),O7*P7/1000,"") | R7: 3211.9 | T7: https://mpcb.gov.in/sites/default/files/inline-files/Agenda%20Index%20of%205th%20CAC%20Meeting%20of%202023-24.pdf | U7: Y
A8: M007 | B8: MPCB | C8: CTO 0000231516 | D8: 15th CAC 2024-25 (ATR) | E8: 2025-02-09 | F8: Datascape Realty Pvt Ltd | G8: CapitaLand | H8: as above | I8: Thane (TTC Digha) | J8: Navi Mumbai - TTC/Thane-Belapur | K8: Consent to 1st Operate (part) | L8: Approved | Q8: =IF(AND(ISNUMBER(O8),ISNUMBER(P8)),O8*P8/1000,"") | T8: https://mpcb.gov.in/sites/default/files/inline-files/Action_Taken_Report_of_15th_CAC_Booklet_no_15_%281%29.pdf | U8: Y
A9: M008 | B9: SEIAA | C9: SIA/MH/INFRA2/475215 (year illegible in scan) | D9: 301st SEIAA minutes (Day-4, table item 02) | E9: 2025-08-14 | F9: Web Werks India Pvt Ltd | G9: Iron Mountain (Web Werks) | H9: Web Werks is Iron Mountain's India JV | I9: Plots R-50 to R-54, TTC Rabale ('MUM-3') | J9: Navi Mumbai - TTC/Thane-Belapur | K9: EC (new DC buildings) | L9: Discussed | M9: 140 | N9: 131 MW demand | O9: 2250 | P9: 103 | Q9: =IF(AND(ISNUMBER(O9),ISNUMBER(P9)),O9*P9/1000,"") -> 231.75 | T9: https://environmentclearance.nic.in/writereaddata/FormB/agenda/1509202585756580%28740114%29MINUTESOF301DAY-4TABLEITEM-Copy.pdf | U9: Y | V9: OCR of scanned minutes; very large for an operator rarely seen in the press
A10: M009 | B10: MPCB | C10: CTE 0000215272 | D10: 6th CAC 2024-25 (ATR) | E10: 2024-09-28 | F10: Web Werks India Pvt Ltd | G10: Iron Mountain | H10: as above | I10: TTC Rabale | J10: Navi Mumbai - TTC/Thane-Belapur | K10: Consent to Establish | L10: Approved | Q10: =IF(AND(ISNUMBER(O10),ISNUMBER(P10)),O10*P10/1000,"") | T10: https://mpcb.gov.in/sites/default/files/inline-files/Action_Taken_Report_of_6th_CAC_Meeting_2024-25.pdf | U10: Y
A11: M010 | B11: SEIAA | C11: SIA/MH/INFRA2/416132/2023 | D11: 301st & 296th SEIAA minutes | E11: 2025-08-14 | F11: Amazon Data Services India Pvt Ltd | G11: AWS | H11: Applicant | I11: CTS 86 pt, Paspoli & CTS 115 pt Tungwa, Powai | J11: Mumbai (island/suburbs) | K11: EC | L11: Discussed | M11: 77 | N11: 75 MW demand (75 MVA) | Q11: =IF(AND(ISNUMBER(O11),ISNUMBER(P11)),O11*P11/1000,"") | S11: Plot 22,258; BUA 84,584 | T11: https://environmentclearance.nic.in/writereaddata/FormB/agenda/1509202585756580%28740114%29MINUTESOF301DAY-4TABLEITEM-Copy.pdf | U11: Y | V11: DC + DG buildings up to 77 m high
A12: M011 | B12: MPCB | C12: CTE 0000217236 | D12: 15th CAC 2024-25 (ATR) | E12: 2025-02-11 | F12: Amazon Data Services India Pvt Ltd | G12: AWS | H12: Applicant | I12: Powai | J12: Mumbai (island/suburbs) | K12: Consent to Establish | L12: Approved | Q12: =IF(AND(ISNUMBER(O12),ISNUMBER(P12)),O12*P12/1000,"") | R12: 2626.63 | T12: https://mpcb.gov.in/sites/default/files/inline-files/Action_Taken_Report_of_15th_CAC_Booklet_no_15_%281%29.pdf | U12: Y | V12: Earlier show-cause notice for refusal (12th CAC 2023-24)
A13: M012 | B13: MPCB | C13: CTE 0000178616 | D13: 16th CAC 2023-24 (index & ATR) | E13: 2023-12-14 | F13: Amazon Data Services India Pvt Ltd | G13: AWS | H13: Applicant | I13: Balkum & Majiwada villages, Thane | J13: MMR - Thane | K13: Consent to Establish | L13: Approved | N13: 272 MW IT load (per EC filing summary) | Q13: =IF(AND(ISNUMBER(O13),ISNUMBER(P13)),O13*P13/1000,"") | R13: 7203.29 | S13: 54.73 acres | T13: https://mpcb.gov.in/sites/default/files/inline-files/Action_taken_Report_of_16th_CAC_Booklet_no_16.pdf | U13: Y
A14: M013 | B14: SEIAA | C14: SIA/MH/INFRA2/477127/2024 | D14: 284th & 304th SEIAA agendas | E14: 2025-08-29 | F14: Amazon Data Services India Pvt Ltd | G14: AWS | H14: Applicant | I14: Balkum & Majiwada villages, Thane | J14: MMR - Thane | K14: EC application | L14: On agenda | Q14: =IF(AND(ISNUMBER(O14),ISNUMBER(P14)),O14*P14/1000,"") | T14: https://www.ecmpcb.in/login/download_ec_document/RTE1NjUyREEwNzhCNEQ1MzkwRTZDQUVFOTNEQUIyRjYucGRm | U14: Y
A15: M014 | B15: SEIAA | C15: SIA/MH/INFRA2/422530/2023 | D15: 292nd & 296th SEIAA minutes | E15: 2025-06-20 | F15: Tusshar Infra Developers & Pantheon Buildcon | G15: Unknown DC operator | H15: Earlier EC in name of Ekta & Shobha Kapoor (2022) | I15: CTS 689/A/1 etc. Marol & 193 pt Tungwe, Saki Vihar-Chandivali jn | J15: Mumbai (island/suburbs) | K15: EC (expansion) - 'Commercial IT (Data Centre)' | L15: Discussed | M15: 113.855 | N15: 91.9 MW demand | O15: 3500 | P15: 80 | Q15: =IF(AND(ISNUMBER(O15),ISNUMBER(P15)),O15*P15/1000,"") -> 280 | R15: 610 | S15: Plot 16,235; BUA 92,393 | T15: https://environmentclearance.nic.in/writereaddata/FormB/agenda/2107202594781152MINUTESOF296DAY-3PART-B.pdf | U15: Y | V15: Tenant not named - candidate unannounced capacity
A16: M015 | B16: SEIAA | C16: SIA/MH/INFRA2/562044/2025 | D16: 319th SEIAA minutes (Day-5 Part B, item 15) | E16: 2026-02-04 | F16: Pune Data Center Ltd (regd. office: Adani Corporate House, Ahmedabad) | G16: AdaniConneX - on ex-Microsoft site | H16: EC transferred from Microsoft Corp (India) to Pune Data Center Ltd on 28-11-2024; adani.com contact | I16: BG 80/B, Bhosari, Pune ('ACXPNQ26') | J16: Pune | K16: EC (expansion) | L16: Referred back to SEAC-III | M16: 75.4 | N16: 74 MW demand | O16: 3150 | P16: 27 | Q16: =IF(AND(ISNUMBER(O16),ISNUMBER(P16)),O16*P16/1000,"") -> 85.05 | T16: https://environmentclearance.nic.in/writereaddata/FormB/agenda/2302202697285484%28921161%29MINUTESOF319DAY-5PART-B.pdf | U16: Y | V16: Plus 1 x 630 kVA DG. Earlier EC SIA/MH/INFRA2/517762/2025 granted 22-07-2025
A17: M016 | B17: MPCB | C17: CTE 0000148492 | D17: 15th CAC 2022-23 (minutes) | E17: 2022-23 | F17: Microsoft Corporation (India) Pvt Ltd | G17: Microsoft (site now with Adani SPV) | H17: Applicant | I17: BG 80/B, Bhosari, Pune | J17: Pune | K17: Consent to Establish | L17: Approved | Q17: =IF(AND(ISNUMBER(O17),ISNUMBER(P17)),O17*P17/1000,"") | R17: 2014.74 | S17: Plot 44,499; BUA 40,140 | T17: https://mpcb.gov.in/sites/default/files/inline-files/Minutes%20of%2015th%20CAC%20Establish%20Booklet%20no%2065.pdf | U17: Y
A18: M017 | B18: MPCB | C18: CTE 0000138540 | D18: 15th CAC 2022-23 (minutes & index) | E18: 2022-23 | F18: Microsoft India Pvt Ltd ('Data Center PNQ06') | G18: Microsoft / AdaniConneX ('Pune Data Center Two Ltd') | H18: SEIAA lists PNQ06 + ACXPNQ27/29 under Pune Data Center Two Ltd | I18: D-I-10-1, MIDC Pimpri Waghere, Pune | J18: Pune | K18: Consent to Establish | L18: Approved | Q18: =IF(AND(ISNUMBER(O18),ISNUMBER(P18)),O18*P18/1000,"") | R18: 5227.84 | S18: Plot 101,182; BUA 82,827 | T18: https://mpcb.gov.in/sites/default/files/inline-files/Minutes%20of%2015th%20CAC%20Establish%20Booklet%20no%2065.pdf | U18: Y
A19: M018 | B19: SEIAA | C19: SIA/MH/INFRA2/517690/2025 & 543691/2025 | D19: 296th & 313th SEIAA agendas | E19: 2025-12-02 | F19: Pune Data Center Two Ltd | G19: AdaniConneX / Microsoft | H19: as above | I19: D-I-10-1, Pimpri Waghere ('PNQ06', 'ACXPNQ27 & ACXPNQ29') | J19: Pune | K19: EC | L19: On agenda | Q19: =IF(AND(ISNUMBER(O19),ISNUMBER(P19)),O19*P19/1000,"") | T19: https://www.ecmpcb.in/login/download_ec_document/MzMzQzM2MDM3QkQ5NEYxQUIyOTNEMjAyNEE2NUNFODgucGRm | U19: Y
A20: M019 | B20: MPCB | C20: CTE 0000195775 | D20: 3rd CAC 2024-25 (minutes) | E20: 2024-25 | F20: 'BOM 2 & BOM 3' (applicant name not printed) | G20: Digital Edge (inferred) | H20: EC date 08-02-2024 matches Digital Edge BOM EC | I20: S.No. 47/2, 48/2, 49/2 (pt), Dighe, Thane-Belapur Rd | J20: Navi Mumbai - TTC/Thane-Belapur | K20: Consent to Establish | L20: Approved | Q20: =IF(AND(ISNUMBER(O20),ISNUMBER(P20)),O20*P20/1000,"") | R20: 3000 | S20: Plot 172,354; BUA 390,772; 8 buildings | T20: https://mpcb.gov.in/sites/default/files/inline-files/Webhost_Minutes_of_3rd_CAC_meeting.pdf | U20: Y | V20: Water 5 CMD
A21: M020 | B21: MPCB | C21: CTO 0000225726 | D21: 17th CAC 2024-25 (ATR) | E21: 2025-04-03 | F21: Digital Edge DC (India) Pvt Ltd | G21: Digital Edge | H21: Applicant | I21: Kalwa village, Thane-Belapur Rd | J21: Navi Mumbai - TTC/Thane-Belapur | K21: Consent to 1st Operate | L21: Approved | Q21: =IF(AND(ISNUMBER(O21),ISNUMBER(P21)),O21*P21/1000,"") | T21: https://mpcb.gov.in/sites/default/files/inline-files/Action_Taken_Report_of_17th_CAC_Booklet_no_17_2024-25.pdf | U21: Y
A22: M021 | B22: SEIAA | C22: SIA/MH/INFRA2/449922/2023 (EC24B039MH149609) | D22: EC letter | E22: 2024-02-08 | F22: Digital Edge DC (India) Pvt Ltd | G22: Digital Edge | H22: Applicant | I22: S.No. 238/2, Kalwa, Thane-Belapur Rd | J22: Navi Mumbai - TTC/Thane-Belapur | K22: EC | L22: Granted | Q22: =IF(AND(ISNUMBER(O22),ISNUMBER(P22)),O22*P22/1000,"") | T22: https://www.digitaledgedc.com/wp-content/uploads/2025/07/EC-Letter-Data-Center.pdf | U22: Y
A23: M022 | B23: SEIAA | C23: SIA/MH/INFRA2/490756/2025 (EC24C3802MH5926451N) | D23: EC letter | E23: 2025-11-21 | F23: Nxtra Data Ltd | G23: Bharti Airtel (Nxtra) | H23: Applicant | I23: Plot IT-07, TTC Mahape | J23: Navi Mumbai - TTC/Thane-Belapur | K23: EC (expansion) | L23: Granted | Q23: =IF(AND(ISNUMBER(O23),ISNUMBER(P23)),O23*P23/1000,"") | T23: https://assets.airtel.in/nxtra/pdf/EC_Environmental_Clearance_Certificate_Nxtra%20Mahape_DC-02_25.11.25.pdf | U23: Y
A24: M023 | B24: MPCB | C24: CTE 0000217674 / CTO 0000244592 | D24: 14th CAC 2024-25; 2nd CAC 2025-26 | E24: 2025-06-16 | F24: Nxtra Data Ltd | G24: Bharti Airtel (Nxtra) | H24: Applicant | I24: Navi Mumbai (Mahape) | J24: Navi Mumbai - TTC/Thane-Belapur | K24: CTE expansion (Feb-25); CTO part (Jun-25) | L24: Approved | Q24: =IF(AND(ISNUMBER(O24),ISNUMBER(P24)),O24*P24/1000,"") | T24: https://mpcb.gov.in/sites/default/files/inline-files/Action_Taken_Report_of_2nd_CAC_Meeting.pdf | U24: Y
A25: M024 | B25: MPCB | C25: CTE 0000145905 | D25: 15th CAC 2022-23 (minutes & index) | E25: 2022-23 | F25: Gramercy Techpark Pvt Ltd | G25: Lumina CloudInfra -> AirTrunk (inferred) | H25: Lumina's Airoli project listed at 'Gramercy Techpark' | I25: Plot 7 & 7A, TTC Airoli | J25: Navi Mumbai - TTC/Thane-Belapur | K25: Consent to Establish | L25: Approved | Q25: =IF(AND(ISNUMBER(O25),ISNUMBER(P25)),O25*P25/1000,"") | R25: 1495 | S25: Plot 24,350; BUA 86,044 | T25: https://mpcb.gov.in/sites/default/files/inline-files/Minutes%20of%2015th%20CAC%20Establish%20Booklet%20no%2065.pdf | U25: Y
A26: M025 | B26: MPCB / SEIAA | C26: CTO 0000240730; SIA/MH/INFRA2/484959/2024 | D26: 1st CAC 2025-26; 310th & 311th(A) SEIAA agendas | E26: 2025-05-13 | F26: Gramercy Techpark Pvt Ltd | G26: Lumina / AirTrunk | H26: as above | I26: Plot 7 & 7A, TTC Airoli | J26: Navi Mumbai - TTC/Thane-Belapur | K26: CTO (part); EC expansion | L26: Approved / on agenda | Q26: =IF(AND(ISNUMBER(O26),ISNUMBER(P26)),O26*P26/1000,"") | T26: https://mpcb.gov.in/sites/default/files/inline-files/Action_Taken_Report_of_1st_CAC_Meeting_Part_I.pdf | U26: Y
A27: M026 | B27: MPCB | C27: CTE 0000200798 & 0000219658 | D27: 2nd & 11th CAC 2024-25 | E27: 2024-12-05 | F27: Gramercy Business Hub Pvt Ltd | G27: Unknown (Gramercy group) | H27: Same group as Lumina SPV | I27: Plot A-831, TTC Mahape | J27: Navi Mumbai - TTC/Thane-Belapur | K27: Consent to Establish | L27: Approved | Q27: =IF(AND(ISNUMBER(O27),ISNUMBER(P27)),O27*P27/1000,"") | T27: https://mpcb.gov.in/sites/default/files/inline-files/ATR_of_2nd_CAC_meeting.pdf | U27: Y | V27: Use not stated - data-centre use unconfirmed
A28: M027 | B28: SEIAA / MPCB | C28: SIA/MH/INFRA2/509611/2024; CTE 0000185134 | D28: 308th SEIAA agenda; 21st CAC 2023-24 | E28: 2025-10-03 | F28: Support Properties Pvt Ltd | G28: AdaniConneX ('ACXNMI-01') | H28: 'ACX' project code | I28: Plot A-GEN-4, TTC Rabale / Ghansoli | J28: Navi Mumbai - TTC/Thane-Belapur | K28: EC expansion; CTE (Feb-24) | L28: On agenda / approved | Q28: =IF(AND(ISNUMBER(O28),ISNUMBER(P28)),O28*P28/1000,"") | T28: https://www.ecmpcb.in/login/download_ec_document/MjMyMTI2NEMzMjYzNDM5M0IxRTJDRDY5MENBNDZFODcucGRm | U28: Y
A29: M028 | B29: SEIAA / MPCB | C29: SIA/MH/INFRA2/504527/2025; CTE 0000224730 | D29: 311th(A) SEIAA agenda; 1st CAC 2025-26 | E29: 2025-05-26 | F29: Sify Infinit Spaces Ltd | G29: Sify | H29: Applicant (EC transferred from Print House (India) - 468263/2024) | I29: R-847/2, R-979, R-847/3, R-847/3/1, R-848, W-377, TTC Rabale | J29: Navi Mumbai - TTC/Thane-Belapur | K29: EC expansion; CTE expansion | L29: Approved / on agenda | Q29: =IF(AND(ISNUMBER(O29),ISNUMBER(P29)),O29*P29/1000,"") | T29: https://www.ecmpcb.in/login/download_ec_document/Nzg4MEM4QkU4NEYwNEI4MzhBOTA5OTlGQUFCQjU4MkQucGRm | U29: Y
A30: M029 | B30: SEIAA | C30: SIA/MH/INFRA2/496938/2024 | D30: 310th SEIAA agenda | E30: 2025-10-26 | F30: Gargantuan Industrial Space Solutions Pvt Ltd | G30: Unknown | H30: - | I30: Plot R-978, Sector 8, Rabale | J30: Navi Mumbai - TTC/Thane-Belapur | K30: EC expansion | L30: On agenda | Q30: =IF(AND(ISNUMBER(O30),ISNUMBER(P30)),O30*P30/1000,"") | T30: https://www.ecmpcb.in/login/download_ec_document/ODY2MDg5MDRCMzNGNDNCN0JEMTFBNDUzNEI4MjlGNEQucGRm | U30: Y
A31: M030 | B31: SEIAA | C31: SIA/MH/INFRA2/533354/2025 | D31: 310th SEIAA additional agenda | E31: 2025-10-29 | F31: Bearys Properties & Developments Pvt Ltd | G31: NTT (likely; Bearys builds NTT NAV1A/1B) | H31: Bearys brochure | I31: Plot ES-05, TTC Mahape | J31: Navi Mumbai - TTC/Thane-Belapur | K31: EC | L31: On agenda | Q31: =IF(AND(ISNUMBER(O31),ISNUMBER(P31)),O31*P31/1000,"") | T31: https://www.ecmpcb.in/login/download_ec_document/QjJCMzlBQzg5M0MzNDZERjg1NDQxQTZGN0YzQzE0MjMucGRm | U31: Y
A32: M031 | B32: SEIAA | C32: SIA/MH/INFRA2/517940/2025 | D32: 309th SEIAA agenda | E32: 2025-10-11 | F32: Larsen & Toubro Ltd | G32: L&T-Vyoma | H32: Applicant | I32: Plot EL-200, TTC Mahape | J32: Navi Mumbai - TTC/Thane-Belapur | K32: EC | L32: On agenda | Q32: =IF(AND(ISNUMBER(O32),ISNUMBER(P32)),O32*P32/1000,"") | T32: https://www.ecmpcb.in/login/download_ec_document/MzI2MjVDNjJFNjhGNEFDMkFCRjA0MDc5NDdENUQ3QjMucGRm | U32: Y
A33: M032 | B33: SEIAA | C33: SIA/MH/INFRA2/502320/2024 | D33: 304th & 313th SEIAA agendas | E33: 2025-12-02 | F33: Larsen & Toubro Ltd | G33: L&T | H33: Applicant | I33: S.No. 39, 42, 49 Bhokarpada, Panvel | J33: Navi Mumbai - Taloja/Panvel | K33: EC (DC + residential) | L33: On agenda | Q33: =IF(AND(ISNUMBER(O33),ISNUMBER(P33)),O33*P33/1000,"") | T33: https://www.ecmpcb.in/login/download_ec_document/MzMzQzM2MDM3QkQ5NEYxQUIyOTNEMjAyNEE2NUNFODgucGRm | U33: Y
A34: M033 | B34: SEIAA / MPCB | C34: SIA/MH/INFRA2/495143/2025; CTO 0000227513 | D34: 309th SEIAA agenda; 17th CAC 2024-25 | E34: 2025 | F34: Newfound Properties & Leasing Pvt Ltd | G34: K Raheja Corp / Mindspace | H34: Applicant | I34: Gen 2/1/D-F, TTC Juinagar | J34: Navi Mumbai - TTC/Thane-Belapur | K34: CTO Part-I for Bldg 5A (Data Centre) | L34: Approved | Q34: =IF(AND(ISNUMBER(O34),ISNUMBER(P34)),O34*P34/1000,"") | S34: Bldg 5A BUA 32,971 | T34: https://mpcb.gov.in/sites/default/files/inline-files/Action_Taken_Report_of_17th_CAC_Booklet_no_17_2024-25.pdf | U34: Y
A35: M034 | B35: SEIAA / MPCB | C35: SIA/MH/INFRA2/540748/2025; 0000232277 | D35: 310th & 318th SEIAA agendas; 4th CAC 2025-26 | E35: 2026-01 | F35: Gigaplex Estate Pvt Ltd | G35: K Raheja Corp / Mindspace | H35: Applicant | I35: IT-5, Airoli Knowledge Park (Bldg 8 = Data Centre) | J35: Navi Mumbai - TTC/Thane-Belapur | K35: CTO application; EC amendment | L35: Listed | Q35: =IF(AND(ISNUMBER(O35),ISNUMBER(P35)),O35*P35/1000,"") | R35: 173.99 | T35: https://mpcb.gov.in/sites/default/files/inline-files/Index_of_4th_CAC_Meeting_of_2025-26.pdf | U35: Y
A36: M035 | B36: MPCB | C36: CTE 0000175818; CTO 0000209776; Amend 0000013617 | D36: 16th/17th CAC 2023-24; 4th & 13th CAC 2024-25 | E36: 2023-12-08 | F36: STT Global Data Centres India Pvt Ltd | G36: STT GDC | H36: Applicant | I36: Plots 51 & 51/1, Gen-50/1, TTC Khairane | J36: Navi Mumbai - TTC/Thane-Belapur | K36: CTE; CTO (part); amendment | L36: Approved | N36: Amendment REMOVED 31 x 2,000 kVA DG sets | Q36: =IF(AND(ISNUMBER(O36),ISNUMBER(P36)),O36*P36/1000,"") | T36: https://mpcb.gov.in/sites/default/files/inline-files/Action_Taken_Report_of_13th_CAC_Minutes_Booklet_no_13.pdf | U36: Y | V36: DG sets removed by amendment, so no DG back-up counted
A37: M036 | B37: MPCB | C37: CTO 0000220412; renewal 0000242125 | D37: 14th CAC 2024-25; 2nd CAC 2025-26 | E37: 2025-07-11 | F37: NTT Global Data Centers NAV2 Pvt Ltd | G37: NTT | H37: Applicant | I37: Plots B1 & B2, TTC Dighe, Airoli | J37: Navi Mumbai - TTC/Thane-Belapur | K37: CTO; renewal (part) | L37: Approved | Q37: =IF(AND(ISNUMBER(O37),ISNUMBER(P37)),O37*P37/1000,"") | T37: https://mpcb.gov.in/sites/default/files/inline-files/Action_Taken_Report_of_2nd_CAC_Meeting.pdf | U37: Y
A38: M037 | B38: MPCB | C38: CTO 0000231448 | D38: 1st CAC 2025-26 | E38: 2025-05-29 | F38: Princeton Digital Group (India) Management Pvt Ltd | G38: PDG | H38: Applicant | I38: TTC Airoli & Dighe | J38: Navi Mumbai - TTC/Thane-Belapur | K38: Consent to 1st Operate | L38: Approved | Q38: =IF(AND(ISNUMBER(O38),ISNUMBER(P38)),O38*P38/1000,"") | T38: https://mpcb.gov.in/sites/default/files/inline-files/Action_Taken_Report_of_1st_CAC_Meeting_Part_I.pdf | U38: Y
A39: M038 | B39: MPCB | C39: CTE exp 0000202331 | D39: 5th CAC 2024-25 | E39: 2024-25 | F39: CtrlS India Pvt Ltd | G39: CtrlS | H39: Applicant | I39: EL-201, 201pt, EL-202 & EL-229, TTC Mahape | J39: Navi Mumbai - TTC/Thane-Belapur | K39: CTE for expansion | L39: Approved | Q39: =IF(AND(ISNUMBER(O39),ISNUMBER(P39)),O39*P39/1000,"") | T39: https://mpcb.gov.in/sites/default/files/inline-files/Action_Taken_report_of_5th_CAC_Booklet_no_5.pdf | U39: Y
A40: M039 | B40: MPCB | C40: 0000172442; renewal 0000227159 | D40: 11th CAC 2023-24; 17th CAC 2024-25 | E40: 2025-04-03 | F40: Data Center Holdings India LLP | G40: Colt DCS-RMZ | H40: Applicant | I40: Plots 5 & 5A, Kalwa Ind. Area, Airoli | J40: Navi Mumbai - TTC/Thane-Belapur | K40: CTO / renewal | L40: Approved | Q40: =IF(AND(ISNUMBER(O40),ISNUMBER(P40)),O40*P40/1000,"") | R40: 756.8 | T40: https://mpcb.gov.in/sites/default/files/inline-files/Agenda%20INdex%20of%2011th%20CAC%20Meeting.pdf | U40: Y
A41: M040 | B41: MPCB | C41: 0000171036 | D41: 15th CAC 2023-24 | E41: 2023-24 | F41: Bridge Data Centres (Mumbai) LLP | G41: Bridge Data Centres | H41: Applicant | I41: Plot 13, Kalwa Ind. Area, Digha | J41: Navi Mumbai - TTC/Thane-Belapur | K41: CTO renewal | L41: Approved | Q41: =IF(AND(ISNUMBER(O41),ISNUMBER(P41)),O41*P41/1000,"") | R41: 598.52 | T41: https://mpcb.gov.in/sites/default/files/inline-files/Index_Of_15th_CAC_Meeting.pdf | U41: Y
A42: M041 | B42: MPCB | C42: Renewal 0000223122 | D42: 1st CAC 2025-26 | E42: 2025-05-26 | F42: NMDC Data Centre Pvt Ltd | G42: Yotta / Hiranandani | H42: CRISIL rationale | I42: Bhokarpada (Panvel) & Talegaon Panshil (Khalapur) | J42: Navi Mumbai - Taloja/Panvel | K42: Renewal of consent | L42: Approved | Q42: =IF(AND(ISNUMBER(O42),ISNUMBER(P42)),O42*P42/1000,"") | T42: https://mpcb.gov.in/sites/default/files/inline-files/Action_Taken_Report_of_1st_CAC_Meeting_Part_I.pdf | U42: Y | V42: Khalapur site is a second Yotta location
A43: M042 | B43: MPCB | C43: CTO 0000132160 | D43: 3rd CAC 2023-24 | E43: 2023-24 | F43: Persipina Developers Pvt Ltd | G43: Hiranandani (Yotta park) | H43: Location | I43: Bhokarpada, Panvel | J43: Navi Mumbai - Taloja/Panvel | K43: CTO for DG sets | L43: Approved | Q43: =IF(AND(ISNUMBER(O43),ISNUMBER(P43)),O43*P43/1000,"") | T43: https://mpcb.gov.in/sites/default/files/inline-files/Webhost%20Minutes%20of%203rd%20CAC%20Booklet%20no.%203.pdf | U43: Y
A44: M043 | B44: MPCB | C44: 0000211215 / 0000219542 | D44: 11th & 16th CAC 2024-25 | E44: 2025-03-19 | F44: Nxtra Data Ltd (Pune-3) | G44: Bharti Airtel (Nxtra) | H44: Applicant | I44: P-1-1 & P-1-2, RGIP Phase-III, Hinjewadi | J44: Pune | K44: CTE expansion; CTO (part) | L44: Approved (after SCN) | Q44: =IF(AND(ISNUMBER(O44),ISNUMBER(P44)),O44*P44/1000,"") | T44: https://mpcb.gov.in/sites/default/files/inline-files/Action_Taken_Report_of_16th_CAC_Booklet_no._16_%281%29.pdf | U44: Y
A45: M044 | B45: MPCB | C45: 0000166776 | D45: 13th CAC 2023-24 | E45: 2023-24 | F45: NTT Global Data Centers & Cloud Infrastructure India | G45: NTT | H45: Applicant | I45: Saki Vihar / Marol, Mumbai | J45: Mumbai (island/suburbs) | K45: CTO renewal | L45: Listed | Q45: =IF(AND(ISNUMBER(O45),ISNUMBER(P45)),O45*P45/1000,"") | R45: 960.53 | T45: https://mpcb.gov.in/sites/default/files/inline-files/Agenda%20Index%20of%2013th%20CAC%20Meeting.pdf | U45: Y
A46: M045 | B46: MERC | C46: Case 88 of 2026 | D46: MERC order | E46: 2026-06-01 | F46: Maharashtra STU (Lodha-funded DDF) | G46: AWS, STT + one more DC | H46: Order text | I46: Ambernath (Palava), Thane | J46: MMR - Palava/Ambernath/Taloja edge | K46: Grid connectivity granted | L46: Approved | M46: 1450 | N46: +1,500 MW under consideration; 4 x 500 MVA 400/220 kV | Q46: =IF(AND(ISNUMBER(O46),ISNUMBER(P46)),O46*P46/1000,"") | T46: https://merc.gov.in/wp-content/uploads/2026/06/Order-88-of-2026.pdf | U46: Y | V46: Connected-load column holds STU-granted connectivity
A48: Totals (excluding the MERC connectivity row)
A49: Connected load in permit records (MW) | M49: =SUMIFS(M2:M46,B2:B46,"<>MERC") -> 644.622
A50: DG back-up in permit records (MVA) | M50: =SUM(Q2:Q46) -> 886.9
A51: Capital investment in consent records (Rs cr) | M51: =SUM(R2:R46) -> 29774.24
A52: STU connectivity granted at Ambernath (MW) | M52: =SUMIFS(M2:M46,B2:B46,"MERC") -> 1450
A53: Permit records | M53: =COUNTA(A2:A46) -> 45

Sheet States_Evidence
A1: ID | B1: State | C1: Source / authority | D1: Reference | E1: Date | F1: Applicant / SPV | G1: Operator (mapped) | H1: Location | I1: Stage | J1: Grid / connected MW | K1: DG back-up (MW) | L1: Investment (Rs cr) | M1: Key facts | N1: Link | O1: Evidence tier | P1: Read in source? (Y/N)
A2: S001 | B2: Andhra Pradesh | C2: SEIAA AP (EC) + CTUIL | D2: EC 18-04-2026 (AP INFRA2 EC VSP 04 2026 2517); CTUIL GNA 11 apps | E2: 2026-04-18 | F2: Vizag Mega Data Center Park Ltd (Adani Infra SPV) | G2: Google (Raiden) - Adani | H2: Tarluvada, Anandapuram mandal | I2: EC granted; GNA 929 MW under process | J2: 929 | K2: 555 | L2: 26400 | M2: 1,000 MW park; BUA 1,48,922 m2; 200 x 2.75 MW + 5 x 1 MW DG; 267 KLD water; HSD storage 1,260 KL | N2: https://countercurrents.org/2026/04/hrf-flags-template-based-clearances-for-massive-andhra-data-centres-seeks-suspension-and-fresh-review/ | O2: A2 | P2: N
A3: S002 | B3: Andhra Pradesh | C3: SEIAA AP (EC) + CTUIL | D3: EC 18-04-2026; CTUIL GNA 8 apps | E3: 2026-04-18 | F3: Vizag Rambilli Data Center Park Ltd (Adani Infra SPV) | G3: Google (Raiden) - Adani | H3: Rambilli Phase-II industrial park, Anakapalli | I3: EC granted; GNA 697 MW under process | J3: 697 | K3: 416.5 | M3: 697 MW (some reports 1 GW); BUA 1,48,476 m2; 150 x 2.75 MW + 4 x 1 MW DG; 234 KLD water | N3: https://countercurrents.org/2026/04/hrf-flags-template-based-clearances-for-massive-andhra-data-centres-seeks-suspension-and-fresh-review/ | O3: A2 | P3: N
A4: S003 | B4: Andhra Pradesh | C4: SEIAA AP (EC) + APPCB (CTE) + CTUIL | D4: EC 05/10-06-2026; APPCB CTE 680/APPCB/CTE/RO-VSP/HO/2026 (14-07-2026); CTUIL GNA 8 apps | E4: 2026-06-10 | F4: Vizag Hyperscale Data Center Park Ltd (Adani Infra SPV) | G4: Google (Raiden) - Adani | H4: Adavivaram & Mudasarlova (~160 acres) | I4: EC & CTE granted; GNA 697 MW under process | J4: 512 | K4: 275 | M4: Power requirement 512 MW from discom (SEIAA affidavit to AP High Court); 100 x 2.75 MW DG; BUA ~1.23 lakh m2; 307 KLD water; air-cooled chillers; CTUIL filing is 697 MW | N4: https://theprint.in/judiciary/google-adani-vizag-data-centre-got-green-nod-on-built-up-area-not-ops-andhra-govt-affidavit-explains/3025598/ | O4: A2 | P4: N
A5: S004 | B5: Andhra Pradesh | C5: CTUIL | D5: GNA register - three Google-Adani SPVs | E5: 2026-05-09 | F5: Vizag Mega / Rambilli / Hyperscale DC Park Ltds | G5: Google - Adani | H5: Gajuwaka & Pendurthi (proposed) 400 kV | I5: Under process | J5: 2323 | M5: Total ISTS bulk-consumer GNA sought by the three SPVs = 929 + 697 + 697 MW - vs '1 GW' in the land GO | N5: https://ctuil.in/nswsapi/gna | O5: A1 | P5: Y
A6: S005 | B6: Andhra Pradesh | C6: AP ITE&C | D6: G.O.Ms.No.40 (11-10-2025) & G.O.Ms.No.66 (02-12-2025) | E6: 2025-12-02 | F6: Raiden Infotech India (Google) | G6: Google | H6: Adavivaram-Mudasarlova, Tarluvada, Rambilli (480 acres) | I6: Land allotment + partners notified | J6: 1000 | M6: 'AI Data Centres with a total capacity of around 1000 MW', US$15bn; partners Adani Infra, AdaniConneX, Adani Power, Airtel, Nxtra | N6: https://cdn.prod.website-files.com/5d70c9269b8d7bd25d8b1696/6a7eb3b63aaa0bf811886bd4_C5dmjgRvarnSVWAcsazFlsX-Tk7A3FFIaxfaW49XR8g.pdf | O6: A1 | P6: Y
A7: S006 | B7: Andhra Pradesh | C7: AP Energy Dept | D7: G.O.Ms.No.32 (Energy), 22-04-2026 | E7: 2026-04-22 | F7: Policy - Strategic Data Centers | G7: All DCs >= 300 MW connected load | H7: Statewide | I7: Policy notified | M7: Deemed Distribution Licence for 'Strategic Data Centers' with connected load >= 300 MW (aggregation across sites allowed) - lets DCs procure/manage own power | N7: https://countercurrents.org/2026/06/ap-govts-data-center-deemed-distribution-licence-policy-ddl-is-legally-unsustainable-must-be-withdrawn/ | O7: A2 | P7: N
A8: S007 | B8: Andhra Pradesh | C8: AP ITE&C | D8: G.O.Ms.No.30 & No.52 (2026, ITC) | E8: 2026 | F8: Reliance Industries | G8: Reliance | H8: Bhogapuram / Vizianagaram (854.97 acres) | I8: Land allotted; amended | J8: 1500 | L8: 108010 | M8: 'Giga-Scale AI Data Center'; activist registry lists 1.5 GW | N8: https://stopdirtydatacenters.org/ | O8: A2 | P8: N
A9: S008 | B9: Andhra Pradesh | C9: AP ITE&C | D9: G.O.Ms.No.55 (2026, ITC) | E9: 2026-08 | F9: Renew AP Green Data Center Pvt Ltd | G9: ReNew | H9: Makavaripalem, Anakapalli (433.3 acres) | I9: Land + incentives | J9: 1000 | L9: 85200 | M9: 1,000 MW | N9: https://www.medianama.com/2026/08/223-andhra-pradesh-ai-data-centres/ | O9: A2 | P9: N
A10: S009 | B10: Andhra Pradesh | C10: AP ITE&C | D10: G.O.Ms.No.56 (21-08-2026, ITC) | E10: 2026-08-21 | F10: Data Centre Holdings India LLP (Colt-RMZ) | G10: Colt DCS / RMZ | H10: Jagnadhapuram, Anandapuram (200 acres) | I10: Land + incentives | J10: 486 | L10: 58743 | M10: 486 MW; Deemed Distribution Licensee status to be facilitated | N10: https://www.medianama.com/2026/08/223-andhra-pradesh-ai-data-centres/ | O10: A2 | P10: N
A11: S010 | B11: Andhra Pradesh | C11: AP ITE&C | D11: G.O.Ms.No.59 (2026, ITC); SIPB 20th meeting 12-08-2026 | E11: 2026-08-12 | F11: AM AI Factory (Vizag) Pvt Ltd | G11: AM Intelligence Labs | H11: Amanam, Bheemunipatnam (6.82 acres per registry) | I11: Approval | J11: 512 | L11: 31387 | M11: 512 MW Green Integrated AI DC, to be set up within 2 years | N11: https://theprint.in/india/andhra-approves-green-ai-data-centre-in-visakhapatnam-with-investment-of-over-rs-30000-cr/3022441/ | O11: A2 | P11: N
A12: S011 | B12: Andhra Pradesh | C12: APTRANSCO / AP Energy Dept | D12: Transmission roadmap statement | E12: 2026-06-10 | F12: APTRANSCO | G12: 16 DC projects | H12: Vizag region (Pendurthi, Maradam, Achyutapuram, Palasa, Padmanabham, Makavaripalem, new Rambilli 400/220 kV) | I12: Plan | J12: 9100 | M12: 16 DC projects = 9.1 GW IT load; ~15 GW total demand by FY2036-37 | N12: https://telanganatoday.com/andhra-pradesh-plans-15-gw-transmission-network-for-data-centres | O12: A2 | P12: N
A13: S012 | B13: Andhra Pradesh | C13: Civil-society registry (compiles GOs/ECs) | D13: stopdirtydatacenters.org project registry | E13: 2026-10 | F13: 14 projects | G13: Various | H13: Vizag / Anakapalli / Vizianagaram | I13: Mixed | J13: 8000 | M13: Registry total 8.0 GW on 2,597 acres (incl. TCS-OpenAI 1 GW Rambilli; Google-Adani 2.5 GW; Reliance 1.5 GW) | N13: https://stopdirtydatacenters.org/ | O13: D | P13: Y
A14: S013 | B14: Telangana | C14: TGTRANSCO (per developer) | D14: Power sanction | E14: 2026-09 | F14: Fortune Hospitality & Infra LLP / Sudeeksha Estates LLP | G14: Fortune | H14: Kandukur mandal, Ranga Reddy (170 acres) | I14: Power sanctioned | L14: 60000 | M14: 2,000 MVA sanctioned (400 MVA Dec-2027; full Dec-2034); 1,200-1,600 MW IT | N14: https://www.convergence-now.com/artificial-intelligence/telanganas-ai-data-centre-race-gets-bigger-with-%E2%82%B91-3-lakh-crore-project/ | O14: C | P14: N
A15: S014 | B15: Telangana | C15: CTUIL | D15: GNA register | E15: 2026-09-25 | F15: HyperVault AI Data Center Ltd (TCS) | G15: TCS / OpenAI | H15: Maheshwaram 765/400 kV | I15: Under process | J15: 1550 | M15: 450 MW (Jun-2026) + 1,100 MW (Sep-2026) | N15: https://ctuil.in/nswsapi/gna | O15: A1 | P15: Y
A16: S015 | B16: Telangana | C16: CTUIL | D16: GNA register | E16: 2026-08-03 | F16: Chandenvalle Infra Park Ltd; Madhuvanti Build Estate Ltd | G16: Unknown (near AWS Chandanvelly site) | H16: LILO of 400 kV Doma-Kethireddypally | I16: Under process | J16: 1056 | M16: 528 MW each, in identical 66/132 MW blocks | N16: https://ctuil.in/nswsapi/gna | O16: A1 | P16: Y
A17: S016 | B17: Telangana | C17: CTUIL | D17: GNA register | E17: 2026-08-03 | F17: Giridhari Build Estate Ltd; Granthik Realtors Pvt Ltd | G17: Unknown | H17: Maheshwaram / Bidar-Maheshwaram 765 kV LILO | I17: Under process | J17: 1346 | M17: Giridhari 1,172 MW + Granthik 174 MW | N17: https://ctuil.in/nswsapi/gna | O17: A1 | P17: Y
A18: S017 | B18: Telangana | C18: CTUIL | D18: GNA register | E18: 2026-09-18 | F18: Avrenta Data Centre Pvt Ltd; CtrlS Datacenters Ltd | G18: Avrenta (unknown); CtrlS | H18: Maheshwaram | I18: Under process / closed | J18: 150 | M18: Avrenta 100 MW (under process); CtrlS 50 MW (closed) | N18: https://ctuil.in/nswsapi/gna | O18: A1 | P18: Y
A19: S018 | B19: Telangana | C19: SEIAA Telangana EC (reported) | D19: EC appraisal - Peddavedu | E19: 2026-05-08 | F19: Amazon Data Services / CtrlS (site-level attribution not given) | G19: AWS or CtrlS | H19: Peddavedu | I19: EC granted / challenged | J19: 278 | K19: 269.5 | M19: 278 MW power demand; 110 x 3,500 kVA DG | N19: https://www.counterview.net/2026/05/scientists-flag-serious-omissions-in.html | O19: A2 | P19: N
A20: S019 | B20: Telangana | C20: Telangana IT Minister | D20: Speech at Microsoft India South Central region launch | E20: 2026-09-25 | F20: State | G20: - | H20: Statewide | I20: Statement | J20: 2000 | M20: >300 MW operational; 2 GW under development; target 5 GW by 2029; ~11 GW in MoUs | N20: https://indianinfrastructure.com/2026/09/25/telangana-government-sets-5-gw-hyperscale-data-centre-target-by-2029-eyes-30-billion-in-investment/ | O20: A2 | P20: N
A21: S020 | B21: Tamil Nadu | C21: TANTRANSCO (reported) | D21: 400/230-110 kV Ambattur GIS (TBCB via TNIDB) | E21: 2025-10-22 | F21: TANTRANSCO | G21: CtrlS, STT, NTT, CapitaLand area | H21: Ambattur Industrial Estate, Chennai | I21: Planned | L21: 1045 | M21: DC requests: 1,036 MVA at 230 kV + 344 MVA at 110 kV; 2 x 500 MVA 400/230 kV + 2 x 200 MVA 400/110 kV ICTs; 3.6 km 400 kV cable to Korattur | N21: https://www.dtnext.in/news/chennai/powerplay-tn-plans-substation-in-ambattur-to-back-data-centres-850341 | O21: A2 | P21: N
A22: S021 | B22: Tamil Nadu | C22: CTUIL | D22: GNA register | E22: 2026-08-12 | F22: Sitac DC Infra Pvt Ltd | G22: Unknown | H22: Tuticorin-II | I22: Under process | J22: 70 | M22: 70 MW | N22: https://ctuil.in/nswsapi/gna | O22: A1 | P22: Y
A23: S022 | B23: Karnataka | C23: CTUIL | D23: GNA register | E23: 2026-08-26 | F23: Sitac DC Pvt Ltd / Sitac DC Infra Pvt Ltd | G23: Unknown | H23: Tumakuru; Bidar | I23: Under process | J23: 120 | M23: 50 MW Tumkur + 70 MW Bidar | N23: https://ctuil.in/nswsapi/gna | O23: A1 | P23: Y
A24: S023 | B24: Karnataka | C24: Karnataka Cabinet | D24: Sustainable Data Centre Policy 2026-31 | E24: 2026-09 | F24: Govt of Karnataka | G24: - | H24: Statewide (Hoskote 500 MW park; Mysuru; Mangaluru) | I24: Policy approved | J24: 1000 | L24: 1300 | M24: Target 1 GW IT by 2031; ~400 MW installed; Rs 1,300.45 cr outlay | N24: https://www.medianama.com/2026/09/223-karnataka-sustainable-data-centre-policy/ | O24: A2 | P24: N
A25: S024 | B25: Uttar Pradesh | C25: UPLC (state dashboard) | D25: UP Data Centre Policy 2021 - impact as on Jun-2025 | E25: 2025-06 | F25: State | G25: Hiranandani NIDP, Adani, SKVR, NTT, STT, Web Werks | H25: Noida / Greater Noida | I25: Dashboard | J25: 133 | L25: 21343 | M25: 29 MoUs (Rs 1,36,124 cr); 644 MW proposed; 133 MW commercialised (NIDP 28, NTT 9, Adani 35, STT 40, SKVR 16, Web Werks 5); 11 MoUs (Rs 46,300 cr) on hold / non-responsive | N25: https://uplc.up.gov.in/en/page/uttar-pradesh-data-center-policy | O25: A1 | P25: Y
A26: S025 | B26: Uttar Pradesh | C26: UP Govt | D26: UP Data Centre Policy 2026 (cabinet 06-07-2026) | E26: 2026-07-06 | F26: Govt of UP | G26: - | H26: Statewide | I26: Policy | J26: 2000 | L26: 200000 | M26: Target +2 GW; DC Parks >= 40 MW; dual-grid subsidy for first 8 parks; DC Parks may seek distribution licence; 50-75% wheeling/transmission charge exemption for 25 yrs | N26: https://invest.up.gov.in/wp-content/uploads/2026/07/UPDCP-2026-Notification-English.pdf | O26: A1 | P26: Y
A27: S026 | B27: Odisha | C27: HLCA (CM-chaired) | D27: Approval | E27: 2026-08 | F27: High Density Data Centre Ltd (Adani Group) | G27: Adani | H27: Naraj (~250 acres) | I27: Approved | J27: 1000 | L27: 104000 | M27: 1 GW AI DC park | N27: https://www.businessworld.in/article/adani-arm-gets-odisha-nod-for-rs-1-04-lakh-cr-data-centre-park-625673 | O27: A2 | P27: N
A28: S027 | B28: Odisha | C28: State approvals | D28: Approval | E28: 2026 | F28: Sentraforge AI; HCLTech-Sarvam; RKD Construction | G28: Various | H28: Puri; Khordha; Cuttack | I28: Approved | J28: 120 | L28: 38391 | M28: Sentraforge 120 MW (Rs 22,634 cr); HCLTech-Sarvam Rs 14,257 cr; RKD Rs 1,500 cr | N28: https://www.business-standard.com/amp/companies/news/hcltech-ai-data-centre-odisha-sarvam-rs-14257-crore-investment-126072400775_1.html | O28: A2 | P28: N
A29: S028 | B29: Maharashtra | C29: CTUIL | D29: GNA register | E29: 2026-01-12 | F29: Support Properties Pvt Ltd | G29: AdaniConneX (ACXNMI-01, inferred) | H29: 400 kV POWERGRID Navi Mumbai (GIS) | I29: APPROVED | J29: 1468 | M29: 13 x 50 MW approved (Jul-2024 apps) + 418 + 74 + 174 + 152 MW approved (Jan-2026 apps) | N29: https://ctuil.in/nswsapi/gna | O29: A1 | P29: Y
A30: S029 | B30: Maharashtra | C30: CTUIL | D30: GNA register | E30: 2026-05-15 | F30: Adani Infra (India) Ltd | G30: Adani (DC inferred) | H30: LILO of 400 kV Padghe-Kharghar (Navi Mumbai) | I30: Under process | J30: 500 | M30: 10 x 50 MW | N30: https://ctuil.in/nswsapi/gna | O30: A1 | P30: Y
A31: S030 | B31: Maharashtra | C31: CTUIL | D31: GNA register | E31: 2026-09-16 | F31: Vardhexa Data Centre Pvt Ltd | G31: Unknown | H31: Pune (Talegaon) | I31: Under process | J31: 100 | M31: 100 MW | N31: https://ctuil.in/nswsapi/gna | O31: A1 | P31: Y

Sheet CTU_Bulk_Register
A1: Sr (CTUIL) | B1: Applicant | C1: Application no. | D1: Application date | E1: Nature of applicant | F1: GNA quantum (MW) | G1: Interconnection point | H1: Status | I1: State (derived) | J1: DC classification
A2: 78 | B2: DISTINGUISHED CONSULTANCY SOLUTIONS PRIVATE LIMITED | C2: 2200004188 | D2: 26-08-2026 | E2: Bulk consumer (including Green Hydrogen / Green Ammonia) seeking to connect to ISTS directly | F2: 100 | G2: VIJAYAWADA | H2: Under Process | I2: Andhra Pradesh | J2: DC - likely (SPV pattern)
A3: 153 | B3: QUBITIQ VENTURES PRIVATE LIMITED | C3: 2200004324 | D3: 06-10-2026 | E3: Bulk consumer (including Green Hydrogen / Green Ammonia) seeking to connect to ISTS directly | F3: 150 | G3: VIJAYAWADA | H3: Under Process | I3: Andhra Pradesh | J3: DC - likely (SPV pattern)
A4: 24 | B4: ADANI INFRA (INDIA) LIMITED | C4: 2200003734 | D4: 20-05-2026 | E4: Bulk consumer (including Green Hydrogen / Green Ammonia) seeking to connect to ISTS directly | F4: 50 | G4: VATAMAN (NEW) SUBSTATION, Gujarat | H4: Under Process | I4: Gujarat | J4: DC - likely (SPV pattern)
A5: 45 | B5: BLUEPARROT PEDESTAL LIMITED | C5: 2200004226 | D5: 03-09-2026 | E5: Bulk consumer (including Green Hydrogen / Green Ammonia) seeking to connect to ISTS directly | F5: 80 | G5: LILO of 765kV Halvad-Vataman line, Houwever Nearest Substation is Vataman | H5: Under Process | I5: Gujarat | J5: DC - likely (SPV pattern)
A6: 46 | B6: BLUEPARROT PEDESTAL LIMITED | C6: 2200004227 | D6: 03-09-2026 | E6: Bulk consumer (including Green Hydrogen / Green Ammonia) seeking to connect to ISTS directly | F6: 80 | G6: LILO of 765kV Halvad-Vataman line, Houwever Nearest Substation is Vataman | H6: Under Process | I6: Gujarat | J6: DC - likely (SPV pattern)
A7: 47 | B7: BLUEPARROT PEDESTAL LIMITED | C7: 2200004228 | D7: 03-09-2026 | E7: Bulk consumer (including Green Hydrogen / Green Ammonia) seeking to connect to ISTS directly | F7: 80 | G7: LILO of 765kV Halvad-Vataman line, Houwever Nearest Substation is Vataman | H7: Under Process | I7: Gujarat | J7: DC - likely (SPV pattern)
A8: 48 | B8: BLUEPARROT PEDESTAL LIMITED | C8: 2200004229 | D8: 03-09-2026 | E8: Bulk consumer (including Green Hydrogen / Green Ammonia) seeking to connect to ISTS directly | F8: 80 | G8: LILO of 765kV Halvad-Vataman line, Houwever Nearest Substation is Vataman | H8: Under Process | I8: Gujarat | J8: DC - likely (SPV pattern)
A9: 49 | B9: BLUEPARROT PEDESTAL LIMITED | C9: 2200004230 | D9: 03-09-2026 | E9: Bulk consumer (including Green Hydrogen / Green Ammonia) seeking to connect to ISTS directly | F9: 80 | G9: LILO of 765kV Halvad-Vataman line, Houwever Nearest Substation is Vataman | H9: Under Process | I9: Gujarat | J9: DC - likely (SPV pattern)
A10: 50 | B10: BLUEPARROT PEDESTAL LIMITED | C10: 2200004231 | D10: 03-09-2026 | E10: Bulk consumer (including Green Hydrogen / Green Ammonia) seeking to connect to ISTS directly | F10: 80 | G10: LILO of 765kV Halvad-Vataman line, Houwever Nearest Substation is Vataman | H10: Under Process | I10: Gujarat | J10: DC - likely (SPV pattern)
A11: 51 | B11: BLUEPARROT PEDESTAL LIMITED | C11: 2200004232 | D11: 03-09-2026 | E11: Bulk consumer (including Green Hydrogen / Green Ammonia) seeking to connect to ISTS directly | F11: 80 | G11: LILO of 765kV Halvad-Vataman line, Houwever Nearest Substation is Vataman | H11: Under Process | I11: Gujarat | J11: DC - likely (SPV pattern)
A12: 52 | B12: BLUEPARROT PEDESTAL LIMITED | C12: 2200004234 | D12: 03-09-2026 | E12: Bulk consumer (including Green Hydrogen / Green Ammonia) seeking to connect to ISTS directly | F12: 80 | G12: LILO of 765kV Halvad-Vataman line, Houwever Nearest Substation is Vataman | H12: Under Process | I12: Gujarat | J12: DC - likely (SPV pattern)
A13: 53 | B13: BLUEPARROT PEDESTAL LIMITED | C13: 2200004235 | D13: 03-09-2026 | E13: Bulk consumer (including Green Hydrogen / Green Ammonia) seeking to connect to ISTS directly | F13: 80 | G13: LILO of 765kV Halvad-Vataman line, Houwever Nearest Substation is Vataman | H13: Under Process | I13: Gujarat | J13: DC - likely (SPV pattern)
... A117: 112 | B117: HIRA ELECTRO SMELTERS LIMITED | C117: 2200004351 | D117: 21-09-2026 | E117: Bulk consumer (including Green Hydrogen / Green Ammonia) seeking to connect to ISTS directly | F117: 150 | G117: Palasa, 765 kV GIS Srikakulam Substation | H117: Under Process | I117: Andhra Pradesh | J117: Not DC (H2 / industrial / rail)
A118: 145 | B118: NTPC GREEN ENERGY LIMITED | C118: 2200001887 | D118: 12-04-2025 | E118: Bulk consumer (including Green Hydrogen / Green Ammonia) seeking to connect to ISTS directly | F118: 2500 | G118: Pudimadka,A.P | I118: Andhra Pradesh | J118: Not DC (H2 / industrial / rail)
A119: 146 | B119: NTPC GREEN ENERGY LIMITED | C119: 2200003870 | D119: 25-06-2026 | E119: Bulk consumer (including Green Hydrogen / Green Ammonia) seeking to connect to ISTS directly | F119: 1000 | G119: NTPC SIMHADRI SWITCHYARD | H119: Under Process | I119: Andhra Pradesh | J119: Not DC (H2 / industrial / rail)
A120: 207 | B120: ULTRATECH CEMENT LIMITED | C120: 2200003430 | D120: 05-03-2026 | E120: Bulk consumer (including Green Hydrogen / Green Ammonia) seeking to connect to ISTS directly | F120: 50 | G120: KURNOOL -3 ( Nandipadu) | H120: Under Process | I120: Andhra Pradesh | J120: Not DC (H2 / industrial / rail)
A121: 44 | B121: BHARAT ALUMINIUM CO LTD | C121: 2200002088 | D121: 31-05-2025 | E121: Bulk consumer (including Green Hydrogen / Green Ammonia) seeking to connect to ISTS directly | F121: 100 | G121: 765/400KV Dharamjaygarh Sub-Station | H121: Approved | I121: Chhattisgarh | J121: Not DC (H2 / industrial / rail)
A122: 127 | B122: JINDAL PANTHER CEMENT PRIVATE LIMITED | C122: 2200002291 | D122: 07-08-2025 | E122: Bulk consumer (including Green Hydrogen / Green Ammonia) seeking to connect to ISTS directly | F122: 50 | G122: 765/400KV Raigarh (Kotra Road) S/S | H122: CLOSED | I122: Chhattisgarh | J122: Not DC (H2 / industrial / rail)
A123: 128 | B123: JINDAL STEEL & POWER LIMITED | C123: 2200001016 | D123: 19-07-2024 | E123: Bulk consumer (including Green Hydrogen / Green Ammonia) seeking to connect to ISTS directly | F123: 260 | G123: POWER GIRD KOTRA | H123: Approved | I123: Chhattisgarh | J123: Not DC (H2 / industrial / rail)
A124: 40 | B124: ARCELORMITTAL NIPPON STEEL INDIA LIMITED | C124: 2200000362 | D124: 22-11-2023 | E124: Bulk consumer (including Green Hydrogen / Green Ammonia) seeking to connect to ISTS directly | F124: 337 | G124: EPTCL 400KV Sub-Station, Hazira, Surat. | H124: Approved | I124: Gujarat | J124: Not DC (H2 / industrial / rail)
A125: 41 | B125: ARCELORMITTAL NIPPON STEEL INDIA LIMITED | C125: 2200000377 | D125: 05-12-2023 | E125: Bulk consumer (including Green Hydrogen / Green Ammonia) seeking to connect to ISTS directly | F125: 150 | G125: EPTCL 400KV Sub-Station, Hazira, Surat | H125: Approved | I125: Gujarat | J125: Not DC (H2 / industrial / rail)
A126: 100 | B126: GRASIM INDUSTRIES LTD | C126: 2200000168 | D126: 03-08-2023 | E126: Bulk consumer (including Green Hydrogen / Green Ammonia) seeking to connect to ISTS directly | F126: 160 | G126: JHANOR | H126: CLOSED | I126: Gujarat | J126: Not DC (H2 / industrial / rail)
A127: 106 | B127: HINDALCO INDUSTRIES LIMITED | C127: 2200002327 | D127: 02-09-2025 | E127: Bulk consumer (including Green Hydrogen / Green Ammonia) seeking to connect to ISTS directly | F127: 150 | G127: DGEN TORRENT DAHEJ SUBSTATION CONNECTED TO NAVSARI ISTS SS | H127: CLOSED | I127: Gujarat | J127: Not DC (H2 / industrial / rail)
A128: 133 | B128: KUTCH CHEMICAL INDUSTRIES LIMITED | C128: 2200000323 | D128: 27-10-2023 | E128: Bulk consumer (including Green Hydrogen / Green Ammonia) seeking to connect to ISTS directly | F128: 100 | G128: POWER GRID CORPORATION OF INDIA BHACHAU SUB-STATION | H128: CLOSED | I128: Gujarat | J128: Not DC (H2 / industrial / rail)
A129: 134 | B129: L&T ENERGY GREEN TECH LIMITED | C129: 2200001742 | D129: 09-04-2025 | E129: Bulk consumer (including Green Hydrogen / Green Ammonia) seeking to connect to ISTS directly | F129: 575 | G129: Kandla (GIS) S/s | H129: CLOSED | I129: Gujarat | J129: Not DC (H2 / industrial / rail)
A130: 135 | B130: L&T GREEN ENERGY KANDLA PRIVATE LIMITED | C130: 2200003943 | D130: 04-07-2026 | E130: Bulk consumer (including Green Hydrogen / Green Ammonia) seeking to connect to ISTS directly | F130: 500 | G130: Kandla (GIS) S/s | H130: Under Process | I130: Gujarat | J130: Not DC (H2 / industrial / rail)
... A153: 149 | B153: OCIOR ENERGY GOPALPUR ONE PRIVATE LIMITED | C153: 2200003030 | D153: 16-01-2026 | E153: Bulk consumer (including Green Hydrogen / Green Ammonia) seeking to connect to ISTS directly | F153: 200 | G153: Gopalpur Substation | H153: Under Process | I153: Odisha | J153: Not DC (H2 / industrial / rail)
A154: 108 | B154: HINDUSTAN ZINC LIMITED | C154: 2200000457 | D154: 13-02-2024 | E154: Bulk consumer (including Green Hydrogen / Green Ammonia) seeking to connect to ISTS directly | F154: 50 | G154: Kankroli | I154: Rajasthan | J154: Not DC (H2 / industrial / rail)
A155: 109 | B155: HINDUSTAN ZINC LIMITED | C155: 2200000453 | D155: 13-02-2024 | E155: Bulk consumer (including Green Hydrogen / Green Ammonia) seeking to connect to ISTS directly | F155: 55 | G155: Kankroli | H155: CLOSED | I155: Rajasthan | J155: Not DC (H2 / industrial / rail)
A156: 110 | B156: HINDUSTAN ZINC LIMITED | C156: 2200001595 | D156: 13-02-2025 | E156: Bulk consumer (including Green Hydrogen / Green Ammonia) seeking to connect to ISTS directly | F156: 220 | G156: PGCIL Chittorgarh | H156: Approved | I156: Rajasthan | J156: Not DC (H2 / industrial / rail)
A157: 211 | B157: VEDANTA LIMITED | C157: 2200001695 | D157: 05-02-2025 | E157: Bulk consumer (including Green Hydrogen / Green Ammonia) seeking to connect to ISTS directly | F157: 100 | G157: Fathegarh-III PS | H157: CLOSED | I157: Rajasthan | J157: Not DC (H2 / industrial / rail)
A158: 118 | B158: Indian Railways | C158: 2200000852 | D158: 26-06-2024 | E158: Bulk consumer (including Green Hydrogen / Green Ammonia) seeking to connect to ISTS directly | F158: 65 | G158: SRIPERUMBUDUR | H158: CLOSED | I158: Tamil Nadu | J158: Not DC (H2 / industrial / rail)
A159: 122 | B159: Indian Railways | C159: 2200002160 | D159: 13-06-2025 | E159: Bulk consumer (including Green Hydrogen / Green Ammonia) seeking to connect to ISTS directly | F159: 60 | G159: Salem | H159: Under Process | I159: Tamil Nadu | J159: Not DC (H2 / industrial / rail)
A160: 123 | B160: Indian Railways | C160: 2200002379 | D160: 02-09-2025 | E160: Bulk consumer (including Green Hydrogen / Green Ammonia) seeking to connect to ISTS directly | F160: 75 | G160: THIRUVALAM ( KLR - MDS, TOWER NO. 0464 ) | H160: Under Process | I160: Tamil Nadu | J160: Not DC (H2 / industrial / rail)
A161: 107 | B161: HINDUSTAN ZINC LIMITED | C161: 2200000467 | D161: 13-02-2024 | E161: Bulk consumer (including Green Hydrogen / Green Ammonia) seeking to connect to ISTS directly | F161: 70 | G161: - | H161: CLOSED | I161: Unclear | J161: Not DC (H2 / industrial / rail)
A162: 111 | B162: HINDUSTAN ZINC LIMITED | C162: 2200002025 | D162: 02-06-2025 | E162: Bulk consumer (including Green Hydrogen / Green Ammonia) seeking to connect to ISTS directly | F162: 180 | G162: - | H162: CLOSED | I162: Unclear | J162: Not DC (H2 / industrial / rail)
A163: 117 | B163: Indian Railways | C163: 2200000375 | D163: 07-05-2024 | E163: Bulk consumer (including Green Hydrogen / Green Ammonia) seeking to connect to ISTS directly | F163: 50 | G163: NAINI | H163: CLOSED | I163: Uttar Pradesh | J163: Not DC (H2 / industrial / rail)
A164: 120 | B164: Indian Railways | C164: 2200001656 | D164: 06-02-2025 | E164: Bulk consumer (including Green Hydrogen / Green Ammonia) seeking to connect to ISTS directly | F164: 50 | G164: NAINI | H164: Approved | I164: Uttar Pradesh | J164: Not DC (H2 / industrial / rail)
A165: 124 | B165: Indian Railways | C165: 2200002494 | D165: 22-10-2025 | E165: Bulk consumer (including Green Hydrogen / Green Ammonia) seeking to connect to ISTS directly | F165: 50 | G165: Mainpuri PGCIL GSS | H165: CLOSED | I165: Uttar Pradesh | J165: Not DC (H2 / industrial / rail)
A166: 155 | B166: RELIANCE INDUSTRIES LIMITED | C166: 2200002406 | D166: 09-09-2025 | E166: Bulk consumer (including Green Hydrogen / Green Ammonia) seeking to connect to ISTS directly | F166: 350 | G166: 400/220 KV Jam Khambhaliya (GIS) | H166: Under Process | I166: Gujarat | J166: Possible (purpose not stated)
... A184: 160 | B184: RELIANCE INDUSTRIES LIMITED | C184: 2200003846 | D184: 15-06-2026 | E184: Bulk consumer (including Green Hydrogen / Green Ammonia) seeking to connect to ISTS directly | F184: 50 | G184: LILO at line -'400/220 KV Pune (Talegaon AIS) to RIL Nagothane' | H184: Under Process | I184: Maharashtra | J184: Possible (purpose not stated)
A186: Source: CTUIL 'Status of Application under GNA Regulation' (stage-II applications; bulk consumers >= 50 MW connecting directly to ISTS), downloaded 19-Oct-2026 from https://ctuil.in/nswsapi/gna . Yellow = data-centre named or likely. Classification is this dataset's judgement - see README.

Sheet Govt_Aggregates
A1: ID | B1: Scope | C1: Body / source owner | D1: Metric | E1: Value | F1: Unit | G1: As-of / date | H1: Evidence tier | I1: Source | J1: Link | K1: Read in source? (Y/N) | L1: Notes
A2: N001 | B2: India | C2: Ministry of Power - Rajya Sabha USQ 956 (MoS Shripad Naik) | D2: Additional load from AI data centres projected by 2031-32 (CEA) | E2: 26300 | F2: MW | G2: 2026-07-27 | H2: A1 | I2: Rajya Sabha unstarred question 956, answered 27-07-2026 | J2: https://sansad.in/getFile/annex/271/AU956_9jPv13.pdf?source=pqars | K2: Y | L2: No state-wise split in the answer. Annexure: all-India peak 289 GW (FY27) -> 388 GW (FY32).
A3: N002 | B3: India | C3: Ministry of Power (as reported) | D3: ...of which already applied for STU connectivity | E3: 17000 | F3: MW | G3: 2026-05-14 | H3: D | I3: Telborg briefing | J3: https://telborg.com/datacentre-briefings/256 | K3: N | L3: 9.3 GW not yet applied; covers 11 states. Need primary confirmation.
A4: N003 | B4: India | C4: Ministry of Power - Rajya Sabha USQ 4151 | D4: Data-centre capacity projected by 2031-32 (earlier estimate) | E4: 13560 | F4: MW | G4: 2026-03-30 | H4: A1 | I4: Rajya Sabha unstarred question 4151, answered 30-03-2026 | J4: https://sansad.in/getFile/annex/270/AU4151_DoYAWR.pdf?source=pqars | K4: Y | L4: Same 13.56 GW in RS USQ 1753 (15-12-2025), which put present DC power requirement at ~1 GW. The official estimate roughly doubled (13.56 -> +26.3 GW) within four months.
A5: N004 | B5: India | C5: Ministry of Power - Rajya Sabha USQ 1753 | D5: Present power requirement of data centres | E5: 1000 | F5: MW | G5: 2025-12-15 | H5: A1 | I5: Rajya Sabha unstarred question 1753, answered 15-12-2025 | J5: https://sansad.in/getFile/annex/269/AU1753_OkjHmF.pdf?source=pqars | K5: Y | L5: 'details of electricity consumed by the Data Centres are not centrally maintained'.
A6: N005 | B6: India | C6: MeitY (Lok Sabha USQ 2990) | D6: Installed data-centre capacity in India | E6: 1575 | F6: MW | G6: 2026-08-05 | H6: A1 | I6: Lok Sabha unstarred question 2990 | J6: https://sansad.in/getFile/lsapps/loksabhaquestions/annex/188/AU2990_SqOT7j.pdf | K6: Y | L6: Up from 375 MW in 2020.
A7: N006 | B7: Maharashtra | C7: MERC order Case 88/2026 (STU submission) | D7: DC load with STU grid connectivity granted - Ambernath region alone | E7: 1450 | F7: MW | G7: 2026-06-01 | H7: A1 | I7: MERC order 88/2026 | J7: https://merc.gov.in/wp-content/uploads/2026/06/Order-88-of-2026.pdf | K7: Y | L7: Plus ~1,500 MW under consideration => 2,950 MW by 2028 in one 400 kV node.
A8: N007 | B8: Maharashtra | C8: MSETCL STU Plan 2024-34 | D8: New 765/400 kV transformation planned at Mahape solely for DC consumers | E8: 6000 | F8: MVA | G8: 2024-25 | H8: A1 | I8: MSETCL STU plan, Annexure-E | J8: https://www.mahatransco.in/uploads/docs/STU%20Plan%202024-25%20to%202033-24.pdf | K8: Y | L8: Plus 2,000 MVA at 400/220 kV.
A9: N008 | B9: Maharashtra | C9: CMO adviser (Kaustubh Dhavse) | D9: State data-centre capacity target by 2032 | E9: 5700 | F9: MW | G9: 2026-09-03 | H9: D | I9: The420.in | J9: https://the420.in/maharashtra-data-centre-investment-ai-5-7-gw-capacity/ | K9: N | L9: Also: >US$300bn of DC investment interest; Maharashtra ~66% of India DC capacity.
A10: N009 | B10: India | C10: CEA Chairman (speech) | D10: Data-centre capacity outlook | E10: 25000 | F10: MW | G10: 2026-10-15 | H10: D | I10: Daily Prabhat | J10: https://www.dailyprabhat.com/indias-data-centre-capacity-may-surge-to-24-26-gw-impact-on-overall-power-demand-to-remain-limited-cea-chairman/ | K10: N | L10: Range 24-26 GW; midpoint shown.
A11: N010 | B11: Maharashtra | C11: Industries Dept & MIDC | D11: Mega DC projects in pipeline (count) | E11: 44 | F11: projects | G11: 2026-05-22 | H11: A2 | I11: IANS via NewKerala | J11: https://www.newkerala.com/news/a/maharashtra-emerges-data-centre-capital-rs-1669-lakh-893.htm | K11: N | L11: 28 under construction (Rs 7.77 lakh cr), 16 planning (Rs 8.91 lakh cr); LoIs issued for 28 projects (Rs 12.46 lakh cr).
A12: N011 | B12: Maharashtra | C12: Industries Dept & MIDC | D12: Combined IT capacity of 44 projects | E12: 23800 | F12: MW | G12: 2026-05-22 | H12: A2 | I12: IANS via NewKerala | J12: https://www.newkerala.com/news/a/maharashtra-emerges-data-centre-capital-rs-1669-lakh-893.htm | K12: N | L12: A second figure, 31,879 MW, is 'mapped to land requirement'.
A13: N012 | B13: Maharashtra | C13: Industries Dept & MIDC | D13: Capacity mapped to land requirement | E13: 31879 | F13: MW | G13: 2026-05-22 | H13: A2 | I13: IANS via NewKerala | J13: https://www.newkerala.com/news/a/maharashtra-emerges-data-centre-capital-rs-1669-lakh-893.htm | K13: N
A14: N013 | B14: Maharashtra | C14: Industries Dept & MIDC | D14: Total investment pipeline | E14: 1669000 | F14: Rs crore | G14: 2026-05-22 | H14: A2 | I14: IANS via NewKerala | J14: https://www.newkerala.com/news/a/maharashtra-emerges-data-centre-capital-rs-1669-lakh-893.htm | K14: N | L14: Rs 16.69 lakh crore.
A15: N014 | B15: Navi Mumbai | C15: Industries Dept & MIDC | D15: Navi Mumbai Hub capacity (7 projects) | E15: 4040 | F15: MW | G15: 2026-05-22 | H15: A2 | I15: IANS via NewKerala | J15: https://www.newkerala.com/news/a/maharashtra-emerges-data-centre-capital-rs-1669-lakh-893.htm | K15: N | L15: Rs 3.48 lakh crore.
A16: N015 | B16: Navi Mumbai | C16: Industries Dept & MIDC | D16: Taloja Corridor capacity (4 projects) | E16: 3770 | F16: MW | G16: 2026-05-22 | H16: A2 | I16: IANS via NewKerala | J16: https://www.newkerala.com/news/a/maharashtra-emerges-data-centre-capital-rs-1669-lakh-893.htm | K16: N | L16: Rs 1.31 lakh crore. Panvel South Rs 1.20 lakh cr (MW n/a).
A17: N016 | B17: Maharashtra | C17: Industries Dept & MIDC | D17: Water demand of DC pipeline | E17: 856 | F17: MLD | G17: 2026-05-22 | H17: A2 | I17: IANS via NewKerala | J17: https://www.newkerala.com/news/a/maharashtra-emerges-data-centre-capital-rs-1669-lakh-893.htm | K17: N | L17: Taloja 140 MLD; Navi Mumbai Hub 136 MLD.
A18: N017 | B18: Andhra Pradesh | C18: AP Energy Dept / APTRANSCO | D18: IT load of 16 DC projects (Vizag region) | E18: 9100 | F18: MW | G18: 2026-06-10 | H18: A2 | I18: PTI via Telangana Today | J18: https://telanganatoday.com/andhra-pradesh-plans-15-gw-transmission-network-for-data-centres | K18: N | L18: Total demand ~15 GW by FY2036-37.
A19: N018 | B19: Andhra Pradesh | C19: AP ITE&C (4 GOs) | D19: Capacity of 4 approved DC projects | E19: 3498 | F19: MW | G19: 2026-08 | H19: A2 | I19: MediaNama | J19: https://www.medianama.com/2026/08/223-andhra-pradesh-ai-data-centres/ | K19: N | L19: Rs 2.83 lakh cr; ~23% of AP record peak (15,016 MW).
A20: N019 | B20: Telangana | C20: State (MoUs) | D20: DC capacity in signed MoUs | E20: 11000 | F20: MW | G20: 2026 | H20: D | I20: w.media | J20: https://w.media/telangana-reveals-plans-to-build-a-1500-acre-data-center-city/ | K20: N
A21: N020 | B21: Uttar Pradesh | C21: Invest UP | D21: DC Policy 2026 target (additional) | E21: 2000 | F21: MW | G21: 2026-07-06 | H21: A2 | I21: Invest UP | J21: https://invest.up.gov.in/uttar-pradesh-data-centre-policy-2026/ | K21: N | L21: 2021-policy dashboard: 29 MoUs, 644 MW proposed, ~101 MW commercialised.
A22: N021 | B22: Gujarat | C22: Govt of Gujarat | D22: DC Policy 2026-29 target | E22: 7500 | F22: MW | G22: 2026 | H22: A2 | I22: Angel One | J22: https://www.angelone.in/news/economy/gujarat-unveils-data-centre-policy-2026-29-with-target-of-6-lakh-crore-investment | K22: N | L22: ~10 GW of proposals received; incentives only for >=150 MW IT.
A23: N022 | B23: Karnataka | C23: Govt of Karnataka | D23: Sustainable DC Policy 2026-31 target | E23: 1000 | F23: MW | G23: 2026-09 | H23: A2 | I23: MediaNama | J23: https://www.medianama.com/2026/09/223-karnataka-sustainable-data-centre-policy/ | K23: N | L23: ~400 MW installed today.
A24: N023 | B24: India - operator | C24: Adani Enterprises (AdaniConneX) | D24: Tied-up capacity | E24: 960 | F24: MW | G24: 2026-07 | H24: B | I24: AEL Q1 FY27 presentation | J24: https://www.adanienterprises.com/-/media/Project/Enterprises/Investors/Investor-Downloads/Results-Presentations/AEL_Investor_Presentation.pdf | K24: Y | L24: 65.4 MW operational; '2 GW platform by 2030'.
A25: N024 | B25: India - operator | C25: NTT GDC India (ICRA) | D25: DC capacity | E25: 280 | F25: MW | G25: 2025 | H25: B | I25: ICRA rationale | J25: https://www.icra.in/Rating/GetRationalReportFilePdf?Id=141427 | K25: Y | L25: Capex Rs 1,200-1,500 cr/yr FY26-28; ~24-25% market share.
A26: N025 | B26: India - operator | C26: Sify Infinit Spaces (DRHP) | D26: Built IT capacity | E26: 188 | F26: MW | G26: 2025-06-30 | H26: B | I26: DRHP coverage (Angel One) | J26: https://www.angelone.in/news/ipos/sify-infinit-spaces-files-drhp-for-3-700-crore-ipo-data-centre-expansion-in-focus | K26: N | L26: 129 MW sold + 81 MW contracted for FY26-27 delivery.
A27: N026 | B27: India - operator | C27: AirTrunk | D27: India build plan by 2030 | E27: 5000 | F27: MW | G27: 2026-06-05 | H27: C | I27: TechCrunch | J27: https://techcrunch.com/2026/06/05/airtrunk-commits-30b-to-build-5gw-of-ai-data-centers-in-india/ | K27: N | L27: US$30bn; ~600 MW existing pipeline across Mumbai, Chennai, Hyderabad.
A28: N027 | B28: India - operator | C28: Nxtra (Bharti Airtel) | D28: Target capacity | E28: 1000 | F28: MW | G28: 2026 | H28: C | I28: CRN Asia | J28: https://www.crnasia.com/india/news/2026/airtel-raises-1-billion-for-nxtra-to-scale-ai-ready-data-centre-capacity-to-1-gw | K28: N | L28: ~250-300 MW today; US$1bn raise led by Alpha Wave.
A29: N028 | B29: India - utility | C29: Tata Power | D29: DC opportunity pipeline | E29: 2800 | F29: MW | G29: 2026-10-14 | H29: B | I29: TaxGuru | J29: https://taxguru.in/finance/business/tata-power-expands-data-centre-opportunities-with-2-8-gw-pipeline.html | K29: N | L29: See Grid sheet.

Sheet To_Pull
A1: # | B1: Document to retrieve | C1: Where | D1: Why it matters | E1: Blocker
A2: 1 | B2: Source of the '17 GW applied with STUs / 11 states' split (not in RS USQ 956) | C2: CEA data-centre committee papers; CEA resource-adequacy reviews; RTI to CEA | D2: Would give state-wise DC connectivity applications - the most direct test of the client thesis | E2: RESOLVED in part: RS USQ 956 retrieved - national figure only
A3: 2 | B3: Maharashtra Industries/MIDC list of 44 mega DC projects (May-2026) | C3: Industries Dept / MIDC / DGIPR press release; RTI if needed | D3: Gives project-level names behind the 23.8 GW; compare against announcements | E3: Only press summaries found
A4: 3 | B4: SEIAA/SEAC minutes for the 19 DC proposals in MH_Permits (connected load, DG, transformer data) | C4: environmentclearance.nic.in SEIAA minutes (scanned - OCR) & SEAC-2/3 minutes on ecmpcb.in | D4: Hard power numbers per project | E4: PARIVESH proposal search shows 'Coming soon'; agendas only list titles
A5: 4 | B5: MSETCL STU connectivity register for data centres (all MH nodes, not just Ambernath) | C5: RTI to MSETCL/STU; MERC petitions citing STU connectivity | D5: MERC 88/2026 shows STU tracks DC connectivity by applicant - same data for Mahape/Kharghar/Taloja nodes would size the hidden pipeline | E5: RESOLVED: MERC 88/2026 retrieved and read
A6: 5 | B6: MSETCL connectivity approvals / MSEDCL HT applications for data centres | C6: mahatransco.in (STU), mahadiscom.in; RTI | D6: Applicant-level MVA - the most direct test of 'unannounced' capacity | E6: Not published routinely
A7: 6 | B7: MPCB consent-to-establish / operate lists filtered for data centres | C7: mpcb.gov.in XGN consent search; consent committee minutes | D7: DG set capacity (kVA) per site => proxy for facility MW; reveals unannounced projects | E7: Portal search is form-based
A8: 7 | B8: CIDCO / MIDC board resolutions on DC land allotments (Taloja, TTC, Kharghar, Raigad-Pen/MMRDA) | C8: cidco.maharashtra.gov.in, midcindia.org, MMRDA PRs | D8: Who has land; acreage => MW potential | E8: Board minutes not indexed
A9: 8 | B9: CTUIL CMETS minutes (all regions, 2025-26) - scan for bulk-consumer / DC applicants | C9: ctuil.in -> ISTS consultation meeting minutes | D9: DC operators applying for 50 MW+ ISTS connectivity | E9: Volume (dozens of PDFs) - next pass
A10: 9 | B10: AP ITE&C GOs (G.O.Ms.56, 59 and others, 2026) | C10: apit.ap.gov.in / goir.ap.gov.in | D10: Primary confirmation of MW for ReNew, Reliance, AM AI Factory | E10: Mirror links 404
A11: 10 | B11: Company filings: Lodha Q1/Q2 FY27 deck; Sify DRHP; Anant Raj deck; Tata Power Q2 FY27 deck; Techno Electric; Yotta | C11: BSE/NSE filings | D11: Firm MW, capex and tenant data | E11: Next pass

Sheet Sources
A1: # | B1: URL | C1: Used in
A2: 1 | B2: https://investors.coreweave.com/news/news-details/2026/CoreWeave-Enters-India-Expanding-AI-Cloud-Platform-With-AdaniConneX/default.aspx | C2: Projects:P001
A3: 2 | B3: https://inc42.com/buzz/coreweave-enters-india-partners-adaniconnex-for-240-mw-data-centre-capacity/ | C3: Projects:P001
A4: 3 | B4: https://www.adanienterprises.com/-/media/Project/Enterprises/Investors/Investor-Downloads/Results-Presentations/AEL_Investor_Presentation.pdf | C4: Govt_Aggregates:N023, Projects:P002, Projects:P043, Projects:P047, Projects:P057, Projects:P060, Projects:P064
A5: 4 | B5: https://www.datacenters.com/adaniconnex-navi | C5: Projects:P003
A6: 5 | B6: https://www.adani.com/newsroom/media-releases/government-of-maharashtra | C6: Projects:P004
A7: 6 | B7: https://blitzindiamedia.com/west/amazon-taloja-data-center-environmental-clearance-seiaa-2026/ | C7: Projects:P005
A8: 7 | B8: https://www.datacenterdynamics.com/en/news/aws-plans-430m-data-center-in-navi-mumbai-india/ | C8: Projects:P005
A9: 8 | B9: https://merc.gov.in/wp-content/uploads/2026/06/Order-88-of-2026.pdf | C9: Govt_Aggregates:N006, Grid_Power:G004, MH_Permits:M045, Projects:P006
A10: 9 | B10: https://www.saurenergy.com/solar-energy-news/maharashtra-approves-transmission-infrastructure-for-13-lakh-crore-data-centre-park-11902218 | C10: Projects:P006
A11: 10 | B11: https://w.media/palava-land-deal-points-to-digital-edges-second-india-data-center/ | C11: Projects:P007
A12: 11 | B12: https://finimize.com/content/lodha-confirms-palava-land-sale-to-data-center-builder | C12: Projects:P007
A13: 12 | B13: https://en.wikipedia.org/wiki/Data_centre_industry_in_India | C13: Projects:P008
... A156: 155 | B156: https://www.crnasia.com/india/news/2026/airtel-raises-1-billion-for-nxtra-to-scale-ai-ready-data-centre-capacity-to-1-gw | C156: Govt_Aggregates:N027
