Workbook

Sheet Daily
A1: Date | B1: US Treasury Debt | C1: non-US Government Debt | D1: Municipal Credit | E1: Corporate Credit | F1: Public Equity | G1: Stocks | H1: Private Equity | I1: Real Estate | J1: Commodities | K1: Diversified Credit | L1: Asset-Backed Credit | M1: Active Strategies | N1: Specialty Finance | O1: Venture Capital | P1: Total
A2: 45658 | B2: 66368606 | C2: 155885 | D2: 0 | E2: 38 | F2: 0 | G2: 3697 | H2: 0 | I2: 4706 | J2: 5984693 | K2: 0 | L2: 0 | M2: 195363703 | N2: 598 | O2: 0 | P2: =SUM(B2:O2) -> 267881926
A3: 45659 | B3: 101591716 | C3: 177733 | D3: 0 | E3: 575 | F3: 0 | G3: 2050 | H3: 0 | I3: 31833 | J3: 36069445 | K3: 25 | L3: 0 | M3: 257741309 | N3: 1679 | O3: 0 | P3: =SUM(B3:O3) -> 395616365
A4: 45660 | B4: 52567227 | C4: 51582 | D4: 0 | E4: 230 | F4: 0 | G4: 84480 | H4: 0 | I4: 188966 | J4: 11369403 | K4: 0 | L4: 0 | M4: 189725522 | N4: 2377 | O4: 0 | P4: =SUM(B4:O4) -> 253989787
A5: 45661 | B5: 50394515 | C5: 22700 | D5: 0 | E5: 76 | F5: 0 | G5: 3397 | H5: 0 | I5: 8048 | J5: 4005716 | K5: 0 | L5: 0 | M5: 283993031 | N5: 389 | O5: 0 | P5: =SUM(B5:O5) -> 338427872
A6: 45662 | B6: 46763867 | C6: 110399 | D6: 0 | E6: 3 | F6: 0 | G6: 66212 | H6: 0 | I6: 5548 | J6: 15440859 | K6: 0 | L6: 0 | M6: 616567187 | N6: 251 | O6: 0 | P6: =SUM(B6:O6) -> 678954326
A7: 45663 | B7: 111439257 | C7: 382251 | D7: 0 | E7: 5 | F7: 0 | G7: 38464 | H7: 0 | I7: 8515 | J7: 24862350 | K7: 25 | L7: 0 | M7: 380425385 | N7: 41517 | O7: 0 | P7: =SUM(B7:O7) -> 517197769
A8: 45664 | B8: 76696127 | C8: 2464274 | D8: 0 | E8: 12 | F8: 0 | G8: 19790 | H8: 0 | I8: 77529 | J8: 67288737 | K8: 162 | L8: 0 | M8: 260851319 | N8: 90150452 | O8: 0 | P8: =SUM(B8:O8) -> 497548402
A9: 45665 | B9: 99308162 | C9: 1274574 | D9: 0 | E9: 131 | F9: 0 | G9: 8164 | H9: 0 | I9: 352093 | J9: 10934631 | K9: 0 | L9: 0 | M9: 469556237 | N9: 247310 | O9: 0 | P9: =SUM(B9:O9) -> 581681302
A10: 45666 | B10: 177209547 | C10: 390504 | D10: 0 | E10: 301 | F10: 0 | G10: 41871 | H10: 0 | I10: 101977 | J10: 6829256 | K10: 0 | L10: 0 | M10: 486100094 | N10: 1508 | O10: 0 | P10: =SUM(B10:O10) -> 670675058
A11: 45667 | B11: 71479464 | C11: 74710 | D11: 0 | E11: 7 | F11: 0 | G11: 112420 | H11: 0 | I11: 77317 | J11: 7303186 | K11: 25 | L11: 0 | M11: 316714220 | N11: 10776 | O11: 0 | P11: =SUM(B11:O11) -> 395772125
A12: 45668 | B12: 56709721 | C12: 123574 | D12: 0 | E12: 130 | F12: 0 | G12: 100 | H12: 0 | I12: 913 | J12: 2117175 | K12: 0 | L12: 0 | M12: 229985925 | N12: 2660 | O12: 0 | P12: =SUM(B12:O12) -> 288940198
A13: 45669 | B13: 17627407 | C13: 65305 | D13: 0 | E13: 5 | F13: 0 | G13: 59534 | H13: 0 | I13: 1414 | J13: 1721457 | K13: 0 | L13: 0 | M13: 155050713 | N13: 0 | O13: 0 | P13: =SUM(B13:O13) -> 174525835
... A618: 46274 | B618: 172346542 | C618: 42610289 | D618: 0 | E618: 6631416 | F618: 9667 | G618: 1630685405 | H618: 8100 | I618: 28919 | J618: 248221119 | K618: 263 | L618: 68827002 | M618: 278150314 | N618: 36476720 | O618: 64959 | P618: =SUM(B618:O618) -> 2484060715
A620: Source: rwa.xyz Overview > Total RWA Value > Transfer Volume (Daily Transfer Volume, USD). Asset Type = Distributed; stablecoins excluded (matches site defaults). Extracted 2026-09-11 via app.rwa.xyz API; data through 2026-09-09. Values rounded to whole dollars.
A621: Total column = SUM of asset-class columns.

Sheet Monthly
A1: Month | B1: US Treasury Debt | C1: non-US Government Debt | D1: Municipal Credit | E1: Corporate Credit | F1: Public Equity | G1: Stocks | H1: Private Equity | I1: Real Estate | J1: Commodities | K1: Diversified Credit | L1: Asset-Backed Credit | M1: Active Strategies | N1: Specialty Finance | O1: Venture Capital | P1: Total | Q1: MoM Change ($) | R1: MoM Change (%)
A2: 45658 | B2: =SUMIFS(Daily!$B$2:$B$618,Daily!$A$2:$A$618,">="&$A2,Daily!$A$2:$A$618,"<"&EDATE($A2,1)) -> 1436507089 | C2: =SUMIFS(Daily!$C$2:$C$618,Daily!$A$2:$A$618,">="&$A2,Daily!$A$2:$A$618,"<"&EDATE($A2,1)) -> 19559603 | D2: =SUMIFS(Daily!$D$2:$D$618,Daily!$A$2:$A$618,">="&$A2,Daily!$A$2:$A$618,"<"&EDATE($A2,1)) -> 0 | E2: =SUMIFS(Daily!$E$2:$E$618,Daily!$A$2:$A$618,">="&$A2,Daily!$A$2:$A$618,"<"&EDATE($A2,1)) -> 1652516 | F2: =SUMIFS(Daily!$F$2:$F$618,Daily!$A$2:$A$618,">="&$A2,Daily!$A$2:$A$618,"<"&EDATE($A2,1)) -> 0 | G2: =SUMIFS(Daily!$G$2:$G$618,Daily!$A$2:$A$618,">="&$A2,Daily!$A$2:$A$618,"<"&EDATE($A2,1)) -> 2396472 | H2: =SUMIFS(Daily!$H$2:$H$618,Daily!$A$2:$A$618,">="&$A2,Daily!$A$2:$A$618,"<"&EDATE($A2,1)) -> 0 | I2: =SUMIFS(Daily!$I$2:$I$618,Daily!$A$2:$A$618,">="&$A2,Daily!$A$2:$A$618,"<"&EDATE($A2,1)) -> 2382459 | J2: =SUMIFS(Daily!$J$2:$J$618,Daily!$A$2:$A$618,">="&$A2,Daily!$A$2:$A$618,"<"&EDATE($A2,1)) -> 440737456 | K2: =SUMIFS(Daily!$K$2:$K$618,Daily!$A$2:$A$618,">="&$A2,Daily!$A$2:$A$618,"<"&EDATE($A2,1)) -> 1315 | L2: =SUMIFS(Daily!$L$2:$L$618,Daily!$A$2:$A$618,">="&$A2,Daily!$A$2:$A$618,"<"&EDATE($A2,1)) -> 0 | M2: =SUMIFS(Daily!$M$2:$M$618,Daily!$A$2:$A$618,">="&$A2,Daily!$A$2:$A$618,"<"&EDATE($A2,1)) -> 8952571412 | N2: =SUMIFS(Daily!$N$2:$N$618,Daily!$A$2:$A$618,">="&$A2,Daily!$A$2:$A$618,"<"&EDATE($A2,1)) -> 90557187 | O2: =SUMIFS(Daily!$O$2:$O$618,Daily!$A$2:$A$618,">="&$A2,Daily!$A$2:$A$618,"<"&EDATE($A2,1)) -> 532255 | P2: =SUM(B2:O2) -> 10946897764 | Q2: - | R2: -
A3: 45689 | B3: =SUMIFS(Daily!$B$2:$B$618,Daily!$A$2:$A$618,">="&$A3,Daily!$A$2:$A$618,"<"&EDATE($A3,1)) -> 527482524 | C3: =SUMIFS(Daily!$C$2:$C$618,Daily!$A$2:$A$618,">="&$A3,Daily!$A$2:$A$618,"<"&EDATE($A3,1)) -> 21700516 | D3: =SUMIFS(Daily!$D$2:$D$618,Daily!$A$2:$A$618,">="&$A3,Daily!$A$2:$A$618,"<"&EDATE($A3,1)) -> 0 | E3: =SUMIFS(Daily!$E$2:$E$618,Daily!$A$2:$A$618,">="&$A3,Daily!$A$2:$A$618,"<"&EDATE($A3,1)) -> 2234719 | F3: =SUMIFS(Daily!$F$2:$F$618,Daily!$A$2:$A$618,">="&$A3,Daily!$A$2:$A$618,"<"&EDATE($A3,1)) -> 0 | G3: =SUMIFS(Daily!$G$2:$G$618,Daily!$A$2:$A$618,">="&$A3,Daily!$A$2:$A$618,"<"&EDATE($A3,1)) -> 897186 | H3: =SUMIFS(Daily!$H$2:$H$618,Daily!$A$2:$A$618,">="&$A3,Daily!$A$2:$A$618,"<"&EDATE($A3,1)) -> 0 | I3: =SUMIFS(Daily!$I$2:$I$618,Daily!$A$2:$A$618,">="&$A3,Daily!$A$2:$A$618,"<"&EDATE($A3,1)) -> 950709 | J3: =SUMIFS(Daily!$J$2:$J$618,Daily!$A$2:$A$618,">="&$A3,Daily!$A$2:$A$618,"<"&EDATE($A3,1)) -> 573712330 | K3: =SUMIFS(Daily!$K$2:$K$618,Daily!$A$2:$A$618,">="&$A3,Daily!$A$2:$A$618,"<"&EDATE($A3,1)) -> 4691 | L3: =SUMIFS(Daily!$L$2:$L$618,Daily!$A$2:$A$618,">="&$A3,Daily!$A$2:$A$618,"<"&EDATE($A3,1)) -> 0 | M3: =SUMIFS(Daily!$M$2:$M$618,Daily!$A$2:$A$618,">="&$A3,Daily!$A$2:$A$618,"<"&EDATE($A3,1)) -> 8146863340 | N3: =SUMIFS(Daily!$N$2:$N$618,Daily!$A$2:$A$618,">="&$A3,Daily!$A$2:$A$618,"<"&EDATE($A3,1)) -> 150251754 | O3: =SUMIFS(Daily!$O$2:$O$618,Daily!$A$2:$A$618,">="&$A3,Daily!$A$2:$A$618,"<"&EDATE($A3,1)) -> 162578 | P3: =SUM(B3:O3) -> 9424260347 | Q3: =P3-P2 -> -1522637417 | R3: =IF(P2=0,"-",P3/P2-1) -> -0.13909305
A4: 45717 | B4: =SUMIFS(Daily!$B$2:$B$618,Daily!$A$2:$A$618,">="&$A4,Daily!$A$2:$A$618,"<"&EDATE($A4,1)) -> 1774968996 | C4: =SUMIFS(Daily!$C$2:$C$618,Daily!$A$2:$A$618,">="&$A4,Daily!$A$2:$A$618,"<"&EDATE($A4,1)) -> 14829447 | D4: =SUMIFS(Daily!$D$2:$D$618,Daily!$A$2:$A$618,">="&$A4,Daily!$A$2:$A$618,"<"&EDATE($A4,1)) -> 0 | E4: =SUMIFS(Daily!$E$2:$E$618,Daily!$A$2:$A$618,">="&$A4,Daily!$A$2:$A$618,"<"&EDATE($A4,1)) -> 5046468 | F4: =SUMIFS(Daily!$F$2:$F$618,Daily!$A$2:$A$618,">="&$A4,Daily!$A$2:$A$618,"<"&EDATE($A4,1)) -> 0 | G4: =SUMIFS(Daily!$G$2:$G$618,Daily!$A$2:$A$618,">="&$A4,Daily!$A$2:$A$618,"<"&EDATE($A4,1)) -> 12693235 | H4: =SUMIFS(Daily!$H$2:$H$618,Daily!$A$2:$A$618,">="&$A4,Daily!$A$2:$A$618,"<"&EDATE($A4,1)) -> 0 | I4: =SUMIFS(Daily!$I$2:$I$618,Daily!$A$2:$A$618,">="&$A4,Daily!$A$2:$A$618,"<"&EDATE($A4,1)) -> 3443576 | J4: =SUMIFS(Daily!$J$2:$J$618,Daily!$A$2:$A$618,">="&$A4,Daily!$A$2:$A$618,"<"&EDATE($A4,1)) -> 611080031 | K4: =SUMIFS(Daily!$K$2:$K$618,Daily!$A$2:$A$618,">="&$A4,Daily!$A$2:$A$618,"<"&EDATE($A4,1)) -> 1062727 | L4: =SUMIFS(Daily!$L$2:$L$618,Daily!$A$2:$A$618,">="&$A4,Daily!$A$2:$A$618,"<"&EDATE($A4,1)) -> 213744274 | M4: =SUMIFS(Daily!$M$2:$M$618,Daily!$A$2:$A$618,">="&$A4,Daily!$A$2:$A$618,"<"&EDATE($A4,1)) -> 8382393634 | N4: =SUMIFS(Daily!$N$2:$N$618,Daily!$A$2:$A$618,">="&$A4,Daily!$A$2:$A$618,"<"&EDATE($A4,1)) -> 2196099 | O4: =SUMIFS(Daily!$O$2:$O$618,Daily!$A$2:$A$618,">="&$A4,Daily!$A$2:$A$618,"<"&EDATE($A4,1)) -> 3080508 | P4: =SUM(B4:O4) -> 11024538995 | Q4: =P4-P3 -> 1600278648 | R4: =IF(P3=0,"-",P4/P3-1) -> 0.16980416
A5: 45748 | B5: =SUMIFS(Daily!$B$2:$B$618,Daily!$A$2:$A$618,">="&$A5,Daily!$A$2:$A$618,"<"&EDATE($A5,1)) -> 803489480 | C5: =SUMIFS(Daily!$C$2:$C$618,Daily!$A$2:$A$618,">="&$A5,Daily!$A$2:$A$618,"<"&EDATE($A5,1)) -> 40321863 | D5: =SUMIFS(Daily!$D$2:$D$618,Daily!$A$2:$A$618,">="&$A5,Daily!$A$2:$A$618,"<"&EDATE($A5,1)) -> 0 | E5: =SUMIFS(Daily!$E$2:$E$618,Daily!$A$2:$A$618,">="&$A5,Daily!$A$2:$A$618,"<"&EDATE($A5,1)) -> 217585 | F5: =SUMIFS(Daily!$F$2:$F$618,Daily!$A$2:$A$618,">="&$A5,Daily!$A$2:$A$618,"<"&EDATE($A5,1)) -> 0 | G5: =SUMIFS(Daily!$G$2:$G$618,Daily!$A$2:$A$618,">="&$A5,Daily!$A$2:$A$618,"<"&EDATE($A5,1)) -> 21412870 | H5: =SUMIFS(Daily!$H$2:$H$618,Daily!$A$2:$A$618,">="&$A5,Daily!$A$2:$A$618,"<"&EDATE($A5,1)) -> 0 | I5: =SUMIFS(Daily!$I$2:$I$618,Daily!$A$2:$A$618,">="&$A5,Daily!$A$2:$A$618,"<"&EDATE($A5,1)) -> 4926710 | J5: =SUMIFS(Daily!$J$2:$J$618,Daily!$A$2:$A$618,">="&$A5,Daily!$A$2:$A$618,"<"&EDATE($A5,1)) -> 1293396749 | K5: =SUMIFS(Daily!$K$2:$K$618,Daily!$A$2:$A$618,">="&$A5,Daily!$A$2:$A$618,"<"&EDATE($A5,1)) -> 16182106 | L5: =SUMIFS(Daily!$L$2:$L$618,Daily!$A$2:$A$618,">="&$A5,Daily!$A$2:$A$618,"<"&EDATE($A5,1)) -> 471708758 | M5: =SUMIFS(Daily!$M$2:$M$618,Daily!$A$2:$A$618,">="&$A5,Daily!$A$2:$A$618,"<"&EDATE($A5,1)) -> 4251794470 | N5: =SUMIFS(Daily!$N$2:$N$618,Daily!$A$2:$A$618,">="&$A5,Daily!$A$2:$A$618,"<"&EDATE($A5,1)) -> 268681787 | O5: =SUMIFS(Daily!$O$2:$O$618,Daily!$A$2:$A$618,">="&$A5,Daily!$A$2:$A$618,"<"&EDATE($A5,1)) -> 654021 | P5: =SUM(B5:O5) -> 7172786399 | Q5: =P5-P4 -> -3851752596 | R5: =IF(P4=0,"-",P5/P4-1) -> -0.34937992
A6: 45778 | B6: =SUMIFS(Daily!$B$2:$B$618,Daily!$A$2:$A$618,">="&$A6,Daily!$A$2:$A$618,"<"&EDATE($A6,1)) -> 1189221817 | C6: =SUMIFS(Daily!$C$2:$C$618,Daily!$A$2:$A$618,">="&$A6,Daily!$A$2:$A$618,"<"&EDATE($A6,1)) -> 39486461 | D6: =SUMIFS(Daily!$D$2:$D$618,Daily!$A$2:$A$618,">="&$A6,Daily!$A$2:$A$618,"<"&EDATE($A6,1)) -> 0 | E6: =SUMIFS(Daily!$E$2:$E$618,Daily!$A$2:$A$618,">="&$A6,Daily!$A$2:$A$618,"<"&EDATE($A6,1)) -> 1653841 | F6: =SUMIFS(Daily!$F$2:$F$618,Daily!$A$2:$A$618,">="&$A6,Daily!$A$2:$A$618,"<"&EDATE($A6,1)) -> 0 | G6: =SUMIFS(Daily!$G$2:$G$618,Daily!$A$2:$A$618,">="&$A6,Daily!$A$2:$A$618,"<"&EDATE($A6,1)) -> 29969519 | H6: =SUMIFS(Daily!$H$2:$H$618,Daily!$A$2:$A$618,">="&$A6,Daily!$A$2:$A$618,"<"&EDATE($A6,1)) -> 0 | I6: =SUMIFS(Daily!$I$2:$I$618,Daily!$A$2:$A$618,">="&$A6,Daily!$A$2:$A$618,"<"&EDATE($A6,1)) -> 72095756 | J6: =SUMIFS(Daily!$J$2:$J$618,Daily!$A$2:$A$618,">="&$A6,Daily!$A$2:$A$618,"<"&EDATE($A6,1)) -> 870877510 | K6: =SUMIFS(Daily!$K$2:$K$618,Daily!$A$2:$A$618,">="&$A6,Daily!$A$2:$A$618,"<"&EDATE($A6,1)) -> 2025417 | L6: =SUMIFS(Daily!$L$2:$L$618,Daily!$A$2:$A$618,">="&$A6,Daily!$A$2:$A$618,"<"&EDATE($A6,1)) -> 862599847 | M6: =SUMIFS(Daily!$M$2:$M$618,Daily!$A$2:$A$618,">="&$A6,Daily!$A$2:$A$618,"<"&EDATE($A6,1)) -> 8982910665 | N6: =SUMIFS(Daily!$N$2:$N$618,Daily!$A$2:$A$618,">="&$A6,Daily!$A$2:$A$618,"<"&EDATE($A6,1)) -> 116825705 | O6: =SUMIFS(Daily!$O$2:$O$618,Daily!$A$2:$A$618,">="&$A6,Daily!$A$2:$A$618,"<"&EDATE($A6,1)) -> 15188185 | P6: =SUM(B6:O6) -> 12182854723 | Q6: =P6-P5 -> 5010068324 | R6: =IF(P5=0,"-",P6/P5-1) -> 0.69848286
A7: 45809 | B7: =SUMIFS(Daily!$B$2:$B$618,Daily!$A$2:$A$618,">="&$A7,Daily!$A$2:$A$618,"<"&EDATE($A7,1)) -> 667474726 | C7: =SUMIFS(Daily!$C$2:$C$618,Daily!$A$2:$A$618,">="&$A7,Daily!$A$2:$A$618,"<"&EDATE($A7,1)) -> 35544406 | D7: =SUMIFS(Daily!$D$2:$D$618,Daily!$A$2:$A$618,">="&$A7,Daily!$A$2:$A$618,"<"&EDATE($A7,1)) -> 0 | E7: =SUMIFS(Daily!$E$2:$E$618,Daily!$A$2:$A$618,">="&$A7,Daily!$A$2:$A$618,"<"&EDATE($A7,1)) -> 115582 | F7: =SUMIFS(Daily!$F$2:$F$618,Daily!$A$2:$A$618,">="&$A7,Daily!$A$2:$A$618,"<"&EDATE($A7,1)) -> 0 | G7: =SUMIFS(Daily!$G$2:$G$618,Daily!$A$2:$A$618,">="&$A7,Daily!$A$2:$A$618,"<"&EDATE($A7,1)) -> 40985905 | H7: =SUMIFS(Daily!$H$2:$H$618,Daily!$A$2:$A$618,">="&$A7,Daily!$A$2:$A$618,"<"&EDATE($A7,1)) -> 0 | I7: =SUMIFS(Daily!$I$2:$I$618,Daily!$A$2:$A$618,">="&$A7,Daily!$A$2:$A$618,"<"&EDATE($A7,1)) -> 26271166 | J7: =SUMIFS(Daily!$J$2:$J$618,Daily!$A$2:$A$618,">="&$A7,Daily!$A$2:$A$618,"<"&EDATE($A7,1)) -> 1963178822 | K7: =SUMIFS(Daily!$K$2:$K$618,Daily!$A$2:$A$618,">="&$A7,Daily!$A$2:$A$618,"<"&EDATE($A7,1)) -> 11958999 | L7: =SUMIFS(Daily!$L$2:$L$618,Daily!$A$2:$A$618,">="&$A7,Daily!$A$2:$A$618,"<"&EDATE($A7,1)) -> 1763647917 | M7: =SUMIFS(Daily!$M$2:$M$618,Daily!$A$2:$A$618,">="&$A7,Daily!$A$2:$A$618,"<"&EDATE($A7,1)) -> 4291844523 | N7: =SUMIFS(Daily!$N$2:$N$618,Daily!$A$2:$A$618,">="&$A7,Daily!$A$2:$A$618,"<"&EDATE($A7,1)) -> 44743323 | O7: =SUMIFS(Daily!$O$2:$O$618,Daily!$A$2:$A$618,">="&$A7,Daily!$A$2:$A$618,"<"&EDATE($A7,1)) -> 552627 | P7: =SUM(B7:O7) -> 8846317996 | Q7: =P7-P6 -> -3336536727 | R7: =IF(P6=0,"-",P7/P6-1) -> -0.2738715
A8: 45839 | B8: =SUMIFS(Daily!$B$2:$B$618,Daily!$A$2:$A$618,">="&$A8,Daily!$A$2:$A$618,"<"&EDATE($A8,1)) -> 2216419168 | C8: =SUMIFS(Daily!$C$2:$C$618,Daily!$A$2:$A$618,">="&$A8,Daily!$A$2:$A$618,"<"&EDATE($A8,1)) -> 54702910 | D8: =SUMIFS(Daily!$D$2:$D$618,Daily!$A$2:$A$618,">="&$A8,Daily!$A$2:$A$618,"<"&EDATE($A8,1)) -> 0 | E8: =SUMIFS(Daily!$E$2:$E$618,Daily!$A$2:$A$618,">="&$A8,Daily!$A$2:$A$618,"<"&EDATE($A8,1)) -> 200020485 | F8: =SUMIFS(Daily!$F$2:$F$618,Daily!$A$2:$A$618,">="&$A8,Daily!$A$2:$A$618,"<"&EDATE($A8,1)) -> 0 | G8: =SUMIFS(Daily!$G$2:$G$618,Daily!$A$2:$A$618,">="&$A8,Daily!$A$2:$A$618,"<"&EDATE($A8,1)) -> 358949851 | H8: =SUMIFS(Daily!$H$2:$H$618,Daily!$A$2:$A$618,">="&$A8,Daily!$A$2:$A$618,"<"&EDATE($A8,1)) -> 0 | I8: =SUMIFS(Daily!$I$2:$I$618,Daily!$A$2:$A$618,">="&$A8,Daily!$A$2:$A$618,"<"&EDATE($A8,1)) -> 6001242 | J8: =SUMIFS(Daily!$J$2:$J$618,Daily!$A$2:$A$618,">="&$A8,Daily!$A$2:$A$618,"<"&EDATE($A8,1)) -> 1367928968 | K8: =SUMIFS(Daily!$K$2:$K$618,Daily!$A$2:$A$618,">="&$A8,Daily!$A$2:$A$618,"<"&EDATE($A8,1)) -> 54761215 | L8: =SUMIFS(Daily!$L$2:$L$618,Daily!$A$2:$A$618,">="&$A8,Daily!$A$2:$A$618,"<"&EDATE($A8,1)) -> 1716254079 | M8: =SUMIFS(Daily!$M$2:$M$618,Daily!$A$2:$A$618,">="&$A8,Daily!$A$2:$A$618,"<"&EDATE($A8,1)) -> 16660896636 | N8: =SUMIFS(Daily!$N$2:$N$618,Daily!$A$2:$A$618,">="&$A8,Daily!$A$2:$A$618,"<"&EDATE($A8,1)) -> 374614771 | O8: =SUMIFS(Daily!$O$2:$O$618,Daily!$A$2:$A$618,">="&$A8,Daily!$A$2:$A$618,"<"&EDATE($A8,1)) -> 3956659 | P8: =SUM(B8:O8) -> 23014505984 | Q8: =P8-P7 -> 14168187988 | R8: =IF(P7=0,"-",P8/P7-1) -> 1.6015915
A9: 45870 | B9: =SUMIFS(Daily!$B$2:$B$618,Daily!$A$2:$A$618,">="&$A9,Daily!$A$2:$A$618,"<"&EDATE($A9,1)) -> 1566828458 | C9: =SUMIFS(Daily!$C$2:$C$618,Daily!$A$2:$A$618,">="&$A9,Daily!$A$2:$A$618,"<"&EDATE($A9,1)) -> 44912822 | D9: =SUMIFS(Daily!$D$2:$D$618,Daily!$A$2:$A$618,">="&$A9,Daily!$A$2:$A$618,"<"&EDATE($A9,1)) -> 0 | E9: =SUMIFS(Daily!$E$2:$E$618,Daily!$A$2:$A$618,">="&$A9,Daily!$A$2:$A$618,"<"&EDATE($A9,1)) -> 616042811 | F9: =SUMIFS(Daily!$F$2:$F$618,Daily!$A$2:$A$618,">="&$A9,Daily!$A$2:$A$618,"<"&EDATE($A9,1)) -> 0 | G9: =SUMIFS(Daily!$G$2:$G$618,Daily!$A$2:$A$618,">="&$A9,Daily!$A$2:$A$618,"<"&EDATE($A9,1)) -> 270003595 | H9: =SUMIFS(Daily!$H$2:$H$618,Daily!$A$2:$A$618,">="&$A9,Daily!$A$2:$A$618,"<"&EDATE($A9,1)) -> 0 | I9: =SUMIFS(Daily!$I$2:$I$618,Daily!$A$2:$A$618,">="&$A9,Daily!$A$2:$A$618,"<"&EDATE($A9,1)) -> 12790235 | J9: =SUMIFS(Daily!$J$2:$J$618,Daily!$A$2:$A$618,">="&$A9,Daily!$A$2:$A$618,"<"&EDATE($A9,1)) -> 934143990 | K9: =SUMIFS(Daily!$K$2:$K$618,Daily!$A$2:$A$618,">="&$A9,Daily!$A$2:$A$618,"<"&EDATE($A9,1)) -> 77507648 | L9: =SUMIFS(Daily!$L$2:$L$618,Daily!$A$2:$A$618,">="&$A9,Daily!$A$2:$A$618,"<"&EDATE($A9,1)) -> 2632428489 | M9: =SUMIFS(Daily!$M$2:$M$618,Daily!$A$2:$A$618,">="&$A9,Daily!$A$2:$A$618,"<"&EDATE($A9,1)) -> 10908558332 | N9: =SUMIFS(Daily!$N$2:$N$618,Daily!$A$2:$A$618,">="&$A9,Daily!$A$2:$A$618,"<"&EDATE($A9,1)) -> 224913423 | O9: =SUMIFS(Daily!$O$2:$O$618,Daily!$A$2:$A$618,">="&$A9,Daily!$A$2:$A$618,"<"&EDATE($A9,1)) -> 1325340 | P9: =SUM(B9:O9) -> 17289455143 | Q9: =P9-P8 -> -5725050841 | R9: =IF(P8=0,"-",P9/P8-1) -> -0.24875836
A10: 45901 | B10: =SUMIFS(Daily!$B$2:$B$618,Daily!$A$2:$A$618,">="&$A10,Daily!$A$2:$A$618,"<"&EDATE($A10,1)) -> 2566513555 | C10: =SUMIFS(Daily!$C$2:$C$618,Daily!$A$2:$A$618,">="&$A10,Daily!$A$2:$A$618,"<"&EDATE($A10,1)) -> 75205799 | D10: =SUMIFS(Daily!$D$2:$D$618,Daily!$A$2:$A$618,">="&$A10,Daily!$A$2:$A$618,"<"&EDATE($A10,1)) -> 0 | E10: =SUMIFS(Daily!$E$2:$E$618,Daily!$A$2:$A$618,">="&$A10,Daily!$A$2:$A$618,"<"&EDATE($A10,1)) -> 281870885 | F10: =SUMIFS(Daily!$F$2:$F$618,Daily!$A$2:$A$618,">="&$A10,Daily!$A$2:$A$618,"<"&EDATE($A10,1)) -> 0 | G10: =SUMIFS(Daily!$G$2:$G$618,Daily!$A$2:$A$618,">="&$A10,Daily!$A$2:$A$618,"<"&EDATE($A10,1)) -> 508325038 | H10: =SUMIFS(Daily!$H$2:$H$618,Daily!$A$2:$A$618,">="&$A10,Daily!$A$2:$A$618,"<"&EDATE($A10,1)) -> 1656924 | I10: =SUMIFS(Daily!$I$2:$I$618,Daily!$A$2:$A$618,">="&$A10,Daily!$A$2:$A$618,"<"&EDATE($A10,1)) -> 9320289 | J10: =SUMIFS(Daily!$J$2:$J$618,Daily!$A$2:$A$618,">="&$A10,Daily!$A$2:$A$618,"<"&EDATE($A10,1)) -> 2229410218 | K10: =SUMIFS(Daily!$K$2:$K$618,Daily!$A$2:$A$618,">="&$A10,Daily!$A$2:$A$618,"<"&EDATE($A10,1)) -> 101850777 | L10: =SUMIFS(Daily!$L$2:$L$618,Daily!$A$2:$A$618,">="&$A10,Daily!$A$2:$A$618,"<"&EDATE($A10,1)) -> 3151370809 | M10: =SUMIFS(Daily!$M$2:$M$618,Daily!$A$2:$A$618,">="&$A10,Daily!$A$2:$A$618,"<"&EDATE($A10,1)) -> 23662414815 | N10: =SUMIFS(Daily!$N$2:$N$618,Daily!$A$2:$A$618,">="&$A10,Daily!$A$2:$A$618,"<"&EDATE($A10,1)) -> 179096032 | O10: =SUMIFS(Daily!$O$2:$O$618,Daily!$A$2:$A$618,">="&$A10,Daily!$A$2:$A$618,"<"&EDATE($A10,1)) -> 4428903 | P10: =SUM(B10:O10) -> 32771464044 | Q10: =P10-P9 -> 15482008901 | R10: =IF(P9=0,"-",P10/P9-1) -> 0.89545962
A11: 45931 | B11: =SUMIFS(Daily!$B$2:$B$618,Daily!$A$2:$A$618,">="&$A11,Daily!$A$2:$A$618,"<"&EDATE($A11,1)) -> 7301016222 | C11: =SUMIFS(Daily!$C$2:$C$618,Daily!$A$2:$A$618,">="&$A11,Daily!$A$2:$A$618,"<"&EDATE($A11,1)) -> 93526717 | D11: =SUMIFS(Daily!$D$2:$D$618,Daily!$A$2:$A$618,">="&$A11,Daily!$A$2:$A$618,"<"&EDATE($A11,1)) -> 0 | E11: =SUMIFS(Daily!$E$2:$E$618,Daily!$A$2:$A$618,">="&$A11,Daily!$A$2:$A$618,"<"&EDATE($A11,1)) -> 253364802 | F11: =SUMIFS(Daily!$F$2:$F$618,Daily!$A$2:$A$618,">="&$A11,Daily!$A$2:$A$618,"<"&EDATE($A11,1)) -> 0 | G11: =SUMIFS(Daily!$G$2:$G$618,Daily!$A$2:$A$618,">="&$A11,Daily!$A$2:$A$618,"<"&EDATE($A11,1)) -> 889504106 | H11: =SUMIFS(Daily!$H$2:$H$618,Daily!$A$2:$A$618,">="&$A11,Daily!$A$2:$A$618,"<"&EDATE($A11,1)) -> 0 | I11: =SUMIFS(Daily!$I$2:$I$618,Daily!$A$2:$A$618,">="&$A11,Daily!$A$2:$A$618,"<"&EDATE($A11,1)) -> 8121879 | J11: =SUMIFS(Daily!$J$2:$J$618,Daily!$A$2:$A$618,">="&$A11,Daily!$A$2:$A$618,"<"&EDATE($A11,1)) -> 9645248395 | K11: =SUMIFS(Daily!$K$2:$K$618,Daily!$A$2:$A$618,">="&$A11,Daily!$A$2:$A$618,"<"&EDATE($A11,1)) -> 135442612 | L11: =SUMIFS(Daily!$L$2:$L$618,Daily!$A$2:$A$618,">="&$A11,Daily!$A$2:$A$618,"<"&EDATE($A11,1)) -> 5425780773 | M11: =SUMIFS(Daily!$M$2:$M$618,Daily!$A$2:$A$618,">="&$A11,Daily!$A$2:$A$618,"<"&EDATE($A11,1)) -> 12874098253 | N11: =SUMIFS(Daily!$N$2:$N$618,Daily!$A$2:$A$618,">="&$A11,Daily!$A$2:$A$618,"<"&EDATE($A11,1)) -> 768351639 | O11: =SUMIFS(Daily!$O$2:$O$618,Daily!$A$2:$A$618,">="&$A11,Daily!$A$2:$A$618,"<"&EDATE($A11,1)) -> 11485789 | P11: =SUM(B11:O11) -> 37405941187 | Q11: =P11-P10 -> 4634477143 | R11: =IF(P10=0,"-",P11/P10-1) -> 0.14141807
A12: 45962 | B12: =SUMIFS(Daily!$B$2:$B$618,Daily!$A$2:$A$618,">="&$A12,Daily!$A$2:$A$618,"<"&EDATE($A12,1)) -> 3228980481 | C12: =SUMIFS(Daily!$C$2:$C$618,Daily!$A$2:$A$618,">="&$A12,Daily!$A$2:$A$618,"<"&EDATE($A12,1)) -> 89737107 | D12: =SUMIFS(Daily!$D$2:$D$618,Daily!$A$2:$A$618,">="&$A12,Daily!$A$2:$A$618,"<"&EDATE($A12,1)) -> 0 | E12: =SUMIFS(Daily!$E$2:$E$618,Daily!$A$2:$A$618,">="&$A12,Daily!$A$2:$A$618,"<"&EDATE($A12,1)) -> 70530982 | F12: =SUMIFS(Daily!$F$2:$F$618,Daily!$A$2:$A$618,">="&$A12,Daily!$A$2:$A$618,"<"&EDATE($A12,1)) -> 0 | G12: =SUMIFS(Daily!$G$2:$G$618,Daily!$A$2:$A$618,">="&$A12,Daily!$A$2:$A$618,"<"&EDATE($A12,1)) -> 1097076519 | H12: =SUMIFS(Daily!$H$2:$H$618,Daily!$A$2:$A$618,">="&$A12,Daily!$A$2:$A$618,"<"&EDATE($A12,1)) -> 2609286 | I12: =SUMIFS(Daily!$I$2:$I$618,Daily!$A$2:$A$618,">="&$A12,Daily!$A$2:$A$618,"<"&EDATE($A12,1)) -> 11736082 | J12: =SUMIFS(Daily!$J$2:$J$618,Daily!$A$2:$A$618,">="&$A12,Daily!$A$2:$A$618,"<"&EDATE($A12,1)) -> 4146777748 | K12: =SUMIFS(Daily!$K$2:$K$618,Daily!$A$2:$A$618,">="&$A12,Daily!$A$2:$A$618,"<"&EDATE($A12,1)) -> 209755590 | L12: =SUMIFS(Daily!$L$2:$L$618,Daily!$A$2:$A$618,">="&$A12,Daily!$A$2:$A$618,"<"&EDATE($A12,1)) -> 6236056949 | M12: =SUMIFS(Daily!$M$2:$M$618,Daily!$A$2:$A$618,">="&$A12,Daily!$A$2:$A$618,"<"&EDATE($A12,1)) -> 14067425258 | N12: =SUMIFS(Daily!$N$2:$N$618,Daily!$A$2:$A$618,">="&$A12,Daily!$A$2:$A$618,"<"&EDATE($A12,1)) -> 720492857 | O12: =SUMIFS(Daily!$O$2:$O$618,Daily!$A$2:$A$618,">="&$A12,Daily!$A$2:$A$618,"<"&EDATE($A12,1)) -> 1016712 | P12: =SUM(B12:O12) -> 29882195571 | Q12: =P12-P11 -> -7523745616 | R12: =IF(P11=0,"-",P12/P11-1) -> -0.20113772
A13: 45992 | B13: =SUMIFS(Daily!$B$2:$B$618,Daily!$A$2:$A$618,">="&$A13,Daily!$A$2:$A$618,"<"&EDATE($A13,1)) -> 2304505633 | C13: =SUMIFS(Daily!$C$2:$C$618,Daily!$A$2:$A$618,">="&$A13,Daily!$A$2:$A$618,"<"&EDATE($A13,1)) -> 223117043 | D13: =SUMIFS(Daily!$D$2:$D$618,Daily!$A$2:$A$618,">="&$A13,Daily!$A$2:$A$618,"<"&EDATE($A13,1)) -> 0 | E13: =SUMIFS(Daily!$E$2:$E$618,Daily!$A$2:$A$618,">="&$A13,Daily!$A$2:$A$618,"<"&EDATE($A13,1)) -> 228916103 | F13: =SUMIFS(Daily!$F$2:$F$618,Daily!$A$2:$A$618,">="&$A13,Daily!$A$2:$A$618,"<"&EDATE($A13,1)) -> 0 | G13: =SUMIFS(Daily!$G$2:$G$618,Daily!$A$2:$A$618,">="&$A13,Daily!$A$2:$A$618,"<"&EDATE($A13,1)) -> 2571783051 | H13: =SUMIFS(Daily!$H$2:$H$618,Daily!$A$2:$A$618,">="&$A13,Daily!$A$2:$A$618,"<"&EDATE($A13,1)) -> 0 | I13: =SUMIFS(Daily!$I$2:$I$618,Daily!$A$2:$A$618,">="&$A13,Daily!$A$2:$A$618,"<"&EDATE($A13,1)) -> 8247368 | J13: =SUMIFS(Daily!$J$2:$J$618,Daily!$A$2:$A$618,">="&$A13,Daily!$A$2:$A$618,"<"&EDATE($A13,1)) -> 4717739480 | K13: =SUMIFS(Daily!$K$2:$K$618,Daily!$A$2:$A$618,">="&$A13,Daily!$A$2:$A$618,"<"&EDATE($A13,1)) -> 248999981 | L13: =SUMIFS(Daily!$L$2:$L$618,Daily!$A$2:$A$618,">="&$A13,Daily!$A$2:$A$618,"<"&EDATE($A13,1)) -> 6556729198 | M13: =SUMIFS(Daily!$M$2:$M$618,Daily!$A$2:$A$618,">="&$A13,Daily!$A$2:$A$618,"<"&EDATE($A13,1)) -> 6763706759 | N13: =SUMIFS(Daily!$N$2:$N$618,Daily!$A$2:$A$618,">="&$A13,Daily!$A$2:$A$618,"<"&EDATE($A13,1)) -> 460500044 | O13: =SUMIFS(Daily!$O$2:$O$618,Daily!$A$2:$A$618,">="&$A13,Daily!$A$2:$A$618,"<"&EDATE($A13,1)) -> 1527917 | P13: =SUM(B13:O13) -> 24085772577 | Q13: =P13-P12 -> -5796422994 | R13: =IF(P12=0,"-",P13/P12-1) -> -0.19397581
A14: 46023 | B14: =SUMIFS(Daily!$B$2:$B$618,Daily!$A$2:$A$618,">="&$A14,Daily!$A$2:$A$618,"<"&EDATE($A14,1)) -> 1951620943 | C14: =SUMIFS(Daily!$C$2:$C$618,Daily!$A$2:$A$618,">="&$A14,Daily!$A$2:$A$618,"<"&EDATE($A14,1)) -> 110071259 | D14: =SUMIFS(Daily!$D$2:$D$618,Daily!$A$2:$A$618,">="&$A14,Daily!$A$2:$A$618,"<"&EDATE($A14,1)) -> 0 | E14: =SUMIFS(Daily!$E$2:$E$618,Daily!$A$2:$A$618,">="&$A14,Daily!$A$2:$A$618,"<"&EDATE($A14,1)) -> 920732425 | F14: =SUMIFS(Daily!$F$2:$F$618,Daily!$A$2:$A$618,">="&$A14,Daily!$A$2:$A$618,"<"&EDATE($A14,1)) -> 0 | G14: =SUMIFS(Daily!$G$2:$G$618,Daily!$A$2:$A$618,">="&$A14,Daily!$A$2:$A$618,"<"&EDATE($A14,1)) -> 1833948998 | H14: =SUMIFS(Daily!$H$2:$H$618,Daily!$A$2:$A$618,">="&$A14,Daily!$A$2:$A$618,"<"&EDATE($A14,1)) -> 19969208 | I14: =SUMIFS(Daily!$I$2:$I$618,Daily!$A$2:$A$618,">="&$A14,Daily!$A$2:$A$618,"<"&EDATE($A14,1)) -> 29797754 | J14: =SUMIFS(Daily!$J$2:$J$618,Daily!$A$2:$A$618,">="&$A14,Daily!$A$2:$A$618,"<"&EDATE($A14,1)) -> 14103595870 | K14: =SUMIFS(Daily!$K$2:$K$618,Daily!$A$2:$A$618,">="&$A14,Daily!$A$2:$A$618,"<"&EDATE($A14,1)) -> 203860810 | L14: =SUMIFS(Daily!$L$2:$L$618,Daily!$A$2:$A$618,">="&$A14,Daily!$A$2:$A$618,"<"&EDATE($A14,1)) -> 7871002208 | M14: =SUMIFS(Daily!$M$2:$M$618,Daily!$A$2:$A$618,">="&$A14,Daily!$A$2:$A$618,"<"&EDATE($A14,1)) -> 6627937849 | N14: =SUMIFS(Daily!$N$2:$N$618,Daily!$A$2:$A$618,">="&$A14,Daily!$A$2:$A$618,"<"&EDATE($A14,1)) -> 416358187 | O14: =SUMIFS(Daily!$O$2:$O$618,Daily!$A$2:$A$618,">="&$A14,Daily!$A$2:$A$618,"<"&EDATE($A14,1)) -> 1681980 | P14: =SUM(B14:O14) -> 34090577491 | Q14: =P14-P13 -> 10004804914 | R14: =IF(P13=0,"-",P14/P13-1) -> 0.41538235
... A22: 46266 | B22: =SUMIFS(Daily!$B$2:$B$618,Daily!$A$2:$A$618,">="&$A22,Daily!$A$2:$A$618,"<"&EDATE($A22,1)) -> 1175552455 | C22: =SUMIFS(Daily!$C$2:$C$618,Daily!$A$2:$A$618,">="&$A22,Daily!$A$2:$A$618,"<"&EDATE($A22,1)) -> 101626500 | D22: =SUMIFS(Daily!$D$2:$D$618,Daily!$A$2:$A$618,">="&$A22,Daily!$A$2:$A$618,"<"&EDATE($A22,1)) -> 0 | E22: =SUMIFS(Daily!$E$2:$E$618,Daily!$A$2:$A$618,">="&$A22,Daily!$A$2:$A$618,"<"&EDATE($A22,1)) -> 82958041 | F22: =SUMIFS(Daily!$F$2:$F$618,Daily!$A$2:$A$618,">="&$A22,Daily!$A$2:$A$618,"<"&EDATE($A22,1)) -> 322938 | G22: =SUMIFS(Daily!$G$2:$G$618,Daily!$A$2:$A$618,">="&$A22,Daily!$A$2:$A$618,"<"&EDATE($A22,1)) -> 13955341715 | H22: =SUMIFS(Daily!$H$2:$H$618,Daily!$A$2:$A$618,">="&$A22,Daily!$A$2:$A$618,"<"&EDATE($A22,1)) -> 9903133 | I22: =SUMIFS(Daily!$I$2:$I$618,Daily!$A$2:$A$618,">="&$A22,Daily!$A$2:$A$618,"<"&EDATE($A22,1)) -> 562725 | J22: =SUMIFS(Daily!$J$2:$J$618,Daily!$A$2:$A$618,">="&$A22,Daily!$A$2:$A$618,"<"&EDATE($A22,1)) -> 2014479792 | K22: =SUMIFS(Daily!$K$2:$K$618,Daily!$A$2:$A$618,">="&$A22,Daily!$A$2:$A$618,"<"&EDATE($A22,1)) -> 30712204 | L22: =SUMIFS(Daily!$L$2:$L$618,Daily!$A$2:$A$618,">="&$A22,Daily!$A$2:$A$618,"<"&EDATE($A22,1)) -> 1282078752 | M22: =SUMIFS(Daily!$M$2:$M$618,Daily!$A$2:$A$618,">="&$A22,Daily!$A$2:$A$618,"<"&EDATE($A22,1)) -> 2141912760 | N22: =SUMIFS(Daily!$N$2:$N$618,Daily!$A$2:$A$618,">="&$A22,Daily!$A$2:$A$618,"<"&EDATE($A22,1)) -> 396859123 | O22: =SUMIFS(Daily!$O$2:$O$618,Daily!$A$2:$A$618,">="&$A22,Daily!$A$2:$A$618,"<"&EDATE($A22,1)) -> 65065 | P22: =SUM(B22:O22) -> 21192375203 | Q22: =P22-P21 -> -33701189709 | R22: =IF(P21=0,"-",P22/P21-1) -> -0.61393698
A24: Monthly figures = SUMIFS over the Daily sheet by calendar month; MoM change compares each month's Total to the prior month.
A25: 2026-09 is a partial month (data through 2026-09-09) — its MoM change is not like-for-like.
