Workbook

Sheet Summary
A1: State-level DC power evidence (non-CTUIL) - summary (MW)
A2: Block B on each state sheet excludes projects already in the CTUIL register, so it can be added to the CTUIL numbers without double counting.
A4: State | B4: Under process | C4: Approved | D4: Total | E4: Of which overlaps CTUIL (Yes/Possible) | F4: Total excl. CTUIL overlap
A5: Maharashtra | B5: =Maharashtra!B30 -> 7108.8 | C5: =Maharashtra!C30 -> 4005.4 | D5: =B5+C5 -> 11114.2 | E5: =SUMIFS(Backup_All_States!$E$2:$E$70,Backup_All_States!$A$2:$A$70,$A5,Backup_All_States!$L$2:$L$70,"Y",Backup_All_States!$J$2:$J$70,"<>No")+SUMIFS(Backup_All_States!$F$2:$F$70,Backup_All_States!$A$2:$A$70,$A5,Backup_All_States!$L$2:$L$70,"Y",Backup_All_States!$J$2:$J$70,"<>No") -> 240 | F5: =D5-E5 -> 10874.2
A6: Andhra Pradesh | B6: ='Andhra Pradesh'!B13 -> 0 | C6: ='Andhra Pradesh'!C13 -> 6486 | D6: =B6+C6 -> 6486 | E6: =SUMIFS(Backup_All_States!$E$2:$E$70,Backup_All_States!$A$2:$A$70,$A6,Backup_All_States!$L$2:$L$70,"Y",Backup_All_States!$J$2:$J$70,"<>No")+SUMIFS(Backup_All_States!$F$2:$F$70,Backup_All_States!$A$2:$A$70,$A6,Backup_All_States!$L$2:$L$70,"Y",Backup_All_States!$J$2:$J$70,"<>No") -> 2138 | F6: =D6-E6 -> 4348
A7: Telangana | B7: =Telangana!B14 -> 2386.8 | C7: =Telangana!C14 -> 2297.2 | D7: =B7+C7 -> 4684 | E7: =SUMIFS(Backup_All_States!$E$2:$E$70,Backup_All_States!$A$2:$A$70,$A7,Backup_All_States!$L$2:$L$70,"Y",Backup_All_States!$J$2:$J$70,"<>No")+SUMIFS(Backup_All_States!$F$2:$F$70,Backup_All_States!$A$2:$A$70,$A7,Backup_All_States!$L$2:$L$70,"Y",Backup_All_States!$J$2:$J$70,"<>No") -> 1406 | F7: =D7-E7 -> 3278
A8: Tamil Nadu | B8: ='Tamil Nadu'!B12 -> 157.9 | C8: ='Tamil Nadu'!C12 -> 239.1 | D8: =B8+C8 -> 397 | E8: =SUMIFS(Backup_All_States!$E$2:$E$70,Backup_All_States!$A$2:$A$70,$A8,Backup_All_States!$L$2:$L$70,"Y",Backup_All_States!$J$2:$J$70,"<>No")+SUMIFS(Backup_All_States!$F$2:$F$70,Backup_All_States!$A$2:$A$70,$A8,Backup_All_States!$L$2:$L$70,"Y",Backup_All_States!$J$2:$J$70,"<>No") -> 0 | F8: =D8-E8 -> 397
A9: Uttar Pradesh | B9: ='Uttar Pradesh'!B12 -> 434.8 | C9: ='Uttar Pradesh'!C12 -> 133 | D9: =B9+C9 -> 567.8 | E9: =SUMIFS(Backup_All_States!$E$2:$E$70,Backup_All_States!$A$2:$A$70,$A9,Backup_All_States!$L$2:$L$70,"Y",Backup_All_States!$J$2:$J$70,"<>No")+SUMIFS(Backup_All_States!$F$2:$F$70,Backup_All_States!$A$2:$A$70,$A9,Backup_All_States!$L$2:$L$70,"Y",Backup_All_States!$J$2:$J$70,"<>No") -> 0 | F9: =D9-E9 -> 567.8
A10: Odisha | B10: =Odisha!B8 -> 0 | C10: =Odisha!C8 -> 1120 | D10: =B10+C10 -> 1120 | E10: =SUMIFS(Backup_All_States!$E$2:$E$70,Backup_All_States!$A$2:$A$70,$A10,Backup_All_States!$L$2:$L$70,"Y",Backup_All_States!$J$2:$J$70,"<>No")+SUMIFS(Backup_All_States!$F$2:$F$70,Backup_All_States!$A$2:$A$70,$A10,Backup_All_States!$L$2:$L$70,"Y",Backup_All_States!$J$2:$J$70,"<>No") -> 0 | F10: =D10-E10 -> 1120
A11: Karnataka | B11: =Karnataka!B7 -> 500 | C11: =Karnataka!C7 -> 0 | D11: =B11+C11 -> 500 | E11: =SUMIFS(Backup_All_States!$E$2:$E$70,Backup_All_States!$A$2:$A$70,$A11,Backup_All_States!$L$2:$L$70,"Y",Backup_All_States!$J$2:$J$70,"<>No")+SUMIFS(Backup_All_States!$F$2:$F$70,Backup_All_States!$A$2:$A$70,$A11,Backup_All_States!$L$2:$L$70,"Y",Backup_All_States!$J$2:$J$70,"<>No") -> 0 | F11: =D11-E11 -> 500
A12: Gujarat | B12: =Gujarat!B7 -> 168 | C12: =Gujarat!C7 -> 0 | D12: =B12+C12 -> 168 | E12: =SUMIFS(Backup_All_States!$E$2:$E$70,Backup_All_States!$A$2:$A$70,$A12,Backup_All_States!$L$2:$L$70,"Y",Backup_All_States!$J$2:$J$70,"<>No")+SUMIFS(Backup_All_States!$F$2:$F$70,Backup_All_States!$A$2:$A$70,$A12,Backup_All_States!$L$2:$L$70,"Y",Backup_All_States!$J$2:$J$70,"<>No") -> 168 | F12: =D12-E12 -> 0
A13: Haryana | B13: =Haryana!B7 -> 279 | C13: =Haryana!C7 -> 28 | D13: =B13+C13 -> 307 | E13: =SUMIFS(Backup_All_States!$E$2:$E$70,Backup_All_States!$A$2:$A$70,$A13,Backup_All_States!$L$2:$L$70,"Y",Backup_All_States!$J$2:$J$70,"<>No")+SUMIFS(Backup_All_States!$F$2:$F$70,Backup_All_States!$A$2:$A$70,$A13,Backup_All_States!$L$2:$L$70,"Y",Backup_All_States!$J$2:$J$70,"<>No") -> 0 | F13: =D13-E13 -> 307
A14: West Bengal | B14: ='West Bengal'!B8 -> 275 | C14: ='West Bengal'!C8 -> 0 | D14: =B14+C14 -> 275 | E14: =SUMIFS(Backup_All_States!$E$2:$E$70,Backup_All_States!$A$2:$A$70,$A14,Backup_All_States!$L$2:$L$70,"Y",Backup_All_States!$J$2:$J$70,"<>No")+SUMIFS(Backup_All_States!$F$2:$F$70,Backup_All_States!$A$2:$A$70,$A14,Backup_All_States!$L$2:$L$70,"Y",Backup_All_States!$J$2:$J$70,"<>No") -> 0 | F14: =D14-E14 -> 275
A15: Total | B15: =SUM(B5:B14) -> 11310.3 | C15: =SUM(C5:C14) -> 14308.7 | D15: =SUM(D5:D14) -> 25619 | E15: =SUM(E5:E14) -> 3952 | F15: =SUM(F5:F14) -> 21667

Sheet MH_Reconciliation
A1: Why Maharashtra state-level data is ~5x the CTUIL data-centre filings
A2: Blue numbers are inputs from the CTUIL workbook (CTUIL_Bulk_Applications_by_State.xlsx, DC groups per your mapping: Adani, TCS, SITAC). All other numbers are formulas on Backup_All_States.
A4: Bridge item (Maharashtra) | B4: Approved (MW) | C4: Under process (MW) | D4: Total (MW) | E4: Share of state total | F4: Comparable to a CTUIL GNA filing?
A5: Lodha/Ambernath via state STU (MERC 88/2026) | B5: =SUMIFS(Backup_All_States!$E$2:$E$70,Backup_All_States!$A$2:$A$70,"Maharashtra",Backup_All_States!$O$2:$O$70,"1 Grid connection granted / sanctioned",Backup_All_States!$L$2:$L$70,"Y") -> 1450 | C5: =SUMIFS(Backup_All_States!$F$2:$F$70,Backup_All_States!$A$2:$A$70,"Maharashtra",Backup_All_States!$O$2:$O$70,"1 Grid connection granted / sanctioned",Backup_All_States!$L$2:$L$70,"Y") -> 1500 | D5: =B5+C5 -> 2950 | E5: =IF($D$10=0,0,D5/$D$10) -> 0.26542621 | F5: Yes in kind - but via STATE grid, so never in CTUIL
A6: Campus permits - mostly existing TTC-belt campuses on MSETCL/MSEDCL 220 kV | B6: =SUMIFS(Backup_All_States!$E$2:$E$70,Backup_All_States!$A$2:$A$70,"Maharashtra",Backup_All_States!$O$2:$O$70,"2 Permit (EC / pollution consent)",Backup_All_States!$L$2:$L$70,"Y") -> 2551.4 | C6: =SUMIFS(Backup_All_States!$F$2:$F$70,Backup_All_States!$A$2:$A$70,"Maharashtra",Backup_All_States!$O$2:$O$70,"2 Permit (EC / pollution consent)",Backup_All_States!$L$2:$L$70,"Y") -> 437.3 | D6: =B6+C6 -> 2988.7 | E6: =IF($D$10=0,0,D6/$D$10) -> 0.26890824 | F6: No - permits, often IT MW, state-grid connected
A7: Government approvals (GO / land) | B7: =SUMIFS(Backup_All_States!$E$2:$E$70,Backup_All_States!$A$2:$A$70,"Maharashtra",Backup_All_States!$O$2:$O$70,"3 Govt approval (GO / land)",Backup_All_States!$L$2:$L$70,"Y") -> 0 | C7: =SUMIFS(Backup_All_States!$F$2:$F$70,Backup_All_States!$A$2:$A$70,"Maharashtra",Backup_All_States!$O$2:$O$70,"3 Govt approval (GO / land)",Backup_All_States!$L$2:$L$70,"Y") -> 0 | D7: =B7+C7 -> 0 | E7: =IF($D$10=0,0,D7/$D$10) -> 0 | F7: No
A8: MoUs / LoIs / announcements (AirTrunk Raigad 3 GW, ReNew, Trentar, MAHAPREIT...) | B8: =SUMIFS(Backup_All_States!$E$2:$E$70,Backup_All_States!$A$2:$A$70,"Maharashtra",Backup_All_States!$O$2:$O$70,"4 MoU / LoI / announced",Backup_All_States!$L$2:$L$70,"Y") -> 4 | C8: =SUMIFS(Backup_All_States!$F$2:$F$70,Backup_All_States!$A$2:$A$70,"Maharashtra",Backup_All_States!$O$2:$O$70,"4 MoU / LoI / announced",Backup_All_States!$L$2:$L$70,"Y") -> 5051.5 | D8: =B8+C8 -> 5055.5 | E8: =IF($D$10=0,0,D8/$D$10) -> 0.45486855 | F8: No - intent only, no grid application yet
A9: Operating / company filings | B9: =SUMIFS(Backup_All_States!$E$2:$E$70,Backup_All_States!$A$2:$A$70,"Maharashtra",Backup_All_States!$O$2:$O$70,"5 Operating / company filing",Backup_All_States!$L$2:$L$70,"Y") -> 0 | C9: =SUMIFS(Backup_All_States!$F$2:$F$70,Backup_All_States!$A$2:$A$70,"Maharashtra",Backup_All_States!$O$2:$O$70,"5 Operating / company filing",Backup_All_States!$L$2:$L$70,"Y") -> 120 | D9: =B9+C9 -> 120 | E9: =IF($D$10=0,0,D9/$D$10) -> 0.010796998 | F9: No
A10: Maharashtra state-level total | B10: =SUM(B5:B9) -> 4005.4 | C10: =SUM(C5:C9) -> 7108.8 | D10: =SUM(D5:D9) -> 11114.2 | E10: =SUM(E5:E9) -> 1
A12: Like-for-like: grid-connection evidence only (MW)
A13: State | B13: CTUIL DC filings (ISTS) | C13: State-grid connection / sanction | D13: Total grid evidence | E13: State-grid share | F13: Main state-grid item
A14: Maharashtra | B14: 2068 | C14: =SUMIFS(Backup_All_States!$E$2:$E$70,Backup_All_States!$A$2:$A$70,$A14,Backup_All_States!$O$2:$O$70,"1 Grid*",Backup_All_States!$L$2:$L$70,"Y")+SUMIFS(Backup_All_States!$F$2:$F$70,Backup_All_States!$A$2:$A$70,$A14,Backup_All_States!$O$2:$O$70,"1 Grid*",Backup_All_States!$L$2:$L$70,"Y") -> 2950 | D14: =B14+C14 -> 5018 | E14: =IF(D14=0,0,C14/D14) -> 0.58788362 | F14: Lodha/Ambernath 1,450 granted + 1,500 under consideration (STU)
A15: Andhra Pradesh | B15: 2573 | C15: =SUMIFS(Backup_All_States!$E$2:$E$70,Backup_All_States!$A$2:$A$70,$A15,Backup_All_States!$O$2:$O$70,"1 Grid*",Backup_All_States!$L$2:$L$70,"Y")+SUMIFS(Backup_All_States!$F$2:$F$70,Backup_All_States!$A$2:$A$70,$A15,Backup_All_States!$O$2:$O$70,"1 Grid*",Backup_All_States!$L$2:$L$70,"Y") -> 0 | D15: =B15+C15 -> 2573 | E15: =IF(D15=0,0,C15/D15) -> 0 | F15: None found - Vizag DCs filed directly with CTUIL
A16: Telangana | B16: 4102 | C16: =SUMIFS(Backup_All_States!$E$2:$E$70,Backup_All_States!$A$2:$A$70,$A16,Backup_All_States!$O$2:$O$70,"1 Grid*",Backup_All_States!$L$2:$L$70,"Y")+SUMIFS(Backup_All_States!$F$2:$F$70,Backup_All_States!$A$2:$A$70,$A16,Backup_All_States!$O$2:$O$70,"1 Grid*",Backup_All_States!$L$2:$L$70,"Y") -> 2000 | D16: =B16+C16 -> 6102 | E16: =IF(D16=0,0,C16/D16) -> 0.32776139 | F16: Fortune 2,000 MVA (TGTRANSCO, per developer)
A18: 1. Different instruments: ~44% of the Maharashtra state number is MoU/LoI/announced capacity (AirTrunk's 3 GW Raigad LoI alone is 26%). These have no grid application yet - they cannot appear in CTUIL.
A19: 2. Different grid: Maharashtra DCs connect through the STATE network (MSETCL 220/400 kV; MSEDCL, Tata Power, AEML distribution). MERC Case 88/2026 records STU - not CTU - connectivity for AWS and STT at Ambernath; MSETCL's STU plan builds a 765/400/220 kV Mahape node 'for Datacenter Consumers' (6,000 + 2,000 MVA).
A20: 3. ISTS access is physically constrained in Navi Mumbai: CTUIL's 26th WR consultation meeting (28-02-2024) recorded 'No margins for drawal of power exist at existing 400/220kV Navi Mumbai S/s'. Only Support Properties (1,468 MW, approved) and Adani Infra (500 MW, pending) have direct ISTS filings.
A21: 4. Different units: most permit rows are IT MW or design capacity of existing campuses (Sify 377, Digital Edge 400, NTT 530), not grid MW.
A22: 5. By contrast, AP and Telangana mega-campuses are greenfield, far from strong state networks, and filed directly with CTUIL (Vizag SPVs at Gajuwaka/Pendurthi; Telangana SPVs at Maheshwaram/Doma) - so CTUIL captures a larger share there.
A23: Conclusion: the 5x is mainly a measurement artefact (instrument + grid route), not double counting. For a like-for-like national chart, use grid-connection evidence only (table above) or CTUIL + state-grid connectivity; show MoU/LoI separately as 'pipeline intent'.
A24: Residual risk: AWS Thane (Balkum, 272 MW IT) and STT's Navi Mumbai rows could partly draw on the Ambernath STU connectivity - not confirmed; kept separate.

Sheet Audit_Log
A1: Row-by-row audit of every MW figure (21-Oct-2026)
A2: Method: each row's linked source was re-fetched (or the local copy / OCR of the scanned minutes used) and the MW figure, company and site searched in it; every match was then read in context.
A4: Backup row | B4: State | C4: Group | D4: Project / site | E4: Approved MW (now) | F4: Under process MW (now) | G4: Tier (now) | H4: Verdict | I4: What was checked / changed
A5: 2 | B5: Maharashtra | C5: Lodha Group (park; tenants AWS, STT) | D5: Palava-Ambernath Green DC Park | E5: 1450 | F5: 1500 | G5: A1 | H5: Verified - primary doc | I5: 1,450 + 1,500 MW quoted in MERC order para 7.15
A6: 3 | B6: Maharashtra | C6: AirTrunk (Blackstone) | D6: Raigad-Pen Growth Centre | F6: 3000 | G6: A2 | H6: Verified - press / reported govt action | I6: 3 GW quoted (CM statement via ANI)
A7: 4 | B7: Maharashtra | C7: AirTrunk (Blackstone) | D7: BOM1, Plot 7 & 7A TTC Airoli | E7: 62 | G7: D | H7: Downgraded | I7: Was 182 MW combined with BOM2; consent verified, 62 MW only from a directory listing
A8: 5 | B8: Maharashtra | C8: AirTrunk (Blackstone) | D8: BOM2, Mahape (5.4 ha) | F8: 120 | G8: C | H8: Corrected | I8: Split out; 120+ MW company figure; moved to under process (no BOM2 permit found)
A9: 6 | B9: Maharashtra | C9: Adani Group | D9: Taloja campus | F9: 240 | G9: C | H9: Verified - company / rating / exchange | I9: 240 MW in CoreWeave release
A10: 7 | B10: Maharashtra | C10: Adani Group | D10: A-GEN-4 TTC Rabale/Ghansoli | G10: A1 | H10: No MW (reference only) | I10: Power captured in CTUIL (Support Properties)
A11: 8 | B11: Maharashtra | C11: Adani Group | D11: ACXPNQ26 / PNQ04, Bhosari, Pune (Microsoft site) | E11: 75.4 | G11: A1 | H11: Verified - primary doc | I11: 75.4 MW connected load in 319th SEIAA minutes (OCR)
A12: 9 | B12: Maharashtra | C12: AWS (Amazon) | D12: Balkum-Majiwada, Thane | E12: 272 | G12: D | H12: Downgraded | I12: CTE + Rs 7,203 cr verified; 272 MW only in a social-media summary of the EC filing
A13: 10 | B13: Maharashtra | C13: AWS (Amazon) | D13: Powai | E13: 77 | G13: A1 | H13: Verified - primary doc | I13: 77,000 kW connected / 75,000 kW demand in 301st SEIAA minutes (OCR)
A14: 11 | B14: Maharashtra | C14: Google | D14: D-31/32 TTC Turbhe | F14: 103.4 | G14: A1 | H14: Verified - primary doc | I14: 1,03,367 kW connected load in Form-1A
A15: 12 | B15: Maharashtra | C15: Google | D15: GEN-2/1/A/1 TTC Turbhe | G15: A1 | H15: No MW (reference only) | I15: CTE verified; no MW disclosed
A16: 13 | B16: Maharashtra | C16: CapitaLand | D16: Digha (DC Navi Mumbai 1) | E16: 135 | G16: A1 | H16: Verified - primary doc | I16: 135 MW connected / 120 MVA in 301st SEIAA minutes (OCR)
A17: 14 | B17: Maharashtra | C17: Iron Mountain | D17: MUM-3, R-50 to R-54 TTC Rabale | E17: 140 | G17: A1 | H17: Verified - primary doc | I17: 140 MW connected / 131 MW demand in 301st SEIAA minutes (OCR)
A18: 15 | B18: Maharashtra | C18: Unidentified (Chandivali) | D18: Saki Vihar-Chandivali, Mumbai | F18: 113.9 | G18: A1 | H18: Verified - primary doc | I18: 113,855 kW connected in 292nd/296th SEIAA minutes (OCR)
A19: 16 | B19: Maharashtra | C19: Digital Edge | D19: BOM campus, Kalwa/Dighe (47 acres) | E19: 350 | G19: C | H19: Corrected | I19: 400 -> 350 MW (company page: 350MW on 47 acres)
A20: 17 | B20: Maharashtra | C20: Sify | D20: Rabale campus | E20: 377 | G20: A1 | H20: Verified - company / rating / exchange | I20: 377+ MW in Sify Integrated Report 2024-25 (link updated in v3 dataset; company page)
A21: 18 | B21: Maharashtra | C21: Yotta (Hiranandani) | D21: NM1 Panvel | E21: 52 | G21: C | H21: Corrected | I21: 250 -> 52 MW (Yotta page); 250 was aggregator-only
A22: 19 | B22: Maharashtra | C22: CtrlS | D22: Mahape DC1-DC7 | E22: 214 | G22: A1 | H22: Verified - company / rating / exchange | I22: DC1&2 40, DC3 10, DC4 36.8, DC5 32 + DC6&7 95 MW on CtrlS homepage
A23: 20 | B23: Maharashtra | C23: STT GDC | D23: TTC Khairane/Mahape | E23: 133 | G23: A1 | H23: Verified - company / rating / exchange | I23: 133MW on STT Mumbai page
A24: 21 | B24: Maharashtra | C24: NTT | D24: NAV1A + NAV2, Airoli/Mahape | E24: 366 | G24: C | H24: Corrected | I24: 530 -> 366 MW IT (was mixing 500 MW facility power with IT)
A25: 22 | B25: Maharashtra | C25: Princeton Digital Group | D25: MU1 Airoli (50 live + 100 expansion) + MU2 (120) | E25: 150 | F25: 120 | G25: C | H25: Corrected | I25: 220 approved -> 150 approved + 120 under process (DCD)
A26: 23 | B26: Maharashtra | C26: Colt DCS - RMZ | D26: Kalwa plots 5 & 5A, Airoli | E26: 148 | G26: C | H26: Corrected | I26: Link fixed: 148 MW is in Oct-2026 article; ICRA says 142 MW
A27: 24 | B27: Maharashtra | C27: L&T | D27: Vyoma EL-200 Mahape | F27: 100 | G27: A1 | H27: Verified - company / rating / exchange | I27: 40 MW of 100 MW campus in L&T release
A28: 25 | B28: Maharashtra | C28: ReNew | D28: MMR green DC park (Panvel/Taloja/Khalapur) | F28: 750 | G28: A2 | H28: Verified - press / reported govt action | I28: 750 MW in Business Standard
A29: 26 | B29: Maharashtra | C29: Trentar (Dorf Ketal) | D29: Location not disclosed | F29: 500 | G29: A2 | H29: Verified - company / rating / exchange | I29: 500 MW in Trentar release
A30: 27 | B30: Maharashtra | C30: Zerra | D30: Navi Mumbai 29 acres | F30: 240 | G30: C | H30: Verified - company / rating / exchange | I30: 240MW on Zerra page
A31: 28 | B31: Maharashtra | C31: MAHAPREIT (state) | D31: State DC project | F31: 200 | G31: A1 | H31: Verified - primary doc | I31: 200 MW in MAHAPREIT EOI
A32: 29 | B32: Maharashtra | C32: ESR | D32: Rabale | F32: 60 | G32: D | H32: Verified - press / reported govt action | I32: 60 MW in CRN Asia
A33: 30 | B33: Maharashtra | C33: TCC Concept / NES Data | D33: Hinjewadi, Pune | E33: 4 | F33: 56 | G33: C | H33: Derived from verified figures | I33: 4 MW op + (60 - 4) under process
A34: 31 | B34: Maharashtra | C34: Avisirah | D34: Navi Mumbai | F34: 5.5 | G34: D | H34: Verified - press / reported govt action | I34: 5.5 MW in PropNewsTime
A35: 32 | B35: Andhra Pradesh | C35: Adani Group | D35: Tarluvada (for Google) | E35: 929 | G35: A2 | H35: Verified - press / reported govt action | I35: 929 MW grid demand quoted from EC (HRF); matches CTUIL 929 MW
A36: 33 | B36: Andhra Pradesh | C36: Adani Group | D36: Rambilli (for Google) | E36: 697 | G36: A2 | H36: Verified - press / reported govt action | I36: 697 MW quoted from EC (HRF); matches CTUIL 697 MW
A37: 34 | B37: Andhra Pradesh | C37: Adani Group | D37: Adavivaram-Mudasarlova (for Google) | E37: 512 | G37: A2 | H37: Verified - press / reported govt action | I37: 512 MW in SEIAA affidavit (ThePrint)
A38: 35 | B38: Andhra Pradesh | C38: ReNew | D38: Makavaripalem, Anakapalli | E38: 1000 | G38: A2 | H38: Verified - press / reported govt action | I38: 1,000 MW quoting GO (MediaNama)
A39: 36 | B39: Andhra Pradesh | C39: Reliance | D39: Bhogapuram / Vizianagaram (854.97 acres) | E39: 1500 | G39: D | H39: Downgraded | I39: Approval verified; 1.5 GW only from registry / derived total
A40: 37 | B40: Andhra Pradesh | C40: Sify | D40: Paradesipalem (53.6 + 25 acres) | E40: 550 | G40: A2 | H40: Corrected | I40: 600 -> 550 MW (GO); dropped 50 MW registry-only site
A41: 38 | B41: Andhra Pradesh | C41: AM Intelligence Labs | D41: Amanam, Bheemunipatnam | E41: 512 | G41: A2 | H41: Verified - press / reported govt action | I41: 512 MW quoting GO (PTI)
A42: 39 | B42: Andhra Pradesh | C42: Colt DCS - RMZ | D42: Jagnadhapuram, Anandapuram | E42: 486 | G42: A2 | H42: Verified - press / reported govt action | I42: 486 MW quoting GO (MediaNama)
A43: 40 | B43: Andhra Pradesh | C43: TCS | D43: Rambilli (~200 acres) | F43: 1000 | G43: D | H43: Excluded | I43: 1 GW in linked article refers to Google, not TCS
A44: 41 | B44: Andhra Pradesh | C44: CtrlS | D44: Rambilli (49.93 acres) | E44: 100 | G44: A2 | H44: Verified - press / reported govt action | I44: 100 MW quoting GO (Deccan Chronicle)
A45: 42 | B45: Andhra Pradesh | C45: Adani Group | D45: Madhurawada (130 acres) | E45: 200 | G45: D | H45: Downgraded | I45: 200 MW from civil-society registry only (tier D)
A46: 43 | B46: Telangana | C46: Fortune | D46: Kandukur mandal (170 acres) | E46: 2000 | G46: C | H46: Verified - press / reported govt action | I46: 2,000 MVA sanction quoted (developer)
A47: 44 | B47: Telangana | C47: TCS | D47: Bharat Future City (264 acres) | F47: 1000 | G47: A2 | H47: Verified - press / reported govt action | I47: 1 GW in ANI (MoU)
A48: 45 | B48: Telangana | C48: AWS / CtrlS (unattributed) | D48: Peddavedu | E48: 278 | G48: A2 | H48: Verified - press / reported govt action | I48: 278 MW quoted from EC documents (Counterview)
A49: 46 | B49: Telangana | C49: Adani Group | D49: Hyderabad | E49: 19.2 | F49: 386.8 | G49: B | H49: Derived from verified figures | I49: 19.2 op + (406 - 19.2) planned, AEL deck
A50: 47 | B50: Telangana | C50: CtrlS | D50: Hyderabad AI cluster | F50: 400 | G50: A2 | H50: Verified - press / reported govt action | I50: 400 MW in state / press releases
A51: 48 | B51: Telangana | C51: NTT Data - Neysa | D51: Hyderabad AI cluster | F51: 400 | G51: A2 | H51: Verified - press / reported govt action | I51: 400 MW in state / press releases
A52: 49 | B52: Telangana | C52: STT GDC | D52: Meerkhanpet | F52: 100 | G52: A2 | H52: Verified - press / reported govt action | I52: 100 MW in Tribune (CMO)
A53: 50 | B53: Telangana | C53: UPC-Volt | D53: Bharat Future City | F53: 100 | G53: A2 | H53: Verified - press / reported govt action | I53: 100 MW in w.media
A54: 51 | B54: Tamil Nadu | C54: CapitaLand | D54: Ambattur (Chennai 01) | E54: 53 | G54: C | H54: Verified - company / rating / exchange | I54: 53 MW gross in CapitaLand release
A55: 52 | B55: Tamil Nadu | C55: Sify | D55: Siruseri (Chennai 02) | E55: 25.9 | F55: 104.1 | G55: B | H55: Corrected | I55: Link fixed to Sify IR (130+ MW); 25.92 MW built verified
A56: 53 | B56: Tamil Nadu | C56: Digital Connexion (Reliance-Brookfield-DLR) | D56: Ambattur | E56: 100 | G56: D | H56: Verified - press / reported govt action | I56: 100 MW in ThePrint photo caption
A57: 54 | B57: Tamil Nadu | C57: STT GDC | D57: Siruseri (Chennai 7) | E57: 7.2 | F57: 37.8 | G57: C | H57: Corrected | I57: Link fixed (old link was a Sify tracker page)
A58: 55 | B58: Tamil Nadu | C58: Techno Digital | D58: Siruseri TD-1 | E58: 36 | G58: C | H58: Verified - press / reported govt action | I58: 36MW in DCD
A59: 56 | B59: Tamil Nadu | C59: Adani Group | D59: Chennai | E59: 17 | F59: 16 | G59: B | H59: Derived from verified figures | I59: 17 op of 33 MW, AEL deck
A60: 57 | B60: Tamil Nadu | C60: Multiple (TANTRANSCO Ambattur requests) | D60: Ambattur Industrial Estate | F60: 1380 | G60: A2 | H60: Verified - press / reported govt action | I60: 1,036 + 344 MVA quoted (excluded from charts - aggregate)
A61: 58 | B61: Uttar Pradesh | C61: Hiranandani (Yotta) | D61: Greater Noida | E61: 28 | F61: 222 | G61: A1 | H61: Derived from verified figures | I61: 28 commercialised of 250 MW, UPLC dashboard
A62: 59 | B62: Uttar Pradesh | C62: Adani Group | D62: Noida | E62: 35 | F62: 65 | G62: A1 | H62: Derived from verified figures | I62: UPLC dashboard commercialised / proposed MW
A63: 60 | B63: Uttar Pradesh | C63: SKVR | D63: UP | E63: 16 | F63: 104 | G63: A1 | H63: Derived from verified figures | I63: 16 commercialised of 120 MW, UPLC dashboard
A64: 61 | B64: Uttar Pradesh | C64: STT GDC | D64: Noida | E64: 40 | G64: A1 | H64: Derived from verified figures | I64: UPLC dashboard commercialised / proposed MW
A65: 62 | B65: Uttar Pradesh | C65: NTT | D65: Noida | E65: 9 | F65: 43.8 | G65: A1 | H65: Derived from verified figures | I65: UPLC dashboard commercialised / proposed MW
A66: 63 | B66: Uttar Pradesh | C66: Iron Mountain | D66: Noida | E66: 5 | G66: A1 | H66: Derived from verified figures | I66: UPLC dashboard commercialised / proposed MW
A67: 64 | B67: Odisha | C67: Adani Group | D67: Naraj (~250 acres) | E67: 1000 | G67: A2 | H67: Verified - press / reported govt action | I67: 1 GW in BW Businessworld (HLCA)
A68: 65 | B68: Odisha | C68: Sentraforge AI | D68: Puri | E68: 120 | G68: A2 | H68: Corrected | I68: Link fixed to Business Today (old link was an HCLTech article)
A69: 66 | B69: Karnataka | C69: Govt of Karnataka (park) | D69: Hoskote | F69: 500 | G69: A2 | H69: Verified - press / reported govt action | I69: 500 MW in w.media
A70: 67 | B70: Gujarat | C70: Reliance | D70: Jamnagar AI DC | F70: 168 | G70: C | H70: Verified - company / rating / exchange | I70: 168 MW in RIL release (pv-magazine link)
A71: 68 | B71: Haryana | C71: Anant Raj | D71: Manesar, Panchkula, Rai | E71: 28 | F71: 279 | G71: B | H71: Verified - press / reported govt action | I71: 28 MW platform / 307 MW target in Value Research; note only 8 MW handed over
A72: 69 | B72: West Bengal | C72: Hiranandani (Yotta) | D72: Uttarpara, Kolkata | F72: 250 | G72: D | H72: Verified - press / reported govt action | I72: 250MW in DCD (2021 - status uncertain)
A73: 70 | B73: West Bengal | C73: NTT | D73: New Town, Kolkata | F73: 25 | G73: C | H73: Corrected | I73: 40 -> 25 MW (NTT page)
A75: Summary
B76: Corrected | C76: =COUNTIF($H$5:$H$73,B76) -> 11
B77: Excluded | C77: =COUNTIF($H$5:$H$73,B77) -> 1
B78: Downgraded | C78: =COUNTIF($H$5:$H$73,B78) -> 4
B79: Verified - primary doc | C79: =COUNTIF($H$5:$H$73,B79) -> 8
B80: Verified - company / rating / exchange | C80: =COUNTIF($H$5:$H$73,B80) -> 9
B81: Verified - press / reported govt action | C81: =COUNTIF($H$5:$H$73,B81) -> 25
B82: Derived from verified figures | C82: =COUNTIF($H$5:$H$73,B82) -> 9
B83: No MW (reference only) | C83: =COUNTIF($H$5:$H$73,B83) -> 2

Sheet Maharashtra
A1: Maharashtra - data-centre power by company group (MW), state-level sources
A2: Approved = government permission granted or operating; Under process = application / MoU / LoI / announced. MW basis varies by row - see Backup_All_States column G.
A4: A. All state-level data
A5: Company / group | B5: Under process | C5: Approved | D5: Total
A6: AirTrunk (Blackstone) | B6: =SUMIFS(Backup_All_States!$F$2:$F$70,Backup_All_States!$A$2:$A$70,"Maharashtra",Backup_All_States!$B$2:$B$70,$A6,Backup_All_States!$L$2:$L$70,"Y") -> 3120 | C6: =SUMIFS(Backup_All_States!$E$2:$E$70,Backup_All_States!$A$2:$A$70,"Maharashtra",Backup_All_States!$B$2:$B$70,$A6,Backup_All_States!$L$2:$L$70,"Y") -> 62 | D6: =B6+C6 -> 3182
A7: Lodha Group (park; tenants AWS, STT) | B7: =SUMIFS(Backup_All_States!$F$2:$F$70,Backup_All_States!$A$2:$A$70,"Maharashtra",Backup_All_States!$B$2:$B$70,$A7,Backup_All_States!$L$2:$L$70,"Y") -> 1500 | C7: =SUMIFS(Backup_All_States!$E$2:$E$70,Backup_All_States!$A$2:$A$70,"Maharashtra",Backup_All_States!$B$2:$B$70,$A7,Backup_All_States!$L$2:$L$70,"Y") -> 1450 | D7: =B7+C7 -> 2950
A8: ReNew | B8: =SUMIFS(Backup_All_States!$F$2:$F$70,Backup_All_States!$A$2:$A$70,"Maharashtra",Backup_All_States!$B$2:$B$70,$A8,Backup_All_States!$L$2:$L$70,"Y") -> 750 | C8: =SUMIFS(Backup_All_States!$E$2:$E$70,Backup_All_States!$A$2:$A$70,"Maharashtra",Backup_All_States!$B$2:$B$70,$A8,Backup_All_States!$L$2:$L$70,"Y") -> 0 | D8: =B8+C8 -> 750
A9: Trentar (Dorf Ketal) | B9: =SUMIFS(Backup_All_States!$F$2:$F$70,Backup_All_States!$A$2:$A$70,"Maharashtra",Backup_All_States!$B$2:$B$70,$A9,Backup_All_States!$L$2:$L$70,"Y") -> 500 | C9: =SUMIFS(Backup_All_States!$E$2:$E$70,Backup_All_States!$A$2:$A$70,"Maharashtra",Backup_All_States!$B$2:$B$70,$A9,Backup_All_States!$L$2:$L$70,"Y") -> 0 | D9: =B9+C9 -> 500
A10: Sify | B10: =SUMIFS(Backup_All_States!$F$2:$F$70,Backup_All_States!$A$2:$A$70,"Maharashtra",Backup_All_States!$B$2:$B$70,$A10,Backup_All_States!$L$2:$L$70,"Y") -> 0 | C10: =SUMIFS(Backup_All_States!$E$2:$E$70,Backup_All_States!$A$2:$A$70,"Maharashtra",Backup_All_States!$B$2:$B$70,$A10,Backup_All_States!$L$2:$L$70,"Y") -> 377 | D10: =B10+C10 -> 377
A11: NTT | B11: =SUMIFS(Backup_All_States!$F$2:$F$70,Backup_All_States!$A$2:$A$70,"Maharashtra",Backup_All_States!$B$2:$B$70,$A11,Backup_All_States!$L$2:$L$70,"Y") -> 0 | C11: =SUMIFS(Backup_All_States!$E$2:$E$70,Backup_All_States!$A$2:$A$70,"Maharashtra",Backup_All_States!$B$2:$B$70,$A11,Backup_All_States!$L$2:$L$70,"Y") -> 366 | D11: =B11+C11 -> 366
A12: Digital Edge | B12: =SUMIFS(Backup_All_States!$F$2:$F$70,Backup_All_States!$A$2:$A$70,"Maharashtra",Backup_All_States!$B$2:$B$70,$A12,Backup_All_States!$L$2:$L$70,"Y") -> 0 | C12: =SUMIFS(Backup_All_States!$E$2:$E$70,Backup_All_States!$A$2:$A$70,"Maharashtra",Backup_All_States!$B$2:$B$70,$A12,Backup_All_States!$L$2:$L$70,"Y") -> 350 | D12: =B12+C12 -> 350
A13: AWS (Amazon) | B13: =SUMIFS(Backup_All_States!$F$2:$F$70,Backup_All_States!$A$2:$A$70,"Maharashtra",Backup_All_States!$B$2:$B$70,$A13,Backup_All_States!$L$2:$L$70,"Y") -> 0 | C13: =SUMIFS(Backup_All_States!$E$2:$E$70,Backup_All_States!$A$2:$A$70,"Maharashtra",Backup_All_States!$B$2:$B$70,$A13,Backup_All_States!$L$2:$L$70,"Y") -> 349 | D13: =B13+C13 -> 349
A14: Adani Group | B14: =SUMIFS(Backup_All_States!$F$2:$F$70,Backup_All_States!$A$2:$A$70,"Maharashtra",Backup_All_States!$B$2:$B$70,$A14,Backup_All_States!$L$2:$L$70,"Y") -> 240 | C14: =SUMIFS(Backup_All_States!$E$2:$E$70,Backup_All_States!$A$2:$A$70,"Maharashtra",Backup_All_States!$B$2:$B$70,$A14,Backup_All_States!$L$2:$L$70,"Y") -> 75.4 | D14: =B14+C14 -> 315.4
A15: Princeton Digital Group | B15: =SUMIFS(Backup_All_States!$F$2:$F$70,Backup_All_States!$A$2:$A$70,"Maharashtra",Backup_All_States!$B$2:$B$70,$A15,Backup_All_States!$L$2:$L$70,"Y") -> 120 | C15: =SUMIFS(Backup_All_States!$E$2:$E$70,Backup_All_States!$A$2:$A$70,"Maharashtra",Backup_All_States!$B$2:$B$70,$A15,Backup_All_States!$L$2:$L$70,"Y") -> 150 | D15: =B15+C15 -> 270
A16: Zerra | B16: =SUMIFS(Backup_All_States!$F$2:$F$70,Backup_All_States!$A$2:$A$70,"Maharashtra",Backup_All_States!$B$2:$B$70,$A16,Backup_All_States!$L$2:$L$70,"Y") -> 240 | C16: =SUMIFS(Backup_All_States!$E$2:$E$70,Backup_All_States!$A$2:$A$70,"Maharashtra",Backup_All_States!$B$2:$B$70,$A16,Backup_All_States!$L$2:$L$70,"Y") -> 0 | D16: =B16+C16 -> 240
A17: CtrlS | B17: =SUMIFS(Backup_All_States!$F$2:$F$70,Backup_All_States!$A$2:$A$70,"Maharashtra",Backup_All_States!$B$2:$B$70,$A17,Backup_All_States!$L$2:$L$70,"Y") -> 0 | C17: =SUMIFS(Backup_All_States!$E$2:$E$70,Backup_All_States!$A$2:$A$70,"Maharashtra",Backup_All_States!$B$2:$B$70,$A17,Backup_All_States!$L$2:$L$70,"Y") -> 214 | D17: =B17+C17 -> 214
... A29: Avisirah | B29: =SUMIFS(Backup_All_States!$F$2:$F$70,Backup_All_States!$A$2:$A$70,"Maharashtra",Backup_All_States!$B$2:$B$70,$A29,Backup_All_States!$L$2:$L$70,"Y") -> 5.5 | C29: =SUMIFS(Backup_All_States!$E$2:$E$70,Backup_All_States!$A$2:$A$70,"Maharashtra",Backup_All_States!$B$2:$B$70,$A29,Backup_All_States!$L$2:$L$70,"Y") -> 0 | D29: =B29+C29 -> 5.5
A30: Total | B30: =SUM(B6:B29) -> 7108.8 | C30: =SUM(C6:C29) -> 4005.4 | D30: =SUM(D6:D29) -> 11114.2
A33: B. Excluding rows that overlap CTUIL (use this to ADD to the CTUIL chart)
A34: Company / group | B34: Under process | C34: Approved | D34: Total
A35: AirTrunk (Blackstone) | B35: =SUMIFS(Backup_All_States!$F$2:$F$70,Backup_All_States!$A$2:$A$70,"Maharashtra",Backup_All_States!$B$2:$B$70,$A35,Backup_All_States!$L$2:$L$70,"Y",Backup_All_States!$J$2:$J$70,"No") -> 3120 | C35: =SUMIFS(Backup_All_States!$E$2:$E$70,Backup_All_States!$A$2:$A$70,"Maharashtra",Backup_All_States!$B$2:$B$70,$A35,Backup_All_States!$L$2:$L$70,"Y",Backup_All_States!$J$2:$J$70,"No") -> 62 | D35: =B35+C35 -> 3182
A36: Lodha Group (park; tenants AWS, STT) | B36: =SUMIFS(Backup_All_States!$F$2:$F$70,Backup_All_States!$A$2:$A$70,"Maharashtra",Backup_All_States!$B$2:$B$70,$A36,Backup_All_States!$L$2:$L$70,"Y",Backup_All_States!$J$2:$J$70,"No") -> 1500 | C36: =SUMIFS(Backup_All_States!$E$2:$E$70,Backup_All_States!$A$2:$A$70,"Maharashtra",Backup_All_States!$B$2:$B$70,$A36,Backup_All_States!$L$2:$L$70,"Y",Backup_All_States!$J$2:$J$70,"No") -> 1450 | D36: =B36+C36 -> 2950
A37: ReNew | B37: =SUMIFS(Backup_All_States!$F$2:$F$70,Backup_All_States!$A$2:$A$70,"Maharashtra",Backup_All_States!$B$2:$B$70,$A37,Backup_All_States!$L$2:$L$70,"Y",Backup_All_States!$J$2:$J$70,"No") -> 750 | C37: =SUMIFS(Backup_All_States!$E$2:$E$70,Backup_All_States!$A$2:$A$70,"Maharashtra",Backup_All_States!$B$2:$B$70,$A37,Backup_All_States!$L$2:$L$70,"Y",Backup_All_States!$J$2:$J$70,"No") -> 0 | D37: =B37+C37 -> 750
A38: Trentar (Dorf Ketal) | B38: =SUMIFS(Backup_All_States!$F$2:$F$70,Backup_All_States!$A$2:$A$70,"Maharashtra",Backup_All_States!$B$2:$B$70,$A38,Backup_All_States!$L$2:$L$70,"Y",Backup_All_States!$J$2:$J$70,"No") -> 500 | C38: =SUMIFS(Backup_All_States!$E$2:$E$70,Backup_All_States!$A$2:$A$70,"Maharashtra",Backup_All_States!$B$2:$B$70,$A38,Backup_All_States!$L$2:$L$70,"Y",Backup_All_States!$J$2:$J$70,"No") -> 0 | D38: =B38+C38 -> 500
A39: Sify | B39: =SUMIFS(Backup_All_States!$F$2:$F$70,Backup_All_States!$A$2:$A$70,"Maharashtra",Backup_All_States!$B$2:$B$70,$A39,Backup_All_States!$L$2:$L$70,"Y",Backup_All_States!$J$2:$J$70,"No") -> 0 | C39: =SUMIFS(Backup_All_States!$E$2:$E$70,Backup_All_States!$A$2:$A$70,"Maharashtra",Backup_All_States!$B$2:$B$70,$A39,Backup_All_States!$L$2:$L$70,"Y",Backup_All_States!$J$2:$J$70,"No") -> 377 | D39: =B39+C39 -> 377
A40: NTT | B40: =SUMIFS(Backup_All_States!$F$2:$F$70,Backup_All_States!$A$2:$A$70,"Maharashtra",Backup_All_States!$B$2:$B$70,$A40,Backup_All_States!$L$2:$L$70,"Y",Backup_All_States!$J$2:$J$70,"No") -> 0 | C40: =SUMIFS(Backup_All_States!$E$2:$E$70,Backup_All_States!$A$2:$A$70,"Maharashtra",Backup_All_States!$B$2:$B$70,$A40,Backup_All_States!$L$2:$L$70,"Y",Backup_All_States!$J$2:$J$70,"No") -> 366 | D40: =B40+C40 -> 366
A41: Digital Edge | B41: =SUMIFS(Backup_All_States!$F$2:$F$70,Backup_All_States!$A$2:$A$70,"Maharashtra",Backup_All_States!$B$2:$B$70,$A41,Backup_All_States!$L$2:$L$70,"Y",Backup_All_States!$J$2:$J$70,"No") -> 0 | C41: =SUMIFS(Backup_All_States!$E$2:$E$70,Backup_All_States!$A$2:$A$70,"Maharashtra",Backup_All_States!$B$2:$B$70,$A41,Backup_All_States!$L$2:$L$70,"Y",Backup_All_States!$J$2:$J$70,"No") -> 350 | D41: =B41+C41 -> 350
A42: AWS (Amazon) | B42: =SUMIFS(Backup_All_States!$F$2:$F$70,Backup_All_States!$A$2:$A$70,"Maharashtra",Backup_All_States!$B$2:$B$70,$A42,Backup_All_States!$L$2:$L$70,"Y",Backup_All_States!$J$2:$J$70,"No") -> 0 | C42: =SUMIFS(Backup_All_States!$E$2:$E$70,Backup_All_States!$A$2:$A$70,"Maharashtra",Backup_All_States!$B$2:$B$70,$A42,Backup_All_States!$L$2:$L$70,"Y",Backup_All_States!$J$2:$J$70,"No") -> 349 | D42: =B42+C42 -> 349
A43: Adani Group | B43: =SUMIFS(Backup_All_States!$F$2:$F$70,Backup_All_States!$A$2:$A$70,"Maharashtra",Backup_All_States!$B$2:$B$70,$A43,Backup_All_States!$L$2:$L$70,"Y",Backup_All_States!$J$2:$J$70,"No") -> 0 | C43: =SUMIFS(Backup_All_States!$E$2:$E$70,Backup_All_States!$A$2:$A$70,"Maharashtra",Backup_All_States!$B$2:$B$70,$A43,Backup_All_States!$L$2:$L$70,"Y",Backup_All_States!$J$2:$J$70,"No") -> 75.4 | D43: =B43+C43 -> 75.4
A44: Princeton Digital Group | B44: =SUMIFS(Backup_All_States!$F$2:$F$70,Backup_All_States!$A$2:$A$70,"Maharashtra",Backup_All_States!$B$2:$B$70,$A44,Backup_All_States!$L$2:$L$70,"Y",Backup_All_States!$J$2:$J$70,"No") -> 120 | C44: =SUMIFS(Backup_All_States!$E$2:$E$70,Backup_All_States!$A$2:$A$70,"Maharashtra",Backup_All_States!$B$2:$B$70,$A44,Backup_All_States!$L$2:$L$70,"Y",Backup_All_States!$J$2:$J$70,"No") -> 150 | D44: =B44+C44 -> 270
A45: Zerra | B45: =SUMIFS(Backup_All_States!$F$2:$F$70,Backup_All_States!$A$2:$A$70,"Maharashtra",Backup_All_States!$B$2:$B$70,$A45,Backup_All_States!$L$2:$L$70,"Y",Backup_All_States!$J$2:$J$70,"No") -> 240 | C45: =SUMIFS(Backup_All_States!$E$2:$E$70,Backup_All_States!$A$2:$A$70,"Maharashtra",Backup_All_States!$B$2:$B$70,$A45,Backup_All_States!$L$2:$L$70,"Y",Backup_All_States!$J$2:$J$70,"No") -> 0 | D45: =B45+C45 -> 240
A46: CtrlS | B46: =SUMIFS(Backup_All_States!$F$2:$F$70,Backup_All_States!$A$2:$A$70,"Maharashtra",Backup_All_States!$B$2:$B$70,$A46,Backup_All_States!$L$2:$L$70,"Y",Backup_All_States!$J$2:$J$70,"No") -> 0 | C46: =SUMIFS(Backup_All_States!$E$2:$E$70,Backup_All_States!$A$2:$A$70,"Maharashtra",Backup_All_States!$B$2:$B$70,$A46,Backup_All_States!$L$2:$L$70,"Y",Backup_All_States!$J$2:$J$70,"No") -> 214 | D46: =B46+C46 -> 214
... A58: Avisirah | B58: =SUMIFS(Backup_All_States!$F$2:$F$70,Backup_All_States!$A$2:$A$70,"Maharashtra",Backup_All_States!$B$2:$B$70,$A58,Backup_All_States!$L$2:$L$70,"Y",Backup_All_States!$J$2:$J$70,"No") -> 5.5 | C58: =SUMIFS(Backup_All_States!$E$2:$E$70,Backup_All_States!$A$2:$A$70,"Maharashtra",Backup_All_States!$B$2:$B$70,$A58,Backup_All_States!$L$2:$L$70,"Y",Backup_All_States!$J$2:$J$70,"No") -> 0 | D58: =B58+C58 -> 5.5
A59: Total | B59: =SUM(B35:B58) -> 6868.8 | C59: =SUM(C35:C58) -> 4005.4 | D59: =SUM(D35:D58) -> 10874.2

Sheet Andhra Pradesh
A1: Andhra Pradesh - data-centre power by company group (MW), state-level sources
A2: Approved = government permission granted or operating; Under process = application / MoU / LoI / announced. MW basis varies by row - see Backup_All_States column G.
A4: A. All state-level data
A5: Company / group | B5: Under process | C5: Approved | D5: Total
A6: Adani Group | B6: =SUMIFS(Backup_All_States!$F$2:$F$70,Backup_All_States!$A$2:$A$70,"Andhra Pradesh",Backup_All_States!$B$2:$B$70,$A6,Backup_All_States!$L$2:$L$70,"Y") -> 0 | C6: =SUMIFS(Backup_All_States!$E$2:$E$70,Backup_All_States!$A$2:$A$70,"Andhra Pradesh",Backup_All_States!$B$2:$B$70,$A6,Backup_All_States!$L$2:$L$70,"Y") -> 2338 | D6: =B6+C6 -> 2338
A7: Reliance | B7: =SUMIFS(Backup_All_States!$F$2:$F$70,Backup_All_States!$A$2:$A$70,"Andhra Pradesh",Backup_All_States!$B$2:$B$70,$A7,Backup_All_States!$L$2:$L$70,"Y") -> 0 | C7: =SUMIFS(Backup_All_States!$E$2:$E$70,Backup_All_States!$A$2:$A$70,"Andhra Pradesh",Backup_All_States!$B$2:$B$70,$A7,Backup_All_States!$L$2:$L$70,"Y") -> 1500 | D7: =B7+C7 -> 1500
A8: ReNew | B8: =SUMIFS(Backup_All_States!$F$2:$F$70,Backup_All_States!$A$2:$A$70,"Andhra Pradesh",Backup_All_States!$B$2:$B$70,$A8,Backup_All_States!$L$2:$L$70,"Y") -> 0 | C8: =SUMIFS(Backup_All_States!$E$2:$E$70,Backup_All_States!$A$2:$A$70,"Andhra Pradesh",Backup_All_States!$B$2:$B$70,$A8,Backup_All_States!$L$2:$L$70,"Y") -> 1000 | D8: =B8+C8 -> 1000
A9: Sify | B9: =SUMIFS(Backup_All_States!$F$2:$F$70,Backup_All_States!$A$2:$A$70,"Andhra Pradesh",Backup_All_States!$B$2:$B$70,$A9,Backup_All_States!$L$2:$L$70,"Y") -> 0 | C9: =SUMIFS(Backup_All_States!$E$2:$E$70,Backup_All_States!$A$2:$A$70,"Andhra Pradesh",Backup_All_States!$B$2:$B$70,$A9,Backup_All_States!$L$2:$L$70,"Y") -> 550 | D9: =B9+C9 -> 550
A10: AM Intelligence Labs | B10: =SUMIFS(Backup_All_States!$F$2:$F$70,Backup_All_States!$A$2:$A$70,"Andhra Pradesh",Backup_All_States!$B$2:$B$70,$A10,Backup_All_States!$L$2:$L$70,"Y") -> 0 | C10: =SUMIFS(Backup_All_States!$E$2:$E$70,Backup_All_States!$A$2:$A$70,"Andhra Pradesh",Backup_All_States!$B$2:$B$70,$A10,Backup_All_States!$L$2:$L$70,"Y") -> 512 | D10: =B10+C10 -> 512
A11: Colt DCS - RMZ | B11: =SUMIFS(Backup_All_States!$F$2:$F$70,Backup_All_States!$A$2:$A$70,"Andhra Pradesh",Backup_All_States!$B$2:$B$70,$A11,Backup_All_States!$L$2:$L$70,"Y") -> 0 | C11: =SUMIFS(Backup_All_States!$E$2:$E$70,Backup_All_States!$A$2:$A$70,"Andhra Pradesh",Backup_All_States!$B$2:$B$70,$A11,Backup_All_States!$L$2:$L$70,"Y") -> 486 | D11: =B11+C11 -> 486
A12: CtrlS | B12: =SUMIFS(Backup_All_States!$F$2:$F$70,Backup_All_States!$A$2:$A$70,"Andhra Pradesh",Backup_All_States!$B$2:$B$70,$A12,Backup_All_States!$L$2:$L$70,"Y") -> 0 | C12: =SUMIFS(Backup_All_States!$E$2:$E$70,Backup_All_States!$A$2:$A$70,"Andhra Pradesh",Backup_All_States!$B$2:$B$70,$A12,Backup_All_States!$L$2:$L$70,"Y") -> 100 | D12: =B12+C12 -> 100
A13: Total | B13: =SUM(B6:B12) -> 0 | C13: =SUM(C6:C12) -> 6486 | D13: =SUM(D6:D12) -> 6486
A16: B. Excluding rows that overlap CTUIL (use this to ADD to the CTUIL chart)
A17: Company / group | B17: Under process | C17: Approved | D17: Total
A18: Adani Group | B18: =SUMIFS(Backup_All_States!$F$2:$F$70,Backup_All_States!$A$2:$A$70,"Andhra Pradesh",Backup_All_States!$B$2:$B$70,$A18,Backup_All_States!$L$2:$L$70,"Y",Backup_All_States!$J$2:$J$70,"No") -> 0 | C18: =SUMIFS(Backup_All_States!$E$2:$E$70,Backup_All_States!$A$2:$A$70,"Andhra Pradesh",Backup_All_States!$B$2:$B$70,$A18,Backup_All_States!$L$2:$L$70,"Y",Backup_All_States!$J$2:$J$70,"No") -> 200 | D18: =B18+C18 -> 200
A19: Reliance | B19: =SUMIFS(Backup_All_States!$F$2:$F$70,Backup_All_States!$A$2:$A$70,"Andhra Pradesh",Backup_All_States!$B$2:$B$70,$A19,Backup_All_States!$L$2:$L$70,"Y",Backup_All_States!$J$2:$J$70,"No") -> 0 | C19: =SUMIFS(Backup_All_States!$E$2:$E$70,Backup_All_States!$A$2:$A$70,"Andhra Pradesh",Backup_All_States!$B$2:$B$70,$A19,Backup_All_States!$L$2:$L$70,"Y",Backup_All_States!$J$2:$J$70,"No") -> 1500 | D19: =B19+C19 -> 1500
A20: ReNew | B20: =SUMIFS(Backup_All_States!$F$2:$F$70,Backup_All_States!$A$2:$A$70,"Andhra Pradesh",Backup_All_States!$B$2:$B$70,$A20,Backup_All_States!$L$2:$L$70,"Y",Backup_All_States!$J$2:$J$70,"No") -> 0 | C20: =SUMIFS(Backup_All_States!$E$2:$E$70,Backup_All_States!$A$2:$A$70,"Andhra Pradesh",Backup_All_States!$B$2:$B$70,$A20,Backup_All_States!$L$2:$L$70,"Y",Backup_All_States!$J$2:$J$70,"No") -> 1000 | D20: =B20+C20 -> 1000
A21: Sify | B21: =SUMIFS(Backup_All_States!$F$2:$F$70,Backup_All_States!$A$2:$A$70,"Andhra Pradesh",Backup_All_States!$B$2:$B$70,$A21,Backup_All_States!$L$2:$L$70,"Y",Backup_All_States!$J$2:$J$70,"No") -> 0 | C21: =SUMIFS(Backup_All_States!$E$2:$E$70,Backup_All_States!$A$2:$A$70,"Andhra Pradesh",Backup_All_States!$B$2:$B$70,$A21,Backup_All_States!$L$2:$L$70,"Y",Backup_All_States!$J$2:$J$70,"No") -> 550 | D21: =B21+C21 -> 550
A22: AM Intelligence Labs | B22: =SUMIFS(Backup_All_States!$F$2:$F$70,Backup_All_States!$A$2:$A$70,"Andhra Pradesh",Backup_All_States!$B$2:$B$70,$A22,Backup_All_States!$L$2:$L$70,"Y",Backup_All_States!$J$2:$J$70,"No") -> 0 | C22: =SUMIFS(Backup_All_States!$E$2:$E$70,Backup_All_States!$A$2:$A$70,"Andhra Pradesh",Backup_All_States!$B$2:$B$70,$A22,Backup_All_States!$L$2:$L$70,"Y",Backup_All_States!$J$2:$J$70,"No") -> 512 | D22: =B22+C22 -> 512
A23: Colt DCS - RMZ | B23: =SUMIFS(Backup_All_States!$F$2:$F$70,Backup_All_States!$A$2:$A$70,"Andhra Pradesh",Backup_All_States!$B$2:$B$70,$A23,Backup_All_States!$L$2:$L$70,"Y",Backup_All_States!$J$2:$J$70,"No") -> 0 | C23: =SUMIFS(Backup_All_States!$E$2:$E$70,Backup_All_States!$A$2:$A$70,"Andhra Pradesh",Backup_All_States!$B$2:$B$70,$A23,Backup_All_States!$L$2:$L$70,"Y",Backup_All_States!$J$2:$J$70,"No") -> 486 | D23: =B23+C23 -> 486
A24: CtrlS | B24: =SUMIFS(Backup_All_States!$F$2:$F$70,Backup_All_States!$A$2:$A$70,"Andhra Pradesh",Backup_All_States!$B$2:$B$70,$A24,Backup_All_States!$L$2:$L$70,"Y",Backup_All_States!$J$2:$J$70,"No") -> 0 | C24: =SUMIFS(Backup_All_States!$E$2:$E$70,Backup_All_States!$A$2:$A$70,"Andhra Pradesh",Backup_All_States!$B$2:$B$70,$A24,Backup_All_States!$L$2:$L$70,"Y",Backup_All_States!$J$2:$J$70,"No") -> 100 | D24: =B24+C24 -> 100
A25: Total | B25: =SUM(B18:B24) -> 0 | C25: =SUM(C18:C24) -> 4348 | D25: =SUM(D18:D24) -> 4348

Sheet Telangana
A1: Telangana - data-centre power by company group (MW), state-level sources
A2: Approved = government permission granted or operating; Under process = application / MoU / LoI / announced. MW basis varies by row - see Backup_All_States column G.
A4: A. All state-level data
A5: Company / group | B5: Under process | C5: Approved | D5: Total
A6: Fortune | B6: =SUMIFS(Backup_All_States!$F$2:$F$70,Backup_All_States!$A$2:$A$70,"Telangana",Backup_All_States!$B$2:$B$70,$A6,Backup_All_States!$L$2:$L$70,"Y") -> 0 | C6: =SUMIFS(Backup_All_States!$E$2:$E$70,Backup_All_States!$A$2:$A$70,"Telangana",Backup_All_States!$B$2:$B$70,$A6,Backup_All_States!$L$2:$L$70,"Y") -> 2000 | D6: =B6+C6 -> 2000
A7: TCS | B7: =SUMIFS(Backup_All_States!$F$2:$F$70,Backup_All_States!$A$2:$A$70,"Telangana",Backup_All_States!$B$2:$B$70,$A7,Backup_All_States!$L$2:$L$70,"Y") -> 1000 | C7: =SUMIFS(Backup_All_States!$E$2:$E$70,Backup_All_States!$A$2:$A$70,"Telangana",Backup_All_States!$B$2:$B$70,$A7,Backup_All_States!$L$2:$L$70,"Y") -> 0 | D7: =B7+C7 -> 1000
A8: Adani Group | B8: =SUMIFS(Backup_All_States!$F$2:$F$70,Backup_All_States!$A$2:$A$70,"Telangana",Backup_All_States!$B$2:$B$70,$A8,Backup_All_States!$L$2:$L$70,"Y") -> 386.8 | C8: =SUMIFS(Backup_All_States!$E$2:$E$70,Backup_All_States!$A$2:$A$70,"Telangana",Backup_All_States!$B$2:$B$70,$A8,Backup_All_States!$L$2:$L$70,"Y") -> 19.2 | D8: =B8+C8 -> 406
A9: CtrlS | B9: =SUMIFS(Backup_All_States!$F$2:$F$70,Backup_All_States!$A$2:$A$70,"Telangana",Backup_All_States!$B$2:$B$70,$A9,Backup_All_States!$L$2:$L$70,"Y") -> 400 | C9: =SUMIFS(Backup_All_States!$E$2:$E$70,Backup_All_States!$A$2:$A$70,"Telangana",Backup_All_States!$B$2:$B$70,$A9,Backup_All_States!$L$2:$L$70,"Y") -> 0 | D9: =B9+C9 -> 400
A10: NTT Data - Neysa | B10: =SUMIFS(Backup_All_States!$F$2:$F$70,Backup_All_States!$A$2:$A$70,"Telangana",Backup_All_States!$B$2:$B$70,$A10,Backup_All_States!$L$2:$L$70,"Y") -> 400 | C10: =SUMIFS(Backup_All_States!$E$2:$E$70,Backup_All_States!$A$2:$A$70,"Telangana",Backup_All_States!$B$2:$B$70,$A10,Backup_All_States!$L$2:$L$70,"Y") -> 0 | D10: =B10+C10 -> 400
A11: AWS / CtrlS (unattributed) | B11: =SUMIFS(Backup_All_States!$F$2:$F$70,Backup_All_States!$A$2:$A$70,"Telangana",Backup_All_States!$B$2:$B$70,$A11,Backup_All_States!$L$2:$L$70,"Y") -> 0 | C11: =SUMIFS(Backup_All_States!$E$2:$E$70,Backup_All_States!$A$2:$A$70,"Telangana",Backup_All_States!$B$2:$B$70,$A11,Backup_All_States!$L$2:$L$70,"Y") -> 278 | D11: =B11+C11 -> 278
A12: STT GDC | B12: =SUMIFS(Backup_All_States!$F$2:$F$70,Backup_All_States!$A$2:$A$70,"Telangana",Backup_All_States!$B$2:$B$70,$A12,Backup_All_States!$L$2:$L$70,"Y") -> 100 | C12: =SUMIFS(Backup_All_States!$E$2:$E$70,Backup_All_States!$A$2:$A$70,"Telangana",Backup_All_States!$B$2:$B$70,$A12,Backup_All_States!$L$2:$L$70,"Y") -> 0 | D12: =B12+C12 -> 100
A13: UPC-Volt | B13: =SUMIFS(Backup_All_States!$F$2:$F$70,Backup_All_States!$A$2:$A$70,"Telangana",Backup_All_States!$B$2:$B$70,$A13,Backup_All_States!$L$2:$L$70,"Y") -> 100 | C13: =SUMIFS(Backup_All_States!$E$2:$E$70,Backup_All_States!$A$2:$A$70,"Telangana",Backup_All_States!$B$2:$B$70,$A13,Backup_All_States!$L$2:$L$70,"Y") -> 0 | D13: =B13+C13 -> 100
A14: Total | B14: =SUM(B6:B13) -> 2386.8 | C14: =SUM(C6:C13) -> 2297.2 | D14: =SUM(D6:D13) -> 4684
A17: B. Excluding rows that overlap CTUIL (use this to ADD to the CTUIL chart)
A18: Company / group | B18: Under process | C18: Approved | D18: Total
A19: Fortune | B19: =SUMIFS(Backup_All_States!$F$2:$F$70,Backup_All_States!$A$2:$A$70,"Telangana",Backup_All_States!$B$2:$B$70,$A19,Backup_All_States!$L$2:$L$70,"Y",Backup_All_States!$J$2:$J$70,"No") -> 0 | C19: =SUMIFS(Backup_All_States!$E$2:$E$70,Backup_All_States!$A$2:$A$70,"Telangana",Backup_All_States!$B$2:$B$70,$A19,Backup_All_States!$L$2:$L$70,"Y",Backup_All_States!$J$2:$J$70,"No") -> 2000 | D19: =B19+C19 -> 2000
A20: TCS | B20: =SUMIFS(Backup_All_States!$F$2:$F$70,Backup_All_States!$A$2:$A$70,"Telangana",Backup_All_States!$B$2:$B$70,$A20,Backup_All_States!$L$2:$L$70,"Y",Backup_All_States!$J$2:$J$70,"No") -> 0 | C20: =SUMIFS(Backup_All_States!$E$2:$E$70,Backup_All_States!$A$2:$A$70,"Telangana",Backup_All_States!$B$2:$B$70,$A20,Backup_All_States!$L$2:$L$70,"Y",Backup_All_States!$J$2:$J$70,"No") -> 0 | D20: =B20+C20 -> 0
A21: Adani Group | B21: =SUMIFS(Backup_All_States!$F$2:$F$70,Backup_All_States!$A$2:$A$70,"Telangana",Backup_All_States!$B$2:$B$70,$A21,Backup_All_States!$L$2:$L$70,"Y",Backup_All_States!$J$2:$J$70,"No") -> 0 | C21: =SUMIFS(Backup_All_States!$E$2:$E$70,Backup_All_States!$A$2:$A$70,"Telangana",Backup_All_States!$B$2:$B$70,$A21,Backup_All_States!$L$2:$L$70,"Y",Backup_All_States!$J$2:$J$70,"No") -> 0 | D21: =B21+C21 -> 0
A22: CtrlS | B22: =SUMIFS(Backup_All_States!$F$2:$F$70,Backup_All_States!$A$2:$A$70,"Telangana",Backup_All_States!$B$2:$B$70,$A22,Backup_All_States!$L$2:$L$70,"Y",Backup_All_States!$J$2:$J$70,"No") -> 400 | C22: =SUMIFS(Backup_All_States!$E$2:$E$70,Backup_All_States!$A$2:$A$70,"Telangana",Backup_All_States!$B$2:$B$70,$A22,Backup_All_States!$L$2:$L$70,"Y",Backup_All_States!$J$2:$J$70,"No") -> 0 | D22: =B22+C22 -> 400
A23: NTT Data - Neysa | B23: =SUMIFS(Backup_All_States!$F$2:$F$70,Backup_All_States!$A$2:$A$70,"Telangana",Backup_All_States!$B$2:$B$70,$A23,Backup_All_States!$L$2:$L$70,"Y",Backup_All_States!$J$2:$J$70,"No") -> 400 | C23: =SUMIFS(Backup_All_States!$E$2:$E$70,Backup_All_States!$A$2:$A$70,"Telangana",Backup_All_States!$B$2:$B$70,$A23,Backup_All_States!$L$2:$L$70,"Y",Backup_All_States!$J$2:$J$70,"No") -> 0 | D23: =B23+C23 -> 400
A24: AWS / CtrlS (unattributed) | B24: =SUMIFS(Backup_All_States!$F$2:$F$70,Backup_All_States!$A$2:$A$70,"Telangana",Backup_All_States!$B$2:$B$70,$A24,Backup_All_States!$L$2:$L$70,"Y",Backup_All_States!$J$2:$J$70,"No") -> 0 | C24: =SUMIFS(Backup_All_States!$E$2:$E$70,Backup_All_States!$A$2:$A$70,"Telangana",Backup_All_States!$B$2:$B$70,$A24,Backup_All_States!$L$2:$L$70,"Y",Backup_All_States!$J$2:$J$70,"No") -> 278 | D24: =B24+C24 -> 278
A25: STT GDC | B25: =SUMIFS(Backup_All_States!$F$2:$F$70,Backup_All_States!$A$2:$A$70,"Telangana",Backup_All_States!$B$2:$B$70,$A25,Backup_All_States!$L$2:$L$70,"Y",Backup_All_States!$J$2:$J$70,"No") -> 100 | C25: =SUMIFS(Backup_All_States!$E$2:$E$70,Backup_All_States!$A$2:$A$70,"Telangana",Backup_All_States!$B$2:$B$70,$A25,Backup_All_States!$L$2:$L$70,"Y",Backup_All_States!$J$2:$J$70,"No") -> 0 | D25: =B25+C25 -> 100
A26: UPC-Volt | B26: =SUMIFS(Backup_All_States!$F$2:$F$70,Backup_All_States!$A$2:$A$70,"Telangana",Backup_All_States!$B$2:$B$70,$A26,Backup_All_States!$L$2:$L$70,"Y",Backup_All_States!$J$2:$J$70,"No") -> 100 | C26: =SUMIFS(Backup_All_States!$E$2:$E$70,Backup_All_States!$A$2:$A$70,"Telangana",Backup_All_States!$B$2:$B$70,$A26,Backup_All_States!$L$2:$L$70,"Y",Backup_All_States!$J$2:$J$70,"No") -> 0 | D26: =B26+C26 -> 100
A27: Total | B27: =SUM(B19:B26) -> 1000 | C27: =SUM(C19:C26) -> 2278 | D27: =SUM(D19:D26) -> 3278

Sheet Tamil Nadu
A1: Tamil Nadu - data-centre power by company group (MW), state-level sources
A2: Approved = government permission granted or operating; Under process = application / MoU / LoI / announced. MW basis varies by row - see Backup_All_States column G.
A4: A. All state-level data
A5: Company / group | B5: Under process | C5: Approved | D5: Total
A6: Sify | B6: =SUMIFS(Backup_All_States!$F$2:$F$70,Backup_All_States!$A$2:$A$70,"Tamil Nadu",Backup_All_States!$B$2:$B$70,$A6,Backup_All_States!$L$2:$L$70,"Y") -> 104.1 | C6: =SUMIFS(Backup_All_States!$E$2:$E$70,Backup_All_States!$A$2:$A$70,"Tamil Nadu",Backup_All_States!$B$2:$B$70,$A6,Backup_All_States!$L$2:$L$70,"Y") -> 25.9 | D6: =B6+C6 -> 130
A7: Digital Connexion (Reliance-Brookfield-DLR) | B7: =SUMIFS(Backup_All_States!$F$2:$F$70,Backup_All_States!$A$2:$A$70,"Tamil Nadu",Backup_All_States!$B$2:$B$70,$A7,Backup_All_States!$L$2:$L$70,"Y") -> 0 | C7: =SUMIFS(Backup_All_States!$E$2:$E$70,Backup_All_States!$A$2:$A$70,"Tamil Nadu",Backup_All_States!$B$2:$B$70,$A7,Backup_All_States!$L$2:$L$70,"Y") -> 100 | D7: =B7+C7 -> 100
A8: CapitaLand | B8: =SUMIFS(Backup_All_States!$F$2:$F$70,Backup_All_States!$A$2:$A$70,"Tamil Nadu",Backup_All_States!$B$2:$B$70,$A8,Backup_All_States!$L$2:$L$70,"Y") -> 0 | C8: =SUMIFS(Backup_All_States!$E$2:$E$70,Backup_All_States!$A$2:$A$70,"Tamil Nadu",Backup_All_States!$B$2:$B$70,$A8,Backup_All_States!$L$2:$L$70,"Y") -> 53 | D8: =B8+C8 -> 53
A9: STT GDC | B9: =SUMIFS(Backup_All_States!$F$2:$F$70,Backup_All_States!$A$2:$A$70,"Tamil Nadu",Backup_All_States!$B$2:$B$70,$A9,Backup_All_States!$L$2:$L$70,"Y") -> 37.8 | C9: =SUMIFS(Backup_All_States!$E$2:$E$70,Backup_All_States!$A$2:$A$70,"Tamil Nadu",Backup_All_States!$B$2:$B$70,$A9,Backup_All_States!$L$2:$L$70,"Y") -> 7.2 | D9: =B9+C9 -> 45
A10: Techno Digital | B10: =SUMIFS(Backup_All_States!$F$2:$F$70,Backup_All_States!$A$2:$A$70,"Tamil Nadu",Backup_All_States!$B$2:$B$70,$A10,Backup_All_States!$L$2:$L$70,"Y") -> 0 | C10: =SUMIFS(Backup_All_States!$E$2:$E$70,Backup_All_States!$A$2:$A$70,"Tamil Nadu",Backup_All_States!$B$2:$B$70,$A10,Backup_All_States!$L$2:$L$70,"Y") -> 36 | D10: =B10+C10 -> 36
A11: Adani Group | B11: =SUMIFS(Backup_All_States!$F$2:$F$70,Backup_All_States!$A$2:$A$70,"Tamil Nadu",Backup_All_States!$B$2:$B$70,$A11,Backup_All_States!$L$2:$L$70,"Y") -> 16 | C11: =SUMIFS(Backup_All_States!$E$2:$E$70,Backup_All_States!$A$2:$A$70,"Tamil Nadu",Backup_All_States!$B$2:$B$70,$A11,Backup_All_States!$L$2:$L$70,"Y") -> 17 | D11: =B11+C11 -> 33
A12: Total | B12: =SUM(B6:B11) -> 157.9 | C12: =SUM(C6:C11) -> 239.1 | D12: =SUM(D6:D11) -> 397
A15: B. Excluding rows that overlap CTUIL (use this to ADD to the CTUIL chart)
A16: Company / group | B16: Under process | C16: Approved | D16: Total
A17: Sify | B17: =SUMIFS(Backup_All_States!$F$2:$F$70,Backup_All_States!$A$2:$A$70,"Tamil Nadu",Backup_All_States!$B$2:$B$70,$A17,Backup_All_States!$L$2:$L$70,"Y",Backup_All_States!$J$2:$J$70,"No") -> 104.1 | C17: =SUMIFS(Backup_All_States!$E$2:$E$70,Backup_All_States!$A$2:$A$70,"Tamil Nadu",Backup_All_States!$B$2:$B$70,$A17,Backup_All_States!$L$2:$L$70,"Y",Backup_All_States!$J$2:$J$70,"No") -> 25.9 | D17: =B17+C17 -> 130
A18: Digital Connexion (Reliance-Brookfield-DLR) | B18: =SUMIFS(Backup_All_States!$F$2:$F$70,Backup_All_States!$A$2:$A$70,"Tamil Nadu",Backup_All_States!$B$2:$B$70,$A18,Backup_All_States!$L$2:$L$70,"Y",Backup_All_States!$J$2:$J$70,"No") -> 0 | C18: =SUMIFS(Backup_All_States!$E$2:$E$70,Backup_All_States!$A$2:$A$70,"Tamil Nadu",Backup_All_States!$B$2:$B$70,$A18,Backup_All_States!$L$2:$L$70,"Y",Backup_All_States!$J$2:$J$70,"No") -> 100 | D18: =B18+C18 -> 100
A19: CapitaLand | B19: =SUMIFS(Backup_All_States!$F$2:$F$70,Backup_All_States!$A$2:$A$70,"Tamil Nadu",Backup_All_States!$B$2:$B$70,$A19,Backup_All_States!$L$2:$L$70,"Y",Backup_All_States!$J$2:$J$70,"No") -> 0 | C19: =SUMIFS(Backup_All_States!$E$2:$E$70,Backup_All_States!$A$2:$A$70,"Tamil Nadu",Backup_All_States!$B$2:$B$70,$A19,Backup_All_States!$L$2:$L$70,"Y",Backup_All_States!$J$2:$J$70,"No") -> 53 | D19: =B19+C19 -> 53
A20: STT GDC | B20: =SUMIFS(Backup_All_States!$F$2:$F$70,Backup_All_States!$A$2:$A$70,"Tamil Nadu",Backup_All_States!$B$2:$B$70,$A20,Backup_All_States!$L$2:$L$70,"Y",Backup_All_States!$J$2:$J$70,"No") -> 37.8 | C20: =SUMIFS(Backup_All_States!$E$2:$E$70,Backup_All_States!$A$2:$A$70,"Tamil Nadu",Backup_All_States!$B$2:$B$70,$A20,Backup_All_States!$L$2:$L$70,"Y",Backup_All_States!$J$2:$J$70,"No") -> 7.2 | D20: =B20+C20 -> 45
A21: Techno Digital | B21: =SUMIFS(Backup_All_States!$F$2:$F$70,Backup_All_States!$A$2:$A$70,"Tamil Nadu",Backup_All_States!$B$2:$B$70,$A21,Backup_All_States!$L$2:$L$70,"Y",Backup_All_States!$J$2:$J$70,"No") -> 0 | C21: =SUMIFS(Backup_All_States!$E$2:$E$70,Backup_All_States!$A$2:$A$70,"Tamil Nadu",Backup_All_States!$B$2:$B$70,$A21,Backup_All_States!$L$2:$L$70,"Y",Backup_All_States!$J$2:$J$70,"No") -> 36 | D21: =B21+C21 -> 36
A22: Adani Group | B22: =SUMIFS(Backup_All_States!$F$2:$F$70,Backup_All_States!$A$2:$A$70,"Tamil Nadu",Backup_All_States!$B$2:$B$70,$A22,Backup_All_States!$L$2:$L$70,"Y",Backup_All_States!$J$2:$J$70,"No") -> 16 | C22: =SUMIFS(Backup_All_States!$E$2:$E$70,Backup_All_States!$A$2:$A$70,"Tamil Nadu",Backup_All_States!$B$2:$B$70,$A22,Backup_All_States!$L$2:$L$70,"Y",Backup_All_States!$J$2:$J$70,"No") -> 17 | D22: =B22+C22 -> 33
A23: Total | B23: =SUM(B17:B22) -> 157.9 | C23: =SUM(C17:C22) -> 239.1 | D23: =SUM(D17:D22) -> 397

Sheet Uttar Pradesh
A1: Uttar Pradesh - data-centre power by company group (MW), state-level sources
A2: Approved = government permission granted or operating; Under process = application / MoU / LoI / announced. MW basis varies by row - see Backup_All_States column G.
A4: A. All state-level data
A5: Company / group | B5: Under process | C5: Approved | D5: Total
A6: Hiranandani (Yotta) | B6: =SUMIFS(Backup_All_States!$F$2:$F$70,Backup_All_States!$A$2:$A$70,"Uttar Pradesh",Backup_All_States!$B$2:$B$70,$A6,Backup_All_States!$L$2:$L$70,"Y") -> 222 | C6: =SUMIFS(Backup_All_States!$E$2:$E$70,Backup_All_States!$A$2:$A$70,"Uttar Pradesh",Backup_All_States!$B$2:$B$70,$A6,Backup_All_States!$L$2:$L$70,"Y") -> 28 | D6: =B6+C6 -> 250
A7: SKVR | B7: =SUMIFS(Backup_All_States!$F$2:$F$70,Backup_All_States!$A$2:$A$70,"Uttar Pradesh",Backup_All_States!$B$2:$B$70,$A7,Backup_All_States!$L$2:$L$70,"Y") -> 104 | C7: =SUMIFS(Backup_All_States!$E$2:$E$70,Backup_All_States!$A$2:$A$70,"Uttar Pradesh",Backup_All_States!$B$2:$B$70,$A7,Backup_All_States!$L$2:$L$70,"Y") -> 16 | D7: =B7+C7 -> 120
A8: Adani Group | B8: =SUMIFS(Backup_All_States!$F$2:$F$70,Backup_All_States!$A$2:$A$70,"Uttar Pradesh",Backup_All_States!$B$2:$B$70,$A8,Backup_All_States!$L$2:$L$70,"Y") -> 65 | C8: =SUMIFS(Backup_All_States!$E$2:$E$70,Backup_All_States!$A$2:$A$70,"Uttar Pradesh",Backup_All_States!$B$2:$B$70,$A8,Backup_All_States!$L$2:$L$70,"Y") -> 35 | D8: =B8+C8 -> 100
A9: NTT | B9: =SUMIFS(Backup_All_States!$F$2:$F$70,Backup_All_States!$A$2:$A$70,"Uttar Pradesh",Backup_All_States!$B$2:$B$70,$A9,Backup_All_States!$L$2:$L$70,"Y") -> 43.8 | C9: =SUMIFS(Backup_All_States!$E$2:$E$70,Backup_All_States!$A$2:$A$70,"Uttar Pradesh",Backup_All_States!$B$2:$B$70,$A9,Backup_All_States!$L$2:$L$70,"Y") -> 9 | D9: =B9+C9 -> 52.8
A10: STT GDC | B10: =SUMIFS(Backup_All_States!$F$2:$F$70,Backup_All_States!$A$2:$A$70,"Uttar Pradesh",Backup_All_States!$B$2:$B$70,$A10,Backup_All_States!$L$2:$L$70,"Y") -> 0 | C10: =SUMIFS(Backup_All_States!$E$2:$E$70,Backup_All_States!$A$2:$A$70,"Uttar Pradesh",Backup_All_States!$B$2:$B$70,$A10,Backup_All_States!$L$2:$L$70,"Y") -> 40 | D10: =B10+C10 -> 40
A11: Iron Mountain | B11: =SUMIFS(Backup_All_States!$F$2:$F$70,Backup_All_States!$A$2:$A$70,"Uttar Pradesh",Backup_All_States!$B$2:$B$70,$A11,Backup_All_States!$L$2:$L$70,"Y") -> 0 | C11: =SUMIFS(Backup_All_States!$E$2:$E$70,Backup_All_States!$A$2:$A$70,"Uttar Pradesh",Backup_All_States!$B$2:$B$70,$A11,Backup_All_States!$L$2:$L$70,"Y") -> 5 | D11: =B11+C11 -> 5
A12: Total | B12: =SUM(B6:B11) -> 434.8 | C12: =SUM(C6:C11) -> 133 | D12: =SUM(D6:D11) -> 567.8
A15: B. Excluding rows that overlap CTUIL (use this to ADD to the CTUIL chart)
A16: Company / group | B16: Under process | C16: Approved | D16: Total
A17: Hiranandani (Yotta) | B17: =SUMIFS(Backup_All_States!$F$2:$F$70,Backup_All_States!$A$2:$A$70,"Uttar Pradesh",Backup_All_States!$B$2:$B$70,$A17,Backup_All_States!$L$2:$L$70,"Y",Backup_All_States!$J$2:$J$70,"No") -> 222 | C17: =SUMIFS(Backup_All_States!$E$2:$E$70,Backup_All_States!$A$2:$A$70,"Uttar Pradesh",Backup_All_States!$B$2:$B$70,$A17,Backup_All_States!$L$2:$L$70,"Y",Backup_All_States!$J$2:$J$70,"No") -> 28 | D17: =B17+C17 -> 250
A18: SKVR | B18: =SUMIFS(Backup_All_States!$F$2:$F$70,Backup_All_States!$A$2:$A$70,"Uttar Pradesh",Backup_All_States!$B$2:$B$70,$A18,Backup_All_States!$L$2:$L$70,"Y",Backup_All_States!$J$2:$J$70,"No") -> 104 | C18: =SUMIFS(Backup_All_States!$E$2:$E$70,Backup_All_States!$A$2:$A$70,"Uttar Pradesh",Backup_All_States!$B$2:$B$70,$A18,Backup_All_States!$L$2:$L$70,"Y",Backup_All_States!$J$2:$J$70,"No") -> 16 | D18: =B18+C18 -> 120
A19: Adani Group | B19: =SUMIFS(Backup_All_States!$F$2:$F$70,Backup_All_States!$A$2:$A$70,"Uttar Pradesh",Backup_All_States!$B$2:$B$70,$A19,Backup_All_States!$L$2:$L$70,"Y",Backup_All_States!$J$2:$J$70,"No") -> 65 | C19: =SUMIFS(Backup_All_States!$E$2:$E$70,Backup_All_States!$A$2:$A$70,"Uttar Pradesh",Backup_All_States!$B$2:$B$70,$A19,Backup_All_States!$L$2:$L$70,"Y",Backup_All_States!$J$2:$J$70,"No") -> 35 | D19: =B19+C19 -> 100
A20: NTT | B20: =SUMIFS(Backup_All_States!$F$2:$F$70,Backup_All_States!$A$2:$A$70,"Uttar Pradesh",Backup_All_States!$B$2:$B$70,$A20,Backup_All_States!$L$2:$L$70,"Y",Backup_All_States!$J$2:$J$70,"No") -> 43.8 | C20: =SUMIFS(Backup_All_States!$E$2:$E$70,Backup_All_States!$A$2:$A$70,"Uttar Pradesh",Backup_All_States!$B$2:$B$70,$A20,Backup_All_States!$L$2:$L$70,"Y",Backup_All_States!$J$2:$J$70,"No") -> 9 | D20: =B20+C20 -> 52.8
A21: STT GDC | B21: =SUMIFS(Backup_All_States!$F$2:$F$70,Backup_All_States!$A$2:$A$70,"Uttar Pradesh",Backup_All_States!$B$2:$B$70,$A21,Backup_All_States!$L$2:$L$70,"Y",Backup_All_States!$J$2:$J$70,"No") -> 0 | C21: =SUMIFS(Backup_All_States!$E$2:$E$70,Backup_All_States!$A$2:$A$70,"Uttar Pradesh",Backup_All_States!$B$2:$B$70,$A21,Backup_All_States!$L$2:$L$70,"Y",Backup_All_States!$J$2:$J$70,"No") -> 40 | D21: =B21+C21 -> 40
A22: Iron Mountain | B22: =SUMIFS(Backup_All_States!$F$2:$F$70,Backup_All_States!$A$2:$A$70,"Uttar Pradesh",Backup_All_States!$B$2:$B$70,$A22,Backup_All_States!$L$2:$L$70,"Y",Backup_All_States!$J$2:$J$70,"No") -> 0 | C22: =SUMIFS(Backup_All_States!$E$2:$E$70,Backup_All_States!$A$2:$A$70,"Uttar Pradesh",Backup_All_States!$B$2:$B$70,$A22,Backup_All_States!$L$2:$L$70,"Y",Backup_All_States!$J$2:$J$70,"No") -> 5 | D22: =B22+C22 -> 5
A23: Total | B23: =SUM(B17:B22) -> 434.8 | C23: =SUM(C17:C22) -> 133 | D23: =SUM(D17:D22) -> 567.8

Sheet Odisha
A1: Odisha - data-centre power by company group (MW), state-level sources
A2: Approved = government permission granted or operating; Under process = application / MoU / LoI / announced. MW basis varies by row - see Backup_All_States column G.
A4: A. All state-level data
A5: Company / group | B5: Under process | C5: Approved | D5: Total
A6: Adani Group | B6: =SUMIFS(Backup_All_States!$F$2:$F$70,Backup_All_States!$A$2:$A$70,"Odisha",Backup_All_States!$B$2:$B$70,$A6,Backup_All_States!$L$2:$L$70,"Y") -> 0 | C6: =SUMIFS(Backup_All_States!$E$2:$E$70,Backup_All_States!$A$2:$A$70,"Odisha",Backup_All_States!$B$2:$B$70,$A6,Backup_All_States!$L$2:$L$70,"Y") -> 1000 | D6: =B6+C6 -> 1000
A7: Sentraforge AI | B7: =SUMIFS(Backup_All_States!$F$2:$F$70,Backup_All_States!$A$2:$A$70,"Odisha",Backup_All_States!$B$2:$B$70,$A7,Backup_All_States!$L$2:$L$70,"Y") -> 0 | C7: =SUMIFS(Backup_All_States!$E$2:$E$70,Backup_All_States!$A$2:$A$70,"Odisha",Backup_All_States!$B$2:$B$70,$A7,Backup_All_States!$L$2:$L$70,"Y") -> 120 | D7: =B7+C7 -> 120
A8: Total | B8: =SUM(B6:B7) -> 0 | C8: =SUM(C6:C7) -> 1120 | D8: =SUM(D6:D7) -> 1120
A11: B. Excluding rows that overlap CTUIL (use this to ADD to the CTUIL chart)
A12: Company / group | B12: Under process | C12: Approved | D12: Total
A13: Adani Group | B13: =SUMIFS(Backup_All_States!$F$2:$F$70,Backup_All_States!$A$2:$A$70,"Odisha",Backup_All_States!$B$2:$B$70,$A13,Backup_All_States!$L$2:$L$70,"Y",Backup_All_States!$J$2:$J$70,"No") -> 0 | C13: =SUMIFS(Backup_All_States!$E$2:$E$70,Backup_All_States!$A$2:$A$70,"Odisha",Backup_All_States!$B$2:$B$70,$A13,Backup_All_States!$L$2:$L$70,"Y",Backup_All_States!$J$2:$J$70,"No") -> 1000 | D13: =B13+C13 -> 1000
A14: Sentraforge AI | B14: =SUMIFS(Backup_All_States!$F$2:$F$70,Backup_All_States!$A$2:$A$70,"Odisha",Backup_All_States!$B$2:$B$70,$A14,Backup_All_States!$L$2:$L$70,"Y",Backup_All_States!$J$2:$J$70,"No") -> 0 | C14: =SUMIFS(Backup_All_States!$E$2:$E$70,Backup_All_States!$A$2:$A$70,"Odisha",Backup_All_States!$B$2:$B$70,$A14,Backup_All_States!$L$2:$L$70,"Y",Backup_All_States!$J$2:$J$70,"No") -> 120 | D14: =B14+C14 -> 120
A15: Total | B15: =SUM(B13:B14) -> 0 | C15: =SUM(C13:C14) -> 1120 | D15: =SUM(D13:D14) -> 1120

Sheet Karnataka
A1: Karnataka - data-centre power by company group (MW), state-level sources
A2: Approved = government permission granted or operating; Under process = application / MoU / LoI / announced. MW basis varies by row - see Backup_All_States column G.
A4: A. All state-level data
A5: Company / group | B5: Under process | C5: Approved | D5: Total
A6: Govt of Karnataka (park) | B6: =SUMIFS(Backup_All_States!$F$2:$F$70,Backup_All_States!$A$2:$A$70,"Karnataka",Backup_All_States!$B$2:$B$70,$A6,Backup_All_States!$L$2:$L$70,"Y") -> 500 | C6: =SUMIFS(Backup_All_States!$E$2:$E$70,Backup_All_States!$A$2:$A$70,"Karnataka",Backup_All_States!$B$2:$B$70,$A6,Backup_All_States!$L$2:$L$70,"Y") -> 0 | D6: =B6+C6 -> 500
A7: Total | B7: =SUM(B6:B6) -> 500 | C7: =SUM(C6:C6) -> 0 | D7: =SUM(D6:D6) -> 500
A10: B. Excluding rows that overlap CTUIL (use this to ADD to the CTUIL chart)
A11: Company / group | B11: Under process | C11: Approved | D11: Total
A12: Govt of Karnataka (park) | B12: =SUMIFS(Backup_All_States!$F$2:$F$70,Backup_All_States!$A$2:$A$70,"Karnataka",Backup_All_States!$B$2:$B$70,$A12,Backup_All_States!$L$2:$L$70,"Y",Backup_All_States!$J$2:$J$70,"No") -> 500 | C12: =SUMIFS(Backup_All_States!$E$2:$E$70,Backup_All_States!$A$2:$A$70,"Karnataka",Backup_All_States!$B$2:$B$70,$A12,Backup_All_States!$L$2:$L$70,"Y",Backup_All_States!$J$2:$J$70,"No") -> 0 | D12: =B12+C12 -> 500
A13: Total | B13: =SUM(B12:B12) -> 500 | C13: =SUM(C12:C12) -> 0 | D13: =SUM(D12:D12) -> 500

Sheet Gujarat
A1: Gujarat - data-centre power by company group (MW), state-level sources
A2: Approved = government permission granted or operating; Under process = application / MoU / LoI / announced. MW basis varies by row - see Backup_All_States column G.
A4: A. All state-level data
A5: Company / group | B5: Under process | C5: Approved | D5: Total
A6: Reliance | B6: =SUMIFS(Backup_All_States!$F$2:$F$70,Backup_All_States!$A$2:$A$70,"Gujarat",Backup_All_States!$B$2:$B$70,$A6,Backup_All_States!$L$2:$L$70,"Y") -> 168 | C6: =SUMIFS(Backup_All_States!$E$2:$E$70,Backup_All_States!$A$2:$A$70,"Gujarat",Backup_All_States!$B$2:$B$70,$A6,Backup_All_States!$L$2:$L$70,"Y") -> 0 | D6: =B6+C6 -> 168
A7: Total | B7: =SUM(B6:B6) -> 168 | C7: =SUM(C6:C6) -> 0 | D7: =SUM(D6:D6) -> 168
A10: B. Excluding rows that overlap CTUIL (use this to ADD to the CTUIL chart)
A11: Company / group | B11: Under process | C11: Approved | D11: Total
A12: Reliance | B12: =SUMIFS(Backup_All_States!$F$2:$F$70,Backup_All_States!$A$2:$A$70,"Gujarat",Backup_All_States!$B$2:$B$70,$A12,Backup_All_States!$L$2:$L$70,"Y",Backup_All_States!$J$2:$J$70,"No") -> 0 | C12: =SUMIFS(Backup_All_States!$E$2:$E$70,Backup_All_States!$A$2:$A$70,"Gujarat",Backup_All_States!$B$2:$B$70,$A12,Backup_All_States!$L$2:$L$70,"Y",Backup_All_States!$J$2:$J$70,"No") -> 0 | D12: =B12+C12 -> 0
A13: Total | B13: =SUM(B12:B12) -> 0 | C13: =SUM(C12:C12) -> 0 | D13: =SUM(D12:D12) -> 0

Sheet Haryana
A1: Haryana - data-centre power by company group (MW), state-level sources
A2: Approved = government permission granted or operating; Under process = application / MoU / LoI / announced. MW basis varies by row - see Backup_All_States column G.
A4: A. All state-level data
A5: Company / group | B5: Under process | C5: Approved | D5: Total
A6: Anant Raj | B6: =SUMIFS(Backup_All_States!$F$2:$F$70,Backup_All_States!$A$2:$A$70,"Haryana",Backup_All_States!$B$2:$B$70,$A6,Backup_All_States!$L$2:$L$70,"Y") -> 279 | C6: =SUMIFS(Backup_All_States!$E$2:$E$70,Backup_All_States!$A$2:$A$70,"Haryana",Backup_All_States!$B$2:$B$70,$A6,Backup_All_States!$L$2:$L$70,"Y") -> 28 | D6: =B6+C6 -> 307
A7: Total | B7: =SUM(B6:B6) -> 279 | C7: =SUM(C6:C6) -> 28 | D7: =SUM(D6:D6) -> 307
A10: B. Excluding rows that overlap CTUIL (use this to ADD to the CTUIL chart)
A11: Company / group | B11: Under process | C11: Approved | D11: Total
A12: Anant Raj | B12: =SUMIFS(Backup_All_States!$F$2:$F$70,Backup_All_States!$A$2:$A$70,"Haryana",Backup_All_States!$B$2:$B$70,$A12,Backup_All_States!$L$2:$L$70,"Y",Backup_All_States!$J$2:$J$70,"No") -> 279 | C12: =SUMIFS(Backup_All_States!$E$2:$E$70,Backup_All_States!$A$2:$A$70,"Haryana",Backup_All_States!$B$2:$B$70,$A12,Backup_All_States!$L$2:$L$70,"Y",Backup_All_States!$J$2:$J$70,"No") -> 28 | D12: =B12+C12 -> 307
A13: Total | B13: =SUM(B12:B12) -> 279 | C13: =SUM(C12:C12) -> 28 | D13: =SUM(D12:D12) -> 307

Sheet West Bengal
A1: West Bengal - data-centre power by company group (MW), state-level sources
A2: Approved = government permission granted or operating; Under process = application / MoU / LoI / announced. MW basis varies by row - see Backup_All_States column G.
A4: A. All state-level data
A5: Company / group | B5: Under process | C5: Approved | D5: Total
A6: Hiranandani (Yotta) | B6: =SUMIFS(Backup_All_States!$F$2:$F$70,Backup_All_States!$A$2:$A$70,"West Bengal",Backup_All_States!$B$2:$B$70,$A6,Backup_All_States!$L$2:$L$70,"Y") -> 250 | C6: =SUMIFS(Backup_All_States!$E$2:$E$70,Backup_All_States!$A$2:$A$70,"West Bengal",Backup_All_States!$B$2:$B$70,$A6,Backup_All_States!$L$2:$L$70,"Y") -> 0 | D6: =B6+C6 -> 250
A7: NTT | B7: =SUMIFS(Backup_All_States!$F$2:$F$70,Backup_All_States!$A$2:$A$70,"West Bengal",Backup_All_States!$B$2:$B$70,$A7,Backup_All_States!$L$2:$L$70,"Y") -> 25 | C7: =SUMIFS(Backup_All_States!$E$2:$E$70,Backup_All_States!$A$2:$A$70,"West Bengal",Backup_All_States!$B$2:$B$70,$A7,Backup_All_States!$L$2:$L$70,"Y") -> 0 | D7: =B7+C7 -> 25
A8: Total | B8: =SUM(B6:B7) -> 275 | C8: =SUM(C6:C7) -> 0 | D8: =SUM(D6:D7) -> 275
A11: B. Excluding rows that overlap CTUIL (use this to ADD to the CTUIL chart)
A12: Company / group | B12: Under process | C12: Approved | D12: Total
A13: Hiranandani (Yotta) | B13: =SUMIFS(Backup_All_States!$F$2:$F$70,Backup_All_States!$A$2:$A$70,"West Bengal",Backup_All_States!$B$2:$B$70,$A13,Backup_All_States!$L$2:$L$70,"Y",Backup_All_States!$J$2:$J$70,"No") -> 250 | C13: =SUMIFS(Backup_All_States!$E$2:$E$70,Backup_All_States!$A$2:$A$70,"West Bengal",Backup_All_States!$B$2:$B$70,$A13,Backup_All_States!$L$2:$L$70,"Y",Backup_All_States!$J$2:$J$70,"No") -> 0 | D13: =B13+C13 -> 250
A14: NTT | B14: =SUMIFS(Backup_All_States!$F$2:$F$70,Backup_All_States!$A$2:$A$70,"West Bengal",Backup_All_States!$B$2:$B$70,$A14,Backup_All_States!$L$2:$L$70,"Y",Backup_All_States!$J$2:$J$70,"No") -> 25 | C14: =SUMIFS(Backup_All_States!$E$2:$E$70,Backup_All_States!$A$2:$A$70,"West Bengal",Backup_All_States!$B$2:$B$70,$A14,Backup_All_States!$L$2:$L$70,"Y",Backup_All_States!$J$2:$J$70,"No") -> 0 | D14: =B14+C14 -> 25
A15: Total | B15: =SUM(B13:B14) -> 275 | C15: =SUM(C13:C14) -> 0 | D15: =SUM(D13:D14) -> 275

Sheet Backup_All_States
A1: State | B1: Group / ecosystem | C1: Company / SPV (as filed) | D1: Project / site | E1: Approved (MW) | F1: Under process (MW) | G1: MW basis | H1: Status basis (why approved / under process) | I1: Evidence tier | J1: Overlap with CTUIL | K1: CTUIL reference | L1: Include in state charts (Y/N) | M1: Source link | N1: Notes | O1: Evidence type
A2: Maharashtra | B2: Lodha Group (park; tenants AWS, STT) | C2: Lodha Developers / Maharashtra STU | D2: Palava-Ambernath Green DC Park | E2: 1450 | F2: 1500 | G2: Grid (STU connectivity) | H2: STU connectivity granted for ~1,450 MW (AWS, STT); ~1,500 MW under consideration - MERC Case 88/2026 | I2: A1 | J2: No | K2: State grid (MSETCL), not ISTS | L2: Y | M2: https://merc.gov.in/wp-content/uploads/2026/06/Order-88-of-2026.pdf | N2: AWS Taloja/Asode 473 MW EC filing sits inside this park - not added separately | O2: 1 Grid connection granted / sanctioned
A3: Maharashtra | B3: AirTrunk (Blackstone) | C3: AirTrunk | D3: Raigad-Pen Growth Centre | F3: 3000 | G3: IT MW | H3: State Letter of Intent for land (Jun-2026) | I3: A2 | J3: No | L3: Y | M3: https://www.aninews.in/news/business/maharashtra-issues-letter-of-intent-to-airtrunk-for-rs-2-lakh-crore-data-centre-project-in-raigad20260601123602/ | O3: 4 MoU / LoI / announced
A4: Maharashtra | B4: AirTrunk (Blackstone) | C4: Gramercy Techpark Pvt Ltd (ex-Lumina) | D4: BOM1, Plot 7 & 7A TTC Airoli | E4: 62 | G4: IT MW | H4: MPCB CTE (CI Rs 1,495 cr) + CTO (part) May-2025 for Gramercy Techpark | I4: D | J4: No | L4: Y | M4: https://mpcb.gov.in/sites/default/files/inline-files/Minutes%20of%2015th%20CAC%20Establish%20Booklet%20no%2065.pdf | N4: AUDIT: consent verified in MPCB link; 62 MW is from a data-centre directory listing (not company/official) - tier D | O4: 2 Permit (EC / pollution consent)
A5: Maharashtra | B5: AirTrunk (Blackstone) | C5: AirTrunk | D5: BOM2, Mahape (5.4 ha) | F5: 120 | G5: IT MW | H5: Company page lists 120+ MW; no permit found for BOM2 | I5: C | J5: No | L5: Y | M5: https://airtrunk.com/location/bom2-mumbai/ | N5: AUDIT: split from BOM1; previously counted as approved - no BOM2 permit found, so moved to under process | O5: 5 Operating / company filing
A6: Maharashtra | B6: Adani Group | C6: AdaniConneX (CoreWeave tenant) | D6: Taloja campus | F6: 240 | G6: IT MW | H6: Contracted; no permit found yet | I6: C | J6: Possible | K6: Adani Infra 10 x 50 MW at LILO of 400 kV Padghe-Kharghar (under process) | L6: Y | M6: https://investors.coreweave.com/news/news-details/2026/CoreWeave-Enters-India-Expanding-AI-Cloud-Platform-With-AdaniConneX/default.aspx | N6: Could be the same load as Adani Infra's CTUIL filing | O6: 4 MoU / LoI / announced
A7: Maharashtra | B7: Adani Group | C7: Support Properties Pvt Ltd ('ACXNMI-01') | D7: A-GEN-4 TTC Rabale/Ghansoli | G7: n/a | H7: MPCB CTE Feb-2024; SEIAA EC expansion on agenda | I7: A1 | J7: Yes | K7: Support Properties 1,468 MW APPROVED at 400 kV Navi Mumbai (GIS) | L7: N | M7: https://www.ecmpcb.in/login/download_ec_document/MjMyMTI2NEMzMjYzNDM5M0IxRTJDRDY5MENBNDZFODcucGRm | N7: Power is captured in CTUIL data - no MW in state data | O7: 2 Permit (EC / pollution consent)
A8: Maharashtra | B8: Adani Group | C8: Pune Data Center Ltd (Adani SPV; ex-Microsoft) | D8: ACXPNQ26 / PNQ04, Bhosari, Pune (Microsoft site) | E8: 75.4 | G8: Connected MW | H8: EC granted 22-07-2025 (517762/2025); expansion referred back Feb-2026 | I8: A1 | J8: No | L8: Y | M8: https://environmentclearance.nic.in/writereaddata/FormB/agenda/2302202697285484%28921161%29MINUTESOF319DAY-5PART-B.pdf | N8: Pimpri PNQ06/ACXPNQ27&29 (CI Rs 5,228 cr) has no MW disclosed - not counted | O8: 2 Permit (EC / pollution consent)
A9: Maharashtra | B9: AWS (Amazon) | C9: Amazon Data Services India | D9: Balkum-Majiwada, Thane | E9: 272 | G9: IT MW | H9: MPCB CTE granted 14-12-2023 (CI Rs 7,203 cr) - verified; EC applications 415824/2023 & 477127/2024 | I9: D | J9: No | L9: Y | M9: https://x.com/cbdhage/status/1762797367529480646 | N9: MW NOT VERIFIED in a primary document: 272 MW IT is from a social-media summary of the EC filing (link). CTE and CI verified in MPCB 16th CAC 2023-24 ATR: https://mpcb.gov.in/sites/default/files/inline-files/Action_taken_Report_of_16th_CAC_Booklet_no_16.pdf | O9: 2 Permit (EC / pollution consent)
A10: Maharashtra | B10: AWS (Amazon) | C10: Amazon Data Services India | D10: Powai | E10: 77 | G10: Connected MW | H10: MPCB CTE granted 11-02-2025 (CI Rs 2,627 cr) | I10: A1 | J10: No | L10: Y | M10: https://environmentclearance.nic.in/writereaddata/FormB/agenda/1509202585756580%28740114%29MINUTESOF301DAY-4TABLEITEM-Copy.pdf | O10: 2 Permit (EC / pollution consent)
A11: Maharashtra | B11: Google | C11: Amanthin Info Parks (EverYondr) - Raiden lease | D11: D-31/32 TTC Turbhe | F11: 103.4 | G11: Connected MW | H11: EC Form-1A filed; status of EC not found | I11: A1 | J11: No | L11: Y | M11: https://environmentclearance.nic.in/DownloadPfdFile.aspx?FileName=Kwy+a1Xl%2FGHp2kMbJYBd8GPrFSz%2FNzzr1mrm87hA6RfsBvasy5U%2FhwjR4PRxBwwupD8Lw8MExL5FqtSFZLEOTQ%3D%3D&FilePath=93ZZBm8LWEXfg+HAlQix2fE2t8z%2FpgnoBhDlYdZCxzXTbTpOQqzWjBW0IF63rxBVcDlG0LKdfbGNs0Ou%2FTEvAA%3D%3D | O11: 2 Permit (EC / pollution consent)
A12: Maharashtra | B12: Google | C12: Raiden Infotech India | D12: GEN-2/1/A/1 TTC Turbhe | G12: n/a | H12: MPCB CTE 26-08-2025; EC application | I12: A1 | J12: No | L12: N | M12: https://mpcb.gov.in/sites/default/files/inline-files/Action_Taken_report_of_5th_CAC_Booklet_no_5_0.pdf | N12: MW not disclosed | O12: 2 Permit (EC / pollution consent)
A13: Maharashtra | B13: CapitaLand | C13: Datascape Realty Pvt Ltd | D13: Digha (DC Navi Mumbai 1) | E13: 135 | G13: Connected MW | H13: MPCB CTE (CI Rs 3,212 cr) + CTO (part) Feb-2025 | I13: A1 | J13: No | L13: Y | M13: https://environmentclearance.nic.in/writereaddata/FormB/agenda/1509202585756580%28740114%29MINUTESOF301DAY-4TABLEITEM-Copy.pdf | N13: 120 MVA max demand; 65 x 2,500 kVA DG | O13: 2 Permit (EC / pollution consent)
A14: Maharashtra | B14: Iron Mountain | C14: Web Werks India | D14: MUM-3, R-50 to R-54 TTC Rabale | E14: 140 | G14: Connected MW | H14: MPCB CTE granted 28-09-2024; EC discussed Aug-2025 | I14: A1 | J14: No | L14: Y | M14: https://environmentclearance.nic.in/writereaddata/FormB/agenda/1509202585756580%28740114%29MINUTESOF301DAY-4TABLEITEM-Copy.pdf | N14: 131 MW demand; 103 x 2,250 kVA DG | O14: 2 Permit (EC / pollution consent)
A15: Maharashtra | B15: Unidentified (Chandivali) | C15: Tusshar Infra Developers & Pantheon Buildcon | D15: Saki Vihar-Chandivali, Mumbai | F15: 113.9 | G15: Connected MW | H15: EC (expansion) under appraisal 2025 | I15: A1 | J15: No | L15: Y | M15: https://environmentclearance.nic.in/writereaddata/FormB/agenda/2107202594781152MINUTESOF296DAY-3PART-B.pdf | O15: 2 Permit (EC / pollution consent)
A16: Maharashtra | B16: Digital Edge | C16: Digital Edge DC (India) | D16: BOM campus, Kalwa/Dighe (47 acres) | E16: 350 | G16: IT MW | H16: SEIAA EC 08-02-2024; MPCB CTE BOM2&3 (CI Rs 3,000 cr) and CTO | I16: C | J16: No | L16: Y | M16: https://www.digitaledgedc.com/products-services/data-centers/india/ | N16: AUDIT: corrected 400 -> 350 MW (company page: 350MW on 47 acres; older page says 300MW). EC letter: https://www.digitaledgedc.com/wp-content/uploads/2025/07/EC-Letter-Data-Center.pdf | O16: 2 Permit (EC / pollution consent)
A17: Maharashtra | B17: Sify | C17: Sify Infinit Spaces | D17: Rabale campus | E17: 377 | G17: IT MW | H17: MPCB CTE (expansion) 26-05-2025; SEIAA EC expansion on agenda | I17: A1 | J17: No | L17: Y | M17: https://www.sifytechnologies.com/data-center/rabale-data-center/ | N17: Campus design capacity | O17: 2 Permit (EC / pollution consent)
A18: Maharashtra | B18: Yotta (Hiranandani) | C18: NMDC Data Centre Pvt Ltd | D18: NM1 Panvel | E18: 52 | G18: IT MW | H18: Operating; MPCB consent renewal May-2025 | I18: C | J18: No | L18: Y | M18: https://colocation.yotta.com/data-center/nm1-datacenter-mumbai-region-maharashtra/ | N18: AUDIT: corrected 250 -> 52 MW (Yotta page: NM1 52MW IT). 250 MW park figure was aggregator-only; NM2 (52-65 MW) not confirmed by Yotta. CRISIL: ~13 MW colocation running | O18: 2 Permit (EC / pollution consent)
A19: Maharashtra | B19: CtrlS | C19: CtrlS India | D19: Mahape DC1-DC7 | E19: 214 | G19: IT MW | H19: Operating + MPCB CTE for expansion | I19: A1 | J19: No | L19: Y | M19: https://www.ctrls.com/ | N19: Excludes the '700 MW' marketing claim | O19: 2 Permit (EC / pollution consent)
A20: Maharashtra | B20: STT GDC | C20: STT Global Data Centres India | D20: TTC Khairane/Mahape | E20: 133 | G20: IT MW | H20: MPCB CTE Dec-2023 + CTO (part) | I20: A1 | J20: No | L20: Y | M20: https://www.sttelemediagdc.com/in-en/locations/mumbai | N20: STT also has Ambernath connectivity (inside Lodha row) | O20: 2 Permit (EC / pollution consent)
A21: Maharashtra | B21: NTT | C21: NTT Global Data Centers NAV2 | D21: NAV1A + NAV2, Airoli/Mahape | E21: 366 | G21: IT MW | H21: MPCB CTO Jan-2025, renewal Jul-2025 | I21: C | J21: No | L21: Y | M21: https://www.datacenterdynamics.com/en/news/ntt-announces-500mw-nav2-data-center-in-navi-mumbai-india/ | N21: AUDIT: corrected 530 -> 366 MW IT (NAV2 336 MW IT + NAV1A 30 MW IT); 530 had mixed NAV2 facility power (500) with IT | O21: 2 Permit (EC / pollution consent)
A22: Maharashtra | B22: Princeton Digital Group | C22: PDG (India) Management | D22: MU1 Airoli (50 live + 100 expansion) + MU2 (120) | E22: 150 | F22: 120 | G22: IT MW | H22: MU1: MPCB CTO May-2025; MU2: construction started Apr-2026, no permit found | I22: C | J22: No | L22: Y | M22: https://www.datacenterdynamics.com/en/news/pdg-breaks-ground-on-latest-mumbai-data-center/ | N22: AUDIT: corrected 220 approved -> 150 approved + 120 under process (DCD: MU1 50MW live + 100MW expansion; MU2 120MW) | O22: 2 Permit (EC / pollution consent)
A23: Maharashtra | B23: Colt DCS - RMZ | C23: Data Center Holdings India LLP | D23: Kalwa plots 5 & 5A, Airoli | E23: 148 | G23: IT MW | H23: MPCB CTO renewal Apr-2025; ICRA-rated | I23: C | J23: No | L23: Y | M23: https://indianinfrastructure.com/2026/10/16/colt-dcs-and-rmz-begin-construction-of-third-data-centre-in-mumbai/ | N23: AUDIT: link corrected - 148 MW potential is in this Oct-2026 article; ICRA rationale (Mar-2026) says 142 MW: https://www.icra.in/Rating/ShowRationalReportFilePdf/141442 | O23: 2 Permit (EC / pollution consent)
A24: Maharashtra | B24: L&T | C24: Larsen & Toubro | D24: Vyoma EL-200 Mahape | F24: 100 | G24: IT MW | H24: SEIAA EC application (Oct-2025) | I24: A1 | J24: No | L24: Y | M24: https://www.larsentoubro.com/pressreleases/2026/2026-01-21-larsen-toubro-vyoma-breaks-ground-on-40-mw-green-ai-ready-data-centre-in-navi-mumbai | O24: 2 Permit (EC / pollution consent)
A25: Maharashtra | B25: ReNew | C25: ReNew Wind Energy | D25: MMR green DC park (Panvel/Taloja/Khalapur) | F25: 750 | G25: IT MW | H25: State MoU Oct-2026 | I25: A2 | J25: No | L25: Y | M25: https://www.business-standard.com/industry/news/renew-signs-mou-with-maharashtra-for-70-000-crore-green-data-centre-park-126100801226_1.html | O25: 4 MoU / LoI / announced
A26: Maharashtra | B26: Trentar (Dorf Ketal) | C26: Trentar Pvt Ltd | D26: Location not disclosed | F26: 500 | G26: IT MW | H26: State LoI + MoU Oct-2026 | I26: A2 | J26: No | L26: Y | M26: https://www.prnewswire.com/in/news-releases/trentar-signs-30-000-crore-3-3-bn-mou-with-maharashtra-for-500-mw-green-integrated-data-center-park-302899623.html | O26: 4 MoU / LoI / announced
A27: Maharashtra | B27: Zerra | C27: Zerra (AGPDC) | D27: Navi Mumbai 29 acres | F27: 240 | G27: IT MW | H27: Company claims consents; no government record found | I27: C | J27: No | L27: Y | M27: https://zerradc.com/projects/navi-mumbai/ | O27: 4 MoU / LoI / announced
A28: Maharashtra | B28: MAHAPREIT (state) | C28: MAHAPREIT | D28: State DC project | F28: 200 | G28: Total load MW | H28: EOI stage | I28: A1 | J28: No | L28: Y | M28: https://mahapreit.in/assets/uploads/tender-ext-65-1786725791.pdf | O28: 4 MoU / LoI / announced
A29: Maharashtra | B29: ESR | C29: ESR | D29: Rabale | F29: 60 | G29: Facility MW | H29: Announced | I29: D | J29: No | L29: Y | M29: https://www.crnasia.com/india/news/2026/esr-enters-india-data-centre-market-with-60-mw-facility-in-mumbai | O29: 4 MoU / LoI / announced
A30: Maharashtra | B30: TCC Concept / NES Data | C30: TCC Concept | D30: Hinjewadi, Pune | E30: 4 | F30: 56 | G30: IT MW | H30: 4 MW operating; land MoU for 60 MW | I30: C | J30: No | L30: Y | M30: https://www.constructionworld.in/policy-updates-and-economic-news/tcc-concept-plans-60-mw-data-centre-campus-in-pune/95832 | O30: 4 MoU / LoI / announced
A31: Maharashtra | B31: Avisirah | C31: Avisirah Technologies | D31: Navi Mumbai | F31: 5.5 | G31: IT MW | H31: Financed | I31: D | J31: No | L31: Y | M31: https://propnewstime.com/latestnewsstories/MzY3MDg=/avisirah-raises-inr-75-crore-for-navi-mumbai-data-centre | O31: 4 MoU / LoI / announced
A32: Andhra Pradesh | B32: Adani Group | C32: Vizag Mega Data Center Park Ltd | D32: Tarluvada (for Google) | E32: 929 | G32: Grid MW | H32: SEIAA EC granted 18-04-2026 | I32: A2 | J32: Yes | K32: CTUIL 929 MW (11 apps, under process) | L32: Y | M32: https://countercurrents.org/2026/04/hrf-flags-template-based-clearances-for-massive-andhra-data-centres-seeks-suspension-and-fresh-review/ | N32: Same project as CTUIL filing | O32: 2 Permit (EC / pollution consent)
A33: Andhra Pradesh | B33: Adani Group | C33: Vizag Rambilli Data Center Park Ltd | D33: Rambilli (for Google) | E33: 697 | G33: Grid MW | H33: SEIAA EC granted 18-04-2026 | I33: A2 | J33: Yes | K33: CTUIL 697 MW (8 apps, under process) | L33: Y | M33: https://countercurrents.org/2026/04/hrf-flags-template-based-clearances-for-massive-andhra-data-centres-seeks-suspension-and-fresh-review/ | N33: Same project as CTUIL filing | O33: 2 Permit (EC / pollution consent)
A34: Andhra Pradesh | B34: Adani Group | C34: Vizag Hyperscale Data Center Park Ltd | D34: Adavivaram-Mudasarlova (for Google) | E34: 512 | G34: Grid MW | H34: SEIAA EC Jun-2026 + APPCB CTE 14-07-2026 | I34: A2 | J34: Yes | K34: CTUIL 697 MW (8 apps, under process) | L34: Y | M34: https://theprint.in/judiciary/google-adani-vizag-data-centre-got-green-nod-on-built-up-area-not-ops-andhra-govt-affidavit-explains/3025598/ | N34: State affidavit: 512 MW; CTUIL filing larger (697 MW) | O34: 2 Permit (EC / pollution consent)
A35: Andhra Pradesh | B35: ReNew | C35: Renew AP Green Data Center Pvt Ltd | D35: Makavaripalem, Anakapalli | E35: 1000 | G35: IT MW | H35: G.O.Ms.No.55 (2026) land + incentives | I35: A2 | J35: No | L35: Y | M35: https://www.medianama.com/2026/08/223-andhra-pradesh-ai-data-centres/ | O35: 3 Govt approval (GO / land)
A36: Andhra Pradesh | B36: Reliance | C36: Reliance Industries | D36: Bhogapuram / Vizianagaram (854.97 acres) | E36: 1500 | G36: IT MW | H36: G.O.Ms.No.30 & 52 land allotment; SIPB clearance (Rs 1,08,010 cr) | I36: D | J36: No | L36: Y | M36: https://stopdirtydatacenters.org/ | N36: AUDIT: MW not in any official/company source - 1.5 GW from civil-society registry (also implied by MediaNama 3,498 MW total). Approval verified via press: https://www.deccanherald.com/india/andhra-pradesh/andhra-sipb-clears-rils-rs-108010-crore-vizag-data-centre-proposal-3993372 | O36: 2 Permit (EC / pollution consent)
A37: Andhra Pradesh | B37: Sify | C37: Sify Infinit Spaces | D37: Paradesipalem (53.6 + 25 acres) | E37: 550 | G37: IT MW | H37: G.O.Ms.No.29 (2025) & 37 (2026) land + incentives | I37: A2 | J37: No | L37: Y | M37: https://w.media/andhra-pradesh-allocates-extra-25-acres-for-sifys-500-mw-dc/ | N37: AUDIT: corrected 600 -> 550 (GO text: 550 MW in phases; this article says 500 MW). Dropped 50 MW Madhurawada site (registry-only) | O37: 3 Govt approval (GO / land)
A38: Andhra Pradesh | B38: AM Intelligence Labs | C38: AM AI Factory (Vizag) Pvt Ltd | D38: Amanam, Bheemunipatnam | E38: 512 | G38: IT MW | H38: SIPB 12-08-2026 + G.O.Ms.No.59 | I38: A2 | J38: No | L38: Y | M38: https://theprint.in/india/andhra-approves-green-ai-data-centre-in-visakhapatnam-with-investment-of-over-rs-30000-cr/3022441/ | O38: 3 Govt approval (GO / land)
A39: Andhra Pradesh | B39: Colt DCS - RMZ | C39: Data Centre Holdings India LLP | D39: Jagnadhapuram, Anandapuram | E39: 486 | G39: IT MW | H39: G.O.Ms.No.56 (21-08-2026) | I39: A2 | J39: No | L39: Y | M39: https://www.medianama.com/2026/08/223-andhra-pradesh-ai-data-centres/ | O39: 3 Govt approval (GO / land)
A40: Andhra Pradesh | B40: TCS | C40: TCS (HyperVault) | D40: Rambilli (~200 acres) | F40: 1000 | G40: IT MW | H40: Land allotted (reported); TCS has not confirmed use or MW | I40: D | J40: No | K40: CTUIL HyperVault filings are in Telangana, not AP | L40: N | M40: https://analyticsindiamag.com/ai-news/tcs-acquires-land-in-vizag-pune-for-openai-data-centres | N40: AUDIT: EXCLUDED - the linked article's 1 GW refers to Google's campus; 1 GW for TCS appears only in a civil-society registry | O40: 3 Govt approval (GO / land)
A41: Andhra Pradesh | B41: CtrlS | C41: CtrlS Datacenters | D41: Rambilli (49.93 acres) | E41: 100 | G41: IT MW | H41: G.O.Ms.No.33 (2026) land + incentives | I41: A2 | J41: No | L41: Y | M41: https://www.deccanchronicle.com/southern-states/andhra-pradesh/ap-approves-sifys-rs-15266-crore-data-centre-expansion-clears-3-other-tech-projects-1967167 | O41: 3 Govt approval (GO / land)
A42: Andhra Pradesh | B42: Adani Group | C42: Adani Enterprises / AdaniConneX | D42: Madhurawada (130 acres) | E42: 200 | G42: IT MW | H42: Land allotted (2021 GOs, per registry) | I42: D | J42: No | L42: Y | M42: https://stopdirtydatacenters.org/ | N42: Kapuluppada 100 MW site cancelled - excluded | O42: 3 Govt approval (GO / land)
A43: Telangana | B43: Fortune | C43: Fortune Hospitality & Infra / Sudeeksha Estates | D43: Kandukur mandal (170 acres) | E43: 2000 | G43: Grid MVA | H43: 2,000 MVA sanctioned by TGTRANSCO (per developer) | I43: C | J43: No | K43: No Fortune/Sudeeksha CTUIL filing found | L43: Y | M43: https://www.convergence-now.com/artificial-intelligence/telanganas-ai-data-centre-race-gets-bigger-with-%E2%82%B91-3-lakh-crore-project/ | N43: IT load 1,200-1,600 MW | O43: 1 Grid connection granted / sanctioned
A44: Telangana | B44: TCS | C44: HyperVault (TCS) | D44: Bharat Future City (264 acres) | F44: 1000 | G44: IT MW | H44: State MoU Sep-2026 | I44: A2 | J44: Yes | K44: CTUIL HyperVault 1,550 MW at Maheshwaram (under process) | L44: Y | M44: https://www.aninews.in/news/national/general-news/tcs-hypervault-signs-mou-with-telangana-for-rs-70000-crore-ai-data-centre-project20260905171224/ | N44: Same project as CTUIL filing | O44: 4 MoU / LoI / announced
A45: Telangana | B45: AWS / CtrlS (unattributed) | C45: Amazon Data Services or CtrlS | D45: Peddavedu | E45: 278 | G45: Power MW | H45: SEIAA Telangana EC (challenged May-2026) | I45: A2 | J45: No | L45: Y | M45: https://www.counterview.net/2026/05/scientists-flag-serious-omissions-in.html | N45: AWS: Rs 60,000 cr, 300 acres (Future City + Chandanvelly) - no MW disclosed | O45: 2 Permit (EC / pollution consent)
A46: Telangana | B46: Adani Group | C46: AdaniConneX | D46: Hyderabad | E46: 19.2 | F46: 386.8 | G46: IT MW | H46: 19.2 MW operating; 406 MW planned (AEL Q1 FY27 deck) | I46: B | J46: Possible | K46: Adani-mapped SPVs at Maheshwaram/Doma (2.4 GW, under process) | L46: Y | M46: https://www.adanienterprises.com/-/media/Project/Enterprises/Investors/Investor-Downloads/Results-Presentations/AEL_Investor_Presentation.pdf | O46: 5 Operating / company filing
A47: Telangana | B47: CtrlS | C47: CtrlS Datacenters | D47: Hyderabad AI cluster | F47: 400 | G47: IT MW | H47: State MoU Jan-2025 | I47: A2 | J47: No | K47: CtrlS 50 MW CTUIL application CLOSED | L47: Y | M47: https://www.telangana.gov.in/news/news-and-press-releases/2025/01/the-telangana-govt-signs-an-mou-with-ctrls-datacenters/ | O47: 4 MoU / LoI / announced
A48: Telangana | B48: NTT Data - Neysa | C48: NTT Data / Neysa Networks | D48: Hyderabad AI cluster | F48: 400 | G48: IT MW | H48: State MoU Apr-2025 | I48: A2 | J48: No | L48: Y | M48: https://w.media/ntt-data-neysa-networks-and-telangana-govt-sign-mou-with-to-build-ai-dc-cluster-worth-rs-10500-crores/ | O48: 4 MoU / LoI / announced
A49: Telangana | B49: STT GDC | C49: STT GDC India | D49: Meerkhanpet | F49: 100 | G49: IT MW | H49: State MoU Jan-2026 | I49: A2 | J49: No | L49: Y | M49: https://www.tribuneindia.com/news/world/telangana-govt-signs-rs-3500-crore-mou-with-st-telemedia-for-ai-ready-data-centre-in-hyderabad/ | O49: 4 MoU / LoI / announced
A50: Telangana | B50: UPC-Volt | C50: UPC-Volt | D50: Bharat Future City | F50: 100 | G50: IT MW | H50: State MoU Jan-2026 | I50: A2 | J50: No | L50: Y | M50: https://w.media/telangana-reveals-plans-to-build-a-1500-acre-data-center-city/ | O50: 4 MoU / LoI / announced
A51: Tamil Nadu | B51: CapitaLand | C51: CapitaLand India Trust | D51: Ambattur (Chennai 01) | E51: 53 | G51: Facility MW (gross) | H51: Under construction with dedicated 110 kV S/S; unveiled by CM Oct-2026 | I51: C | J51: No | L51: Y | M51: https://www.capitaland.com/content/dam/capitaland-newsroom/International/2026/october/cli-affirms-long-term-commitment-to-tamil-nadu/CapitaLand%20Investment%20reaffirms%20long-term%20commitment%20to%20Tamil%20Nadu%20with%20unveiling%20of%20new%20Chennai%20data%20centre.pdf | N51: 34 MW IT | O51: 5 Operating / company filing
A52: Tamil Nadu | B52: Sify | C52: Sify Infinit Spaces | D52: Siruseri (Chennai 02) | E52: 25.9 | F52: 104.1 | G52: IT MW | H52: 25.92 MW built; 130+ MW full build | I52: B | J52: No | L52: Y | M52: https://sifyinfinitspaces.com/wp-content/uploads/2025/07/Sify-Infinit-Spaces-IR-2025.pdf | N52: AUDIT: link corrected - 130+ MW is in Sify Integrated Report 2024-25 (another page of the same report says 40+ MW - conflicting); 25.92 MW built per Sify Chennai 02 page | O52: 5 Operating / company filing
A53: Tamil Nadu | B53: Digital Connexion (Reliance-Brookfield-DLR) | C53: Digital Connexion | D53: Ambattur | E53: 100 | G53: IT MW | H53: Operating / expanding | I53: D | J53: No | L53: Y | M53: https://theprint.in/ground-reports/inside-chennais-data-centres-fortresses-of-the-ai-era/2856488/ | O53: 5 Operating / company filing
A54: Tamil Nadu | B54: STT GDC | C54: STT GDC India | D54: Siruseri (Chennai 7) | E54: 7.2 | F54: 37.8 | G54: IT MW | H54: 7.2 MW live Feb-2026; 45 MW campus | I54: C | J54: No | L54: Y | M54: https://w.media/stt-gdc-india-launches-fourth-dc-in-chennai/ | N54: AUDIT: link corrected (previous link was a tracker page for a Sify site) | O54: 5 Operating / company filing
A55: Tamil Nadu | B55: Techno Digital | C55: Techno Digital | D55: Siruseri TD-1 | E55: 36 | G55: IT MW | H55: Operating | I55: C | J55: No | L55: Y | M55: https://www.datacenterdynamics.com/en/news/indias-techno-digital-opens-36mw-data-center/ | O55: 5 Operating / company filing
A56: Tamil Nadu | B56: Adani Group | C56: AdaniConneX | D56: Chennai | E56: 17 | F56: 16 | G56: IT MW | H56: 17 MW operating; 33 MW total (AEL deck) | I56: B | J56: No | L56: Y | M56: https://www.adanienterprises.com/-/media/Project/Enterprises/Investors/Investor-Downloads/Results-Presentations/AEL_Investor_Presentation.pdf | O56: 5 Operating / company filing
A57: Tamil Nadu | B57: Multiple (TANTRANSCO Ambattur requests) | C57: CtrlS, STT, NTT, CapitaLand area | D57: Ambattur Industrial Estate | F57: 1380 | G57: Grid MVA | H57: DC supply requests: 1,036 MVA @230 kV + 344 MVA @110 kV (justify new 400 kV S/S) | I57: A2 | J57: No | L57: N | M57: https://www.dtnext.in/news/chennai/powerplay-tn-plans-substation-in-ambattur-to-back-data-centres-850341 | N57: Aggregate of many companies; overlaps rows above - excluded from charts | O57: 5 Operating / company filing
A58: Uttar Pradesh | B58: Hiranandani (Yotta) | C58: NIDP Developers | D58: Greater Noida | E58: 28 | F58: 222 | G58: Total load MW | H58: Dashboard: 28 MW commercialised of 250 MW | I58: A1 | J58: No | L58: Y | M58: https://uplc.up.gov.in/en/page/uttar-pradesh-data-center-policy | O58: 5 Operating / company filing
A59: Uttar Pradesh | B59: Adani Group | C59: Adani Enterprises (Projects 1 & 2) | D59: Noida | E59: 35 | F59: 65 | G59: Total load MW | H59: Dashboard: 35 MW commercialised of 100 MW | I59: A1 | J59: No | L59: Y | M59: https://uplc.up.gov.in/en/page/uttar-pradesh-data-center-policy | N59: AdaniConneX Noida 50 MW (AEL) is part of this | O59: 5 Operating / company filing
A60: Uttar Pradesh | B60: SKVR | C60: SKVR Software Solutions | D60: UP | E60: 16 | F60: 104 | G60: Total load MW | H60: Dashboard: 16 MW commercialised of 120 MW | I60: A1 | J60: No | L60: Y | M60: https://uplc.up.gov.in/en/page/uttar-pradesh-data-center-policy | O60: 5 Operating / company filing
A61: Uttar Pradesh | B61: STT GDC | C61: STT GDC India | D61: Noida | E61: 40 | G61: Total load MW | H61: Dashboard: 40 MW commercialised | I61: A1 | J61: No | K61: STT 7 MW GNA-RE (drawee, not bulk) | L61: Y | M61: https://uplc.up.gov.in/en/page/uttar-pradesh-data-center-policy | O61: 5 Operating / company filing
A62: Uttar Pradesh | B62: NTT | C62: NTT Global Data Centres | D62: Noida | E62: 9 | F62: 43.8 | G62: Total load MW | H62: Dashboard: 9 MW commercialised; Noida 2 = 52.8 MW at full build | I62: A1 | J62: No | L62: Y | M62: https://uplc.up.gov.in/en/page/uttar-pradesh-data-center-policy | O62: 5 Operating / company filing
A63: Uttar Pradesh | B63: Iron Mountain | C63: Web Werks India | D63: Noida | E63: 5 | G63: Total load MW | H63: Dashboard: 5 MW commercialised | I63: A1 | J63: No | L63: Y | M63: https://uplc.up.gov.in/en/page/uttar-pradesh-data-center-policy | O63: 5 Operating / company filing
A64: Odisha | B64: Adani Group | C64: High Density Data Centre Ltd | D64: Naraj (~250 acres) | E64: 1000 | G64: IT MW | H64: HLCA approval (CM-chaired) | I64: A2 | J64: No | K64: No Adani bulk filing in Odisha on CTUIL | L64: Y | M64: https://www.businessworld.in/article/adani-arm-gets-odisha-nod-for-rs-1-04-lakh-cr-data-centre-park-625673 | O64: 3 Govt approval (GO / land)
A65: Odisha | B65: Sentraforge AI | C65: Sentraforge AI | D65: Puri | E65: 120 | G65: IT MW | H65: Odisha HLCA approval (46th meeting, Sep-2026) | I65: A2 | J65: No | L65: Y | M65: https://www.businesstoday.in/india/story/odisha-clears-sentraforge-ais-massive-rs22634-crore-sovereign-compute-project-558006-2026-09-26 | N65: AUDIT: link corrected (previous link was an HCLTech article). 120 MW is company-stated | O65: 3 Govt approval (GO / land)
A66: Karnataka | B66: Govt of Karnataka (park) | C66: State DC park | D66: Hoskote | F66: 500 | G66: IT MW | H66: State decision May-2026 (planned park) | I66: A2 | J66: No | L66: Y | M66: https://w.media/karnataka-plans-three-sustainable-data-center-parks-with-combined-capacity-of-1-gw/ | N66: Only company-level Karnataka data are CTUIL (SITAC) | O66: 3 Govt approval (GO / land)
A67: Gujarat | B67: Reliance | C67: Reliance Industries (Meta tenant) | D67: Jamnagar AI DC | F67: 168 | G67: IT MW | H67: Announced Jun-2026 | I67: C | J67: Possible | K67: Reliance 14.65 GW CTUIL filings at Jamnagar (purpose not stated) | L67: Y | M67: https://www.pv-magazine-india.com/2026/06/10/reliance-meta-to-develop-168-mw-ai-data-centre-powered-by-renewable-energy-in-jamnagar/ | O67: 4 MoU / LoI / announced
A68: Haryana | B68: Anant Raj | C68: Anant Raj | D68: Manesar, Panchkula, Rai | E68: 28 | F68: 279 | G68: IT MW | H68: 28 MW platform built (only 8 MW colocation handed over by Q2 FY26); 307 MW target by FY32 | I68: B | J68: No | L68: Y | M68: https://www.valueresearchonline.com/stories/228694/anant-raj-data-centre-execution-delay-investment-risk/ | O68: 5 Operating / company filing
A69: West Bengal | B69: Hiranandani (Yotta) | C69: Yotta / Hiranandani | D69: Uttarpara, Kolkata | F69: 250 | G69: IT MW | H69: 2021 MoU; status uncertain | I69: D | J69: No | L69: Y | M69: https://www.datacenterdynamics.com/en/news/hiranandani-group-build-six-hyperscale-data-centers-bengal/ | O69: 4 MoU / LoI / announced
A70: West Bengal | B70: NTT | C70: NTT Global Data Centers | D70: New Town, Kolkata | F70: 25 | G70: IT MW | H70: Phase 1 (6.4 MW) planned; 25 MW full build | I70: C | J70: No | L70: Y | M70: https://services.global.ntt/en-us/services-and-products/global-data-centers/global-locations/india/kolkata-1-data-center | N70: AUDIT: corrected 40 -> 25 MW (NTT page: over 25MW critical IT at full build) | O70: 5 Operating / company filing
A72: Definitions - Approved: a government permission granted (land GO / SIPB / HLCA approval, environmental clearance, pollution-board consent, grid connectivity or power sanction) or capacity already operating. Under process: application, MoU, LoI or announcement only.
A73: MW basis differs by row (IT MW vs connected / grid MW vs MVA) - see column G. Connected/grid MW is comparable to CTUIL GNA quantum; IT MW is roughly 1.3-1.6x smaller than facility power.
A74: Overlap with CTUIL - Yes: same project appears in the CTUIL GNA register. Possible: same sponsor files with CTUIL in that state and it may be the same load. No: no matching CTUIL bulk-consumer filing found (most DCs connect via the state grid).
A75: Grey rows are kept for reference but excluded from the state charts (no MW, or an aggregate that double counts other rows). CTUIL-only applicants (e.g. SITAC Group, Qubitiq, Giridhari) are NOT repeated here - they live in the CTUIL workbook.
A76: Sources: the India_DC_Power_Dataset_v3 workbook (Projects, MH_Permits, States_Evidence sheets). This sheet is the reference; state sheets are formulas on it.
